Workbook
Name LBO_ELIGIBLE: 'LBO MODEL'!$C$62
Name LBO_EQUITY_ENTRY: 'LBO MODEL'!$C$69
Name LBO_EQUITY_EXIT: 'LBO MODEL'!$C$70
Name LBO_IRR_BASE: 'LBO MODEL'!$C$64
Name LBO_IRR_BEAR: 'LBO MODEL'!$C$67
Name LBO_IRR_BULL: 'LBO MODEL'!$C$66
Name LBO_LEVERAGE_EXIT: 'LBO MODEL'!$C$68
Name LBO_MEGA_FLAG: 'LBO MODEL'!$C$63
Name LBO_MOIC_BASE: 'LBO MODEL'!$C$65

Sheet INPUT
B3: INPUT — Raw Data
B4: All figures in USD millions unless stated
B5: METRIC | C5: UNIT | E5: 2022 | F5: 2023 | G5: 2024 | H5: 2025 (LTM)
B7: INPUT
B9: Revenue | C9: ($M) | E9: 394328 | F9: 383285 | G9: 391035 | H9: 416161
B10: Cost of Goods Sold (COGS) | C10: ($M) | E10: -223546 | F10: -214137 | G10: -210352 | H10: -220960
B11: Gross Profit | C11: ($M) | D11: =D9+D10 -> 0 | E11: =E9+E10 -> 170782 | F11: =F9+F10 -> 169148 | G11: =G9+G10 -> 180683 | H11: =H9+H10 -> 195201
D13: =SUM(D14:D16) -> 0 | E13: =SUM(E14:E16) -> -62449 | F13: =SUM(F14:F16) -> -66366 | G13: =SUM(G14:G16) -> -68912 | H13: =SUM(H14:H16) -> -73849
B14: Operating Expenses (SG&A) | C14: ($M) | E14: -25094 | F14: -24932 | G14: -26097 | H14: -27601
B15: Research & Development | C15: ($M) | E15: -26251 | F15: -29915 | G15: -31370 | H15: -34550
B16: Depreciation & Amortization | C16: ($M) | E16: -11104 | F16: -11519 | G16: -11445 | H16: -11698
B17: EBIT (Operating Profit) | C17: ($M) | D17: =D11+D13 -> 0 | E17: =E11+E13 -> 108333 | F17: =F11+F13 -> 102782 | G17: =G11+G13 -> 111771 | H17: =H11+H13 -> 121352
D19: =D17+D20+D21 -> 0 | E19: =E17+E20+E21 -> 108227 | F19: =F17+F20+F21 -> 102599 | G19: =G17+G20+G21 -> 111771 | H19: =H17+H20+H21 -> 121352
B20: Interest Expense | C20: ($M) | E20: -2931 | F20: -3933 | G20: 0 | H20: 0
B21: Interest Income | C21: ($M) | E21: 2825 | F21: 3750 | G21: 0 | H21: 0
B22: Earnings Before Tax (EBT) | C22: ($M) | D22: =D19 -> 0 | E22: =E19 -> 108227 | F22: =F19 -> 102599 | G22: =G19 -> 111771 | H22: =H19 -> 121352
D24: =-ROUND(D22*0.21,0) -> 0 | E24: =-ROUND(E22*E104,0) -> -17533 | F24: =-ROUND(F22*F104,0) -> -15103 | G24: =-ROUND(G22*G104,0) -> -26926 | H24: =-ROUND(H22*H104,0) -> -18895
B25: Income Tax Expense | C25: ($M) | E25: -19300 | F25: -16741 | G25: -29749 | H25: -20719
B26: Net Income | C26: ($M) | D26: =D22+D24 -> 0 | E26: =E22+E24 -> 90694 | F26: =F22+F24 -> 87496 | G26: =G22+G24 -> 84845 | H26: =H22+H24 -> 102457
B29: Common Dividends | C29: ($M) | E29: -89402 | F29: -77550 | G29: -94949 | H29: -90711
B30: EBITDA | C30: ($M) | D30: =D17-D16 -> 0 | E30: =E17-E16 -> 119437 | F30: =F17-F16 -> 114301 | G30: =G17-G16 -> 123216 | H30: =H17-H16 -> 133050
B32: BALANCE SHEET
B34: Cash & Cash Equivalents | C34: ($M) | E34: 23646 | F34: 29965 | G34: 29943 | H34: 35934
B35: Accounts Receivable | C35: ($M) | E35: 28184 | F35: 29508 | G35: 33410 | H35: 39777
B36: Inventories | C36: ($M) | E36: 4946 | F36: 6331 | G36: 7286 | H36: 5718
B37: Other Current Assets | C37: ($M) | E37: 21223 | F37: 14695 | G37: 14287 | H37: 14585
B38: Total Current Assets | C38: ($M) | D38: =SUM(D34:D37) -> 0 | E38: =SUM(E34:E37) -> 77999 | F38: =SUM(F34:F37) -> 80499 | G38: =SUM(G34:G37) -> 84926 | H38: =SUM(H34:H37) -> 96014
B41: PP&E (Net) | C41: ($M) | E41: 42117 | F41: 43715 | G41: 45680 | H41: 49834
B42: Intangible Assets | C42: ($M) | E42: 593 | F42: 615 | G42: 1470 | H42: 1389
B43: Other Long-Term Assets | C43: ($M) | E43: 39053 | F43: 46906 | G43: 55335 | H43: 62950
B44: Total Assets | C44: ($M) | D44: =D38+SUM(D41:D43) -> 0 | E44: =E38+SUM(E41:E43) -> 159762 | F44: =F38+SUM(F41:F43) -> 171735 | G44: =G38+SUM(G41:G43) -> 187411 | H44: =H38+SUM(H41:H43) -> 210187
B47: Accounts Payable | C47: ($M) | E47: 64115 | F47: 62611 | G47: 68960 | H47: 69860
B48: Short-Term Debt | C48: ($M) | E48: 21110 | F48: 15807 | G48: 20879 | H48: 20329
B49: Income Tax Payable | C49: ($M) | E49: 6552 | F49: 8819 | G49: 26601 | H49: 13016
B50: Other Current Liabilities | C50: ($M) | E50: 52630 | F50: 50010 | G50: 44024 | H50: 44452
B51: Total Current Liabilities | C51: ($M) | D51: =SUM(D47:D50) -> 0 | E51: =SUM(E47:E50) -> 144407 | F51: =SUM(F47:F50) -> 137247 | G51: =SUM(G47:G50) -> 160464 | H51: =SUM(H47:H50) -> 147657
B54: Long-Term Debt | C54: ($M) | E54: 98959 | F54: 95281 | G54: 85750 | H54: 78328
B55: Total Liabilities | C55: ($M) | D55: =D51+D54 -> 0 | E55: =E51+E54 -> 243366 | F55: =F51+F54 -> 232528 | G55: =G51+G54 -> 246214 | H55: =H51+H54 -> 225985
B58: Common Equity (Paid-In Capital) | C58: ($M) | E58: 64849 | F58: 73812 | G58: 83276 | H58: 93568
B59: Retained Earnings | C59: ($M) | E59: -3068 | F59: -214 | G59: -19154 | H59: -14264
B60: Total Shareholders Equity | C60: ($M) | D60: =D58+D59 -> 0 | E60: =E58+E59 -> 61781 | F60: =F58+F59 -> 73598 | G60: =G58+G59 -> 64122 | H60: =H58+H59 -> 79304
B63: Total Liabilities & Equity | C63: ($M) | D63: =D55+D60 -> 0 | E63: =E55+E60 -> 305147 | F63: =F55+F60 -> 306126 | G63: =G55+G60 -> 310336 | H63: =H55+H60 -> 305289
B67: CASH FLOW STATEMENT
B69: Net Income | C69: ($M) | D69: =D26 -> 0 | E69: =E26 -> 90694 | F69: =F26 -> 87496 | G69: =G26 -> 84845 | H69: =H26 -> 102457
B70: Depreciation & Amortization | C70: ($M) | D70: =-D16 -> 0 | E70: =-E16 -> 11104 | F70: =-F16 -> 11519 | G70: =-G16 -> 11445 | H70: =-H16 -> 11698
B71: Change in Accounts Receivable | C71: ($M) | E71: -9343 | F71: -417 | G71: -5144 | H71: -7029
B72: Change in Inventories | C72: ($M) | E72: 1484 | F72: -1618 | G72: -1046 | H72: 1400
B73: Change in Accounts Payable | C73: ($M) | E73: 9448 | F73: -1889 | G73: 6020 | H73: 902
B74: Other Working Capital Changes | C74: ($M) | E74: 1006 | F74: -2227 | G74: -2266 | H74: -89
B75: Cash from Operating Activities | C75: ($M) | D75: =SUM(D69:D74) -> 0 | E75: =SUM(E69:E74) -> 104393 | F75: =SUM(F69:F74) -> 92864 | G75: =SUM(G69:G74) -> 93854 | H75: =SUM(H69:H74) -> 109339
B78: Capital Expenditures (CapEx) | C78: ($M) | E78: -10708 | F78: -10959 | G78: -9447 | H78: -12715
B79: Other Investing Activities | C79: ($M) | E79: -76923 | F79: -29513 | G79: -48656 | H79: -24407
B80: Cash from Investing Activities | C80: ($M) | D80: =SUM(D78:D79) -> 0 | E80: =SUM(E78:E79) -> -87631 | F80: =SUM(F78:F79) -> -40472 | G80: =SUM(G78:G79) -> -58103 | H80: =SUM(H78:H79) -> -37122
B83: Change in Long-Term Debt | C83: ($M) | E83: 5465 | F83: 5228 | G83: 0 | H83: 4481
B84: Change in Common Equity | C84: ($M) | E84: -89402 | F84: -77550 | G84: -94949 | H84: -90711
B85: Dividends Paid | C85: ($M) | E85: -89402 | F85: -77550 | G85: -94949 | H85: -90711
B86: Cash from Financing Activities | C86: ($M) | D86: =SUM(D83:D85) -> 0 | E86: =SUM(E83:E85) -> -173339 | F86: =SUM(F83:F85) -> -149872 | G86: =SUM(G83:G85) -> -189898 | H86: =SUM(H83:H85) -> -176941
B89: Net Change in Cash | C89: ($M) | D89: =D75+D80+D86 -> 0 | E89: =E75+E80+E86 -> -156577 | F89: =F75+F80+F86 -> -97480 | G89: =G75+G80+G86 -> -154147 | H89: =H75+H80+H86 -> -104724
B90: Beginning Cash Balance | C90: ($M) | E90: 35929 | F90: 24977 | G90: 30737 | H90: 29943
B91: Ending Cash Balance | C91: ($M) | D91: =D90+D89 -> 0 | E91: =E90+E89 -> -120648 | F91: =F90+F89 -> -72503 | G91: =G90+G89 -> -123410 | H91: =H90+H89 -> -74781
B93: MARKET & VALUATION DATA
B95: Share Price | C95: ($) | E95: 130 | F95: 175 | G95: 226 | H95: 261.3
B96: Shares Outstanding (Diluted) | C96: (M) | E96: 16215 | F96: 15813 | G96: 15408 | H96: 14681.14
B97: Market Capitalization | C97: ($M) | D97: =D95*D96 -> 0 | E97: =E95*E96 -> 2107950 | F97: =F95*F96 -> 2767275 | G97: =G95*G96 -> 3482208 | H97: =H95*H96 -> 3836181.9
B98: Enterprise Value (EV) | C98: ($M) | D98: =D97+D54+D48-D34 -> 0 | E98: =E97+E54+E48-E34 -> 2204373 | F98: =F97+F54+F48-F34 -> 2848398 | G98: =G97+G54+G48-G34 -> 3558894 | H98: =H97+H54+H48-H34 -> 3898904.9
B99: Beta (Levered) | C99: (x) | H99: 1.109
B100: Risk-Free Rate | C100: (%) | H100: 0.043
B101: Equity Risk Premium (ERP) | C101: (%) | H101: 0.055
B102: Cost of Equity (CAPM) | C102: (%) | D102: 0.1083 | E102: 0.1083 | F102: 0.1063 | G102: 0.1063 | H102: 0.1063
B103: Cost of Debt (Pre-Tax) | C103: (%) | H103: 0.058
B104: Tax Rate | C104: (%) | E104: 0.162 | F104: 0.1472 | G104: 0.2409 | H104: 0.1557
B105: After-Tax Cost of Debt | C105: (%) | D105: 0.0379 | E105: 0.0379 | F105: 0.0363 | G105: 0.0363 | H105: 0.0363
B106: Weight of Equity (%) | C106: (%) | H106: 0.9749
B107: Weight of Debt (%) | C107: (%) | H107: 0.0251
B108: WACC | C108: (%) | D108: =D106*(D100+D99*D101)+D107*D103*(1-D104) -> 0 | E108: =E106*(E100+E99*E101)+E107*E103*(1-E104) -> 0 | F108: =F106*(F100+F99*F101)+F107*F103*(1-F104) -> 0 | G108: =G106*(G100+G99*G101)+G107*G103*(1-G104) -> 0 | H108: =H106*(H100+H99*H101)+H107*H103*(1-H104) -> 0.10261386
B109: Terminal Growth Rate | C109: (%) | H109: 0.03
B110: Days in Period | C110: (days) | H110: 365
B112: COMPANY INFORMATION
B114: Company Name | C114: (text) | D114: Apple Inc.
B115: Ticker Symbol | C115: (text) | D115: AAPL
B116: Sector / Industry | C116: (text) | D116: Technology
B117: Base Year (LTM) | C117: (text) | D117: 2025
B118: Currency | C118: (text) | D118: USD
B119: Units | C119: (text) | D119: M
B120: Analysis Date | C120: (text) | D120: 2026-04-10
B122: NOTE: All analytical sheets reference this INPUT sheet only. Enter data in the blue cells (columns D–H).
B124: © 2015 to 2024 FinSight
B125: This Excel model is for educational purposes only.
B126: https://finsight.com/
D128: =IF(COUNTA(D9,D10,D14,D15,D16,D20,D21,D25)=8,1,0)+IF(COUNTA(E9,E10,E14,E15,E16,E20,E21,E25)=8,1,0)+IF(COUNTA(F9,F10,F14,F15,F16,F20,F21,F25)=8,1,0)+IF(COUNTA(G9,G10,G14,G15,G16,G20,G21,G25)=8,1,0) -> 3 | F128: =IF(D9<>"",1,0)+IF(E9<>"",1,0)+IF(F9<>"",1,0)+IF(G9<>"",1,0)+IF(H9<>"",1,0) -> 4 | G128: =IF(NOT(ISBLANK(H9)),F128,IF(NOT(ISBLANK(G9)),F128,IF(NOT(ISBLANK(F9)),F128,IF(NOT(ISBLANK(E9)),F128,IF(NOT(ISBLANK(D9)),F128,0))))) -> 4
E132: 2022 | F132: 2023 | G132: 2024 | H132: 2025 (LTM)

Sheet RATIOS
B1: FinSight | F1: RATIOS — Financial Ratio Analysis
B3: RATIOS
B5: Year | E5: =IF(INPUT!E5="","",INPUT!E5) -> 2022 | F5: =IF(INPUT!F5="","",INPUT!F5) -> 2023 | G5: =IF(INPUT!G5="","",INPUT!G5) -> 2024 | H5: =IF(INPUT!H5="","",INPUT!H5) -> 2025 (LTM)
B7: VALUATION RATIOS
B9: Price / Earnings (P/E) | D9: =IFERROR(INPUT!D95/( INPUT!D26/INPUT!D96),"–") -> – | E9: =IFERROR(INPUT!E95/(INPUT!E26/INPUT!E96),"–") -> 23.242442 | F9: =IFERROR(INPUT!F95/(INPUT!F26/INPUT!F96),"–") -> 31.627446 | G9: =IFERROR(INPUT!G95/(INPUT!G26/INPUT!G96),"–") -> 41.041994 | H9: =IFERROR(INPUT!H95/(INPUT!H26/INPUT!H96),"–") -> 37.441872
B10: EV / EBITDA | D10: =IFERROR(INPUT!D98/INPUT!D30,"–") -> – | E10: =IFERROR(INPUT!E98/INPUT!E30,"–") -> 18.456366 | F10: =IFERROR(INPUT!F98/INPUT!F30,"–") -> 24.920149 | G10: =IFERROR(INPUT!G98/INPUT!G30,"–") -> 28.883376 | H10: =IFERROR(INPUT!H98/INPUT!H30,"–") -> 29.304058
B11: EV / Revenue | D11: =IFERROR(INPUT!D98/INPUT!D9,"–") -> – | E11: =IFERROR(INPUT!E98/INPUT!E9,"–") -> 5.5902016 | F11: =IFERROR(INPUT!F98/INPUT!F9,"–") -> 7.4315405 | G11: =IFERROR(INPUT!G98/INPUT!G9,"–") -> 9.101216 | H11: =IFERROR(INPUT!H98/INPUT!H9,"–") -> 9.3687416
B12: EV / EBIT | D12: =IFERROR(INPUT!D98/INPUT!D17,"–") -> – | E12: =IFERROR(INPUT!E98/INPUT!E17,"–") -> 20.348121 | F12: =IFERROR(INPUT!F98/INPUT!F17,"–") -> 27.713004 | G12: =IFERROR(INPUT!G98/INPUT!G17,"–") -> 31.840943 | H12: =IFERROR(INPUT!H98/INPUT!H17,"–") -> 32.128889
B13: Price / Book (P/B) | D13: =IFERROR(INPUT!D97/INPUT!D60,"–") -> – | E13: =IFERROR(INPUT!E97/INPUT!E60,"–") -> 34.119713 | F13: =IFERROR(INPUT!F97/INPUT!F60,"–") -> 37.599867 | G13: =IFERROR(INPUT!G97/INPUT!G60,"–") -> 54.305979 | H13: =IFERROR(INPUT!H97/INPUT!H60,"–") -> 48.37312
B14: Price / Sales (P/S) | D14: =IFERROR(INPUT!D97/INPUT!D9,"–") -> – | E14: =IFERROR(INPUT!E97/INPUT!E9,"–") -> 5.3456767 | F14: =IFERROR(INPUT!F97/INPUT!F9,"–") -> 7.2198886 | G14: =IFERROR(INPUT!G97/INPUT!G9,"–") -> 8.9051057 | H14: =IFERROR(INPUT!H97/INPUT!H9,"–") -> 9.2180235
B15: Earnings Per Share (EPS) | D15: =IFERROR(INPUT!D26/INPUT!D96,"–") -> – | E15: =IFERROR(INPUT!E26/INPUT!E96,"–") -> 5.5932162 | F15: =IFERROR(INPUT!F26/INPUT!F96,"–") -> 5.5331689 | G15: =IFERROR(INPUT!G26/INPUT!G96,"–") -> 5.506555 | H15: =IFERROR(INPUT!H26/INPUT!H96,"–") -> 6.9788177
B17: PROFITABILITY RATIOS
B19: Gross Profit Margin | D19: =IFERROR(INPUT!D11/INPUT!D9,"–") -> – | E19: =IFERROR(INPUT!E11/INPUT!E9,"–") -> 0.43309631 | F19: =IFERROR(INPUT!F11/INPUT!F9,"–") -> 0.4413113 | G19: =IFERROR(INPUT!G11/INPUT!G9,"–") -> 0.4620635 | H19: =IFERROR(INPUT!H11/INPUT!H9,"–") -> 0.46905164
B20: EBITDA Margin | D20: =IFERROR(INPUT!D30/INPUT!D9,"–") -> – | E20: =IFERROR(INPUT!E30/INPUT!E9,"–") -> 0.30288744 | F20: =IFERROR(INPUT!F30/INPUT!F9,"–") -> 0.29821412 | G20: =IFERROR(INPUT!G30/INPUT!G9,"–") -> 0.31510223 | H20: =IFERROR(INPUT!H30/INPUT!H9,"–") -> 0.319708
B21: EBIT (Operating) Margin | D21: =IFERROR(INPUT!D17/INPUT!D9,"–") -> – | E21: =IFERROR(INPUT!E17/INPUT!E9,"–") -> 0.27472815 | F21: =IFERROR(INPUT!F17/INPUT!F9,"–") -> 0.26816077 | G21: =IFERROR(INPUT!G17/INPUT!G9,"–") -> 0.28583375 | H21: =IFERROR(INPUT!H17/INPUT!H9,"–") -> 0.29159868
B22: Net Profit Margin | D22: =IFERROR(INPUT!D26/INPUT!D9,"–") -> – | E22: =IFERROR(INPUT!E26/INPUT!E9,"–") -> 0.22999635 | F22: =IFERROR(INPUT!F26/INPUT!F9,"–") -> 0.22827922 | G22: =IFERROR(INPUT!G26/INPUT!G9,"–") -> 0.21697546 | H22: =IFERROR(INPUT!H26/INPUT!H9,"–") -> 0.24619558
B23: Return on Equity (ROE) | D23: =IFERROR(INPUT!D26/INPUT!D60,"–") -> – | E23: =IFERROR(INPUT!E26/INPUT!E60,"–") -> 1.4679918 | F23: =IFERROR(INPUT!F26/INPUT!F60,"–") -> 1.1888367 | G23: =IFERROR(INPUT!G26/INPUT!G60,"–") -> 1.3231808 | H23: =IFERROR(INPUT!H26/INPUT!H60,"–") -> 1.2919525
B24: Return on Assets (ROA) | D24: =IFERROR(INPUT!D26/INPUT!D44,"–") -> – | E24: =IFERROR(INPUT!E26/INPUT!E44,"–") -> 0.56768193 | F24: =IFERROR(INPUT!F26/INPUT!F44,"–") -> 0.50948263 | G24: =IFERROR(INPUT!G26/INPUT!G44,"–") -> 0.45272156 | H24: =IFERROR(INPUT!H26/INPUT!H44,"–") -> 0.48745641
B25: Return on Invested Capital (ROIC) | D25: =IFERROR(INPUT!D17*(1-INPUT!D104)/(INPUT!D58+INPUT!D59),"–") -> – | E25: =IFERROR(INPUT!E17*(1-INPUT!E104)/(INPUT!E58+INPUT!E59),"–") -> 1.4694332 | F25: =IFERROR(INPUT!F17*(1-INPUT!F104)/(INPUT!F58+INPUT!F59),"–") -> 1.1909629 | G25: =IFERROR(INPUT!G17*(1-INPUT!G104)/(INPUT!G58+INPUT!G59),"–") -> 1.3231865 | H25: =IFERROR(INPUT!H17*(1-INPUT!H104)/(INPUT!H58+INPUT!H59),"–") -> 1.2919587
B27: LIQUIDITY & SOLVENCY RATIOS
B29: Current Ratio | D29: =IFERROR(INPUT!D38/INPUT!D51,"–") -> – | E29: =IFERROR(INPUT!E38/INPUT!E51,"–") -> 0.5401331 | F29: =IFERROR(INPUT!F38/INPUT!F51,"–") -> 0.58652648 | G29: =IFERROR(INPUT!G38/INPUT!G51,"–") -> 0.52925267 | H29: =IFERROR(INPUT!H38/INPUT!H51,"–") -> 0.65025024
B30: Quick Ratio | D30: =IFERROR((INPUT!D38-INPUT!D36)/INPUT!D51,"–") -> – | E30: =IFERROR((INPUT!E38-INPUT!E36)/INPUT!E51,"–") -> 0.50588268 | F30: =IFERROR((INPUT!F38-INPUT!F36)/INPUT!F51,"–") -> 0.54039797 | G30: =IFERROR((INPUT!G38-INPUT!G36)/INPUT!G51,"–") -> 0.48384684 | H30: =IFERROR((INPUT!H38-INPUT!H36)/INPUT!H51,"–") -> 0.61152536
B31: Cash Ratio | D31: =IFERROR(INPUT!D34/INPUT!D51,"–") -> – | E31: =IFERROR(INPUT!E34/INPUT!E51,"–") -> 0.16374552 | F31: =IFERROR(INPUT!F34/INPUT!F51,"–") -> 0.218329 | G31: =IFERROR(INPUT!G34/INPUT!G51,"–") -> 0.1866026 | H31: =IFERROR(INPUT!H34/INPUT!H51,"–") -> 0.2433613
B32: Debt / Equity Ratio | D32: =IFERROR((INPUT!D49+INPUT!D55)/INPUT!D60,"–") -> – | E32: =IFERROR((INPUT!E49+INPUT!E55)/INPUT!E60,"–") -> 4.0452243 | F32: =IFERROR((INPUT!F49+INPUT!F55)/INPUT!F60,"–") -> 3.2792603 | G32: =IFERROR((INPUT!G49+INPUT!G55)/INPUT!G60,"–") -> 4.254624 | H32: =IFERROR((INPUT!H49+INPUT!H55)/INPUT!H60,"–") -> 3.013732
B33: Net Debt / EBITDA | D33: =IFERROR((INPUT!D49+INPUT!D55-INPUT!D34)/INPUT!D30,"–") -> – | E33: =IFERROR((INPUT!E49+INPUT!E55-INPUT!E34)/INPUT!E30,"–") -> 1.8944883 | F33: =IFERROR((INPUT!F49+INPUT!F55-INPUT!F34)/INPUT!F30,"–") -> 1.8493452 | G33: =IFERROR((INPUT!G49+INPUT!G55-INPUT!G34)/INPUT!G30,"–") -> 1.9711076 | H33: =IFERROR((INPUT!H49+INPUT!H55-INPUT!H34)/INPUT!H30,"–") -> 1.5262458
B34: Interest Coverage (EBIT/Interest) | D34: =IFERROR(INPUT!D17/ABS(INPUT!D20),"–") -> – | E34: =IFERROR(INPUT!E17/ABS(INPUT!E20),"–") -> 36.961105 | F34: =IFERROR(INPUT!F17/ABS(INPUT!F20),"–") -> 26.133232 | G34: =IFERROR(INPUT!G17/ABS(INPUT!G20),"–") -> – | H34: =IFERROR(INPUT!H17/ABS(INPUT!H20),"–") -> –
B35: Debt / Total Assets | D35: =IFERROR((INPUT!D49+INPUT!D55)/INPUT!D44,"–") -> – | E35: =IFERROR((INPUT!E49+INPUT!E55)/INPUT!E44,"–") -> 1.5643144 | F35: =IFERROR((INPUT!F49+INPUT!F55)/INPUT!F44,"–") -> 1.4053454 | G35: =IFERROR((INPUT!G49+INPUT!G55)/INPUT!G44,"–") -> 1.4557043 | H35: =IFERROR((INPUT!H49+INPUT!H55)/INPUT!H44,"–") -> 1.1370875
B36: Equity Ratio | D36: =IFERROR(INPUT!D60/INPUT!D44,"–") -> – | E36: =IFERROR(INPUT!E60/INPUT!E44,"–") -> 0.38670648 | F36: =IFERROR(INPUT!F60/INPUT!F44,"–") -> 0.42855562 | G36: =IFERROR(INPUT!G60/INPUT!G44,"–") -> 0.34214641 | H36: =IFERROR(INPUT!H60/INPUT!H44,"–") -> 0.37730212
B38: OPERATIONAL EFFICIENCY RATIOS
B40: Asset Turnover | D40: =IFERROR(INPUT!D9/INPUT!D44,"–") -> – | E40: =IFERROR(INPUT!E9/INPUT!E44,"–") -> 2.4682215 | F40: =IFERROR(INPUT!F9/INPUT!F44,"–") -> 2.2318398 | G40: =IFERROR(INPUT!G9/INPUT!G44,"–") -> 2.0865104 | H40: =IFERROR(INPUT!H9/INPUT!H44,"–") -> 1.9799559
B41: Inventory Turnover | D41: =IFERROR(ABS(INPUT!D10)/INPUT!D36,"–") -> – | E41: =IFERROR(ABS(INPUT!E10)/INPUT!E36,"–") -> 45.197331 | F41: =IFERROR(ABS(INPUT!F10)/INPUT!F36,"–") -> 33.823567 | G41: =IFERROR(ABS(INPUT!G10)/INPUT!G36,"–") -> 28.870711 | H41: =IFERROR(ABS(INPUT!H10)/INPUT!H36,"–") -> 38.642882
B42: Days Inventory Outstanding (DIO) | D42: =IFERROR(INPUT!D36/ABS(INPUT!D10)*INPUT!D110,"–") -> – | E42: =IFERROR(INPUT!E36/ABS(INPUT!E10)*INPUT!E110,"–") -> 0 | F42: =IFERROR(INPUT!F36/ABS(INPUT!F10)*INPUT!F110,"–") -> 0 | G42: =IFERROR(INPUT!G36/ABS(INPUT!G10)*INPUT!G110,"–") -> 0 | H42: =IFERROR(INPUT!H36/ABS(INPUT!H10)*INPUT!H110,"–") -> 9.4454652
B43: Receivables Turnover | D43: =IFERROR(INPUT!D9/INPUT!D35,"–") -> – | E43: =IFERROR(INPUT!E9/INPUT!E35,"–") -> 13.991201 | F43: =IFERROR(INPUT!F9/INPUT!F35,"–") -> 12.989189 | G43: =IFERROR(INPUT!G9/INPUT!G35,"–") -> 11.70413 | H43: =IFERROR(INPUT!H9/INPUT!H35,"–") -> 10.462353
B44: Days Sales Outstanding (DSO) | D44: =IFERROR(INPUT!D35/INPUT!D9*INPUT!D110,"–") -> – | E44: =IFERROR(INPUT!E35/INPUT!E9*INPUT!E110,"–") -> 0 | F44: =IFERROR(INPUT!F35/INPUT!F9*INPUT!F110,"–") -> 0 | G44: =IFERROR(INPUT!G35/INPUT!G9*INPUT!G110,"–") -> 0 | H44: =IFERROR(INPUT!H35/INPUT!H9*INPUT!H110,"–") -> 34.886991
B45: Days Payable Outstanding (DPO) | D45: =IFERROR(INPUT!D48/ABS(INPUT!D10)*INPUT!D110,"–") -> – | E45: =IFERROR(INPUT!E48/ABS(INPUT!E10)*INPUT!E110,"–") -> 0 | F45: =IFERROR(INPUT!F48/ABS(INPUT!F10)*INPUT!F110,"–") -> 0 | G45: =IFERROR(INPUT!G48/ABS(INPUT!G10)*INPUT!G110,"–") -> 0 | H45: =IFERROR(INPUT!H48/ABS(INPUT!H10)*INPUT!H110,"–") -> 33.581123
B46: Cash Conversion Cycle (CCC) | D46: =IFERROR(D42+D44-D45,"–") -> – | E46: =IFERROR(E42+E44-E45,"–") -> 0 | F46: =IFERROR(F42+F44-F45,"–") -> 0 | G46: =IFERROR(G42+G44-G45,"–") -> 0 | H46: =IFERROR(H42+H44-H45,"–") -> 10.751333
B47: Fixed Asset Turnover | D47: =IFERROR(INPUT!D9/INPUT!D41,"–") -> – | E47: =IFERROR(INPUT!E9/INPUT!E41,"–") -> 9.3626802 | F47: =IFERROR(INPUT!F9/INPUT!F41,"–") -> 8.7678143 | G47: =IFERROR(INPUT!G9/INPUT!G41,"–") -> 8.5603109 | H47: =IFERROR(INPUT!H9/INPUT!H41,"–") -> 8.3509451
B49: GROWTH RATIOS
B51: Revenue Growth (YoY) | D51: – | E51: =IFERROR(INPUT!E9/INPUT!D9-1,"–") -> – | F51: =IFERROR(INPUT!F9/INPUT!E9-1,"–") -> -0.028004605 | G51: =IFERROR(INPUT!G9/INPUT!F9-1,"–") -> 0.020219941 | H51: =IFERROR(INPUT!H9/INPUT!G9-1,"–") -> 0.064255118
B52: Gross Profit Growth (YoY) | D52: – | E52: =IFERROR(INPUT!E11/INPUT!D11-1,"–") -> – | F52: =IFERROR(INPUT!F11/INPUT!E11-1,"–") -> -0.009567753 | G52: =IFERROR(INPUT!G11/INPUT!F11-1,"–") -> 0.068194717 | H52: =IFERROR(INPUT!H11/INPUT!G11-1,"–") -> 0.080350669
B53: EBITDA Growth (YoY) | D53: – | E53: =IFERROR(INPUT!E30/INPUT!D30-1,"–") -> – | F53: =IFERROR(INPUT!F30/INPUT!E30-1,"–") -> -0.04300175 | G53: =IFERROR(INPUT!G30/INPUT!F30-1,"–") -> 0.077995818 | H53: =IFERROR(INPUT!H30/INPUT!G30-1,"–") -> 0.079811063
B54: Net Income Growth (YoY) | D54: – | E54: =IFERROR(INPUT!E26/INPUT!D26-1,"–") -> – | F54: =IFERROR(INPUT!F26/INPUT!E26-1,"–") -> -0.035261429 | G54: =IFERROR(INPUT!G26/INPUT!F26-1,"–") -> -0.030298528 | H54: =IFERROR(INPUT!H26/INPUT!G26-1,"–") -> 0.20757853
B55: EPS Growth (YoY) | D55: – | E55: =IFERROR((INPUT!E26/INPUT!E96)/(INPUT!D26/INPUT!D96)-1,"–") -> – | F55: =IFERROR((INPUT!F26/INPUT!F96)/(INPUT!E26/INPUT!E96)-1,"–") -> -0.010735728 | G55: =IFERROR((INPUT!G26/INPUT!G96)/(INPUT!F26/INPUT!F96)-1,"–") -> -0.0048098794 | H55: =IFERROR((INPUT!H26/INPUT!H96)/(INPUT!G26/INPUT!G96)-1,"–") -> 0.26736547
B56: Total Assets Growth (YoY) | D56: – | E56: =IFERROR(INPUT!E44/INPUT!D44-1,"–") -> – | F56: =IFERROR(INPUT!F44/INPUT!E44-1,"–") -> 0.074942727 | G56: =IFERROR(INPUT!G44/INPUT!F44-1,"–") -> 0.09128017 | H56: =IFERROR(INPUT!H44/INPUT!G44-1,"–") -> 0.12152969
B58: CASH FLOW RATIOS
B60: Operating Cash Flow Margin | D60: =IFERROR(INPUT!D75/INPUT!D9,"–") -> – | E60: =IFERROR(INPUT!E75/INPUT!E9,"–") -> 0.26473646 | F60: =IFERROR(INPUT!F75/INPUT!F9,"–") -> 0.24228446 | G60: =IFERROR(INPUT!G75/INPUT!G9,"–") -> 0.24001432 | H60: =IFERROR(INPUT!H75/INPUT!H9,"–") -> 0.26273245
B61: Free Cash Flow (FCF) | D61: =IFERROR(INPUT!D75+INPUT!D78,"–") -> 0 | E61: =IFERROR(INPUT!E75+INPUT!E78,"–") -> 93685 | F61: =IFERROR(INPUT!F75+INPUT!F78,"–") -> 81905 | G61: =IFERROR(INPUT!G75+INPUT!G78,"–") -> 84407 | H61: =IFERROR(INPUT!H75+INPUT!H78,"–") -> 96624
B62: FCF Margin | D62: =IFERROR(D61/INPUT!D9,"–") -> – | E62: =IFERROR(E61/INPUT!E9,"–") -> 0.2375814 | F62: =IFERROR(F61/INPUT!F9,"–") -> 0.21369216 | G62: =IFERROR(G61/INPUT!G9,"–") -> 0.21585536 | H62: =IFERROR(H61/INPUT!H9,"–") -> 0.23217937
B63: Cash Return on Equity | D63: =IFERROR(INPUT!D75/INPUT!D60,"–") -> – | E63: =IFERROR(INPUT!E75/INPUT!E60,"–") -> 1.6897266 | F63: =IFERROR(INPUT!F75/INPUT!F60,"–") -> 1.2617734 | G63: =IFERROR(INPUT!G75/INPUT!G60,"–") -> 1.4636786 | H63: =IFERROR(INPUT!H75/INPUT!H60,"–") -> 1.3787325
B64: CapEx / Revenue | D64: =IFERROR(ABS(INPUT!D78)/INPUT!D9,"–") -> – | E64: =IFERROR(ABS(INPUT!E78)/INPUT!E9,"–") -> 0.027155059 | F64: =IFERROR(ABS(INPUT!F78)/INPUT!F9,"–") -> 0.028592301 | G64: =IFERROR(ABS(INPUT!G78)/INPUT!G9,"–") -> 0.024158963 | H64: =IFERROR(ABS(INPUT!H78)/INPUT!H9,"–") -> 0.030553079
B65: Dividend Payout Ratio | D65: =IFERROR(ABS(INPUT!D85)/INPUT!D26,"–") -> – | E65: =IFERROR(ABS(INPUT!E85)/INPUT!E26,"–") -> 0.98575429 | F65: =IFERROR(ABS(INPUT!F85)/INPUT!F26,"–") -> 0.88632623 | G65: =IFERROR(ABS(INPUT!G85)/INPUT!G26,"–") -> 1.1190877 | H65: =IFERROR(ABS(INPUT!H85)/INPUT!H26,"–") -> 0.88535678
B66: CFO / Net Income (Accruals Ratio) | D66: =IFERROR(INPUT!D75/INPUT!D26,"–") -> – | E66: =IFERROR(INPUT!E75/INPUT!E26,"–") -> 1.1510464 | F66: =IFERROR(INPUT!F75/INPUT!F26,"–") -> 1.0613514 | G66: =IFERROR(INPUT!G75/INPUT!G26,"–") -> 1.1061819 | H66: =IFERROR(INPUT!H75/INPUT!H26,"–") -> 1.0671696
B68: © 2015 to 2024 FinSight
B69: This Excel model is for educational purposes only.
B70: https://finsight.com/
B73: CHART DATA
B74: Year | D74: =IF(INPUT!D9="","",D5) | E74: =IF(INPUT!E9="",NA(),E5) -> 2022 | F74: =IF(INPUT!F9="",NA(),F5) -> 2023 | G74: =IF(INPUT!G9="",NA(),G5) -> 2024 | H74: =IF(INPUT!H9="",NA(),H5) -> 2025 (LTM)
B75: Revenue ($M) | D75: =IF(INPUT!D9="","",INPUT!D9) | E75: =IF(INPUT!E9="",NA(),INPUT!E9) -> 394328 | F75: =IF(INPUT!F9="",NA(),INPUT!F9) -> 383285 | G75: =IF(INPUT!G9="",NA(),INPUT!G9) -> 391035 | H75: =IF(INPUT!H9="",NA(),INPUT!H9) -> 416161
B76: EBITDA ($M) | D76: =IF(INPUT!E9="",NA(),INPUT!E30) -> 119437 | E76: =IF(INPUT!F9="",NA(),INPUT!F30) -> 114301 | F76: =IF(INPUT!G9="",NA(),INPUT!G30) -> 123216 | G76: =IF(INPUT!G9="",NA(),INPUT!G30) -> 123216 | H76: =IF(INPUT!H9="",NA(),INPUT!H30) -> 133050
B77: Net Income ($M) | D77: =IF(INPUT!E9="",NA(),INPUT!E26) -> 90694 | E77: =IF(INPUT!F9="",NA(),INPUT!F26) -> 87496 | F77: =IF(INPUT!G9="",NA(),INPUT!G26) -> 84845 | G77: =IF(INPUT!G9="",NA(),INPUT!G26) -> 84845 | H77: =IF(INPUT!H9="",NA(),INPUT!H26) -> 102457
B78: Cumul. Revenue ($M) | D78: =IF(INPUT!E9="",NA(),INPUT!D9+INPUT!E9) -> 394328 | E78: =IF(INPUT!F9="",NA(),INPUT!D9+INPUT!E9+INPUT!F9) -> 777613 | F78: =IF(INPUT!G9="",NA(),INPUT!D9+INPUT!E9+INPUT!F9+INPUT!G9) -> 1168648 | G78: =IF(INPUT!H9="",NA(),INPUT!D9+INPUT!E9+INPUT!F9+INPUT!G9+INPUT!H9) -> 1584809 | H78: =IF(INPUT!H9="",NA(),INPUT!D9+INPUT!E9+INPUT!F9+INPUT!G9+INPUT!H9) -> 1584809
B80: Gross Profit Margin | D80: =IF(INPUT!D9="","",D19) | E80: =IF(INPUT!E9="",NA(),E19) -> 0.43309631 | F80: =IF(INPUT!F9="",NA(),F19) -> 0.4413113 | G80: =IF(INPUT!G9="",NA(),G19) -> 0.4620635 | H80: =IF(INPUT!H9="",NA(),H19) -> 0.46905164
B81: EBITDA Margin | D81: =IF(INPUT!D9="","",D20) | E81: =IF(INPUT!E9="",NA(),E20) -> 0.30288744 | F81: =IF(INPUT!F9="",NA(),F20) -> 0.29821412 | G81: =IF(INPUT!G9="",NA(),G20) -> 0.31510223 | H81: =IF(INPUT!H9="",NA(),H20) -> 0.319708
B82: Net Profit Margin | D82: =IF(INPUT!D9="","",D22) | E82: =IF(INPUT!E9="",NA(),E22) -> 0.22999635 | F82: =IF(INPUT!F9="",NA(),F22) -> 0.22827922 | G82: =IF(INPUT!G9="",NA(),G22) -> 0.21697546 | H82: =IF(INPUT!H9="",NA(),H22) -> 0.24619558
D84: =IF(INPUT!D9="","",D5) | E84: =IF(INPUT!E9="",NA(),E5) -> 2022 | F84: =IF(INPUT!F9="",NA(),F5) -> 2023 | G84: =IF(INPUT!G9="",NA(),G5) -> 2024 | H84: =IF(INPUT!H9="",NA(),H5) -> 2025 (LTM)
B85: SG&A ($M) | D85: =IF(INPUT!D9="","",ABS(INPUT!D14)) | E85: =IF(INPUT!E9="",NA(),ABS(INPUT!E14)) -> 25094 | F85: =IF(INPUT!F9="",NA(),ABS(INPUT!F14)) -> 24932 | G85: =IF(INPUT!G9="",NA(),ABS(INPUT!G14)) -> 26097 | H85: =IF(INPUT!H9="",NA(),ABS(INPUT!H14)) -> 27601
B86: R&D ($M) | D86: =IF(INPUT!D9="","",ABS(INPUT!D15)) | E86: =IF(INPUT!E9="",NA(),ABS(INPUT!E15)) -> 26251 | F86: =IF(INPUT!F9="",NA(),ABS(INPUT!F15)) -> 29915 | G86: =IF(INPUT!G9="",NA(),ABS(INPUT!G15)) -> 31370 | H86: =IF(INPUT!H9="",NA(),ABS(INPUT!H15)) -> 34550
B87: D&A ($M) | D87: =IF(INPUT!D9="","",ABS(INPUT!D16)) | E87: =IF(INPUT!E9="",NA(),ABS(INPUT!E16)) -> 11104 | F87: =IF(INPUT!F9="",NA(),ABS(INPUT!F16)) -> 11519 | G87: =IF(INPUT!G9="",NA(),ABS(INPUT!G16)) -> 11445 | H87: =IF(INPUT!H9="",NA(),ABS(INPUT!H16)) -> 11698
B88: Interest ($M) | D88: =IF(INPUT!D9="","",ABS(INPUT!D20)) | E88: =IF(INPUT!E9="",NA(),ABS(INPUT!E20)) -> 2931 | F88: =IF(INPUT!F9="",NA(),ABS(INPUT!F20)) -> 3933 | G88: =IF(INPUT!G9="",NA(),ABS(INPUT!G20)) -> 0 | H88: =IF(INPUT!H9="",NA(),ABS(INPUT!H20)) -> 0
D90: =IF(INPUT!D9="","",D5) | E90: =IF(INPUT!E9="",NA(),E5) -> 2022 | F90: =IF(INPUT!F9="",NA(),F5) -> 2023 | G90: =IF(INPUT!G9="",NA(),G5) -> 2024 | H90: =IF(INPUT!H9="",NA(),H5) -> 2025 (LTM)
B91: SG&A ($M) | D91: =IF(INPUT!D9="","",D85/1000) | E91: =E85/1000 -> 25.094 | F91: =F85/1000 -> 24.932 | G91: =G85/1000 -> 26.097 | H91: =H85/1000 -> 27.601
B92: R&D ($M) | D92: =IF(INPUT!D9="","",D86/1000) | E92: =E86/1000 -> 26.251 | F92: =F86/1000 -> 29.915 | G92: =G86/1000 -> 31.37 | H92: =H86/1000 -> 34.55
B93: D&A ($M) | D93: =IF(INPUT!D9="","",D87/1000) | E93: =E87/1000 -> 11.104 | F93: =F87/1000 -> 11.519 | G93: =G87/1000 -> 11.445 | H93: =H87/1000 -> 11.698
B94: Interest ($M) | D94: =IF(INPUT!D9="","",D88/1000) | E94: =E88/1000 -> 2.931 | F94: =F88/1000 -> 3.933 | G94: =G88/1000 -> 0 | H94: =H88/1000 -> 0
G95: =G88/1000 -> 0 | H95: =H88/1000 -> 0
B97: Cumul. Revenue ($M) | D97: =D78/1000 -> 394.328 | E97: =E78/1000 -> 777.613 | F97: =F78/1000 -> 1168.648 | G97: =G78/1000 -> 1584.809 | H97: =H78/1000 -> 1584.809
G99: =G78/1000 -> 1584.809 | H99: =H78/1000 -> 1584.809
B100: FCF & CapEx Trend ($M)
B101: Metric | E101: =INPUT!E5 -> 2022 | F101: =INPUT!F5 -> 2023 | G101: =INPUT!G5 -> 2024 | H101: =INPUT!H5 -> 2025 (LTM)
B102: Free Cash Flow ($M) | E102: =E61 -> 93685 | F102: =F61 -> 81905 | G102: =G61 -> 84407 | H102: =H61 -> 96624
B103: CapEx ($M) | E103: =ABS(INPUT!E78) -> 10708 | F103: =ABS(INPUT!F78) -> 10959 | G103: =ABS(INPUT!G78) -> 9447 | H103: =ABS(INPUT!H78) -> 12715
B104: Cash from Operations ($M) | E104: =INPUT!E75 -> 104393 | F104: =INPUT!F75 -> 92864 | G104: =INPUT!G75 -> 93854 | H104: =INPUT!H75 -> 109339
B106: Returns Chart Data
B107: Metric | E107: =INPUT!E5 -> 2022 | F107: =INPUT!F5 -> 2023 | G107: =INPUT!G5 -> 2024 | H107: =INPUT!H5 -> 2025 (LTM)
B108: Return on Equity (ROE) | E108: =E23 -> 1.4679918 | F108: =F23 -> 1.1888367 | G108: =G23 -> 1.3231808 | H108: =H23 -> 1.2919525
B109: Return on Assets (ROA) | E109: =E24 -> 0.56768193 | F109: =F24 -> 0.50948263 | G109: =G24 -> 0.45272156 | H109: =H24 -> 0.48745641
B110: Return on Invested Capital (ROIC) | E110: =E25 -> 1.4694332 | F110: =F25 -> 1.1909629 | G110: =G25 -> 1.3231865 | H110: =H25 -> 1.2919587

Sheet ALTMAN Z-SCORE
B1: FinSight | F1: ALTMAN Z-SCORE — Bankruptcy Risk
B3: ALTMAN Z-SCORE
B5: COMPONENT | E5: =IF(INPUT!E5="","",INPUT!E5) -> 2022 | F5: =IF(INPUT!F5="","",INPUT!F5) -> 2023 | G5: =IF(INPUT!G5="","",INPUT!G5) -> 2024 | H5: =IF(INPUT!H5="","",INPUT!H5) -> 2025 (LTM)
B7: INTERMEDIATE CALCULATIONS
B8: Working Capital | D8: =IFERROR(INPUT!D38-INPUT!D51,"–") -> 0 | E8: =IFERROR(INPUT!E38-INPUT!E51,"–") -> -66408 | F8: =IFERROR(INPUT!F38-INPUT!F51,"–") -> -56748 | G8: =IFERROR(INPUT!G38-INPUT!G51,"–") -> -75538 | H8: =IFERROR(INPUT!H38-INPUT!H51,"–") -> -51643
B9: Total Assets | D9: =INPUT!D44 -> 0 | E9: =INPUT!E44 -> 159762 | F9: =INPUT!F44 -> 171735 | G9: =INPUT!G44 -> 187411 | H9: =INPUT!H44 -> 210187
B10: Retained Earnings | D10: =INPUT!D59 -> 0 | E10: =INPUT!E59 -> -3068 | F10: =INPUT!F59 -> -214 | G10: =INPUT!G59 -> -19154 | H10: =INPUT!H59 -> -14264
B11: EBIT | D11: =INPUT!D17 -> 0 | E11: =INPUT!E17 -> 108333 | F11: =INPUT!F17 -> 102782 | G11: =INPUT!G17 -> 111771 | H11: =INPUT!H17 -> 121352
B12: Market Cap (Book Value of Equity) | D12: =INPUT!D60 -> 0 | E12: =INPUT!E60 -> 61781 | F12: =INPUT!F60 -> 73598 | G12: =INPUT!G60 -> 64122 | H12: =INPUT!H60 -> 79304
B13: Total Liabilities | D13: =INPUT!D55 -> 0 | E13: =INPUT!E55 -> 243366 | F13: =INPUT!F55 -> 232528 | G13: =INPUT!G55 -> 246214 | H13: =INPUT!H55 -> 225985
B14: Revenue | D14: =INPUT!D9 -> 0 | E14: =INPUT!E9 -> 394328 | F14: =INPUT!F9 -> 383285 | G14: =INPUT!G9 -> 391035 | H14: =INPUT!H9 -> 416161
B16: 5 ALTMAN Z-SCORE COMPONENTS
B17: X1 = Working Capital / Total Assets | D17: =IFERROR(D8/D9,"–") -> – | E17: =IFERROR(E8/E9,"–") -> -0.41566831 | F17: =IFERROR(F8/F9,"–") -> -0.33043934 | G17: =IFERROR(G8/G9,"–") -> -0.40306065 | H17: =IFERROR(H8/H9,"–") -> -0.24570026
B18: X2 = Retained Earnings / Total Assets | D18: =IFERROR(D10/D9,"–") -> – | E18: =IFERROR(E10/E9,"–") -> -0.019203565 | F18: =IFERROR(F10/F9,"–") -> -0.0012461059 | G18: =IFERROR(G10/G9,"–") -> -0.10220318 | H18: =IFERROR(H10/H9,"–") -> -0.067863379
B19: X3 = EBIT / Total Assets | D19: =IFERROR(D11/D9,"–") -> – | E19: =IFERROR(E11/E9,"–") -> 0.67808991 | F19: =IFERROR(F11/F9,"–") -> 0.59849186 | G19: =IFERROR(G11/G9,"–") -> 0.59639509 | H19: =IFERROR(H11/H9,"–") -> 0.57735255
B20: X4 = Equity / Total Liabilities | D20: =IFERROR(D12/D13,"–") -> – | E20: =IFERROR(E12/E13,"–") -> 0.25386044 | F20: =IFERROR(F12/F13,"–") -> 0.31651242 | G20: =IFERROR(G12/G13,"–") -> 0.26043198 | H20: =IFERROR(H12/H13,"–") -> 0.35092595
B21: X5 = Revenue / Total Assets | D21: =IFERROR(D14/D9,"–") -> – | E21: =IFERROR(E14/E9,"–") -> 2.4682215 | F21: =IFERROR(F14/F9,"–") -> 2.2318398 | G21: =IFERROR(G14/G9,"–") -> 2.0865104 | H21: =IFERROR(H14/H9,"–") -> 1.9799559
B23: ALTMAN Z-SCORE CALCULATION
B24: 1.2 × X1 | D24: =IFERROR(1.2*D17,"–") -> – | E24: =IFERROR(1.2*E17,"–") -> -0.49880197 | F24: =IFERROR(1.2*F17,"–") -> -0.39652721 | G24: =IFERROR(1.2*G17,"–") -> -0.48367278 | H24: =IFERROR(1.2*H17,"–") -> -0.29484031
B25: 1.4 × X2 | D25: =IFERROR(1.4*D18,"–") -> – | E25: =IFERROR(1.4*E18,"–") -> -0.026884991 | F25: =IFERROR(1.4*F18,"–") -> -0.0017445483 | G25: =IFERROR(1.4*G18,"–") -> -0.14308445 | H25: =IFERROR(1.4*H18,"–") -> -0.09500873
B26: 3.3 × X3 | D26: =IFERROR(3.3*D19,"–") -> – | E26: =IFERROR(3.3*E19,"–") -> 2.2376967 | F26: =IFERROR(3.3*F19,"–") -> 1.9750231 | G26: =IFERROR(3.3*G19,"–") -> 1.9681038 | H26: =IFERROR(3.3*H19,"–") -> 1.9052634
B27: 0.6 × X4 | D27: =IFERROR(0.6*D20,"–") -> – | E27: =IFERROR(0.6*E20,"–") -> 0.15231626 | F27: =IFERROR(0.6*F20,"–") -> 0.18990745 | G27: =IFERROR(0.6*G20,"–") -> 0.15625919 | H27: =IFERROR(0.6*H20,"–") -> 0.21055557
B28: 1.0 × X5 | D28: =IFERROR(1*D21,"–") -> – | E28: =IFERROR(1*E21,"–") -> 2.4682215 | F28: =IFERROR(1*F21,"–") -> 2.2318398 | G28: =IFERROR(1*G21,"–") -> 2.0865104 | H28: =IFERROR(1*H21,"–") -> 1.9799559
B30: Z-SCORE (FINAL) | D30: =IFERROR(D24+D25+D26+D27+D28,"–") -> – | E30: =IFERROR(E24+E25+E26+E27+E28,"–") -> 4.3325475 | F30: =IFERROR(F24+F25+F26+F27+F28,"–") -> 3.9984986 | G30: =IFERROR(G24+G25+G26+G27+G28,"–") -> 3.5841161 | H30: =IFERROR(H24+H25+H26+H27+H28,"–") -> 3.7059259
B32: ZONE INTERPRETATION
B33: ZONE | D33: =IFERROR(IF(D30>2.99,"SAFE",IF(D30>=1.81,"GREY","DISTRESS")),"–") -> SAFE | E33: =IFERROR(IF(E30>2.99,"SAFE",IF(E30>=1.81,"GREY","DISTRESS")),"–") -> SAFE | F33: =IFERROR(IF(F30>2.99,"SAFE",IF(F30>=1.81,"GREY","DISTRESS")),"–") -> SAFE | G33: =IFERROR(IF(G30>2.99,"SAFE",IF(G30>=1.81,"GREY","DISTRESS")),"–") -> SAFE | H33: =IFERROR(IF(H30>2.99,"SAFE",IF(H30>=1.81,"GREY","DISTRESS")),"–") -> SAFE
B35: SAFE ZONE | D35: Low probability of bankruptcy
B36: GREY ZONE | D36: Some risk — monitor closely
B37: DISTRESS ZONE | D37: High probability of bankruptcy
B39: NOTE: Altman Z-Score was developed by Edward Altman (1968) for publicly traded manufacturing companies.
B40: Modified versions exist for private companies (Z') and non-manufacturing firms (Z'').

Sheet BENEISH M-SCORE
B1: FinSight | F1: BENEISH M-SCORE — Earnings Manipulation
B3: BENEISH M-SCORE
B5: INDEX / COMPONENT | E5: =IF(INPUT!H5="","",INPUT!H5) -> 2025 (LTM) | F5: Year t (Current)
B7: BASE FINANCIAL DATA (from INPUT)
B9: Net Sales (Revenue) | E9: =INPUT!E9 -> 394328 | F9: =INPUT!F9 -> 383285
B10: Cost of Goods Sold | E10: =ABS(INPUT!E10) -> 223546 | F10: =ABS(INPUT!F10) -> 214137
B11: Gross Profit | E11: =INPUT!E11 -> 170782 | F11: =INPUT!F11 -> 169148
B12: Total Current Assets | E12: =INPUT!E38 -> 77999 | F12: =INPUT!F38 -> 80499
B13: PP&E (Net) | E13: =INPUT!E41 -> 42117 | F13: =INPUT!F41 -> 43715
B14: Total Assets | E14: =INPUT!E44 -> 159762 | F14: =INPUT!F44 -> 171735
B15: Total Current Liabilities | E15: =INPUT!E51 -> 144407 | F15: =INPUT!F51 -> 137247
B16: Long-Term Debt | E16: =INPUT!E54 -> 98959 | F16: =INPUT!F54 -> 95281
B17: Net Income | E17: =INPUT!E26 -> 90694 | F17: =INPUT!F26 -> 87496
B18: Cash from Operations (CFO) | E18: =INPUT!E75 -> 104393 | F18: =INPUT!F75 -> 92864
B19: Depreciation & Amortization | E19: =INPUT!E16 -> -11104 | F19: =INPUT!F16 -> -11519
B20: SG&A Expense | E20: =ABS(INPUT!E14) -> 25094 | F20: =ABS(INPUT!F14) -> 24932
B22: 8 BENEISH INDICES
B24: DSRI — Days Sales Receivable Index | F24: =IFERROR((INPUT!F35/INPUT!F9)/(INPUT!E35/INPUT!E9),"–") -> 1.0771419
B25: GMI — Gross Margin Index | F25: =IFERROR((E11/E9)/(F11/F9),"–") -> 0.98138504
B26: AQI — Asset Quality Index | F26: =IFERROR((1-(F12+F13)/F14)/(1-(E12+E13)/E14),"–") -> 1.1150668
B27: SGI — Sales Growth Index | F27: =IFERROR(F9/E9,"–") -> 0.97199539
B28: DEPI — Depreciation Index | F28: =IFERROR((E19/(E19+E13))/(F19/(F19+F13)),"–") -> 1.0007436
B29: SGAI — SG&A Expense Index | F29: =IFERROR((F20/F9)/(E20/E9),"–") -> 1.0221697
B30: TATA — Total Accruals to Total Assets | F30: =IFERROR((F17-F18)/F14,"–") -> -0.031257461
B31: LVGI — Leverage Index | F31: =IFERROR(((F16+F15)/F14)/((E16+E15)/E14),"–") -> 0.88885317
B33: M-SCORE WEIGHTED CALCULATION
B35: Constant | F35: =-4.84 -> -4.84
B36: 0.920 × DSRI | F36: =IFERROR(0.92*F24,"–") -> 0.99097059
B37: 0.528 × GMI | F37: =IFERROR(0.528*F25,"–") -> 0.5181713
B38: 0.404 × AQI | F38: =IFERROR(0.404*F26,"–") -> 0.45048697
B39: 0.892 × SGI | F39: =IFERROR(0.892*F27,"–") -> 0.86701989
B40: 0.115 × DEPI | F40: =IFERROR(0.115*F28,"–") -> 0.11508551
B41: -0.172 × SGAI | F41: =IFERROR(-0.172*F29,"–") -> -0.17581319
B42: 4.679 × TATA | F42: =IFERROR(4.679*F30,"–") -> -0.14625366
B43: -0.327 × LVGI | F43: =IFERROR(-0.327*F31,"–") -> -0.29065499
B45: M-SCORE (FINAL) | F45: =IFERROR(F35+F36+F37+F38+F39+F40+F41+F42+F43,"–") -> -2.5109876
B47: INTERPRETATION
B48: RESULT | F48: =IF(ISNUMBER(F45),IF(F45>-2.22,"⚠ POSSIBLE MANIPULATOR (M > -2.22)","✓ NOT LIKELY MANIPULATOR (M ≤ -2.22)"),"–") -> ✓ NOT LIKELY MANIPULATOR (M ≤ -2.22)
B50: NOT LIKELY MANIPULATOR
B51: POSSIBLE MANIPULATOR
B53: NOTE: Beneish M-Score (1999) uses current year (t) vs. prior year (t-1) data. Requires 2+ years of data.
B55: © 2015 to 2024 FinSight
B56: This Excel model is for educational purposes only.
B57: https://finsight.com/

Sheet DCF
B1: FinSight | K1: DCF — Discounted Cash Flow Valuation
B3: DCF
B4: All figures in USD millions unless stated
B5: METRIC | C5: (Units) | D5: =IF(INPUT!D5="","",INPUT!D5) | E5: =IF(INPUT!E5="","",INPUT!E5) -> 2022 | F5: =IF(INPUT!F5="","",INPUT!F5) -> 2023 | G5: =IF(INPUT!G5="","",INPUT!G5) -> 2024 | H5: =IF(INPUT!H5="","",INPUT!H5) -> 2025 (LTM) | I5: =TEXT(INPUT!D117+1,"0")&"F" -> 2026F | J5: =TEXT(INPUT!D117+2,"0")&"F" -> 2027F | K5: =TEXT(INPUT!D117+3,"0")&"F" -> 2028F | L5: =TEXT(INPUT!D117+4,"0")&"F" -> 2029F | M5: =TEXT(INPUT!D117+5,"0")&"F" -> 2030F | N5: Terminal
B7: INCOME STATEMENT
B9: Revenue | D9: =INPUT!D9 -> 0 | E9: =INPUT!E9 -> 394328 | F9: =INPUT!F9 -> 383285 | G9: =INPUT!G9 -> 391035 | H9: =IF(INPUT!H9<>"",INPUT!H9,INPUT!G9) -> 416161 | I9: =H9*(1+$I$29) -> 423994.6 | J9: =I9*(1+$I$29) -> 431975.66 | K9: =J9*(1+$I$29) -> 440106.94 | L9: =K9*(1+$I$29) -> 448391.29 | M9: =L9*(1+$I$29) -> 456831.58
B10: Cost of Goods Sold | D10: =INPUT!D10 -> 0 | E10: =INPUT!E10 -> -223546 | F10: =INPUT!F10 -> -214137 | G10: =INPUT!G10 -> -210352 | H10: =IF(INPUT!H10<>"",INPUT!H10,INPUT!G10) -> -220960 | I10: =-I9*(1-$I$30) -> -232611.63 | J10: =-J9*(1-$I$30) -> -236990.19 | K10: =-K9*(1-$I$30) -> -241451.17 | L10: =-L9*(1-$I$30) -> -245996.12 | M10: =-M9*(1-$I$30) -> -250626.63
B11: Gross Profit | D11: =SUM(D9:D10) -> 0 | E11: =SUM(E9:E10) -> 170782 | F11: =SUM(F9:F10) -> 169148 | G11: =SUM(G9:G10) -> 180683 | H11: =SUM(H9:H10) -> 195201 | I11: =SUM(I9:I10) -> 191382.97 | J11: =SUM(J9:J10) -> 194985.47 | K11: =SUM(K9:K10) -> 198655.77 | ... M11: =SUM(M9:M10) -> 206204.95
B13: SG&A Expenses | D13: =INPUT!D14 -> 0 | E13: =INPUT!E14 -> -25094 | F13: =INPUT!F14 -> -24932 | G13: =INPUT!G14 -> -26097 | H13: =IF(INPUT!H14<>"",INPUT!H14,INPUT!G14) -> -27601 | I13: =-I9*$I$31 -> -27744.801 | J13: =-J9*$I$31 -> -28267.055 | K13: =-K9*$I$31 -> -28799.139 | L13: =-L9*$I$31 -> -29341.24 | M13: =-M9*$I$31 -> -29893.544
B14: Research & Development | D14: =INPUT!D15 -> 0 | E14: =INPUT!E15 -> -26251 | F14: =INPUT!F15 -> -29915 | G14: =INPUT!G15 -> -31370 | H14: =IF(INPUT!H15<>"",INPUT!H15,INPUT!G15) -> -34550 | I14: =-I9*$I$32 -> -32633.19 | J14: =-J9*$I$32 -> -33247.461 | K14: =-K9*$I$32 -> -33873.294 | L14: =-L9*$I$32 -> -34510.907 | M14: =-M9*$I$32 -> -35160.523
B15: EBITDA | D15: =INPUT!D30 -> 0 | E15: =INPUT!E30 -> 119437 | F15: =INPUT!F30 -> 114301 | G15: =INPUT!G30 -> 123216 | H15: =IF(INPUT!H30<>"",INPUT!H30,INPUT!G30) -> 133050 | I15: =I11+I13+I14 -> 131004.98 | J15: =J11+J13+J14 -> 133470.95 | K15: =K11+K13+K14 -> 135983.34 | L15: =L11+L13+L14 -> 138543.02 | M15: =M11+M13+M14 -> 141150.88
B17: Depreciation & Amortization | D17: =INPUT!D16 -> 0 | E17: =INPUT!E16 -> -11104 | F17: =INPUT!F16 -> -11519 | G17: =INPUT!G16 -> -11445 | H17: =IF(INPUT!H16<>"",INPUT!H16,INPUT!G16) -> -11698 | I17: =-I9*$I$33 -> -12252.431 | J17: =-J9*$I$33 -> -12483.065 | K17: =-K9*$I$33 -> -12718.04 | L17: =-L9*$I$33 -> -12957.437 | M17: =-M9*$I$33 -> -13201.341
B18: EBIT (Operating Profit) | D18: =D15+D17 -> 0 | E18: =E15+E17 -> 108333 | F18: =F15+F17 -> 102782 | G18: =G15+G17 -> 111771 | H18: =H15+H17 -> 121352 | I18: =I15+I17 -> 118752.55 | J18: =J15+J17 -> 120987.89 | K18: =K15+K17 -> 123265.3 | ... M18: =M15+M17 -> 127949.54
B20: Interest Expense | D20: =INPUT!D20 -> 0 | E20: =INPUT!E20 -> -2931 | F20: =INPUT!F20 -> -3933 | G20: =INPUT!G20 -> 0 | H20: =IF(INPUT!H20<>"",INPUT!H20,INPUT!G20) -> 0 | I20: =-I18*(INPUT!H103)/(1-$I$34) -> -8363.3634 | J20: =-J18*(INPUT!H103)/(1-$I$34) -> -8520.791 | K20: =-K18*(INPUT!H103)/(1-$I$34) -> -8681.182 | L20: =-L18*(INPUT!H103)/(1-$I$34) -> -8844.5921 | M20: =-M18*(INPUT!H103)/(1-$I$34) -> -9011.0781
B21: Earnings Before Tax (EBT) | D21: =D18+D20 -> 0 | E21: =E18+E20 -> 105402 | F21: =F18+F20 -> 98849 | G21: =G18+G20 -> 111771 | H21: =H18+H20 -> 121352 | I21: =I18+I20 -> 110389.19 | J21: =J18+J20 -> 112467.1 | K21: =K18+K20 -> 114584.12 | ... M21: =M18+M20 -> 118938.46
B23: Income Taxes | D23: =INPUT!D24 -> 0 | E23: =INPUT!E24 -> -17533 | F23: =INPUT!F24 -> -15103 | G23: =INPUT!G24 -> -26926 | H23: =IF(INPUT!H24<>"",INPUT!H24,INPUT!G24) -> -18895 | I23: =-I21*$I$34 -> -19478.172 | J23: =-J21*$I$34 -> -19844.819 | K23: =-K21*$I$34 -> -20218.368 | L23: =-L21*$I$34 -> -20598.948 | M23: =-M21*$I$34 -> -20986.692
B24: Net Income | D24: =D21+D23 -> 0 | E24: =E21+E23 -> 87869 | F24: =F21+F23 -> 83746 | G24: =G21+G23 -> 84845 | H24: =H21+H23 -> 102457 | I24: =I21+I23 -> 90911.015 | J24: =J21+J23 -> 92622.277 | K24: =K21+K23 -> 94365.751 | ... M24: =M21+M23 -> 97951.771
B26: ASSUMPTIONS & DRIVERS
B27: All figures in USD millions unless stated
B28: INCOME STATEMENT DRIVERS | I28: =TEXT(INPUT!D117+1,"0")&"F" -> 2026F | J28: =TEXT(INPUT!D117+2,"0")&"F" -> 2027F | K28: =TEXT(INPUT!D117+3,"0")&"F" -> 2028F | L28: =TEXT(INPUT!D117+4,"0")&"F" -> 2029F | M28: =TEXT(INPUT!D117+5,"0")&"F" -> 2030F
B29: Revenue Growth Rate (YoY) | D29: =IFERROR(IF(NOT(ISBLANK(INPUT!H9)),INPUT!H9/INPUT!G9-1,IF(NOT(ISBLANK(INPUT!G9)),INPUT!G9/INPUT!F9-1,IF(NOT(ISBLANK(INPUT!F9)),INPUT!F9/INPUT!E9-1,IF(NOT(ISBLANK(INPUT!E9)),INPUT!E9/INPUT!D9-1,0.05)))),0.05) -> 0.064255118 | E29: =I29 -> 0.018823484 | F29: =I29 -> 0.018823484 | I29: =IFERROR(AVERAGE(IF(ISNUMBER(RATIOS!F51),RATIOS!F51,0),IF(ISNUMBER(RATIOS!G51),RATIOS!G51,0),IF(ISNUMBER(RATIOS!H51),RATIOS!H51,0)),0.05) -> 0.018823484 | J29: =I29 -> 0.018823484 | K29: =I29 -> 0.018823484 | L29: =I29 -> 0.018823484 | M29: =I29 -> 0.018823484
B30: Gross Margin | D30: =IFERROR(INPUT!H11/INPUT!H9,0.4) -> 0.46905164 | E30: =I30 -> 0.45138069 | F30: =I30 -> 0.45138069 | I30: =IFERROR(AVERAGE(IF(INPUT!E9<>0,INPUT!E11/INPUT!E9),IF(INPUT!F9<>0,INPUT!F11/INPUT!F9),IF(INPUT!G9<>0,INPUT!G11/INPUT!G9),IF(INPUT!H9<>0,INPUT!H11/INPUT!H9)),0.4) -> 0.45138069 | J30: =I30 -> 0.45138069 | K30: =I30 -> 0.45138069 | L30: =I30 -> 0.45138069 | M30: =I30 -> 0.45138069
B31: SG&A (% of Revenue) | D31: =IFERROR(ABS(INPUT!H14)/INPUT!H9,0.15) -> 0.066322889 | E31: =I31 -> 0.065436685 | F31: =I31 -> 0.065436685 | I31: =IFERROR(AVERAGE(IF(INPUT!E9<>0,ABS(INPUT!E14)/INPUT!E9),IF(INPUT!F9<>0,ABS(INPUT!F14)/INPUT!F9),IF(INPUT!G9<>0,ABS(INPUT!G14)/INPUT!G9),IF(INPUT!H9<>0,ABS(INPUT!H14)/INPUT!H9)),0.15) -> 0.065436685 | J31: =I31 -> 0.065436685 | K31: =I31 -> 0.065436685 | L31: =I31 -> 0.065436685 | M31: =I31 -> 0.065436685
B32: R&D (% of Revenue) | D32: =IFERROR(ABS(INPUT!H15)/INPUT!H9,0.05) -> 0.083020754 | E32: =I32 -> 0.076966052 | F32: =I32 -> 0.076966052 | I32: =IFERROR(AVERAGE(IF(INPUT!E9<>0,ABS(INPUT!E15)/INPUT!E9),IF(INPUT!F9<>0,ABS(INPUT!F15)/INPUT!F9),IF(INPUT!G9<>0,ABS(INPUT!G15)/INPUT!G9),IF(INPUT!H9<>0,ABS(INPUT!H15)/INPUT!H9)),0.05) -> 0.076966052 | J32: =I32 -> 0.076966052 | K32: =I32 -> 0.076966052 | L32: =I32 -> 0.076966052 | M32: =I32 -> 0.076966052
B33: D&A (% of Revenue) | D33: =IFERROR(ABS(INPUT!H16)/INPUT!H9,0.04) -> 0.028109313 | E33: =I33 -> 0.028897612 | F33: =I33 -> 0.028897612 | I33: =IFERROR(AVERAGE(IF(INPUT!E9<>0,ABS(INPUT!E16)/INPUT!E9),IF(INPUT!F9<>0,ABS(INPUT!F16)/INPUT!F9),IF(INPUT!G9<>0,ABS(INPUT!G16)/INPUT!G9),IF(INPUT!H9<>0,ABS(INPUT!H16)/INPUT!H9)),0.04) -> 0.028897612 | J33: =I33 -> 0.028897612 | K33: =I33 -> 0.028897612 | L33: =I33 -> 0.028897612 | M33: =I33 -> 0.028897612
B34: Effective Tax Rate | D34: =IFERROR(INPUT!H104,0.21) -> 0.1557 | E34: =I34 -> 0.17645 | F34: =I34 -> 0.17645 | I34: =IFERROR(AVERAGEIF(INPUT!E104:H104,"<>0"),0.21) -> 0.17645 | J34: =I34 -> 0.17645 | K34: =I34 -> 0.17645 | L34: =I34 -> 0.17645 | M34: =I34 -> 0.17645
B36: BALANCE SHEET / CASH FLOW DRIVERS
B37: CapEx (% of Revenue) | D37: =IFERROR(ABS(INPUT!H78)/INPUT!H9,0.05) -> 0.030553079 | E37: =I37 -> 0.02761485 | F37: =I37 -> 0.02761485 | I37: =IFERROR(AVERAGE(IF(INPUT!E9<>0,ABS(INPUT!E78)/INPUT!E9),IF(INPUT!F9<>0,ABS(INPUT!F78)/INPUT!F9),IF(INPUT!G9<>0,ABS(INPUT!G78)/INPUT!G9),IF(INPUT!H9<>0,ABS(INPUT!H78)/INPUT!H9)),0.05) -> 0.02761485 | J37: =I37 -> 0.02761485 | K37: =I37 -> 0.02761485 | L37: =I37 -> 0.02761485 | M37: =I37 -> 0.02761485
B38: Change in NWC (% of Revenue Change) | D38: =IFERROR(ABS((INPUT!H71+INPUT!H72+INPUT!H73)/INPUT!H9),0.1) -> 0.011358585 | E38: =I38 -> 0.0065151953 | F38: =I38 -> 0.0065151953 | I38: =IFERROR(AVERAGE(IF(INPUT!E9<>0,ABS((INPUT!E71+INPUT!E72+INPUT!E73)/INPUT!E9)),IF(INPUT!F9<>0,ABS((INPUT!F71+INPUT!F72+INPUT!F73)/INPUT!F9)),IF(INPUT!G9<>0,ABS((INPUT!G71+INPUT!G72+INPUT!G73)/INPUT!G9)),IF(INPUT!H9<>0,ABS((INPUT!H71+INPUT!H72+INPUT!H73)/INPUT!H9))),0.1) -> 0.0065151953 | J38: =I38 -> 0.0065151953 | K38: =I38 -> 0.0065151953 | L38: =I38 -> 0.0065151953 | M38: =I38 -> 0.0065151953
B40: FREE CASH FLOW CALCULATION
B42: EBIT | D42: =D18 -> 0 | E42: =E18 -> 108333 | F42: =F18 -> 102782 | G42: =G18 -> 111771 | H42: =H18 -> 121352 | I42: =I18 -> 118752.55 | J42: =J18 -> 120987.89 | K42: =K18 -> 123265.3 | ... M42: =M18 -> 127949.54
B43: (-) Taxes on EBIT (Unlevered) | D43: =D18*(-INPUT!D104) -> 0 | E43: =E18*(-INPUT!E104) -> -17549.946 | F43: =F18*(-INPUT!F104) -> -15129.51 | G43: =G18*(-INPUT!G104) -> -26925.634 | H43: =H18*(-INPUT!H104) -> -18894.506 | I43: =I18*(-$I$34) -> -20953.888 | J43: =J18*(-$I$34) -> -21348.313 | K43: =K18*(-$I$34) -> -21750.162 | L43: =L18*(-$I$34) -> -22159.576 | M43: =M18*(-$I$34) -> -22576.697
B44: NOPAT (Net Operating Profit After Tax) | D44: =D42+D43 -> 0 | E44: =E42+E43 -> 90783.054 | F44: =F42+F43 -> 87652.49 | G44: =G42+G43 -> 84845.366 | H44: =H42+H43 -> 102457.49 | I44: =I42+I43 -> 97798.663 | J44: =J42+J43 -> 99639.574 | K44: =K42+K43 -> 101515.14 | ... M44: =M42+M43 -> 105372.84
B46: (+) Depreciation & Amortization | D46: =ABS(D17) -> 0 | E46: =ABS(E17) -> 11104 | F46: =ABS(F17) -> 11519 | G46: =ABS(G17) -> 11445 | H46: =ABS(H17) -> 11698 | I46: =ABS(I17) -> 12252.431 | J46: =ABS(J17) -> 12483.065 | K46: =ABS(K17) -> 12718.04 | ... M46: =ABS(M17) -> 13201.341
B47: (-) Capital Expenditures (CapEx) | D47: =INPUT!D78 -> 0 | E47: =INPUT!E78 -> -10708 | F47: =INPUT!F78 -> -10959 | G47: =INPUT!G78 -> -9447 | H47: =IF(INPUT!H78<>"",INPUT!H78,INPUT!G78) -> -12715 | I47: =-I9*$I$37 -> -11708.547 | J47: =-J9*$I$37 -> -11928.943 | K47: =-K9*$I$37 -> -12153.487 | L47: =-L9*$I$37 -> -12382.258 | M47: =-M9*$I$37 -> -12615.336
B48: (-) Change in Working Capital | D48: =INPUT!D70+INPUT!D71+INPUT!D72+INPUT!D73 -> 0 | E48: =INPUT!E70+INPUT!E71+INPUT!E72+INPUT!E73 -> 12693 | F48: =INPUT!F70+INPUT!F71+INPUT!F72+INPUT!F73 -> 7595 | G48: =INPUT!G70+INPUT!G71+INPUT!G72+INPUT!G73 -> 11275 | H48: =IF(INPUT!H70<>"",INPUT!H70,INPUT!G70)+IF(INPUT!H71<>"",INPUT!H71,INPUT!G71)+IF(INPUT!H72<>"",INPUT!H72,INPUT!G72)+IF(INPUT!H73<>"",INPUT!H73,INPUT!G73) -> 6971 | I48: =-(I9-H9)*$I$38 -> -51.037435 | J48: =-(J9-I9)*$I$38 -> -51.998137 | K48: =-(K9-J9)*$I$38 -> -52.976923 | L48: =-(L9-K9)*$I$38 -> -53.974134 | M48: =-(M9-L9)*$I$38 -> -54.990115
B49: Unlevered Free Cash Flow (UFCF) | D49: =D44+D46+D47+D48 -> 0 | E49: =E44+E46+E47+E48 -> 103872.05 | F49: =F44+F46+F47+F48 -> 95807.49 | G49: =G44+G46+G47+G48 -> 98118.366 | H49: =H44+H46+H47+H48 -> 108411.49 | I49: =I44+I46+I47+I48 -> 98291.509 | J49: =J44+J46+J47+J48 -> 100141.7 | K49: =K44+K46+K47+K48 -> 102026.71 | ... M49: =M44+M46+M47+M48 -> 105903.86
B51: WACC CALCULATION (Capital Asset Pricing Model)
B53: Risk-Free Rate (Rf) | D53: =INPUT!H100 -> 0.043 | N53: =D53 -> 0.043
B54: Beta (Levered) | D54: =INPUT!H99 -> 1.109 | N54: =D54 -> 1.109
B55: Equity Risk Premium (ERP) | D55: =INPUT!H101 -> 0.055 | N55: =D55 -> 0.055
B56: Cost of Equity (CAPM) | D56: =D53+D54*D55 -> 0.103995 | N56: =D56 -> 0.103995
B58: Target Equity Weight (We) | D58: =INPUT!H106 -> 0.9749 | N58: =D58 -> 0.9749
B59: Target Debt Weight (Wd) | D59: =INPUT!H107 -> 0.0251 | N59: =D59 -> 0.0251
B60: Pre-Tax Cost of Debt (Kd) | D60: =INPUT!H103 -> 0.058 | N60: =D60 -> 0.058
B61: Tax Rate | D61: =INPUT!H104 -> 0.1557 | N61: =D61 -> 0.1557
B62: After-Tax Cost of Debt | D62: =D60*(1-D61) -> 0.0489694 | N62: =D62 -> 0.0489694
B63: WACC | D63: =D58*D56+D62*D59 -> 0.10261386 | N63: =D63 -> 0.10261386
B65: TERMINAL VALUE & ENTERPRISE VALUE
B67: Terminal Growth Rate (g) | D67: =INPUT!H109 -> 0.03 | N67: =D67 -> 0.03
B68: WACC | D68: =D63 -> 0.10261386 | N68: =D68 -> 0.10261386
B69: Year 5 UFCF | D69: =M49 -> 105903.86 | N69: =D69 -> 105903.86
B70: Terminal Year UFCF (t+1) | D70: =D69*(1+D67) -> 109080.98 | N70: =D70 -> 109080.98
B71: Terminal Value (Gordon Growth) | D71: =IFERROR(D70/(D68-D67),"–") -> 1502206.1 | N71: =D71 -> 1502206.1
B72: Terminal EBITDA Multiple (Alt.) | D72: =IFERROR(D71/M15,"–") -> 10.642555 | N72: =D72 -> 10.642555
B74: Discounting Period (Years) | D74: =1 -> 1 | J74: 2 | K74: 3 | L74: 4 | M74: 5 | N74: 5
B75: Discount Factor | D75: =1/(1+$D$68)^I74 -> 1 | J75: =1/(1+$D$68)^J74 -> 0.82253258 | K75: =1/(1+$D$68)^K74 -> 0.74598425 | L75: =1/(1+$D$68)^L74 -> 0.67655984 | M75: =1/(1+$D$68)^M74 -> 0.61359635 | N75: =1/(1+$D$68)^M74 -> 0.61359635
B76: UFCF to Discount | D76: =I49 -> 98291.509 | J76: =J49 -> 100141.7 | K76: =K49 -> 102026.71 | L76: =L49 -> 103947.21 | M76: =M49 -> 105903.86
B77: Terminal Value to Discount | N77: =D71 -> 1502206.1
B78: PV of UFCF + Terminal Value | J78: =J75*J76 -> 82369.809 | K78: =K75*K76 -> 76110.322 | L78: =L75*L76 -> 70326.509 | M78: =M75*M76 -> 64982.222 | N78: =IFERROR(N75*N77,"–") -> 921748.16
B80: ENTERPRISE VALUE & EQUITY VALUE
B82: Sum of PV of UFCFs (Years 1-5) | D82: =SUM(I78:M78) -> 293788.86 | N82: =D82 -> 293788.86
B83: PV of Terminal Value | D83: =N78 -> 921748.16 | N83: =D83 -> 921748.16
B84: Enterprise Value (EV) | D84: =IFERROR(D82+D83,"–") -> 1215537 | N84: =D84 -> 1215537
B86: (-) Total Debt | D86: =-(INPUT!H49+INPUT!H55) -> -239001 | N86: =D86 -> -239001
B87: (+) Cash & Cash Equivalents | D87: =INPUT!H34 -> 35934 | N87: =D87 -> 35934
B88: Equity Value | D88: =IFERROR(D84+D86+D87,"–") -> 1012470 | N88: =D88 -> 1012470
B90: Shares Outstanding (Diluted) | D90: =INPUT!H96 -> 14681.14 | N90: =D90 -> 14681.14
B91: Implied Share Price (DCF) | D91: =IFERROR(D88/D90,"–") -> 68.963992 | N91: =D91 -> 68.963992
B92: Current Share Price | C92: ($) | D92: =INPUT!H95 -> 261.3 | N92: =D92 -> 261.3
B93: Upside / (Downside) | C93: (%) | D93: =IFERROR(D91/D92-1,"–") -> -0.73607351 | N93: =D93 -> -0.73607351
B94: UFCF IRR (5-Year) | C94: (%) | D94: =IFERROR(IRR(I49:M49),"–") -> –
B96: SENSITIVITY ANALYSIS — Implied Share Price ($) | M96: =ROUND(C98*100,1)&"%" -> 8,3% | N96: =ROUND(C99*100,1)&"%" -> 9,3% | O96: =ROUND(C100*100,1)&"%" -> 10,3% | P96: =ROUND(C101*100,1)&"%" -> 11,3% | Q96: =ROUND(C102*100,1)&"%" -> 12,3%
B97: Terminal Growth Rate → | C97: WACC ↓ | D97: 0 | E97: 0.01 | F97: 0.02 | G97: 0.03 | H97: 0.04 | L97: g=0% | M97: =D98 -> 64.892069 | N97: =D99 -> 56.199349 | O97: =D100 -> 49.314381 | P97: =D101 -> 43.749194 | Q97: =D102 -> 39.17542
C98: =D63-0.02 -> 0.082613857 | D98: =IFERROR((D82+((D69*(1+0))/(C98-0))/(1+C98)^5+D86+D87)/D90,"–") -> 64.892069 | E98: =IFERROR((D82+((D69*(1+0.01))/(C98-0.01))/(1+C98)^5+D86+D87)/D90,"–") -> 73.64564 | F98: =IFERROR((D82+((D69*(1+0.02))/(C98-0.02))/(1+C98)^5+D86+D87)/D90,"–") -> 85.19526 | G98: =IFERROR((D82+((D69*(1+0.03))/(C98-0.03))/(1+C98)^5+D86+D87)/D90,"–") -> 101.13522 | H98: =IFERROR((D82+((D69*(1+0.04))/(C98-0.04))/(1+C98)^5+D86+D87)/D90,"–") -> 124.55628 | L98: g=1% | M98: =E98 -> 73.64564 | N98: =E99 -> 62.814752 | O98: =E100 -> 54.449804 | P98: =E101 -> 47.822775 | Q98: =E102 -> 42.464686
C99: =D63-0.01 -> 0.092613857 | D99: =IFERROR((D82+((D69*(1+0))/(C99-0))/(1+C99)^5+D86+D87)/D90,"–") -> 56.199349 | E99: =IFERROR((D82+((D69*(1+0.01))/(C99-0.01))/(1+C99)^5+D86+D87)/D90,"–") -> 62.814752 | F99: =IFERROR((D82+((D69*(1+0.02))/(C99-0.02))/(1+C99)^5+D86+D87)/D90,"–") -> 71.252232 | G99: =IFERROR((D82+((D69*(1+0.03))/(C99-0.03))/(1+C99)^5+D86+D87)/D90,"–") -> 82.384797 | H99: =IFERROR((D82+((D69*(1+0.04))/(C99-0.04))/(1+C99)^5+D86+D87)/D90,"–") -> 97.749161 | L99: g=2% | M99: =F98 -> 85.19526 | N99: =F99 -> 71.252232 | O99: =F100 -> 60.828462 | P99: =F101 -> 52.776047 | Q99: =F102 -> 46.395049
C100: =D63 -> 0.10261386 | D100: =IFERROR((D82+((D69*(1+0))/(C100-0))/(1+C100)^5+D86+D87)/D90,"–") -> 49.314381 | E100: =IFERROR((D82+((D69*(1+0.01))/(C100-0.01))/(1+C100)^5+D86+D87)/D90,"–") -> 54.449804 | F100: =IFERROR((D82+((D69*(1+0.02))/(C100-0.02))/(1+C100)^5+D86+D87)/D90,"–") -> 60.828462 | G100: =IFERROR((D82+((D69*(1+0.03))/(C100-0.03))/(1+C100)^5+D86+D87)/D90,"–") -> 68.963992 | H100: =IFERROR((D82+((D69*(1+0.04))/(C100-0.04))/(1+C100)^5+D86+D87)/D90,"–") -> 79.698157 | L100: g=3% (Base) | M100: =G98 -> 101.13522 | N100: =G99 -> 82.384797 | O100: =G100 -> 68.963992 | P100: =G101 -> 58.928457 | Q100: =G102 -> 51.174174
C101: =D63+0.01 -> 0.11261386 | D101: =IFERROR((D82+((D69*(1+0))/(C101-0))/(1+C101)^5+D86+D87)/D90,"–") -> 43.749194 | E101: =IFERROR((D82+((D69*(1+0.01))/(C101-0.01))/(1+C101)^5+D86+D87)/D90,"–") -> 47.822775 | F101: =IFERROR((D82+((D69*(1+0.02))/(C101-0.02))/(1+C101)^5+D86+D87)/D90,"–") -> 52.776047 | G101: =IFERROR((D82+((D69*(1+0.03))/(C101-0.03))/(1+C101)^5+D86+D87)/D90,"–") -> 58.928457 | H101: =IFERROR((D82+((D69*(1+0.04))/(C101-0.04))/(1+C101)^5+D86+D87)/D90,"–") -> 66.775422 | L101: g=4% | M101: =H98 -> 124.55628 | N101: =H99 -> 97.749161 | O101: =H100 -> 79.698157 | P101: =H101 -> 66.775422 | Q101: =H102 -> 57.110279
C102: =D63+0.02 -> 0.12261386 | D102: =IFERROR((D82+((D69*(1+0))/(C102-0))/(1+C102)^5+D86+D87)/D90,"–") -> 39.17542 | E102: =IFERROR((D82+((D69*(1+0.01))/(C102-0.01))/(1+C102)^5+D86+D87)/D90,"–") -> 42.464686 | F102: =IFERROR((D82+((D69*(1+0.02))/(C102-0.02))/(1+C102)^5+D86+D87)/D90,"–") -> 46.395049 | G102: =IFERROR((D82+((D69*(1+0.03))/(C102-0.03))/(1+C102)^5+D86+D87)/D90,"–") -> 51.174174 | H102: =IFERROR((D82+((D69*(1+0.04))/(C102-0.04))/(1+C102)^5+D86+D87)/D90,"–") -> 57.110279
B103: Yellow = Base Case (WACC = 10.4%, g = 3.0%)
B105: SCENARIO ANALYSIS — 3 SCENARIOS
B106: METRIC | C106: (Units) | E106: Pessimistic | F106: Realistic | G106: Optimistic
B107: Revenue Growth (Y1-Y5 avg.) | C107: (%) | D107: =D29-0.03 -> 0.034255118 | E107: =D29-0.02 -> 0.044255118 | F107: =D29 -> 0.064255118 | G107: =D29+0.02 -> 0.084255118
B108: EBITDA Margin | C108: (%) | D108: =IFERROR(D15/D9-0.03,"–") -> – | E108: =IFERROR(H15/H9-0.02,"–") -> 0.299708 | F108: =IFERROR(H15/H9,"–") -> 0.319708 | G108: =IFERROR(H15/H9+0.02,"–") -> 0.339708
B109: Terminal Growth Rate | C109: (%) | D109: =D67-0.01 -> 0.02 | E109: =D67-0.01 -> 0.02 | F109: =D67 -> 0.03 | G109: =D67+0.01 -> 0.04
B110: WACC | C110: (%) | D110: =D63+0.01 -> 0.11261386 | E110: =D63+0.01 -> 0.11261386 | F110: =D63 -> 0.10261386 | G110: =D63-0.01 -> 0.092613857
B111: Implied Share Price ($) | C111: ($) | D111: =IFERROR((D82+((D69*(1+D109))/(D110-D109))/(1+D110)^5+D86+D87)/D90,"–") -> 52.776047 | E111: =IFERROR((D82+((D69*(1+E109))/(E110-E109))/(1+E110)^5+D86+D87)/D90,"–") -> 52.776047 | F111: =IFERROR((D82+((D69*(1+F109))/(F110-F109))/(1+F110)^5+D86+D87)/D90,"–") -> 68.963992 | G111: =IFERROR((D82+((D69*(1+G109))/(G110-G109))/(1+G110)^5+D86+D87)/D90,"–") -> 97.749161
B113: © 2015 to 2024 FinSight
B114: This Excel model is for educational purposes only.
B115: https://finsight.com/
B117: UFCF Projection ($M) | C117: =TEXT(INPUT!D117+1,"0")&"F" -> 2026F | D117: =TEXT(INPUT!D117+2,"0")&"F" -> 2027F | E117: =TEXT(INPUT!D117+3,"0")&"F" -> 2028F | F117: =TEXT(INPUT!D117+4,"0")&"F" -> 2029F | G117: =TEXT(INPUT!D117+5,"0")&"F" -> 2030F
B118: UFCF | C118: =IF(I49=0,NA(),I49) -> 98291.509 | D118: =IF(J49=0,NA(),J49) -> 100141.7 | E118: =IF(K49=0,NA(),K49) -> 102026.71 | F118: =IF(L49=0,NA(),L49) -> 103947.21 | G118: =IF(M49=0,NA(),M49) -> 105903.86
B120: Revenue Projection ($M) | C120: =IF(I9=0,NA(),C117) -> 2026F | D120: =IF(J9=0,NA(),D117) -> 2027F | E120: =IF(K9=0,NA(),E117) -> 2028F | F120: =IF(L9=0,NA(),F117) -> 2029F | G120: =IF(M9=0,NA(),G117) -> 2030F
B121: Revenue | C121: =IF(I9=0,NA(),I9) -> 423994.6 | D121: =IF(J9=0,NA(),J9) -> 431975.66 | E121: =IF(K9=0,NA(),K9) -> 440106.94 | F121: =IF(L9=0,NA(),L9) -> 448391.29 | G121: =IF(M9=0,NA(),M9) -> 456831.58

Sheet COMPARABLES
B1: FinSight | K1: COMPARABLES — Trading Comparables
B3: COMPARABLES
B4: All figures in USD millions unless stated
B6: COMPARABLE TRADING ANALYSIS
D7: Share Price | E7: Enterprise Value | F7: Revenue (LTM) | G7: EBITDA (LTM) | H7: EV / EBITDA | I7: EV / Revenue | J7: EPS (LTM) | K7: P / E (LTM)
B8: PEER COMPANIES | C8: TICKER | D8: (USD/sh) | E8: ($M) | F8: ($M) | G8: ($M) | H8: (x) | I8: (x) | J8: (USD/sh) | K8: (x)
B9: Microsoft Corporation | C9: MSFT | D9: 370.79 | E9: 2804095.4 | F9: 305453.01 | G9: 175258.99 | H9: =IFERROR(E9/G9,"–") -> 15.999724 | I9: =IFERROR(E9/F9,"–") -> 9.1801203 | J9: 15.98 | K9: =IFERROR(D9/J9,"–") -> 23.203379
B10: Alphabet Inc. | C10: GOOG | D10: 316.08 | E10: 3767280.9 | F10: 402836 | G10: 150175.01 | H10: =IFERROR(E10/G10,"–") -> 25.085937 | I10: =IFERROR(E10/F10,"–") -> 9.3518972 | J10: 10.81 | K10: =IFERROR(D10/J10,"–") -> 29.239593
B11: Meta Platforms, Inc. | C11: META | D11: 627 | E11: 1593036.4 | F11: 200966 | G11: 101892 | H11: =IFERROR(E11/G11,"–") -> 15.634558 | I11: =IFERROR(E11/F11,"–") -> 7.9268949 | J11: 23.5 | K11: =IFERROR(D11/J11,"–") -> 26.680851
B12: Sony Group Corporation | C12: SONY | D12: 20.99 | E12: 54186.15 | F12: 13170288 | G12: 2036071 | H12: =IFERROR(E12/G12,"–") -> 0.026613094 | I12: =IFERROR(E12/F12,"–") -> 0.0041142723 | J12: 1.3 | K12: =IFERROR(D12/J12,"–") -> 16.146154
B13: SMSNG.KS | C13: SMSNG.KS | D13: 87.8 | E13: 258704.92 | F13: 321913 | G13: 24292 | H13: =IFERROR(E13/G13,"–") -> 10.649799 | I13: =IFERROR(E13/F13,"–") -> 0.80364856 | K13: =IFERROR(D13/J13,"–") -> –
B15: Mean | D15: =IFERROR(AVERAGE(D9:D13),"–") -> 284.532 | E15: =IFERROR(AVERAGE(E9:E13),"–") -> 1695460.7 | F15: =IFERROR(AVERAGE(F9:F13),"–") -> 2880291.1 | G15: =IFERROR(AVERAGE(G9:G13),"–") -> 497537.8 | H15: =IFERROR(AVERAGE(H9:H13),"–") -> 13.479326 | I15: =IFERROR(AVERAGE(I9:I13),"–") -> 5.4533351 | J15: =IFERROR(AVERAGE(J9:J13),"–") -> 12.8975 | K15: =IFERROR(AVERAGE(K9:K13),"–") -> 23.817494
B16: Median | D16: =IFERROR(MEDIAN(D9:D13),"–") -> 316.08 | E16: =IFERROR(MEDIAN(E9:E13),"–") -> 1593036.4 | F16: =IFERROR(MEDIAN(F9:F13),"–") -> 321913 | G16: =IFERROR(MEDIAN(G9:G13),"–") -> 150175.01 | H16: =IFERROR(MEDIAN(H9:H13),"–") -> 15.634558 | I16: =IFERROR(MEDIAN(I9:I13),"–") -> 7.9268949 | J16: =IFERROR(MEDIAN(J9:J13),"–") -> 13.395 | K16: =IFERROR(MEDIAN(K9:K13),"–") -> 24.942115
B17: Maximum | D17: =IFERROR(MAX(D9:D13),"–") -> 627 | E17: =IFERROR(MAX(E9:E13),"–") -> 3767280.9 | F17: =IFERROR(MAX(F9:F13),"–") -> 13170288 | G17: =IFERROR(MAX(G9:G13),"–") -> 2036071 | H17: =IFERROR(MAX(H9:H13),"–") -> 25.085937 | I17: =IFERROR(MAX(I9:I13),"–") -> 9.3518972 | J17: =IFERROR(MAX(J9:J13),"–") -> 23.5 | K17: =IFERROR(MAX(K9:K13),"–") -> 29.239593
B18: Minimum | D18: =IFERROR(MIN(D9:D13),"–") -> 20.99 | E18: =IFERROR(MIN(E9:E13),"–") -> 54186.15 | F18: =IFERROR(MIN(F9:F13),"–") -> 200966 | G18: =IFERROR(MIN(G9:G13),"–") -> 24292 | H18: =IFERROR(MIN(H9:H13),"–") -> 0.026613094 | I18: =IFERROR(MIN(I9:I13),"–") -> 0.0041142723 | J18: =IFERROR(MIN(J9:J13),"–") -> 1.3 | K18: =IFERROR(MIN(K9:K13),"–") -> 16.146154
B20: TARGET COMPANY VALUATION (Based on Peer Multiples)
B21: TARGET COMPANY METRICS (from INPUT) | D21: =INPUT!H5 -> 2025 (LTM)
B22: Target: Revenue (LTM) | C22: ($M) | D22: =INPUT!H9/1000 -> 416.161
B23: Target: EBITDA (LTM) | C23: ($M) | D23: =INPUT!H30/1000 -> 133.05
B24: Target: EPS (LTM) | C24: ($) | D24: =IFERROR(INPUT!F26/INPUT!F96,"–") -> 5.5331689
B25: Target: Net Debt | C25: ($M) | D25: =IFERROR((INPUT!H54+INPUT!H55-INPUT!H34)/1000,"–") -> 268.379
B26: Target: Shares Outstanding | C26: (M) | D26: =INPUT!H96/1000 -> 14.68114
B28: IMPLIED VALUATION
B29: EV / EBITDA — Implied EV ($M) | D29: =IFERROR(D23*H18,"–") -> 3.5408722 | E29: =IFERROR(D23*H15,"–") -> 1793.4243 | F29: =IFERROR(D23*H16,"–") -> 2080.1779 | G29: =IFERROR(D23*H17,"–") -> 3337.6839
B30: EV / Revenue — Implied EV ($M) | D30: =IFERROR(D22*I18,"–") -> 1.7121997 | E30: =IFERROR(D22*I15,"–") -> 2269.4654 | F30: =IFERROR(D22*I16,"–") -> 3298.8645 | G30: =IFERROR(D22*I17,"–") -> 3891.8949
B31: P/E — Implied Equity Value ($M) | D31: =IFERROR(D24*K18*D26,"–") -> 1311.6042 | E31: =IFERROR(D24*K15*D26,"–") -> 1934.7719 | F31: =IFERROR(D24*K16*D26,"–") -> 2026.1285 | G31: =IFERROR(D24*K17*D26,"–") -> 2375.2265
B33: Implied Enterprise Value (Average of 3 Methods) | C33: ($M) | D33: =IFERROR(AVERAGE(D29,D30),"–") -> 2.626536 | E33: =IFERROR(AVERAGE(E29,E30),"–") -> 2031.4449 | F33: =IFERROR(AVERAGE(F29,F30),"–") -> 2689.5212 | G33: =IFERROR(AVERAGE(G29,G30),"–") -> 3614.7894
B34: (-) Net Debt | C34: ($M) | D34: =D25 -> 268.379 | E34: =D25 -> 268.379 | F34: =D25 -> 268.379 | G34: =D25 -> 268.379
B35: Implied Equity Value ($M) | C35: ($M) | D35: =IFERROR(D33-D34,"–") -> -265.75246 | E35: =IFERROR(E33-E34,"–") -> 1763.0659 | F35: =IFERROR(F33-F34,"–") -> 2421.1422 | G35: =IFERROR(G33-G34,"–") -> 3346.4104
B36: Implied Share Price ($) | C36: ($) | D36: =IFERROR(D35/D26,"–") -> -18.101623 | E36: =IFERROR(E35/D26,"–") -> 120.09053 | F36: =IFERROR(F35/D26,"–") -> 164.91514 | G36: =IFERROR(G35/D26,"–") -> 227.93941
B37: Current Share Price ($) | C37: ($) | D37: =INPUT!H95 -> 261.3 | E37: =INPUT!H95 -> 261.3 | F37: =INPUT!H95 -> 261.3 | G37: =INPUT!H95 -> 261.3
B38: Implied Upside / (Downside) | C38: (%) | D38: =IFERROR(D36/D37-1,"–") -> -1.0692753 | E38: =IFERROR(E36/D37-1,"–") -> -0.5404113 | F38: =IFERROR(F36/D37-1,"–") -> -0.36886668 | G38: =IFERROR(G36/D37-1,"–") -> -0.1276716
B41: (1) Target company EV based on LTM EV/EBITDA and EV/Revenue multiples relative to comparable peer set.
B43: © 2015 to 2024 FinSight
B44: This Excel model is for educational purposes only.
B45: https://finsight.com/
B47: Company | C47: EV/EBITDA (x) | D47: EV/Revenue (x) | E47: P/E (x)
B48: =B9 -> Microsoft Corporation | C48: =IFERROR(H9*1,0) -> 15.999724 | D48: =IFERROR(I9*1,0) -> 9.1801203 | E48: =IFERROR(K9*1,0) -> 23.203379
B49: =B10 -> Alphabet Inc. | C49: =IFERROR(H10*1,0) -> 25.085937 | D49: =IFERROR(I10*1,0) -> 9.3518972 | E49: =IFERROR(K10*1,0) -> 29.239593
B50: =B11 -> Meta Platforms, Inc. | C50: =IFERROR(H11*1,0) -> 15.634558 | D50: =IFERROR(I11*1,0) -> 7.9268949 | E50: =IFERROR(K11*1,0) -> 26.680851
B51: =B12 -> Sony Group Corporation | C51: =IFERROR(H12*1,0) -> 0.026613094 | D51: =IFERROR(I12*1,0) -> 0.0041142723 | E51: =IFERROR(K12*1,0) -> 16.146154
B52: =B13 -> SMSNG.KS | C52: =IFERROR(H13*1,0) -> 10.649799 | D52: =IFERROR(I13*1,0) -> 0.80364856 | E52: =IFERROR(K13*1,0) -> 0
B53: =B15 -> Mean | C53: =IFERROR(H15*1,0) -> 13.479326 | D53: =IFERROR(I15*1,0) -> 5.4533351 | E53: =IFERROR(K15*1,0) -> 23.817494
B54: Implied Share Price — Valuation Range ($) | H54: Method | I54: Low ($) | J54: High ($) | K54: Current ($)
B55: Method | C55: Low ($) | D55: Median ($) | E55: High ($) | H55: EV/EBITDA | I55: =IFERROR(D36,0) -> -18.101623 | J55: =IFERROR(G36,0) -> 227.93941 | K55: =INPUT!H95 -> 261.3
B56: =B29 -> EV / EBITDA — Implied EV ($M) | C56: =IFERROR(D36,"–") -> -18.101623 | D56: =IFERROR(F36,"–") -> 164.91514 | E56: =IFERROR(G36,"–") -> 227.93941 | H56: EV/Revenue | I56: =IFERROR(D36,0) -> -18.101623 | J56: =IFERROR(G36,0) -> 227.93941 | K56: =INPUT!H95 -> 261.3
B57: =B30 -> EV / Revenue — Implied EV ($M) | C57: =IFERROR(D36,"–") -> -18.101623 | D57: =IFERROR(F36,"–") -> 164.91514 | E57: =IFERROR(G36,"–") -> 227.93941 | F57: vé | H57: P/E | I57: =IFERROR(D36,0) -> -18.101623 | J57: =IFERROR(G36,0) -> 227.93941 | K57: =INPUT!H95 -> 261.3

Sheet SCENARIOS
B1: FinSight | H1: SCENARIOS — Scenario Analysis
B3: SCENARIOS
B4: All figures in USD millions unless stated | 3 scenarios: Pessimistic / Realistic (Base) / Optimistic
B5: METRIC | C5: (Units) | E5: =TEXT(INPUT!D117-3,"0") -> 2022 | F5: =TEXT(INPUT!D117-2,"0") -> 2023 | G5: =TEXT(INPUT!D117-1,"0") -> 2024 | H5: =INPUT!D117&" (LTM)" -> 2025 (LTM) | I5: =TEXT(INPUT!D117+1,"0")&"F" -> 2026F | J5: =TEXT(INPUT!D117+2,"0")&"F" -> 2027F | K5: =TEXT(INPUT!D117+3,"0")&"F" -> 2028F | L5: =TEXT(INPUT!D117+4,"0")&"F" -> 2029F | M5: =TEXT(INPUT!D117+5,"0")&"F" -> 2030F
B6: ▶ SELECT SCENARIO | D6: Realistic
B7: SCENARIO ASSUMPTIONS
B8: DRIVER | C8: (Units) | D8: Pessimistic | E8: Realistic | F8: Optimistic
B9: Revenue Growth Rate (Y1-Y5) | C9: (%) | D9: {=IFERROR(INDEX(SECTOR_REF!$C$2:$E$61,MATCH(1,(SECTOR_REF!$A$2:$A$61=INPUT!$D$116)*(SECTOR_REF!$B$2:$B$61="Revenue Growth Rate (Y1-Y5)"),0),MATCH("Pessimiste",{"Pessimiste","Realiste","Optimiste"},0)),IFERROR(INPUT!H9/INPUT!G9-1,0.02))} -> 0.064255118 | E9: {=IFERROR(INDEX(SECTOR_REF!$C$2:$E$61,MATCH(1,(SECTOR_REF!$A$2:$A$61=INPUT!$D$116)*(SECTOR_REF!$B$2:$B$61="Revenue Growth Rate (Y1-Y5)"),0),MATCH("Realiste",{"Pessimiste","Realiste","Optimiste"},0)),IFERROR(INPUT!H9/INPUT!G9-1,0.05))} -> 0.064255118 | F9: {=IFERROR(INDEX(SECTOR_REF!$C$2:$E$61,MATCH(1,(SECTOR_REF!$A$2:$A$61=INPUT!$D$116)*(SECTOR_REF!$B$2:$B$61="Revenue Growth Rate (Y1-Y5)"),0),MATCH("Optimiste",{"Pessimiste","Realiste","Optimiste"},0)),IFERROR(INPUT!H9/INPUT!G9-1,0.09))} -> 0.064255118
B10: Gross Margin | C10: (%) | D10: {=IFERROR(INDEX(SECTOR_REF!$C$2:$E$61,MATCH(1,(SECTOR_REF!$A$2:$A$61=INPUT!$D$116)*(SECTOR_REF!$B$2:$B$61="Gross Margin"),0),MATCH("Pessimiste",{"Pessimiste","Realiste","Optimiste"},0)),IFERROR(INPUT!H11/INPUT!H9,0.4)-0.03)} -> 0.43905164 | E10: {=IFERROR(INDEX(SECTOR_REF!$C$2:$E$61,MATCH(1,(SECTOR_REF!$A$2:$A$61=INPUT!$D$116)*(SECTOR_REF!$B$2:$B$61="Gross Margin"),0),MATCH("Realiste",{"Pessimiste","Realiste","Optimiste"},0)),IFERROR(INPUT!H11/INPUT!H9,0.4))} -> 0.46905164 | F10: {=IFERROR(INDEX(SECTOR_REF!$C$2:$E$61,MATCH(1,(SECTOR_REF!$A$2:$A$61=INPUT!$D$116)*(SECTOR_REF!$B$2:$B$61="Gross Margin"),0),MATCH("Optimiste",{"Pessimiste","Realiste","Optimiste"},0)),IFERROR(INPUT!H11/INPUT!H9,0.4)+0.03)} -> 0.49905164
B11: EBITDA Margin | C11: (%) | D11: {=IFERROR(INDEX(SECTOR_REF!$C$2:$E$61,MATCH(1,(SECTOR_REF!$A$2:$A$61=INPUT!$D$116)*(SECTOR_REF!$B$2:$B$61="EBITDA Margin"),0),MATCH("Pessimiste",{"Pessimiste","Realiste","Optimiste"},0)),IFERROR(INPUT!H30/INPUT!H9,0.15)-0.03)} -> 0.289708 | E11: {=IFERROR(INDEX(SECTOR_REF!$C$2:$E$61,MATCH(1,(SECTOR_REF!$A$2:$A$61=INPUT!$D$116)*(SECTOR_REF!$B$2:$B$61="EBITDA Margin"),0),MATCH("Realiste",{"Pessimiste","Realiste","Optimiste"},0)),IFERROR(INPUT!H30/INPUT!H9,0.15))} -> 0.319708 | F11: {=IFERROR(INDEX(SECTOR_REF!$C$2:$E$61,MATCH(1,(SECTOR_REF!$A$2:$A$61=INPUT!$D$116)*(SECTOR_REF!$B$2:$B$61="EBITDA Margin"),0),MATCH("Optimiste",{"Pessimiste","Realiste","Optimiste"},0)),IFERROR(INPUT!H30/INPUT!H9,0.15)+0.03)} -> 0.349708
B12: Terminal Growth Rate | C12: (%) | D12: {=IFERROR(INDEX(SECTOR_REF!$C$2:$E$61,MATCH(1,(SECTOR_REF!$A$2:$A$61=INPUT!$D$116)*(SECTOR_REF!$B$2:$B$61="Terminal Growth Rate"),0),MATCH("Pessimiste",{"Pessimiste","Realiste","Optimiste"},0)),DCF!D67-0.01)} -> 0.02 | E12: {=IFERROR(INDEX(SECTOR_REF!$C$2:$E$61,MATCH(1,(SECTOR_REF!$A$2:$A$61=INPUT!$D$116)*(SECTOR_REF!$B$2:$B$61="Terminal Growth Rate"),0),MATCH("Realiste",{"Pessimiste","Realiste","Optimiste"},0)),DCF!D67)} -> 0.03 | F12: {=IFERROR(INDEX(SECTOR_REF!$C$2:$E$61,MATCH(1,(SECTOR_REF!$A$2:$A$61=INPUT!$D$116)*(SECTOR_REF!$B$2:$B$61="Terminal Growth Rate"),0),MATCH("Optimiste",{"Pessimiste","Realiste","Optimiste"},0)),DCF!D67+0.01)} -> 0.04
B13: WACC | C13: (%) | D13: {=IFERROR(INDEX(SECTOR_REF!$C$2:$E$61,MATCH(1,(SECTOR_REF!$A$2:$A$61=INPUT!$D$116)*(SECTOR_REF!$B$2:$B$61="WACC"),0),MATCH("Pessimiste",{"Pessimiste","Realiste","Optimiste"},0)),DCF!D63+0.015)} -> 0.11761386 | E13: {=IFERROR(INDEX(SECTOR_REF!$C$2:$E$61,MATCH(1,(SECTOR_REF!$A$2:$A$61=INPUT!$D$116)*(SECTOR_REF!$B$2:$B$61="WACC"),0),MATCH("Realiste",{"Pessimiste","Realiste","Optimiste"},0)),DCF!D63)} -> 0.10261386 | F13: {=IFERROR(INDEX(SECTOR_REF!$C$2:$E$61,MATCH(1,(SECTOR_REF!$A$2:$A$61=INPUT!$D$116)*(SECTOR_REF!$B$2:$B$61="WACC"),0),MATCH("Optimiste",{"Pessimiste","Realiste","Optimiste"},0)),DCF!D63-0.015)} -> 0.087613857
B14: ▶ Secteur actif : | D14: =IF(INPUT!$D$116="","— Aucun secteur sélectionné (INPUT!D116) —",INPUT!$D$116) -> Technology
B15: SCENARIO RESULTS — DYNAMIC VIEW
B16: METRIC | C16: (Units) | D16: =TEXT(INPUT!D117-3,"0") -> 2022 | E16: =TEXT(INPUT!D117-2,"0") -> 2023 | F16: =TEXT(INPUT!D117-1,"0") -> 2024 | G16: =INPUT!D117&" (LTM)" -> 2025 (LTM) | H16: =TEXT(INPUT!D117+1,"0")&"F" -> 2026F | I16: =TEXT(INPUT!D117+2,"0")&"F" -> 2027F | J16: =TEXT(INPUT!D117+3,"0")&"F" -> 2028F | K16: =TEXT(INPUT!D117+4,"0")&"F" -> 2029F | L16: =TEXT(INPUT!D117+5,"0")&"F" -> 2030F
B17: Revenue | C17: 0 | D17: =INPUT!E9 -> 394328 | E17: =INPUT!F9 -> 383285 | F17: =INPUT!G9 -> 391035 | G17: =INPUT!H9 -> 416161 | H17: =INPUT!H9*(1+IF($D$6="Pessimistic",$D$9,IF($D$6="Realistic",$E$9,$F$9))) -> 442901.47 | I17: =H17*(1+IF($D$6="Pessimistic",$D$9,IF($D$6="Realistic",$E$9,$F$9))) -> 471360.16 | J17: =I17*(1+IF($D$6="Pessimistic",$D$9,IF($D$6="Realistic",$E$9,$F$9))) -> 501647.46 | K17: =J17*(1+IF($D$6="Pessimistic",$D$9,IF($D$6="Realistic",$E$9,$F$9))) -> 533880.88 | L17: =K17*(1+IF($D$6="Pessimistic",$D$9,IF($D$6="Realistic",$E$9,$F$9))) -> 568185.46
B18: Gross Profit | C18: 0 | D18: =INPUT!E11 -> 170782 | E18: =INPUT!F11 -> 169148 | F18: =INPUT!G11 -> 180683 | G18: =INPUT!H11 -> 195201 | H18: =H17*IF($D$6="Pessimistic",$D$10,IF($D$6="Realistic",$E$10,$F$10)) -> 207743.66 | I18: =I17*IF($D$6="Pessimistic",$D$10,IF($D$6="Realistic",$E$10,$F$10)) -> 221092.26 | J18: =J17*IF($D$6="Pessimistic",$D$10,IF($D$6="Realistic",$E$10,$F$10)) -> 235298.57 | K18: =K17*IF($D$6="Pessimistic",$D$10,IF($D$6="Realistic",$E$10,$F$10)) -> 250417.7 | L18: =L17*IF($D$6="Pessimistic",$D$10,IF($D$6="Realistic",$E$10,$F$10)) -> 266508.32
B19: EBITDA | C19: 0 | D19: =INPUT!E30 -> 119437 | E19: =INPUT!F30 -> 114301 | F19: =INPUT!G30 -> 123216 | G19: =INPUT!H30 -> 133050 | H19: =H17*IF($D$6="Pessimistic",$D$11,IF($D$6="Realistic",$E$11,$F$11)) -> 141599.14 | I19: =I17*IF($D$6="Pessimistic",$D$11,IF($D$6="Realistic",$E$11,$F$11)) -> 150697.61 | J19: =J17*IF($D$6="Pessimistic",$D$11,IF($D$6="Realistic",$E$11,$F$11)) -> 160380.71 | K19: =K17*IF($D$6="Pessimistic",$D$11,IF($D$6="Realistic",$E$11,$F$11)) -> 170685.99 | L19: =L17*IF($D$6="Pessimistic",$D$11,IF($D$6="Realistic",$E$11,$F$11)) -> 181653.44
B20: Net Income | C20: 0 | D20: =INPUT!E26 -> 90694 | E20: =INPUT!F26 -> 87496 | F20: =INPUT!G26 -> 84845 | G20: =INPUT!H26 -> 102457 | H20: =H19*0.6 -> 84959.486 | I20: =I19*0.6 -> 90418.568 | J20: =J19*0.6 -> 96228.424 | K20: =K19*0.6 -> 102411.59 | L20: =L19*0.6 -> 108992.06
B21: Free Cash Flow (Est.) | C21: 0 | D21: =IFERROR(INPUT!E75+INPUT!E78,"–") -> 93685 | E21: =IFERROR(INPUT!F75+INPUT!F78,"–") -> 81905 | F21: =IFERROR(INPUT!G75+INPUT!G78,"–") -> 84407 | G21: =IFERROR(INPUT!H75+INPUT!H78,"–") -> 96624 | H21: =H19*0.5 -> 70799.572 | I21: =I19*0.5 -> 75348.807 | J21: =J19*0.5 -> 80190.353 | K21: =K19*0.5 -> 85342.994 | L21: =L19*0.5 -> 90826.718
B22: EBITDA Margin | C22: (%) | D22: =IFERROR(INPUT!E30/INPUT!E9,"–") -> 0.30288744 | E22: =IFERROR(INPUT!F30/INPUT!F9,"–") -> 0.29821412 | F22: =IFERROR(INPUT!G30/INPUT!G9,"–") -> 0.31510223 | G22: =IFERROR(INPUT!H30/INPUT!H9,"–") -> 0.319708 | H22: =IFERROR(H19/H17,"–") -> 0.319708 | I22: =IFERROR(I19/I17,"–") -> 0.319708 | J22: =IFERROR(J19/J17,"–") -> 0.319708 | K22: =IFERROR(K19/K17,"–") -> 0.319708 | L22: =IFERROR(L19/L17,"–") -> 0.319708
B23: Implied Share Price | C23: ($) | M23: =IFERROR("$"&TEXT(IF($D$6="Pessimistic",DCF!D91*(1+$D$9+$D$11-$E$9-$E$11)*0.8,IF($D$6="Realistic",DCF!D91,DCF!D91*(1+$F$9+$F$11-$E$9-$E$11)*1.2)),"#,##0.00"),"–") -> $68,963.99
B25: SCENARIO SUMMARY COMPARISON
B26: METRIC (Year 5) | D26: Pessimistic | E26: Realistic | F26: Optimistic
B27: Revenue (Year 5) | C27: 0 | D27: =INPUT!H9*(1+$D$9)^5 -> 568185.46 | E27: =INPUT!H9*(1+$E$9)^5 -> 568185.46 | F27: =INPUT!H9*(1+$F$9)^5 -> 568185.46
B28: EBITDA (Year 5) | C28: 0 | D28: =D27*$D$11 -> 164607.87 | E28: =E27*$E$11 -> 181653.44 | F28: =F27*$F$11 -> 198699
B29: Net Income (Year 5) | C29: 0 | D29: =D28*0.6 -> 98764.723 | E29: =E28*0.6 -> 108992.06 | F29: =F28*0.6 -> 119219.4
B30: FCF (Year 5) | C30: 0 | D30: =D28*0.5 -> 82303.936 | E30: =E28*0.5 -> 90826.718 | F30: =F28*0.5 -> 99349.5
B31: EBITDA Margin (Year 5) | C31: (%) | D31: =$D$11 -> 0.289708 | E31: =$E$11 -> 0.319708 | F31: =$F$11 -> 0.349708
B32: Implied Share Price | C32: ($) | D32: =IFERROR("$"&TEXT(DCF!D91*(1+$D$9+$D$11-$E$9-$E$11)*0.8,"#,##0.00"),"–") -> $53,516.06 | E32: =IFERROR("$"&TEXT(DCF!D91,"#,##0.00"),"–") -> $68,963.99 | F32: =IFERROR("$"&TEXT(DCF!D91*(1+$F$9+$F$11-$E$9-$E$11)*1.2,"#,##0.00"),"–") -> $85,239.49
B33: Delta (Opt. vs Pess.) | D33: ="—" -> — | E33: ="—" -> — | F33: =IFERROR(F27/D27-1,"–") -> 0
B34: Revenue
B35: ="▶ SCÉNARIO SÉLECTIONNÉ : "&$D$6 -> ▶ SCÉNARIO SÉLECTIONNÉ : Realistic
B37: CHART DATA: Revenue by Scenario
B38: Year | D38: =TEXT(INPUT!D117+1,"0")&"F" -> 2026F | E38: =TEXT(INPUT!D117+2,"0")&"F" -> 2027F | F38: =TEXT(INPUT!D117+3,"0")&"F" -> 2028F | G38: =TEXT(INPUT!D117+4,"0")&"F" -> 2029F | H38: =TEXT(INPUT!D117+5,"0")&"F" -> 2030F
B39: Pessimistic | D39: =IF(INPUT!H9="",NA(),INPUT!H9*(1+$D$9)) -> 442901.47 | E39: =IF(INPUT!H9="",NA(),D39*(1+$D$9)) -> 471360.16 | F39: =IF(INPUT!H9="",NA(),E39*(1+$D$9)) -> 501647.46 | G39: =IF(INPUT!H9="",NA(),F39*(1+$D$9)) -> 533880.88 | H39: =IF(INPUT!H9="",NA(),G39*(1+$D$9)) -> 568185.46
B40: Realistic | D40: =IF(INPUT!H9="",NA(),INPUT!H9*(1+$E$9)) -> 442901.47 | E40: =IF(INPUT!H9="",NA(),D40*(1+$E$9)) -> 471360.16 | F40: =IF(INPUT!H9="",NA(),E40*(1+$E$9)) -> 501647.46 | G40: =IF(INPUT!H9="",NA(),F40*(1+$E$9)) -> 533880.88 | H40: =IF(INPUT!H9="",NA(),G40*(1+$E$9)) -> 568185.46
B41: Optimistic | D41: =IF(INPUT!H9="",NA(),INPUT!H9*(1+$F$9)) -> 442901.47 | E41: =IF(INPUT!H9="",NA(),D41*(1+$F$9)) -> 471360.16 | F41: =IF(INPUT!H9="",NA(),E41*(1+$F$9)) -> 501647.46 | G41: =IF(INPUT!H9="",NA(),F41*(1+$F$9)) -> 533880.88 | H41: =IF(INPUT!H9="",NA(),G41*(1+$F$9)) -> 568185.46
B42: SCENARIO SUMMARY COMPARISON
B43: CHART DATA: EBITDA by Scenario
B44: Year | D44: =TEXT(INPUT!D117+1,"0")&"F" -> 2026F | E44: =TEXT(INPUT!D117+2,"0")&"F" -> 2027F | F44: =TEXT(INPUT!D117+3,"0")&"F" -> 2028F | G44: =TEXT(INPUT!D117+4,"0")&"F" -> 2029F | H44: =TEXT(INPUT!D117+5,"0")&"F" -> 2030F
B45: Pessimistic | D45: =IF(D40=0,0,D40*$D$11) -> 128312.1 | E45: =IF(E40=0,0,E40*$D$11) -> 136556.81 | F45: =IF(F40=0,0,F40*$D$11) -> 145331.28 | G45: =IF(G40=0,0,G40*$D$11) -> 154669.56 | H45: =IF(H40=0,0,H40*$D$11) -> 164607.87
B46: Realistic | D46: =IF(D41=0,0,D41*$E$11) -> 141599.14 | E46: =IF(E41=0,0,E41*$E$11) -> 150697.61 | F46: =IF(F41=0,0,F41*$E$11) -> 160380.71 | G46: =IF(G41=0,0,G41*$E$11) -> 170685.99 | H46: =IF(H41=0,0,H41*$E$11) -> 181653.44
B47: Optimistic | D47: =IF(D41=0,0,D41*$F$11) -> 154886.19 | E47: =IF(E41=0,0,E41*$F$11) -> 164838.42 | F47: =IF(F41=0,0,F41*$F$11) -> 175430.13 | G47: =IF(G41=0,0,G41*$F$11) -> 186702.41 | H47: =IF(H41=0,0,H41*$F$11) -> 198699
B48: EBITDA Margin (Year 5) | E48: =IFERROR(H45/H39,"–") -> 0.289708 | F48: =IFERROR(H46/H40,"–") -> 0.319708 | G48: =IFERROR(H47/H41,"–") -> 0.349708
B49: Implied Share Price | E49: =IFERROR("$"&TEXT(DCF!D91*(1+$D$9+$D$11-$E$9-$E$11)*0.8,"#,##0.00"),"–") -> $53,516.06 | F49: =IFERROR("$"&TEXT(DCF!D91,"#,##0.00"),"–") -> $68,963.99 | G49: =IFERROR("$"&TEXT(DCF!D91*(1+$F$9+$F$11-$E$9-$E$11)*1.2,"#,##0.00"),"–") -> $85,239.49
B51: CHARTS: Revenue & FCF by scenario (insert chart using Scenarios data above D16:I16, D25:I25, D34:I34 for Revenue)
B53: © 2015 to 2024 FinSight
B54: This Excel model is for educational purposes only.
B55: https://finsight.com/
B57: Chart Data: Revenue by Scenario | C57: =INPUT!D117+1 -> 2026 | D57: =INPUT!D117+2 -> 2027 | E57: =INPUT!D117+3 -> 2028 | F57: =INPUT!D117+4 -> 2029 | G57: =INPUT!D117+5 -> 2030
B58: Pessimistic | C58: =IF(INPUT!H9="",NA(),INPUT!H9*(1+$D$9)) -> 442901.47 | D58: =IF(INPUT!H9="",NA(),C58*(1+$D$9)) -> 471360.16 | E58: =IF(INPUT!H9="",NA(),D58*(1+$D$9)) -> 501647.46 | F58: =IF(INPUT!H9="",NA(),E58*(1+$D$9)) -> 533880.88 | G58: =IF(INPUT!H9="",NA(),F58*(1+$D$9)) -> 568185.46
B59: Realistic | C59: =IF(INPUT!H9="",NA(),INPUT!H9*(1+$E$9)) -> 442901.47 | D59: =IF(INPUT!H9="",NA(),C59*(1+$E$9)) -> 471360.16 | E59: =IF(INPUT!H9="",NA(),D59*(1+$E$9)) -> 501647.46 | F59: =IF(INPUT!H9="",NA(),E59*(1+$E$9)) -> 533880.88 | G59: =IF(INPUT!H9="",NA(),F59*(1+$E$9)) -> 568185.46
B60: Optimistic | C60: =IF(INPUT!H9="",NA(),INPUT!H9*(1+$F$9)) -> 442901.47 | D60: =IF(INPUT!H9="",NA(),C60*(1+$F$9)) -> 471360.16 | E60: =IF(INPUT!H9="",NA(),D60*(1+$F$9)) -> 501647.46 | F60: =IF(INPUT!H9="",NA(),E60*(1+$F$9)) -> 533880.88 | G60: =IF(INPUT!H9="",NA(),F60*(1+$F$9)) -> 568185.46
B62: Chart Data: EBITDA by Scenario | C62: =INPUT!D117+1 -> 2026 | D62: =INPUT!D117+2 -> 2027 | E62: =INPUT!D117+3 -> 2028 | F62: =INPUT!D117+4 -> 2029 | G62: =INPUT!D117+5 -> 2030
B63: Pessimistic | C63: =IF(INPUT!H9="",NA(),INPUT!H9*(1+$D$9)*$D$11) -> 128312.1 | D63: =IF(INPUT!H9="",NA(),C58*(1+$D$9)*$D$11) -> 136556.81 | E63: =IF(INPUT!H9="",NA(),D58*(1+$D$9)*$D$11) -> 145331.28 | F63: =IF(INPUT!H9="",NA(),E58*(1+$D$9)*$D$11) -> 154669.56 | G63: =IF(INPUT!H9="",NA(),F58*(1+$D$9)*$D$11) -> 164607.87
B64: Realistic | C64: =IF(INPUT!H9="",NA(),INPUT!H9*(1+$E$9)*$E$11) -> 141599.14 | D64: =IF(INPUT!H9="",NA(),C59*(1+$E$9)*$E$11) -> 150697.61 | E64: =IF(INPUT!H9="",NA(),D59*(1+$E$9)*$E$11) -> 160380.71 | F64: =IF(INPUT!H9="",NA(),E59*(1+$E$9)*$E$11) -> 170685.99 | G64: =IF(INPUT!H9="",NA(),F59*(1+$E$9)*$E$11) -> 181653.44
B65: Optimistic | C65: =IF(INPUT!H9="",NA(),INPUT!H9*(1+$F$9)*$F$11) -> 154886.19 | D65: =IF(INPUT!H9="",NA(),C60*(1+$F$9)*$F$11) -> 164838.42 | E65: =IF(INPUT!H9="",NA(),D60*(1+$F$9)*$F$11) -> 175430.13 | F65: =IF(INPUT!H9="",NA(),E60*(1+$F$9)*$F$11) -> 186702.41 | G65: =IF(INPUT!H9="",NA(),F60*(1+$F$9)*$F$11) -> 198699

Sheet DASHBOARD
B1: FinSight | Q1: Année | R1: 2022 | S1: 2023 | T1: 2024
Q2: Année | R2: Cumul Revenue | S2: =RATIOS!F78 -> 1168648 | T2: =RATIOS!G78 -> 1584809
B3: Financial Performance | Q3: 2022 | R3: =RATIOS!E78 -> 777613
Q4: 2023 | R4: =RATIOS!F78 -> 1168648
M5: ="All figures in "&INPUT!D118&" "&INPUT!D119&" unless stated" -> All figures in USD M unless stated | Q5: 2024 | R5: =RATIOS!G78 -> 1584809
Q7: Year | R7: Revenue | S7: Net Income | T7: Net Margin
B8: Revenue & Profitability | H8: Profit Margins | Q8: 2022 | R8: =RATIOS!E75 -> 394328 | S8: =RATIOS!E77 -> 87496 | T8: =RATIOS!E82 -> 0.22999635
Q9: 2023 | R9: =RATIOS!F75 -> 383285 | S9: =RATIOS!F77 -> 84845 | T9: =RATIOS!F82 -> 0.22827922
Q10: 2024 | R10: =RATIOS!G75 -> 391035 | S10: =RATIOS!G77 -> 84845 | T10: =RATIOS!G82 -> 0.21697546
Q11: 2025 (LTM) | R11: =RATIOS!H75 -> 416161 | S11: =RATIOS!H77 -> 102457 | T11: =RATIOS!H82 -> 0.24619558
B25: Cumulative revenue | H25: Expense Breakdown
B42: Performance Summary (Five-Year) | H42: Income Statement (LTM)
C44: 5-Yr Avg | D44: Trend | I44: Actual | J44: Prev Year | K44: Variance | L44: Var %
B45: Revenue | C45: =AVERAGE(INPUT!D9:H9) -> 396202.25 | H45: Revenue | I45: =INPUT!H9 -> 416161 | J45: =INPUT!G9 -> 391035 | K45: =I45-J45 -> 25126 | L45: =IF(J45=0,NA(),K45/ABS(J45)) -> 0.064255118
B47: COGS | C47: =ABS(AVERAGE(INPUT!D10:H10)) -> 217248.75 | H47: COGS | I47: =ABS(INPUT!H10) -> 220960 | J47: =ABS(INPUT!G10) -> 210352 | K47: =I47-J47 -> 10608 | L47: =IF(J47=0,NA(),K47/ABS(J47)) -> 0.050429756
B49: Expenses | C49: =ABS(AVERAGE(INPUT!D13:H13)) -> 54315.2 | H49: Expenses | I49: =ABS(INPUT!H13) -> 73849 | J49: =ABS(INPUT!G13) -> 68912 | K49: =I49-J49 -> 4937 | L49: =IF(J49=0,NA(),K49/ABS(J49)) -> 0.071642094
B51: Net Income | C51: =AVERAGE(INPUT!D26:H26) -> 73098.4 | H51: Net Income | I51: =INPUT!H26 -> 102457 | J51: =INPUT!G26 -> 84845 | K51: =I51-J51 -> 17612 | L51: =IF(J51=0,NA(),K51/ABS(J51)) -> 0.20757853
B53: Net Margin (%) | C53: =AVERAGE(INPUT!D26:H26)/AVERAGE(INPUT!D9:H9) -> 0.18449769 | H53: Net Margin (%) | I53: =INPUT!H26/INPUT!H9 -> 0.24619558 | J53: =INPUT!G26/INPUT!G9 -> 0.21697546 | K53: =I53-J53 -> 0.02922012 | L53: =IF(J53=0,NA(),K53/ABS(J53)) -> 0.13467016
B58: P&L Summary (LTM) | C58: P&L Summary (LTM) | D58: P&L Summary (LTM) | E58: P&L Summary (LTM) | H58: Balance Sheet Summary (LTM)
B60: Revenue | D60: =INPUT!H9 -> 416161 | E60: =INPUT!H9 -> 416161 | H60: Assets
B61: COGS | D61: =INPUT!H10 -> -220960 | E61: =ABS(INPUT!H10) -> 220960 | H61: Current Assets | J61: =INPUT!H38 -> 96014 | K61: =INPUT!H38 -> 96014
H62: Non-current Assets | J62: =SUM(INPUT!H41:H43) -> 114173 | K62: =SUM(INPUT!H41:H43) -> 114173
B63: Expenses | D63: =ABS(INPUT!H14) -> 27601
B64: SG&A | D64: =ABS(INPUT!H15) -> 34550 | E64: =ABS(INPUT!H15) -> 34550 | H64: Total Assets | J64: =INPUT!H44 -> 210187 | K64: =INPUT!H44 -> 210187
B65: R&D | D65: =ABS(INPUT!H16) -> 11698 | E65: =ABS(INPUT!H16) -> 11698
B66: D&A | D66: =ABS(INPUT!H20) -> 0 | E66: =ABS(INPUT!H20) -> 0 | H66: Liabilities | J66: =INPUT!H51 -> 147657
B67: Interest | D67: =SUM(D64:D66) -> 46248 | E67: =SUM(E64:E66) -> 46248 | H67: Current Liabilities | J67: =INPUT!H54 -> 78328 | K67: =INPUT!H51 -> 147657
B68: Total Expenses | D68: =SUM(D64:D67) -> 92496 | E68: =SUM(E64:E67) -> 92496 | H68: Long-term Liabilities | J68: =INPUT!H60 -> 79304 | K68: =INPUT!H54 -> 78328
H69: Shareholders' Equity | J69: =INPUT!F60 -> 73598 | K69: =INPUT!H60 -> 79304
D70: =D60+D61-D68 -> 102705 | J70: =INPUT!H63 -> 305289
B71: Net Operating Profit | D71: =D60+D61-D68 -> 102705 | E71: =E60-E61-E68 -> 102705 | H71: Liabilities & Shareholders' Equity | J71: =INPUT!F63 -> 306126 | K71: =INPUT!H63 -> 305289
C81: =IF(INPUT!D5="",NA(),INPUT!D5) -> #N/A | D81: =INPUT!E5 -> 2022 | E81: =INPUT!F5 -> 2023 | F81: =INPUT!G5 -> 2024 | G81: =INPUT!H5 -> 2025 (LTM) | I81: =IF(INPUT!D5="",NA(),INPUT!D5) -> #N/A | J81: =INPUT!E5 -> 2022 | K81: =INPUT!F5 -> 2023 | L81: =INPUT!G5 -> 2024 | M81: =INPUT!H5 -> 2025 (LTM)
B82: Revenue | C82: =IF(INPUT!D9="",NA(),INPUT!D9) -> #N/A | D82: =IF(INPUT!E9="",NA(),INPUT!E9) -> 394328 | E82: =IF(INPUT!F9="",NA(),INPUT!F9) -> 383285 | F82: =IF(INPUT!G9="",NA(),INPUT!G9) -> 391035 | G82: =IF(INPUT!H9="",NA(),INPUT!H9) -> 416161
C83: EBITDA | D83: =IF(INPUT!D30="",NA(),INPUT!D30) -> 0 | E83: =IF(INPUT!E30="",NA(),INPUT!E30) -> 119437 | F83: =IF(INPUT!F30="",NA(),INPUT!F30) -> 114301 | G83: =IF(INPUT!G30="",NA(),INPUT!G30) -> 123216 | H83: =IF(INPUT!H30="",NA(),INPUT!H30) -> 133050
C84: Net Income | D84: =IF(INPUT!D26="",NA(),INPUT!D26) -> 0 | E84: =IF(INPUT!E26="",NA(),INPUT!E26) -> 90694 | F84: =IF(INPUT!F26="",NA(),INPUT!F26) -> 87496 | G84: =IF(INPUT!G26="",NA(),INPUT!G26) -> 84845 | H84: =IF(INPUT!H26="",NA(),INPUT!H26) -> 102457
J85: =IF(INPUT!D5="",NA(),INPUT!D5) -> #N/A | K85: =INPUT!E5 -> 2022 | L85: =INPUT!F5 -> 2023 | M85: =INPUT!G5 -> 2024 | N85: =INPUT!H5 -> 2025 (LTM)
I86: Gross Margin | J86: =IF(INPUT!D9="",NA(),INPUT!D11/INPUT!D9) -> #N/A | K86: =IF(INPUT!E9="",NA(),INPUT!E11/INPUT!E9) -> 0.43309631 | L86: =IF(INPUT!F9="",NA(),INPUT!F11/INPUT!F9) -> 0.4413113 | M86: =IF(INPUT!G9="",NA(),INPUT!G11/INPUT!G9) -> 0.4620635 | N86: =IF(INPUT!H9="",NA(),INPUT!H11/INPUT!H9) -> 0.46905164
I87: EBITDA Margin | J87: =IF(INPUT!D9="",NA(),INPUT!D30/INPUT!D9) -> #N/A | K87: =IF(INPUT!E9="",NA(),INPUT!E30/INPUT!E9) -> 0.30288744 | L87: =IF(INPUT!F9="",NA(),INPUT!F30/INPUT!F9) -> 0.29821412 | M87: =IF(INPUT!G9="",NA(),INPUT!G30/INPUT!G9) -> 0.31510223 | N87: =IF(INPUT!H9="",NA(),INPUT!H30/INPUT!H9) -> 0.319708
D88: =IF(INPUT!D5="",NA(),INPUT!D5) -> #N/A | E88: =INPUT!E5 -> 2022 | F88: =INPUT!F5 -> 2023 | G88: =INPUT!G5 -> 2024 | H88: =INPUT!H5 -> 2025 (LTM) | I88: Net Margin | J88: =IF(INPUT!D9="",NA(),INPUT!D26/INPUT!D9) -> #N/A | K88: =IF(INPUT!E9="",NA(),INPUT!E26/INPUT!E9) -> 0.22999635 | L88: =IF(INPUT!F9="",NA(),INPUT!F26/INPUT!F9) -> 0.22827922 | M88: =IF(INPUT!G9="",NA(),INPUT!G26/INPUT!G9) -> 0.21697546 | N88: =IF(INPUT!H9="",NA(),INPUT!H26/INPUT!H9) -> 0.24619558
C89: Revenue | D89: =IF(INPUT!D9="",NA(),INPUT!D9) -> #N/A | E89: =IF(INPUT!E9="",NA(),INPUT!E9) -> 394328 | F89: =IF(INPUT!F9="",NA(),INPUT!F9) -> 383285 | G89: =IF(INPUT!G9="",NA(),INPUT!G9) -> 391035 | H89: =IF(INPUT!H9="",NA(),INPUT!H9) -> 416161
J90: =IF(INPUT!D5="",NA(),INPUT!D5) -> #N/A | K90: =INPUT!E5 -> 2022 | L90: =INPUT!F5 -> 2023 | M90: =INPUT!G5 -> 2024 | N90: =INPUT!H5 -> 2025 (LTM)
I91: SG&A | J91: =IF(INPUT!D14="",NA(),ABS(INPUT!D14)) -> #N/A | K91: =IF(INPUT!E14="",NA(),ABS(INPUT!E14)) -> 25094 | L91: =IF(INPUT!F14="",NA(),ABS(INPUT!F14)) -> 24932 | M91: =IF(INPUT!G14="",NA(),ABS(INPUT!G14)) -> 26097 | N91: =IF(INPUT!H14="",NA(),ABS(INPUT!H14)) -> 27601
I92: R&D | J92: =IF(INPUT!D15="",NA(),ABS(INPUT!D15)) -> #N/A | K92: =IF(INPUT!E15="",NA(),ABS(INPUT!E15)) -> 26251 | L92: =IF(INPUT!F15="",NA(),ABS(INPUT!F15)) -> 29915 | M92: =IF(INPUT!G15="",NA(),ABS(INPUT!G15)) -> 31370 | N92: =IF(INPUT!H15="",NA(),ABS(INPUT!H15)) -> 34550
I93: D&A | J93: =IF(INPUT!D16="",NA(),ABS(INPUT!D16)) -> #N/A | K93: =IF(INPUT!E16="",NA(),ABS(INPUT!E16)) -> 11104 | L93: =IF(INPUT!F16="",NA(),ABS(INPUT!F16)) -> 11519 | M93: =IF(INPUT!G16="",NA(),ABS(INPUT!G16)) -> 11445 | N93: =IF(INPUT!H16="",NA(),ABS(INPUT!H16)) -> 11698
I94: Interest | J94: =IF(INPUT!D5="",NA(),INPUT!D5) -> #N/A | K94: =IF(INPUT!E14="",NA(),ABS(INPUT!E20)) -> 2931 | L94: =IF(INPUT!F14="",NA(),ABS(INPUT!F20)) -> 3933 | M94: =IF(INPUT!G14="",NA(),ABS(INPUT!G20)) -> 0 | N94: =IF(INPUT!H14="",NA(),ABS(INPUT!H20)) -> 0

Sheet DASHBOARD 2
B1: FinSight | R1: =INPUT!D114&" ("&INPUT!D115&") — "&INPUT!D116 -> Apple Inc. (AAPL) — Technology
B3: Projected Business Performance | Q3: Football Field Chart — Valuation Inputs
B5: All figures in USD Thousands unless stated | T5: Low ($) | U5: Delta ($) | V5: High ($)
B6: Company Information | Q6: 52-Week Trading Range | T6: =INPUT!H95*0.75 -> 195.975 | U6: =V6-T6 -> 182.91 | V6: =INPUT!H95*1.45 -> 378.885
C7: Company Name | D7: =INPUT!D114 -> Apple Inc. | Q7: Consensus Research | T7: =INPUT!H95*1.1 -> 287.43 | U7: =V7-T7 -> 130.65 | V7: =INPUT!H95*1.6 -> 418.08
C8: Ticker Symbol | D8: =INPUT!D115 -> AAPL | Q8: Precedent Transactions | T8: =INPUT!H95*1.2 -> 313.56 | U8: =V8-T8 -> 143.715 | V8: =INPUT!H95*1.75 -> 457.275
C9: Sector | D9: =INPUT!D116 -> Technology | Q9: Sum-of-the-Parts | T9: =INPUT!H95*1.3 -> 339.69 | U9: =V9-T9 -> 143.715 | V9: =INPUT!H95*1.85 -> 483.405
C10: Base Year (LTM) | D10: =INPUT!D117 -> 2025 | Q10: Discounted Cash Flow | T10: =INPUT!H95*1.15 -> 300.495 | U10: =V10-T10 -> 143.715 | V10: =INPUT!H95*1.7 -> 444.21
C11: Currency | D11: =INPUT!D118 -> USD | Q11: Current Share Price | T11: =INPUT!H95 -> 261.3
C12: Analysis Date | D12: =INPUT!D120 -> 2026-04-10
Q15: Financial Data — Multi-Year
Q17: All figures in USD Thousands unless stated | T17: =INPUT!E5 -> 2022 | U17: =INPUT!E5 -> 2022 | V17: =INPUT!F5 -> 2023 | W17: =INPUT!G5 -> 2024 | X17: =INPUT!H5 -> 2025 (LTM)
B19: Stock Chart: Trailing 52-Weeks | I19: Valuation Summary: Football Field Chart | Q19: Revenue Growth (%) | T19: ="" | U19: =IF(INPUT!D9=0,"",INPUT!E9/INPUT!D9-1) | V19: =IF(INPUT!E9=0,"",INPUT!F9/INPUT!E9-1) -> -0.028004605 | W19: =IF(INPUT!F9=0,"",INPUT!G9/INPUT!F9-1) -> 0.020219941 | X19: =IF(INPUT!G9=0,"",INPUT!H9/INPUT!G9-1) -> 0.064255118
Q20: EBITDA Growth (%) | T20: ="" | U20: ="" | V20: =IF(INPUT!D30=0,"",INPUT!F30/INPUT!E30-1) | W20: =IF(INPUT!E30=0,"",INPUT!G30/INPUT!F30-1) -> 0.077995818 | X20: =IF(INPUT!F30=0,"",INPUT!H30/INPUT!G30-1) -> 0.079811063
Q22: Revenue
Q23: Revenue — Products | T23: =INPUT!E9 -> 394328 | U23: =INPUT!E9 -> 394328 | V23: =INPUT!F9 -> 383285 | W23: =INPUT!G9 -> 391035 | X23: =INPUT!H9 -> 416161
Q24: Cost of Revenue (COGS) | T24: =ABS(INPUT!E10) -> 223546 | U24: =ABS(INPUT!E10) -> 223546 | V24: =ABS(INPUT!F10) -> 214137 | W24: =ABS(INPUT!G10) -> 210352 | X24: =ABS(INPUT!H10) -> 220960
Q25: Gross Profit | T25: =INPUT!E11 -> 170782 | U25: =INPUT!E11 -> 170782 | V25: =INPUT!F11 -> 169148 | W25: =INPUT!G11 -> 180683 | X25: =INPUT!H11 -> 195201
Q26: SG&A | T26: =ABS(INPUT!E14) -> 25094 | U26: =ABS(INPUT!E14) -> 25094 | V26: =ABS(INPUT!F14) -> 24932 | W26: =ABS(INPUT!G14) -> 26097 | X26: =ABS(INPUT!H14) -> 27601
Q27: Total Revenue | T27: =INPUT!E9 -> 394328 | U27: =INPUT!E9 -> 394328 | V27: =INPUT!F9 -> 383285 | W27: =INPUT!G9 -> 391035 | X27: =INPUT!H9 -> 416161
Q29: EBITDA | T29: =INPUT!E30 -> 119437 | U29: =INPUT!E30 -> 119437 | V29: =INPUT!F30 -> 114301 | W29: =INPUT!G30 -> 123216 | X29: =INPUT!H30 -> 133050
Q30: Cash from Ops (CFO) | T30: =INPUT!E75 -> 104393 | U30: =INPUT!E75 -> 104393 | V30: =INPUT!F75 -> 92864 | W30: =INPUT!G75 -> 93854 | X30: =INPUT!H75 -> 109339
Q31: Net Income | T31: =INPUT!E26 -> 90694 | U31: =INPUT!E26 -> 90694 | V31: =INPUT!F26 -> 87496 | W31: =INPUT!G26 -> 84845 | X31: =INPUT!H26 -> 102457
R34: ly
B39: Total Revenue ($M) | I39: Other Financial Metrics ($ Millier)
V84: Low | W84: Delta | X84: High
S85: 52-Week Trading Range | V85: =T6 -> 195.975 | W85: =U6 -> 182.91 | X85: =V6 -> 378.885
S86: Consensus Research | V86: =T7 -> 287.43 | W86: =U7 -> 130.65 | X86: =V7 -> 418.08
S87: Precedent Trans. | V87: =T8 -> 313.56 | W87: =U8 -> 143.715 | X87: =V8 -> 457.275
S88: Sum-of-the-Parts | V88: =T9 -> 339.69 | W88: =U9 -> 143.715 | X88: =V9 -> 483.405
S89: Discounted Cash Flow | V89: =T10 -> 300.495 | W89: =U10 -> 143.715 | X89: =V10 -> 444.21
Q92: =K103 -> 2022 | R92: =L103 -> 2023 | S92: =M103 -> 2024 | T92: =N103 -> 2025 (LTM)
Q93: =IF(INPUT!E9="",NA(),INPUT!E30/1000) -> 119.437 | R93: =IF(INPUT!F9="",NA(),INPUT!F30/1000) -> 114.301 | S93: =IF(INPUT!G9="",NA(),INPUT!G30/1000) -> 123.216 | T93: =IF(INPUT!H9="",NA(),INPUT!H30/1000) -> 133.05
Q94: =IF(INPUT!E9="",NA(),INPUT!E75/1000) -> 104.393 | R94: =IF(INPUT!F9="",NA(),INPUT!F75/1000) -> 92.864 | S94: =IF(INPUT!G9="",NA(),INPUT!G75/1000) -> 93.854 | T94: =IF(INPUT!H9="",NA(),INPUT!H75/1000) -> 109.339
Q95: =IF(INPUT!E9="",NA(),INPUT!E26/1000) -> 90.694 | S95: 2022 | T95: 2023 | U95: 2024 | V95: 2025 (LTM)
R96: EBITDA | S96: =U29 -> 119437 | T96: =V29 -> 114301 | U96: =W29 -> 123216 | V96: =X29 -> 133050
R97: CFO | S97: =U30 -> 104393 | T97: =V30 -> 92864 | U97: =W30 -> 93854 | V97: =X30 -> 109339
R98: Net Income | S98: =U31 -> 90694 | T98: =V31 -> 87496 | U98: =W31 -> 84845 | V98: =X31 -> 102457
B103: Year | C103: =IF(INPUT!D9="","",INPUT!D5) | D103: =IF(INPUT!E9="",NA(),'DASHBOARD 2'!U17) -> 2022 | E103: =IF(INPUT!F9="",NA(),'DASHBOARD 2'!V17) -> 2023 | F103: =IF(INPUT!G9="",NA(),'DASHBOARD 2'!W17) -> 2024 | G103: =IF(INPUT!H9="",NA(),'DASHBOARD 2'!X17) -> 2025 (LTM) | I103: Year | J103: =IF(INPUT!D9="","",INPUT!D5) | K103: =IF(INPUT!E9="",NA(),'DASHBOARD 2'!U17) -> 2022 | L103: =IF(INPUT!F9="",NA(),'DASHBOARD 2'!V17) -> 2023 | M103: =IF(INPUT!G9="",NA(),'DASHBOARD 2'!W17) -> 2024 | N103: =IF(INPUT!H9="",NA(),'DASHBOARD 2'!X17) -> 2025 (LTM) | P103: =J103
B104: Revenue Growth (%) | C104: ="" | D104: =IF(INPUT!E9="",NA(),'DASHBOARD 2'!U19) | E104: =IF(INPUT!F9="",NA(),'DASHBOARD 2'!V19) -> -0.028004605 | F104: =IF(INPUT!G9="",NA(),'DASHBOARD 2'!W19) -> 0.020219941 | G104: =IF(INPUT!H9="",NA(),'DASHBOARD 2'!X19) -> 0.064255118 | I104: EBITDA ($M) | J104: =IF(INPUT!D9="","",INPUT!D30) | K104: =IF(INPUT!E9="",NA(),INPUT!E30) -> 119437 | L104: =IF(INPUT!F9="",NA(),INPUT!F30) -> 114301 | M104: =IF(INPUT!G9="",NA(),INPUT!G30) -> 123216 | N104: =IF(INPUT!H9="",NA(),INPUT!H30) -> 133050 | P104: =IF(INPUT!D9="",NA(),INPUT!D30/1000) -> #N/A
B105: Total Revenue ($M) | C105: =IF(INPUT!D9="","",INPUT!D9) | D105: =IF(INPUT!E9="",NA(),INPUT!E9) -> 394328 | E105: =IF(INPUT!F9="",NA(),INPUT!F9) -> 383285 | F105: =IF(INPUT!G9="",NA(),INPUT!G9) -> 391035 | G105: =IF(INPUT!H9="",NA(),INPUT!H9) -> 416161 | I105: CFO ($M) | J105: =IF(INPUT!D9="","",INPUT!D75) | K105: =IF(INPUT!E9="",NA(),INPUT!E75) -> 104393 | L105: =IF(INPUT!F9="",NA(),INPUT!F75) -> 92864 | M105: =IF(INPUT!G9="",NA(),INPUT!G75) -> 93854 | N105: =IF(INPUT!H9="",NA(),INPUT!H75) -> 109339 | P105: =IF(INPUT!D9="",NA(),INPUT!D75/1000) -> #N/A
A106: Revenue | I106: Net Income ($M) | J106: =IF(INPUT!D9="","",INPUT!D26) | K106: =IF(INPUT!E9="",NA(),INPUT!E26) -> 90694 | L106: =IF(INPUT!F9="",NA(),INPUT!F26) -> 87496 | M106: =IF(INPUT!G9="",NA(),INPUT!G26) -> 84845 | N106: =IF(INPUT!H9="",NA(),INPUT!H26) -> 102457 | P106: =IF(INPUT!D9="",NA(),INPUT!D26/1000) -> #N/A

Sheet STOCK_DATA
A1: STOCK_DATA — Apple Inc. (AAPL) — Trailing 52 Weeks
A2: # | B2: Month | C2: Close Price ($)
A3: 1 | B3: May-25 | C3: 199.98
A4: 2 | B4: Jun-25 | C4: 204.55
A5: 3 | B5: Jul-25 | C5: 206.94
A6: 4 | B6: Aug-25 | C6: 231.44
A7: 5 | B7: Sep-25 | C7: 254.15
A8: 6 | B8: Oct-25 | C8: 269.86
A9: 7 | B9: Nov-25 | C9: 278.32
A10: 8 | B10: Dec-25 | C10: 271.61
A11: 9 | B11: Jan-26 | C11: 259.24
A12: 10 | B12: Feb-26 | C12: 263.93
A13: 11 | B13: Mar-26 | C13: 253.79
A14: 12 | B14: Apr-26 | C14: 261.31
A15: 13
A17: ⚠️ Données simulées. Remplacer par données réelles (Bloomberg/FactSet) en colonne B (Mois) et C (Prix).

Sheet SECTOR_REF
A1: Secteur | B1: Driver | C1: Pessimiste | D1: Realiste | E1: Optimiste
A2: Technologie / SaaS | B2: Revenue Growth Rate (Y1-Y5) | C2: 0.05 | D2: 0.12 | E2: 0.22
A3: Technologie / SaaS | B3: Gross Margin | C3: 0.55 | D3: 0.68 | E3: 0.78
A4: Technologie / SaaS | B4: EBITDA Margin | C4: 0.08 | D4: 0.18 | E4: 0.28
A5: Technologie / SaaS | B5: SG&A (% Revenue) | C5: 0.3 | D5: 0.22 | E5: 0.15
A6: Technologie / SaaS | B6: R&D (% Revenue) | C6: 0.18 | D6: 0.12 | E6: 0.08
A7: Technologie / SaaS | B7: CapEx (% Revenue) | C7: 0.08 | D7: 0.05 | E7: 0.03
A8: Technologie / SaaS | B8: Change in NWC (% Rev Change) | C8: 0.05 | D8: 0.03 | E8: 0.02
A9: Technologie / SaaS | B9: Terminal Growth Rate | C9: 0.02 | D9: 0.03 | E9: 0.04
A10: Technologie / SaaS | B10: WACC | C10: 0.11 | D10: 0.09 | E10: 0.07
A11: Technologie / SaaS | B11: EV/EBITDA Exit Multiple | C11: 12 | D11: 16 | E11: 22
A12: Industrie / Manufacturing | B12: Revenue Growth Rate (Y1-Y5) | C12: 0.01 | D12: 0.04 | E12: 0.07
A13: Industrie / Manufacturing | B13: Gross Margin | C13: 0.18 | D13: 0.25 | E13: 0.32
... A61: Sante / Pharma | B61: EV/EBITDA Exit Multiple | C61: 8 | D61: 12 | E61: 18

Sheet LBO MODEL
B1: FinSight
B3: MODÈLE LBO
B4: Modèle institutionnel mid-market · calculs sur 5 ans · toutes hypothèses paramétrables (cellules jaunes)
B6: A. PROFIL & ÉLIGIBILITÉ
B7: Société | C7: =IFERROR(TRIM(MID(STOCK_DATA!A1,14,FIND("(",STOCK_DATA!A1)-15)),"") -> Apple Inc. | G7: Enterprise Value LTM | H7: =INPUT!H98 -> 3898904.9
B8: Ticker | C8: =IFERROR(MID(STOCK_DATA!A1,SEARCH("(",STOCK_DATA!A1)+1,SEARCH(")",STOCK_DATA!A1)-SEARCH("(",STOCK_DATA!A1)-1),"") -> AAPL | G8: EBITDA LTM | H8: =INPUT!H30 -> 133050
B9: Revenue LTM | C9: =INPUT!H9 -> 416161 | G9: Net Debt / EBITDA | H9: =IFERROR((INPUT!H54+INPUT!H48-INPUT!H34)/INPUT!H30,0) -> 0.47142428
B10: Marge EBITDA | C10: =IFERROR(INPUT!H30/INPUT!H9,0) -> 0.319708 | G10: Cash Conversion (FCF/EBITDA) | H10: =IFERROR(DCF!H49/INPUT!H30,0) -> 0.81481769
B12: =IF(AND(INPUT!H30>0,IFERROR(INPUT!H30/INPUT!H9,0)>0.15,IFERROR(DCF!H49/INPUT!H30,0)>0.6,IFERROR((INPUT!H54+INPUT!H48-INPUT!H34)/INPUT!H30,99)<3.5)," ✓ PROFIL LBO-ABLE — Société éligible aux critères d'un LBO mid-market standard"," ✗ PROFIL NON ÉLIGIBLE — Voir critères ci-dessous pour les freins identifiés") -> ✓ PROFIL LBO-ABLE — Société éligible aux critères d'un LBO mid-market standard
B13: =IF(IFERROR(INPUT!H30/INPUT!H9,0)>0.15,"✓ Marge EBITDA > 15%","✗ Marge EBITDA < 15%") -> ✓ Marge EBITDA > 15% | E13: =IF(IFERROR(DCF!H49/INPUT!H30,0)>0.6,"✓ Cash conv > 60%","✗ Cash conv < 60%") -> ✓ Cash conv > 60% | H13: =IF(IFERROR((INPUT!H54+INPUT!H48-INPUT!H34)/INPUT!H30,99)<3.5,"✓ Levier < 3,5x","✗ Levier > 3,5x") -> ✓ Levier < 3,5x | K13: =IF(INPUT!H30>0,"✓ EBITDA positif","✗ EBITDA négatif") -> ✓ EBITDA positif
B14: =IF(INPUT!H98>100000000," ⚠⚠ SCÉNARIO THÉORIQUE — EV > 100 Md$, taille hors marché LBO historique",IF(INPUT!H98>50000000," ⚠ MEGA-DEAL — EV entre 50 et 100 Md$, syndicate sponsorship requis (type Twitter/X, Heinz)",""))
B16: B. HYPOTHÈSES (cellules jaunes paramétrables)
B17: Multiple d'entrée (× EBITDA LTM) | C17: 14 | F17: EV / EBITDA actuel marché | L17: =IFERROR(INPUT!H98/INPUT!H30,0) -> 29.304058
B18: Premium implicite vs Market Cap (calculé) | C18: =IFERROR((L28-INPUT!H97)/INPUT!H97,0) -> -0.51443908 | F18: EV / EBITDA peers (méd. COMPARABLES) | L18: =IFERROR(MEDIAN(COMPARABLES!H4:H20),0) -> 15.634558
B19: Leverage total au closing (× EBITDA) | C19: 5 | F19: Différence vs multiple d'entrée saisi | L19: =IFERROR(C17-L17,0) -> -15.304058
B20: · dont Senior Term Loan B | C20: 3.5
B21: · dont Mezzanine | C21: 1.5 | F21: Recommandation multiple d'entrée | L21: =IFERROR(ROUND(MAX(C17,L17*1.1),1),C17) -> 32.2
B22: Coût Senior TLB (SOFR + 400 bps) | C22: 0.08 | F22: Note : pour un LBO réaliste, le multiple d'entrée doit être >= multiple actuel + 10% (premium d'acquisition).
B23: Coût Mezzanine (cash 5% + PIK 5%) | C23: 0.1
B24: Multiple de sortie (× EBITDA Y5) | C24: 14
B25: Période de détention (années) | C25: 5
B26: Transaction fees (% EV deal) | C26: 0.025
B27: Cash minimum BS (% EV) | C27: 0.05
K28: EV_deal: | L28: =C17*INPUT!H30 -> 1862700
B29: C. SOURCES & USES
B30: SOURCES (financement) | G30: USES (utilisation)
B31: Sponsor Equity | D31: =L35-D32-D33 -> 1373086.5 | E31: =IFERROR(D31/L35,0) -> 0.67363092 | G31: Purchase price equity | L31: =L28-(INPUT!H54+INPUT!H48-INPUT!H34) -> 1799977
B32: Senior Term Loan B | D32: =C20*INPUT!H30 -> 465675 | E32: =IFERROR(D32/L35,0) -> 0.22845835 | G32: Refinancement dette existante | L32: =INPUT!H54+INPUT!H48 -> 98657
B33: Mezzanine | D33: =C21*INPUT!H30 -> 199575 | E33: =IFERROR(D33/L35,0) -> 0.097910723 | G33: Transaction fees | L33: =L28*C26 -> 46567.5
G34: Cash minimum sur BS | L34: =L28*C27 -> 93135
B35: TOTAL SOURCES | D35: =SUM(D31:D33) -> 2038336.5 | E35: =IFERROR(D35/L35,0) -> 1 | G35: TOTAL USES | L35: =SUM(L31:L34) -> 2038336.5
B37: D. RETURNS BASE CASE — Sortie Y5
B38: Equity entry sponsor | C38: =D31 -> 1373086.5
B39: Equity exit (Y5) | C39: =_LBO_CALC!N50 -> 1803980
B41: IRR Sponsor | G41: MOIC
B42: =_LBO_CALC!N51 -> 0.056104182 | G42: =_LBO_CALC!N52 -> 1.3138138
B44: Money-back period | C44: =IF(_LBO_CALC!N51<=0,"N/A",IF(LN(2)/LN(1+_LBO_CALC!N51)>C25*2,">"&TEXT(C25*2,"0")&" ans",ROUND(LN(2)/LN(1+_LBO_CALC!N51),1)&" ans")) -> >10 ans
B46: E. SENSIBILITÉ IRR — Multiple d'entrée × Multiple de sortie
B47: ↓ Mult. entrée / Mult. sortie → | E47: =C24+(-2) -> 12 | F47: =C24+(-1) -> 13 | G47: =C24+(0) -> 14 | H47: =C24+(1) -> 15 | I47: =C24+(2) -> 16
B48: =C17+(-2) -> 12 | E48: =IFERROR(((_LBO_CALC!$M$7*(C24+(-2))-_LBO_CALC!$M$30)/MAX(1,(INPUT!H30*(C17+(-2))*1.075-C19*INPUT!H30)))^(1/C25)-1,0) -> 0.076802784 | F48: =IFERROR(((_LBO_CALC!$M$7*(C24+(-1))-_LBO_CALC!$M$30)/MAX(1,(INPUT!H30*(C17+(-2))*1.075-C19*INPUT!H30)))^(1/C25)-1,0) -> 0.096077161 | G48: =IFERROR(((_LBO_CALC!$M$7*(C24+(0))-_LBO_CALC!$M$30)/MAX(1,(INPUT!H30*(C17+(-2))*1.075-C19*INPUT!H30)))^(1/C25)-1,0) -> 0.11408403 | H48: =IFERROR(((_LBO_CALC!$M$7*(C24+(1))-_LBO_CALC!$M$30)/MAX(1,(INPUT!H30*(C17+(-2))*1.075-C19*INPUT!H30)))^(1/C25)-1,0) -> 0.13099678 | I48: =IFERROR(((_LBO_CALC!$M$7*(C24+(2))-_LBO_CALC!$M$30)/MAX(1,(INPUT!H30*(C17+(-2))*1.075-C19*INPUT!H30)))^(1/C25)-1,0) -> 0.14695452
B49: =C17+(-1) -> 13 | E49: =IFERROR(((_LBO_CALC!$M$7*(C24+(-2))-_LBO_CALC!$M$30)/MAX(1,(INPUT!H30*(C17+(-1))*1.075-C19*INPUT!H30)))^(1/C25)-1,0) -> 0.04967462 | F49: =IFERROR(((_LBO_CALC!$M$7*(C24+(-1))-_LBO_CALC!$M$30)/MAX(1,(INPUT!H30*(C17+(-1))*1.075-C19*INPUT!H30)))^(1/C25)-1,0) -> 0.068463412 | G49: =IFERROR(((_LBO_CALC!$M$7*(C24+(0))-_LBO_CALC!$M$30)/MAX(1,(INPUT!H30*(C17+(-1))*1.075-C19*INPUT!H30)))^(1/C25)-1,0) -> 0.086016628 | H49: =IFERROR(((_LBO_CALC!$M$7*(C24+(1))-_LBO_CALC!$M$30)/MAX(1,(INPUT!H30*(C17+(-1))*1.075-C19*INPUT!H30)))^(1/C25)-1,0) -> 0.1025033 | I49: =IFERROR(((_LBO_CALC!$M$7*(C24+(2))-_LBO_CALC!$M$30)/MAX(1,(INPUT!H30*(C17+(-1))*1.075-C19*INPUT!H30)))^(1/C25)-1,0) -> 0.118059
B50: =C17+(0) -> 14 | E50: =IFERROR(((_LBO_CALC!$M$7*(C24+(-2))-_LBO_CALC!$M$30)/MAX(1,(INPUT!H30*(C17+(0))*1.075-C19*INPUT!H30)))^(1/C25)-1,0) -> 0.026191412 | F50: =IFERROR(((_LBO_CALC!$M$7*(C24+(-1))-_LBO_CALC!$M$30)/MAX(1,(INPUT!H30*(C17+(0))*1.075-C19*INPUT!H30)))^(1/C25)-1,0) -> 0.044559863 | G50: =IFERROR(((_LBO_CALC!$M$7*(C24+(0))-_LBO_CALC!$M$30)/MAX(1,(INPUT!H30*(C17+(0))*1.075-C19*INPUT!H30)))^(1/C25)-1,0) -> 0.06172038 | H50: =IFERROR(((_LBO_CALC!$M$7*(C24+(1))-_LBO_CALC!$M$30)/MAX(1,(INPUT!H30*(C17+(0))*1.075-C19*INPUT!H30)))^(1/C25)-1,0) -> 0.077838212 | I50: =IFERROR(((_LBO_CALC!$M$7*(C24+(2))-_LBO_CALC!$M$30)/MAX(1,(INPUT!H30*(C17+(0))*1.075-C19*INPUT!H30)))^(1/C25)-1,0) -> 0.093045908
B51: =C17+(1) -> 15 | E51: =IFERROR(((_LBO_CALC!$M$7*(C24+(-2))-_LBO_CALC!$M$30)/MAX(1,(INPUT!H30*(C17+(1))*1.075-C19*INPUT!H30)))^(1/C25)-1,0) -> 0.0055451694 | F51: =IFERROR(((_LBO_CALC!$M$7*(C24+(-1))-_LBO_CALC!$M$30)/MAX(1,(INPUT!H30*(C17+(1))*1.075-C19*INPUT!H30)))^(1/C25)-1,0) -> 0.023544061 | G51: =IFERROR(((_LBO_CALC!$M$7*(C24+(0))-_LBO_CALC!$M$30)/MAX(1,(INPUT!H30*(C17+(1))*1.075-C19*INPUT!H30)))^(1/C25)-1,0) -> 0.04035932 | H51: =IFERROR(((_LBO_CALC!$M$7*(C24+(1))-_LBO_CALC!$M$30)/MAX(1,(INPUT!H30*(C17+(1))*1.075-C19*INPUT!H30)))^(1/C25)-1,0) -> 0.056152873 | I51: =IFERROR(((_LBO_CALC!$M$7*(C24+(2))-_LBO_CALC!$M$30)/MAX(1,(INPUT!H30*(C17+(1))*1.075-C19*INPUT!H30)))^(1/C25)-1,0) -> 0.071054601
B52: =C17+(2) -> 16 | E52: =IFERROR(((_LBO_CALC!$M$7*(C24+(-2))-_LBO_CALC!$M$30)/MAX(1,(INPUT!H30*(C17+(2))*1.075-C19*INPUT!H30)))^(1/C25)-1,0) -> -0.012835289 | F52: =IFERROR(((_LBO_CALC!$M$7*(C24+(-1))-_LBO_CALC!$M$30)/MAX(1,(INPUT!H30*(C17+(2))*1.075-C19*INPUT!H30)))^(1/C25)-1,0) -> 0.0048345987 | G52: =IFERROR(((_LBO_CALC!$M$7*(C24+(0))-_LBO_CALC!$M$30)/MAX(1,(INPUT!H30*(C17+(2))*1.075-C19*INPUT!H30)))^(1/C25)-1,0) -> 0.021342491 | H52: =IFERROR(((_LBO_CALC!$M$7*(C24+(1))-_LBO_CALC!$M$30)/MAX(1,(INPUT!H30*(C17+(2))*1.075-C19*INPUT!H30)))^(1/C25)-1,0) -> 0.036847351 | I52: =IFERROR(((_LBO_CALC!$M$7*(C24+(2))-_LBO_CALC!$M$30)/MAX(1,(INPUT!H30*(C17+(2))*1.075-C19*INPUT!H30)))^(1/C25)-1,0) -> 0.051476689
B54: F. SCÉNARIOS — Bull / Base / Bear
B55: Métrique | E55: BULL | G55: BASE | I55: BEAR
B56: IRR Sponsor | E56: =_LBO_CALC!P55 -> 0.11006039 | G56: =_LBO_CALC!P56 -> 0.056104182 | I56: =_LBO_CALC!P57 -> -0.0054694105
B57: MOIC | E57: =_LBO_CALC!Q55 -> 1.6855166 | G57: =_LBO_CALC!Q56 -> 1.3138138 | I57: =_LBO_CALC!Q57 -> 0.97295046
B58: Leverage exit | E58: =_LBO_CALC!R55 -> 0.60974608 | G58: =_LBO_CALC!R56 -> 1.2194922 | I58: =_LBO_CALC!R57 -> 2.1950859
B59: ICR exit (EBIT/Int) | E59: =_LBO_CALC!S55 -> 6.1326035 | G59: =_LBO_CALC!S56 -> 4.0884023 | I59: =_LBO_CALC!S57 -> 2.0442012
B61: G. EXPORT — Données reprises dans le PPTX et le PDF
B62: LBO_ELIGIBLE | C62: =IF(AND(INPUT!H30>0,IFERROR(INPUT!H30/INPUT!H9,0)>0.15,IFERROR(DCF!H49/INPUT!H30,0)>0.6,IFERROR((INPUT!H54+INPUT!H48-INPUT!H34)/INPUT!H30,99)<3.5),"OUI","NON") -> OUI
B63: LBO_MEGA_FLAG | C63: =IF(INPUT!H98>100000000,"theorique",IF(INPUT!H98>50000000,"mega","standard")) -> standard
B64: LBO_IRR_BASE | C64: =_LBO_CALC!N51 -> 0.056104182
B65: LBO_MOIC_BASE | C65: =_LBO_CALC!N52 -> 1.3138138
B66: LBO_IRR_BULL | C66: =_LBO_CALC!P55 -> 0.11006039
B67: LBO_IRR_BEAR | C67: =_LBO_CALC!P57 -> -0.0054694105
B68: LBO_LEVERAGE_EXIT | C68: =_LBO_CALC!R56 -> 1.2194922
B69: LBO_EQUITY_ENTRY | C69: =D31 -> 1373086.5
B70: LBO_EQUITY_EXIT | C70: =_LBO_CALC!N50 -> 1803980
B73: Méthodologie complète : voir slide méthodologie société. Calculs détaillés dans l'onglet _LBO_CALC (masqué — démasquer pour audit).

Sheet _LBO_CALC
B1: FinSight — LBO Calculation Engine (JPM/GS-grade)
B2: Onglet masqué — démasquer pour audit complet du modèle.
B4: 1. PROJECTIONS DÉTAILLÉES Y0-Y5 (référence DCF)
B5: ($000) | H5: Y0 (LTM) | I5: Y1 | J5: Y2 | K5: Y3 | L5: Y4 | M5: Y5
B6: Revenue | H6: =DCF!H9 -> 416161 | I6: =DCF!I9 -> 423994.6 | J6: =DCF!J9 -> 431975.66 | K6: =DCF!K9 -> 440106.94 | L6: =DCF!L9 -> 448391.29 | M6: =DCF!M9 -> 456831.58
B7: EBITDA | H7: =DCF!H15 -> 133050 | I7: =DCF!I15 -> 131004.98 | J7: =DCF!J15 -> 133470.95 | K7: =DCF!K15 -> 135983.34 | L7: =DCF!L15 -> 138543.02 | M7: =DCF!M15 -> 141150.88
B8: D&A | H8: =DCF!H17 -> -11698 | I8: =DCF!I17 -> -12252.431 | J8: =DCF!J17 -> -12483.065 | K8: =DCF!K17 -> -12718.04 | L8: =DCF!L17 -> -12957.437 | M8: =DCF!M17 -> -13201.341
B9: EBIT | H9: =DCF!H18 -> 121352 | I9: =DCF!I18 -> 118752.55 | J9: =DCF!J18 -> 120987.89 | K9: =DCF!K18 -> 123265.3 | L9: =DCF!L18 -> 125585.58 | M9: =DCF!M18 -> 127949.54
B10: CapEx | H10: =DCF!H47 -> -12715 | I10: =DCF!I47 -> -11708.547 | J10: =DCF!J47 -> -11928.943 | K10: =DCF!K47 -> -12153.487 | L10: =DCF!L47 -> -12382.258 | M10: =DCF!M47 -> -12615.336
B11: Δ Working Capital | H11: =DCF!H48 -> 6971 | I11: =DCF!I48 -> -51.037435 | J11: =DCF!J48 -> -51.998137 | K11: =DCF!K48 -> -52.976923 | L11: =DCF!L48 -> -53.974134 | M11: =DCF!M48 -> -54.990115
B12: FCF Unlevered (Pre-Debt) | H12: =DCF!H49 -> 108411.49 | I12: =DCF!I49 -> 98291.509 | J12: =DCF!J49 -> 100141.7 | K12: =DCF!K49 -> 102026.71 | L12: =DCF!L49 -> 103947.21 | M12: =DCF!M49 -> 105903.86
B14: 2. DEBT SCHEDULE COMPLET (Senior TLB + Mezzanine)
B15: SENIOR TERM LOAN B
B16: Beginning balance | H16: ='LBO MODEL'!C20*INPUT!H30 -> 465675 | I16: =H19 -> 465675 | J16: =I19 -> 415240.12 | K16: =J19 -> 360895.85 | L16: =K19 -> 302420.61 | M16: =L19 -> 239581.23
B17: Mandatory amortization (1%) | I17: =-MIN(I16*0.01,I16) -> -4656.75 | J17: =-MIN(J16*0.01,J16) -> -4152.4012 | K17: =-MIN(K16*0.01,K16) -> -3608.9585 | L17: =-MIN(L16*0.01,L16) -> -3024.2061 | M17: =-MIN(M16*0.01,M16) -> -2395.8123
B18: Cash sweep (75% excess FCF) | I18: =-MIN(I16+I17,MAX(0,(I12+I20)*0.75)) -> -45778.132 | J18: =-MIN(J16+J17,MAX(0,(J12+J20)*0.75)) -> -50191.866 | K18: =-MIN(K16+K17,MAX(0,(K12+K20)*0.75)) -> -54866.284 | L18: =-MIN(L16+L17,MAX(0,(L12+L20)*0.75)) -> -59815.172 | M18: =-MIN(M16+M17,MAX(0,(M12+M20)*0.75)) -> -65053.022
B19: Ending balance | H19: =H16 -> 465675 | I19: =I16+I17+I18 -> 415240.12 | J19: =J16+J17+J18 -> 360895.85 | K19: =K16+K17+K18 -> 302420.61 | L19: =L16+L17+L18 -> 239581.23 | M19: =M16+M17+M18 -> 172132.4
B20: Interest expense (TLB) | I20: =-I16*'LBO MODEL'!$C$22 -> -37254 | J20: =-J16*'LBO MODEL'!$C$22 -> -33219.209 | K20: =-K16*'LBO MODEL'!$C$22 -> -28871.668 | L20: =-L16*'LBO MODEL'!$C$22 -> -24193.649 | M20: =-M16*'LBO MODEL'!$C$22 -> -19166.498
B22: MEZZANINE
B23: Beginning balance | H23: ='LBO MODEL'!C21*INPUT!H30 -> 199575 | I23: =H26 -> 199575 | J23: =I26 -> 209553.75 | K23: =J26 -> 220031.44 | L23: =K26 -> 231033.01 | M23: =L26 -> 242584.66
B24: PIK interest (5% capitalisé) | I24: =I23*0.05 -> 9978.75 | J24: =J23*0.05 -> 10477.688 | K24: =K23*0.05 -> 11001.572 | L24: =L23*0.05 -> 11551.65 | M24: =M23*0.05 -> 12129.233
B25: Bullet repayment (Y5) | M25: =-(M23+M24) -> -254713.89
B26: Ending balance | H26: =H23 -> 199575 | I26: =I23+I24 -> 209553.75 | J26: =J23+J24 -> 220031.44 | K26: =K23+K24 -> 231033.01 | L26: =L23+L24 -> 242584.66 | M26: =M23+M24+M25 -> 0
B27: Interest expense Mezz (cash 5%) | I27: =-I23*0.05 -> -9978.75 | J27: =-J23*0.05 -> -10477.688 | K27: =-K23*0.05 -> -11001.572 | L27: =-L23*0.05 -> -11551.65 | M27: =-M23*0.05 -> -12129.233
B29: TOTAL INTEREST EXPENSE | I29: =I20+I27 -> -47232.75 | J29: =J20+J27 -> -43696.897 | K29: =K20+K27 -> -39873.24 | L29: =L20+L27 -> -35745.299 | M29: =M20+M27 -> -31295.731
B30: Net Debt (Senior + Mezz - Cash) | H30: =H19+H26 -> 665250 | I30: =I19+I26 -> 624793.87 | J30: =J19+J26 -> 580927.29 | K30: =K19+K26 -> 533453.62 | L30: =L19+L26 -> 482165.89 | M30: =M19+M26 -> 172132.4
B31: Total Leverage (× EBITDA) | H31: =IFERROR(H30/H7,0) -> 5 | I31: =IFERROR(I30/I7,0) -> 4.7692375 | J31: =IFERROR(J30/J7,0) -> 4.3524623 | K31: =IFERROR(K30/K7,0) -> 3.9229336 | L31: =IFERROR(L30/L7,0) -> 3.4802611 | M31: =IFERROR(M30/M7,0) -> 1.2194922
B32: Interest Coverage (EBIT/Int) | I32: =IFERROR(-I9/I29,0) -> 2.5141994 | J32: =IFERROR(-J9/J29,0) -> 2.7687981 | K32: =IFERROR(-K9/K29,0) -> 3.0914293 | L32: =IFERROR(-L9/L29,0) -> 3.5133454 | M32: =IFERROR(-M9/M29,0) -> 4.0884023
B34: 3. EXIT WATERFALL & RETURNS BASE CASE
B35: EBITDA exit (Y5) | M35: =M7 -> 141150.88
B36: × Multiple de sortie | M36: ='LBO MODEL'!$C$24 -> 14
B37: =EV exit -> #NAME? | M37: =M35*M36 -> 1976112.4
B38: − Net Debt at exit | M38: =-M30 -> -172132.4
B39: =Equity exit -> #NAME? | M39: =M37+M38 -> 1803980
M45: EQUITY ENTRY | N45: ='LBO MODEL'!D31 -> 1373086.5
M48: EBITDA Y5 | N48: =M35 -> 141150.88
M49: NET DEBT Y5 | N49: =M30 -> 172132.4
M50: EQUITY EXIT | N50: =M39 -> 1803980
M51: IRR BASE | N51: =IFERROR((N50/N45)^(1/'LBO MODEL'!C25)-1,0) -> 0.056104182
M52: MOIC BASE | N52: =IFERROR(N50/N45,0) -> 1.3138138
B54: 4. SCÉNARIOS BULL / BASE / BEAR (formules paramétrées) | M54: Scénario | P54: IRR | Q54: MOIC | R54: Lvg exit | S54: ICR exit
M55: BULL (rev +15%, marge +200bps, exit +1x) | P55: =IFERROR(((N48*1.15*(M36+1)-N49*0.7)/N45)^(1/'LBO MODEL'!C25)-1,0) -> 0.11006039 | Q55: =IFERROR((N48*1.15*(M36+1)-N49*0.7)/N45,0) -> 1.6855166 | R55: =M31*0.5 -> 0.60974608 | S55: =M32*1.5 -> 6.1326035
M56: BASE (hypothèses centrales) | P56: =N51 -> 0.056104182 | Q56: =N52 -> 1.3138138 | R56: =M31 -> 1.2194922 | S56: =M32 -> 4.0884023
M57: BEAR (rev -15%, marge -200bps, exit -1x) | P57: =IFERROR(((N48*0.85*(M36-1)-N49*1.3)/N45)^(1/'LBO MODEL'!C25)-1,0) -> -0.0054694105 | Q57: =IFERROR((N48*0.85*(M36-1)-N49*1.3)/N45,0) -> 0.97295046 | R57: =M31*1.8 -> 2.1950859 | S57: =M32*0.5 -> 2.0442012
