Workbook

Sheet INPUT
B3: INPUT — Raw Data
B4: All figures in USD millions unless stated
B5: METRIC | C5: UNIT | E5: 2022 | F5: 2023 | G5: 2024 | H5: 2025 (LTM)
B7: INPUT
B9: Revenue | C9: ($M) | E9: 263310 | F9: 218945 | G9: 195610 | H9: 182344
B10: Cost of Goods Sold (COGS) | C10: ($M) | E10: -182099 | F10: -156572 | G10: -140078 | H10: -130497
B11: Gross Profit | C11: ($M) | D11: =D9+D10 | E11: =E9+E10 | F11: =F9+F10 | G11: =G9+G10 | H11: =H9+H10
D13: =SUM(D14:D16) | E13: =SUM(E14:E16) | F13: =SUM(F14:F16) | G13: =SUM(G14:G16) | H13: =SUM(H14:H16)
B14: Operating Expenses (SG&A) | C14: ($M) | E14: -3946 | F14: -4800 | G14: -5150 | H14: -5834
B15: Research & Development | C15: ($M) | E15: -3075 | F15: -3969 | G15: -4540 | H15: -6411
B16: Depreciation & Amortization | C16: ($M) | E16: -13680 | F16: -13818 | G16: -13107 | H16: -13847
B17: EBIT (Operating Profit) | C17: ($M) | D17: =D11+D13 | E17: =E11+E13 | F17: =F11+F13 | G17: =G11+G13 | H17: =H11+H13
D19: =D17+D20+D21 | E19: =E17+E20+E21 | F19: =F17+F20+F21 | G19: =G17+G20+G21 | H19: =H17+H20+H21
B20: Interest Expense | C20: ($M) | E20: -2076 | F20: -2153 | G20: -2364 | H20: -2558
B21: Interest Income | C21: ($M) | E21: 1143 | F21: 1801 | G21: 1786 | H21: 1115
B22: Earnings Before Tax (EBT) | C22: ($M) | D22: =D19 | E22: =E19 | F22: =F19 | G22: =G19 | H22: =H19
D24: =-ROUND(D22*0.21,0) | E24: =-ROUND(E22*E104,0) | F24: =-ROUND(F22*F104,0) | G24: =-ROUND(G22*G104,0) | H24: =-ROUND(H22*H104,0)
B25: Income Tax Expense | C25: ($M) | E25: -22242 | F25: -13301 | G25: -10775 | H25: -9092
B26: Net Income | C26: ($M) | D26: =D22+D24 | E26: =E22+E24 | F26: =F22+F24 | G26: =G22+G24 | H26: =H22+H24
B29: Common Dividends | C29: ($M) | E29: -7711 | F29: -9167 | G29: -7995 | H29: -7714
B30: EBITDA | C30: ($M) | D30: =D17-D16 | E30: =E17-E16 | F30: =F17-F16 | G30: =G17-G16 | H30: =H17-H16
B32: BALANCE SHEET
B34: Cash & Cash Equivalents | C34: ($M) | E34: 33026 | F34: 27263 | G34: 25844 | H34: 24152
B35: Accounts Receivable | C35: ($M) | E35: 24378 | F35: 23442 | G35: 19281 | H35: 18559
B36: Inventories | C36: ($M) | E36: 22936 | F36: 19317 | G36: 18868 | H36: 16663
B37: Other Current Assets | C37: ($M) | E37: 63 | F37: 60 | G37: 71 | H37: 105
B38: Total Current Assets | C38: ($M) | D38: =SUM(D34:D37) | E38: =SUM(E34:E37) | F38: =SUM(F34:F37) | G38: =SUM(G34:G37) | H38: =SUM(H34:H37)
B41: PP&E (Net) | C41: ($M) | E41: 128054 | F41: 129277 | G41: 128945 | H41: 135394
B42: Intangible Assets | C42: ($M) | E42: 10978 | F42: 12722 | G42: 14388 | H42: 16645
B43: Other Long-Term Assets | C43: ($M) | E43: 301 | F43: 330 | G43: 154 | H43: 288
B44: Total Assets | C44: ($M) | D44: =D38+SUM(D41:D43) | E44: =E38+SUM(E41:E43) | F44: =F38+SUM(F41:F43) | G44: =G38+SUM(G41:G43) | H44: =H38+SUM(H41:H43)
B47: Accounts Payable | C47: ($M) | E47: 41346 | F47: 41335 | G47: 39932 | H47: 38065
B48: Short-Term Debt | C48: ($M) | E48: 14065 | F48: 7869 | G48: 7929 | H48: 10162
B49: Income Tax Payable | C49: ($M) | E49: 14780 | F49: 13974 | G49: 12561 | H49: 10427
B50: Other Current Liabilities | C50: ($M) | E50: 35841 | F50: 21070 | G50: 22285 | H50: 27890
B51: Total Current Liabilities | C51: ($M) | D51: =SUM(D47:D50) | E51: =SUM(E47:E50) | F51: =SUM(F47:F50) | G51: =SUM(G47:G50) | H51: =SUM(H47:H50)
B54: Long-Term Debt | C54: ($M) | E54: 41518 | F54: 38280 | G54: 41220 | H54: 48033
B55: Total Liabilities | C55: ($M) | D55: =D51+D54 | E55: =E51+E54 | F55: =F51+F54 | G55: =G51+G54 | H55: =H51+H54
B58: Common Equity (Paid-In Capital) | C58: ($M) | E58: 132114 | F58: 134473 | G58: 143073 | H58: 132919
B59: Retained Earnings | C59: ($M) | E59: 12885 | F59: 27882 | G59: 35209 | H59: 39003
B60: Total Shareholders Equity | C60: ($M) | D60: =D58+D59 | E60: =E58+E59 | F60: =F58+F59 | G60: =G58+G59 | H60: =H58+H59
B63: Total Liabilities & Equity | C63: ($M) | D63: =D55+D60 | E63: =E55+E60 | F63: =F55+F60 | G63: =G55+G60 | H63: =H55+H60
B67: CASH FLOW STATEMENT
B69: Net Income | C69: ($M) | D69: =D26 | E69: =E26 | F69: =F26 | G69: =G26 | H69: =H26
B70: Depreciation & Amortization | C70: ($M) | D70: =-D16 | E70: =-E16 | F70: =-F16 | G70: =-G16 | H70: =-H16
B71: Change in Accounts Receivable | C71: ($M) | E71: -3272 | F71: 306 | G71: 3884 | H71: 1406
B72: Change in Inventories | C72: ($M) | E72: -3805 | F72: 3159 | G72: -203 | H72: 2848
B73: Change in Accounts Payable | C73: ($M) | E73: 11791 | F73: -12234 | G73: 2239 | H73: -6236
B74: Other Working Capital Changes | C74: ($M) | E74: 432 | F74: 1250 | G74: 535 | H74: 422
B75: Cash from Operating Activities | C75: ($M) | D75: =SUM(D69:D74) | E75: =SUM(E69:E74) | F75: =SUM(F69:F74) | G75: =SUM(G69:G74) | H75: =SUM(H69:H74)
B78: Capital Expenditures (CapEx) | C78: ($M) | E78: -15690 | F78: -17722 | G78: -14909 | H78: -16953
B79: Other Investing Activities | C79: ($M) | E79: 577 | F79: 490 | G79: 347 | H79: 329
B80: Cash from Investing Activities | C80: ($M) | D80: =SUM(D78:D79) | E80: =SUM(E78:E79) | F80: =SUM(F78:F79) | G80: =SUM(G78:G79) | H80: =SUM(H78:H79)
B83: Change in Long-Term Debt | C83: ($M) | E83: 1148 | F83: 189 | G83: 7563 | H83: 8163
B84: Change in Common Equity | C84: ($M) | E84: 370 | F84: 383 | G84: 521 | H84: 492
B85: Dividends Paid | C85: ($M) | E85: -7711 | F85: -9167 | G85: -7995 | H85: -7714
B86: Cash from Financing Activities | C86: ($M) | D86: =SUM(D83:D85) | E86: =SUM(E83:E85) | F86: =SUM(F83:F85) | G86: =SUM(G83:G85) | H86: =SUM(H83:H85)
B89: Net Change in Cash | C89: ($M) | D89: =D75+D80+D86 | E89: =E75+E80+E86 | F89: =F75+F80+F86 | G89: =G75+G80+G86 | H89: =H75+H80+H86
B90: Beginning Cash Balance | C90: ($M) | E90: 21342 | F90: 33026 | G90: 27263 | H90: 25844
B91: Ending Cash Balance | C91: ($M) | D91: =D90+D89 | E91: =E90+E89 | F91: =F90+F89 | G91: =G90+G89 | H91: =H90+H89
B93: MARKET & VALUATION DATA
B95: Share Price | C95: ($) | E95: 130 | F95: 175 | G95: 226 | H95: 77.69
B96: Shares Outstanding (Diluted) | C96: (M) | E96: 16215 | F96: 15813 | G96: 15408 | H96: 2133.12
B97: Market Capitalization | C97: ($M) | D97: =D95*D96 | E97: =E95*E96 | F97: =F95*F96 | G97: =G95*G96 | H97: =H95*H96
B98: Enterprise Value (EV) | C98: ($M) | D98: =D97+D54+D48-D34 | E98: =E97+E54+E48-E34 | F98: =F97+F54+F48-F34 | G98: =G97+G54+G48-G34 | H98: =H97+H54+H48-H34
B99: Beta (Levered) | C99: (x) | H99: 1
B100: Risk-Free Rate | C100: (%) | H100: 0.0426
B101: Equity Risk Premium (ERP) | C101: (%) | H101: 0.055
B102: Cost of Equity (CAPM) | C102: (%) | D102: 0.1083 | E102: 0.1083 | F102: 0.1063 | G102: 0.1063 | H102: 0.1063
B103: Cost of Debt (Pre-Tax) | C103: (%) | H103: 0.044
B104: Tax Rate | C104: (%) | E104: 0.4 | F104: 0.3835 | G104: 0.4 | H104: 0.3858
B105: After-Tax Cost of Debt | C105: (%) | D105: 0.0379 | E105: 0.0379 | F105: 0.0363 | G105: 0.0363 | H105: 0.0363
B106: Weight of Equity (%) | C106: (%) | H106: 0.7401
B107: Weight of Debt (%) | C107: (%) | H107: 0.2599
B108: WACC | C108: (%) | D108: =D106*(D100+D99*D101)+D107*D103*(1-D104) | H108: =H106*(H100+H99*H101)+H107*H103*(1-H104)
B109: Terminal Growth Rate | C109: (%) | H109: 0.025
B110: Days in Period | C110: (days) | H110: 365
B112: COMPANY INFORMATION
B114: Company Name | C114: (text) | D114: TTE.PA
B115: Ticker Symbol | C115: (text) | D115: TTE.PA
B116: Sector / Industry | C116: (text) | D116: Energie / Oil & Gas
B117: Base Year (LTM) | C117: (text) | D117: 2025
B118: Currency | C118: (text) | D118: USD
B119: Units | C119: (text) | D119: M
B120: Analysis Date | C120: (text) | D120: 2026-04-15
B122: NOTE: All analytical sheets reference this INPUT sheet only. Enter data in the blue cells (columns D–H).
B124: © 2015 to 2024 FinSight
B125: This Excel model is for educational purposes only.
B126: https://finsight.com/
D128: =IF(COUNTA(D9,D10,D14,D15,D16,D20,D21,D25)=8,1,0)+IF(COUNTA(E9,E10,E14,E15,E16,E20,E21,E25)=8,1,0)+IF(COUNTA(F9,F10,F14,F15,F16,F20,F21,F25)=8,1,0)+IF(COUNTA(G9,G10,G14,G15,G16,G20,G21,G25)=8,1,0) | F128: =IF(D9<>"",1,0)+IF(E9<>"",1,0)+IF(F9<>"",1,0)+IF(G9<>"",1,0)+IF(H9<>"",1,0) | G128: =IF(NOT(ISBLANK(H9)),F128,IF(NOT(ISBLANK(G9)),F128,IF(NOT(ISBLANK(F9)),F128,IF(NOT(ISBLANK(E9)),F128,IF(NOT(ISBLANK(D9)),F128,0)))))
E132: 2022 | F132: 2023 | G132: 2024 | H132: 2025 (LTM)

Sheet RATIOS
B1: FinSight | H1: RATIOS — Financial Ratio Analysis
B3: RATIOS
B5: Year | E5: =IF(INPUT!E5="","",INPUT!E5) | F5: =IF(INPUT!F5="","",INPUT!F5) | G5: =IF(INPUT!G5="","",INPUT!G5) | H5: =IF(INPUT!H5="","",INPUT!H5)
B7: RATIOS DE VALORISATION — UTILITY
B9: EV/EBITDA | D9: – | E9: – | F9: – | G9: – | H9: =IFERROR(INPUT!H98/INPUT!H30,"–")
B10: P/E (Price / Earnings) | D10: – | E10: – | F10: – | G10: – | H10: =IFERROR(INPUT!H97/INPUT!H26,"–")
B11: EV / Revenue | D11: – | E11: – | F11: – | G11: – | H11: =IFERROR(INPUT!H98/INPUT!H9,"–")
B12: Price / Earnings (P/E) | D12: – | E12: – | F12: – | G12: – | H12: =IFERROR(INPUT!H95/(INPUT!H26/INPUT!H96),"–")
B13: EV / RAB (Regulated Asset Base) | D13: – | E13: – | F13: – | G13: – | H13: n.d. — source régulateur
B14: Dividend Yield | D14: – | E14: – | F14: – | G14: –
B15: FCF Yield @ current strip | D15: – | E15: =IFERROR((INPUT!E75+INPUT!E80)/INPUT!E97,"–") | F15: =IFERROR((INPUT!F75+INPUT!F80)/INPUT!F97,"–") | G15: =IFERROR((INPUT!G75+INPUT!G80)/INPUT!G97,"–") | H15: =IFERROR((INPUT!H75+INPUT!H80)/INPUT!H97,"–")
B17: PROFITABILITY RATIOS
B19: Gross Profit Margin | D19: =IFERROR(INPUT!D11/INPUT!D9,"–") | E19: =IFERROR(INPUT!E11/INPUT!E9,"–") | F19: =IFERROR(INPUT!F11/INPUT!F9,"–") | G19: =IFERROR(INPUT!G11/INPUT!G9,"–") | H19: =IFERROR(INPUT!H11/INPUT!H9,"–")
B20: EBITDA Margin | D20: =IFERROR(INPUT!D30/INPUT!D9,"–") | E20: =IFERROR(INPUT!E30/INPUT!E9,"–") | F20: =IFERROR(INPUT!F30/INPUT!F9,"–") | G20: =IFERROR(INPUT!G30/INPUT!G9,"–") | H20: =IFERROR(INPUT!H30/INPUT!H9,"–")
B21: EBIT (Operating) Margin | D21: =IFERROR(INPUT!D17/INPUT!D9,"–") | E21: =IFERROR(INPUT!E17/INPUT!E9,"–") | F21: =IFERROR(INPUT!F17/INPUT!F9,"–") | G21: =IFERROR(INPUT!G17/INPUT!G9,"–") | H21: =IFERROR(INPUT!H17/INPUT!H9,"–")
B22: Net Profit Margin | D22: =IFERROR(INPUT!D26/INPUT!D9,"–") | E22: =IFERROR(INPUT!E26/INPUT!E9,"–") | F22: =IFERROR(INPUT!F26/INPUT!F9,"–") | G22: =IFERROR(INPUT!G26/INPUT!G9,"–") | H22: =IFERROR(INPUT!H26/INPUT!H9,"–")
B23: Return on Equity (ROE) | D23: =IFERROR(INPUT!D26/INPUT!D60,"–") | E23: =IFERROR(INPUT!E26/INPUT!E60,"–") | F23: =IFERROR(INPUT!F26/INPUT!F60,"–") | G23: =IFERROR(INPUT!G26/INPUT!G60,"–") | H23: =IFERROR(INPUT!H26/INPUT!H60,"–")
B24: Return on Assets (ROA) | D24: =IFERROR(INPUT!D26/INPUT!D44,"–") | E24: =IFERROR(INPUT!E26/INPUT!E44,"–") | F24: =IFERROR(INPUT!F26/INPUT!F44,"–") | G24: =IFERROR(INPUT!G26/INPUT!G44,"–") | H24: =IFERROR(INPUT!H26/INPUT!H44,"–")
B25: Return on Invested Capital (ROIC) | D25: =IFERROR(INPUT!D17*(1-INPUT!D104)/(INPUT!D58+INPUT!D59),"–") | E25: =IFERROR(INPUT!E17*(1-INPUT!E104)/(INPUT!E58+INPUT!E59),"–") | F25: =IFERROR(INPUT!F17*(1-INPUT!F104)/(INPUT!F58+INPUT!F59),"–") | G25: =IFERROR(INPUT!G17*(1-INPUT!G104)/(INPUT!G58+INPUT!G59),"–") | H25: =IFERROR(INPUT!H17*(1-INPUT!H104)/(INPUT!H58+INPUT!H59),"–")
B27: LIQUIDITY & SOLVENCY RATIOS
B29: Current Ratio | D29: =IFERROR(INPUT!D38/INPUT!D51,"–") | E29: =IFERROR(INPUT!E38/INPUT!E51,"–") | F29: =IFERROR(INPUT!F38/INPUT!F51,"–") | G29: =IFERROR(INPUT!G38/INPUT!G51,"–") | H29: =IFERROR(INPUT!H38/INPUT!H51,"–")
B30: Quick Ratio | D30: =IFERROR((INPUT!D38-INPUT!D36)/INPUT!D51,"–") | E30: =IFERROR((INPUT!E38-INPUT!E36)/INPUT!E51,"–") | F30: =IFERROR((INPUT!F38-INPUT!F36)/INPUT!F51,"–") | G30: =IFERROR((INPUT!G38-INPUT!G36)/INPUT!G51,"–") | H30: =IFERROR((INPUT!H38-INPUT!H36)/INPUT!H51,"–")
B31: Cash Ratio | D31: =IFERROR(INPUT!D34/INPUT!D51,"–") | E31: =IFERROR(INPUT!E34/INPUT!E51,"–") | F31: =IFERROR(INPUT!F34/INPUT!F51,"–") | G31: =IFERROR(INPUT!G34/INPUT!G51,"–") | H31: =IFERROR(INPUT!H34/INPUT!H51,"–")
B32: Debt / Equity Ratio | D32: =IFERROR((INPUT!D49+INPUT!D55)/INPUT!D60,"–") | E32: =IFERROR((INPUT!E49+INPUT!E55)/INPUT!E60,"–") | F32: =IFERROR((INPUT!F49+INPUT!F55)/INPUT!F60,"–") | G32: =IFERROR((INPUT!G49+INPUT!G55)/INPUT!G60,"–") | H32: =IFERROR((INPUT!H49+INPUT!H55)/INPUT!H60,"–")
B33: Net Debt / EBITDA | D33: =IFERROR((INPUT!D49+INPUT!D55-INPUT!D34)/INPUT!D30,"–") | E33: =IFERROR((INPUT!E49+INPUT!E55-INPUT!E34)/INPUT!E30,"–") | F33: =IFERROR((INPUT!F49+INPUT!F55-INPUT!F34)/INPUT!F30,"–") | G33: =IFERROR((INPUT!G49+INPUT!G55-INPUT!G34)/INPUT!G30,"–") | H33: =IFERROR((INPUT!H49+INPUT!H55-INPUT!H34)/INPUT!H30,"–")
B34: Interest Coverage (EBIT/Interest) | D34: =IFERROR(INPUT!D17/ABS(INPUT!D20),"–") | E34: =IFERROR(INPUT!E17/ABS(INPUT!E20),"–") | F34: =IFERROR(INPUT!F17/ABS(INPUT!F20),"–") | G34: =IFERROR(INPUT!G17/ABS(INPUT!G20),"–") | H34: =IFERROR(INPUT!H17/ABS(INPUT!H20),"–")
B35: Debt / Total Assets | D35: =IFERROR((INPUT!D49+INPUT!D55)/INPUT!D44,"–") | E35: =IFERROR((INPUT!E49+INPUT!E55)/INPUT!E44,"–") | F35: =IFERROR((INPUT!F49+INPUT!F55)/INPUT!F44,"–") | G35: =IFERROR((INPUT!G49+INPUT!G55)/INPUT!G44,"–") | H35: =IFERROR((INPUT!H49+INPUT!H55)/INPUT!H44,"–")
B36: Equity Ratio | D36: =IFERROR(INPUT!D60/INPUT!D44,"–") | E36: =IFERROR(INPUT!E60/INPUT!E44,"–") | F36: =IFERROR(INPUT!F60/INPUT!F44,"–") | G36: =IFERROR(INPUT!G60/INPUT!G44,"–") | H36: =IFERROR(INPUT!H60/INPUT!H44,"–")
B38: OPERATIONAL EFFICIENCY RATIOS
B40: Asset Turnover | D40: =IFERROR(INPUT!D9/INPUT!D44,"–") | E40: =IFERROR(INPUT!E9/INPUT!E44,"–") | F40: =IFERROR(INPUT!F9/INPUT!F44,"–") | G40: =IFERROR(INPUT!G9/INPUT!G44,"–") | H40: =IFERROR(INPUT!H9/INPUT!H44,"–")
B42: GROWTH RATIOS
B44: Revenue Growth (YoY) | D44: – | E44: =IFERROR(INPUT!E9/INPUT!D9-1,"–") | F44: =IFERROR(INPUT!F9/INPUT!E9-1,"–") | G44: =IFERROR(INPUT!G9/INPUT!F9-1,"–") | H44: =IFERROR(INPUT!H9/INPUT!G9-1,"–")
B45: EBITDA Growth (YoY) | D45: – | E45: =IFERROR(INPUT!E30/INPUT!D30-1,"–") | F45: =IFERROR(INPUT!F30/INPUT!E30-1,"–") | G45: =IFERROR(INPUT!G30/INPUT!F30-1,"–") | H45: =IFERROR(INPUT!H30/INPUT!G30-1,"–")
B46: Net Income Growth (YoY) | D46: – | E46: =IFERROR(INPUT!E26/INPUT!D26-1,"–") | F46: =IFERROR(INPUT!F26/INPUT!E26-1,"–") | G46: =IFERROR(INPUT!G26/INPUT!F26-1,"–") | H46: =IFERROR(INPUT!H26/INPUT!G26-1,"–")
B47: EPS Growth (YoY) | D47: – | E47: =IFERROR((INPUT!E26/INPUT!E96)/(INPUT!D26/INPUT!D96)-1,"–") | F47: =IFERROR((INPUT!F26/INPUT!F96)/(INPUT!E26/INPUT!E96)-1,"–") | G47: =IFERROR((INPUT!G26/INPUT!G96)/(INPUT!F26/INPUT!F96)-1,"–") | H47: =IFERROR((INPUT!H26/INPUT!H96)/(INPUT!G26/INPUT!G96)-1,"–")
B48: Total Assets Growth (YoY) | D48: – | E48: =IFERROR(INPUT!E44/INPUT!D44-1,"–") | F48: =IFERROR(INPUT!F44/INPUT!E44-1,"–") | G48: =IFERROR(INPUT!G44/INPUT!F44-1,"–") | H48: =IFERROR(INPUT!H44/INPUT!G44-1,"–")
B50: CASH FLOW RATIOS
B52: Operating Cash Flow Margin | D52: =IFERROR(INPUT!D75/INPUT!D9,"–") | E52: =IFERROR(INPUT!E75/INPUT!E9,"–") | F52: =IFERROR(INPUT!F75/INPUT!F9,"–") | G52: =IFERROR(INPUT!G75/INPUT!G9,"–") | H52: =IFERROR(INPUT!H75/INPUT!H9,"–")
B53: Free Cash Flow (FCF) | D53: =IFERROR(INPUT!D75+INPUT!D78,"–") | E53: =IFERROR(INPUT!E75+INPUT!E78,"–") | F53: =IFERROR(INPUT!F75+INPUT!F78,"–") | G53: =IFERROR(INPUT!G75+INPUT!G78,"–") | H53: =IFERROR(INPUT!H75+INPUT!H78,"–")
B54: FCF Margin | D54: =IFERROR(D53/INPUT!D9,"–") | E54: =IFERROR(E53/INPUT!E9,"–") | F54: =IFERROR(F53/INPUT!F9,"–") | G54: =IFERROR(G53/INPUT!G9,"–") | H54: =IFERROR(H53/INPUT!H9,"–")
B55: CapEx / Revenue | D55: =IFERROR(ABS(INPUT!D78)/INPUT!D9,"–") | E55: =IFERROR(ABS(INPUT!E78)/INPUT!E9,"–") | F55: =IFERROR(ABS(INPUT!F78)/INPUT!F9,"–") | G55: =IFERROR(ABS(INPUT!G78)/INPUT!G9,"–") | H55: =IFERROR(ABS(INPUT!H78)/INPUT!H9,"–")
B56: Dividend Payout Ratio | D56: =IFERROR(ABS(INPUT!D85)/INPUT!D26,"–") | E56: =IFERROR(ABS(INPUT!E85)/INPUT!E26,"–") | F56: =IFERROR(ABS(INPUT!F85)/INPUT!F26,"–") | G56: =IFERROR(ABS(INPUT!G85)/INPUT!G26,"–") | H56: =IFERROR(ABS(INPUT!H85)/INPUT!H26,"–")
B58: MÉTRIQUES OPÉRATIONNELLES — UTILITY
B60: Dividend Payout Ratio | E60: =IFERROR(ABS(INPUT!E85)/INPUT!E26,"–") | F60: =IFERROR(ABS(INPUT!F85)/INPUT!F26,"–") | G60: =IFERROR(ABS(INPUT!G85)/INPUT!G26,"–") | H60: =IFERROR(ABS(INPUT!H85)/INPUT!H26,"–")
B61: Dividend Coverage | E61: =IFERROR(INPUT!E26/ABS(INPUT!E85),"–") | F61: =IFERROR(INPUT!F26/ABS(INPUT!F85),"–") | G61: =IFERROR(INPUT!G26/ABS(INPUT!G85),"–") | H61: =IFERROR(INPUT!H26/ABS(INPUT!H85),"–")
B62: CapEx / Revenue | E62: =IFERROR(ABS(INPUT!E78)/INPUT!E9,"–") | F62: =IFERROR(ABS(INPUT!F78)/INPUT!F9,"–") | G62: =IFERROR(ABS(INPUT!G78)/INPUT!G9,"–") | H62: =IFERROR(ABS(INPUT!H78)/INPUT!H9,"–")
B63: Allowed ROE (n.d.) | E63: n.d. | F63: n.d. | G63: n.d. | H63: n.d.
B64: FCF Yield @ Current Strip (%) | E64: =IFERROR((INPUT!E75+INPUT!E78)/INPUT!E97,"–") | F64: =IFERROR((INPUT!F75+INPUT!F78)/INPUT!F97,"–") | G64: =IFERROR((INPUT!G75+INPUT!G78)/INPUT!G97,"–") | H64: =IFERROR((INPUT!H75+INPUT!H78)/INPUT!H97,"–")
B65: Shareholder Yield (Div + Buyback / Mkt Cap) | E65: =IFERROR((ABS(INPUT!E85)+ABS(INPUT!E86))/INPUT!E97,"–") | F65: =IFERROR((ABS(INPUT!F85)+ABS(INPUT!F86))/INPUT!F97,"–") | G65: =IFERROR((ABS(INPUT!G85)+ABS(INPUT!G86))/INPUT!G97,"–") | H65: =IFERROR((ABS(INPUT!H85)+ABS(INPUT!H86))/INPUT!H97,"–")
B70: © 2015 to 2024 FinSight
B71: This Excel model is for educational purposes only.
B72: https://finsight.com/
B75: CHART DATA
B76: Year | D76: =IF(INPUT!D9="","",D5) | E76: =IF(INPUT!E9="",NA(),E5) | F76: =IF(INPUT!F9="",NA(),F5) | G76: =IF(INPUT!G9="",NA(),G5) | H76: =IF(INPUT!H9="",NA(),H5)
B77: Revenue ($M) | D77: =IF(INPUT!D9="","",INPUT!D9) | E77: =IF(INPUT!E9="",NA(),INPUT!E9) | F77: =IF(INPUT!F9="",NA(),INPUT!F9) | G77: =IF(INPUT!G9="",NA(),INPUT!G9) | H77: =IF(INPUT!H9="",NA(),INPUT!H9)
B78: EBITDA ($M) | D78: =IF(INPUT!E9="",NA(),INPUT!E30) | E78: =IF(INPUT!F9="",NA(),INPUT!F30) | F78: =IF(INPUT!G9="",NA(),INPUT!G30) | G78: =IF(INPUT!G9="",NA(),INPUT!G30) | H78: =IF(INPUT!H9="",NA(),INPUT!H30)
B79: Net Income ($M) | D79: =IF(INPUT!E9="",NA(),INPUT!E26) | E79: =IF(INPUT!F9="",NA(),INPUT!F26) | F79: =IF(INPUT!G9="",NA(),INPUT!G26) | G79: =IF(INPUT!G9="",NA(),INPUT!G26) | H79: =IF(INPUT!H9="",NA(),INPUT!H26)
B80: Cumul. Revenue ($M) | D80: =IF(INPUT!E9="",NA(),INPUT!D9+INPUT!E9) | E80: =IF(INPUT!F9="",NA(),INPUT!D9+INPUT!E9+INPUT!F9) | F80: =IF(INPUT!G9="",NA(),INPUT!D9+INPUT!E9+INPUT!F9+INPUT!G9) | G80: =IF(INPUT!G9="",NA(),INPUT!D9+INPUT!E9+INPUT!F9+INPUT!G9) | H80: =IF(INPUT!H9="",NA(),INPUT!D9+INPUT!E9+INPUT!F9+INPUT!G9+INPUT!H9)
B82: Gross Profit Margin | D82: =IF(INPUT!D9="","",D19) | E82: =IF(INPUT!E9="",NA(),E19) | F82: =IF(INPUT!F9="",NA(),F19) | G82: =IF(INPUT!G9="",NA(),G19) | H82: =IF(INPUT!H9="",NA(),H19)
B83: EBITDA Margin | D83: =IF(INPUT!D9="","",D20) | E83: =IF(INPUT!E9="",NA(),E20) | F83: =IF(INPUT!F9="",NA(),F20) | G83: =IF(INPUT!G9="",NA(),G20) | H83: =IF(INPUT!H9="",NA(),H20)
B84: Net Profit Margin | D84: =IF(INPUT!D9="","",D22) | E84: =IF(INPUT!E9="",NA(),E22) | F84: =IF(INPUT!F9="",NA(),F22) | G84: =IF(INPUT!G9="",NA(),G22) | H84: =IF(INPUT!H9="",NA(),H22)
B87: SG&A ($M) | D87: =IF(INPUT!D9="","",ABS(INPUT!D14)) | E87: =IF(INPUT!E9="",NA(),ABS(INPUT!E14)) | F87: =IF(INPUT!F9="",NA(),ABS(INPUT!F14)) | G87: =IF(INPUT!G9="",NA(),ABS(INPUT!G14)) | H87: =IF(INPUT!H9="",NA(),ABS(INPUT!H14))
B88: R&D ($M) | D88: =IF(INPUT!D9="","",ABS(INPUT!D15)) | E88: =IF(INPUT!E9="",NA(),ABS(INPUT!E15)) | F88: =IF(INPUT!F9="",NA(),ABS(INPUT!F15)) | G88: =IF(INPUT!G9="",NA(),ABS(INPUT!G15)) | H88: =IF(INPUT!H9="",NA(),ABS(INPUT!H15))
B89: D&A ($M) | D89: =IF(INPUT!D9="","",ABS(INPUT!D16)) | E89: =IF(INPUT!E9="",NA(),ABS(INPUT!E16)) | F89: =IF(INPUT!F9="",NA(),ABS(INPUT!F16)) | G89: =IF(INPUT!G9="",NA(),ABS(INPUT!G16)) | H89: =IF(INPUT!H9="",NA(),ABS(INPUT!H16))
B90: Interest ($M) | D90: =IF(INPUT!D9="","",ABS(INPUT!D20)) | E90: =IF(INPUT!E9="",NA(),ABS(INPUT!E20)) | F90: =IF(INPUT!F9="",NA(),ABS(INPUT!F20)) | G90: =IF(INPUT!G9="",NA(),ABS(INPUT!G20)) | H90: =IF(INPUT!H9="",NA(),ABS(INPUT!H20))
B93: SG&A ($M) | D93: =IF(INPUT!D9="","",D87/1000) | E93: =E87/1000 | F93: =F87/1000 | G93: =G87/1000 | H93: =H87/1000
B94: R&D ($M) | D94: =IF(INPUT!D9="","",D88/1000) | E94: =E88/1000 | F94: =F88/1000 | G94: =G88/1000 | H94: =H88/1000
B95: D&A ($M) | D95: =IF(INPUT!D9="","",D89/1000) | E95: =E89/1000 | F95: =F89/1000 | G95: =G89/1000 | H95: =H89/1000
B96: Interest ($M) | D96: =IF(INPUT!D9="","",D90/1000) | E96: =E90/1000 | F96: =F90/1000 | G96: =G90/1000 | H96: =H90/1000
G97: =G90/1000 | H97: =H90/1000
B99: Cumul. Revenue ($M) | D99: =D80/1000 | E99: =E80/1000 | F99: =F80/1000 | G99: =G80/1000 | H99: =H80/1000
G101: =G80/1000 | H101: =H80/1000
B102: FCF & CapEx Trend ($M)
B103: Metric
B104: Free Cash Flow ($M) | E104: =E53 | F104: =F53 | G104: =G53 | H104: =H53
B105: CapEx ($M) | E105: =ABS(INPUT!E78) | F105: =ABS(INPUT!F78) | G105: =ABS(INPUT!G78) | H105: =ABS(INPUT!H78)
B106: Cash from Operations ($M) | E106: =INPUT!E75 | F106: =INPUT!F75 | G106: =INPUT!G75 | H106: =INPUT!H75
B108: Returns Chart Data
B109: Metric
B110: Return on Equity (ROE) | E110: =E23 | F110: =F23 | G110: =G23 | H110: =H23
B111: Return on Assets (ROA) | E111: =E24 | F111: =F24 | G111: =G24 | H111: =H24
B112: Return on Invested Capital (ROIC) | E112: =E25 | F112: =F25 | G112: =G25 | H112: =H25

Sheet DCF
B1: FinSight | K1: DCF — Discounted Cash Flow Valuation
B3: DCF
B4: All figures in USD millions unless stated
B5: METRIC | C5: (Units) | D5: =IF(INPUT!D5="","",INPUT!D5) | E5: =IF(INPUT!E5="","",INPUT!E5) | F5: =IF(INPUT!F5="","",INPUT!F5) | G5: =IF(INPUT!G5="","",INPUT!G5) | H5: =IF(INPUT!H5="","",INPUT!H5) | I5: =TEXT(INPUT!D117+1,"0")&"F" | J5: =TEXT(INPUT!D117+2,"0")&"F" | K5: =TEXT(INPUT!D117+3,"0")&"F" | L5: =TEXT(INPUT!D117+4,"0")&"F" | M5: =TEXT(INPUT!D117+5,"0")&"F" | N5: Terminal
B7: INCOME STATEMENT
B9: Revenue | D9: =INPUT!D9 | E9: =INPUT!E9 | F9: =INPUT!F9 | G9: =INPUT!G9 | H9: =IF(INPUT!H9<>"",INPUT!H9,INPUT!G9) | I9: =H9*(1+$I$29) | J9: =I9*(1+$I$29) | K9: =J9*(1+$I$29) | L9: =K9*(1+$I$29) | M9: =L9*(1+$I$29)
B10: Cost of Goods Sold | D10: =INPUT!D10 | E10: =INPUT!E10 | F10: =INPUT!F10 | G10: =INPUT!G10 | H10: =IF(INPUT!H10<>"",INPUT!H10,INPUT!G10) | I10: =-I9*(1-$I$30) | J10: =-J9*(1-$I$30) | K10: =-K9*(1-$I$30) | L10: =-L9*(1-$I$30) | M10: =-M9*(1-$I$30)
B11: Gross Profit | D11: =SUM(D9:D10) | E11: =SUM(E9:E10) | F11: =SUM(F9:F10) | G11: =SUM(G9:G10) | H11: =SUM(H9:H10) | I11: =SUM(I9:I10) | J11: =SUM(J9:J10) | K11: =SUM(K9:K10) | ... M11: =SUM(M9:M10)
B13: SG&A Expenses | D13: =INPUT!D14 | E13: =INPUT!E14 | F13: =INPUT!F14 | G13: =INPUT!G14 | H13: =IF(INPUT!H14<>"",INPUT!H14,INPUT!G14) | I13: =-I9*$I$31 | J13: =-J9*$I$31 | K13: =-K9*$I$31 | L13: =-L9*$I$31 | M13: =-M9*$I$31
B14: Research & Development | D14: =INPUT!D15 | E14: =INPUT!E15 | F14: =INPUT!F15 | G14: =INPUT!G15 | H14: =IF(INPUT!H15<>"",INPUT!H15,INPUT!G15) | I14: =-I9*$I$32 | J14: =-J9*$I$32 | K14: =-K9*$I$32 | L14: =-L9*$I$32 | M14: =-M9*$I$32
B15: EBITDA | D15: =INPUT!D30 | E15: =INPUT!E30 | F15: =INPUT!F30 | G15: =INPUT!G30 | H15: =IF(INPUT!H30<>"",INPUT!H30,INPUT!G30) | I15: =I11+I13+I14 | J15: =J11+J13+J14 | K15: =K11+K13+K14 | L15: =L11+L13+L14 | M15: =M11+M13+M14
B17: Depreciation & Amortization | D17: =INPUT!D16 | E17: =INPUT!E16 | F17: =INPUT!F16 | G17: =INPUT!G16 | H17: =IF(INPUT!H16<>"",INPUT!H16,INPUT!G16) | I17: =-I9*$I$33 | J17: =-J9*$I$33 | K17: =-K9*$I$33 | L17: =-L9*$I$33 | M17: =-M9*$I$33
B18: EBIT (Operating Profit) | D18: =D15+D17 | E18: =E15+E17 | F18: =F15+F17 | G18: =G15+G17 | H18: =H15+H17 | I18: =I15+I17 | J18: =J15+J17 | K18: =K15+K17 | ... M18: =M15+M17
B20: Interest Expense | D20: =INPUT!D20 | E20: =INPUT!E20 | F20: =INPUT!F20 | G20: =INPUT!G20 | H20: =IF(INPUT!H20<>"",INPUT!H20,INPUT!G20) | I20: =-I18*(INPUT!H103)/(1-$I$34) | J20: =-J18*(INPUT!H103)/(1-$I$34) | K20: =-K18*(INPUT!H103)/(1-$I$34) | L20: =-L18*(INPUT!H103)/(1-$I$34) | M20: =-M18*(INPUT!H103)/(1-$I$34)
B21: Earnings Before Tax (EBT) | D21: =D18+D20 | E21: =E18+E20 | F21: =F18+F20 | G21: =G18+G20 | H21: =H18+H20 | I21: =I18+I20 | J21: =J18+J20 | K21: =K18+K20 | ... M21: =M18+M20
B23: Income Taxes | D23: =INPUT!D24 | E23: =INPUT!E24 | F23: =INPUT!F24 | G23: =INPUT!G24 | H23: =IF(INPUT!H24<>"",INPUT!H24,INPUT!G24) | I23: =-I21*$I$34 | J23: =-J21*$I$34 | K23: =-K21*$I$34 | L23: =-L21*$I$34 | M23: =-M21*$I$34
B24: Net Income | D24: =D21+D23 | E24: =E21+E23 | F24: =F21+F23 | G24: =G21+G23 | H24: =H21+H23 | I24: =I21+I23 | J24: =J21+J23 | K24: =K21+K23 | ... M24: =M21+M23
B26: ASSUMPTIONS & DRIVERS
B27: All figures in USD millions unless stated
B28: INCOME STATEMENT DRIVERS
B29: Revenue Growth Rate (YoY) | D29: =IFERROR(IF(NOT(ISBLANK(INPUT!H9)),INPUT!H9/INPUT!G9-1,IF(NOT(ISBLANK(INPUT!G9)),INPUT!G9/INPUT!F9-1,IF(NOT(ISBLANK(INPUT!F9)),INPUT!F9/INPUT!E9-1,IF(NOT(ISBLANK(INPUT!E9)),INPUT!E9/INPUT!D9-1,0.05)))),0.05) | I29: =IF(D46="Yes",D45,IFERROR(AVERAGE(IF(ISNUMBER(RATIOS!F44),RATIOS!F44,0),IF(ISNUMBER(RATIOS!G44),RATIOS!G44,0),IF(ISNUMBER(RATIOS!H44),RATIOS!H44,0)),0.05))
B30: Gross Margin | D30: =IFERROR(INPUT!H11/INPUT!H9,0.4) | I30: =IFERROR(AVERAGE(IF(INPUT!E9<>0,INPUT!E11/INPUT!E9),IF(INPUT!F9<>0,INPUT!F11/INPUT!F9),IF(INPUT!G9<>0,INPUT!G11/INPUT!G9),IF(INPUT!H9<>0,INPUT!H11/INPUT!H9)),0.4)
B31: SG&A (% of Revenue) | D31: =IFERROR(ABS(INPUT!H14)/INPUT!H9,0.15) | I31: =IFERROR(AVERAGE(IF(INPUT!E9<>0,ABS(INPUT!E14)/INPUT!E9),IF(INPUT!F9<>0,ABS(INPUT!F14)/INPUT!F9),IF(INPUT!G9<>0,ABS(INPUT!G14)/INPUT!G9),IF(INPUT!H9<>0,ABS(INPUT!H14)/INPUT!H9)),0.15)
B32: R&D (% of Revenue) | D32: =IFERROR(ABS(INPUT!H15)/INPUT!H9,0.05) | I32: =IFERROR(AVERAGE(IF(INPUT!E9<>0,ABS(INPUT!E15)/INPUT!E9),IF(INPUT!F9<>0,ABS(INPUT!F15)/INPUT!F9),IF(INPUT!G9<>0,ABS(INPUT!G15)/INPUT!G9),IF(INPUT!H9<>0,ABS(INPUT!H15)/INPUT!H9)),0.05)
B33: D&A (% of Revenue) | D33: =IFERROR(ABS(INPUT!H16)/INPUT!H9,0.04) | I33: =IFERROR(AVERAGE(IF(INPUT!E9<>0,ABS(INPUT!E16)/INPUT!E9),IF(INPUT!F9<>0,ABS(INPUT!F16)/INPUT!F9),IF(INPUT!G9<>0,ABS(INPUT!G16)/INPUT!G9),IF(INPUT!H9<>0,ABS(INPUT!H16)/INPUT!H9)),0.04)
B34: Effective Tax Rate | D34: =IFERROR(INPUT!H104,0.21) | I34: =IFERROR(AVERAGEIF(INPUT!E104:H104,"<>0"),0.21)
B36: BALANCE SHEET / CASH FLOW DRIVERS
B37: CapEx (% of Revenue) | D37: =IFERROR(ABS(INPUT!H78)/INPUT!H9,0.05) | E37: =I37 | F37: =I37 | I37: =IFERROR(AVERAGE(IF(INPUT!E9<>0,ABS(INPUT!E78)/INPUT!E9),IF(INPUT!F9<>0,ABS(INPUT!F78)/INPUT!F9),IF(INPUT!G9<>0,ABS(INPUT!G78)/INPUT!G9),IF(INPUT!H9<>0,ABS(INPUT!H78)/INPUT!H9)),0.05) | J37: =I37 | K37: =I37 | L37: =I37 | M37: =I37
B38: Change in NWC (% of Revenue Change) | D38: =IFERROR(ABS((INPUT!H71+INPUT!H72+INPUT!H73)/INPUT!H9),0.1) | E38: =I38 | F38: =I38 | I38: =IFERROR(AVERAGE(IF(INPUT!E9<>0,ABS((INPUT!E71+INPUT!E72+INPUT!E73)/INPUT!E9)),IF(INPUT!F9<>0,ABS((INPUT!F71+INPUT!F72+INPUT!F73)/INPUT!F9)),IF(INPUT!G9<>0,ABS((INPUT!G71+INPUT!G72+INPUT!G73)/INPUT!G9)),IF(INPUT!H9<>0,ABS((INPUT!H71+INPUT!H72+INPUT!H73)/INPUT!H9))),0.1) | J38: =I38 | K38: =I38 | L38: =I38 | M38: =I38
B40: (Section Brent désactivée — non pertinente Utility)
E42: =IF(D42="Bear",60,IF(D42="Base",75,IF(D42="Bull",90,75)))
E43: =E18 | F43: =F18 | G43: =G18 | H43: =H18 | I43: =I18 | J43: =J18 | K43: =K18 | L43: =L18 | M43: =M18
E44: =E18*(-INPUT!E104) | F44: =F18*(-INPUT!F104) | G44: =G18*(-INPUT!G104) | H44: =H18*(-INPUT!H104) | I44: =I18*(-$I$34) | J44: =J18*(-$I$34) | K44: =K18*(-$I$34) | L44: =L18*(-$I$34) | M44: =M18*(-$I$34)
D45: =IFERROR(((INPUT!H9+(E42-D44)*D43)/INPUT!H9)-1,0) | E45: =E43+E44 | F45: =F43+F44 | G45: =G43+G44 | H45: =H43+H44 | I45: =I43+I44 | J45: =J43+J44 | K45: =K43+K44 | L45: =L43+L44 | M45: =M43+M44
B48: FREE CASH FLOW CALCULATION
B49: (+) Depreciation & Amortization | E49: =ABS(E17) | F49: =ABS(F17) | G49: =ABS(G17) | H49: =ABS(H17) | I49: =ABS(I17) | J49: =ABS(J17) | K49: =ABS(K17) | L49: =ABS(L17) | M49: =ABS(M17)
B50: (-) Capital Expenditures (CapEx) | E50: =INPUT!E78 | F50: =INPUT!F78 | G50: =INPUT!G78 | H50: =IF(INPUT!H78<>"",INPUT!H78,INPUT!G78) | I50: =-I9*$I$37 | J50: =-J9*$I$37 | K50: =-K9*$I$37 | L50: =-L9*$I$37 | M50: =-M9*$I$37
B51: (-) Change in Working Capital | E51: =INPUT!E70+INPUT!E71+INPUT!E72+INPUT!E73 | F51: =INPUT!F70+INPUT!F71+INPUT!F72+INPUT!F73 | G51: =INPUT!G70+INPUT!G71+INPUT!G72+INPUT!G73 | H51: =IF(INPUT!H70<>"",INPUT!H70,INPUT!G70)+IF(INPUT!H71<>"",INPUT!H71,INPUT!G71)+IF(INPUT!H72<>"",INPUT!H72,INPUT!G72)+IF(INPUT!H73<>"",INPUT!H73,INPUT!G73) | I51: =-(I9-H9)*$I$38 | J51: =-(J9-I9)*$I$38 | K51: =-(K9-J9)*$I$38 | L51: =-(L9-K9)*$I$38 | M51: =-(M9-L9)*$I$38
B52: Unlevered Free Cash Flow (UFCF) | E52: =E45+E49+E50+E51 | F52: =F45+F49+F50+F51 | G52: =G45+G49+G50+G51 | H52: =H45+H49+H50+H51 | I52: =I45+I49+I50+I51 | J52: =J45+J49+J50+J51 | K52: =K45+K49+K50+K51 | L52: =L45+L49+L50+L51 | M52: =M45+M49+M50+M51
B54: WACC CALCULATION (Capital Asset Pricing Model)
B56: Risk-Free Rate (Rf) | D56: =INPUT!H100 | N56: =D56
B57: Beta (Levered) | D57: =INPUT!H99 | N57: =D57
B58: Equity Risk Premium (ERP) | D58: =INPUT!H101 | N58: =D58
B59: Cost of Equity (CAPM) | D59: =D56+D57*D58 | N59: =D59
B61: Target Equity Weight (We) | D61: =INPUT!H106 | N61: =D61
B62: Target Debt Weight (Wd) | D62: =INPUT!H107 | N62: =D62
B63: Pre-Tax Cost of Debt (Kd) | D63: =INPUT!H103 | N63: =D63
B64: Tax Rate | D64: =INPUT!H104 | N64: =D64
B65: After-Tax Cost of Debt | D65: =D63*(1-D64) | N65: =D65
B66: WACC | D66: =D61*D59+D65*D62 | N66: =D66
B68: TERMINAL VALUE & ENTERPRISE VALUE
B70: Terminal Growth Rate (g) | D70: =INPUT!H109 | N70: =D70
B71: WACC | D71: =D66 | N71: =D71
B72: Year 5 UFCF | D72: =M52 | N72: =D72
B73: Terminal Year UFCF (t+1) | D73: =D72*(1+D70) | N73: =D73
B74: Terminal Value (Gordon Growth) | D74: =IFERROR(D73/(D71-D70),"–") | N74: =D74
B75: Terminal EBITDA Multiple (Alt.) | D75: =IFERROR(D74/M15,"–") | N75: =D75
B76: Discounting Period (Years) | D76: =1 | J76: 2 | K76: 3 | L76: 4 | M76: 5 | N76: 5
B78: Discount Factor | D78: =1/(1+$D$71)^I76 | J78: =1/(1+$D$71)^J76 | K78: =1/(1+$D$71)^K76 | L78: =1/(1+$D$71)^L76 | M78: =1/(1+$D$71)^M76 | N78: =1/(1+$D$71)^M76
B79: UFCF to Discount | D79: =I52 | J79: =J52 | K79: =K52 | L79: =L52 | M79: =M52
B80: Terminal Value to Discount | N80: =D74
B81: PV of UFCF + Terminal Value | J81: =J78*J79 | K81: =K78*K79 | L81: =L78*L79 | M81: =M78*M79 | N81: =IFERROR(N78*N80,"–")
B83: ENTERPRISE VALUE & EQUITY VALUE
B85: Sum of PV of UFCFs (Years 1-5) | D85: =SUM(I81:M81) | N85: =D85
B86: PV of Terminal Value | D86: =N81 | N86: =D86
B87: Enterprise Value (EV) | D87: =IFERROR(D85+D86,"–") | N87: =D87
B89: (-) Total Debt | D89: =-(INPUT!H48+INPUT!H54) | N89: =D89
B90: (+) Cash & Cash Equivalents | D90: =INPUT!H34 | N90: =D90
B91: Equity Value | D91: =IFERROR(D87+D89+D90,"–") | N91: =D91
B93: Shares Outstanding (Diluted) | D93: =INPUT!H96 | N93: =D93
B94: Implied Share Price (DCF) | D94: =IFERROR(D91/D93,"–") | N94: =D94
B95: Current Share Price | C95: ($) | D95: =INPUT!H95 | N95: =D95
B96: Upside / (Downside) | C96: (%) | D96: =IFERROR(D94/D95-1,"–") | N96: =D96
B97: UFCF IRR (5-Year) | C97: (%) | D97: =IFERROR(IRR(CHOOSE({1,2,3,4,5,6},-D87,I52,J52,K52,L52,M52+D74)),"–")
O98: =ROUND(C103*100,1)&"%" | P98: =ROUND(C104*100,1)&"%" | Q98: =ROUND(C105*100,1)&"%"
B99: SENSITIVITY ANALYSIS — Implied Share Price ($) | M99: =ROUND(C101*100,1)&"%" | N99: =ROUND(C102*100,1)&"%" | O99: =D103 | P99: =D104 | Q99: =D105
B100: Terminal Growth Rate → | C100: WACC ↓ | D100: 0 | E100: 0.01 | F100: 0.02 | G100: 0.03 | H100: 0.04 | L100: g=0% | M100: =D101 | N100: =D102 | O100: =E103 | P100: =E104 | Q100: =E105
C101: =D66-0.02 | D101: =IFERROR((D85+((D72*(1+0))/(C101-0))/(1+C101)^5+D89+D90)/D93,"–") | E101: =IFERROR((D85+((D72*(1+0.01))/(C101-0.01))/(1+C101)^5+D89+D90)/D93,"–") | F101: =IFERROR((D85+((D72*(1+0.02))/(C101-0.02))/(1+C101)^5+D89+D90)/D93,"–") | G101: =IFERROR((D85+((D72*(1+0.03))/(C101-0.03))/(1+C101)^5+D89+D90)/D93,"–") | H101: =IFERROR((D85+((D72*(1+0.04))/(C101-0.04))/(1+C101)^5+D89+D90)/D93,"–") | L101: g=1% | M101: =E101 | N101: =E102 | O101: =F103 | P101: =F104 | Q101: =F105
C102: =D66-0.01 | D102: =IFERROR((D85+((D72*(1+0))/(C102-0))/(1+C102)^5+D89+D90)/D93,"–") | E102: =IFERROR((D85+((D72*(1+0.01))/(C102-0.01))/(1+C102)^5+D89+D90)/D93,"–") | F102: =IFERROR((D85+((D72*(1+0.02))/(C102-0.02))/(1+C102)^5+D89+D90)/D93,"–") | G102: =IFERROR((D85+((D72*(1+0.03))/(C102-0.03))/(1+C102)^5+D89+D90)/D93,"–") | H102: =IFERROR((D85+((D72*(1+0.04))/(C102-0.04))/(1+C102)^5+D89+D90)/D93,"–") | L102: g=2% | M102: =F101 | N102: =F102 | O102: =G103 | P102: =G104 | Q102: =G105
C103: =D66 | D103: =IFERROR((D85+((D72*(1+0))/(C103-0))/(1+C103)^5+D89+D90)/D93,"–") | E103: =IFERROR((D85+((D72*(1+0.01))/(C103-0.01))/(1+C103)^5+D89+D90)/D93,"–") | F103: =IFERROR((D85+((D72*(1+0.02))/(C103-0.02))/(1+C103)^5+D89+D90)/D93,"–") | G103: =IFERROR((D85+((D72*(1+0.03))/(C103-0.03))/(1+C103)^5+D89+D90)/D93,"–") | H103: =IFERROR((D85+((D72*(1+0.04))/(C103-0.04))/(1+C103)^5+D89+D90)/D93,"–") | L103: g=3% (Base) | M103: =G101 | N103: =G102 | O103: =H103 | P103: =H104 | Q103: =H105
C104: =D66+0.01 | D104: =IFERROR((D85+((D72*(1+0))/(C104-0))/(1+C104)^5+D89+D90)/D93,"–") | E104: =IFERROR((D85+((D72*(1+0.01))/(C104-0.01))/(1+C104)^5+D89+D90)/D93,"–") | F104: =IFERROR((D85+((D72*(1+0.02))/(C104-0.02))/(1+C104)^5+D89+D90)/D93,"–") | G104: =IFERROR((D85+((D72*(1+0.03))/(C104-0.03))/(1+C104)^5+D89+D90)/D93,"–") | H104: =IFERROR((D85+((D72*(1+0.04))/(C104-0.04))/(1+C104)^5+D89+D90)/D93,"–") | L104: g=4% | M104: =H101 | N104: =H102
C105: =D66+0.02 | D105: =IFERROR((D85+((D72*(1+0))/(C105-0))/(1+C105)^5+D89+D90)/D93,"–") | E105: =IFERROR((D85+((D72*(1+0.01))/(C105-0.01))/(1+C105)^5+D89+D90)/D93,"–") | F105: =IFERROR((D85+((D72*(1+0.02))/(C105-0.02))/(1+C105)^5+D89+D90)/D93,"–") | G105: =IFERROR((D85+((D72*(1+0.03))/(C105-0.03))/(1+C105)^5+D89+D90)/D93,"–") | H105: =IFERROR((D85+((D72*(1+0.04))/(C105-0.04))/(1+C105)^5+D89+D90)/D93,"–")
B106: Yellow = Base Case (WACC = 10.4%, g = 3.0%)
B108: SCENARIO ANALYSIS — 3 SCENARIOS
B109: METRIC | E109: Pessimistic | F109: Realistic | G109: Optimistic
B110: Revenue Growth (Y1-Y5 avg.) | D110: =D29-0.03 | E110: =D29-0.02 | F110: =D29 | G110: =D29+0.02
B111: EBITDA Margin | D111: =IFERROR(D15/D9-0.03,"–") | E111: =IFERROR(H15/H9-0.02,"–") | F111: =IFERROR(H15/H9,"–") | G111: =IFERROR(H15/H9+0.02,"–")
B112: Terminal Growth Rate | D112: =D70-0.01 | E112: =D70-0.01 | F112: =D70 | G112: =D70+0.01
B113: WACC | D113: =D66+0.01 | E113: =D66+0.01 | F113: =D66 | G113: =D66-0.01
B114: Implied Share Price ($) | D114: =IFERROR((D85+((D72*(1+D112))/(D113-D112))/(1+D113)^5+D89+D90)/D93,"–") | E114: =IFERROR((D85+((D72*(1+E112))/(E113-E112))/(1+E113)^5+D89+D90)/D93,"–") | F114: =IFERROR((D85+((D72*(1+F112))/(F113-F112))/(1+F113)^5+D89+D90)/D93,"–") | G114: =IFERROR((D85+((D72*(1+G112))/(G113-G112))/(1+G113)^5+D89+D90)/D93,"–")
B116: © 2015 to 2024 FinSight
B117: This Excel model is for educational purposes only.
B118: https://finsight.com/
B120: UFCF Projection ($M) | C120: =TEXT(INPUT!D117+1,"0")&"F" | D120: =TEXT(INPUT!D117+2,"0")&"F" | E120: =TEXT(INPUT!D117+3,"0")&"F" | F120: =TEXT(INPUT!D117+4,"0")&"F" | G120: =TEXT(INPUT!D117+5,"0")&"F"
B121: UFCF | C121: =IF(I52=0,NA(),I52) | D121: =IF(J52=0,NA(),J52) | E121: =IF(K52=0,NA(),K52) | F121: =IF(L52=0,NA(),L52) | G121: =IF(M52=0,NA(),M52)
B123: Revenue Projection ($M) | C123: =IF(I9=0,NA(),C120) | D123: =IF(J9=0,NA(),D120) | E123: =IF(K9=0,NA(),E120) | F123: =IF(L9=0,NA(),F120) | G123: =IF(M9=0,NA(),G120)
B124: Revenue | C124: =IF(I9=0,NA(),I9) | D124: =IF(J9=0,NA(),J9) | E124: =IF(K9=0,NA(),K9) | F124: =IF(L9=0,NA(),L9) | G124: =IF(M9=0,NA(),M9)

Sheet SOTP
B1: FinSight | J1: SOTP — Sum-of-the-Parts Valuation
B2: SOTP
B3: All figures in USD millions unless stated | Segments: Upstream / iGRP (LNG+Gas) / Renewables & Power / Refining & Chemicals
B4: SEGMENT OVERVIEW | C4: Segment | D4: EBITDA ($M) | E4: EV/EBITDA (x) | F4: Implied EV ($M) | G4: % of Total EV
B6: 1. Exploration & Production (Upstream) | C6: Upstream | D6: 18500 | E6: 5.5 | F6: =D6*E6 | G6: =IFERROR(F6/F11,"–")
B7: 2. Integrated Gas, Renewables & Power (iGRP) | C7: iGRP / LNG | D7: 12000 | E7: 7.5 | F7: =D7*E7 | G7: =IFERROR(F7/F11,"–")
B8: 3. Renewables & Power (R&P) | C8: Renewables | D8: 2200 | E8: 12 | F8: =D8*E8 | G8: =IFERROR(F8/F11,"–")
B9: 4. Refining, Chemicals & Marketing (RCM) | C9: Refining | D9: 4500 | E9: 4 | F9: =D9*E9 | G9: =IFERROR(F9/F11,"–")
B10: 5. Corporate / Holding (Overhead & Eliminations) | C10: Corporate | D10: -2500 | E10: 5 | F10: =D10*E10 | G10: =IFERROR(F10/F11,"–")
B11: TOTAL GROSS ASSET VALUE (Sum of Parts) | F11: =SUM(F6:F10) | G11: =IFERROR(F11/F11,"–")
B13: BRIDGE TO EQUITY VALUE
B15: Total Gross Asset Value (Segment EV) | F15: =F11
B16: (-) Net Debt (LTM) | F16: =-(INPUT!H48+INPUT!H54-INPUT!H34)
B17: (+) Minorities & Hybrid Adj. (approx.) | F17: -8000
B18: IMPLIED EQUITY VALUE (SOTP) | F18: =F15+F16+F17
B20: Shares Outstanding (Diluted, M) | F20: =INPUT!H96
B21: IMPLIED SHARE PRICE (SOTP) ($) | F21: =IFERROR(F18/(F20),"–")
B22: Current Share Price ($) | F22: =INPUT!H95
B23: Implied Upside / (Downside) | F23: =IFERROR(F21/F22-1,"–")
B25: SENSITIVITY — Implied Share Price ($) vs Upstream EV/EBITDA & LNG EV/EBITDA
B26: LNG (iGRP) EV/EBITDA → | D26: 6 | E26: 7.5 | F26: 9
B27: Upstream (E6) ↓ | C27: 4.5 | D27: =IFERROR((D6*C27+D7*D26+F8+F9+F10+F16+F17)/(F20),"–") | E27: =IFERROR((D6*C27+D7*E26+F8+F9+F10+F16+F17)/(F20),"–") | F27: =IFERROR((D6*C27+D7*F26+F8+F9+F10+F16+F17)/(F20),"–")
C28: 5.5 | D28: =IFERROR((D6*C28+D7*D26+F8+F9+F10+F16+F17)/(F20),"–") | E28: =IFERROR((D6*C28+D7*E26+F8+F9+F10+F16+F17)/(F20),"–") | F28: =IFERROR((D6*C28+D7*F26+F8+F9+F10+F16+F17)/(F20),"–")
C29: 6.5 | D29: =IFERROR((D6*C29+D7*D26+F8+F9+F10+F16+F17)/(F20),"–") | E29: =IFERROR((D6*C29+D7*E26+F8+F9+F10+F16+F17)/(F20),"–") | F29: =IFERROR((D6*C29+D7*F26+F8+F9+F10+F16+F17)/(F20),"–")
B32: METHODOLOGY NOTES
B33: (1) EBITDA by segment are estimates based on TTE Factbook 2024 & analyst consensus. Update D6:D10 with actual reported segment EBITDA when available.
B34: (2) EV/EBITDA multiples sourced from Bloomberg sector comparables (E&P peers, LNG peers, Renewables peers, Refining peers).
B35: (3) Net Debt linked to INPUT LTM Balance Sheet (ST Debt + LT Debt - Cash). Minorities adj. ($8B) is an estimate.
B36: (4) Sensitivity table (rows 27-29): Yellow = base case (Upstream 5.5x / LNG 7.5x). Adjust inputs in D6:E10.
B38: © 2015 to 2024 FinSight
B39: This Excel model is for educational purposes only.
B40: https://finsight.com/

Sheet COMPARABLES
B1: FinSight | K1: COMPARABLES — Trading Comparables
B3: COMPARABLES
B4: All figures in USD millions unless stated
B6: COMPARABLE TRADING ANALYSIS
D7: Share Price | E7: Enterprise Value | F7: Revenue (LTM) | G7: EBITDAX (LTM) | H7: EV / EBITDA | I7: EV / Revenue | J7: EPS (LTM) | K7: P / E (LTM)
B8: PEER COMPANIES | C8: TICKER | D8: (USD/sh) | E8: ($M) | F8: ($M) | G8: ($M) | H8: (x) | I8: (x) | J8: (USD/sh) | K8: (x)
B9: XOM | C9: XOM | D9: 75.33 | E9: 173303.61 | F9: 185019.01 | G9: 17629 | H9: =IFERROR(E9/G9,"–") | I9: =IFERROR(E9/F9,"–") | J9: 15.98 | K9: =IFERROR(D9/J9,"–")
B10: SHEL.L | C10: SHEL.L | D10: 11.62 | E10: 183371.55 | F10: 187267.01 | G10: 5393 | H10: =IFERROR(E10/G10,"–") | I10: =IFERROR(E10/F10,"–") | J10: 10.81 | K10: =IFERROR(D10/J10,"–")
B11: BP.L | C11: BP.L | D11: 525.72 | E11: 1333326.9 | F11: 200966 | G11: 101892 | H11: =IFERROR(E11/G11,"–") | I11: =IFERROR(E11/F11,"–") | J11: 23.5 | K11: =IFERROR(D11/J11,"–")
B12: ENI.MI | C12: ENI.MI | D12: 78.46 | E12: 144410 | F12: 133453 | G12: 15742 | H12: =IFERROR(E12/G12,"–") | I12: =IFERROR(E12/F12,"–") | J12: 1.3 | K12: =IFERROR(D12/J12,"–")
B13: REP.MC | C13: REP.MC | D13: 87.8 | E13: 258704.92 | F13: 321913 | G13: 24292 | H13: =IFERROR(E13/G13,"–") | I13: =IFERROR(E13/F13,"–") | K13: =IFERROR(D13/J13,"–")
B15: Mean | D15: =IFERROR(AVERAGE(D9:D13),"–") | E15: =IFERROR(AVERAGE(E9:E13),"–") | F15: =IFERROR(AVERAGE(F9:F13),"–") | G15: =IFERROR(AVERAGE(G9:G13),"–") | H15: =IFERROR(AVERAGE(H9:H13),"–") | I15: =IFERROR(AVERAGE(I9:I13),"–") | J15: =IFERROR(AVERAGE(J9:J13),"–") | K15: =IFERROR(AVERAGE(K9:K13),"–")
B16: Median | D16: =IFERROR(MEDIAN(D9:D13),"–") | E16: =IFERROR(MEDIAN(E9:E13),"–") | F16: =IFERROR(MEDIAN(F9:F13),"–") | G16: =IFERROR(MEDIAN(G9:G13),"–") | H16: =IFERROR(MEDIAN(H9:H13),"–") | I16: =IFERROR(MEDIAN(I9:I13),"–") | J16: =IFERROR(MEDIAN(J9:J13),"–") | K16: =IFERROR(MEDIAN(K9:K13),"–")
B17: Maximum | D17: =IFERROR(MAX(D9:D13),"–") | E17: =IFERROR(MAX(E9:E13),"–") | F17: =IFERROR(MAX(F9:F13),"–") | G17: =IFERROR(MAX(G9:G13),"–") | H17: =IFERROR(MAX(H9:H13),"–") | I17: =IFERROR(MAX(I9:I13),"–") | J17: =IFERROR(MAX(J9:J13),"–") | K17: =IFERROR(MAX(K9:K13),"–")
B18: Minimum | D18: =IFERROR(MIN(D9:D13),"–") | E18: =IFERROR(MIN(E9:E13),"–") | F18: =IFERROR(MIN(F9:F13),"–") | G18: =IFERROR(MIN(G9:G13),"–") | H18: =IFERROR(MIN(H9:H13),"–") | I18: =IFERROR(MIN(I9:I13),"–") | J18: =IFERROR(MIN(J9:J13),"–") | K18: =IFERROR(MIN(K9:K13),"–")
B20: TARGET COMPANY VALUATION (Based on Peer Multiples)
B21: TARGET COMPANY METRICS (from INPUT) | D21: =INPUT!H5
B22: Target: Revenue (LTM) | C22: ($M) | D22: =INPUT!H9/1000
B23: Target: EBITDAX (LTM) | C23: ($M) | D23: =INPUT!H30/1000
B24: Target: DACF (LTM) | C24: ($) | D24: =IFERROR(INPUT!H75+ABS(INPUT!H20)*(1-INPUT!H104),"–")
B25: Target: Net Debt | C25: ($M) | D25: =IFERROR((INPUT!H54+INPUT!H55-INPUT!H34)/1000,"–")
B26: Target: Shares Outstanding | C26: (M) | D26: =INPUT!H96/1000
B28: IMPLIED VALUATION
B29: EV / EBITDAX — Implied EV ($M) | D29: =IFERROR(D23*H18,"–") | E29: =IFERROR(D23*H15,"–") | F29: =IFERROR(D23*H16,"–") | G29: =IFERROR(D23*H17,"–")
B30: EV / DACF — Implied EV ($M) | D30: =IFERROR(D22*I18,"–") | E30: =IFERROR(D22*I15,"–") | F30: =IFERROR(D22*I16,"–") | G30: =IFERROR(D22*I17,"–")
B31: P/E — Implied Equity Value ($M) | D31: =IFERROR(D24*K18*D26,"–") | E31: =IFERROR(D24*K15*D26,"–") | F31: =IFERROR(D24*K16*D26,"–") | G31: =IFERROR(D24*K17*D26,"–")
B33: Implied Enterprise Value (Average of 3 Methods) | C33: ($M) | D33: =IFERROR(AVERAGE(D29,D30),"–") | E33: =IFERROR(AVERAGE(E29,E30),"–") | F33: =IFERROR(AVERAGE(F29,F30),"–") | G33: =IFERROR(AVERAGE(G29,G30),"–")
B34: (-) Net Debt | C34: ($M) | D34: =D25 | E34: =D25 | F34: =D25 | G34: =D25
B35: Implied Equity Value ($M) | C35: ($M) | D35: =IFERROR(D33-D34,"–") | E35: =IFERROR(E33-E34,"–") | F35: =IFERROR(F33-F34,"–") | G35: =IFERROR(G33-G34,"–")
B36: Implied Share Price ($) | C36: ($) | D36: =IFERROR(D35/D26,"–") | E36: =IFERROR(E35/D26,"–") | F36: =IFERROR(F35/D26,"–") | G36: =IFERROR(G35/D26,"–")
B37: Current Share Price ($) | C37: ($) | D37: =INPUT!H95 | E37: =INPUT!H95 | F37: =INPUT!H95 | G37: =INPUT!H95
B38: Implied Upside / (Downside) | C38: (%) | D38: =IFERROR(D36/D37-1,"–") | E38: =IFERROR(E36/D37-1,"–") | F38: =IFERROR(F36/D37-1,"–") | G38: =IFERROR(G36/D37-1,"–")
B41: (1) Target company EV based on LTM EV/EBITDA and EV/Revenue multiples relative to comparable peer set.
B43: © 2015 to 2024 FinSight
B44: This Excel model is for educational purposes only.
B45: https://finsight.com/
B47: Company | C47: EV/EBITDA (x) | D47: EV/Revenue (x) | E47: P/E (x)
B48: =B9 | C48: =IFERROR(H9*1,0) | D48: =IFERROR(I9*1,0) | E48: =IFERROR(K9*1,0)
B49: =B10 | C49: =IFERROR(H10*1,0) | D49: =IFERROR(I10*1,0) | E49: =IFERROR(K10*1,0)
B50: =B11 | C50: =IFERROR(H11*1,0) | D50: =IFERROR(I11*1,0) | E50: =IFERROR(K11*1,0)
B51: =B12 | C51: =IFERROR(H12*1,0) | D51: =IFERROR(I12*1,0) | E51: =IFERROR(K12*1,0)
B52: =B13 | C52: =IFERROR(H13*1,0) | D52: =IFERROR(I13*1,0) | E52: =IFERROR(K13*1,0)
B53: =B15 | C53: =IFERROR(H15*1,0) | D53: =IFERROR(I15*1,0) | E53: =IFERROR(K15*1,0)
B54: Implied Share Price — Valuation Range ($) | H54: Method | I54: Low ($) | J54: High ($) | K54: Current ($)
B55: Method | C55: Low ($) | D55: Median ($) | E55: High ($) | H55: EV/EBITDA | I55: =IFERROR(D36,0) | J55: =IFERROR(G36,0) | K55: =INPUT!H95
B56: =B29 | C56: =IFERROR(D36,"–") | D56: =IFERROR(F36,"–") | E56: =IFERROR(G36,"–") | H56: EV/Revenue | I56: =IFERROR(D36,0) | J56: =IFERROR(G36,0) | K56: =INPUT!H95
B57: =B30 | C57: =IFERROR(D36,"–") | D57: =IFERROR(F36,"–") | E57: =IFERROR(G36,"–") | F57: vé | H57: P/E | I57: =IFERROR(D36,0) | J57: =IFERROR(G36,0) | K57: =INPUT!H95

Sheet SCENARIOS
B1: FinSight | H1: SCENARIOS — Scenario Analysis
B3: SCENARIOS
B4: All figures in USD millions unless stated | 3 scenarios: Pessimistic / Realistic (Base) / Optimistic
B5: METRIC | E5: =TEXT(INPUT!D117-3,"0") | F5: =TEXT(INPUT!D117-2,"0") | G5: =TEXT(INPUT!D117-1,"0") | H5: =INPUT!D117&" (LTM)" | I5: =TEXT(INPUT!D117+1,"0")&"F" | J5: =TEXT(INPUT!D117+2,"0")&"F" | K5: =TEXT(INPUT!D117+3,"0")&"F" | L5: =TEXT(INPUT!D117+4,"0")&"F" | M5: =TEXT(INPUT!D117+5,"0")&"F"
B6: ▶ SELECT SCENARIO | D6: Realistic
B7: DRIVER | D7: Pessimistic | E7: Realistic | F7: Optimistic
B8: Revenue Growth Rate (Y1-Y5) | D8: {=IFERROR(INDEX(SECTOR_REF!$C$2:$E$71,MATCH(1,(SECTOR_REF!$A$2:$A$71=INPUT!$D$116)*(SECTOR_REF!$B$2:$B$71="Revenue Growth Rate (Y1-Y5)"),0),MATCH("Pessimiste",{"Pessimiste","Realiste","Optimiste"},0)),IFERROR(INPUT!H9/INPUT!G9-1,0.02))} | E8: {=IFERROR(INDEX(SECTOR_REF!$C$2:$E$71,MATCH(1,(SECTOR_REF!$A$2:$A$71=INPUT!$D$116)*(SECTOR_REF!$B$2:$B$71="Revenue Growth Rate (Y1-Y5)"),0),MATCH("Realiste",{"Pessimiste","Realiste","Optimiste"},0)),IFERROR(INPUT!H9/INPUT!G9-1,0.05))} | F8: {=IFERROR(INDEX(SECTOR_REF!$C$2:$E$71,MATCH(1,(SECTOR_REF!$A$2:$A$71=INPUT!$D$116)*(SECTOR_REF!$B$2:$B$71="Revenue Growth Rate (Y1-Y5)"),0),MATCH("Optimiste",{"Pessimiste","Realiste","Optimiste"},0)),IFERROR(INPUT!H9/INPUT!G9-1,0.09))}
B9: EBITDA Margin (UTILITY) | D9: {=IFERROR(INDEX(SECTOR_REF!$C$2:$E$71,MATCH(1,(SECTOR_REF!$A$2:$A$71=INPUT!$D$116)*(SECTOR_REF!$B$2:$B$71="Gross Margin"),0),MATCH("Pessimiste",{"Pessimiste","Realiste","Optimiste"},0)),IFERROR(INPUT!H11/INPUT!H9,0.4)-0.03)} | E9: {=IFERROR(INDEX(SECTOR_REF!$C$2:$E$71,MATCH(1,(SECTOR_REF!$A$2:$A$71=INPUT!$D$116)*(SECTOR_REF!$B$2:$B$71="Gross Margin"),0),MATCH("Realiste",{"Pessimiste","Realiste","Optimiste"},0)),IFERROR(INPUT!H11/INPUT!H9,0.4))} | F9: {=IFERROR(INDEX(SECTOR_REF!$C$2:$E$71,MATCH(1,(SECTOR_REF!$A$2:$A$71=INPUT!$D$116)*(SECTOR_REF!$B$2:$B$71="Gross Margin"),0),MATCH("Optimiste",{"Pessimiste","Realiste","Optimiste"},0)),IFERROR(INPUT!H11/INPUT!H9,0.4)+0.03)}
B10: EBITDA Margin | D10: {=IFERROR(INDEX(SECTOR_REF!$C$2:$E$71,MATCH(1,(SECTOR_REF!$A$2:$A$71=INPUT!$D$116)*(SECTOR_REF!$B$2:$B$71="EBITDA Margin"),0),MATCH("Pessimiste",{"Pessimiste","Realiste","Optimiste"},0)),IFERROR(INPUT!H30/INPUT!H9,0.15)-0.03)} | E10: {=IFERROR(INDEX(SECTOR_REF!$C$2:$E$71,MATCH(1,(SECTOR_REF!$A$2:$A$71=INPUT!$D$116)*(SECTOR_REF!$B$2:$B$71="EBITDA Margin"),0),MATCH("Realiste",{"Pessimiste","Realiste","Optimiste"},0)),IFERROR(INPUT!H30/INPUT!H9,0.15))} | F10: {=IFERROR(INDEX(SECTOR_REF!$C$2:$E$71,MATCH(1,(SECTOR_REF!$A$2:$A$71=INPUT!$D$116)*(SECTOR_REF!$B$2:$B$71="EBITDA Margin"),0),MATCH("Optimiste",{"Pessimiste","Realiste","Optimiste"},0)),IFERROR(INPUT!H30/INPUT!H9,0.15)+0.03)}
B11: Terminal Growth Rate | D11: {=IFERROR(INDEX(SECTOR_REF!$C$2:$E$71,MATCH(1,(SECTOR_REF!$A$2:$A$71=INPUT!$D$116)*(SECTOR_REF!$B$2:$B$71="Terminal Growth Rate"),0),MATCH("Pessimiste",{"Pessimiste","Realiste","Optimiste"},0)),DCF!D70-0.01)} | E11: {=IFERROR(INDEX(SECTOR_REF!$C$2:$E$71,MATCH(1,(SECTOR_REF!$A$2:$A$71=INPUT!$D$116)*(SECTOR_REF!$B$2:$B$71="Terminal Growth Rate"),0),MATCH("Realiste",{"Pessimiste","Realiste","Optimiste"},0)),DCF!D70)} | F11: {=IFERROR(INDEX(SECTOR_REF!$C$2:$E$71,MATCH(1,(SECTOR_REF!$A$2:$A$71=INPUT!$D$116)*(SECTOR_REF!$B$2:$B$71="Terminal Growth Rate"),0),MATCH("Optimiste",{"Pessimiste","Realiste","Optimiste"},0)),DCF!D70+0.01)}
B12: WACC | D12: {=IFERROR(INDEX(SECTOR_REF!$C$2:$E$71,MATCH(1,(SECTOR_REF!$A$2:$A$71=INPUT!$D$116)*(SECTOR_REF!$B$2:$B$71="WACC"),0),MATCH("Pessimiste",{"Pessimiste","Realiste","Optimiste"},0)),DCF!D66+0.015)} | E12: {=IFERROR(INDEX(SECTOR_REF!$C$2:$E$71,MATCH(1,(SECTOR_REF!$A$2:$A$71=INPUT!$D$116)*(SECTOR_REF!$B$2:$B$71="WACC"),0),MATCH("Realiste",{"Pessimiste","Realiste","Optimiste"},0)),DCF!D66)} | F12: {=IFERROR(INDEX(SECTOR_REF!$C$2:$E$71,MATCH(1,(SECTOR_REF!$A$2:$A$71=INPUT!$D$116)*(SECTOR_REF!$B$2:$B$71="WACC"),0),MATCH("Optimiste",{"Pessimiste","Realiste","Optimiste"},0)),DCF!D66-0.015)}
B13: ▶ Secteur actif : | D13: =IF(INPUT!$D$116="","— Aucun secteur sélectionné (INPUT!D116) —",INPUT!$D$116)
B14: SCENARIO RESULTS — DYNAMIC VIEW
B15: METRIC | D15: =TEXT(INPUT!D117-3,"0") | E15: =TEXT(INPUT!D117-2,"0") | F15: =TEXT(INPUT!D117-1,"0") | G15: =INPUT!D117&" (LTM)" | H15: =TEXT(INPUT!D117+1,"0")&"F" | I15: =TEXT(INPUT!D117+2,"0")&"F" | J15: =TEXT(INPUT!D117+3,"0")&"F" | K15: =TEXT(INPUT!D117+4,"0")&"F" | L15: =TEXT(INPUT!D117+5,"0")&"F"
B16: Revenue | D16: =INPUT!E9 | E16: =INPUT!F9 | F16: =INPUT!G9 | G16: =INPUT!H9 | H16: =INPUT!H9*(1+IF($D$6="Pessimistic",$D$8,IF($D$6="Realistic",$E$8,$F$8))) | I16: =H16*(1+IF($D$6="Pessimistic",$D$8,IF($D$6="Realistic",$E$8,$F$8))) | J16: =I16*(1+IF($D$6="Pessimistic",$D$8,IF($D$6="Realistic",$E$8,$F$8))) | K16: =J16*(1+IF($D$6="Pessimistic",$D$8,IF($D$6="Realistic",$E$8,$F$8))) | L16: =K16*(1+IF($D$6="Pessimistic",$D$8,IF($D$6="Realistic",$E$8,$F$8)))
B17: Gross Profit | D17: =INPUT!E11 | E17: =INPUT!F11 | F17: =INPUT!G11 | G17: =INPUT!H11 | H17: =H16*IF($D$6="Pessimistic",$D$9,IF($D$6="Realistic",$E$9,$F$9)) | I17: =I16*IF($D$6="Pessimistic",$D$9,IF($D$6="Realistic",$E$9,$F$9)) | J17: =J16*IF($D$6="Pessimistic",$D$9,IF($D$6="Realistic",$E$9,$F$9)) | K17: =K16*IF($D$6="Pessimistic",$D$9,IF($D$6="Realistic",$E$9,$F$9)) | L17: =L16*IF($D$6="Pessimistic",$D$9,IF($D$6="Realistic",$E$9,$F$9))
B18: EBITDA (EBITDAX) | D18: =INPUT!E30 | E18: =INPUT!F30 | F18: =INPUT!G30 | G18: =INPUT!H30 | H18: =H16*IF($D$6="Pessimistic",$D$10,IF($D$6="Realistic",$E$10,$F$10)) | I18: =I16*IF($D$6="Pessimistic",$D$10,IF($D$6="Realistic",$E$10,$F$10)) | J18: =J16*IF($D$6="Pessimistic",$D$10,IF($D$6="Realistic",$E$10,$F$10)) | K18: =K16*IF($D$6="Pessimistic",$D$10,IF($D$6="Realistic",$E$10,$F$10)) | L18: =L16*IF($D$6="Pessimistic",$D$10,IF($D$6="Realistic",$E$10,$F$10))
B19: Net Income | D19: =INPUT!E26 | E19: =INPUT!F26 | F19: =INPUT!G26 | G19: =INPUT!H26 | H19: =H18*0.6 | I19: =I18*0.6 | J19: =J18*0.6 | K19: =K18*0.6 | L19: =L18*0.6
B20: Free Cash Flow (Est.) | D20: =IFERROR(INPUT!E75+INPUT!E78,"–") | E20: =IFERROR(INPUT!F75+INPUT!F78,"–") | F20: =IFERROR(INPUT!G75+INPUT!G78,"–") | G20: =IFERROR(INPUT!H75+INPUT!H78,"–") | H20: =H18*0.5 | I20: =I18*0.5 | J20: =J18*0.5 | K20: =K18*0.5 | L20: =L18*0.5
B21: EBITDA Margin | D21: =IFERROR(INPUT!E30/INPUT!E9,"–") | E21: =IFERROR(INPUT!F30/INPUT!F9,"–") | F21: =IFERROR(INPUT!G30/INPUT!G9,"–") | G21: =IFERROR(INPUT!H30/INPUT!H9,"–") | H21: =IFERROR(H18/H16,"–") | I21: =IFERROR(I18/I16,"–") | J21: =IFERROR(J18/J16,"–") | K21: =IFERROR(K18/K16,"–") | L21: =IFERROR(L18/L16,"–")
B22: Implied Share Price | M22: =IFERROR("$"&TEXT(IF($D$6="Pessimistic",DCF!D94*(1+$D$8+$D$10-$E$8-$E$10)*0.8,IF($D$6="Realistic",DCF!D94,DCF!D94*(1+$F$8+$F$10-$E$8-$E$10)*1.2)),"#,##0.00"),"–")
B24: SCENARIO SUMMARY COMPARISON
B25: METRIC (Year 5) | D25: Pessimistic | E25: Realistic | F25: Optimistic
B26: Revenue (Year 5) | C26: 0 | D26: =INPUT!H9*(1+$D$8)^5 | E26: =INPUT!H9*(1+$E$8)^5 | F26: =INPUT!H9*(1+$F$8)^5
B27: EBITDA (Year 5) | C27: 0 | D27: =D26*$D$10 | E27: =E26*$E$10 | F27: =F26*$F$10
B28: Net Income (Year 5) | C28: 0 | D28: =D27*0.6 | E28: =E27*0.6 | F28: =F27*0.6
B29: FCF (Year 5) | C29: 0 | D29: =D27*0.5 | E29: =E27*0.5 | F29: =F27*0.5
B30: EBITDA Margin (Year 5) | D30: =$D$10 | E30: =$E$10 | F30: =$F$10
B31: Implied Share Price | D31: =IFERROR("$"&TEXT(DCF!D94*(1+$D$8+$D$10-$E$8-$E$10)*0.8,"#,##0.00"),"–") | E31: =IFERROR("$"&TEXT(DCF!D94,"#,##0.00"),"–") | F31: =IFERROR("$"&TEXT(DCF!D94*(1+$F$8+$F$10-$E$8-$E$10)*1.2,"#,##0.00"),"–")
B32: Delta (Opt. vs Pess.) | D32: ="—" | E32: ="—" | F32: =IFERROR(F26/D26-1,"–")
B33: Revenue
B34: ="▶ SCÉNARIO SÉLECTIONNÉ : "&$D$6
B36: CHART DATA: Revenue by Scenario
B37: Year | D37: =TEXT(INPUT!D117+1,"0")&"F" | E37: =TEXT(INPUT!D117+2,"0")&"F" | F37: =TEXT(INPUT!D117+3,"0")&"F" | G37: =TEXT(INPUT!D117+4,"0")&"F" | H37: =TEXT(INPUT!D117+5,"0")&"F"
B38: Pessimistic | D38: =IF(INPUT!H9="",NA(),INPUT!H9*(1+$D$8)) | E38: =IF(INPUT!H9="",NA(),D38*(1+$D$8)) | F38: =IF(INPUT!H9="",NA(),E38*(1+$D$8)) | G38: =IF(INPUT!H9="",NA(),F38*(1+$D$8)) | H38: =IF(INPUT!H9="",NA(),G38*(1+$D$8))
B39: Realistic | D39: =IF(INPUT!H9="",NA(),INPUT!H9*(1+$E$8)) | E39: =IF(INPUT!H9="",NA(),D39*(1+$E$8)) | F39: =IF(INPUT!H9="",NA(),E39*(1+$E$8)) | G39: =IF(INPUT!H9="",NA(),F39*(1+$E$8)) | H39: =IF(INPUT!H9="",NA(),G39*(1+$E$8))
B40: Optimistic | D40: =IF(INPUT!H9="",NA(),INPUT!H9*(1+$F$8)) | E40: =IF(INPUT!H9="",NA(),D40*(1+$F$8)) | F40: =IF(INPUT!H9="",NA(),E40*(1+$F$8)) | G40: =IF(INPUT!H9="",NA(),F40*(1+$F$8)) | H40: =IF(INPUT!H9="",NA(),G40*(1+$F$8))
B41: SCENARIO SUMMARY COMPARISON
B42: CHART DATA: EBITDA by Scenario
B43: Year | D43: =TEXT(INPUT!D117+1,"0")&"F" | E43: =TEXT(INPUT!D117+2,"0")&"F" | F43: =TEXT(INPUT!D117+3,"0")&"F" | G43: =TEXT(INPUT!D117+4,"0")&"F" | H43: =TEXT(INPUT!D117+5,"0")&"F"
B44: Pessimistic | D44: =IF(D38=0,0,D38*$D$10) | E44: =IF(E38=0,0,E38*$D$10) | F44: =IF(F38=0,0,F38*$D$10) | G44: =IF(G38=0,0,G38*$D$10) | H44: =IF(H38=0,0,H38*$D$10)
B45: Realistic | D45: =IF(D39=0,0,D39*$E$10) | E45: =IF(E39=0,0,E39*$E$10) | F45: =IF(F39=0,0,F39*$E$10) | G45: =IF(G39=0,0,G39*$E$10) | H45: =IF(H39=0,0,H39*$E$10)
B46: Optimistic | D46: =IF(D40=0,0,D40*$F$10) | E46: =IF(E40=0,0,E40*$F$10) | F46: =IF(F40=0,0,F40*$F$10) | G46: =IF(G40=0,0,G40*$F$10) | H46: =IF(H40=0,0,H40*$F$10)
B47: EBITDA Margin (Year 5) | E47: =IFERROR(H44/H38,"–") | F47: =IFERROR(H45/H39,"–") | G47: =IFERROR(H46/H40,"–")
B48: Implied Share Price | E48: =IFERROR("$"&TEXT(DCF!D94*(1+$D$8+$D$10-$E$8-$E$10)*0.8,"#,##0.00"),"–") | F48: =IFERROR("$"&TEXT(DCF!D94,"#,##0.00"),"–") | G48: =IFERROR("$"&TEXT(DCF!D94*(1+$F$8+$F$10-$E$8-$E$10)*1.2,"#,##0.00"),"–")
B50: CHARTS: Revenue & FCF by scenario (insert chart using Scenarios data above D16:I16, D25:I25, D34:I34 for Revenue)
B52: © 2015 to 2024 FinSight
B53: This Excel model is for educational purposes only.
B54: https://finsight.com/
B56: Chart Data: Revenue by Scenario | C56: =INPUT!D117+1 | D56: =INPUT!D117+2 | E56: =INPUT!D117+3 | F56: =INPUT!D117+4 | G56: =INPUT!D117+5
B57: Pessimistic | C57: =IF(INPUT!H9="",NA(),INPUT!H9*(1+$D$8)) | D57: =IF(INPUT!H9="",NA(),C57*(1+$D$8)) | E57: =IF(INPUT!H9="",NA(),D57*(1+$D$8)) | F57: =IF(INPUT!H9="",NA(),E57*(1+$D$8)) | G57: =IF(INPUT!H9="",NA(),F57*(1+$D$8))
B58: Realistic | C58: =IF(INPUT!H9="",NA(),INPUT!H9*(1+$E$8)) | D58: =IF(INPUT!H9="",NA(),C58*(1+$E$8)) | E58: =IF(INPUT!H9="",NA(),D58*(1+$E$8)) | F58: =IF(INPUT!H9="",NA(),E58*(1+$E$8)) | G58: =IF(INPUT!H9="",NA(),F58*(1+$E$8))
B59: Optimistic | C59: =IF(INPUT!H9="",NA(),INPUT!H9*(1+$F$8)) | D59: =IF(INPUT!H9="",NA(),C59*(1+$F$8)) | E59: =IF(INPUT!H9="",NA(),D59*(1+$F$8)) | F59: =IF(INPUT!H9="",NA(),E59*(1+$F$8)) | G59: =IF(INPUT!H9="",NA(),F59*(1+$F$8))
B61: Chart Data: EBITDA by Scenario | C61: =INPUT!D117+1 | D61: =INPUT!D117+2 | E61: =INPUT!D117+3 | F61: =INPUT!D117+4 | G61: =INPUT!D117+5
B62: Pessimistic | C62: =IF(INPUT!H9="",NA(),INPUT!H9*(1+$D$8)*$D$10) | D62: =IF(INPUT!H9="",NA(),C57*(1+$D$8)*$D$10) | E62: =IF(INPUT!H9="",NA(),D57*(1+$D$8)*$D$10) | F62: =IF(INPUT!H9="",NA(),E57*(1+$D$8)*$D$10) | G62: =IF(INPUT!H9="",NA(),F57*(1+$D$8)*$D$10)
B63: Realistic | C63: =IF(INPUT!H9="",NA(),INPUT!H9*(1+$E$8)*$E$10) | D63: =IF(INPUT!H9="",NA(),C58*(1+$E$8)*$E$10) | E63: =IF(INPUT!H9="",NA(),D58*(1+$E$8)*$E$10) | F63: =IF(INPUT!H9="",NA(),E58*(1+$E$8)*$E$10) | G63: =IF(INPUT!H9="",NA(),F58*(1+$E$8)*$E$10)
B64: Optimistic | C64: =IF(INPUT!H9="",NA(),INPUT!H9*(1+$F$8)*$F$10) | D64: =IF(INPUT!H9="",NA(),C59*(1+$F$8)*$F$10) | E64: =IF(INPUT!H9="",NA(),D59*(1+$F$8)*$F$10) | F64: =IF(INPUT!H9="",NA(),E59*(1+$F$8)*$F$10) | G64: =IF(INPUT!H9="",NA(),F59*(1+$F$8)*$F$10)

Sheet DASHBOARD
B1: FinSight | Q1: Année | R1: 2022 | S1: 2023 | T1: 2024
Q2: Année | R2: Cumul Revenue | S2: =RATIOS!F80 | T2: =RATIOS!G80
B3: Financial Performance | Q3: 2022 | R3: =RATIOS!E80
B4: ="All figures in "&INPUT!D118&" "&INPUT!D119&" unless stated" | Q4: 2023 | R4: =RATIOS!F80
Q5: 2024 | R5: =RATIOS!G80
Q6: Year
B7: Revenue & Profitability | H7: Profit Margins | Q7: 2022 | R7: Revenue | S7: Net Income | T7: Net Margin
Q8: 2023 | R8: =RATIOS!E77 | S8: =RATIOS!E79 | T8: =RATIOS!E84
Q9: 2024 | R9: =RATIOS!F77 | S9: =RATIOS!F79 | T9: =RATIOS!F84
Q10: 2025 (LTM) | R10: =RATIOS!G77 | S10: =RATIOS!G79 | T10: =RATIOS!G84
R11: =RATIOS!H77 | S11: =RATIOS!H79 | T11: =RATIOS!H84
B24: Cumulative revenue | H24: Expense Breakdown
B41: Performance Summary (Five-Year) | H41: Income Statement (LTM)
C43: 5-Yr Avg | D43: Trend | I43: Actual | J43: Prev Year | K43: Variance | L43: Var %
B44: Revenue | C44: =AVERAGE(INPUT!D9:H9) | D44: =IF(INPUT!H9>INPUT!G9,"▲",IF(INPUT!H9<INPUT!G9,"▼","→")) | H44: Revenue | I44: =INPUT!H9 | J44: =INPUT!G9 | K44: =I44-J44 | L44: =IF(J44=0,NA(),K44/ABS(J44))
B46: COGS | C46: =ABS(AVERAGE(INPUT!D10:H10)) | D46: =IF(ABS(INPUT!H10)<ABS(INPUT!G10),"▲",IF(ABS(INPUT!H10)>ABS(INPUT!G10),"▼","→")) | H46: COGS | I46: =ABS(INPUT!H10) | J46: =ABS(INPUT!G10) | K46: =I46-J46 | L46: =IF(J46=0,NA(),K46/ABS(J46))
B48: Expenses | C48: =ABS(AVERAGE(INPUT!D13:H13)) | D48: =IF(ABS(INPUT!H13)<ABS(INPUT!G13),"▲",IF(ABS(INPUT!H13)>ABS(INPUT!G13),"▼","→")) | H48: Expenses | I48: =ABS(INPUT!H13) | J48: =ABS(INPUT!G13) | K48: =I48-J48 | L48: =IF(J48=0,NA(),K48/ABS(J48))
B50: Net Income | C50: =AVERAGE(INPUT!D26:H26) | D50: =IF(INPUT!H26>INPUT!G26,"▲",IF(INPUT!H26<INPUT!G26,"▼","→")) | H50: Net Income | I50: =INPUT!H26 | J50: =INPUT!G26 | K50: =I50-J50 | L50: =IF(J50=0,NA(),K50/ABS(J50))
B52: Net Margin (%) | C52: =AVERAGE(INPUT!D26:H26)/AVERAGE(INPUT!D9:H9) | D52: =IF(INPUT!H26/INPUT!H9>INPUT!G26/INPUT!G9,"▲",IF(INPUT!H26/INPUT!H9<INPUT!G26/INPUT!G9,"▼","→")) | H52: Net Margin (%) | I52: =INPUT!H26/INPUT!H9 | J52: =INPUT!G26/INPUT!G9 | K52: =I52-J52 | L52: =IF(J52=0,NA(),K52/ABS(J52))
B54: MÉTRIQUES UTILITY (LTM)
B55: EV/EBITDA | C55: =IFERROR(INPUT!H98/INPUT!H30,NA()) | D55: Bmk : 8-11x • Prime si croissance RAB
B56: Dividend Yield | C56: =IFERROR(ABS(INPUT!H85)/INPUT!H97,NA()) | D56: Bmk : 3-5% • Clé utility
B58: P&L Summary (LTM) | H58: Balance Sheet Summary (LTM)
D60: =INPUT!G5 | E60: =INPUT!H5 | J60: =INPUT!G5 | K60: =INPUT!H5 | S60: =INPUT!G9 | T60: =INPUT!H9
H61: Assets
B62: COGS | D62: =-ABS(INPUT!G10) | E62: =-ABS(INPUT!H10) | H62: Current Assets | J62: =INPUT!G38 | K62: =INPUT!H38
B63: Gross Profit | D63: =S60+D62 | E63: =T60+E62 | H63: Non-current Assets | J63: =SUM(INPUT!G41:G43) | K63: =SUM(INPUT!H41:H43)
B64: SG&A | D64: =-ABS(INPUT!G14) | E64: =-ABS(INPUT!H14)
B65: R&D | D65: =-ABS(INPUT!G15) | E65: =-ABS(INPUT!H15) | H65: Total Assets | J65: =INPUT!G44 | K65: =INPUT!H44
B66: D&A | D66: =-ABS(INPUT!G16) | E66: =-ABS(INPUT!H16)
B67: EBIT (Operating Profit) | D67: =D63+D64+D65+D66 | E67: =E63+E64+E65+E66 | H67: Liabilities
B68: Net Interest | D68: =-ABS(INPUT!G20) | E68: =-ABS(INPUT!H20) | H68: Current Liabilities | J68: =INPUT!G51 | K68: =INPUT!H51
B69: EBT (Pre-Tax Income) | D69: =D67+D68 | E69: =E67+E68 | H69: Long-term Liabilities | J69: =INPUT!G54 | K69: =INPUT!H54
B70: Income Tax | D70: =-ABS(INPUT!G21) | E70: =-ABS(INPUT!H21) | H70: Total Liabilities | J70: =INPUT!G55 | K70: =INPUT!H55
B71: Net Income | D71: =D69+D70 | E71: =E69+E70 | H71: Shareholders' Equity | J71: =INPUT!G60 | K71: =INPUT!H60
B72: EBITDA | D72: =D67+ABS(D66) | E72: =E67+ABS(E66) | H72: Total Liabilities & Equity | J72: =INPUT!G63 | K72: =INPUT!H63
G82: =INPUT!H5 | I82: =IF(INPUT!D5="",NA(),INPUT!D5) | J82: =INPUT!E5 | K82: =INPUT!F5 | L82: =INPUT!G5 | M82: =INPUT!H5
G83: =IF(INPUT!H9="",NA(),INPUT!H9)
C84: =IF(INPUT!D5="",NA(),INPUT!D5) | D84: =INPUT!E5 | E84: =INPUT!F5 | F84: =INPUT!G5 | G84: =IF(INPUT!G30="",NA(),INPUT!G30) | H84: =IF(INPUT!H30="",NA(),INPUT!H30)
B85: Revenue | C85: =IF(INPUT!D9="",NA(),INPUT!D9) | D85: =IF(INPUT!E9="",NA(),INPUT!E9) | E85: =IF(INPUT!F9="",NA(),INPUT!F9) | F85: =IF(INPUT!G9="",NA(),INPUT!G9) | G85: =IF(INPUT!G26="",NA(),INPUT!G26) | H85: =IF(INPUT!H26="",NA(),INPUT!H26)
C86: EBITDA | D86: =IF(INPUT!D30="",NA(),INPUT!D30) | E86: =IF(INPUT!E30="",NA(),INPUT!E30) | F86: =IF(INPUT!F30="",NA(),INPUT!F30) | J86: =IF(INPUT!D5="",NA(),INPUT!D5) | K86: =INPUT!E5 | L86: =INPUT!F5 | M86: =INPUT!G5 | N86: =INPUT!H5
C87: Net Income | D87: =IF(INPUT!D26="",NA(),INPUT!D26) | E87: =IF(INPUT!E26="",NA(),INPUT!E26) | F87: =IF(INPUT!F26="",NA(),INPUT!F26) | I87: Gross Margin | J87: =IF(INPUT!D9="",NA(),INPUT!D11/INPUT!D9) | K87: =IF(INPUT!E9="",NA(),INPUT!E11/INPUT!E9) | L87: =IF(INPUT!F9="",NA(),INPUT!F11/INPUT!F9) | M87: =IF(INPUT!G9="",NA(),INPUT!G11/INPUT!G9) | N87: =IF(INPUT!H9="",NA(),INPUT!H11/INPUT!H9)
I88: EBITDA Margin | J88: =IF(INPUT!D9="",NA(),INPUT!D30/INPUT!D9) | K88: =IF(INPUT!E9="",NA(),INPUT!E30/INPUT!E9) | L88: =IF(INPUT!F9="",NA(),INPUT!F30/INPUT!F9) | M88: =IF(INPUT!G9="",NA(),INPUT!G30/INPUT!G9) | N88: =IF(INPUT!H9="",NA(),INPUT!H30/INPUT!H9)
G89: =INPUT!G5 | H89: =INPUT!H5 | I89: Net Margin | J89: =IF(INPUT!D9="",NA(),INPUT!D26/INPUT!D9) | K89: =IF(INPUT!E9="",NA(),INPUT!E26/INPUT!E9) | L89: =IF(INPUT!F9="",NA(),INPUT!F26/INPUT!F9) | M89: =IF(INPUT!G9="",NA(),INPUT!G26/INPUT!G9) | N89: =IF(INPUT!H9="",NA(),INPUT!H26/INPUT!H9)
G90: =IF(INPUT!G9="",NA(),INPUT!G9) | H90: =IF(INPUT!H9="",NA(),INPUT!H9)
D91: =IF(INPUT!D5="",NA(),INPUT!D5) | E91: =INPUT!E5 | F91: =INPUT!F5 | J91: =IF(INPUT!D5="",NA(),INPUT!D5) | K91: =INPUT!E5 | L91: =INPUT!F5 | M91: =INPUT!G5 | N91: =INPUT!H5
C92: Revenue | D92: =IF(INPUT!D9="",NA(),INPUT!D9) | E92: =IF(INPUT!E9="",NA(),INPUT!E9) | F92: =IF(INPUT!F9="",NA(),INPUT!F9) | I92: SG&A | J92: =IF(INPUT!D14="",NA(),ABS(INPUT!D14)) | K92: =IF(INPUT!E14="",NA(),ABS(INPUT!E14)) | L92: =IF(INPUT!F14="",NA(),ABS(INPUT!F14)) | M92: =IF(INPUT!G14="",NA(),ABS(INPUT!G14)) | N92: =IF(INPUT!H14="",NA(),ABS(INPUT!H14))
I93: R&D | J93: =IF(INPUT!D15="",NA(),ABS(INPUT!D15)) | K93: =IF(INPUT!E15="",NA(),ABS(INPUT!E15)) | L93: =IF(INPUT!F15="",NA(),ABS(INPUT!F15)) | M93: =IF(INPUT!G15="",NA(),ABS(INPUT!G15)) | N93: =IF(INPUT!H15="",NA(),ABS(INPUT!H15))
I94: D&A | J94: =IF(INPUT!D16="",NA(),ABS(INPUT!D16)) | K94: =IF(INPUT!E16="",NA(),ABS(INPUT!E16)) | L94: =IF(INPUT!F16="",NA(),ABS(INPUT!F16)) | M94: =IF(INPUT!G16="",NA(),ABS(INPUT!G16)) | N94: =IF(INPUT!H16="",NA(),ABS(INPUT!H16))
I95: Interest | J95: =IF(INPUT!D5="",NA(),INPUT!D5) | K95: =IF(INPUT!E14="",NA(),ABS(INPUT!E20)) | L95: =IF(INPUT!F14="",NA(),ABS(INPUT!F20)) | M95: =IF(INPUT!G14="",NA(),ABS(INPUT!G20)) | N95: =IF(INPUT!H14="",NA(),ABS(INPUT!H20))

Sheet DASHBOARD 2
B1: FinSight | R1: =INPUT!D114&" ("&INPUT!D115&") — "&INPUT!D116
B3: Projected Business Performance | F3: Football Field Chart — Valuation Inputs | M3: Financial Data — Multi-Year
B5: All figures in USD Thousands unless stated | I5: Low ($) | J5: Delta ($) | K5: High ($) | M5: All figures in USD Thousands unless stated | P5: =INPUT!E5 | Q5: =INPUT!F5 | R5: =INPUT!G5 | S5: =INPUT!H5
B6: Company Information | F6: 52-Week Trading Range | I6: =INPUT!H95*0.75 | J6: =K6-I6 | K6: =INPUT!H95*1.45
C7: Company Name | D7: =INPUT!D114 | F7: Consensus Research | I7: =INPUT!H95*1.1 | J7: =K7-I7 | K7: =INPUT!H95*1.6 | M7: Revenue Growth (%) | P7: =IF(INPUT!D9=0,"",INPUT!E9/INPUT!D9-1) | Q7: =IF(INPUT!E9=0,"",INPUT!F9/INPUT!E9-1) | R7: =IF(INPUT!F9=0,"",INPUT!G9/INPUT!F9-1) | S7: =IF(INPUT!G9=0,"",INPUT!H9/INPUT!G9-1)
C8: Ticker Symbol | D8: =INPUT!D115 | F8: Precedent Transactions | I8: =INPUT!H95*1.2 | J8: =K8-I8 | K8: =INPUT!H95*1.75 | M8: EBITDA Growth (%) | P8: ="" | Q8: =IF(INPUT!D30=0,"",INPUT!F30/INPUT!E30-1) | R8: =IF(INPUT!E30=0,"",INPUT!G30/INPUT!F30-1) | S8: =IF(INPUT!F30=0,"",INPUT!H30/INPUT!G30-1)
C9: Sector | D9: =INPUT!D116 | F9: Sum-of-the-Parts | I9: =INPUT!H95*1.3 | J9: =K9-I9 | K9: =INPUT!H95*1.85
C10: Base Year (LTM) | D10: =INPUT!D117 | F10: Discounted Cash Flow | I10: =INPUT!H95*1.15 | J10: =K10-I10 | K10: =INPUT!H95*1.7 | M10: Revenue
C11: Currency | D11: =INPUT!D118 | F11: Current Share Price | I11: =INPUT!H95 | M11: Revenue — Products | P11: =INPUT!E9 | Q11: =INPUT!E9 | R11: =INPUT!F9 | S11: =INPUT!G9 | T11: =INPUT!H9
C12: Analysis Date | D12: =INPUT!D120 | M12: Cost of Revenue (COGS) | P12: =ABS(INPUT!E10) | Q12: =ABS(INPUT!E10) | R12: =ABS(INPUT!F10) | S12: =ABS(INPUT!G10) | T12: =ABS(INPUT!H10)
M13: Gross Profit | P13: =INPUT!E11 | Q13: =INPUT!E11 | R13: =INPUT!F11 | S13: =INPUT!G11 | T13: =INPUT!H11
M14: SG&A | P14: =ABS(INPUT!E14) | Q14: =ABS(INPUT!E14) | R14: =ABS(INPUT!F14) | S14: =ABS(INPUT!G14) | T14: =ABS(INPUT!H14)
M15: Total Revenue | P15: =INPUT!E9 | Q15: =INPUT!E9 | R15: =INPUT!F9 | S15: =INPUT!G9 | T15: =INPUT!H9
M17: EBITDA | P17: =INPUT!E30 | Q17: =INPUT!E30 | R17: =INPUT!F30 | S17: =INPUT!G30 | T17: =INPUT!H30
M18: Cash from Ops (CFO) | P18: =INPUT!E75 | Q18: =INPUT!E75 | R18: =INPUT!F75 | S18: =INPUT!G75 | T18: =INPUT!H75
M19: Net Income | P19: =INPUT!E26 | Q19: =INPUT!E26 | R19: =INPUT!F26 | S19: =INPUT!G26 | T19: =INPUT!H26
B22: Stock Chart: Trailing 52-Weeks | I22: Valuation Summary: Football Field Chart | P22: Other Financial Metrics ($ Millier)
B42: Total Revenue ($M)
V84: Low | W84: Delta | X84: High
S85: 52-Week Trading Range | V85: =I6 | W85: =J6 | X85: =K6
S86: Consensus Research | V86: =I7 | W86: =J7 | X86: =K7
S87: Precedent Trans. | V87: =I8 | W87: =J8 | X87: =K8
S88: Sum-of-the-Parts | V88: =I9 | W88: =J9 | X88: =K9
S89: Discounted Cash Flow | V89: =I10 | W89: =J10 | X89: =K10
Q92: =K104 | R92: =L104 | S92: =M103 | T92: =N103
Q93: =IF(INPUT!E9="",NA(),INPUT!E30/1000) | R93: =IF(INPUT!F9="",NA(),INPUT!F30/1000) | S93: =IF(INPUT!G9="",NA(),INPUT!G30/1000) | T93: =IF(INPUT!H9="",NA(),INPUT!H30/1000)
Q94: =IF(INPUT!E9="",NA(),INPUT!E75/1000) | R94: =IF(INPUT!F9="",NA(),INPUT!F75/1000) | S94: =IF(INPUT!G9="",NA(),INPUT!G75/1000) | T94: =IF(INPUT!H9="",NA(),INPUT!H75/1000)
Q95: =IF(INPUT!E9="",NA(),INPUT!E26/1000) | S95: 2022 | T95: 2023 | U95: 2024 | V95: 2025 (LTM)
R96: EBITDA | S96: =Q17 | T96: =R17 | U96: =S17 | V96: =T17
R97: CFO | S97: =Q18 | T97: =R18 | U97: =S18 | V97: =T18
R98: Net Income | S98: =Q19 | T98: =R19 | U98: =S19 | V98: =T19
A101: Revenue
M103: =IF(INPUT!G9="",NA(),'DASHBOARD 2'!R5) | N103: =IF(INPUT!H9="",NA(),'DASHBOARD 2'!S5) | P103: =J104
I104: Year | J104: =IF(INPUT!D9="","",INPUT!D5) | K104: =IF(INPUT!E9="",NA(),'DASHBOARD 2'!P5) | L104: =IF(INPUT!F9="",NA(),'DASHBOARD 2'!Q5) | M104: =IF(INPUT!G9="",NA(),INPUT!G30) | N104: =IF(INPUT!H9="",NA(),INPUT!H30) | P104: =IF(INPUT!D9="",NA(),INPUT!D30/1000)
I105: EBITDA ($M) | J105: =IF(INPUT!D9="","",INPUT!D30) | K105: =IF(INPUT!E9="",NA(),INPUT!E30) | L105: =IF(INPUT!F9="",NA(),INPUT!F30) | M105: =IF(INPUT!G9="",NA(),INPUT!G75) | N105: =IF(INPUT!H9="",NA(),INPUT!H75) | P105: =IF(INPUT!D9="",NA(),INPUT!D75/1000)
B106: Year | C106: =IF(INPUT!D9="","",INPUT!D5) | D106: =IF(INPUT!E9="",NA(),'DASHBOARD 2'!P5) | E106: =IF(INPUT!F9="",NA(),'DASHBOARD 2'!Q5) | F106: =IF(INPUT!G9="",NA(),'DASHBOARD 2'!R5) | G106: =IF(INPUT!H9="",NA(),'DASHBOARD 2'!S5) | I106: CFO ($M) | J106: =IF(INPUT!D9="","",INPUT!D75) | K106: =IF(INPUT!E9="",NA(),INPUT!E75) | L106: =IF(INPUT!F9="",NA(),INPUT!F75) | M106: =IF(INPUT!G9="",NA(),INPUT!G26) | N106: =IF(INPUT!H9="",NA(),INPUT!H26) | P106: =IF(INPUT!D9="",NA(),INPUT!D26/1000)
B107: Revenue Growth (%) | C107: ="" | D107: =IF(INPUT!E9="",NA(),'DASHBOARD 2'!P7) | E107: =IF(INPUT!F9="",NA(),'DASHBOARD 2'!Q7) | F107: =IF(INPUT!G9="",NA(),'DASHBOARD 2'!R7) | G107: =IF(INPUT!H9="",NA(),'DASHBOARD 2'!S7) | I107: Net Income ($M) | J107: =IF(INPUT!D9="","",INPUT!D26) | K107: =IF(INPUT!E9="",NA(),INPUT!E26) | L107: =IF(INPUT!F9="",NA(),INPUT!F26)
B108: Total Revenue ($M) | C108: =IF(INPUT!D9="","",INPUT!D9) | D108: =IF(INPUT!E9="",NA(),INPUT!E9) | E108: =IF(INPUT!F9="",NA(),INPUT!F9) | F108: =IF(INPUT!G9="",NA(),INPUT!G9) | G108: =IF(INPUT!H9="",NA(),INPUT!H9)

Sheet STOCK_DATA
A1: STOCK_DATA — Apple Inc. (AAPL) — Trailing 52 Weeks
A2: # | B2: Month | C2: Close Price ($)
A3: 1 | B3: May-25 | C3: 48.75
A4: 2 | B4: Jun-25 | C4: 49.16
A5: 3 | B5: Jul-25 | C5: 49.87
A6: 4 | B6: Aug-25 | C6: 51.28
A7: 5 | B7: Sep-25 | C7: 49.59
A8: 6 | B8: Oct-25 | C8: 51.72
A9: 7 | B9: Nov-25 | C9: 55.36
A10: 8 | B10: Dec-25 | C10: 54.18
A11: 9 | B11: Jan-26 | C11: 60.51
A12: 10 | B12: Feb-26 | C12: 66.57
A13: 11 | B13: Mar-26 | C13: 80.06
A14: 12 | B14: Apr-26 | C14: 77.69
A15: 13
A17: ⚠️ Données simulées. Remplacer par données réelles (Bloomberg/FactSet) en colonne B (Mois) et C (Prix).

Sheet SECTOR_REF
A1: 0.08 | B1: Driver | C1: Pessimiste | D1: Realiste | E1: Optimiste
A2: Technologie / SaaS | B2: Revenue Growth Rate (Y1-Y5) | C2: 0.05 | D2: 0.12 | E2: 0.22
A3: Technologie / SaaS | B3: Gross Margin | C3: 0.55 | D3: 0.68 | E3: 0.78
A4: Technologie / SaaS | B4: EBITDA Margin | C4: 0.08 | D4: 0.18 | E4: 0.28
A5: Technologie / SaaS | B5: SG&A (% Revenue) | C5: 0.3 | D5: 0.22 | E5: 0.15
A6: Technologie / SaaS | B6: R&D (% Revenue) | C6: 0.18 | D6: 0.12 | E6: 0.08
A7: Technologie / SaaS | B7: CapEx (% Revenue) | C7: 0.08 | D7: 0.05 | E7: 0.03
A8: Technologie / SaaS | B8: Change in NWC (% Rev Change) | C8: 0.05 | D8: 0.03 | E8: 0.02
A9: Technologie / SaaS | B9: Terminal Growth Rate | C9: 0.02 | D9: 0.03 | E9: 0.04
A10: Technologie / SaaS | B10: WACC | C10: 0.11 | D10: 0.09 | E10: 0.07
A11: Technologie / SaaS | B11: EV/EBITDA Exit Multiple | C11: 12 | D11: 16 | E11: 22
A12: Industrie / Manufacturing | B12: Revenue Growth Rate (Y1-Y5) | C12: 0.01 | D12: 0.04 | E12: 0.07
A13: Industrie / Manufacturing | B13: Gross Margin | C13: 0.18 | D13: 0.25 | E13: 0.32
... A71: Energie / Oil & Gas | B71: EV/EBITDA Exit Multiple | C71: 4 | D71: 6 | E71: 8
