Workbook

Sheet DASHBOARD
A1: FinSight IA · Tableau de Bord — Screening Euro Stoxx 50 | R1: Confidentiel · Usage interne
D3: =COUNTA('DONNÉES BRUTES'!A:A)-2 -> 40 | J3: {=COUNTA(_xlfn.UNIQUE(_xlfn._xlws.FILTER('DONNÉES BRUTES'!C3:C42,'DONNÉES BRUTES'!C3:C42<>"")))} -> 10 | P3: =_xlfn.XLOOKUP(MAX('DONNÉES BRUTES'!AB3:AB42),'DONNÉES BRUTES'!AB3:AB42,'DONNÉES BRUTES'!A3:A42)&" — "&MAX('DONNÉES BRUTES'!AB3:AB42)&"/100" -> ASML.AS — 75/100 | V3: 12/04/2026
D4: SOCIÉTÉS ANALYSÉES | J4: SECTEURS COUVERTS | P4: MEILLEUR SCORE GLOBAL | V4: DATE D'ANALYSE
B6: TOP 5 · Classements par Facteur d'Investissement
B7: # | C7: Ticker | D7: Société | E7: Score | F7: Mét. | H7: # | I7: Ticker | J7: Société | K7: Score | L7: Mét. | N7: # | O7: Ticker | P7: Société | Q7: Score | R7: Mét. | T7: # | U7: Ticker | V7: Société | W7: Score | X7: Mét.
B8: 1 | C8: {=IFERROR(INDEX('DONNÉES BRUTES'!A$3:A$42,MATCH(_xlfn.AGGREGATE(14,6,'DONNÉES BRUTES'!AB$3:AB$42*1000+(40-ROW('DONNÉES BRUTES'!AB$3:AB$42)+ROW('DONNÉES BRUTES'!AB$3)),1),'DONNÉES BRUTES'!AB$3:AB$42*1000+(40-ROW('DONNÉES BRUTES'!AB$3:AB$42)+ROW('DONNÉES BRUTES'!AB$3)),0)),"—")} -> ASML.AS | D8: {=IFERROR(LEFT(INDEX('DONNÉES BRUTES'!B$3:B$42,MATCH(_xlfn.AGGREGATE(14,6,'DONNÉES BRUTES'!AB$3:AB$42*1000+(40-ROW('DONNÉES BRUTES'!AB$3:AB$42)+ROW('DONNÉES BRUTES'!AB$3)),1),'DONNÉES BRUTES'!AB$3:AB$42*1000+(40-ROW('DONNÉES BRUTES'!AB$3:AB$42)+ROW('DONNÉES BRUTES'!AB$3)),0)),18),"—")} -> ASML Holding N.V. | E8: {=IFERROR(INT(_xlfn.AGGREGATE(14,6,'DONNÉES BRUTES'!AB$3:AB$42*1000+(40-ROW('DONNÉES BRUTES'!AB$3:AB$42)+ROW('DONNÉES BRUTES'!AB$3)),1)/1000)&"/100","—")} -> 75/100 | F8: {=IFERROR(INDEX('DONNÉES BRUTES'!I$3:I$42,MATCH(_xlfn.AGGREGATE(14,6,'DONNÉES BRUTES'!AB$3:AB$42*1000+(40-ROW('DONNÉES BRUTES'!AB$3:AB$42)+ROW('DONNÉES BRUTES'!AB$3)),1),'DONNÉES BRUTES'!AB$3:AB$42*1000+(40-ROW('DONNÉES BRUTES'!AB$3:AB$42)+ROW('DONNÉES BRUTES'!AB$3)),0)),"—")} -> — | H8: 1 | I8: {=IFERROR(INDEX('DONNÉES BRUTES'!A$3:A$42,MATCH(_xlfn.AGGREGATE(14,6,'DONNÉES BRUTES'!Y$3:Y$42*1000+(40-ROW('DONNÉES BRUTES'!Y$3:Y$42)+ROW('DONNÉES BRUTES'!Y$3)),1),'DONNÉES BRUTES'!Y$3:Y$42*1000+(40-ROW('DONNÉES BRUTES'!Y$3:Y$42)+ROW('DONNÉES BRUTES'!Y$3)),0)),"—")} -> ASML.AS | J8: {=IFERROR(LEFT(INDEX('DONNÉES BRUTES'!B$3:B$42,MATCH(_xlfn.AGGREGATE(14,6,'DONNÉES BRUTES'!Y$3:Y$42*1000+(40-ROW('DONNÉES BRUTES'!Y$3:Y$42)+ROW('DONNÉES BRUTES'!Y$3)),1),'DONNÉES BRUTES'!Y$3:Y$42*1000+(40-ROW('DONNÉES BRUTES'!Y$3:Y$42)+ROW('DONNÉES BRUTES'!Y$3)),0)),18),"—")} -> ASML Holding N.V. | K8: {=IFERROR(INT(_xlfn.AGGREGATE(14,6,'DONNÉES BRUTES'!Y$3:Y$42*1000+(40-ROW('DONNÉES BRUTES'!Y$3:Y$42)+ROW('DONNÉES BRUTES'!Y$3)),1)/1000)&"/100","—")} -> 92/100 | L8: {=IFERROR(INDEX('DONNÉES BRUTES'!P$3:P$42,MATCH(_xlfn.AGGREGATE(14,6,'DONNÉES BRUTES'!Y$3:Y$42*1000+(40-ROW('DONNÉES BRUTES'!Y$3:Y$42)+ROW('DONNÉES BRUTES'!Y$3)),1),'DONNÉES BRUTES'!Y$3:Y$42*1000+(40-ROW('DONNÉES BRUTES'!Y$3:Y$42)+ROW('DONNÉES BRUTES'!Y$3)),0)),"—")} -> +15.6% | N8: 1 | O8: {=IFERROR(INDEX('DONNÉES BRUTES'!A$3:A$42,MATCH(_xlfn.AGGREGATE(14,6,'DONNÉES BRUTES'!Z$3:Z$42*1000+(40-ROW('DONNÉES BRUTES'!Z$3:Z$42)+ROW('DONNÉES BRUTES'!Z$3)),1),'DONNÉES BRUTES'!Z$3:Z$42*1000+(40-ROW('DONNÉES BRUTES'!Z$3:Z$42)+ROW('DONNÉES BRUTES'!Z$3)),0)),"—")} -> RMS.PA | P8: {=IFERROR(LEFT(INDEX('DONNÉES BRUTES'!B$3:B$42,MATCH(_xlfn.AGGREGATE(14,6,'DONNÉES BRUTES'!Z$3:Z$42*1000+(40-ROW('DONNÉES BRUTES'!Z$3:Z$42)+ROW('DONNÉES BRUTES'!Z$3)),1),'DONNÉES BRUTES'!Z$3:Z$42*1000+(40-ROW('DONNÉES BRUTES'!Z$3:Z$42)+ROW('DONNÉES BRUTES'!Z$3)),0)),18),"—")} -> Hermès Internation | Q8: {=IFERROR(INT(_xlfn.AGGREGATE(14,6,'DONNÉES BRUTES'!Z$3:Z$42*1000+(40-ROW('DONNÉES BRUTES'!Z$3:Z$42)+ROW('DONNÉES BRUTES'!Z$3)),1)/1000)&"/100","—")} -> 99/100 | R8: {=IFERROR(INDEX('DONNÉES BRUTES'!U$3:U$42,MATCH(_xlfn.AGGREGATE(14,6,'DONNÉES BRUTES'!Z$3:Z$42*1000+(40-ROW('DONNÉES BRUTES'!Z$3:Z$42)+ROW('DONNÉES BRUTES'!Z$3)),1),'DONNÉES BRUTES'!Z$3:Z$42*1000+(40-ROW('DONNÉES BRUTES'!Z$3:Z$42)+ROW('DONNÉES BRUTES'!Z$3)),0)),"—")} -> 9.47 | T8: 1 | U8: {=IFERROR(INDEX('DONNÉES BRUTES'!A$3:A$42,MATCH(_xlfn.AGGREGATE(14,6,'DONNÉES BRUTES'!AA$3:AA$42*1000+(40-ROW('DONNÉES BRUTES'!AA$3:AA$42)+ROW('DONNÉES BRUTES'!AA$3)),1),'DONNÉES BRUTES'!AA$3:AA$42*1000+(40-ROW('DONNÉES BRUTES'!AA$3:AA$42)+ROW('DONNÉES BRUTES'!AA$3)),0)),"—")} -> ASML.AS | V8: {=IFERROR(LEFT(INDEX('DONNÉES BRUTES'!B$3:B$42,MATCH(_xlfn.AGGREGATE(14,6,'DONNÉES BRUTES'!AA$3:AA$42*1000+(40-ROW('DONNÉES BRUTES'!AA$3:AA$42)+ROW('DONNÉES BRUTES'!AA$3)),1),'DONNÉES BRUTES'!AA$3:AA$42*1000+(40-ROW('DONNÉES BRUTES'!AA$3:AA$42)+ROW('DONNÉES BRUTES'!AA$3)),0)),18),"—")} -> ASML Holding N.V. | W8: {=IFERROR(INT(_xlfn.AGGREGATE(14,6,'DONNÉES BRUTES'!AA$3:AA$42*1000+(40-ROW('DONNÉES BRUTES'!AA$3:AA$42)+ROW('DONNÉES BRUTES'!AA$3)),1)/1000)&"/100","—")} -> 98/100 | X8: {=IFERROR(INDEX('DONNÉES BRUTES'!P$3:P$42,MATCH(_xlfn.AGGREGATE(14,6,'DONNÉES BRUTES'!AA$3:AA$42*1000+(40-ROW('DONNÉES BRUTES'!AA$3:AA$42)+ROW('DONNÉES BRUTES'!AA$3)),1),'DONNÉES BRUTES'!AA$3:AA$42*1000+(40-ROW('DONNÉES BRUTES'!AA$3:AA$42)+ROW('DONNÉES BRUTES'!AA$3)),0)),"—")} -> +15.6%
B9: 2 | C9: {=IFERROR(INDEX('DONNÉES BRUTES'!A$3:A$42,MATCH(_xlfn.AGGREGATE(14,6,'DONNÉES BRUTES'!AB$3:AB$42*1000+(40-ROW('DONNÉES BRUTES'!AB$3:AB$42)+ROW('DONNÉES BRUTES'!AB$3)),2),'DONNÉES BRUTES'!AB$3:AB$42*1000+(40-ROW('DONNÉES BRUTES'!AB$3:AB$42)+ROW('DONNÉES BRUTES'!AB$3)),0)),"—")} -> RIO.L | D9: {=IFERROR(LEFT(INDEX('DONNÉES BRUTES'!B$3:B$42,MATCH(_xlfn.AGGREGATE(14,6,'DONNÉES BRUTES'!AB$3:AB$42*1000+(40-ROW('DONNÉES BRUTES'!AB$3:AB$42)+ROW('DONNÉES BRUTES'!AB$3)),2),'DONNÉES BRUTES'!AB$3:AB$42*1000+(40-ROW('DONNÉES BRUTES'!AB$3:AB$42)+ROW('DONNÉES BRUTES'!AB$3)),0)),18),"—")} -> Rio Tinto Group | E9: {=IFERROR(INT(_xlfn.AGGREGATE(14,6,'DONNÉES BRUTES'!AB$3:AB$42*1000+(40-ROW('DONNÉES BRUTES'!AB$3:AB$42)+ROW('DONNÉES BRUTES'!AB$3)),2)/1000)&"/100","—")} -> 70/100 | F9: {=IFERROR(INDEX('DONNÉES BRUTES'!I$3:I$42,MATCH(_xlfn.AGGREGATE(14,6,'DONNÉES BRUTES'!AB$3:AB$42*1000+(40-ROW('DONNÉES BRUTES'!AB$3:AB$42)+ROW('DONNÉES BRUTES'!AB$3)),2),'DONNÉES BRUTES'!AB$3:AB$42*1000+(40-ROW('DONNÉES BRUTES'!AB$3:AB$42)+ROW('DONNÉES BRUTES'!AB$3)),0)),"—")} -> 401.8 | H9: 2 | I9: {=IFERROR(INDEX('DONNÉES BRUTES'!A$3:A$42,MATCH(_xlfn.AGGREGATE(14,6,'DONNÉES BRUTES'!Y$3:Y$42*1000+(40-ROW('DONNÉES BRUTES'!Y$3:Y$42)+ROW('DONNÉES BRUTES'!Y$3)),2),'DONNÉES BRUTES'!Y$3:Y$42*1000+(40-ROW('DONNÉES BRUTES'!Y$3:Y$42)+ROW('DONNÉES BRUTES'!Y$3)),0)),"—")} -> AZN.L | J9: {=IFERROR(LEFT(INDEX('DONNÉES BRUTES'!B$3:B$42,MATCH(_xlfn.AGGREGATE(14,6,'DONNÉES BRUTES'!Y$3:Y$42*1000+(40-ROW('DONNÉES BRUTES'!Y$3:Y$42)+ROW('DONNÉES BRUTES'!Y$3)),2),'DONNÉES BRUTES'!Y$3:Y$42*1000+(40-ROW('DONNÉES BRUTES'!Y$3:Y$42)+ROW('DONNÉES BRUTES'!Y$3)),0)),18),"—")} -> AstraZeneca PLC | K9: {=IFERROR(INT(_xlfn.AGGREGATE(14,6,'DONNÉES BRUTES'!Y$3:Y$42*1000+(40-ROW('DONNÉES BRUTES'!Y$3:Y$42)+ROW('DONNÉES BRUTES'!Y$3)),2)/1000)&"/100","—")} -> 87/100 | L9: {=IFERROR(INDEX('DONNÉES BRUTES'!P$3:P$42,MATCH(_xlfn.AGGREGATE(14,6,'DONNÉES BRUTES'!Y$3:Y$42*1000+(40-ROW('DONNÉES BRUTES'!Y$3:Y$42)+ROW('DONNÉES BRUTES'!Y$3)),2),'DONNÉES BRUTES'!Y$3:Y$42*1000+(40-ROW('DONNÉES BRUTES'!Y$3:Y$42)+ROW('DONNÉES BRUTES'!Y$3)),0)),"—")} -> +8.6% | N9: 2 | O9: {=IFERROR(INDEX('DONNÉES BRUTES'!A$3:A$42,MATCH(_xlfn.AGGREGATE(14,6,'DONNÉES BRUTES'!Z$3:Z$42*1000+(40-ROW('DONNÉES BRUTES'!Z$3:Z$42)+ROW('DONNÉES BRUTES'!Z$3)),2),'DONNÉES BRUTES'!Z$3:Z$42*1000+(40-ROW('DONNÉES BRUTES'!Z$3:Z$42)+ROW('DONNÉES BRUTES'!Z$3)),0)),"—")} -> ASML.AS | P9: {=IFERROR(LEFT(INDEX('DONNÉES BRUTES'!B$3:B$42,MATCH(_xlfn.AGGREGATE(14,6,'DONNÉES BRUTES'!Z$3:Z$42*1000+(40-ROW('DONNÉES BRUTES'!Z$3:Z$42)+ROW('DONNÉES BRUTES'!Z$3)),2),'DONNÉES BRUTES'!Z$3:Z$42*1000+(40-ROW('DONNÉES BRUTES'!Z$3:Z$42)+ROW('DONNÉES BRUTES'!Z$3)),0)),18),"—")} -> ASML Holding N.V. | Q9: {=IFERROR(INT(_xlfn.AGGREGATE(14,6,'DONNÉES BRUTES'!Z$3:Z$42*1000+(40-ROW('DONNÉES BRUTES'!Z$3:Z$42)+ROW('DONNÉES BRUTES'!Z$3)),2)/1000)&"/100","—")} -> 86/100 | R9: {=IFERROR(INDEX('DONNÉES BRUTES'!U$3:U$42,MATCH(_xlfn.AGGREGATE(14,6,'DONNÉES BRUTES'!Z$3:Z$42*1000+(40-ROW('DONNÉES BRUTES'!Z$3:Z$42)+ROW('DONNÉES BRUTES'!Z$3)),2),'DONNÉES BRUTES'!Z$3:Z$42*1000+(40-ROW('DONNÉES BRUTES'!Z$3:Z$42)+ROW('DONNÉES BRUTES'!Z$3)),0)),"—")} -> 4.15 | T9: 2 | U9: {=IFERROR(INDEX('DONNÉES BRUTES'!A$3:A$42,MATCH(_xlfn.AGGREGATE(14,6,'DONNÉES BRUTES'!AA$3:AA$42*1000+(40-ROW('DONNÉES BRUTES'!AA$3:AA$42)+ROW('DONNÉES BRUTES'!AA$3)),2),'DONNÉES BRUTES'!AA$3:AA$42*1000+(40-ROW('DONNÉES BRUTES'!AA$3:AA$42)+ROW('DONNÉES BRUTES'!AA$3)),0)),"—")} -> RWE.DE | V9: {=IFERROR(LEFT(INDEX('DONNÉES BRUTES'!B$3:B$42,MATCH(_xlfn.AGGREGATE(14,6,'DONNÉES BRUTES'!AA$3:AA$42*1000+(40-ROW('DONNÉES BRUTES'!AA$3:AA$42)+ROW('DONNÉES BRUTES'!AA$3)),2),'DONNÉES BRUTES'!AA$3:AA$42*1000+(40-ROW('DONNÉES BRUTES'!AA$3:AA$42)+ROW('DONNÉES BRUTES'!AA$3)),0)),18),"—")} -> RWE Aktiengesellsc | W9: {=IFERROR(INT(_xlfn.AGGREGATE(14,6,'DONNÉES BRUTES'!AA$3:AA$42*1000+(40-ROW('DONNÉES BRUTES'!AA$3:AA$42)+ROW('DONNÉES BRUTES'!AA$3)),2)/1000)&"/100","—")} -> 96/100 | X9: {=IFERROR(INDEX('DONNÉES BRUTES'!P$3:P$42,MATCH(_xlfn.AGGREGATE(14,6,'DONNÉES BRUTES'!AA$3:AA$42*1000+(40-ROW('DONNÉES BRUTES'!AA$3:AA$42)+ROW('DONNÉES BRUTES'!AA$3)),2),'DONNÉES BRUTES'!AA$3:AA$42*1000+(40-ROW('DONNÉES BRUTES'!AA$3:AA$42)+ROW('DONNÉES BRUTES'!AA$3)),0)),"—")} -> -27.2%
B10: 3 | C10: {=IFERROR(INDEX('DONNÉES BRUTES'!A$3:A$42,MATCH(_xlfn.AGGREGATE(14,6,'DONNÉES BRUTES'!AB$3:AB$42*1000+(40-ROW('DONNÉES BRUTES'!AB$3:AB$42)+ROW('DONNÉES BRUTES'!AB$3)),3),'DONNÉES BRUTES'!AB$3:AB$42*1000+(40-ROW('DONNÉES BRUTES'!AB$3:AB$42)+ROW('DONNÉES BRUTES'!AB$3)),0)),"—")} -> RMS.PA | D10: {=IFERROR(LEFT(INDEX('DONNÉES BRUTES'!B$3:B$42,MATCH(_xlfn.AGGREGATE(14,6,'DONNÉES BRUTES'!AB$3:AB$42*1000+(40-ROW('DONNÉES BRUTES'!AB$3:AB$42)+ROW('DONNÉES BRUTES'!AB$3)),3),'DONNÉES BRUTES'!AB$3:AB$42*1000+(40-ROW('DONNÉES BRUTES'!AB$3:AB$42)+ROW('DONNÉES BRUTES'!AB$3)),0)),18),"—")} -> Hermès Internation | E10: {=IFERROR(INT(_xlfn.AGGREGATE(14,6,'DONNÉES BRUTES'!AB$3:AB$42*1000+(40-ROW('DONNÉES BRUTES'!AB$3:AB$42)+ROW('DONNÉES BRUTES'!AB$3)),3)/1000)&"/100","—")} -> 65/100 | F10: {=IFERROR(INDEX('DONNÉES BRUTES'!I$3:I$42,MATCH(_xlfn.AGGREGATE(14,6,'DONNÉES BRUTES'!AB$3:AB$42*1000+(40-ROW('DONNÉES BRUTES'!AB$3:AB$42)+ROW('DONNÉES BRUTES'!AB$3)),3),'DONNÉES BRUTES'!AB$3:AB$42*1000+(40-ROW('DONNÉES BRUTES'!AB$3:AB$42)+ROW('DONNÉES BRUTES'!AB$3)),0)),"—")} -> 22.9 | H10: 3 | I10: {=IFERROR(INDEX('DONNÉES BRUTES'!A$3:A$42,MATCH(_xlfn.AGGREGATE(14,6,'DONNÉES BRUTES'!Y$3:Y$42*1000+(40-ROW('DONNÉES BRUTES'!Y$3:Y$42)+ROW('DONNÉES BRUTES'!Y$3)),3),'DONNÉES BRUTES'!Y$3:Y$42*1000+(40-ROW('DONNÉES BRUTES'!Y$3:Y$42)+ROW('DONNÉES BRUTES'!Y$3)),0)),"—")} -> RMS.PA | J10: {=IFERROR(LEFT(INDEX('DONNÉES BRUTES'!B$3:B$42,MATCH(_xlfn.AGGREGATE(14,6,'DONNÉES BRUTES'!Y$3:Y$42*1000+(40-ROW('DONNÉES BRUTES'!Y$3:Y$42)+ROW('DONNÉES BRUTES'!Y$3)),3),'DONNÉES BRUTES'!Y$3:Y$42*1000+(40-ROW('DONNÉES BRUTES'!Y$3:Y$42)+ROW('DONNÉES BRUTES'!Y$3)),0)),18),"—")} -> Hermès Internation | K10: {=IFERROR(INT(_xlfn.AGGREGATE(14,6,'DONNÉES BRUTES'!Y$3:Y$42*1000+(40-ROW('DONNÉES BRUTES'!Y$3:Y$42)+ROW('DONNÉES BRUTES'!Y$3)),3)/1000)&"/100","—")} -> 81/100 | L10: {=IFERROR(INDEX('DONNÉES BRUTES'!P$3:P$42,MATCH(_xlfn.AGGREGATE(14,6,'DONNÉES BRUTES'!Y$3:Y$42*1000+(40-ROW('DONNÉES BRUTES'!Y$3:Y$42)+ROW('DONNÉES BRUTES'!Y$3)),3),'DONNÉES BRUTES'!Y$3:Y$42*1000+(40-ROW('DONNÉES BRUTES'!Y$3:Y$42)+ROW('DONNÉES BRUTES'!Y$3)),0)),"—")} -> +5.5% | N10: 3 | O10: {=IFERROR(INDEX('DONNÉES BRUTES'!A$3:A$42,MATCH(_xlfn.AGGREGATE(14,6,'DONNÉES BRUTES'!Z$3:Z$42*1000+(40-ROW('DONNÉES BRUTES'!Z$3:Z$42)+ROW('DONNÉES BRUTES'!Z$3)),3),'DONNÉES BRUTES'!Z$3:Z$42*1000+(40-ROW('DONNÉES BRUTES'!Z$3:Z$42)+ROW('DONNÉES BRUTES'!Z$3)),0)),"—")} -> ITX.MC | P10: {=IFERROR(LEFT(INDEX('DONNÉES BRUTES'!B$3:B$42,MATCH(_xlfn.AGGREGATE(14,6,'DONNÉES BRUTES'!Z$3:Z$42*1000+(40-ROW('DONNÉES BRUTES'!Z$3:Z$42)+ROW('DONNÉES BRUTES'!Z$3)),3),'DONNÉES BRUTES'!Z$3:Z$42*1000+(40-ROW('DONNÉES BRUTES'!Z$3:Z$42)+ROW('DONNÉES BRUTES'!Z$3)),0)),18),"—")} -> Industria de Diseñ | Q10: {=IFERROR(INT(_xlfn.AGGREGATE(14,6,'DONNÉES BRUTES'!Z$3:Z$42*1000+(40-ROW('DONNÉES BRUTES'!Z$3:Z$42)+ROW('DONNÉES BRUTES'!Z$3)),3)/1000)&"/100","—")} -> 83/100 | R10: {=IFERROR(INDEX('DONNÉES BRUTES'!U$3:U$42,MATCH(_xlfn.AGGREGATE(14,6,'DONNÉES BRUTES'!Z$3:Z$42*1000+(40-ROW('DONNÉES BRUTES'!Z$3:Z$42)+ROW('DONNÉES BRUTES'!Z$3)),3),'DONNÉES BRUTES'!Z$3:Z$42*1000+(40-ROW('DONNÉES BRUTES'!Z$3:Z$42)+ROW('DONNÉES BRUTES'!Z$3)),0)),"—")} -> 4.57 | T10: 3 | U10: {=IFERROR(INDEX('DONNÉES BRUTES'!A$3:A$42,MATCH(_xlfn.AGGREGATE(14,6,'DONNÉES BRUTES'!AA$3:AA$42*1000+(40-ROW('DONNÉES BRUTES'!AA$3:AA$42)+ROW('DONNÉES BRUTES'!AA$3)),3),'DONNÉES BRUTES'!AA$3:AA$42*1000+(40-ROW('DONNÉES BRUTES'!AA$3:AA$42)+ROW('DONNÉES BRUTES'!AA$3)),0)),"—")} -> NOKIA.HE | V10: {=IFERROR(LEFT(INDEX('DONNÉES BRUTES'!B$3:B$42,MATCH(_xlfn.AGGREGATE(14,6,'DONNÉES BRUTES'!AA$3:AA$42*1000+(40-ROW('DONNÉES BRUTES'!AA$3:AA$42)+ROW('DONNÉES BRUTES'!AA$3)),3),'DONNÉES BRUTES'!AA$3:AA$42*1000+(40-ROW('DONNÉES BRUTES'!AA$3:AA$42)+ROW('DONNÉES BRUTES'!AA$3)),0)),18),"—")} -> Nokia Oyj | W10: {=IFERROR(INT(_xlfn.AGGREGATE(14,6,'DONNÉES BRUTES'!AA$3:AA$42*1000+(40-ROW('DONNÉES BRUTES'!AA$3:AA$42)+ROW('DONNÉES BRUTES'!AA$3)),3)/1000)&"/100","—")} -> 94/100 | X10: {=IFERROR(INDEX('DONNÉES BRUTES'!P$3:P$42,MATCH(_xlfn.AGGREGATE(14,6,'DONNÉES BRUTES'!AA$3:AA$42*1000+(40-ROW('DONNÉES BRUTES'!AA$3:AA$42)+ROW('DONNÉES BRUTES'!AA$3)),3),'DONNÉES BRUTES'!AA$3:AA$42*1000+(40-ROW('DONNÉES BRUTES'!AA$3:AA$42)+ROW('DONNÉES BRUTES'!AA$3)),0)),"—")} -> +3.5%
B11: 4 | C11: {=IFERROR(INDEX('DONNÉES BRUTES'!A$3:A$42,MATCH(_xlfn.AGGREGATE(14,6,'DONNÉES BRUTES'!AB$3:AB$42*1000+(40-ROW('DONNÉES BRUTES'!AB$3:AB$42)+ROW('DONNÉES BRUTES'!AB$3)),4),'DONNÉES BRUTES'!AB$3:AB$42*1000+(40-ROW('DONNÉES BRUTES'!AB$3:AB$42)+ROW('DONNÉES BRUTES'!AB$3)),0)),"—")} -> SAP.DE | D11: {=IFERROR(LEFT(INDEX('DONNÉES BRUTES'!B$3:B$42,MATCH(_xlfn.AGGREGATE(14,6,'DONNÉES BRUTES'!AB$3:AB$42*1000+(40-ROW('DONNÉES BRUTES'!AB$3:AB$42)+ROW('DONNÉES BRUTES'!AB$3)),4),'DONNÉES BRUTES'!AB$3:AB$42*1000+(40-ROW('DONNÉES BRUTES'!AB$3:AB$42)+ROW('DONNÉES BRUTES'!AB$3)),0)),18),"—")} -> SAP SE | E11: {=IFERROR(INT(_xlfn.AGGREGATE(14,6,'DONNÉES BRUTES'!AB$3:AB$42*1000+(40-ROW('DONNÉES BRUTES'!AB$3:AB$42)+ROW('DONNÉES BRUTES'!AB$3)),4)/1000)&"/100","—")} -> 62/100 | F11: {=IFERROR(INDEX('DONNÉES BRUTES'!I$3:I$42,MATCH(_xlfn.AGGREGATE(14,6,'DONNÉES BRUTES'!AB$3:AB$42*1000+(40-ROW('DONNÉES BRUTES'!AB$3:AB$42)+ROW('DONNÉES BRUTES'!AB$3)),4),'DONNÉES BRUTES'!AB$3:AB$42*1000+(40-ROW('DONNÉES BRUTES'!AB$3:AB$42)+ROW('DONNÉES BRUTES'!AB$3)),0)),"—")} -> 13.3 | H11: 4 | I11: {=IFERROR(INDEX('DONNÉES BRUTES'!A$3:A$42,MATCH(_xlfn.AGGREGATE(14,6,'DONNÉES BRUTES'!Y$3:Y$42*1000+(40-ROW('DONNÉES BRUTES'!Y$3:Y$42)+ROW('DONNÉES BRUTES'!Y$3)),4),'DONNÉES BRUTES'!Y$3:Y$42*1000+(40-ROW('DONNÉES BRUTES'!Y$3:Y$42)+ROW('DONNÉES BRUTES'!Y$3)),0)),"—")} -> SAP.DE | J11: {=IFERROR(LEFT(INDEX('DONNÉES BRUTES'!B$3:B$42,MATCH(_xlfn.AGGREGATE(14,6,'DONNÉES BRUTES'!Y$3:Y$42*1000+(40-ROW('DONNÉES BRUTES'!Y$3:Y$42)+ROW('DONNÉES BRUTES'!Y$3)),4),'DONNÉES BRUTES'!Y$3:Y$42*1000+(40-ROW('DONNÉES BRUTES'!Y$3:Y$42)+ROW('DONNÉES BRUTES'!Y$3)),0)),18),"—")} -> SAP SE | K11: {=IFERROR(INT(_xlfn.AGGREGATE(14,6,'DONNÉES BRUTES'!Y$3:Y$42*1000+(40-ROW('DONNÉES BRUTES'!Y$3:Y$42)+ROW('DONNÉES BRUTES'!Y$3)),4)/1000)&"/100","—")} -> 78/100 | L11: {=IFERROR(INDEX('DONNÉES BRUTES'!P$3:P$42,MATCH(_xlfn.AGGREGATE(14,6,'DONNÉES BRUTES'!Y$3:Y$42*1000+(40-ROW('DONNÉES BRUTES'!Y$3:Y$42)+ROW('DONNÉES BRUTES'!Y$3)),4),'DONNÉES BRUTES'!Y$3:Y$42*1000+(40-ROW('DONNÉES BRUTES'!Y$3:Y$42)+ROW('DONNÉES BRUTES'!Y$3)),0)),"—")} -> +7.7% | N11: 4 | O11: {=IFERROR(INDEX('DONNÉES BRUTES'!A$3:A$42,MATCH(_xlfn.AGGREGATE(14,6,'DONNÉES BRUTES'!Z$3:Z$42*1000+(40-ROW('DONNÉES BRUTES'!Z$3:Z$42)+ROW('DONNÉES BRUTES'!Z$3)),4),'DONNÉES BRUTES'!Z$3:Z$42*1000+(40-ROW('DONNÉES BRUTES'!Z$3:Z$42)+ROW('DONNÉES BRUTES'!Z$3)),0)),"—")} -> SAP.DE | P11: {=IFERROR(LEFT(INDEX('DONNÉES BRUTES'!B$3:B$42,MATCH(_xlfn.AGGREGATE(14,6,'DONNÉES BRUTES'!Z$3:Z$42*1000+(40-ROW('DONNÉES BRUTES'!Z$3:Z$42)+ROW('DONNÉES BRUTES'!Z$3)),4),'DONNÉES BRUTES'!Z$3:Z$42*1000+(40-ROW('DONNÉES BRUTES'!Z$3:Z$42)+ROW('DONNÉES BRUTES'!Z$3)),0)),18),"—")} -> SAP SE | Q11: {=IFERROR(INT(_xlfn.AGGREGATE(14,6,'DONNÉES BRUTES'!Z$3:Z$42*1000+(40-ROW('DONNÉES BRUTES'!Z$3:Z$42)+ROW('DONNÉES BRUTES'!Z$3)),4)/1000)&"/100","—")} -> 80/100 | R11: {=IFERROR(INDEX('DONNÉES BRUTES'!U$3:U$42,MATCH(_xlfn.AGGREGATE(14,6,'DONNÉES BRUTES'!Z$3:Z$42*1000+(40-ROW('DONNÉES BRUTES'!Z$3:Z$42)+ROW('DONNÉES BRUTES'!Z$3)),4),'DONNÉES BRUTES'!Z$3:Z$42*1000+(40-ROW('DONNÉES BRUTES'!Z$3:Z$42)+ROW('DONNÉES BRUTES'!Z$3)),0)),"—")} -> 5.34 | T11: 4 | U11: {=IFERROR(INDEX('DONNÉES BRUTES'!A$3:A$42,MATCH(_xlfn.AGGREGATE(14,6,'DONNÉES BRUTES'!AA$3:AA$42*1000+(40-ROW('DONNÉES BRUTES'!AA$3:AA$42)+ROW('DONNÉES BRUTES'!AA$3)),4),'DONNÉES BRUTES'!AA$3:AA$42*1000+(40-ROW('DONNÉES BRUTES'!AA$3:AA$42)+ROW('DONNÉES BRUTES'!AA$3)),0)),"—")} -> RIO.L | V11: {=IFERROR(LEFT(INDEX('DONNÉES BRUTES'!B$3:B$42,MATCH(_xlfn.AGGREGATE(14,6,'DONNÉES BRUTES'!AA$3:AA$42*1000+(40-ROW('DONNÉES BRUTES'!AA$3:AA$42)+ROW('DONNÉES BRUTES'!AA$3)),4),'DONNÉES BRUTES'!AA$3:AA$42*1000+(40-ROW('DONNÉES BRUTES'!AA$3:AA$42)+ROW('DONNÉES BRUTES'!AA$3)),0)),18),"—")} -> Rio Tinto Group | W11: {=IFERROR(INT(_xlfn.AGGREGATE(14,6,'DONNÉES BRUTES'!AA$3:AA$42*1000+(40-ROW('DONNÉES BRUTES'!AA$3:AA$42)+ROW('DONNÉES BRUTES'!AA$3)),4)/1000)&"/100","—")} -> 91/100 | X11: {=IFERROR(INDEX('DONNÉES BRUTES'!P$3:P$42,MATCH(_xlfn.AGGREGATE(14,6,'DONNÉES BRUTES'!AA$3:AA$42*1000+(40-ROW('DONNÉES BRUTES'!AA$3:AA$42)+ROW('DONNÉES BRUTES'!AA$3)),4),'DONNÉES BRUTES'!AA$3:AA$42*1000+(40-ROW('DONNÉES BRUTES'!AA$3:AA$42)+ROW('DONNÉES BRUTES'!AA$3)),0)),"—")} -> +7.4%
B12: 5 | C12: {=IFERROR(INDEX('DONNÉES BRUTES'!A$3:A$42,MATCH(_xlfn.AGGREGATE(14,6,'DONNÉES BRUTES'!AB$3:AB$42*1000+(40-ROW('DONNÉES BRUTES'!AB$3:AB$42)+ROW('DONNÉES BRUTES'!AB$3)),5),'DONNÉES BRUTES'!AB$3:AB$42*1000+(40-ROW('DONNÉES BRUTES'!AB$3:AB$42)+ROW('DONNÉES BRUTES'!AB$3)),0)),"—")} -> AZN.L | D12: {=IFERROR(LEFT(INDEX('DONNÉES BRUTES'!B$3:B$42,MATCH(_xlfn.AGGREGATE(14,6,'DONNÉES BRUTES'!AB$3:AB$42*1000+(40-ROW('DONNÉES BRUTES'!AB$3:AB$42)+ROW('DONNÉES BRUTES'!AB$3)),5),'DONNÉES BRUTES'!AB$3:AB$42*1000+(40-ROW('DONNÉES BRUTES'!AB$3:AB$42)+ROW('DONNÉES BRUTES'!AB$3)),0)),18),"—")} -> AstraZeneca PLC | E12: {=IFERROR(INT(_xlfn.AGGREGATE(14,6,'DONNÉES BRUTES'!AB$3:AB$42*1000+(40-ROW('DONNÉES BRUTES'!AB$3:AB$42)+ROW('DONNÉES BRUTES'!AB$3)),5)/1000)&"/100","—")} -> 60/100 | F12: {=IFERROR(INDEX('DONNÉES BRUTES'!I$3:I$42,MATCH(_xlfn.AGGREGATE(14,6,'DONNÉES BRUTES'!AB$3:AB$42*1000+(40-ROW('DONNÉES BRUTES'!AB$3:AB$42)+ROW('DONNÉES BRUTES'!AB$3)),5),'DONNÉES BRUTES'!AB$3:AB$42*1000+(40-ROW('DONNÉES BRUTES'!AB$3:AB$42)+ROW('DONNÉES BRUTES'!AB$3)),0)),"—")} -> 1211.7 | H12: 5 | I12: {=IFERROR(INDEX('DONNÉES BRUTES'!A$3:A$42,MATCH(_xlfn.AGGREGATE(14,6,'DONNÉES BRUTES'!Y$3:Y$42*1000+(40-ROW('DONNÉES BRUTES'!Y$3:Y$42)+ROW('DONNÉES BRUTES'!Y$3)),5),'DONNÉES BRUTES'!Y$3:Y$42*1000+(40-ROW('DONNÉES BRUTES'!Y$3:Y$42)+ROW('DONNÉES BRUTES'!Y$3)),0)),"—")} -> GSK.L | J12: {=IFERROR(LEFT(INDEX('DONNÉES BRUTES'!B$3:B$42,MATCH(_xlfn.AGGREGATE(14,6,'DONNÉES BRUTES'!Y$3:Y$42*1000+(40-ROW('DONNÉES BRUTES'!Y$3:Y$42)+ROW('DONNÉES BRUTES'!Y$3)),5),'DONNÉES BRUTES'!Y$3:Y$42*1000+(40-ROW('DONNÉES BRUTES'!Y$3:Y$42)+ROW('DONNÉES BRUTES'!Y$3)),0)),18),"—")} -> GSK plc | K12: {=IFERROR(INT(_xlfn.AGGREGATE(14,6,'DONNÉES BRUTES'!Y$3:Y$42*1000+(40-ROW('DONNÉES BRUTES'!Y$3:Y$42)+ROW('DONNÉES BRUTES'!Y$3)),5)/1000)&"/100","—")} -> 78/100 | L12: {=IFERROR(INDEX('DONNÉES BRUTES'!P$3:P$42,MATCH(_xlfn.AGGREGATE(14,6,'DONNÉES BRUTES'!Y$3:Y$42*1000+(40-ROW('DONNÉES BRUTES'!Y$3:Y$42)+ROW('DONNÉES BRUTES'!Y$3)),5),'DONNÉES BRUTES'!Y$3:Y$42*1000+(40-ROW('DONNÉES BRUTES'!Y$3:Y$42)+ROW('DONNÉES BRUTES'!Y$3)),0)),"—")} -> +4.1% | N12: 5 | O12: {=IFERROR(INDEX('DONNÉES BRUTES'!A$3:A$42,MATCH(_xlfn.AGGREGATE(14,6,'DONNÉES BRUTES'!Z$3:Z$42*1000+(40-ROW('DONNÉES BRUTES'!Z$3:Z$42)+ROW('DONNÉES BRUTES'!Z$3)),5),'DONNÉES BRUTES'!Z$3:Z$42*1000+(40-ROW('DONNÉES BRUTES'!Z$3:Z$42)+ROW('DONNÉES BRUTES'!Z$3)),0)),"—")} -> RIO.L | P12: {=IFERROR(LEFT(INDEX('DONNÉES BRUTES'!B$3:B$42,MATCH(_xlfn.AGGREGATE(14,6,'DONNÉES BRUTES'!Z$3:Z$42*1000+(40-ROW('DONNÉES BRUTES'!Z$3:Z$42)+ROW('DONNÉES BRUTES'!Z$3)),5),'DONNÉES BRUTES'!Z$3:Z$42*1000+(40-ROW('DONNÉES BRUTES'!Z$3:Z$42)+ROW('DONNÉES BRUTES'!Z$3)),0)),18),"—")} -> Rio Tinto Group | Q12: {=IFERROR(INT(_xlfn.AGGREGATE(14,6,'DONNÉES BRUTES'!Z$3:Z$42*1000+(40-ROW('DONNÉES BRUTES'!Z$3:Z$42)+ROW('DONNÉES BRUTES'!Z$3)),5)/1000)&"/100","—")} -> 78/100 | R12: {=IFERROR(INDEX('DONNÉES BRUTES'!U$3:U$42,MATCH(_xlfn.AGGREGATE(14,6,'DONNÉES BRUTES'!Z$3:Z$42*1000+(40-ROW('DONNÉES BRUTES'!Z$3:Z$42)+ROW('DONNÉES BRUTES'!Z$3)),5),'DONNÉES BRUTES'!Z$3:Z$42*1000+(40-ROW('DONNÉES BRUTES'!Z$3:Z$42)+ROW('DONNÉES BRUTES'!Z$3)),0)),"—")} -> 3.45 | T12: 5 | U12: {=IFERROR(INDEX('DONNÉES BRUTES'!A$3:A$42,MATCH(_xlfn.AGGREGATE(14,6,'DONNÉES BRUTES'!AA$3:AA$42*1000+(40-ROW('DONNÉES BRUTES'!AA$3:AA$42)+ROW('DONNÉES BRUTES'!AA$3)),5),'DONNÉES BRUTES'!AA$3:AA$42*1000+(40-ROW('DONNÉES BRUTES'!AA$3:AA$42)+ROW('DONNÉES BRUTES'!AA$3)),0)),"—")} -> KER.PA | V12: {=IFERROR(LEFT(INDEX('DONNÉES BRUTES'!B$3:B$42,MATCH(_xlfn.AGGREGATE(14,6,'DONNÉES BRUTES'!AA$3:AA$42*1000+(40-ROW('DONNÉES BRUTES'!AA$3:AA$42)+ROW('DONNÉES BRUTES'!AA$3)),5),'DONNÉES BRUTES'!AA$3:AA$42*1000+(40-ROW('DONNÉES BRUTES'!AA$3:AA$42)+ROW('DONNÉES BRUTES'!AA$3)),0)),18),"—")} -> Kering SA | W12: {=IFERROR(INT(_xlfn.AGGREGATE(14,6,'DONNÉES BRUTES'!AA$3:AA$42*1000+(40-ROW('DONNÉES BRUTES'!AA$3:AA$42)+ROW('DONNÉES BRUTES'!AA$3)),5)/1000)&"/100","—")} -> 89/100 | X12: {=IFERROR(INDEX('DONNÉES BRUTES'!P$3:P$42,MATCH(_xlfn.AGGREGATE(14,6,'DONNÉES BRUTES'!AA$3:AA$42*1000+(40-ROW('DONNÉES BRUTES'!AA$3:AA$42)+ROW('DONNÉES BRUTES'!AA$3)),5),'DONNÉES BRUTES'!AA$3:AA$42*1000+(40-ROW('DONNÉES BRUTES'!AA$3:AA$42)+ROW('DONNÉES BRUTES'!AA$3)),0)),"—")} -> -13.0%
B14: TOP 10 GLOBAL · Score Composite · Value / Growth / Quality / Momentum
B15: # | C15: Ticker | D15: Société | E15: Secteur | F15: Score | H15: Growth | I15: Quality | J15: Momentum | K15: Mg.EBITDA | L15: Croiss. | N15: Next Earn. | R15: Signal
B16: 1 | C16: {=IFERROR(INDEX('DONNÉES BRUTES'!A$3:A$42,MATCH(_xlfn.AGGREGATE(14,6,'DONNÉES BRUTES'!AB$3:AB$42*1000+(40-ROW('DONNÉES BRUTES'!AB$3:AB$42)+ROW('DONNÉES BRUTES'!AB$3)),1),'DONNÉES BRUTES'!AB$3:AB$42*1000+(40-ROW('DONNÉES BRUTES'!AB$3:AB$42)+ROW('DONNÉES BRUTES'!AB$3)),0)),"—")} -> ASML.AS | D16: {=IFERROR(LEFT(IFERROR(INDEX('DONNÉES BRUTES'!B$3:B$42,MATCH(_xlfn.AGGREGATE(14,6,'DONNÉES BRUTES'!AB$3:AB$42*1000+(40-ROW('DONNÉES BRUTES'!AB$3:AB$42)+ROW('DONNÉES BRUTES'!AB$3)),1),'DONNÉES BRUTES'!AB$3:AB$42*1000+(40-ROW('DONNÉES BRUTES'!AB$3:AB$42)+ROW('DONNÉES BRUTES'!AB$3)),0)),"—"),18),"—")} -> ASML Holding N.V. | E16: {=IFERROR(INDEX('DONNÉES BRUTES'!C$3:C$42,MATCH(_xlfn.AGGREGATE(14,6,'DONNÉES BRUTES'!AB$3:AB$42*1000+(40-ROW('DONNÉES BRUTES'!AB$3:AB$42)+ROW('DONNÉES BRUTES'!AB$3)),1),'DONNÉES BRUTES'!AB$3:AB$42*1000+(40-ROW('DONNÉES BRUTES'!AB$3:AB$42)+ROW('DONNÉES BRUTES'!AB$3)),0)),"—")} -> Technologie | F16: {=IFERROR(INT(_xlfn.AGGREGATE(14,6,'DONNÉES BRUTES'!AB$3:AB$42*1000+(40-ROW('DONNÉES BRUTES'!AB$3:AB$42)+ROW('DONNÉES BRUTES'!AB$3)),1)/1000)&"/100","—")} -> 75/100 | H16: {=IFERROR(INDEX('DONNÉES BRUTES'!Y$3:Y$42,MATCH(_xlfn.AGGREGATE(14,6,'DONNÉES BRUTES'!AB$3:AB$42*1000+(40-ROW('DONNÉES BRUTES'!AB$3:AB$42)+ROW('DONNÉES BRUTES'!AB$3)),1),'DONNÉES BRUTES'!AB$3:AB$42*1000+(40-ROW('DONNÉES BRUTES'!AB$3:AB$42)+ROW('DONNÉES BRUTES'!AB$3)),0)),"—")} -> 92 | I16: {=IFERROR(INDEX('DONNÉES BRUTES'!Z$3:Z$42,MATCH(_xlfn.AGGREGATE(14,6,'DONNÉES BRUTES'!AB$3:AB$42*1000+(40-ROW('DONNÉES BRUTES'!AB$3:AB$42)+ROW('DONNÉES BRUTES'!AB$3)),1),'DONNÉES BRUTES'!AB$3:AB$42*1000+(40-ROW('DONNÉES BRUTES'!AB$3:AB$42)+ROW('DONNÉES BRUTES'!AB$3)),0)),"—")} -> 86 | J16: {=IFERROR(INDEX('DONNÉES BRUTES'!AA$3:AA$42,MATCH(_xlfn.AGGREGATE(14,6,'DONNÉES BRUTES'!AB$3:AB$42*1000+(40-ROW('DONNÉES BRUTES'!AB$3:AB$42)+ROW('DONNÉES BRUTES'!AB$3)),1),'DONNÉES BRUTES'!AB$3:AB$42*1000+(40-ROW('DONNÉES BRUTES'!AB$3:AB$42)+ROW('DONNÉES BRUTES'!AB$3)),0)),"—")} -> 98 | K16: {=IFERROR(INDEX('DONNÉES BRUTES'!N$3:N$42,MATCH(_xlfn.AGGREGATE(14,6,'DONNÉES BRUTES'!AB$3:AB$42*1000+(40-ROW('DONNÉES BRUTES'!AB$3:AB$42)+ROW('DONNÉES BRUTES'!AB$3)),1),'DONNÉES BRUTES'!AB$3:AB$42*1000+(40-ROW('DONNÉES BRUTES'!AB$3:AB$42)+ROW('DONNÉES BRUTES'!AB$3)),0)),"—")} -> 38.4% | L16: {=IFERROR(INDEX('DONNÉES BRUTES'!P$3:P$42,MATCH(_xlfn.AGGREGATE(14,6,'DONNÉES BRUTES'!AB$3:AB$42*1000+(40-ROW('DONNÉES BRUTES'!AB$3:AB$42)+ROW('DONNÉES BRUTES'!AB$3)),1),'DONNÉES BRUTES'!AB$3:AB$42*1000+(40-ROW('DONNÉES BRUTES'!AB$3:AB$42)+ROW('DONNÉES BRUTES'!AB$3)),0)),"—")} -> +15.6% | N16: {=IFERROR(INDEX('DONNÉES BRUTES'!AC$3:AC$42,MATCH(_xlfn.AGGREGATE(14,6,'DONNÉES BRUTES'!AB$3:AB$42*1000+(40-ROW('DONNÉES BRUTES'!AB$3:AB$42)+ROW('DONNÉES BRUTES'!AB$3)),1),'DONNÉES BRUTES'!AB$3:AB$42*1000+(40-ROW('DONNÉES BRUTES'!AB$3:AB$42)+ROW('DONNÉES BRUTES'!AB$3)),0)),"—")} -> 2026-04-15 | R16: {=IFERROR(INDEX('DONNÉES BRUTES'!AD$3:AD$42,MATCH(_xlfn.AGGREGATE(14,6,'DONNÉES BRUTES'!AB$3:AB$42*1000+(40-ROW('DONNÉES BRUTES'!AB$3:AB$42)+ROW('DONNÉES BRUTES'!AB$3)),1),'DONNÉES BRUTES'!AB$3:AB$42*1000+(40-ROW('DONNÉES BRUTES'!AB$3:AB$42)+ROW('DONNÉES BRUTES'!AB$3)),0)),"—")} -> Surpondérer
B17: 2 | C17: {=IFERROR(INDEX('DONNÉES BRUTES'!A$3:A$42,MATCH(_xlfn.AGGREGATE(14,6,'DONNÉES BRUTES'!AB$3:AB$42*1000+(40-ROW('DONNÉES BRUTES'!AB$3:AB$42)+ROW('DONNÉES BRUTES'!AB$3)),2),'DONNÉES BRUTES'!AB$3:AB$42*1000+(40-ROW('DONNÉES BRUTES'!AB$3:AB$42)+ROW('DONNÉES BRUTES'!AB$3)),0)),"—")} -> RIO.L | D17: {=IFERROR(LEFT(IFERROR(INDEX('DONNÉES BRUTES'!B$3:B$42,MATCH(_xlfn.AGGREGATE(14,6,'DONNÉES BRUTES'!AB$3:AB$42*1000+(40-ROW('DONNÉES BRUTES'!AB$3:AB$42)+ROW('DONNÉES BRUTES'!AB$3)),2),'DONNÉES BRUTES'!AB$3:AB$42*1000+(40-ROW('DONNÉES BRUTES'!AB$3:AB$42)+ROW('DONNÉES BRUTES'!AB$3)),0)),"—"),18),"—")} -> Rio Tinto Group | E17: {=IFERROR(INDEX('DONNÉES BRUTES'!C$3:C$42,MATCH(_xlfn.AGGREGATE(14,6,'DONNÉES BRUTES'!AB$3:AB$42*1000+(40-ROW('DONNÉES BRUTES'!AB$3:AB$42)+ROW('DONNÉES BRUTES'!AB$3)),2),'DONNÉES BRUTES'!AB$3:AB$42*1000+(40-ROW('DONNÉES BRUTES'!AB$3:AB$42)+ROW('DONNÉES BRUTES'!AB$3)),0)),"—")} -> Matériaux | F17: {=IFERROR(INT(_xlfn.AGGREGATE(14,6,'DONNÉES BRUTES'!AB$3:AB$42*1000+(40-ROW('DONNÉES BRUTES'!AB$3:AB$42)+ROW('DONNÉES BRUTES'!AB$3)),2)/1000)&"/100","—")} -> 70/100 | H17: {=IFERROR(INDEX('DONNÉES BRUTES'!Y$3:Y$42,MATCH(_xlfn.AGGREGATE(14,6,'DONNÉES BRUTES'!AB$3:AB$42*1000+(40-ROW('DONNÉES BRUTES'!AB$3:AB$42)+ROW('DONNÉES BRUTES'!AB$3)),2),'DONNÉES BRUTES'!AB$3:AB$42*1000+(40-ROW('DONNÉES BRUTES'!AB$3:AB$42)+ROW('DONNÉES BRUTES'!AB$3)),0)),"—")} -> 77 | I17: {=IFERROR(INDEX('DONNÉES BRUTES'!Z$3:Z$42,MATCH(_xlfn.AGGREGATE(14,6,'DONNÉES BRUTES'!AB$3:AB$42*1000+(40-ROW('DONNÉES BRUTES'!AB$3:AB$42)+ROW('DONNÉES BRUTES'!AB$3)),2),'DONNÉES BRUTES'!AB$3:AB$42*1000+(40-ROW('DONNÉES BRUTES'!AB$3:AB$42)+ROW('DONNÉES BRUTES'!AB$3)),0)),"—")} -> 78 | J17: {=IFERROR(INDEX('DONNÉES BRUTES'!AA$3:AA$42,MATCH(_xlfn.AGGREGATE(14,6,'DONNÉES BRUTES'!AB$3:AB$42*1000+(40-ROW('DONNÉES BRUTES'!AB$3:AB$42)+ROW('DONNÉES BRUTES'!AB$3)),2),'DONNÉES BRUTES'!AB$3:AB$42*1000+(40-ROW('DONNÉES BRUTES'!AB$3:AB$42)+ROW('DONNÉES BRUTES'!AB$3)),0)),"—")} -> 91 | K17: {=IFERROR(INDEX('DONNÉES BRUTES'!N$3:N$42,MATCH(_xlfn.AGGREGATE(14,6,'DONNÉES BRUTES'!AB$3:AB$42*1000+(40-ROW('DONNÉES BRUTES'!AB$3:AB$42)+ROW('DONNÉES BRUTES'!AB$3)),2),'DONNÉES BRUTES'!AB$3:AB$42*1000+(40-ROW('DONNÉES BRUTES'!AB$3:AB$42)+ROW('DONNÉES BRUTES'!AB$3)),0)),"—")} -> 39.9% | L17: {=IFERROR(INDEX('DONNÉES BRUTES'!P$3:P$42,MATCH(_xlfn.AGGREGATE(14,6,'DONNÉES BRUTES'!AB$3:AB$42*1000+(40-ROW('DONNÉES BRUTES'!AB$3:AB$42)+ROW('DONNÉES BRUTES'!AB$3)),2),'DONNÉES BRUTES'!AB$3:AB$42*1000+(40-ROW('DONNÉES BRUTES'!AB$3:AB$42)+ROW('DONNÉES BRUTES'!AB$3)),0)),"—")} -> +7.4% | N17: {=IFERROR(INDEX('DONNÉES BRUTES'!AC$3:AC$42,MATCH(_xlfn.AGGREGATE(14,6,'DONNÉES BRUTES'!AB$3:AB$42*1000+(40-ROW('DONNÉES BRUTES'!AB$3:AB$42)+ROW('DONNÉES BRUTES'!AB$3)),2),'DONNÉES BRUTES'!AB$3:AB$42*1000+(40-ROW('DONNÉES BRUTES'!AB$3:AB$42)+ROW('DONNÉES BRUTES'!AB$3)),0)),"—")} -> — | R17: {=IFERROR(INDEX('DONNÉES BRUTES'!AD$3:AD$42,MATCH(_xlfn.AGGREGATE(14,6,'DONNÉES BRUTES'!AB$3:AB$42*1000+(40-ROW('DONNÉES BRUTES'!AB$3:AB$42)+ROW('DONNÉES BRUTES'!AB$3)),2),'DONNÉES BRUTES'!AB$3:AB$42*1000+(40-ROW('DONNÉES BRUTES'!AB$3:AB$42)+ROW('DONNÉES BRUTES'!AB$3)),0)),"—")} -> Surpondérer
B18: 3 | C18: {=IFERROR(INDEX('DONNÉES BRUTES'!A$3:A$42,MATCH(_xlfn.AGGREGATE(14,6,'DONNÉES BRUTES'!AB$3:AB$42*1000+(40-ROW('DONNÉES BRUTES'!AB$3:AB$42)+ROW('DONNÉES BRUTES'!AB$3)),3),'DONNÉES BRUTES'!AB$3:AB$42*1000+(40-ROW('DONNÉES BRUTES'!AB$3:AB$42)+ROW('DONNÉES BRUTES'!AB$3)),0)),"—")} -> RMS.PA | D18: {=IFERROR(LEFT(IFERROR(INDEX('DONNÉES BRUTES'!B$3:B$42,MATCH(_xlfn.AGGREGATE(14,6,'DONNÉES BRUTES'!AB$3:AB$42*1000+(40-ROW('DONNÉES BRUTES'!AB$3:AB$42)+ROW('DONNÉES BRUTES'!AB$3)),3),'DONNÉES BRUTES'!AB$3:AB$42*1000+(40-ROW('DONNÉES BRUTES'!AB$3:AB$42)+ROW('DONNÉES BRUTES'!AB$3)),0)),"—"),18),"—")} -> Hermès Internation | E18: {=IFERROR(INDEX('DONNÉES BRUTES'!C$3:C$42,MATCH(_xlfn.AGGREGATE(14,6,'DONNÉES BRUTES'!AB$3:AB$42*1000+(40-ROW('DONNÉES BRUTES'!AB$3:AB$42)+ROW('DONNÉES BRUTES'!AB$3)),3),'DONNÉES BRUTES'!AB$3:AB$42*1000+(40-ROW('DONNÉES BRUTES'!AB$3:AB$42)+ROW('DONNÉES BRUTES'!AB$3)),0)),"—")} -> Conso. Cycl. | F18: {=IFERROR(INT(_xlfn.AGGREGATE(14,6,'DONNÉES BRUTES'!AB$3:AB$42*1000+(40-ROW('DONNÉES BRUTES'!AB$3:AB$42)+ROW('DONNÉES BRUTES'!AB$3)),3)/1000)&"/100","—")} -> 65/100 | H18: {=IFERROR(INDEX('DONNÉES BRUTES'!Y$3:Y$42,MATCH(_xlfn.AGGREGATE(14,6,'DONNÉES BRUTES'!AB$3:AB$42*1000+(40-ROW('DONNÉES BRUTES'!AB$3:AB$42)+ROW('DONNÉES BRUTES'!AB$3)),3),'DONNÉES BRUTES'!AB$3:AB$42*1000+(40-ROW('DONNÉES BRUTES'!AB$3:AB$42)+ROW('DONNÉES BRUTES'!AB$3)),0)),"—")} -> 81 | I18: {=IFERROR(INDEX('DONNÉES BRUTES'!Z$3:Z$42,MATCH(_xlfn.AGGREGATE(14,6,'DONNÉES BRUTES'!AB$3:AB$42*1000+(40-ROW('DONNÉES BRUTES'!AB$3:AB$42)+ROW('DONNÉES BRUTES'!AB$3)),3),'DONNÉES BRUTES'!AB$3:AB$42*1000+(40-ROW('DONNÉES BRUTES'!AB$3:AB$42)+ROW('DONNÉES BRUTES'!AB$3)),0)),"—")} -> 99 | J18: {=IFERROR(INDEX('DONNÉES BRUTES'!AA$3:AA$42,MATCH(_xlfn.AGGREGATE(14,6,'DONNÉES BRUTES'!AB$3:AB$42*1000+(40-ROW('DONNÉES BRUTES'!AB$3:AB$42)+ROW('DONNÉES BRUTES'!AB$3)),3),'DONNÉES BRUTES'!AB$3:AB$42*1000+(40-ROW('DONNÉES BRUTES'!AB$3:AB$42)+ROW('DONNÉES BRUTES'!AB$3)),0)),"—")} -> 4 | K18: {=IFERROR(INDEX('DONNÉES BRUTES'!N$3:N$42,MATCH(_xlfn.AGGREGATE(14,6,'DONNÉES BRUTES'!AB$3:AB$42*1000+(40-ROW('DONNÉES BRUTES'!AB$3:AB$42)+ROW('DONNÉES BRUTES'!AB$3)),3),'DONNÉES BRUTES'!AB$3:AB$42*1000+(40-ROW('DONNÉES BRUTES'!AB$3:AB$42)+ROW('DONNÉES BRUTES'!AB$3)),0)),"—")} -> 46.8% | L18: {=IFERROR(INDEX('DONNÉES BRUTES'!P$3:P$42,MATCH(_xlfn.AGGREGATE(14,6,'DONNÉES BRUTES'!AB$3:AB$42*1000+(40-ROW('DONNÉES BRUTES'!AB$3:AB$42)+ROW('DONNÉES BRUTES'!AB$3)),3),'DONNÉES BRUTES'!AB$3:AB$42*1000+(40-ROW('DONNÉES BRUTES'!AB$3:AB$42)+ROW('DONNÉES BRUTES'!AB$3)),0)),"—")} -> +5.5% | N18: {=IFERROR(INDEX('DONNÉES BRUTES'!AC$3:AC$42,MATCH(_xlfn.AGGREGATE(14,6,'DONNÉES BRUTES'!AB$3:AB$42*1000+(40-ROW('DONNÉES BRUTES'!AB$3:AB$42)+ROW('DONNÉES BRUTES'!AB$3)),3),'DONNÉES BRUTES'!AB$3:AB$42*1000+(40-ROW('DONNÉES BRUTES'!AB$3:AB$42)+ROW('DONNÉES BRUTES'!AB$3)),0)),"—")} -> — | R18: {=IFERROR(INDEX('DONNÉES BRUTES'!AD$3:AD$42,MATCH(_xlfn.AGGREGATE(14,6,'DONNÉES BRUTES'!AB$3:AB$42*1000+(40-ROW('DONNÉES BRUTES'!AB$3:AB$42)+ROW('DONNÉES BRUTES'!AB$3)),3),'DONNÉES BRUTES'!AB$3:AB$42*1000+(40-ROW('DONNÉES BRUTES'!AB$3:AB$42)+ROW('DONNÉES BRUTES'!AB$3)),0)),"—")} -> Surpondérer
B19: 4 | C19: {=IFERROR(INDEX('DONNÉES BRUTES'!A$3:A$42,MATCH(_xlfn.AGGREGATE(14,6,'DONNÉES BRUTES'!AB$3:AB$42*1000+(40-ROW('DONNÉES BRUTES'!AB$3:AB$42)+ROW('DONNÉES BRUTES'!AB$3)),4),'DONNÉES BRUTES'!AB$3:AB$42*1000+(40-ROW('DONNÉES BRUTES'!AB$3:AB$42)+ROW('DONNÉES BRUTES'!AB$3)),0)),"—")} -> SAP.DE | D19: {=IFERROR(LEFT(IFERROR(INDEX('DONNÉES BRUTES'!B$3:B$42,MATCH(_xlfn.AGGREGATE(14,6,'DONNÉES BRUTES'!AB$3:AB$42*1000+(40-ROW('DONNÉES BRUTES'!AB$3:AB$42)+ROW('DONNÉES BRUTES'!AB$3)),4),'DONNÉES BRUTES'!AB$3:AB$42*1000+(40-ROW('DONNÉES BRUTES'!AB$3:AB$42)+ROW('DONNÉES BRUTES'!AB$3)),0)),"—"),18),"—")} -> SAP SE | E19: {=IFERROR(INDEX('DONNÉES BRUTES'!C$3:C$42,MATCH(_xlfn.AGGREGATE(14,6,'DONNÉES BRUTES'!AB$3:AB$42*1000+(40-ROW('DONNÉES BRUTES'!AB$3:AB$42)+ROW('DONNÉES BRUTES'!AB$3)),4),'DONNÉES BRUTES'!AB$3:AB$42*1000+(40-ROW('DONNÉES BRUTES'!AB$3:AB$42)+ROW('DONNÉES BRUTES'!AB$3)),0)),"—")} -> Technologie | F19: {=IFERROR(INT(_xlfn.AGGREGATE(14,6,'DONNÉES BRUTES'!AB$3:AB$42*1000+(40-ROW('DONNÉES BRUTES'!AB$3:AB$42)+ROW('DONNÉES BRUTES'!AB$3)),4)/1000)&"/100","—")} -> 62/100 | H19: {=IFERROR(INDEX('DONNÉES BRUTES'!Y$3:Y$42,MATCH(_xlfn.AGGREGATE(14,6,'DONNÉES BRUTES'!AB$3:AB$42*1000+(40-ROW('DONNÉES BRUTES'!AB$3:AB$42)+ROW('DONNÉES BRUTES'!AB$3)),4),'DONNÉES BRUTES'!AB$3:AB$42*1000+(40-ROW('DONNÉES BRUTES'!AB$3:AB$42)+ROW('DONNÉES BRUTES'!AB$3)),0)),"—")} -> 78 | I19: {=IFERROR(INDEX('DONNÉES BRUTES'!Z$3:Z$42,MATCH(_xlfn.AGGREGATE(14,6,'DONNÉES BRUTES'!AB$3:AB$42*1000+(40-ROW('DONNÉES BRUTES'!AB$3:AB$42)+ROW('DONNÉES BRUTES'!AB$3)),4),'DONNÉES BRUTES'!AB$3:AB$42*1000+(40-ROW('DONNÉES BRUTES'!AB$3:AB$42)+ROW('DONNÉES BRUTES'!AB$3)),0)),"—")} -> 80 | J19: {=IFERROR(INDEX('DONNÉES BRUTES'!AA$3:AA$42,MATCH(_xlfn.AGGREGATE(14,6,'DONNÉES BRUTES'!AB$3:AB$42*1000+(40-ROW('DONNÉES BRUTES'!AB$3:AB$42)+ROW('DONNÉES BRUTES'!AB$3)),4),'DONNÉES BRUTES'!AB$3:AB$42*1000+(40-ROW('DONNÉES BRUTES'!AB$3:AB$42)+ROW('DONNÉES BRUTES'!AB$3)),0)),"—")} -> 0 | K19: {=IFERROR(INDEX('DONNÉES BRUTES'!N$3:N$42,MATCH(_xlfn.AGGREGATE(14,6,'DONNÉES BRUTES'!AB$3:AB$42*1000+(40-ROW('DONNÉES BRUTES'!AB$3:AB$42)+ROW('DONNÉES BRUTES'!AB$3)),4),'DONNÉES BRUTES'!AB$3:AB$42*1000+(40-ROW('DONNÉES BRUTES'!AB$3:AB$42)+ROW('DONNÉES BRUTES'!AB$3)),0)),"—")} -> 32.8% | L19: {=IFERROR(INDEX('DONNÉES BRUTES'!P$3:P$42,MATCH(_xlfn.AGGREGATE(14,6,'DONNÉES BRUTES'!AB$3:AB$42*1000+(40-ROW('DONNÉES BRUTES'!AB$3:AB$42)+ROW('DONNÉES BRUTES'!AB$3)),4),'DONNÉES BRUTES'!AB$3:AB$42*1000+(40-ROW('DONNÉES BRUTES'!AB$3:AB$42)+ROW('DONNÉES BRUTES'!AB$3)),0)),"—")} -> +7.7% | N19: {=IFERROR(INDEX('DONNÉES BRUTES'!AC$3:AC$42,MATCH(_xlfn.AGGREGATE(14,6,'DONNÉES BRUTES'!AB$3:AB$42*1000+(40-ROW('DONNÉES BRUTES'!AB$3:AB$42)+ROW('DONNÉES BRUTES'!AB$3)),4),'DONNÉES BRUTES'!AB$3:AB$42*1000+(40-ROW('DONNÉES BRUTES'!AB$3:AB$42)+ROW('DONNÉES BRUTES'!AB$3)),0)),"—")} -> 2026-04-23 | R19: {=IFERROR(INDEX('DONNÉES BRUTES'!AD$3:AD$42,MATCH(_xlfn.AGGREGATE(14,6,'DONNÉES BRUTES'!AB$3:AB$42*1000+(40-ROW('DONNÉES BRUTES'!AB$3:AB$42)+ROW('DONNÉES BRUTES'!AB$3)),4),'DONNÉES BRUTES'!AB$3:AB$42*1000+(40-ROW('DONNÉES BRUTES'!AB$3:AB$42)+ROW('DONNÉES BRUTES'!AB$3)),0)),"—")} -> Surpondérer
B20: 5 | C20: {=IFERROR(INDEX('DONNÉES BRUTES'!A$3:A$42,MATCH(_xlfn.AGGREGATE(14,6,'DONNÉES BRUTES'!AB$3:AB$42*1000+(40-ROW('DONNÉES BRUTES'!AB$3:AB$42)+ROW('DONNÉES BRUTES'!AB$3)),5),'DONNÉES BRUTES'!AB$3:AB$42*1000+(40-ROW('DONNÉES BRUTES'!AB$3:AB$42)+ROW('DONNÉES BRUTES'!AB$3)),0)),"—")} -> AZN.L | D20: {=IFERROR(LEFT(IFERROR(INDEX('DONNÉES BRUTES'!B$3:B$42,MATCH(_xlfn.AGGREGATE(14,6,'DONNÉES BRUTES'!AB$3:AB$42*1000+(40-ROW('DONNÉES BRUTES'!AB$3:AB$42)+ROW('DONNÉES BRUTES'!AB$3)),5),'DONNÉES BRUTES'!AB$3:AB$42*1000+(40-ROW('DONNÉES BRUTES'!AB$3:AB$42)+ROW('DONNÉES BRUTES'!AB$3)),0)),"—"),18),"—")} -> AstraZeneca PLC | E20: {=IFERROR(INDEX('DONNÉES BRUTES'!C$3:C$42,MATCH(_xlfn.AGGREGATE(14,6,'DONNÉES BRUTES'!AB$3:AB$42*1000+(40-ROW('DONNÉES BRUTES'!AB$3:AB$42)+ROW('DONNÉES BRUTES'!AB$3)),5),'DONNÉES BRUTES'!AB$3:AB$42*1000+(40-ROW('DONNÉES BRUTES'!AB$3:AB$42)+ROW('DONNÉES BRUTES'!AB$3)),0)),"—")} -> Santé | F20: {=IFERROR(INT(_xlfn.AGGREGATE(14,6,'DONNÉES BRUTES'!AB$3:AB$42*1000+(40-ROW('DONNÉES BRUTES'!AB$3:AB$42)+ROW('DONNÉES BRUTES'!AB$3)),5)/1000)&"/100","—")} -> 60/100 | H20: {=IFERROR(INDEX('DONNÉES BRUTES'!Y$3:Y$42,MATCH(_xlfn.AGGREGATE(14,6,'DONNÉES BRUTES'!AB$3:AB$42*1000+(40-ROW('DONNÉES BRUTES'!AB$3:AB$42)+ROW('DONNÉES BRUTES'!AB$3)),5),'DONNÉES BRUTES'!AB$3:AB$42*1000+(40-ROW('DONNÉES BRUTES'!AB$3:AB$42)+ROW('DONNÉES BRUTES'!AB$3)),0)),"—")} -> 87 | I20: {=IFERROR(INDEX('DONNÉES BRUTES'!Z$3:Z$42,MATCH(_xlfn.AGGREGATE(14,6,'DONNÉES BRUTES'!AB$3:AB$42*1000+(40-ROW('DONNÉES BRUTES'!AB$3:AB$42)+ROW('DONNÉES BRUTES'!AB$3)),5),'DONNÉES BRUTES'!AB$3:AB$42*1000+(40-ROW('DONNÉES BRUTES'!AB$3:AB$42)+ROW('DONNÉES BRUTES'!AB$3)),0)),"—")} -> 50 | J20: {=IFERROR(INDEX('DONNÉES BRUTES'!AA$3:AA$42,MATCH(_xlfn.AGGREGATE(14,6,'DONNÉES BRUTES'!AB$3:AB$42*1000+(40-ROW('DONNÉES BRUTES'!AB$3:AB$42)+ROW('DONNÉES BRUTES'!AB$3)),5),'DONNÉES BRUTES'!AB$3:AB$42*1000+(40-ROW('DONNÉES BRUTES'!AB$3:AB$42)+ROW('DONNÉES BRUTES'!AB$3)),0)),"—")} -> 70 | K20: {=IFERROR(INDEX('DONNÉES BRUTES'!N$3:N$42,MATCH(_xlfn.AGGREGATE(14,6,'DONNÉES BRUTES'!AB$3:AB$42*1000+(40-ROW('DONNÉES BRUTES'!AB$3:AB$42)+ROW('DONNÉES BRUTES'!AB$3)),5),'DONNÉES BRUTES'!AB$3:AB$42*1000+(40-ROW('DONNÉES BRUTES'!AB$3:AB$42)+ROW('DONNÉES BRUTES'!AB$3)),0)),"—")} -> 33.2% | L20: {=IFERROR(INDEX('DONNÉES BRUTES'!P$3:P$42,MATCH(_xlfn.AGGREGATE(14,6,'DONNÉES BRUTES'!AB$3:AB$42*1000+(40-ROW('DONNÉES BRUTES'!AB$3:AB$42)+ROW('DONNÉES BRUTES'!AB$3)),5),'DONNÉES BRUTES'!AB$3:AB$42*1000+(40-ROW('DONNÉES BRUTES'!AB$3:AB$42)+ROW('DONNÉES BRUTES'!AB$3)),0)),"—")} -> +8.6% | N20: {=IFERROR(INDEX('DONNÉES BRUTES'!AC$3:AC$42,MATCH(_xlfn.AGGREGATE(14,6,'DONNÉES BRUTES'!AB$3:AB$42*1000+(40-ROW('DONNÉES BRUTES'!AB$3:AB$42)+ROW('DONNÉES BRUTES'!AB$3)),5),'DONNÉES BRUTES'!AB$3:AB$42*1000+(40-ROW('DONNÉES BRUTES'!AB$3:AB$42)+ROW('DONNÉES BRUTES'!AB$3)),0)),"—")} -> 2026-04-29 | R20: {=IFERROR(INDEX('DONNÉES BRUTES'!AD$3:AD$42,MATCH(_xlfn.AGGREGATE(14,6,'DONNÉES BRUTES'!AB$3:AB$42*1000+(40-ROW('DONNÉES BRUTES'!AB$3:AB$42)+ROW('DONNÉES BRUTES'!AB$3)),5),'DONNÉES BRUTES'!AB$3:AB$42*1000+(40-ROW('DONNÉES BRUTES'!AB$3:AB$42)+ROW('DONNÉES BRUTES'!AB$3)),0)),"—")} -> Surpondérer
B21: 6 | C21: {=IFERROR(INDEX('DONNÉES BRUTES'!A$3:A$42,MATCH(_xlfn.AGGREGATE(14,6,'DONNÉES BRUTES'!AB$3:AB$42*1000+(40-ROW('DONNÉES BRUTES'!AB$3:AB$42)+ROW('DONNÉES BRUTES'!AB$3)),6),'DONNÉES BRUTES'!AB$3:AB$42*1000+(40-ROW('DONNÉES BRUTES'!AB$3:AB$42)+ROW('DONNÉES BRUTES'!AB$3)),0)),"—")} -> RWE.DE | D21: {=IFERROR(LEFT(IFERROR(INDEX('DONNÉES BRUTES'!B$3:B$42,MATCH(_xlfn.AGGREGATE(14,6,'DONNÉES BRUTES'!AB$3:AB$42*1000+(40-ROW('DONNÉES BRUTES'!AB$3:AB$42)+ROW('DONNÉES BRUTES'!AB$3)),6),'DONNÉES BRUTES'!AB$3:AB$42*1000+(40-ROW('DONNÉES BRUTES'!AB$3:AB$42)+ROW('DONNÉES BRUTES'!AB$3)),0)),"—"),18),"—")} -> RWE Aktiengesellsc | E21: {=IFERROR(INDEX('DONNÉES BRUTES'!C$3:C$42,MATCH(_xlfn.AGGREGATE(14,6,'DONNÉES BRUTES'!AB$3:AB$42*1000+(40-ROW('DONNÉES BRUTES'!AB$3:AB$42)+ROW('DONNÉES BRUTES'!AB$3)),6),'DONNÉES BRUTES'!AB$3:AB$42*1000+(40-ROW('DONNÉES BRUTES'!AB$3:AB$42)+ROW('DONNÉES BRUTES'!AB$3)),0)),"—")} -> Serv. Publ. | F21: {=IFERROR(INT(_xlfn.AGGREGATE(14,6,'DONNÉES BRUTES'!AB$3:AB$42*1000+(40-ROW('DONNÉES BRUTES'!AB$3:AB$42)+ROW('DONNÉES BRUTES'!AB$3)),6)/1000)&"/100","—")} -> 60/100 | H21: {=IFERROR(INDEX('DONNÉES BRUTES'!Y$3:Y$42,MATCH(_xlfn.AGGREGATE(14,6,'DONNÉES BRUTES'!AB$3:AB$42*1000+(40-ROW('DONNÉES BRUTES'!AB$3:AB$42)+ROW('DONNÉES BRUTES'!AB$3)),6),'DONNÉES BRUTES'!AB$3:AB$42*1000+(40-ROW('DONNÉES BRUTES'!AB$3:AB$42)+ROW('DONNÉES BRUTES'!AB$3)),0)),"—")} -> 37 | I21: {=IFERROR(INDEX('DONNÉES BRUTES'!Z$3:Z$42,MATCH(_xlfn.AGGREGATE(14,6,'DONNÉES BRUTES'!AB$3:AB$42*1000+(40-ROW('DONNÉES BRUTES'!AB$3:AB$42)+ROW('DONNÉES BRUTES'!AB$3)),6),'DONNÉES BRUTES'!AB$3:AB$42*1000+(40-ROW('DONNÉES BRUTES'!AB$3:AB$42)+ROW('DONNÉES BRUTES'!AB$3)),0)),"—")} -> 66 | J21: {=IFERROR(INDEX('DONNÉES BRUTES'!AA$3:AA$42,MATCH(_xlfn.AGGREGATE(14,6,'DONNÉES BRUTES'!AB$3:AB$42*1000+(40-ROW('DONNÉES BRUTES'!AB$3:AB$42)+ROW('DONNÉES BRUTES'!AB$3)),6),'DONNÉES BRUTES'!AB$3:AB$42*1000+(40-ROW('DONNÉES BRUTES'!AB$3:AB$42)+ROW('DONNÉES BRUTES'!AB$3)),0)),"—")} -> 96 | K21: {=IFERROR(INDEX('DONNÉES BRUTES'!N$3:N$42,MATCH(_xlfn.AGGREGATE(14,6,'DONNÉES BRUTES'!AB$3:AB$42*1000+(40-ROW('DONNÉES BRUTES'!AB$3:AB$42)+ROW('DONNÉES BRUTES'!AB$3)),6),'DONNÉES BRUTES'!AB$3:AB$42*1000+(40-ROW('DONNÉES BRUTES'!AB$3:AB$42)+ROW('DONNÉES BRUTES'!AB$3)),0)),"—")} -> 39.1% | L21: {=IFERROR(INDEX('DONNÉES BRUTES'!P$3:P$42,MATCH(_xlfn.AGGREGATE(14,6,'DONNÉES BRUTES'!AB$3:AB$42*1000+(40-ROW('DONNÉES BRUTES'!AB$3:AB$42)+ROW('DONNÉES BRUTES'!AB$3)),6),'DONNÉES BRUTES'!AB$3:AB$42*1000+(40-ROW('DONNÉES BRUTES'!AB$3:AB$42)+ROW('DONNÉES BRUTES'!AB$3)),0)),"—")} -> -27.2% | N21: {=IFERROR(INDEX('DONNÉES BRUTES'!AC$3:AC$42,MATCH(_xlfn.AGGREGATE(14,6,'DONNÉES BRUTES'!AB$3:AB$42*1000+(40-ROW('DONNÉES BRUTES'!AB$3:AB$42)+ROW('DONNÉES BRUTES'!AB$3)),6),'DONNÉES BRUTES'!AB$3:AB$42*1000+(40-ROW('DONNÉES BRUTES'!AB$3:AB$42)+ROW('DONNÉES BRUTES'!AB$3)),0)),"—")} -> 2026-05-13 | R21: {=IFERROR(INDEX('DONNÉES BRUTES'!AD$3:AD$42,MATCH(_xlfn.AGGREGATE(14,6,'DONNÉES BRUTES'!AB$3:AB$42*1000+(40-ROW('DONNÉES BRUTES'!AB$3:AB$42)+ROW('DONNÉES BRUTES'!AB$3)),6),'DONNÉES BRUTES'!AB$3:AB$42*1000+(40-ROW('DONNÉES BRUTES'!AB$3:AB$42)+ROW('DONNÉES BRUTES'!AB$3)),0)),"—")} -> Surpondérer
B22: 7 | C22: {=IFERROR(INDEX('DONNÉES BRUTES'!A$3:A$42,MATCH(_xlfn.AGGREGATE(14,6,'DONNÉES BRUTES'!AB$3:AB$42*1000+(40-ROW('DONNÉES BRUTES'!AB$3:AB$42)+ROW('DONNÉES BRUTES'!AB$3)),7),'DONNÉES BRUTES'!AB$3:AB$42*1000+(40-ROW('DONNÉES BRUTES'!AB$3:AB$42)+ROW('DONNÉES BRUTES'!AB$3)),0)),"—")} -> ITX.MC | D22: {=IFERROR(LEFT(IFERROR(INDEX('DONNÉES BRUTES'!B$3:B$42,MATCH(_xlfn.AGGREGATE(14,6,'DONNÉES BRUTES'!AB$3:AB$42*1000+(40-ROW('DONNÉES BRUTES'!AB$3:AB$42)+ROW('DONNÉES BRUTES'!AB$3)),7),'DONNÉES BRUTES'!AB$3:AB$42*1000+(40-ROW('DONNÉES BRUTES'!AB$3:AB$42)+ROW('DONNÉES BRUTES'!AB$3)),0)),"—"),18),"—")} -> Industria de Diseñ | E22: {=IFERROR(INDEX('DONNÉES BRUTES'!C$3:C$42,MATCH(_xlfn.AGGREGATE(14,6,'DONNÉES BRUTES'!AB$3:AB$42*1000+(40-ROW('DONNÉES BRUTES'!AB$3:AB$42)+ROW('DONNÉES BRUTES'!AB$3)),7),'DONNÉES BRUTES'!AB$3:AB$42*1000+(40-ROW('DONNÉES BRUTES'!AB$3:AB$42)+ROW('DONNÉES BRUTES'!AB$3)),0)),"—")} -> Conso. Cycl. | F22: {=IFERROR(INT(_xlfn.AGGREGATE(14,6,'DONNÉES BRUTES'!AB$3:AB$42*1000+(40-ROW('DONNÉES BRUTES'!AB$3:AB$42)+ROW('DONNÉES BRUTES'!AB$3)),7)/1000)&"/100","—")} -> 58/100 | H22: {=IFERROR(INDEX('DONNÉES BRUTES'!Y$3:Y$42,MATCH(_xlfn.AGGREGATE(14,6,'DONNÉES BRUTES'!AB$3:AB$42*1000+(40-ROW('DONNÉES BRUTES'!AB$3:AB$42)+ROW('DONNÉES BRUTES'!AB$3)),7),'DONNÉES BRUTES'!AB$3:AB$42*1000+(40-ROW('DONNÉES BRUTES'!AB$3:AB$42)+ROW('DONNÉES BRUTES'!AB$3)),0)),"—")} -> 67 | I22: {=IFERROR(INDEX('DONNÉES BRUTES'!Z$3:Z$42,MATCH(_xlfn.AGGREGATE(14,6,'DONNÉES BRUTES'!AB$3:AB$42*1000+(40-ROW('DONNÉES BRUTES'!AB$3:AB$42)+ROW('DONNÉES BRUTES'!AB$3)),7),'DONNÉES BRUTES'!AB$3:AB$42*1000+(40-ROW('DONNÉES BRUTES'!AB$3:AB$42)+ROW('DONNÉES BRUTES'!AB$3)),0)),"—")} -> 83 | J22: {=IFERROR(INDEX('DONNÉES BRUTES'!AA$3:AA$42,MATCH(_xlfn.AGGREGATE(14,6,'DONNÉES BRUTES'!AB$3:AB$42*1000+(40-ROW('DONNÉES BRUTES'!AB$3:AB$42)+ROW('DONNÉES BRUTES'!AB$3)),7),'DONNÉES BRUTES'!AB$3:AB$42*1000+(40-ROW('DONNÉES BRUTES'!AB$3:AB$42)+ROW('DONNÉES BRUTES'!AB$3)),0)),"—")} -> 51 | K22: {=IFERROR(INDEX('DONNÉES BRUTES'!N$3:N$42,MATCH(_xlfn.AGGREGATE(14,6,'DONNÉES BRUTES'!AB$3:AB$42*1000+(40-ROW('DONNÉES BRUTES'!AB$3:AB$42)+ROW('DONNÉES BRUTES'!AB$3)),7),'DONNÉES BRUTES'!AB$3:AB$42*1000+(40-ROW('DONNÉES BRUTES'!AB$3:AB$42)+ROW('DONNÉES BRUTES'!AB$3)),0)),"—")} -> 29.2% | L22: {=IFERROR(INDEX('DONNÉES BRUTES'!P$3:P$42,MATCH(_xlfn.AGGREGATE(14,6,'DONNÉES BRUTES'!AB$3:AB$42*1000+(40-ROW('DONNÉES BRUTES'!AB$3:AB$42)+ROW('DONNÉES BRUTES'!AB$3)),7),'DONNÉES BRUTES'!AB$3:AB$42*1000+(40-ROW('DONNÉES BRUTES'!AB$3:AB$42)+ROW('DONNÉES BRUTES'!AB$3)),0)),"—")} -> +3.2% | N22: {=IFERROR(INDEX('DONNÉES BRUTES'!AC$3:AC$42,MATCH(_xlfn.AGGREGATE(14,6,'DONNÉES BRUTES'!AB$3:AB$42*1000+(40-ROW('DONNÉES BRUTES'!AB$3:AB$42)+ROW('DONNÉES BRUTES'!AB$3)),7),'DONNÉES BRUTES'!AB$3:AB$42*1000+(40-ROW('DONNÉES BRUTES'!AB$3:AB$42)+ROW('DONNÉES BRUTES'!AB$3)),0)),"—")} -> 2026-06-03 | R22: {=IFERROR(INDEX('DONNÉES BRUTES'!AD$3:AD$42,MATCH(_xlfn.AGGREGATE(14,6,'DONNÉES BRUTES'!AB$3:AB$42*1000+(40-ROW('DONNÉES BRUTES'!AB$3:AB$42)+ROW('DONNÉES BRUTES'!AB$3)),7),'DONNÉES BRUTES'!AB$3:AB$42*1000+(40-ROW('DONNÉES BRUTES'!AB$3:AB$42)+ROW('DONNÉES BRUTES'!AB$3)),0)),"—")} -> Neutre
B23: 8 | C23: {=IFERROR(INDEX('DONNÉES BRUTES'!A$3:A$42,MATCH(_xlfn.AGGREGATE(14,6,'DONNÉES BRUTES'!AB$3:AB$42*1000+(40-ROW('DONNÉES BRUTES'!AB$3:AB$42)+ROW('DONNÉES BRUTES'!AB$3)),8),'DONNÉES BRUTES'!AB$3:AB$42*1000+(40-ROW('DONNÉES BRUTES'!AB$3:AB$42)+ROW('DONNÉES BRUTES'!AB$3)),0)),"—")} -> GSK.L | D23: {=IFERROR(LEFT(IFERROR(INDEX('DONNÉES BRUTES'!B$3:B$42,MATCH(_xlfn.AGGREGATE(14,6,'DONNÉES BRUTES'!AB$3:AB$42*1000+(40-ROW('DONNÉES BRUTES'!AB$3:AB$42)+ROW('DONNÉES BRUTES'!AB$3)),8),'DONNÉES BRUTES'!AB$3:AB$42*1000+(40-ROW('DONNÉES BRUTES'!AB$3:AB$42)+ROW('DONNÉES BRUTES'!AB$3)),0)),"—"),18),"—")} -> GSK plc | E23: {=IFERROR(INDEX('DONNÉES BRUTES'!C$3:C$42,MATCH(_xlfn.AGGREGATE(14,6,'DONNÉES BRUTES'!AB$3:AB$42*1000+(40-ROW('DONNÉES BRUTES'!AB$3:AB$42)+ROW('DONNÉES BRUTES'!AB$3)),8),'DONNÉES BRUTES'!AB$3:AB$42*1000+(40-ROW('DONNÉES BRUTES'!AB$3:AB$42)+ROW('DONNÉES BRUTES'!AB$3)),0)),"—")} -> Santé | F23: {=IFERROR(INT(_xlfn.AGGREGATE(14,6,'DONNÉES BRUTES'!AB$3:AB$42*1000+(40-ROW('DONNÉES BRUTES'!AB$3:AB$42)+ROW('DONNÉES BRUTES'!AB$3)),8)/1000)&"/100","—")} -> 56/100 | H23: {=IFERROR(INDEX('DONNÉES BRUTES'!Y$3:Y$42,MATCH(_xlfn.AGGREGATE(14,6,'DONNÉES BRUTES'!AB$3:AB$42*1000+(40-ROW('DONNÉES BRUTES'!AB$3:AB$42)+ROW('DONNÉES BRUTES'!AB$3)),8),'DONNÉES BRUTES'!AB$3:AB$42*1000+(40-ROW('DONNÉES BRUTES'!AB$3:AB$42)+ROW('DONNÉES BRUTES'!AB$3)),0)),"—")} -> 78 | I23: {=IFERROR(INDEX('DONNÉES BRUTES'!Z$3:Z$42,MATCH(_xlfn.AGGREGATE(14,6,'DONNÉES BRUTES'!AB$3:AB$42*1000+(40-ROW('DONNÉES BRUTES'!AB$3:AB$42)+ROW('DONNÉES BRUTES'!AB$3)),8),'DONNÉES BRUTES'!AB$3:AB$42*1000+(40-ROW('DONNÉES BRUTES'!AB$3:AB$42)+ROW('DONNÉES BRUTES'!AB$3)),0)),"—")} -> 41 | J23: {=IFERROR(INDEX('DONNÉES BRUTES'!AA$3:AA$42,MATCH(_xlfn.AGGREGATE(14,6,'DONNÉES BRUTES'!AB$3:AB$42*1000+(40-ROW('DONNÉES BRUTES'!AB$3:AB$42)+ROW('DONNÉES BRUTES'!AB$3)),8),'DONNÉES BRUTES'!AB$3:AB$42*1000+(40-ROW('DONNÉES BRUTES'!AB$3:AB$42)+ROW('DONNÉES BRUTES'!AB$3)),0)),"—")} -> 72 | K23: {=IFERROR(INDEX('DONNÉES BRUTES'!N$3:N$42,MATCH(_xlfn.AGGREGATE(14,6,'DONNÉES BRUTES'!AB$3:AB$42*1000+(40-ROW('DONNÉES BRUTES'!AB$3:AB$42)+ROW('DONNÉES BRUTES'!AB$3)),8),'DONNÉES BRUTES'!AB$3:AB$42*1000+(40-ROW('DONNÉES BRUTES'!AB$3:AB$42)+ROW('DONNÉES BRUTES'!AB$3)),0)),"—")} -> 31.8% | L23: {=IFERROR(INDEX('DONNÉES BRUTES'!P$3:P$42,MATCH(_xlfn.AGGREGATE(14,6,'DONNÉES BRUTES'!AB$3:AB$42*1000+(40-ROW('DONNÉES BRUTES'!AB$3:AB$42)+ROW('DONNÉES BRUTES'!AB$3)),8),'DONNÉES BRUTES'!AB$3:AB$42*1000+(40-ROW('DONNÉES BRUTES'!AB$3:AB$42)+ROW('DONNÉES BRUTES'!AB$3)),0)),"—")} -> +4.1% | N23: {=IFERROR(INDEX('DONNÉES BRUTES'!AC$3:AC$42,MATCH(_xlfn.AGGREGATE(14,6,'DONNÉES BRUTES'!AB$3:AB$42*1000+(40-ROW('DONNÉES BRUTES'!AB$3:AB$42)+ROW('DONNÉES BRUTES'!AB$3)),8),'DONNÉES BRUTES'!AB$3:AB$42*1000+(40-ROW('DONNÉES BRUTES'!AB$3:AB$42)+ROW('DONNÉES BRUTES'!AB$3)),0)),"—")} -> 2026-04-29 | R23: {=IFERROR(INDEX('DONNÉES BRUTES'!AD$3:AD$42,MATCH(_xlfn.AGGREGATE(14,6,'DONNÉES BRUTES'!AB$3:AB$42*1000+(40-ROW('DONNÉES BRUTES'!AB$3:AB$42)+ROW('DONNÉES BRUTES'!AB$3)),8),'DONNÉES BRUTES'!AB$3:AB$42*1000+(40-ROW('DONNÉES BRUTES'!AB$3:AB$42)+ROW('DONNÉES BRUTES'!AB$3)),0)),"—")} -> Neutre
B24: 9 | C24: {=IFERROR(INDEX('DONNÉES BRUTES'!A$3:A$42,MATCH(_xlfn.AGGREGATE(14,6,'DONNÉES BRUTES'!AB$3:AB$42*1000+(40-ROW('DONNÉES BRUTES'!AB$3:AB$42)+ROW('DONNÉES BRUTES'!AB$3)),9),'DONNÉES BRUTES'!AB$3:AB$42*1000+(40-ROW('DONNÉES BRUTES'!AB$3:AB$42)+ROW('DONNÉES BRUTES'!AB$3)),0)),"—")} -> PRX.AS | D24: {=IFERROR(LEFT(IFERROR(INDEX('DONNÉES BRUTES'!B$3:B$42,MATCH(_xlfn.AGGREGATE(14,6,'DONNÉES BRUTES'!AB$3:AB$42*1000+(40-ROW('DONNÉES BRUTES'!AB$3:AB$42)+ROW('DONNÉES BRUTES'!AB$3)),9),'DONNÉES BRUTES'!AB$3:AB$42*1000+(40-ROW('DONNÉES BRUTES'!AB$3:AB$42)+ROW('DONNÉES BRUTES'!AB$3)),0)),"—"),18),"—")} -> Prosus N.V. | E24: {=IFERROR(INDEX('DONNÉES BRUTES'!C$3:C$42,MATCH(_xlfn.AGGREGATE(14,6,'DONNÉES BRUTES'!AB$3:AB$42*1000+(40-ROW('DONNÉES BRUTES'!AB$3:AB$42)+ROW('DONNÉES BRUTES'!AB$3)),9),'DONNÉES BRUTES'!AB$3:AB$42*1000+(40-ROW('DONNÉES BRUTES'!AB$3:AB$42)+ROW('DONNÉES BRUTES'!AB$3)),0)),"—")} -> Conso. Cycl. | F24: {=IFERROR(INT(_xlfn.AGGREGATE(14,6,'DONNÉES BRUTES'!AB$3:AB$42*1000+(40-ROW('DONNÉES BRUTES'!AB$3:AB$42)+ROW('DONNÉES BRUTES'!AB$3)),9)/1000)&"/100","—")} -> 56/100 | H24: {=IFERROR(INDEX('DONNÉES BRUTES'!Y$3:Y$42,MATCH(_xlfn.AGGREGATE(14,6,'DONNÉES BRUTES'!AB$3:AB$42*1000+(40-ROW('DONNÉES BRUTES'!AB$3:AB$42)+ROW('DONNÉES BRUTES'!AB$3)),9),'DONNÉES BRUTES'!AB$3:AB$42*1000+(40-ROW('DONNÉES BRUTES'!AB$3:AB$42)+ROW('DONNÉES BRUTES'!AB$3)),0)),"—")} -> 66 | I24: {=IFERROR(INDEX('DONNÉES BRUTES'!Z$3:Z$42,MATCH(_xlfn.AGGREGATE(14,6,'DONNÉES BRUTES'!AB$3:AB$42*1000+(40-ROW('DONNÉES BRUTES'!AB$3:AB$42)+ROW('DONNÉES BRUTES'!AB$3)),9),'DONNÉES BRUTES'!AB$3:AB$42*1000+(40-ROW('DONNÉES BRUTES'!AB$3:AB$42)+ROW('DONNÉES BRUTES'!AB$3)),0)),"—")} -> 59 | J24: {=IFERROR(INDEX('DONNÉES BRUTES'!AA$3:AA$42,MATCH(_xlfn.AGGREGATE(14,6,'DONNÉES BRUTES'!AB$3:AB$42*1000+(40-ROW('DONNÉES BRUTES'!AB$3:AB$42)+ROW('DONNÉES BRUTES'!AB$3)),9),'DONNÉES BRUTES'!AB$3:AB$42*1000+(40-ROW('DONNÉES BRUTES'!AB$3:AB$42)+ROW('DONNÉES BRUTES'!AB$3)),0)),"—")} -> 15 | K24: {=IFERROR(INDEX('DONNÉES BRUTES'!N$3:N$42,MATCH(_xlfn.AGGREGATE(14,6,'DONNÉES BRUTES'!AB$3:AB$42*1000+(40-ROW('DONNÉES BRUTES'!AB$3:AB$42)+ROW('DONNÉES BRUTES'!AB$3)),9),'DONNÉES BRUTES'!AB$3:AB$42*1000+(40-ROW('DONNÉES BRUTES'!AB$3:AB$42)+ROW('DONNÉES BRUTES'!AB$3)),0)),"—")} -> — | L24: {=IFERROR(INDEX('DONNÉES BRUTES'!P$3:P$42,MATCH(_xlfn.AGGREGATE(14,6,'DONNÉES BRUTES'!AB$3:AB$42*1000+(40-ROW('DONNÉES BRUTES'!AB$3:AB$42)+ROW('DONNÉES BRUTES'!AB$3)),9),'DONNÉES BRUTES'!AB$3:AB$42*1000+(40-ROW('DONNÉES BRUTES'!AB$3:AB$42)+ROW('DONNÉES BRUTES'!AB$3)),0)),"—")} -> +12.9% | N24: {=IFERROR(INDEX('DONNÉES BRUTES'!AC$3:AC$42,MATCH(_xlfn.AGGREGATE(14,6,'DONNÉES BRUTES'!AB$3:AB$42*1000+(40-ROW('DONNÉES BRUTES'!AB$3:AB$42)+ROW('DONNÉES BRUTES'!AB$3)),9),'DONNÉES BRUTES'!AB$3:AB$42*1000+(40-ROW('DONNÉES BRUTES'!AB$3:AB$42)+ROW('DONNÉES BRUTES'!AB$3)),0)),"—")} -> — | R24: {=IFERROR(INDEX('DONNÉES BRUTES'!AD$3:AD$42,MATCH(_xlfn.AGGREGATE(14,6,'DONNÉES BRUTES'!AB$3:AB$42*1000+(40-ROW('DONNÉES BRUTES'!AB$3:AB$42)+ROW('DONNÉES BRUTES'!AB$3)),9),'DONNÉES BRUTES'!AB$3:AB$42*1000+(40-ROW('DONNÉES BRUTES'!AB$3:AB$42)+ROW('DONNÉES BRUTES'!AB$3)),0)),"—")} -> Neutre
B25: 10 | C25: {=IFERROR(INDEX('DONNÉES BRUTES'!A$3:A$42,MATCH(_xlfn.AGGREGATE(14,6,'DONNÉES BRUTES'!AB$3:AB$42*1000+(40-ROW('DONNÉES BRUTES'!AB$3:AB$42)+ROW('DONNÉES BRUTES'!AB$3)),10),'DONNÉES BRUTES'!AB$3:AB$42*1000+(40-ROW('DONNÉES BRUTES'!AB$3:AB$42)+ROW('DONNÉES BRUTES'!AB$3)),0)),"—")} -> OR.PA | D25: {=IFERROR(LEFT(IFERROR(INDEX('DONNÉES BRUTES'!B$3:B$42,MATCH(_xlfn.AGGREGATE(14,6,'DONNÉES BRUTES'!AB$3:AB$42*1000+(40-ROW('DONNÉES BRUTES'!AB$3:AB$42)+ROW('DONNÉES BRUTES'!AB$3)),10),'DONNÉES BRUTES'!AB$3:AB$42*1000+(40-ROW('DONNÉES BRUTES'!AB$3:AB$42)+ROW('DONNÉES BRUTES'!AB$3)),0)),"—"),18),"—")} -> L'Oréal S.A. | E25: {=IFERROR(INDEX('DONNÉES BRUTES'!C$3:C$42,MATCH(_xlfn.AGGREGATE(14,6,'DONNÉES BRUTES'!AB$3:AB$42*1000+(40-ROW('DONNÉES BRUTES'!AB$3:AB$42)+ROW('DONNÉES BRUTES'!AB$3)),10),'DONNÉES BRUTES'!AB$3:AB$42*1000+(40-ROW('DONNÉES BRUTES'!AB$3:AB$42)+ROW('DONNÉES BRUTES'!AB$3)),0)),"—")} -> Conso. Déf. | F25: {=IFERROR(INT(_xlfn.AGGREGATE(14,6,'DONNÉES BRUTES'!AB$3:AB$42*1000+(40-ROW('DONNÉES BRUTES'!AB$3:AB$42)+ROW('DONNÉES BRUTES'!AB$3)),10)/1000)&"/100","—")} -> 56/100 | H25: {=IFERROR(INDEX('DONNÉES BRUTES'!Y$3:Y$42,MATCH(_xlfn.AGGREGATE(14,6,'DONNÉES BRUTES'!AB$3:AB$42*1000+(40-ROW('DONNÉES BRUTES'!AB$3:AB$42)+ROW('DONNÉES BRUTES'!AB$3)),10),'DONNÉES BRUTES'!AB$3:AB$42*1000+(40-ROW('DONNÉES BRUTES'!AB$3:AB$42)+ROW('DONNÉES BRUTES'!AB$3)),0)),"—")} -> 57 | I25: {=IFERROR(INDEX('DONNÉES BRUTES'!Z$3:Z$42,MATCH(_xlfn.AGGREGATE(14,6,'DONNÉES BRUTES'!AB$3:AB$42*1000+(40-ROW('DONNÉES BRUTES'!AB$3:AB$42)+ROW('DONNÉES BRUTES'!AB$3)),10),'DONNÉES BRUTES'!AB$3:AB$42*1000+(40-ROW('DONNÉES BRUTES'!AB$3:AB$42)+ROW('DONNÉES BRUTES'!AB$3)),0)),"—")} -> 72 | J25: {=IFERROR(INDEX('DONNÉES BRUTES'!AA$3:AA$42,MATCH(_xlfn.AGGREGATE(14,6,'DONNÉES BRUTES'!AB$3:AB$42*1000+(40-ROW('DONNÉES BRUTES'!AB$3:AB$42)+ROW('DONNÉES BRUTES'!AB$3)),10),'DONNÉES BRUTES'!AB$3:AB$42*1000+(40-ROW('DONNÉES BRUTES'!AB$3:AB$42)+ROW('DONNÉES BRUTES'!AB$3)),0)),"—")} -> 21 | K25: {=IFERROR(INDEX('DONNÉES BRUTES'!N$3:N$42,MATCH(_xlfn.AGGREGATE(14,6,'DONNÉES BRUTES'!AB$3:AB$42*1000+(40-ROW('DONNÉES BRUTES'!AB$3:AB$42)+ROW('DONNÉES BRUTES'!AB$3)),10),'DONNÉES BRUTES'!AB$3:AB$42*1000+(40-ROW('DONNÉES BRUTES'!AB$3:AB$42)+ROW('DONNÉES BRUTES'!AB$3)),0)),"—")} -> 24.3% | L25: {=IFERROR(INDEX('DONNÉES BRUTES'!P$3:P$42,MATCH(_xlfn.AGGREGATE(14,6,'DONNÉES BRUTES'!AB$3:AB$42*1000+(40-ROW('DONNÉES BRUTES'!AB$3:AB$42)+ROW('DONNÉES BRUTES'!AB$3)),10),'DONNÉES BRUTES'!AB$3:AB$42*1000+(40-ROW('DONNÉES BRUTES'!AB$3:AB$42)+ROW('DONNÉES BRUTES'!AB$3)),0)),"—")} -> +1.3% | N25: {=IFERROR(INDEX('DONNÉES BRUTES'!AC$3:AC$42,MATCH(_xlfn.AGGREGATE(14,6,'DONNÉES BRUTES'!AB$3:AB$42*1000+(40-ROW('DONNÉES BRUTES'!AB$3:AB$42)+ROW('DONNÉES BRUTES'!AB$3)),10),'DONNÉES BRUTES'!AB$3:AB$42*1000+(40-ROW('DONNÉES BRUTES'!AB$3:AB$42)+ROW('DONNÉES BRUTES'!AB$3)),0)),"—")} -> — | R25: {=IFERROR(INDEX('DONNÉES BRUTES'!AD$3:AD$42,MATCH(_xlfn.AGGREGATE(14,6,'DONNÉES BRUTES'!AB$3:AB$42*1000+(40-ROW('DONNÉES BRUTES'!AB$3:AB$42)+ROW('DONNÉES BRUTES'!AB$3)),10),'DONNÉES BRUTES'!AB$3:AB$42*1000+(40-ROW('DONNÉES BRUTES'!AB$3:AB$42)+ROW('DONNÉES BRUTES'!AB$3)),0)),"—")} -> Neutre
B26: FinSight IA · Données issues de Supabase/Python · Scores calculés sur métriques Value, Growth, Quality, Momentum · Usage confidentiel

Sheet VALUE
A1: FinSight IA · Analyse VALUE · Euro Stoxx 50 | O1: Société | P1: Score Global | Q1: Signal
A2: Usage confidentiel · Calculs Python/yfinance | O2: =IF(B4<>"—",LEFT(C4,20),"—") -> SAP SE | P2: =IF(E4<>"—",VALUE(LEFT(E4,FIND("/",E4)-1)),"") -> 74
A3: Rang | B3: Ticker | C3: Société | D3: Secteur | E3: Score | F3: EV/EBITDA | G3: EV/Revenue | H3: P/E | I3: Marge Brute | J3: Marge EBITDA | K3: Altman Z | L3: FCF Yield | M3: Décote DCF estimée | O3: =IF(B5<>"—",LEFT(C5,20),"—") -> Prosus N.V. | P3: =IF(E5<>"—",VALUE(LEFT(E5,FIND("/",E5)-1)),"") -> 72
A4: 1 | B4: SAP.DE | C4: SAP SE | D4: Technologie | E4: 74/100 | F4: 13.3 | G4: 4.4 | H4: 22.7 | I4: 72.9% | J4: 32.8% | K4: 5.34 | L4: +5.2% | M4: -41.3 % | O4: =IF(B6<>"—",LEFT(C6,20),"—") -> Sanofi | P4: =IF(E6<>"—",VALUE(LEFT(E6,FIND("/",E6)-1)),"") -> 68
A5: 2 | B5: PRX.AS | C5: Prosus N.V. | D5: Conso. Cycl. | E5: 72/100 | F5: 7.4 | G5: 16 | H5: 7.3 | I5: 42.5% | J5: — | K5: 8.72 | L5: +2.0% | M5: +82.6 % | O5: =IF(B7<>"—",LEFT(C7,20),"—") -> L'Oréal S.A. | P5: =IF(E7<>"—",VALUE(LEFT(E7,FIND("/",E7)-1)),"") -> 66
A6: 3 | B6: SAN.PA | C6: Sanofi | D6: Santé | E6: 68/100 | F6: 8.6 | G6: 2.3 | H6: 12.4 | I6: 72.1% | J6: 26.7% | K6: — | L6: +7.5% | M6: +7.5 % | O6: =IF(B8<>"—",LEFT(C8,20),"—") -> Telefónica, S.A. | P6: =IF(E8<>"—",VALUE(LEFT(E8,FIND("/",E8)-1)),"") -> 60
A7: 4 | B7: OR.PA | C7: L'Oréal S.A. | D7: Conso. Déf. | E7: 66/100 | F7: 17.9 | G7: 4.4 | H7: 31.3 | I7: 74.3% | J7: 24.3% | K7: 3.38 | L7: +3.7% | M7: -57.4 % | O7: =IF(B9<>"—",LEFT(C9,20),"—") -> Hermès International | P7: =IF(E9<>"—",VALUE(LEFT(E9,FIND("/",E9)-1)),"") -> 60
A8: 5 | B8: TEF.MC | C8: Telefónica, S.A. | D8: Télécoms | E8: 60/100 | F8: 4.1 | G8: 1.2 | H8: — | I8: 69.6% | J8: 29.9% | K8: 1.01 | L8: +24.0% | M8: — | O8: =IF(B10<>"—",LEFT(C10,20),"—") -> TotalEnergies SE | P8: =IF(E10<>"—",VALUE(LEFT(E10,FIND("/",E10)-1)),"") -> 59
A9: 6 | B9: RMS.PA | C9: Hermès International Société en commandite par actions | D9: Conso. Cycl. | E9: 60/100 | F9: 22.9 | G9: 10.8 | H9: 40.7 | I9: 71.1% | J9: 46.8% | K9: 9.47 | L9: +2.9% | M9: -67.2 % | O9: =IF(B11<>"—",LEFT(C11,20),"—") -> Siemens Aktiengesell | P9: =IF(E11<>"—",VALUE(LEFT(E11,FIND("/",E11)-1)),"") -> 56
A10: 7 | B10: TTE.PA | C10: TotalEnergies SE | D10: Énergie | E10: 59/100 | F10: 6.2 | G10: 1.1 | H10: 15.9 | I10: 36.0% | J10: 18.0% | K10: — | L10: +9.5% | M10: -16.1 % | O10: =IF(B12<>"—",LEFT(C12,20),"—") -> Volkswagen AG | P10: =IF(E12<>"—",VALUE(LEFT(E12,FIND("/",E12)-1)),"") -> 56
A11: 8 | B11: SIE.DE | C11: Siemens Aktiengesellschaft | D11: Industrie | E11: 56/100 | F11: 13.4 | G11: 2.7 | H11: 18.2 | I11: 38.5% | J11: 20.1% | K11: 2.83 | L11: +6.2% | M11: -26.7 % | O11: =IF(B13<>"—",LEFT(C13,20),"—") -> Koninklijke Philips | P11: =IF(E13<>"—",VALUE(LEFT(E13,FIND("/",E13)-1)),"") -> 53
A12: 9 | B12: VOW3.DE | C12: Volkswagen AG | D12: Conso. Cycl. | E12: 56/100 | F12: 3.4 | G12: 0.5 | H12: 2.5 | I12: 15.9% | J12: 15.5% | K12: 1.61 | L12: -50.9% | M12: +433.3 % | O12: =IF(B14<>"—",LEFT(C14,20),"—") -> RWE Aktiengesellscha | P12: =IF(E14<>"—",VALUE(LEFT(E14,FIND("/",E14)-1)),"") -> 53
A13: 10 | B13: PHIA.AS | C13: Koninklijke Philips N.V. | D13: Santé | E13: 53/100 | F13: 10.4 | G13: 1.5 | H13: 25.8 | I13: 45.2% | J13: 14.6% | K13: 2.11 | L13: +2.2% | M13: -48.3 % | O13: =IF(B15<>"—",LEFT(C15,20),"—") -> Banco Santander, S.A | P13: =IF(E15<>"—",VALUE(LEFT(E15,FIND("/",E15)-1)),"") -> 48
A14: 11 | B14: RWE.DE | C14: RWE Aktiengesellschaft | D14: Serv. Publ. | E14: 53/100 | F14: 7.1 | G14: 2.8 | H14: 13.4 | I14: 32.8% | J14: 39.1% | K14: 2.35 | L14: -12.0% | M14: -0.5 % | O14: =IF(B16<>"—",LEFT(C16,20),"—") -> Schneider Electric S | P14: =IF(E16<>"—",VALUE(LEFT(E16,FIND("/",E16)-1)),"") -> 39
A15: 12 | B15: SAN.MC | C15: Banco Santander, S.A. | D15: Finance | E15: 48/100 | F15: 3.6 | G15: 4.9 | H15: 10.7 | I15: — | J15: — | K15: — | L15: -14.8% | M15: +24.6 % | O15: =IF(B17<>"—",LEFT(C17,20),"—") -> Rio Tinto Group | P15: =IF(E17<>"—",VALUE(LEFT(E17,FIND("/",E17)-1)),"") -> 38
A16: 13 | B16: SU.PA | C16: Schneider Electric S.E. | D16: Industrie | E16: 39/100 | F16: 19.1 | G16: 4 | H16: 35.1 | I16: 42.1% | J16: 20.9% | K16: — | L16: +3.1% | M16: -62.0 % | O16: =IF(B18<>"—",LEFT(C18,20),"—") -> GSK plc | P16: =IF(E18<>"—",VALUE(LEFT(E18,FIND("/",E18)-1)),"") -> 33
A17: 14 | B17: RIO.L | C17: Rio Tinto Group | D17: Matériaux | E17: 38/100 | F17: 401.8 | G17: 160.1 | H17: 925.1 | I17: 57.4% | J17: 39.9% | K17: 3.45 | L17: +0.0% | M17: -98.6 %
A18: 15 | B18: GSK.L | C18: GSK plc | D18: Santé | E18: 33/100 | F18: 837.4 | G18: 266.6 | H18: 1521.7 | I18: 72.4% | J18: 31.8% | K18: 1.4 | L18: +0.1% | M18: -99.1 %

Sheet GROWTH
A1: FinSight IA · Analyse GROWTH · Euro Stoxx 50 | O1: Société | P1: Score Gr
A2: Usage confidentiel · Calculs Python/yfinance | O2: =IF(B4<>"—",LEFT(C4,18),"—") -> ASML Holding N.V. | P2: =IF(E4<>"—",VALUE(LEFT(E4,FIND("/",E4)-1)),"") -> 92
A3: Rang | B3: Ticker | C3: Société | D3: Secteur | E3: Score | F3: Croissance Rev. YoY | G3: Marge EBITDA | H3: Marge Nette | I3: ROE | J3: Croissance EPS | K3: Révisions Analystes | L3: Signal | O3: =IF(B5<>"—",LEFT(C5,18),"—") -> AstraZeneca PLC | P3: =IF(E5<>"—",VALUE(LEFT(E5,FIND("/",E5)-1)),"") -> 87
A4: 1 | B4: ASML.AS | C4: ASML Holding N.V. | D4: Technologie | E4: 92/100 | F4: +15.6% | G4: 38.4% | H4: 29.4% | I4: +49.0% | J4: +26.9% | K4: — | L4: Surpondérer | O4: =IF(B6<>"—",LEFT(C6,18),"—") -> Hermès Internation | P4: =IF(E6<>"—",VALUE(LEFT(E6,FIND("/",E6)-1)),"") -> 81
A5: 2 | B5: AZN.L | C5: AstraZeneca PLC | D5: Santé | E5: 87/100 | F5: +8.6% | G5: 33.2% | H5: 17.4% | I5: +21.0% | J5: +53.9% | K5: — | L5: Surpondérer | O5: =IF(B7<>"—",LEFT(C7,18),"—") -> GSK plc | P5: =IF(E7<>"—",VALUE(LEFT(E7,FIND("/",E7)-1)),"") -> 78
A6: 3 | B6: RMS.PA | C6: Hermès International Société en commandite par actions | D6: Conso. Cycl. | E6: 81/100 | F6: +5.5% | G6: 46.8% | H6: 28.3% | I6: +24.0% | J6: +1.8% | K6: — | L6: Neutre | O6: =IF(B8<>"—",LEFT(C8,18),"—") -> SAP SE | P6: =IF(E8<>"—",VALUE(LEFT(E8,FIND("/",E8)-1)),"") -> 78
A7: 4 | B7: GSK.L | C7: GSK plc | D7: Santé | E7: 78/100 | F7: +4.1% | G7: 31.8% | H7: 17.5% | I7: +34.9% | J7: +54.7% | K7: — | L7: Surpondérer | O7: =IF(B9<>"—",LEFT(C9,18),"—") -> Rio Tinto Group | P7: =IF(E9<>"—",VALUE(LEFT(E9,FIND("/",E9)-1)),"") -> 77
A8: 5 | B8: SAP.DE | C8: SAP SE | D8: Technologie | E8: 78/100 | F8: +7.7% | G8: 32.8% | H8: 19.5% | I8: +16.1% | J8: +5.0% | K8: — | L8: Surpondérer | O8: =IF(B10<>"—",LEFT(C10,18),"—") -> Münchener Rückvers | P8: =IF(E10<>"—",VALUE(LEFT(E10,FIND("/",E10)-1)),"") -> 71
A9: 6 | B9: RIO.L | C9: Rio Tinto Group | D9: Matériaux | E9: 77/100 | F9: +7.4% | G9: 39.9% | H9: 17.3% | I9: +16.0% | J9: -5.6% | K9: — | L9: Surpondérer | O9: =IF(B11<>"—",LEFT(C11,18),"—") -> Sanofi | P9: =IF(E11<>"—",VALUE(LEFT(E11,FIND("/",E11)-1)),"") -> 67
A10: 7 | B10: MUV2.DE | C10: Münchener Rückversicherungs-Gesellschaft Aktiengesellschaft in München | D10: Finance | E10: 71/100 | F10: +6.6% | G10: 22.2% | H10: 13.4% | I10: +17.4% | J10: +23.4% | K10: — | L10: Neutre | O10: =IF(B12<>"—",LEFT(C12,18),"—") -> Industria de Diseñ | P10: =IF(E12<>"—",VALUE(LEFT(E12,FIND("/",E12)-1)),"") -> 67
A11: 8 | B11: SAN.PA | C11: Sanofi | D11: Santé | E11: 67/100 | F11: +5.5% | G11: 26.7% | H11: 16.7% | I11: +10.9% | J11: +40.5% | K11: — | L11: Surpondérer | O11: =IF(B13<>"—",LEFT(C13,18),"—") -> Prosus N.V. | P11: =IF(E13<>"—",VALUE(LEFT(E13,FIND("/",E13)-1)),"") -> 66
A12: 9 | B12: ITX.MC | C12: Industria de Diseño Textil, S.A. | D12: Conso. Cycl. | E12: 67/100 | F12: +3.2% | G12: 29.2% | H12: 15.6% | I12: +30.5% | J12: +6.0% | K12: — | L12: Surpondérer
A13: 10 | B13: PRX.AS | C13: Prosus N.V. | D13: Conso. Cycl. | E13: 66/100 | F13: +12.9% | G13: — | H13: — | I13: +24.2% | J13: +95.0% | K13: — | L13: Neutre
A14: 11 | B14: GLE.PA | C14: Société Générale Société anonyme | D14: Finance | E14: 65/100 | F14: +0.2% | G14: 98.1% | H14: 11.4% | I14: +8.6% | J14: +42.9% | K14: — | L14: Neutre
A15: 12 | B15: DTE.DE | C15: Deutsche Telekom AG | D15: Télécoms | E15: 63/100 | F15: +2.8% | G15: 42.2% | H15: 8.1% | I15: +15.5% | J15: -14.3% | K15: — | L15: Neutre
A16: 13 | B16: AIR.PA | C16: Airbus SE | D16: Industrie | E16: 62/100 | F16: +6.1% | G16: 14.0% | H16: 7.1% | I16: +20.0% | J16: +23.4% | K16: — | L16: Neutre
A17: 14 | B17: ADS.DE | C17: adidas AG | D17: Conso. Cycl. | E17: 61/100 | F17: +4.8% | G17: 12.8% | H17: 5.4% | I17: +23.2% | J17: +75.4% | K17: — | L17: Neutre
A18: 15 | B18: SU.PA | C18: Schneider Electric S.E. | D18: Industrie | E18: 60/100 | F18: +5.2% | G18: 20.9% | H18: 10.4% | I18: +17.2% | J18: -6.2% | K18: — | L18: Neutre

Sheet QUALITY
A1: FinSight IA · Analyse QUALITY · Euro Stoxx 50 | O1: Société | P1: Score Qual | Q1: Altman Z | R1: Beneish M
A2: Usage confidentiel · Calculs Python/yfinance | O2: =IF(B4<>"—",LEFT(C4,15),"—") -> Hermès Internat | P2: =IF(E4<>"—",VALUE(LEFT(E4,FIND("/",E4)-1)),"") -> 99 | Q2: =IF(F4<>"—",F4,"") -> 9.47 | R2: =IF(H4<>"—",H4,"") -> -3.21
A3: Rang | B3: Ticker | C3: Société | D3: Secteur | E3: Score | F3: Altman Z-Score | G3: Signal Z | H3: Beneish M | I3: Signal M | J3: Marge EBITDA | K3: ROE | L3: Interest Coverage | M3: Current Ratio | O3: =IF(B5<>"—",LEFT(C5,15),"—") -> ASML Holding N. | P3: =IF(E5<>"—",VALUE(LEFT(E5,FIND("/",E5)-1)),"") -> 86 | Q3: =IF(F5<>"—",F5,"") -> 4.15 | R3: =IF(H5<>"—",H5,"") -> -3.3
A4: 1 | B4: RMS.PA | C4: Hermès International Société en commandite par actions | D4: Conso. Cycl. | E4: 99/100 | F4: 9.47 | G4: Sain | H4: -3.21 | I4: Ok | J4: 46.8% | K4: +24.0% | L4: — | M4: 4.99 | O4: =IF(B6<>"—",LEFT(C6,15),"—") -> Industria de Di | P4: =IF(E6<>"—",VALUE(LEFT(E6,FIND("/",E6)-1)),"") -> 83 | Q4: =IF(F6<>"—",F6,"") -> 4.57 | R4: =IF(H6<>"—",H6,"") -> -1.62
A5: 2 | B5: ASML.AS | C5: ASML Holding N.V. | D5: Technologie | E5: 86/100 | F5: 4.15 | G5: Sain | H5: -3.3 | I5: Ok | J5: 38.4% | K5: +49.0% | L5: 97 | M5: 1.26 | O5: =IF(B7<>"—",LEFT(C7,15),"—") -> SAP SE | P5: =IF(E7<>"—",VALUE(LEFT(E7,FIND("/",E7)-1)),"") -> 80 | Q5: =IF(F7<>"—",F7,"") -> 5.34 | R5: =IF(H7<>"—",H7,"") -> -3.14
A6: 3 | B6: ITX.MC | C6: Industria de Diseño Textil, S.A. | D6: Conso. Cycl. | E6: 83/100 | F6: 4.57 | G6: Sain | H6: -1.62 | I6: Risque | J6: 29.2% | K6: +30.5% | L6: 23 | M6: 1.54 | O6: =IF(B8<>"—",LEFT(C8,15),"—") -> Rio Tinto Group | P6: =IF(E8<>"—",VALUE(LEFT(E8,FIND("/",E8)-1)),"") -> 78 | Q6: =IF(F8<>"—",F8,"") -> 3.45 | R6: =IF(H8<>"—",H8,"") -> -2.93
A7: 4 | B7: SAP.DE | C7: SAP SE | D7: Technologie | E7: 80/100 | F7: 5.34 | G7: Sain | H7: -3.14 | I7: Ok | J7: 32.8% | K7: +16.1% | L7: 22 | M7: 1.16 | O7: =IF(B9<>"—",LEFT(C9,15),"—") -> L'Oréal S.A. | P7: =IF(E9<>"—",VALUE(LEFT(E9,FIND("/",E9)-1)),"") -> 72 | Q7: =IF(F9<>"—",F9,"") -> 3.38 | R7: =IF(H9<>"—",H9,"") -> -3.16
A8: 5 | B8: RIO.L | C8: Rio Tinto Group | D8: Matériaux | E8: 78/100 | F8: 3.45 | G8: Sain | H8: -2.93 | I8: Ok | J8: 39.9% | K8: +16.0% | L8: 9 | M8: 1.44 | O8: =IF(B10<>"—",LEFT(C10,15),"—") -> LVMH Moët Henne | P8: =IF(E10<>"—",VALUE(LEFT(E10,FIND("/",E10)-1)),"") -> 69 | Q8: =IF(F10<>"—",F10,"") -> 2.88 | R8: =IF(H10<>"—",H10,"") -> -3.19
A9: 6 | B9: OR.PA | C9: L'Oréal S.A. | D9: Conso. Déf. | E9: 72/100 | F9: 3.38 | G9: Sain | H9: -3.16 | I9: Ok | J9: 24.3% | K9: +17.5% | L9: 24 | M9: 1.44 | O9: =IF(B11<>"—",LEFT(C11,15),"—") -> RWE Aktiengesel | P9: =IF(E11<>"—",VALUE(LEFT(E11,FIND("/",E11)-1)),"") -> 66 | Q9: =IF(F11<>"—",F11,"") -> 2.35 | R9: =IF(H11<>"—",H11,"") -> -3.22
A10: 7 | B10: MC.PA | C10: LVMH Moët Hennessy - Louis Vuitton, Société Européenne | D10: Conso. Cycl. | E10: 69/100 | F10: 2.88 | G10: Zone grise | H10: -3.19 | I10: Ok | J10: 32.0% | K10: +16.1% | L10: 16 | M10: 1.58 | O10: =IF(B12<>"—",LEFT(C12,15),"—") -> Shell plc | P10: =IF(E12<>"—",VALUE(LEFT(E12,FIND("/",E12)-1)),"") -> 61 | Q10: =IF(F12<>"—",F12,"") -> 3.35 | R10: =IF(H12<>"—",H12,"") -> -3.05
A11: 8 | B11: RWE.DE | C11: RWE Aktiengesellschaft | D11: Serv. Publ. | E11: 66/100 | F11: 2.35 | G11: Zone grise | H11: -3.22 | I11: Ok | J11: 39.1% | K11: +9.1% | L11: 7 | M11: 1.5 | O11: =IF(B13<>"—",LEFT(C13,15),"—") -> Prosus N.V. | P11: =IF(E13<>"—",VALUE(LEFT(E13,FIND("/",E13)-1)),"") -> 59 | Q11: =IF(F13<>"—",F13,"") -> 8.72 | R11: =IF(H13<>"—",H13,"") -> -3.26
A12: 9 | B12: SHEL.L | C12: Shell plc | D12: Énergie | E12: 61/100 | F12: 3.35 | G12: Sain | H12: -3.05 | I12: Ok | J12: 21.2% | K12: +10.2% | L12: 7 | M12: 1.3
A13: 10 | B13: PRX.AS | C13: Prosus N.V. | D13: Conso. Cycl. | E13: 59/100 | F13: 8.72 | G13: Sain | H13: -3.26 | I13: Ok | J13: — | K13: +24.2% | L13: 24 | M13: 3.54
A14: 11 | B14: IFX.DE | C14: Infineon Technologies AG | D14: Technologie | E14: 59/100 | F14: 3.37 | G14: Sain | H14: -2.99 | I14: Ok | J14: 24.0% | K14: +6.0% | L14: 7 | M14: 1.7
A15: 12 | B15: AI.PA | C15: L'Air Liquide S.A. | D15: Matériaux | E15: 58/100 | F15: 3.26 | G15: Sain | H15: -3.19 | I15: Ok | J15: 27.9% | K15: +13.4% | L15: 60 | M15: 1.17
A16: 13 | B16: NOKIA.HE | C16: Nokia Oyj | D16: Technologie | E16: 57/100 | F16: 2.7 | G16: Zone grise | H16: -3.05 | I16: Ok | J16: 11.3% | K16: +3.1% | L16: 5 | M16: 1.58
A17: 14 | B17: ADS.DE | C17: adidas AG | D17: Conso. Cycl. | E17: 52/100 | F17: 2.97 | G17: Sain | H17: -3.04 | I17: Ok | J17: 12.8% | K17: +23.2% | L17: 9 | M17: 1.32
A18: 15 | B18: AZN.L | C18: AstraZeneca PLC | D18: Santé | E18: 50/100 | F18: 1.81 | G18: Zone grise | H18: -2.92 | I18: Ok | J18: 33.2% | K18: +21.0% | L18: 9 | M18: 0.94

Sheet MOMENTUM
A1: FinSight IA · Analyse MOMENTUM · Euro Stoxx 50 | O1: Société | P1: Score Mom
A2: Usage confidentiel · Calculs Python/yfinance | O2: =IF(B4<>"—",LEFT(C4,18),"—") -> Eni S.p.A. | P2: =IF(E4<>"—",VALUE(LEFT(E4,FIND("/",E4)-1)),"") -> 100
A3: Rang | B3: Ticker | C3: Société | D3: Secteur | E3: Score | F3: Momentum 52W | G3: Cours actuel (€) | H3: Mkt Cap (Mds€) | I3: Score Global | J3: Next Earnings | K3: Signal | O3: =IF(B5<>"—",LEFT(C5,18),"—") -> ASML Holding N.V. | P3: =IF(E5<>"—",VALUE(LEFT(E5,FIND("/",E5)-1)),"") -> 98
A4: 1 | B4: ENI.MI | C4: Eni S.p.A. | D4: Énergie | E4: 100/100 | F4: +96.8% | G4: 23.95 | H4: — | I4: 22 | J4: 2026-04-24 | K4: Neutre | O4: =IF(B6<>"—",LEFT(C6,18),"—") -> RWE Aktiengesellsc | P4: =IF(E6<>"—",VALUE(LEFT(E6,FIND("/",E6)-1)),"") -> 96
A5: 2 | B5: ASML.AS | C5: ASML Holding N.V. | D5: Technologie | E5: 98/100 | F5: +95.3% | G5: 1270 | H5: — | I5: 75 | J5: 2026-04-15 | K5: Surpondérer | O5: =IF(B7<>"—",LEFT(C7,18),"—") -> Nokia Oyj | P5: =IF(E7<>"—",VALUE(LEFT(E7,FIND("/",E7)-1)),"") -> 94
A6: 3 | B6: RWE.DE | C6: RWE Aktiengesellschaft | D6: Serv. Publ. | E6: 96/100 | F6: +84.1% | G6: 59.04 | H6: 42.1 | I6: 60 | J6: 2026-05-13 | K6: Neutre | O6: =IF(B8<>"—",LEFT(C8,18),"—") -> Rio Tinto Group | P6: =IF(E8<>"—",VALUE(LEFT(E8,FIND("/",E8)-1)),"") -> 91
A7: 4 | B7: NOKIA.HE | C7: Nokia Oyj | D7: Technologie | E7: 94/100 | F7: +81.1% | G7: 8.03 | H7: — | I7: 46 | J7: 2026-04-23 | K7: Neutre | O7: =IF(B9<>"—",LEFT(C9,18),"—") -> Kering SA | P7: =IF(E9<>"—",VALUE(LEFT(E9,FIND("/",E9)-1)),"") -> 89
A8: 5 | B8: RIO.L | C8: Rio Tinto Group | D8: Matériaux | E8: 91/100 | F8: +66.9% | G8: 7345 | H8: 9214.1 | I8: 70 | J8: — | K8: Surpondérer | O8: =IF(B10<>"—",LEFT(C10,18),"—") -> Bayer Aktiengesell | P8: =IF(E10<>"—",VALUE(LEFT(E10,FIND("/",E10)-1)),"") -> 87
A9: 6 | B9: KER.PA | C9: Kering SA | D9: Conso. Cycl. | E9: 89/100 | F9: +64.6% | G9: 276.45 | H9: — | I9: 37 | J9: — | K9: Surpondérer | O9: =IF(B11<>"—",LEFT(C11,18),"—") -> TotalEnergies SE | P9: =IF(E11<>"—",VALUE(LEFT(E11,FIND("/",E11)-1)),"") -> 85
A10: 7 | B10: BAYN.DE | C10: Bayer Aktiengesellschaft | D10: Santé | E10: 87/100 | F10: +62.2% | G10: 40.12 | H10: — | I10: 25 | J10: 2026-05-12 | K10: Neutre | O10: =IF(B12<>"—",LEFT(C12,18),"—") -> BP p.l.c. | P10: =IF(E12<>"—",VALUE(LEFT(E12,FIND("/",E12)-1)),"") -> 83
A11: 8 | B11: TTE.PA | C11: TotalEnergies SE | D11: Énergie | E11: 85/100 | F11: +61.3% | G11: 78.61 | H11: 167.7 | I11: 40 | J11: 2026-04-29 | K11: Surpondérer | O11: =IF(B13<>"—",LEFT(C13,18),"—") -> Société Générale S | P11: =IF(E13<>"—",VALUE(LEFT(E13,FIND("/",E13)-1)),"") -> 81
A12: 9 | B12: BP.L | C12: BP p.l.c. | D12: Énergie | E12: 83/100 | F12: +59.7% | G12: 574.1 | H12: 8869.1 | I12: 38 | J12: 2026-04-28 | K12: Neutre
A13: 10 | B13: GLE.PA | C13: Société Générale Société anonyme | D13: Finance | E13: 81/100 | F13: +54.4% | G13: 71.4 | H13: — | I13: 47 | J13: 2026-04-30 | K13: Neutre
A14: 11 | B14: HSBA.L | C14: HSBC Holdings plc | D14: Finance | E14: 79/100 | F14: +53.6% | G14: 1340.2 | H14: 22982 | I14: 39 | J14: 2026-05-05 | K14: Neutre
A15: 12 | B15: ENGI.PA | C15: Engie SA | D15: Serv. Publ. | E15: 77/100 | F15: +53.4% | G15: 29.13 | H15: — | I15: 31 | J15: 2026-05-07 | K15: Neutre
A16: 13 | B16: SAN.MC | C16: Banco Santander, S.A. | D16: Finance | E16: 74/100 | F16: +51.5% | G16: 10.52 | H16: 151.6 | I16: 41 | J16: 2026-04-29 | K16: Surpondérer
A17: 14 | B17: GSK.L | C17: GSK plc | D17: Santé | E17: 72/100 | F17: +44.5% | G17: 2176 | H17: 8695 | I17: 56 | J17: 2026-04-29 | K17: Surpondérer
A18: 15 | B18: AZN.L | C18: AstraZeneca PLC | D18: Santé | E18: 70/100 | F18: +42.1% | G18: 15230 | H18: 23619.2 | I18: 60 | J18: 2026-04-29 | K18: Surpondérer

Sheet PAR SECTEUR
B1: FinSight IA · Euro Stoxx 50 — Vue Macro Sectorielle | H1: 12/04/2026 | L1: Secteur | M1: Score
A2: Usage confidentiel · Calculs Python/NumPy depuis cache Supabase | L2: Technologie | M2: 56
B3: Scoring composite Value / Growth / Quality / Momentum · Métriques médianes par secteur · Usage confidentiel | L3: Matériaux | M3: 50
L4: Santé | M4: 46
B5: SCORECARD SECTORIELLE · Score composite, metriques medianes, signal d'investissement — Euro Stoxx 50 | L5: Industrie | M5: 41
L6: Serv. Publ. | M6: 40
B7: Secteur | C7: # Soc. | D7: Score | E7: Score (indicateur) | F7: Top Société | G7: Mg. EBITDA | H7: Croiss. Rev. | I7: Altman Z | J7: Signal | L7: Conso. Déf. | M7: 40
B8: Technologie | C8: 4 | D8: 56 | E8: ██████░░░░ | F8: ASML Holding N.V. | G8: 0.284 | H8: 0.056 | I8: 3.76 | J8: Neutre | L8: Conso. Cycl. | M8: 38
B9: Matériaux | C9: 3 | D9: 50 | E9: █████░░░░░ | F9: Rio Tinto Group | G9: 0.279 | H9: -0.004 | I9: 3.45 | J9: Neutre | L9: Télécoms | M9: 38
B10: Santé | C10: 6 | D10: 46 | E10: █████░░░░░ | F10: AstraZeneca PLC | G10: 0.249 | H10: 0.048 | I10: 1.96 | J10: Neutre | L10: Énergie | M10: 37
B11: Industrie | C11: 4 | D11: 41 | E11: ████░░░░░░ | F11: Siemens Aktiengesell | G11: 0.191 | H11: 0.046 | I11: 1.64 | J11: Negatif | L11: Finance | M11: 34
B12: Serv. Publ. | C12: 4 | D12: 40 | E12: ████░░░░░░ | F12: RWE Aktiengesellscha | G12: 0.287 | H12: -0.022 | I12: 1.32 | J12: Negatif
B13: Conso. Déf. | C13: 4 | D13: 40 | E13: ████░░░░░░ | F13: L'Oréal S.A. | G13: 0.232 | H13: 0.003 | I13: 2.86 | J13: Negatif | L13: Secteur | M13: Mg EBITDA Méd.
B14: Conso. Cycl. | C14: 10 | D14: 38 | E14: ████░░░░░░ | F14: Hermès International | G14: 0.155 | H14: -0.015 | I14: 2.92 | J14: Negatif | L14: Financials | M14: 103.4
B15: Télécoms | C15: 2 | D15: 38 | E15: ████░░░░░░ | F15: Telefónica, S.A. | G15: 0.361 | H15: 0.022 | I15: 1.01 | J15: Negatif | L15: Real Estate | M15: 89.1
B16: Énergie | C16: 4 | D16: 37 | E16: ████░░░░░░ | F16: Shell plc | G16: 0.18 | H16: -0.03 | I16: 2.3 | J16: Negatif | L16: Consumer Disc. | M16: 28.3
B17: Finance | C17: 7 | D17: 34 | E17: ███░░░░░░░ | F17: Société Générale Soc | G17: 0.222 | H17: 0.002 | I17: — | J17: Negatif | L17: Healthcare | M17: 23.2
B18: Euro Stoxx 50 — Total | C18: 48 | D18: 42 | F18: mediane | G18: 0.241 | H18: 0.003 | L18: Materials | M18: 22.7
B19: COMPOSITION DÉTAIL · Nb sociétés, score moyen, orientation — données pour allocation | K19: 4 | L19: Consumer Staples | M19: 16.1
H20: Secteur | I20: Mg EBITDA %
B21: Secteur | C21: Nb Soc. | D21: Score Moyen | E21: Score (barre) | F21: Orientation | H21: Télécoms | I21: 36.1
B22: Technologie | C22: 4 | D22: 56/100 | E22: ██████░░░░ | F22: → Neutre | H22: Serv. Publ. | I22: 28.7
B23: Matériaux | C23: 3 | D23: 50/100 | E23: █████░░░░░ | F23: → Neutre | H23: Technologie | I23: 28.4
B24: Santé | C24: 6 | D24: 46/100 | E24: █████░░░░░ | F24: → Neutre | H24: Matériaux | I24: 27.9
B25: Industrie | C25: 4 | D25: 41/100 | E25: ████░░░░░░ | F25: ↓ Negatif | H25: Santé | I25: 24.9
B26: Serv. Publ. | C26: 4 | D26: 40/100 | E26: ████░░░░░░ | F26: ↓ Negatif | H26: Conso. Déf. | I26: 23.2
B27: Conso. Déf. | C27: 4 | D27: 40/100 | E27: ████░░░░░░ | F27: ↓ Negatif | H27: Finance | I27: 22.2
B28: Conso. Cycl. | C28: 10 | D28: 38/100 | E28: ████░░░░░░ | F28: ↓ Negatif | H28: Industrie | I28: 19.1
B29: Télécoms | C29: 2 | D29: 38/100 | E29: ████░░░░░░ | F29: ↓ Negatif | H29: Énergie | I29: 18
B30: Énergie | C30: 4 | D30: 37/100 | E30: ████░░░░░░ | F30: ↓ Negatif | H30: Conso. Cycl. | I30: 15.5
B31: Finance | C31: 7 | D31: 34/100 | E31: ███░░░░░░░ | F31: ↓ Negatif | L31: Healthcare | M31: 3
L32: Comm. Services | M32: 3
H33: Secteur | I33: Nb Soc. | L33: Materials | M33: 2
H34: Conso. Cycl. | I34: 10 | L34: Real Estate | M34: 1
H35: Finance | I35: 7 | L35: Energy | M35: 1
H36: Santé | I36: 6 | L36: Utilities | M36: 1
H37: Technologie | I37: 4
H38: Énergie | I38: 4
H39: Industrie | I39: 4
H40: Serv. Publ. | I40: 4
H41: Conso. Déf. | I41: 4
H42: Matériaux | I42: 3
H43: Télécoms | I43: 2

Sheet SECTOR OVERVIEW
B1: FinSight IA · CAC 40 — Analyse Sectorielle | J1: 12/04/2026 | M1: Conso. Cycl. | O1: Secteur | P1: Score | Q1: Mg EBITDA
A2: Usage confidentiel · Calculs Python/NumPy depuis cache Supabase | M2: Conso. Déf. | O2: Healthcare | P2: 69 | Q2: 23.2
B3: Screening quantitatif · Scores composites Value / Growth / Quality / Momentum · Usage confidentiel · Calculs Python/NumPy | M3: Finance | O3: Real Estate | P3: 69 | Q3: 89.1
M4: Industrie | O4: Consumer Staples | P4: 56 | Q4: 16.1
B5: SCORECARD SECTORIELLE · Score FinSight composite, métriques médianes, signal d'investissement | M5: Matériaux | O5: Financials | P5: 55 | Q5: 103.4
M6: Santé | O6: Industrials | P6: 54 | Q6: 15.7
B7: Secteur | C7: # Soc. | D7: Score /100 | E7: Score (barre) | F7: Top Société | G7: Mg. EBITDA Méd. | H7: Score Gr. Méd. | I7: Altman Z Méd. | J7: Signal | K7: Tendance | M7: Serv. Publ. | O7: Materials | P7: 54 | Q7: 22.7
B8: =IFERROR(INDEX('SECTOR OVERVIEW'!M$1:M$21,1),"") -> Conso. Cycl. | C8: =IFERROR(IF(ISNUMBER(MATCH(INDEX('SECTOR OVERVIEW'!M$1:M$21,1),'DONNÉES BRUTES'!C$3:C$42,0)),COUNTIF('DONNÉES BRUTES'!C$3:C$42,INDEX('SECTOR OVERVIEW'!M$1:M$21,1)),""),"") -> 7 | D8: =IFERROR(IF(ISNUMBER(MATCH(INDEX('SECTOR OVERVIEW'!M$1:M$21,1),'DONNÉES BRUTES'!C$3:C$42,0)),ROUND(AVERAGEIF('DONNÉES BRUTES'!C$3:C$42,INDEX('SECTOR OVERVIEW'!M$1:M$21,1),'DONNÉES BRUTES'!AB$3:AB$42),0),""),"") -> 47 | E8: =IFERROR(IF(ISNUMBER(MATCH(INDEX('SECTOR OVERVIEW'!M$1:M$21,1),'DONNÉES BRUTES'!C$3:C$42,0)),REPT("█",ROUND(AVERAGEIF('DONNÉES BRUTES'!C$3:C$42,INDEX('SECTOR OVERVIEW'!M$1:M$21,1),'DONNÉES BRUTES'!AB$3:AB$42)/10,0))&REPT("░",10-ROUND(AVERAGEIF('DONNÉES BRUTES'!C$3:C$42,INDEX('SECTOR OVERVIEW'!M$1:M$21,1),'DONNÉES BRUTES'!AB$3:AB$42)/10,0))&" "&ROUND(AVERAGEIF('DONNÉES BRUTES'!C$3:C$42,INDEX('SECTOR OVERVIEW'!M$1:M$21,1),'DONNÉES BRUTES'!AB$3:AB$42),0),""),"") -> █████░░░░░ 47 | F8: =IFERROR(IF(ISNUMBER(MATCH(INDEX('SECTOR OVERVIEW'!M$1:M$21,1),'DONNÉES BRUTES'!C$3:C$42,0)),_xlfn.XLOOKUP(_xlfn.MAXIFS('DONNÉES BRUTES'!AB$3:AB$42,'DONNÉES BRUTES'!C$3:C$42,INDEX('SECTOR OVERVIEW'!M$1:M$21,1)),'DONNÉES BRUTES'!AB$3:AB$42,'DONNÉES BRUTES'!B$3:B$42),"—"),"—") -> Hermès International Société en commandite par actions | G8: 27.2% | H8: 23 | I8: {=IFERROR(IF(ISNUMBER(MATCH(INDEX('SECTOR OVERVIEW'!M$1:M$21,1),'DONNÉES BRUTES'!C$3:C$42,0)),ROUND(MEDIAN(IF('DONNÉES BRUTES'!C$3:C$42=INDEX('SECTOR OVERVIEW'!M$1:M$21,1),IF(ISNUMBER('DONNÉES BRUTES'!U$3:U$42),'DONNÉES BRUTES'!U$3:U$42))),2),"—"),"—")} -> 3.77 | J8: =IFERROR(IF(ISNUMBER(MATCH(INDEX('SECTOR OVERVIEW'!M$1:M$21,1),'DONNÉES BRUTES'!C$3:C$42,0)),IF(COUNTIFS('DONNÉES BRUTES'!C$3:C$42,INDEX('SECTOR OVERVIEW'!M$1:M$21,1),'DONNÉES BRUTES'!AD$3:AD$42,"Surpondérer")>0,"Surpondérer",IF(COUNTIFS('DONNÉES BRUTES'!C$3:C$42,INDEX('SECTOR OVERVIEW'!M$1:M$21,1),'DONNÉES BRUTES'!AD$3:AD$42,"Neutre")>=COUNTIFS('DONNÉES BRUTES'!C$3:C$42,INDEX('SECTOR OVERVIEW'!M$1:M$21,1),'DONNÉES BRUTES'!AD$3:AD$42,"Sous-pondérer"),"Neutre","Sous-pondérer")),"—"),"—") -> Surpondérer | K8: =IFERROR(IF(ISNUMBER(MATCH(INDEX('SECTOR OVERVIEW'!M$1:M$21,1),'DONNÉES BRUTES'!C$3:C$42,0)),IF(AVERAGEIF('DONNÉES BRUTES'!C$3:C$42,INDEX('SECTOR OVERVIEW'!M$1:M$21,1),'DONNÉES BRUTES'!AB$3:AB$42)>=65,"↑ Positif",IF(AVERAGEIF('DONNÉES BRUTES'!C$3:C$42,INDEX('SECTOR OVERVIEW'!M$1:M$21,1),'DONNÉES BRUTES'!AB$3:AB$42)>=50,"→ Neutre","↓ Négatif")),"—"),"—") -> ↓ Négatif | M8: Technologie | O8: Utilities | P8: 46 | Q8: 20
B9: =IFERROR(INDEX('SECTOR OVERVIEW'!M$1:M$21,2),"") -> Conso. Déf. | C9: =IFERROR(IF(ISNUMBER(MATCH(INDEX('SECTOR OVERVIEW'!M$1:M$21,2),'DONNÉES BRUTES'!C$3:C$42,0)),COUNTIF('DONNÉES BRUTES'!C$3:C$42,INDEX('SECTOR OVERVIEW'!M$1:M$21,2)),""),"") -> 4 | D9: =IFERROR(IF(ISNUMBER(MATCH(INDEX('SECTOR OVERVIEW'!M$1:M$21,2),'DONNÉES BRUTES'!C$3:C$42,0)),ROUND(AVERAGEIF('DONNÉES BRUTES'!C$3:C$42,INDEX('SECTOR OVERVIEW'!M$1:M$21,2),'DONNÉES BRUTES'!AB$3:AB$42),0),""),"") -> 40 | E9: =IFERROR(IF(ISNUMBER(MATCH(INDEX('SECTOR OVERVIEW'!M$1:M$21,2),'DONNÉES BRUTES'!C$3:C$42,0)),REPT("█",ROUND(AVERAGEIF('DONNÉES BRUTES'!C$3:C$42,INDEX('SECTOR OVERVIEW'!M$1:M$21,2),'DONNÉES BRUTES'!AB$3:AB$42)/10,0))&REPT("░",10-ROUND(AVERAGEIF('DONNÉES BRUTES'!C$3:C$42,INDEX('SECTOR OVERVIEW'!M$1:M$21,2),'DONNÉES BRUTES'!AB$3:AB$42)/10,0))&" "&ROUND(AVERAGEIF('DONNÉES BRUTES'!C$3:C$42,INDEX('SECTOR OVERVIEW'!M$1:M$21,2),'DONNÉES BRUTES'!AB$3:AB$42),0),""),"") -> ████░░░░░░ 40 | F9: =IFERROR(IF(ISNUMBER(MATCH(INDEX('SECTOR OVERVIEW'!M$1:M$21,2),'DONNÉES BRUTES'!C$3:C$42,0)),_xlfn.XLOOKUP(_xlfn.MAXIFS('DONNÉES BRUTES'!AB$3:AB$42,'DONNÉES BRUTES'!C$3:C$42,INDEX('SECTOR OVERVIEW'!M$1:M$21,2)),'DONNÉES BRUTES'!AB$3:AB$42,'DONNÉES BRUTES'!B$3:B$42),"—"),"—") -> GSK plc | G9: 28.3% | H9: 66 | I9: {=IFERROR(IF(ISNUMBER(MATCH(INDEX('SECTOR OVERVIEW'!M$1:M$21,2),'DONNÉES BRUTES'!C$3:C$42,0)),ROUND(MEDIAN(IF('DONNÉES BRUTES'!C$3:C$42=INDEX('SECTOR OVERVIEW'!M$1:M$21,2),IF(ISNUMBER('DONNÉES BRUTES'!U$3:U$42),'DONNÉES BRUTES'!U$3:U$42))),2),"—"),"—")} -> 2.86 | J9: =IFERROR(IF(ISNUMBER(MATCH(INDEX('SECTOR OVERVIEW'!M$1:M$21,2),'DONNÉES BRUTES'!C$3:C$42,0)),IF(COUNTIFS('DONNÉES BRUTES'!C$3:C$42,INDEX('SECTOR OVERVIEW'!M$1:M$21,2),'DONNÉES BRUTES'!AD$3:AD$42,"Surpondérer")>0,"Surpondérer",IF(COUNTIFS('DONNÉES BRUTES'!C$3:C$42,INDEX('SECTOR OVERVIEW'!M$1:M$21,2),'DONNÉES BRUTES'!AD$3:AD$42,"Neutre")>=COUNTIFS('DONNÉES BRUTES'!C$3:C$42,INDEX('SECTOR OVERVIEW'!M$1:M$21,2),'DONNÉES BRUTES'!AD$3:AD$42,"Sous-pondérer"),"Neutre","Sous-pondérer")),"—"),"—") -> Sous-pondérer | K9: =IFERROR(IF(ISNUMBER(MATCH(INDEX('SECTOR OVERVIEW'!M$1:M$21,2),'DONNÉES BRUTES'!C$3:C$42,0)),IF(AVERAGEIF('DONNÉES BRUTES'!C$3:C$42,INDEX('SECTOR OVERVIEW'!M$1:M$21,2),'DONNÉES BRUTES'!AB$3:AB$42)>=65,"↑ Positif",IF(AVERAGEIF('DONNÉES BRUTES'!C$3:C$42,INDEX('SECTOR OVERVIEW'!M$1:M$21,2),'DONNÉES BRUTES'!AB$3:AB$42)>=50,"→ Neutre","↓ Négatif")),"—"),"—") -> ↓ Négatif | M9: Télécoms | O9: Technology | P9: 36 | Q9: 19.6
B10: =IFERROR(INDEX('SECTOR OVERVIEW'!M$1:M$21,3),"") -> Finance | C10: =IFERROR(IF(ISNUMBER(MATCH(INDEX('SECTOR OVERVIEW'!M$1:M$21,3),'DONNÉES BRUTES'!C$3:C$42,0)),COUNTIF('DONNÉES BRUTES'!C$3:C$42,INDEX('SECTOR OVERVIEW'!M$1:M$21,3)),""),"") -> 5 | D10: =IFERROR(IF(ISNUMBER(MATCH(INDEX('SECTOR OVERVIEW'!M$1:M$21,3),'DONNÉES BRUTES'!C$3:C$42,0)),ROUND(AVERAGEIF('DONNÉES BRUTES'!C$3:C$42,INDEX('SECTOR OVERVIEW'!M$1:M$21,3),'DONNÉES BRUTES'!AB$3:AB$42),0),""),"") -> 38 | E10: =IFERROR(IF(ISNUMBER(MATCH(INDEX('SECTOR OVERVIEW'!M$1:M$21,3),'DONNÉES BRUTES'!C$3:C$42,0)),REPT("█",ROUND(AVERAGEIF('DONNÉES BRUTES'!C$3:C$42,INDEX('SECTOR OVERVIEW'!M$1:M$21,3),'DONNÉES BRUTES'!AB$3:AB$42)/10,0))&REPT("░",10-ROUND(AVERAGEIF('DONNÉES BRUTES'!C$3:C$42,INDEX('SECTOR OVERVIEW'!M$1:M$21,3),'DONNÉES BRUTES'!AB$3:AB$42)/10,0))&" "&ROUND(AVERAGEIF('DONNÉES BRUTES'!C$3:C$42,INDEX('SECTOR OVERVIEW'!M$1:M$21,3),'DONNÉES BRUTES'!AB$3:AB$42),0),""),"") -> ████░░░░░░ 38 | F10: =IFERROR(IF(ISNUMBER(MATCH(INDEX('SECTOR OVERVIEW'!M$1:M$21,3),'DONNÉES BRUTES'!C$3:C$42,0)),_xlfn.XLOOKUP(_xlfn.MAXIFS('DONNÉES BRUTES'!AB$3:AB$42,'DONNÉES BRUTES'!C$3:C$42,INDEX('SECTOR OVERVIEW'!M$1:M$21,3)),'DONNÉES BRUTES'!AB$3:AB$42,'DONNÉES BRUTES'!B$3:B$42),"—"),"—") -> Koninklijke Philips N.V. | G10: 16.1% | H10: 59 | I10: {=IFERROR(IF(ISNUMBER(MATCH(INDEX('SECTOR OVERVIEW'!M$1:M$21,3),'DONNÉES BRUTES'!C$3:C$42,0)),ROUND(MEDIAN(IF('DONNÉES BRUTES'!C$3:C$42=INDEX('SECTOR OVERVIEW'!M$1:M$21,3),IF(ISNUMBER('DONNÉES BRUTES'!U$3:U$42),'DONNÉES BRUTES'!U$3:U$42))),2),"—"),"—")} -> — | J10: =IFERROR(IF(ISNUMBER(MATCH(INDEX('SECTOR OVERVIEW'!M$1:M$21,3),'DONNÉES BRUTES'!C$3:C$42,0)),IF(COUNTIFS('DONNÉES BRUTES'!C$3:C$42,INDEX('SECTOR OVERVIEW'!M$1:M$21,3),'DONNÉES BRUTES'!AD$3:AD$42,"Surpondérer")>0,"Surpondérer",IF(COUNTIFS('DONNÉES BRUTES'!C$3:C$42,INDEX('SECTOR OVERVIEW'!M$1:M$21,3),'DONNÉES BRUTES'!AD$3:AD$42,"Neutre")>=COUNTIFS('DONNÉES BRUTES'!C$3:C$42,INDEX('SECTOR OVERVIEW'!M$1:M$21,3),'DONNÉES BRUTES'!AD$3:AD$42,"Sous-pondérer"),"Neutre","Sous-pondérer")),"—"),"—") -> Sous-pondérer | K10: =IFERROR(IF(ISNUMBER(MATCH(INDEX('SECTOR OVERVIEW'!M$1:M$21,3),'DONNÉES BRUTES'!C$3:C$42,0)),IF(AVERAGEIF('DONNÉES BRUTES'!C$3:C$42,INDEX('SECTOR OVERVIEW'!M$1:M$21,3),'DONNÉES BRUTES'!AB$3:AB$42)>=65,"↑ Positif",IF(AVERAGEIF('DONNÉES BRUTES'!C$3:C$42,INDEX('SECTOR OVERVIEW'!M$1:M$21,3),'DONNÉES BRUTES'!AB$3:AB$42)>=50,"→ Neutre","↓ Négatif")),"—"),"—") -> ↓ Négatif | M10: Énergie | O10: Consumer Disc. | P10: 41 | Q10: 28.3
B11: =IFERROR(INDEX('SECTOR OVERVIEW'!M$1:M$21,4),"") -> Industrie | C11: =IFERROR(IF(ISNUMBER(MATCH(INDEX('SECTOR OVERVIEW'!M$1:M$21,4),'DONNÉES BRUTES'!C$3:C$42,0)),COUNTIF('DONNÉES BRUTES'!C$3:C$42,INDEX('SECTOR OVERVIEW'!M$1:M$21,4)),""),"") -> 4 | D11: =IFERROR(IF(ISNUMBER(MATCH(INDEX('SECTOR OVERVIEW'!M$1:M$21,4),'DONNÉES BRUTES'!C$3:C$42,0)),ROUND(AVERAGEIF('DONNÉES BRUTES'!C$3:C$42,INDEX('SECTOR OVERVIEW'!M$1:M$21,4),'DONNÉES BRUTES'!AB$3:AB$42),0),""),"") -> 41 | E11: =IFERROR(IF(ISNUMBER(MATCH(INDEX('SECTOR OVERVIEW'!M$1:M$21,4),'DONNÉES BRUTES'!C$3:C$42,0)),REPT("█",ROUND(AVERAGEIF('DONNÉES BRUTES'!C$3:C$42,INDEX('SECTOR OVERVIEW'!M$1:M$21,4),'DONNÉES BRUTES'!AB$3:AB$42)/10,0))&REPT("░",10-ROUND(AVERAGEIF('DONNÉES BRUTES'!C$3:C$42,INDEX('SECTOR OVERVIEW'!M$1:M$21,4),'DONNÉES BRUTES'!AB$3:AB$42)/10,0))&" "&ROUND(AVERAGEIF('DONNÉES BRUTES'!C$3:C$42,INDEX('SECTOR OVERVIEW'!M$1:M$21,4),'DONNÉES BRUTES'!AB$3:AB$42),0),""),"") -> ████░░░░░░ 41 | F11: =IFERROR(IF(ISNUMBER(MATCH(INDEX('SECTOR OVERVIEW'!M$1:M$21,4),'DONNÉES BRUTES'!C$3:C$42,0)),_xlfn.XLOOKUP(_xlfn.MAXIFS('DONNÉES BRUTES'!AB$3:AB$42,'DONNÉES BRUTES'!C$3:C$42,INDEX('SECTOR OVERVIEW'!M$1:M$21,4)),'DONNÉES BRUTES'!AB$3:AB$42,'DONNÉES BRUTES'!B$3:B$42),"—"),"—") -> Siemens Aktiengesellschaft | G11: — | H11: — | I11: {=IFERROR(IF(ISNUMBER(MATCH(INDEX('SECTOR OVERVIEW'!M$1:M$21,4),'DONNÉES BRUTES'!C$3:C$42,0)),ROUND(MEDIAN(IF('DONNÉES BRUTES'!C$3:C$42=INDEX('SECTOR OVERVIEW'!M$1:M$21,4),IF(ISNUMBER('DONNÉES BRUTES'!U$3:U$42),'DONNÉES BRUTES'!U$3:U$42))),2),"—"),"—")} -> 1.64 | J11: =IFERROR(IF(ISNUMBER(MATCH(INDEX('SECTOR OVERVIEW'!M$1:M$21,4),'DONNÉES BRUTES'!C$3:C$42,0)),IF(COUNTIFS('DONNÉES BRUTES'!C$3:C$42,INDEX('SECTOR OVERVIEW'!M$1:M$21,4),'DONNÉES BRUTES'!AD$3:AD$42,"Surpondérer")>0,"Surpondérer",IF(COUNTIFS('DONNÉES BRUTES'!C$3:C$42,INDEX('SECTOR OVERVIEW'!M$1:M$21,4),'DONNÉES BRUTES'!AD$3:AD$42,"Neutre")>=COUNTIFS('DONNÉES BRUTES'!C$3:C$42,INDEX('SECTOR OVERVIEW'!M$1:M$21,4),'DONNÉES BRUTES'!AD$3:AD$42,"Sous-pondérer"),"Neutre","Sous-pondérer")),"—"),"—") -> Neutre | K11: =IFERROR(IF(ISNUMBER(MATCH(INDEX('SECTOR OVERVIEW'!M$1:M$21,4),'DONNÉES BRUTES'!C$3:C$42,0)),IF(AVERAGEIF('DONNÉES BRUTES'!C$3:C$42,INDEX('SECTOR OVERVIEW'!M$1:M$21,4),'DONNÉES BRUTES'!AB$3:AB$42)>=65,"↑ Positif",IF(AVERAGEIF('DONNÉES BRUTES'!C$3:C$42,INDEX('SECTOR OVERVIEW'!M$1:M$21,4),'DONNÉES BRUTES'!AB$3:AB$42)>=50,"→ Neutre","↓ Négatif")),"—"),"—") -> ↓ Négatif | O11: Comm. Services | P11: 38 | Q11: 27.2
B12: =IFERROR(INDEX('SECTOR OVERVIEW'!M$1:M$21,5),"") -> Matériaux | C12: =IFERROR(IF(ISNUMBER(MATCH(INDEX('SECTOR OVERVIEW'!M$1:M$21,5),'DONNÉES BRUTES'!C$3:C$42,0)),COUNTIF('DONNÉES BRUTES'!C$3:C$42,INDEX('SECTOR OVERVIEW'!M$1:M$21,5)),""),"") -> 3 | D12: =IFERROR(IF(ISNUMBER(MATCH(INDEX('SECTOR OVERVIEW'!M$1:M$21,5),'DONNÉES BRUTES'!C$3:C$42,0)),ROUND(AVERAGEIF('DONNÉES BRUTES'!C$3:C$42,INDEX('SECTOR OVERVIEW'!M$1:M$21,5),'DONNÉES BRUTES'!AB$3:AB$42),0),""),"") -> 50 | E12: =IFERROR(IF(ISNUMBER(MATCH(INDEX('SECTOR OVERVIEW'!M$1:M$21,5),'DONNÉES BRUTES'!C$3:C$42,0)),REPT("█",ROUND(AVERAGEIF('DONNÉES BRUTES'!C$3:C$42,INDEX('SECTOR OVERVIEW'!M$1:M$21,5),'DONNÉES BRUTES'!AB$3:AB$42)/10,0))&REPT("░",10-ROUND(AVERAGEIF('DONNÉES BRUTES'!C$3:C$42,INDEX('SECTOR OVERVIEW'!M$1:M$21,5),'DONNÉES BRUTES'!AB$3:AB$42)/10,0))&" "&ROUND(AVERAGEIF('DONNÉES BRUTES'!C$3:C$42,INDEX('SECTOR OVERVIEW'!M$1:M$21,5),'DONNÉES BRUTES'!AB$3:AB$42),0),""),"") -> █████░░░░░ 50 | F12: =IFERROR(IF(ISNUMBER(MATCH(INDEX('SECTOR OVERVIEW'!M$1:M$21,5),'DONNÉES BRUTES'!C$3:C$42,0)),_xlfn.XLOOKUP(_xlfn.MAXIFS('DONNÉES BRUTES'!AB$3:AB$42,'DONNÉES BRUTES'!C$3:C$42,INDEX('SECTOR OVERVIEW'!M$1:M$21,5)),'DONNÉES BRUTES'!AB$3:AB$42,'DONNÉES BRUTES'!B$3:B$42),"—"),"—") -> Rio Tinto Group | G12: 103.4% | H12: 55 | I12: {=IFERROR(IF(ISNUMBER(MATCH(INDEX('SECTOR OVERVIEW'!M$1:M$21,5),'DONNÉES BRUTES'!C$3:C$42,0)),ROUND(MEDIAN(IF('DONNÉES BRUTES'!C$3:C$42=INDEX('SECTOR OVERVIEW'!M$1:M$21,5),IF(ISNUMBER('DONNÉES BRUTES'!U$3:U$42),'DONNÉES BRUTES'!U$3:U$42))),2),"—"),"—")} -> 3.45 | J12: =IFERROR(IF(ISNUMBER(MATCH(INDEX('SECTOR OVERVIEW'!M$1:M$21,5),'DONNÉES BRUTES'!C$3:C$42,0)),IF(COUNTIFS('DONNÉES BRUTES'!C$3:C$42,INDEX('SECTOR OVERVIEW'!M$1:M$21,5),'DONNÉES BRUTES'!AD$3:AD$42,"Surpondérer")>0,"Surpondérer",IF(COUNTIFS('DONNÉES BRUTES'!C$3:C$42,INDEX('SECTOR OVERVIEW'!M$1:M$21,5),'DONNÉES BRUTES'!AD$3:AD$42,"Neutre")>=COUNTIFS('DONNÉES BRUTES'!C$3:C$42,INDEX('SECTOR OVERVIEW'!M$1:M$21,5),'DONNÉES BRUTES'!AD$3:AD$42,"Sous-pondérer"),"Neutre","Sous-pondérer")),"—"),"—") -> Surpondérer | K12: =IFERROR(IF(ISNUMBER(MATCH(INDEX('SECTOR OVERVIEW'!M$1:M$21,5),'DONNÉES BRUTES'!C$3:C$42,0)),IF(AVERAGEIF('DONNÉES BRUTES'!C$3:C$42,INDEX('SECTOR OVERVIEW'!M$1:M$21,5),'DONNÉES BRUTES'!AB$3:AB$42)>=65,"↑ Positif",IF(AVERAGEIF('DONNÉES BRUTES'!C$3:C$42,INDEX('SECTOR OVERVIEW'!M$1:M$21,5),'DONNÉES BRUTES'!AB$3:AB$42)>=50,"→ Neutre","↓ Négatif")),"—"),"—") -> → Neutre | O12: Energy | P12: 18 | Q12: 0
B13: =IFERROR(INDEX('SECTOR OVERVIEW'!M$1:M$21,6),"") -> Santé | C13: =IFERROR(IF(ISNUMBER(MATCH(INDEX('SECTOR OVERVIEW'!M$1:M$21,6),'DONNÉES BRUTES'!C$3:C$42,0)),COUNTIF('DONNÉES BRUTES'!C$3:C$42,INDEX('SECTOR OVERVIEW'!M$1:M$21,6)),""),"") -> 5 | D13: =IFERROR(IF(ISNUMBER(MATCH(INDEX('SECTOR OVERVIEW'!M$1:M$21,6),'DONNÉES BRUTES'!C$3:C$42,0)),ROUND(AVERAGEIF('DONNÉES BRUTES'!C$3:C$42,INDEX('SECTOR OVERVIEW'!M$1:M$21,6),'DONNÉES BRUTES'!AB$3:AB$42),0),""),"") -> 50 | E13: =IFERROR(IF(ISNUMBER(MATCH(INDEX('SECTOR OVERVIEW'!M$1:M$21,6),'DONNÉES BRUTES'!C$3:C$42,0)),REPT("█",ROUND(AVERAGEIF('DONNÉES BRUTES'!C$3:C$42,INDEX('SECTOR OVERVIEW'!M$1:M$21,6),'DONNÉES BRUTES'!AB$3:AB$42)/10,0))&REPT("░",10-ROUND(AVERAGEIF('DONNÉES BRUTES'!C$3:C$42,INDEX('SECTOR OVERVIEW'!M$1:M$21,6),'DONNÉES BRUTES'!AB$3:AB$42)/10,0))&" "&ROUND(AVERAGEIF('DONNÉES BRUTES'!C$3:C$42,INDEX('SECTOR OVERVIEW'!M$1:M$21,6),'DONNÉES BRUTES'!AB$3:AB$42),0),""),"") -> █████░░░░░ 50 | F13: =IFERROR(IF(ISNUMBER(MATCH(INDEX('SECTOR OVERVIEW'!M$1:M$21,6),'DONNÉES BRUTES'!C$3:C$42,0)),_xlfn.XLOOKUP(_xlfn.MAXIFS('DONNÉES BRUTES'!AB$3:AB$42,'DONNÉES BRUTES'!C$3:C$42,INDEX('SECTOR OVERVIEW'!M$1:M$21,6)),'DONNÉES BRUTES'!AB$3:AB$42,'DONNÉES BRUTES'!B$3:B$42),"—"),"—") -> AstraZeneca PLC | G13: 23.2% | H13: 72 | I13: {=IFERROR(IF(ISNUMBER(MATCH(INDEX('SECTOR OVERVIEW'!M$1:M$21,6),'DONNÉES BRUTES'!C$3:C$42,0)),ROUND(MEDIAN(IF('DONNÉES BRUTES'!C$3:C$42=INDEX('SECTOR OVERVIEW'!M$1:M$21,6),IF(ISNUMBER('DONNÉES BRUTES'!U$3:U$42),'DONNÉES BRUTES'!U$3:U$42))),2),"—"),"—")} -> 1.96 | J13: =IFERROR(IF(ISNUMBER(MATCH(INDEX('SECTOR OVERVIEW'!M$1:M$21,6),'DONNÉES BRUTES'!C$3:C$42,0)),IF(COUNTIFS('DONNÉES BRUTES'!C$3:C$42,INDEX('SECTOR OVERVIEW'!M$1:M$21,6),'DONNÉES BRUTES'!AD$3:AD$42,"Surpondérer")>0,"Surpondérer",IF(COUNTIFS('DONNÉES BRUTES'!C$3:C$42,INDEX('SECTOR OVERVIEW'!M$1:M$21,6),'DONNÉES BRUTES'!AD$3:AD$42,"Neutre")>=COUNTIFS('DONNÉES BRUTES'!C$3:C$42,INDEX('SECTOR OVERVIEW'!M$1:M$21,6),'DONNÉES BRUTES'!AD$3:AD$42,"Sous-pondérer"),"Neutre","Sous-pondérer")),"—"),"—") -> Surpondérer | K13: =IFERROR(IF(ISNUMBER(MATCH(INDEX('SECTOR OVERVIEW'!M$1:M$21,6),'DONNÉES BRUTES'!C$3:C$42,0)),IF(AVERAGEIF('DONNÉES BRUTES'!C$3:C$42,INDEX('SECTOR OVERVIEW'!M$1:M$21,6),'DONNÉES BRUTES'!AB$3:AB$42)>=65,"↑ Positif",IF(AVERAGEIF('DONNÉES BRUTES'!C$3:C$42,INDEX('SECTOR OVERVIEW'!M$1:M$21,6),'DONNÉES BRUTES'!AB$3:AB$42)>=50,"→ Neutre","↓ Négatif")),"—"),"—") -> ↓ Négatif
B14: =IFERROR(INDEX('SECTOR OVERVIEW'!M$1:M$21,7),"") -> Serv. Publ. | C14: =IFERROR(IF(ISNUMBER(MATCH(INDEX('SECTOR OVERVIEW'!M$1:M$21,7),'DONNÉES BRUTES'!C$3:C$42,0)),COUNTIF('DONNÉES BRUTES'!C$3:C$42,INDEX('SECTOR OVERVIEW'!M$1:M$21,7)),""),"") -> 3 | D14: =IFERROR(IF(ISNUMBER(MATCH(INDEX('SECTOR OVERVIEW'!M$1:M$21,7),'DONNÉES BRUTES'!C$3:C$42,0)),ROUND(AVERAGEIF('DONNÉES BRUTES'!C$3:C$42,INDEX('SECTOR OVERVIEW'!M$1:M$21,7),'DONNÉES BRUTES'!AB$3:AB$42),0),""),"") -> 44 | E14: =IFERROR(IF(ISNUMBER(MATCH(INDEX('SECTOR OVERVIEW'!M$1:M$21,7),'DONNÉES BRUTES'!C$3:C$42,0)),REPT("█",ROUND(AVERAGEIF('DONNÉES BRUTES'!C$3:C$42,INDEX('SECTOR OVERVIEW'!M$1:M$21,7),'DONNÉES BRUTES'!AB$3:AB$42)/10,0))&REPT("░",10-ROUND(AVERAGEIF('DONNÉES BRUTES'!C$3:C$42,INDEX('SECTOR OVERVIEW'!M$1:M$21,7),'DONNÉES BRUTES'!AB$3:AB$42)/10,0))&" "&ROUND(AVERAGEIF('DONNÉES BRUTES'!C$3:C$42,INDEX('SECTOR OVERVIEW'!M$1:M$21,7),'DONNÉES BRUTES'!AB$3:AB$42),0),""),"") -> ████░░░░░░ 44 | F14: =IFERROR(IF(ISNUMBER(MATCH(INDEX('SECTOR OVERVIEW'!M$1:M$21,7),'DONNÉES BRUTES'!C$3:C$42,0)),_xlfn.XLOOKUP(_xlfn.MAXIFS('DONNÉES BRUTES'!AB$3:AB$42,'DONNÉES BRUTES'!C$3:C$42,INDEX('SECTOR OVERVIEW'!M$1:M$21,7)),'DONNÉES BRUTES'!AB$3:AB$42,'DONNÉES BRUTES'!B$3:B$42),"—"),"—") -> AstraZeneca PLC | G14: 15.7% | H14: 31 | I14: {=IFERROR(IF(ISNUMBER(MATCH(INDEX('SECTOR OVERVIEW'!M$1:M$21,7),'DONNÉES BRUTES'!C$3:C$42,0)),ROUND(MEDIAN(IF('DONNÉES BRUTES'!C$3:C$42=INDEX('SECTOR OVERVIEW'!M$1:M$21,7),IF(ISNUMBER('DONNÉES BRUTES'!U$3:U$42),'DONNÉES BRUTES'!U$3:U$42))),2),"—"),"—")} -> 1.84 | J14: =IFERROR(IF(ISNUMBER(MATCH(INDEX('SECTOR OVERVIEW'!M$1:M$21,7),'DONNÉES BRUTES'!C$3:C$42,0)),IF(COUNTIFS('DONNÉES BRUTES'!C$3:C$42,INDEX('SECTOR OVERVIEW'!M$1:M$21,7),'DONNÉES BRUTES'!AD$3:AD$42,"Surpondérer")>0,"Surpondérer",IF(COUNTIFS('DONNÉES BRUTES'!C$3:C$42,INDEX('SECTOR OVERVIEW'!M$1:M$21,7),'DONNÉES BRUTES'!AD$3:AD$42,"Neutre")>=COUNTIFS('DONNÉES BRUTES'!C$3:C$42,INDEX('SECTOR OVERVIEW'!M$1:M$21,7),'DONNÉES BRUTES'!AD$3:AD$42,"Sous-pondérer"),"Neutre","Sous-pondérer")),"—"),"—") -> Surpondérer | K14: =IFERROR(IF(ISNUMBER(MATCH(INDEX('SECTOR OVERVIEW'!M$1:M$21,7),'DONNÉES BRUTES'!C$3:C$42,0)),IF(AVERAGEIF('DONNÉES BRUTES'!C$3:C$42,INDEX('SECTOR OVERVIEW'!M$1:M$21,7),'DONNÉES BRUTES'!AB$3:AB$42)>=65,"↑ Positif",IF(AVERAGEIF('DONNÉES BRUTES'!C$3:C$42,INDEX('SECTOR OVERVIEW'!M$1:M$21,7),'DONNÉES BRUTES'!AB$3:AB$42)>=50,"→ Neutre","↓ Négatif")),"—"),"—") -> ↓ Négatif
B15: =IFERROR(INDEX('SECTOR OVERVIEW'!M$1:M$21,8),"") -> Technologie | C15: =IFERROR(IF(ISNUMBER(MATCH(INDEX('SECTOR OVERVIEW'!M$1:M$21,8),'DONNÉES BRUTES'!C$3:C$42,0)),COUNTIF('DONNÉES BRUTES'!C$3:C$42,INDEX('SECTOR OVERVIEW'!M$1:M$21,8)),""),"") -> 4 | D15: =IFERROR(IF(ISNUMBER(MATCH(INDEX('SECTOR OVERVIEW'!M$1:M$21,8),'DONNÉES BRUTES'!C$3:C$42,0)),ROUND(AVERAGEIF('DONNÉES BRUTES'!C$3:C$42,INDEX('SECTOR OVERVIEW'!M$1:M$21,8),'DONNÉES BRUTES'!AB$3:AB$42),0),""),"") -> 56 | E15: =IFERROR(IF(ISNUMBER(MATCH(INDEX('SECTOR OVERVIEW'!M$1:M$21,8),'DONNÉES BRUTES'!C$3:C$42,0)),REPT("█",ROUND(AVERAGEIF('DONNÉES BRUTES'!C$3:C$42,INDEX('SECTOR OVERVIEW'!M$1:M$21,8),'DONNÉES BRUTES'!AB$3:AB$42)/10,0))&REPT("░",10-ROUND(AVERAGEIF('DONNÉES BRUTES'!C$3:C$42,INDEX('SECTOR OVERVIEW'!M$1:M$21,8),'DONNÉES BRUTES'!AB$3:AB$42)/10,0))&" "&ROUND(AVERAGEIF('DONNÉES BRUTES'!C$3:C$42,INDEX('SECTOR OVERVIEW'!M$1:M$21,8),'DONNÉES BRUTES'!AB$3:AB$42),0),""),"") -> ██████░░░░ 56 | F15: =IFERROR(IF(ISNUMBER(MATCH(INDEX('SECTOR OVERVIEW'!M$1:M$21,8),'DONNÉES BRUTES'!C$3:C$42,0)),_xlfn.XLOOKUP(_xlfn.MAXIFS('DONNÉES BRUTES'!AB$3:AB$42,'DONNÉES BRUTES'!C$3:C$42,INDEX('SECTOR OVERVIEW'!M$1:M$21,8)),'DONNÉES BRUTES'!AB$3:AB$42,'DONNÉES BRUTES'!B$3:B$42),"—"),"—") -> ASML Holding N.V. | G15: 22.7% | H15: 66 | I15: {=IFERROR(IF(ISNUMBER(MATCH(INDEX('SECTOR OVERVIEW'!M$1:M$21,8),'DONNÉES BRUTES'!C$3:C$42,0)),ROUND(MEDIAN(IF('DONNÉES BRUTES'!C$3:C$42=INDEX('SECTOR OVERVIEW'!M$1:M$21,8),IF(ISNUMBER('DONNÉES BRUTES'!U$3:U$42),'DONNÉES BRUTES'!U$3:U$42))),2),"—"),"—")} -> 3.76 | J15: =IFERROR(IF(ISNUMBER(MATCH(INDEX('SECTOR OVERVIEW'!M$1:M$21,8),'DONNÉES BRUTES'!C$3:C$42,0)),IF(COUNTIFS('DONNÉES BRUTES'!C$3:C$42,INDEX('SECTOR OVERVIEW'!M$1:M$21,8),'DONNÉES BRUTES'!AD$3:AD$42,"Surpondérer")>0,"Surpondérer",IF(COUNTIFS('DONNÉES BRUTES'!C$3:C$42,INDEX('SECTOR OVERVIEW'!M$1:M$21,8),'DONNÉES BRUTES'!AD$3:AD$42,"Neutre")>=COUNTIFS('DONNÉES BRUTES'!C$3:C$42,INDEX('SECTOR OVERVIEW'!M$1:M$21,8),'DONNÉES BRUTES'!AD$3:AD$42,"Sous-pondérer"),"Neutre","Sous-pondérer")),"—"),"—") -> Surpondérer | K15: =IFERROR(IF(ISNUMBER(MATCH(INDEX('SECTOR OVERVIEW'!M$1:M$21,8),'DONNÉES BRUTES'!C$3:C$42,0)),IF(AVERAGEIF('DONNÉES BRUTES'!C$3:C$42,INDEX('SECTOR OVERVIEW'!M$1:M$21,8),'DONNÉES BRUTES'!AB$3:AB$42)>=65,"↑ Positif",IF(AVERAGEIF('DONNÉES BRUTES'!C$3:C$42,INDEX('SECTOR OVERVIEW'!M$1:M$21,8),'DONNÉES BRUTES'!AB$3:AB$42)>=50,"→ Neutre","↓ Négatif")),"—"),"—") -> → Neutre
B16: =IFERROR(INDEX('SECTOR OVERVIEW'!M$1:M$21,9),"") -> Télécoms | C16: =IFERROR(IF(ISNUMBER(MATCH(INDEX('SECTOR OVERVIEW'!M$1:M$21,9),'DONNÉES BRUTES'!C$3:C$42,0)),COUNTIF('DONNÉES BRUTES'!C$3:C$42,INDEX('SECTOR OVERVIEW'!M$1:M$21,9)),""),"") -> 2 | D16: =IFERROR(IF(ISNUMBER(MATCH(INDEX('SECTOR OVERVIEW'!M$1:M$21,9),'DONNÉES BRUTES'!C$3:C$42,0)),ROUND(AVERAGEIF('DONNÉES BRUTES'!C$3:C$42,INDEX('SECTOR OVERVIEW'!M$1:M$21,9),'DONNÉES BRUTES'!AB$3:AB$42),0),""),"") -> 39 | E16: =IFERROR(IF(ISNUMBER(MATCH(INDEX('SECTOR OVERVIEW'!M$1:M$21,9),'DONNÉES BRUTES'!C$3:C$42,0)),REPT("█",ROUND(AVERAGEIF('DONNÉES BRUTES'!C$3:C$42,INDEX('SECTOR OVERVIEW'!M$1:M$21,9),'DONNÉES BRUTES'!AB$3:AB$42)/10,0))&REPT("░",10-ROUND(AVERAGEIF('DONNÉES BRUTES'!C$3:C$42,INDEX('SECTOR OVERVIEW'!M$1:M$21,9),'DONNÉES BRUTES'!AB$3:AB$42)/10,0))&" "&ROUND(AVERAGEIF('DONNÉES BRUTES'!C$3:C$42,INDEX('SECTOR OVERVIEW'!M$1:M$21,9),'DONNÉES BRUTES'!AB$3:AB$42),0),""),"") -> ████░░░░░░ 39 | F16: =IFERROR(IF(ISNUMBER(MATCH(INDEX('SECTOR OVERVIEW'!M$1:M$21,9),'DONNÉES BRUTES'!C$3:C$42,0)),_xlfn.XLOOKUP(_xlfn.MAXIFS('DONNÉES BRUTES'!AB$3:AB$42,'DONNÉES BRUTES'!C$3:C$42,INDEX('SECTOR OVERVIEW'!M$1:M$21,9)),'DONNÉES BRUTES'!AB$3:AB$42,'DONNÉES BRUTES'!B$3:B$42),"—"),"—") -> TotalEnergies SE | G16: 19.8% | H16: 50 | I16: {=IFERROR(IF(ISNUMBER(MATCH(INDEX('SECTOR OVERVIEW'!M$1:M$21,9),'DONNÉES BRUTES'!C$3:C$42,0)),ROUND(MEDIAN(IF('DONNÉES BRUTES'!C$3:C$42=INDEX('SECTOR OVERVIEW'!M$1:M$21,9),IF(ISNUMBER('DONNÉES BRUTES'!U$3:U$42),'DONNÉES BRUTES'!U$3:U$42))),2),"—"),"—")} -> 1.01 | J16: =IFERROR(IF(ISNUMBER(MATCH(INDEX('SECTOR OVERVIEW'!M$1:M$21,9),'DONNÉES BRUTES'!C$3:C$42,0)),IF(COUNTIFS('DONNÉES BRUTES'!C$3:C$42,INDEX('SECTOR OVERVIEW'!M$1:M$21,9),'DONNÉES BRUTES'!AD$3:AD$42,"Surpondérer")>0,"Surpondérer",IF(COUNTIFS('DONNÉES BRUTES'!C$3:C$42,INDEX('SECTOR OVERVIEW'!M$1:M$21,9),'DONNÉES BRUTES'!AD$3:AD$42,"Neutre")>=COUNTIFS('DONNÉES BRUTES'!C$3:C$42,INDEX('SECTOR OVERVIEW'!M$1:M$21,9),'DONNÉES BRUTES'!AD$3:AD$42,"Sous-pondérer"),"Neutre","Sous-pondérer")),"—"),"—") -> Neutre | K16: =IFERROR(IF(ISNUMBER(MATCH(INDEX('SECTOR OVERVIEW'!M$1:M$21,9),'DONNÉES BRUTES'!C$3:C$42,0)),IF(AVERAGEIF('DONNÉES BRUTES'!C$3:C$42,INDEX('SECTOR OVERVIEW'!M$1:M$21,9),'DONNÉES BRUTES'!AB$3:AB$42)>=65,"↑ Positif",IF(AVERAGEIF('DONNÉES BRUTES'!C$3:C$42,INDEX('SECTOR OVERVIEW'!M$1:M$21,9),'DONNÉES BRUTES'!AB$3:AB$42)>=50,"→ Neutre","↓ Négatif")),"—"),"—") -> ↓ Négatif
B17: =COUNTA('DONNÉES BRUTES'!A3:A42)&" sociétés — CAC 40" -> 40 sociétés — CAC 40 | C17: =COUNTA('DONNÉES BRUTES'!A3:A42) -> 40 | D17: =ROUND(AVERAGE('DONNÉES BRUTES'!AB3:AB42),0) -> 45 | E17: █████░░░░░ 50 | F17: =IFERROR(_xlfn.XLOOKUP(MAX('DONNÉES BRUTES'!AB$3:AB$42),'DONNÉES BRUTES'!AB$3:AB$42,'DONNÉES BRUTES'!B$3:B$42),"—") -> ASML Holding N.V. | G17: 19.8% | H17: 50 | I17: {=IFERROR(IF(ISNUMBER(MATCH(INDEX('SECTOR OVERVIEW'!M$1:M$21,10),'DONNÉES BRUTES'!C$3:C$42,0)),ROUND(MEDIAN(IF('DONNÉES BRUTES'!C$3:C$42=INDEX('SECTOR OVERVIEW'!M$1:M$21,10),IF(ISNUMBER('DONNÉES BRUTES'!U$3:U$42),'DONNÉES BRUTES'!U$3:U$42))),2),"—"),"—")} -> 2.3 | J17: =IFERROR(IF(ISNUMBER(MATCH(INDEX('SECTOR OVERVIEW'!M$1:M$21,10),'DONNÉES BRUTES'!C$3:C$42,0)),IF(COUNTIFS('DONNÉES BRUTES'!C$3:C$42,INDEX('SECTOR OVERVIEW'!M$1:M$21,10),'DONNÉES BRUTES'!AD$3:AD$42,"Surpondérer")>0,"Surpondérer",IF(COUNTIFS('DONNÉES BRUTES'!C$3:C$42,INDEX('SECTOR OVERVIEW'!M$1:M$21,10),'DONNÉES BRUTES'!AD$3:AD$42,"Neutre")>=COUNTIFS('DONNÉES BRUTES'!C$3:C$42,INDEX('SECTOR OVERVIEW'!M$1:M$21,10),'DONNÉES BRUTES'!AD$3:AD$42,"Sous-pondérer"),"Neutre","Sous-pondérer")),"—"),"—") -> Neutre | K17: =IFERROR(IF(ISNUMBER(MATCH(INDEX('SECTOR OVERVIEW'!M$1:M$21,10),'DONNÉES BRUTES'!C$3:C$42,0)),IF(AVERAGEIF('DONNÉES BRUTES'!C$3:C$42,INDEX('SECTOR OVERVIEW'!M$1:M$21,10),'DONNÉES BRUTES'!AB$3:AB$42)>=65,"↑ Positif",IF(AVERAGEIF('DONNÉES BRUTES'!C$3:C$42,INDEX('SECTOR OVERVIEW'!M$1:M$21,10),'DONNÉES BRUTES'!AB$3:AB$42)>=50,"→ Neutre","↓ Négatif")),"—"),"—") -> ↓ Négatif
B18: =IFERROR(INDEX('SECTOR OVERVIEW'!M$1:M$20,10),"") -> Énergie | C18: =IFERROR(IF(ISNUMBER(MATCH(INDEX('SECTOR OVERVIEW'!M$1:M$20,10),'DONNÉES BRUTES'!C$3:C$42,0)),COUNTIF('DONNÉES BRUTES'!C$3:C$42,INDEX('SECTOR OVERVIEW'!M$1:M$20,10)),""),"") -> 3 | D18: =IFERROR(IF(ISNUMBER(MATCH(INDEX('SECTOR OVERVIEW'!M$1:M$20,10),'DONNÉES BRUTES'!C$3:C$42,0)),ROUND(AVERAGEIF('DONNÉES BRUTES'!C$3:C$42,INDEX('SECTOR OVERVIEW'!M$1:M$20,10),'DONNÉES BRUTES'!AB$3:AB$42),0),""),"") -> 42 | E18: ████░░░░░░ 36 | F18: =IFERROR(_xlfn.XLOOKUP(_xlfn.MAXIFS('DONNÉES BRUTES'!AB$3:AB$42,'DONNÉES BRUTES'!C$3:C$42,INDEX('SECTOR OVERVIEW'!M$1:M$20,10)),'DONNÉES BRUTES'!AB$3:AB$42,'DONNÉES BRUTES'!B$3:B$42),"—") -> Koninklijke Philips N.V. | G18: 19.6% | H18: 45 | I18: {=IFERROR(ROUND(MEDIAN(IF('DONNÉES BRUTES'!C$3:C$42=INDEX('SECTOR OVERVIEW'!M$1:M$20,10),IF(ISNUMBER('DONNÉES BRUTES'!U$3:U$42),'DONNÉES BRUTES'!U$3:U$42))),2),"—")} -> 2.3 | J18: =IFERROR(IF(ISNUMBER(MATCH(INDEX('SECTOR OVERVIEW'!M$1:M$20,10),'DONNÉES BRUTES'!C$3:C$42,0)),IF(COUNTIFS('DONNÉES BRUTES'!C$3:C$42,INDEX('SECTOR OVERVIEW'!M$1:M$20,10),'DONNÉES BRUTES'!AD$3:AD$42,"Surpondérer")>0,"Surpondérer",IF(COUNTIFS('DONNÉES BRUTES'!C$3:C$42,INDEX('SECTOR OVERVIEW'!M$1:M$20,10),'DONNÉES BRUTES'!AD$3:AD$42,"Neutre")>=COUNTIFS('DONNÉES BRUTES'!C$3:C$42,INDEX('SECTOR OVERVIEW'!M$1:M$20,10),'DONNÉES BRUTES'!AD$3:AD$42,"Sous-pondérer"),"Neutre","Sous-pondérer")),"—"),"—") -> Neutre | K18: =IFERROR(IF(AVERAGEIF('DONNÉES BRUTES'!C$3:C$42,INDEX('SECTOR OVERVIEW'!M$1:M$20,10),'DONNÉES BRUTES'!AB$3:AB$42)>=65,"↑ Positif",IF(AVERAGEIF('DONNÉES BRUTES'!C$3:C$42,INDEX('SECTOR OVERVIEW'!M$1:M$20,10),'DONNÉES BRUTES'!AB$3:AB$42)>=50,"→ Neutre","↓ Négatif")),"—") -> ↓ Négatif
B19: =IFERROR(INDEX('SECTOR OVERVIEW'!M$1:M$21,11),"") -> 0 | C19: =IFERROR(IF(ISNUMBER(MATCH(INDEX('SECTOR OVERVIEW'!M$1:M$21,11),'DONNÉES BRUTES'!C$3:C$42,0)),COUNTIF('DONNÉES BRUTES'!C$3:C$42,INDEX('SECTOR OVERVIEW'!M$1:M$21,11)),""),"") | D19: =IFERROR(IF(ISNUMBER(MATCH(INDEX('SECTOR OVERVIEW'!M$1:M$21,11),'DONNÉES BRUTES'!C$3:C$42,0)),ROUND(AVERAGEIF('DONNÉES BRUTES'!C$3:C$42,INDEX('SECTOR OVERVIEW'!M$1:M$21,11),'DONNÉES BRUTES'!AB$3:AB$42),0),""),"") | E19: =IFERROR(IF(ISNUMBER(MATCH(INDEX('SECTOR OVERVIEW'!M$1:M$21,11),'DONNÉES BRUTES'!C$3:C$42,0)),REPT("█",ROUND(AVERAGEIF('DONNÉES BRUTES'!C$3:C$42,INDEX('SECTOR OVERVIEW'!M$1:M$21,11),'DONNÉES BRUTES'!AB$3:AB$42)/10,0))&REPT("░",10-ROUND(AVERAGEIF('DONNÉES BRUTES'!C$3:C$42,INDEX('SECTOR OVERVIEW'!M$1:M$21,11),'DONNÉES BRUTES'!AB$3:AB$42)/10,0))&" "&ROUND(AVERAGEIF('DONNÉES BRUTES'!C$3:C$42,INDEX('SECTOR OVERVIEW'!M$1:M$21,11),'DONNÉES BRUTES'!AB$3:AB$42),0),""),"") | F19: =IFERROR(IF(ISNUMBER(MATCH(INDEX('SECTOR OVERVIEW'!M$1:M$21,11),'DONNÉES BRUTES'!C$3:C$42,0)),_xlfn.XLOOKUP(_xlfn.MAXIFS('DONNÉES BRUTES'!AB$3:AB$42,'DONNÉES BRUTES'!C$3:C$42,INDEX('SECTOR OVERVIEW'!M$1:M$21,11)),'DONNÉES BRUTES'!AB$3:AB$42,'DONNÉES BRUTES'!B$3:B$42),"—"),"—") -> — | G19: 20.0% | H19: 49 | I19: {=IFERROR(IF(ISNUMBER(MATCH(INDEX('SECTOR OVERVIEW'!M$1:M$21,11),'DONNÉES BRUTES'!C$3:C$42,0)),ROUND(MEDIAN(IF('DONNÉES BRUTES'!C$3:C$42=INDEX('SECTOR OVERVIEW'!M$1:M$21,11),IF(ISNUMBER('DONNÉES BRUTES'!U$3:U$42),'DONNÉES BRUTES'!U$3:U$42))),2),"—"),"—")} -> — | J19: =IFERROR(IF(ISNUMBER(MATCH(INDEX('SECTOR OVERVIEW'!M$1:M$21,11),'DONNÉES BRUTES'!C$3:C$42,0)),IF(COUNTIFS('DONNÉES BRUTES'!C$3:C$42,INDEX('SECTOR OVERVIEW'!M$1:M$21,11),'DONNÉES BRUTES'!AD$3:AD$42,"Surpondérer")>0,"Surpondérer",IF(COUNTIFS('DONNÉES BRUTES'!C$3:C$42,INDEX('SECTOR OVERVIEW'!M$1:M$21,11),'DONNÉES BRUTES'!AD$3:AD$42,"Neutre")>=COUNTIFS('DONNÉES BRUTES'!C$3:C$42,INDEX('SECTOR OVERVIEW'!M$1:M$21,11),'DONNÉES BRUTES'!AD$3:AD$42,"Sous-pondérer"),"Neutre","Sous-pondérer")),"—"),"—") -> — | K19: =IFERROR(IF(ISNUMBER(MATCH(INDEX('SECTOR OVERVIEW'!M$1:M$21,11),'DONNÉES BRUTES'!C$3:C$42,0)),IF(AVERAGEIF('DONNÉES BRUTES'!C$3:C$42,INDEX('SECTOR OVERVIEW'!M$1:M$21,11),'DONNÉES BRUTES'!AB$3:AB$42)>=65,"↑ Positif",IF(AVERAGEIF('DONNÉES BRUTES'!C$3:C$42,INDEX('SECTOR OVERVIEW'!M$1:M$21,11),'DONNÉES BRUTES'!AB$3:AB$42)>=50,"→ Neutre","↓ Négatif")),"—"),"—") -> —

Sheet TECHNOLOGY
B1: ="FinSight IA · Technology · CAC 40 · "&COUNTIF('DONNÉES BRUTES'!C$3:C$42,"Technologie")&" sociétés · 12/04/2026" -> FinSight IA · Technology · CAC 40 · 4 sociétés · 12/04/2026
B2: Zoom sectoriel · Ratios clés · Score FinSight · Usage confidentiel
C5: 4 | E5: 56/100 | H5: {=IFERROR(INDEX('DONNÉES BRUTES'!B$3:B$42,MATCH(LARGE(IF('DONNÉES BRUTES'!C$3:C$42="Technologie",'DONNÉES BRUTES'!AB$3:AB$42+(ROW('DONNÉES BRUTES'!A$3:A$42)-ROW('DONNÉES BRUTES'!A$3))/1000,0),1),IF('DONNÉES BRUTES'!C$3:C$42="Technologie",'DONNÉES BRUTES'!AB$3:AB$42+(ROW('DONNÉES BRUTES'!A$3:A$42)-ROW('DONNÉES BRUTES'!A$3))/1000,0),0)),"—")} -> ASML Holding N.V. | L5: 0.227 | N5: {=IFERROR(ROUND(MEDIAN(IF('DONNÉES BRUTES'!C$3:C$42="Technologie",IF(ISNUMBER('DONNÉES BRUTES'!Y$3:Y$42),'DONNÉES BRUTES'!Y$3:Y$42))),0),"—")} -> 55 | P5: Surpondérer
C6: Sociétés | E6: Score moyen | H6: Meilleure société | L6: Mg. EBITDA Méd. | N6: Score Growth Méd. | P6: Signal
B8: ="ANALYSE DÉTAILLÉE · "&UPPER("Technologie")&" · "&COUNTIF('DONNÉES BRUTES'!C$3:C$42,"Technologie")&" sociétés · Triée par Score Global" -> ANALYSE DÉTAILLÉE · TECHNOLOGIE · 4 sociétés · Triée par Score Global
B10: # | C10: Ticker | D10: Société | E10: Score | F10: Gr. | G10: Qual. | H10: Mom. | I10: Mg. Brute | J10: Mg. EBITDA | K10: Mg. Nette | L10: Croiss. Rev. | M10: ROE | N10: Curr. R. | O10: ND/EBITDA | P10: Altman Z | Q10: Signal
B11: 1 | C11: {=IFERROR(IF(1>COUNTIF('DONNÉES BRUTES'!C$3:C$42,"Technologie"),"",INDEX('DONNÉES BRUTES'!A$3:A$42,MATCH(LARGE(IF('DONNÉES BRUTES'!C$3:C$42="Technologie",'DONNÉES BRUTES'!AB$3:AB$42+(ROW('DONNÉES BRUTES'!A$3:A$42)-ROW('DONNÉES BRUTES'!A$3))/1000,0),1),IF('DONNÉES BRUTES'!C$3:C$42="Technologie",'DONNÉES BRUTES'!AB$3:AB$42+(ROW('DONNÉES BRUTES'!A$3:A$42)-ROW('DONNÉES BRUTES'!A$3))/1000,0),0))),"—")} -> ASML.AS | D11: {=IFERROR(IF(1>COUNTIF('DONNÉES BRUTES'!C$3:C$42,"Technologie"),"",INDEX('DONNÉES BRUTES'!B$3:B$42,MATCH(LARGE(IF('DONNÉES BRUTES'!C$3:C$42="Technologie",'DONNÉES BRUTES'!AB$3:AB$42+(ROW('DONNÉES BRUTES'!A$3:A$42)-ROW('DONNÉES BRUTES'!A$3))/1000,0),1),IF('DONNÉES BRUTES'!C$3:C$42="Technologie",'DONNÉES BRUTES'!AB$3:AB$42+(ROW('DONNÉES BRUTES'!A$3:A$42)-ROW('DONNÉES BRUTES'!A$3))/1000,0),0))),"—")} -> ASML Holding N.V. | E11: {=IFERROR(IF(1>COUNTIF('DONNÉES BRUTES'!C$3:C$42,"Technologie"),"",INT(LARGE(IF('DONNÉES BRUTES'!C$3:C$42="Technologie",'DONNÉES BRUTES'!AB$3:AB$42+(ROW('DONNÉES BRUTES'!A$3:A$42)-ROW('DONNÉES BRUTES'!A$3))/1000,0),1))&"/100"),"—")} -> 75/100 | F11: {=IFERROR(IF(1>COUNTIF('DONNÉES BRUTES'!C$3:C$42,"Technologie"),"",INDEX('DONNÉES BRUTES'!Y$3:Y$42,MATCH(LARGE(IF('DONNÉES BRUTES'!C$3:C$42="Technologie",'DONNÉES BRUTES'!AB$3:AB$42+(ROW('DONNÉES BRUTES'!A$3:A$42)-ROW('DONNÉES BRUTES'!A$3))/1000,0),1),IF('DONNÉES BRUTES'!C$3:C$42="Technologie",'DONNÉES BRUTES'!AB$3:AB$42+(ROW('DONNÉES BRUTES'!A$3:A$42)-ROW('DONNÉES BRUTES'!A$3))/1000,0),0))),"—")} -> 92 | G11: {=IFERROR(IF(1>COUNTIF('DONNÉES BRUTES'!C$3:C$42,"Technologie"),"",INDEX('DONNÉES BRUTES'!Z$3:Z$42,MATCH(LARGE(IF('DONNÉES BRUTES'!C$3:C$42="Technologie",'DONNÉES BRUTES'!AB$3:AB$42+(ROW('DONNÉES BRUTES'!A$3:A$42)-ROW('DONNÉES BRUTES'!A$3))/1000,0),1),IF('DONNÉES BRUTES'!C$3:C$42="Technologie",'DONNÉES BRUTES'!AB$3:AB$42+(ROW('DONNÉES BRUTES'!A$3:A$42)-ROW('DONNÉES BRUTES'!A$3))/1000,0),0))),"—")} -> 86 | H11: {=IFERROR(IF(1>COUNTIF('DONNÉES BRUTES'!C$3:C$42,"Technologie"),"",INDEX('DONNÉES BRUTES'!AA$3:AA$42,MATCH(LARGE(IF('DONNÉES BRUTES'!C$3:C$42="Technologie",'DONNÉES BRUTES'!AB$3:AB$42+(ROW('DONNÉES BRUTES'!A$3:A$42)-ROW('DONNÉES BRUTES'!A$3))/1000,0),1),IF('DONNÉES BRUTES'!C$3:C$42="Technologie",'DONNÉES BRUTES'!AB$3:AB$42+(ROW('DONNÉES BRUTES'!A$3:A$42)-ROW('DONNÉES BRUTES'!A$3))/1000,0),0))),"—")} -> 98 | I11: {=IFERROR(IF(1>COUNTIF('DONNÉES BRUTES'!C$3:C$42,"Technologie"),"",INDEX('DONNÉES BRUTES'!M$3:M$42,MATCH(LARGE(IF('DONNÉES BRUTES'!C$3:C$42="Technologie",'DONNÉES BRUTES'!AB$3:AB$42+(ROW('DONNÉES BRUTES'!A$3:A$42)-ROW('DONNÉES BRUTES'!A$3))/1000,0),1),IF('DONNÉES BRUTES'!C$3:C$42="Technologie",'DONNÉES BRUTES'!AB$3:AB$42+(ROW('DONNÉES BRUTES'!A$3:A$42)-ROW('DONNÉES BRUTES'!A$3))/1000,0),0))),"—")} -> 52.8% | J11: {=IFERROR(IF(1>COUNTIF('DONNÉES BRUTES'!C$3:C$42,"Technologie"),"",INDEX('DONNÉES BRUTES'!N$3:N$42,MATCH(LARGE(IF('DONNÉES BRUTES'!C$3:C$42="Technologie",'DONNÉES BRUTES'!AB$3:AB$42+(ROW('DONNÉES BRUTES'!A$3:A$42)-ROW('DONNÉES BRUTES'!A$3))/1000,0),1),IF('DONNÉES BRUTES'!C$3:C$42="Technologie",'DONNÉES BRUTES'!AB$3:AB$42+(ROW('DONNÉES BRUTES'!A$3:A$42)-ROW('DONNÉES BRUTES'!A$3))/1000,0),0))),"—")} -> 38.4% | K11: {=IFERROR(IF(1>COUNTIF('DONNÉES BRUTES'!C$3:C$42,"Technologie"),"",INDEX('DONNÉES BRUTES'!O$3:O$42,MATCH(LARGE(IF('DONNÉES BRUTES'!C$3:C$42="Technologie",'DONNÉES BRUTES'!AB$3:AB$42+(ROW('DONNÉES BRUTES'!A$3:A$42)-ROW('DONNÉES BRUTES'!A$3))/1000,0),1),IF('DONNÉES BRUTES'!C$3:C$42="Technologie",'DONNÉES BRUTES'!AB$3:AB$42+(ROW('DONNÉES BRUTES'!A$3:A$42)-ROW('DONNÉES BRUTES'!A$3))/1000,0),0))),"—")} -> 29.4% | L11: {=IFERROR(IF(1>COUNTIF('DONNÉES BRUTES'!C$3:C$42,"Technologie"),"",INDEX('DONNÉES BRUTES'!P$3:P$42,MATCH(LARGE(IF('DONNÉES BRUTES'!C$3:C$42="Technologie",'DONNÉES BRUTES'!AB$3:AB$42+(ROW('DONNÉES BRUTES'!A$3:A$42)-ROW('DONNÉES BRUTES'!A$3))/1000,0),1),IF('DONNÉES BRUTES'!C$3:C$42="Technologie",'DONNÉES BRUTES'!AB$3:AB$42+(ROW('DONNÉES BRUTES'!A$3:A$42)-ROW('DONNÉES BRUTES'!A$3))/1000,0),0))),"—")} -> +15.6% | M11: {=IFERROR(IF(1>COUNTIF('DONNÉES BRUTES'!C$3:C$42,"Technologie"),"",INDEX('DONNÉES BRUTES'!Q$3:Q$42,MATCH(LARGE(IF('DONNÉES BRUTES'!C$3:C$42="Technologie",'DONNÉES BRUTES'!AB$3:AB$42+(ROW('DONNÉES BRUTES'!A$3:A$42)-ROW('DONNÉES BRUTES'!A$3))/1000,0),1),IF('DONNÉES BRUTES'!C$3:C$42="Technologie",'DONNÉES BRUTES'!AB$3:AB$42+(ROW('DONNÉES BRUTES'!A$3:A$42)-ROW('DONNÉES BRUTES'!A$3))/1000,0),0))),"—")} -> +49.0% | N11: {=IFERROR(IF(1>COUNTIF('DONNÉES BRUTES'!C$3:C$42,"Technologie"),"",INDEX('DONNÉES BRUTES'!S$3:S$42,MATCH(LARGE(IF('DONNÉES BRUTES'!C$3:C$42="Technologie",'DONNÉES BRUTES'!AB$3:AB$42+(ROW('DONNÉES BRUTES'!A$3:A$42)-ROW('DONNÉES BRUTES'!A$3))/1000,0),1),IF('DONNÉES BRUTES'!C$3:C$42="Technologie",'DONNÉES BRUTES'!AB$3:AB$42+(ROW('DONNÉES BRUTES'!A$3:A$42)-ROW('DONNÉES BRUTES'!A$3))/1000,0),0))),"—")} -> 1.26 | O11: {=IFERROR(IF(1>COUNTIF('DONNÉES BRUTES'!C$3:C$42,"Technologie"),"",INDEX('DONNÉES BRUTES'!T$3:T$42,MATCH(LARGE(IF('DONNÉES BRUTES'!C$3:C$42="Technologie",'DONNÉES BRUTES'!AB$3:AB$42+(ROW('DONNÉES BRUTES'!A$3:A$42)-ROW('DONNÉES BRUTES'!A$3))/1000,0),1),IF('DONNÉES BRUTES'!C$3:C$42="Technologie",'DONNÉES BRUTES'!AB$3:AB$42+(ROW('DONNÉES BRUTES'!A$3:A$42)-ROW('DONNÉES BRUTES'!A$3))/1000,0),0))),"—")} -> -0.7x | P11: {=IFERROR(IF(1>COUNTIF('DONNÉES BRUTES'!C$3:C$42,"Technologie"),"",INDEX('DONNÉES BRUTES'!U$3:U$42,MATCH(LARGE(IF('DONNÉES BRUTES'!C$3:C$42="Technologie",'DONNÉES BRUTES'!AB$3:AB$42+(ROW('DONNÉES BRUTES'!A$3:A$42)-ROW('DONNÉES BRUTES'!A$3))/1000,0),1),IF('DONNÉES BRUTES'!C$3:C$42="Technologie",'DONNÉES BRUTES'!AB$3:AB$42+(ROW('DONNÉES BRUTES'!A$3:A$42)-ROW('DONNÉES BRUTES'!A$3))/1000,0),0))),"—")} -> 4.15 | Q11: {=IFERROR(IF(1>COUNTIF('DONNÉES BRUTES'!C$3:C$42,"Technologie"),"",INDEX('DONNÉES BRUTES'!AD$3:AD$42,MATCH(LARGE(IF('DONNÉES BRUTES'!C$3:C$42="Technologie",'DONNÉES BRUTES'!AB$3:AB$42+(ROW('DONNÉES BRUTES'!A$3:A$42)-ROW('DONNÉES BRUTES'!A$3))/1000,0),1),IF('DONNÉES BRUTES'!C$3:C$42="Technologie",'DONNÉES BRUTES'!AB$3:AB$42+(ROW('DONNÉES BRUTES'!A$3:A$42)-ROW('DONNÉES BRUTES'!A$3))/1000,0),0))),"—")} -> Surpondérer
B12: 2 | C12: {=IFERROR(IF(2>COUNTIF('DONNÉES BRUTES'!C$3:C$42,"Technologie"),"",INDEX('DONNÉES BRUTES'!A$3:A$42,MATCH(LARGE(IF('DONNÉES BRUTES'!C$3:C$42="Technologie",'DONNÉES BRUTES'!AB$3:AB$42+(ROW('DONNÉES BRUTES'!A$3:A$42)-ROW('DONNÉES BRUTES'!A$3))/1000,0),2),IF('DONNÉES BRUTES'!C$3:C$42="Technologie",'DONNÉES BRUTES'!AB$3:AB$42+(ROW('DONNÉES BRUTES'!A$3:A$42)-ROW('DONNÉES BRUTES'!A$3))/1000,0),0))),"—")} -> SAP.DE | D12: {=IFERROR(IF(2>COUNTIF('DONNÉES BRUTES'!C$3:C$42,"Technologie"),"",INDEX('DONNÉES BRUTES'!B$3:B$42,MATCH(LARGE(IF('DONNÉES BRUTES'!C$3:C$42="Technologie",'DONNÉES BRUTES'!AB$3:AB$42+(ROW('DONNÉES BRUTES'!A$3:A$42)-ROW('DONNÉES BRUTES'!A$3))/1000,0),2),IF('DONNÉES BRUTES'!C$3:C$42="Technologie",'DONNÉES BRUTES'!AB$3:AB$42+(ROW('DONNÉES BRUTES'!A$3:A$42)-ROW('DONNÉES BRUTES'!A$3))/1000,0),0))),"—")} -> SAP SE | E12: {=IFERROR(IF(2>COUNTIF('DONNÉES BRUTES'!C$3:C$42,"Technologie"),"",INT(LARGE(IF('DONNÉES BRUTES'!C$3:C$42="Technologie",'DONNÉES BRUTES'!AB$3:AB$42+(ROW('DONNÉES BRUTES'!A$3:A$42)-ROW('DONNÉES BRUTES'!A$3))/1000,0),2))&"/100"),"—")} -> 62/100 | F12: {=IFERROR(IF(2>COUNTIF('DONNÉES BRUTES'!C$3:C$42,"Technologie"),"",INDEX('DONNÉES BRUTES'!Y$3:Y$42,MATCH(LARGE(IF('DONNÉES BRUTES'!C$3:C$42="Technologie",'DONNÉES BRUTES'!AB$3:AB$42+(ROW('DONNÉES BRUTES'!A$3:A$42)-ROW('DONNÉES BRUTES'!A$3))/1000,0),2),IF('DONNÉES BRUTES'!C$3:C$42="Technologie",'DONNÉES BRUTES'!AB$3:AB$42+(ROW('DONNÉES BRUTES'!A$3:A$42)-ROW('DONNÉES BRUTES'!A$3))/1000,0),0))),"—")} -> 78 | G12: {=IFERROR(IF(2>COUNTIF('DONNÉES BRUTES'!C$3:C$42,"Technologie"),"",INDEX('DONNÉES BRUTES'!Z$3:Z$42,MATCH(LARGE(IF('DONNÉES BRUTES'!C$3:C$42="Technologie",'DONNÉES BRUTES'!AB$3:AB$42+(ROW('DONNÉES BRUTES'!A$3:A$42)-ROW('DONNÉES BRUTES'!A$3))/1000,0),2),IF('DONNÉES BRUTES'!C$3:C$42="Technologie",'DONNÉES BRUTES'!AB$3:AB$42+(ROW('DONNÉES BRUTES'!A$3:A$42)-ROW('DONNÉES BRUTES'!A$3))/1000,0),0))),"—")} -> 80 | H12: {=IFERROR(IF(2>COUNTIF('DONNÉES BRUTES'!C$3:C$42,"Technologie"),"",INDEX('DONNÉES BRUTES'!AA$3:AA$42,MATCH(LARGE(IF('DONNÉES BRUTES'!C$3:C$42="Technologie",'DONNÉES BRUTES'!AB$3:AB$42+(ROW('DONNÉES BRUTES'!A$3:A$42)-ROW('DONNÉES BRUTES'!A$3))/1000,0),2),IF('DONNÉES BRUTES'!C$3:C$42="Technologie",'DONNÉES BRUTES'!AB$3:AB$42+(ROW('DONNÉES BRUTES'!A$3:A$42)-ROW('DONNÉES BRUTES'!A$3))/1000,0),0))),"—")} -> 0 | I12: {=IFERROR(IF(2>COUNTIF('DONNÉES BRUTES'!C$3:C$42,"Technologie"),"",INDEX('DONNÉES BRUTES'!M$3:M$42,MATCH(LARGE(IF('DONNÉES BRUTES'!C$3:C$42="Technologie",'DONNÉES BRUTES'!AB$3:AB$42+(ROW('DONNÉES BRUTES'!A$3:A$42)-ROW('DONNÉES BRUTES'!A$3))/1000,0),2),IF('DONNÉES BRUTES'!C$3:C$42="Technologie",'DONNÉES BRUTES'!AB$3:AB$42+(ROW('DONNÉES BRUTES'!A$3:A$42)-ROW('DONNÉES BRUTES'!A$3))/1000,0),0))),"—")} -> 72.9% | J12: {=IFERROR(IF(2>COUNTIF('DONNÉES BRUTES'!C$3:C$42,"Technologie"),"",INDEX('DONNÉES BRUTES'!N$3:N$42,MATCH(LARGE(IF('DONNÉES BRUTES'!C$3:C$42="Technologie",'DONNÉES BRUTES'!AB$3:AB$42+(ROW('DONNÉES BRUTES'!A$3:A$42)-ROW('DONNÉES BRUTES'!A$3))/1000,0),2),IF('DONNÉES BRUTES'!C$3:C$42="Technologie",'DONNÉES BRUTES'!AB$3:AB$42+(ROW('DONNÉES BRUTES'!A$3:A$42)-ROW('DONNÉES BRUTES'!A$3))/1000,0),0))),"—")} -> 32.8% | K12: {=IFERROR(IF(2>COUNTIF('DONNÉES BRUTES'!C$3:C$42,"Technologie"),"",INDEX('DONNÉES BRUTES'!O$3:O$42,MATCH(LARGE(IF('DONNÉES BRUTES'!C$3:C$42="Technologie",'DONNÉES BRUTES'!AB$3:AB$42+(ROW('DONNÉES BRUTES'!A$3:A$42)-ROW('DONNÉES BRUTES'!A$3))/1000,0),2),IF('DONNÉES BRUTES'!C$3:C$42="Technologie",'DONNÉES BRUTES'!AB$3:AB$42+(ROW('DONNÉES BRUTES'!A$3:A$42)-ROW('DONNÉES BRUTES'!A$3))/1000,0),0))),"—")} -> 19.5% | L12: {=IFERROR(IF(2>COUNTIF('DONNÉES BRUTES'!C$3:C$42,"Technologie"),"",INDEX('DONNÉES BRUTES'!P$3:P$42,MATCH(LARGE(IF('DONNÉES BRUTES'!C$3:C$42="Technologie",'DONNÉES BRUTES'!AB$3:AB$42+(ROW('DONNÉES BRUTES'!A$3:A$42)-ROW('DONNÉES BRUTES'!A$3))/1000,0),2),IF('DONNÉES BRUTES'!C$3:C$42="Technologie",'DONNÉES BRUTES'!AB$3:AB$42+(ROW('DONNÉES BRUTES'!A$3:A$42)-ROW('DONNÉES BRUTES'!A$3))/1000,0),0))),"—")} -> +7.7% | M12: {=IFERROR(IF(2>COUNTIF('DONNÉES BRUTES'!C$3:C$42,"Technologie"),"",INDEX('DONNÉES BRUTES'!Q$3:Q$42,MATCH(LARGE(IF('DONNÉES BRUTES'!C$3:C$42="Technologie",'DONNÉES BRUTES'!AB$3:AB$42+(ROW('DONNÉES BRUTES'!A$3:A$42)-ROW('DONNÉES BRUTES'!A$3))/1000,0),2),IF('DONNÉES BRUTES'!C$3:C$42="Technologie",'DONNÉES BRUTES'!AB$3:AB$42+(ROW('DONNÉES BRUTES'!A$3:A$42)-ROW('DONNÉES BRUTES'!A$3))/1000,0),0))),"—")} -> +16.1% | N12: {=IFERROR(IF(2>COUNTIF('DONNÉES BRUTES'!C$3:C$42,"Technologie"),"",INDEX('DONNÉES BRUTES'!S$3:S$42,MATCH(LARGE(IF('DONNÉES BRUTES'!C$3:C$42="Technologie",'DONNÉES BRUTES'!AB$3:AB$42+(ROW('DONNÉES BRUTES'!A$3:A$42)-ROW('DONNÉES BRUTES'!A$3))/1000,0),2),IF('DONNÉES BRUTES'!C$3:C$42="Technologie",'DONNÉES BRUTES'!AB$3:AB$42+(ROW('DONNÉES BRUTES'!A$3:A$42)-ROW('DONNÉES BRUTES'!A$3))/1000,0),0))),"—")} -> 1.16 | O12: {=IFERROR(IF(2>COUNTIF('DONNÉES BRUTES'!C$3:C$42,"Technologie"),"",INDEX('DONNÉES BRUTES'!T$3:T$42,MATCH(LARGE(IF('DONNÉES BRUTES'!C$3:C$42="Technologie",'DONNÉES BRUTES'!AB$3:AB$42+(ROW('DONNÉES BRUTES'!A$3:A$42)-ROW('DONNÉES BRUTES'!A$3))/1000,0),2),IF('DONNÉES BRUTES'!C$3:C$42="Technologie",'DONNÉES BRUTES'!AB$3:AB$42+(ROW('DONNÉES BRUTES'!A$3:A$42)-ROW('DONNÉES BRUTES'!A$3))/1000,0),0))),"—")} -> -0.2x | P12: {=IFERROR(IF(2>COUNTIF('DONNÉES BRUTES'!C$3:C$42,"Technologie"),"",INDEX('DONNÉES BRUTES'!U$3:U$42,MATCH(LARGE(IF('DONNÉES BRUTES'!C$3:C$42="Technologie",'DONNÉES BRUTES'!AB$3:AB$42+(ROW('DONNÉES BRUTES'!A$3:A$42)-ROW('DONNÉES BRUTES'!A$3))/1000,0),2),IF('DONNÉES BRUTES'!C$3:C$42="Technologie",'DONNÉES BRUTES'!AB$3:AB$42+(ROW('DONNÉES BRUTES'!A$3:A$42)-ROW('DONNÉES BRUTES'!A$3))/1000,0),0))),"—")} -> 5.34 | Q12: {=IFERROR(IF(2>COUNTIF('DONNÉES BRUTES'!C$3:C$42,"Technologie"),"",INDEX('DONNÉES BRUTES'!AD$3:AD$42,MATCH(LARGE(IF('DONNÉES BRUTES'!C$3:C$42="Technologie",'DONNÉES BRUTES'!AB$3:AB$42+(ROW('DONNÉES BRUTES'!A$3:A$42)-ROW('DONNÉES BRUTES'!A$3))/1000,0),2),IF('DONNÉES BRUTES'!C$3:C$42="Technologie",'DONNÉES BRUTES'!AB$3:AB$42+(ROW('DONNÉES BRUTES'!A$3:A$42)-ROW('DONNÉES BRUTES'!A$3))/1000,0),0))),"—")} -> Surpondérer
B13: 3 | C13: {=IFERROR(IF(3>COUNTIF('DONNÉES BRUTES'!C$3:C$42,"Technologie"),"",INDEX('DONNÉES BRUTES'!A$3:A$42,MATCH(LARGE(IF('DONNÉES BRUTES'!C$3:C$42="Technologie",'DONNÉES BRUTES'!AB$3:AB$42+(ROW('DONNÉES BRUTES'!A$3:A$42)-ROW('DONNÉES BRUTES'!A$3))/1000,0),3),IF('DONNÉES BRUTES'!C$3:C$42="Technologie",'DONNÉES BRUTES'!AB$3:AB$42+(ROW('DONNÉES BRUTES'!A$3:A$42)-ROW('DONNÉES BRUTES'!A$3))/1000,0),0))),"—")} -> NOKIA.HE | D13: {=IFERROR(IF(3>COUNTIF('DONNÉES BRUTES'!C$3:C$42,"Technologie"),"",INDEX('DONNÉES BRUTES'!B$3:B$42,MATCH(LARGE(IF('DONNÉES BRUTES'!C$3:C$42="Technologie",'DONNÉES BRUTES'!AB$3:AB$42+(ROW('DONNÉES BRUTES'!A$3:A$42)-ROW('DONNÉES BRUTES'!A$3))/1000,0),3),IF('DONNÉES BRUTES'!C$3:C$42="Technologie",'DONNÉES BRUTES'!AB$3:AB$42+(ROW('DONNÉES BRUTES'!A$3:A$42)-ROW('DONNÉES BRUTES'!A$3))/1000,0),0))),"—")} -> Nokia Oyj | E13: {=IFERROR(IF(3>COUNTIF('DONNÉES BRUTES'!C$3:C$42,"Technologie"),"",INT(LARGE(IF('DONNÉES BRUTES'!C$3:C$42="Technologie",'DONNÉES BRUTES'!AB$3:AB$42+(ROW('DONNÉES BRUTES'!A$3:A$42)-ROW('DONNÉES BRUTES'!A$3))/1000,0),3))&"/100"),"—")} -> 46/100 | F13: {=IFERROR(IF(3>COUNTIF('DONNÉES BRUTES'!C$3:C$42,"Technologie"),"",INDEX('DONNÉES BRUTES'!Y$3:Y$42,MATCH(LARGE(IF('DONNÉES BRUTES'!C$3:C$42="Technologie",'DONNÉES BRUTES'!AB$3:AB$42+(ROW('DONNÉES BRUTES'!A$3:A$42)-ROW('DONNÉES BRUTES'!A$3))/1000,0),3),IF('DONNÉES BRUTES'!C$3:C$42="Technologie",'DONNÉES BRUTES'!AB$3:AB$42+(ROW('DONNÉES BRUTES'!A$3:A$42)-ROW('DONNÉES BRUTES'!A$3))/1000,0),0))),"—")} -> 29 | G13: {=IFERROR(IF(3>COUNTIF('DONNÉES BRUTES'!C$3:C$42,"Technologie"),"",INDEX('DONNÉES BRUTES'!Z$3:Z$42,MATCH(LARGE(IF('DONNÉES BRUTES'!C$3:C$42="Technologie",'DONNÉES BRUTES'!AB$3:AB$42+(ROW('DONNÉES BRUTES'!A$3:A$42)-ROW('DONNÉES BRUTES'!A$3))/1000,0),3),IF('DONNÉES BRUTES'!C$3:C$42="Technologie",'DONNÉES BRUTES'!AB$3:AB$42+(ROW('DONNÉES BRUTES'!A$3:A$42)-ROW('DONNÉES BRUTES'!A$3))/1000,0),0))),"—")} -> 57 | H13: {=IFERROR(IF(3>COUNTIF('DONNÉES BRUTES'!C$3:C$42,"Technologie"),"",INDEX('DONNÉES BRUTES'!AA$3:AA$42,MATCH(LARGE(IF('DONNÉES BRUTES'!C$3:C$42="Technologie",'DONNÉES BRUTES'!AB$3:AB$42+(ROW('DONNÉES BRUTES'!A$3:A$42)-ROW('DONNÉES BRUTES'!A$3))/1000,0),3),IF('DONNÉES BRUTES'!C$3:C$42="Technologie",'DONNÉES BRUTES'!AB$3:AB$42+(ROW('DONNÉES BRUTES'!A$3:A$42)-ROW('DONNÉES BRUTES'!A$3))/1000,0),0))),"—")} -> 94 | I13: {=IFERROR(IF(3>COUNTIF('DONNÉES BRUTES'!C$3:C$42,"Technologie"),"",INDEX('DONNÉES BRUTES'!M$3:M$42,MATCH(LARGE(IF('DONNÉES BRUTES'!C$3:C$42="Technologie",'DONNÉES BRUTES'!AB$3:AB$42+(ROW('DONNÉES BRUTES'!A$3:A$42)-ROW('DONNÉES BRUTES'!A$3))/1000,0),3),IF('DONNÉES BRUTES'!C$3:C$42="Technologie",'DONNÉES BRUTES'!AB$3:AB$42+(ROW('DONNÉES BRUTES'!A$3:A$42)-ROW('DONNÉES BRUTES'!A$3))/1000,0),0))),"—")} -> 43.5% | J13: {=IFERROR(IF(3>COUNTIF('DONNÉES BRUTES'!C$3:C$42,"Technologie"),"",INDEX('DONNÉES BRUTES'!N$3:N$42,MATCH(LARGE(IF('DONNÉES BRUTES'!C$3:C$42="Technologie",'DONNÉES BRUTES'!AB$3:AB$42+(ROW('DONNÉES BRUTES'!A$3:A$42)-ROW('DONNÉES BRUTES'!A$3))/1000,0),3),IF('DONNÉES BRUTES'!C$3:C$42="Technologie",'DONNÉES BRUTES'!AB$3:AB$42+(ROW('DONNÉES BRUTES'!A$3:A$42)-ROW('DONNÉES BRUTES'!A$3))/1000,0),0))),"—")} -> 11.3% | K13: {=IFERROR(IF(3>COUNTIF('DONNÉES BRUTES'!C$3:C$42,"Technologie"),"",INDEX('DONNÉES BRUTES'!O$3:O$42,MATCH(LARGE(IF('DONNÉES BRUTES'!C$3:C$42="Technologie",'DONNÉES BRUTES'!AB$3:AB$42+(ROW('DONNÉES BRUTES'!A$3:A$42)-ROW('DONNÉES BRUTES'!A$3))/1000,0),3),IF('DONNÉES BRUTES'!C$3:C$42="Technologie",'DONNÉES BRUTES'!AB$3:AB$42+(ROW('DONNÉES BRUTES'!A$3:A$42)-ROW('DONNÉES BRUTES'!A$3))/1000,0),0))),"—")} -> 3.3% | L13: {=IFERROR(IF(3>COUNTIF('DONNÉES BRUTES'!C$3:C$42,"Technologie"),"",INDEX('DONNÉES BRUTES'!P$3:P$42,MATCH(LARGE(IF('DONNÉES BRUTES'!C$3:C$42="Technologie",'DONNÉES BRUTES'!AB$3:AB$42+(ROW('DONNÉES BRUTES'!A$3:A$42)-ROW('DONNÉES BRUTES'!A$3))/1000,0),3),IF('DONNÉES BRUTES'!C$3:C$42="Technologie",'DONNÉES BRUTES'!AB$3:AB$42+(ROW('DONNÉES BRUTES'!A$3:A$42)-ROW('DONNÉES BRUTES'!A$3))/1000,0),0))),"—")} -> +3.5% | M13: {=IFERROR(IF(3>COUNTIF('DONNÉES BRUTES'!C$3:C$42,"Technologie"),"",INDEX('DONNÉES BRUTES'!Q$3:Q$42,MATCH(LARGE(IF('DONNÉES BRUTES'!C$3:C$42="Technologie",'DONNÉES BRUTES'!AB$3:AB$42+(ROW('DONNÉES BRUTES'!A$3:A$42)-ROW('DONNÉES BRUTES'!A$3))/1000,0),3),IF('DONNÉES BRUTES'!C$3:C$42="Technologie",'DONNÉES BRUTES'!AB$3:AB$42+(ROW('DONNÉES BRUTES'!A$3:A$42)-ROW('DONNÉES BRUTES'!A$3))/1000,0),0))),"—")} -> +3.1% | N13: {=IFERROR(IF(3>COUNTIF('DONNÉES BRUTES'!C$3:C$42,"Technologie"),"",INDEX('DONNÉES BRUTES'!S$3:S$42,MATCH(LARGE(IF('DONNÉES BRUTES'!C$3:C$42="Technologie",'DONNÉES BRUTES'!AB$3:AB$42+(ROW('DONNÉES BRUTES'!A$3:A$42)-ROW('DONNÉES BRUTES'!A$3))/1000,0),3),IF('DONNÉES BRUTES'!C$3:C$42="Technologie",'DONNÉES BRUTES'!AB$3:AB$42+(ROW('DONNÉES BRUTES'!A$3:A$42)-ROW('DONNÉES BRUTES'!A$3))/1000,0),0))),"—")} -> 1.58 | O13: {=IFERROR(IF(3>COUNTIF('DONNÉES BRUTES'!C$3:C$42,"Technologie"),"",INDEX('DONNÉES BRUTES'!T$3:T$42,MATCH(LARGE(IF('DONNÉES BRUTES'!C$3:C$42="Technologie",'DONNÉES BRUTES'!AB$3:AB$42+(ROW('DONNÉES BRUTES'!A$3:A$42)-ROW('DONNÉES BRUTES'!A$3))/1000,0),3),IF('DONNÉES BRUTES'!C$3:C$42="Technologie",'DONNÉES BRUTES'!AB$3:AB$42+(ROW('DONNÉES BRUTES'!A$3:A$42)-ROW('DONNÉES BRUTES'!A$3))/1000,0),0))),"—")} -> -0.9x | P13: {=IFERROR(IF(3>COUNTIF('DONNÉES BRUTES'!C$3:C$42,"Technologie"),"",INDEX('DONNÉES BRUTES'!U$3:U$42,MATCH(LARGE(IF('DONNÉES BRUTES'!C$3:C$42="Technologie",'DONNÉES BRUTES'!AB$3:AB$42+(ROW('DONNÉES BRUTES'!A$3:A$42)-ROW('DONNÉES BRUTES'!A$3))/1000,0),3),IF('DONNÉES BRUTES'!C$3:C$42="Technologie",'DONNÉES BRUTES'!AB$3:AB$42+(ROW('DONNÉES BRUTES'!A$3:A$42)-ROW('DONNÉES BRUTES'!A$3))/1000,0),0))),"—")} -> 2.7 | Q13: {=IFERROR(IF(3>COUNTIF('DONNÉES BRUTES'!C$3:C$42,"Technologie"),"",INDEX('DONNÉES BRUTES'!AD$3:AD$42,MATCH(LARGE(IF('DONNÉES BRUTES'!C$3:C$42="Technologie",'DONNÉES BRUTES'!AB$3:AB$42+(ROW('DONNÉES BRUTES'!A$3:A$42)-ROW('DONNÉES BRUTES'!A$3))/1000,0),3),IF('DONNÉES BRUTES'!C$3:C$42="Technologie",'DONNÉES BRUTES'!AB$3:AB$42+(ROW('DONNÉES BRUTES'!A$3:A$42)-ROW('DONNÉES BRUTES'!A$3))/1000,0),0))),"—")} -> Neutre
B14: 4 | C14: {=IFERROR(IF(4>COUNTIF('DONNÉES BRUTES'!C$3:C$42,"Technologie"),"",INDEX('DONNÉES BRUTES'!A$3:A$42,MATCH(LARGE(IF('DONNÉES BRUTES'!C$3:C$42="Technologie",'DONNÉES BRUTES'!AB$3:AB$42+(ROW('DONNÉES BRUTES'!A$3:A$42)-ROW('DONNÉES BRUTES'!A$3))/1000,0),4),IF('DONNÉES BRUTES'!C$3:C$42="Technologie",'DONNÉES BRUTES'!AB$3:AB$42+(ROW('DONNÉES BRUTES'!A$3:A$42)-ROW('DONNÉES BRUTES'!A$3))/1000,0),0))),"—")} -> IFX.DE | D14: {=IFERROR(IF(4>COUNTIF('DONNÉES BRUTES'!C$3:C$42,"Technologie"),"",INDEX('DONNÉES BRUTES'!B$3:B$42,MATCH(LARGE(IF('DONNÉES BRUTES'!C$3:C$42="Technologie",'DONNÉES BRUTES'!AB$3:AB$42+(ROW('DONNÉES BRUTES'!A$3:A$42)-ROW('DONNÉES BRUTES'!A$3))/1000,0),4),IF('DONNÉES BRUTES'!C$3:C$42="Technologie",'DONNÉES BRUTES'!AB$3:AB$42+(ROW('DONNÉES BRUTES'!A$3:A$42)-ROW('DONNÉES BRUTES'!A$3))/1000,0),0))),"—")} -> Infineon Technologies AG | E14: {=IFERROR(IF(4>COUNTIF('DONNÉES BRUTES'!C$3:C$42,"Technologie"),"",INT(LARGE(IF('DONNÉES BRUTES'!C$3:C$42="Technologie",'DONNÉES BRUTES'!AB$3:AB$42+(ROW('DONNÉES BRUTES'!A$3:A$42)-ROW('DONNÉES BRUTES'!A$3))/1000,0),4))&"/100"),"—")} -> 40/100 | F14: {=IFERROR(IF(4>COUNTIF('DONNÉES BRUTES'!C$3:C$42,"Technologie"),"",INDEX('DONNÉES BRUTES'!Y$3:Y$42,MATCH(LARGE(IF('DONNÉES BRUTES'!C$3:C$42="Technologie",'DONNÉES BRUTES'!AB$3:AB$42+(ROW('DONNÉES BRUTES'!A$3:A$42)-ROW('DONNÉES BRUTES'!A$3))/1000,0),4),IF('DONNÉES BRUTES'!C$3:C$42="Technologie",'DONNÉES BRUTES'!AB$3:AB$42+(ROW('DONNÉES BRUTES'!A$3:A$42)-ROW('DONNÉES BRUTES'!A$3))/1000,0),0))),"—")} -> 32 | G14: {=IFERROR(IF(4>COUNTIF('DONNÉES BRUTES'!C$3:C$42,"Technologie"),"",INDEX('DONNÉES BRUTES'!Z$3:Z$42,MATCH(LARGE(IF('DONNÉES BRUTES'!C$3:C$42="Technologie",'DONNÉES BRUTES'!AB$3:AB$42+(ROW('DONNÉES BRUTES'!A$3:A$42)-ROW('DONNÉES BRUTES'!A$3))/1000,0),4),IF('DONNÉES BRUTES'!C$3:C$42="Technologie",'DONNÉES BRUTES'!AB$3:AB$42+(ROW('DONNÉES BRUTES'!A$3:A$42)-ROW('DONNÉES BRUTES'!A$3))/1000,0),0))),"—")} -> 59 | H14: {=IFERROR(IF(4>COUNTIF('DONNÉES BRUTES'!C$3:C$42,"Technologie"),"",INDEX('DONNÉES BRUTES'!AA$3:AA$42,MATCH(LARGE(IF('DONNÉES BRUTES'!C$3:C$42="Technologie",'DONNÉES BRUTES'!AB$3:AB$42+(ROW('DONNÉES BRUTES'!A$3:A$42)-ROW('DONNÉES BRUTES'!A$3))/1000,0),4),IF('DONNÉES BRUTES'!C$3:C$42="Technologie",'DONNÉES BRUTES'!AB$3:AB$42+(ROW('DONNÉES BRUTES'!A$3:A$42)-ROW('DONNÉES BRUTES'!A$3))/1000,0),0))),"—")} -> 57 | I14: {=IFERROR(IF(4>COUNTIF('DONNÉES BRUTES'!C$3:C$42,"Technologie"),"",INDEX('DONNÉES BRUTES'!M$3:M$42,MATCH(LARGE(IF('DONNÉES BRUTES'!C$3:C$42="Technologie",'DONNÉES BRUTES'!AB$3:AB$42+(ROW('DONNÉES BRUTES'!A$3:A$42)-ROW('DONNÉES BRUTES'!A$3))/1000,0),4),IF('DONNÉES BRUTES'!C$3:C$42="Technologie",'DONNÉES BRUTES'!AB$3:AB$42+(ROW('DONNÉES BRUTES'!A$3:A$42)-ROW('DONNÉES BRUTES'!A$3))/1000,0),0))),"—")} -> 39.2% | J14: {=IFERROR(IF(4>COUNTIF('DONNÉES BRUTES'!C$3:C$42,"Technologie"),"",INDEX('DONNÉES BRUTES'!N$3:N$42,MATCH(LARGE(IF('DONNÉES BRUTES'!C$3:C$42="Technologie",'DONNÉES BRUTES'!AB$3:AB$42+(ROW('DONNÉES BRUTES'!A$3:A$42)-ROW('DONNÉES BRUTES'!A$3))/1000,0),4),IF('DONNÉES BRUTES'!C$3:C$42="Technologie",'DONNÉES BRUTES'!AB$3:AB$42+(ROW('DONNÉES BRUTES'!A$3:A$42)-ROW('DONNÉES BRUTES'!A$3))/1000,0),0))),"—")} -> 24.0% | K14: {=IFERROR(IF(4>COUNTIF('DONNÉES BRUTES'!C$3:C$42,"Technologie"),"",INDEX('DONNÉES BRUTES'!O$3:O$42,MATCH(LARGE(IF('DONNÉES BRUTES'!C$3:C$42="Technologie",'DONNÉES BRUTES'!AB$3:AB$42+(ROW('DONNÉES BRUTES'!A$3:A$42)-ROW('DONNÉES BRUTES'!A$3))/1000,0),4),IF('DONNÉES BRUTES'!C$3:C$42="Technologie",'DONNÉES BRUTES'!AB$3:AB$42+(ROW('DONNÉES BRUTES'!A$3:A$42)-ROW('DONNÉES BRUTES'!A$3))/1000,0),0))),"—")} -> 6.9% | L14: {=IFERROR(IF(4>COUNTIF('DONNÉES BRUTES'!C$3:C$42,"Technologie"),"",INDEX('DONNÉES BRUTES'!P$3:P$42,MATCH(LARGE(IF('DONNÉES BRUTES'!C$3:C$42="Technologie",'DONNÉES BRUTES'!AB$3:AB$42+(ROW('DONNÉES BRUTES'!A$3:A$42)-ROW('DONNÉES BRUTES'!A$3))/1000,0),4),IF('DONNÉES BRUTES'!C$3:C$42="Technologie",'DONNÉES BRUTES'!AB$3:AB$42+(ROW('DONNÉES BRUTES'!A$3:A$42)-ROW('DONNÉES BRUTES'!A$3))/1000,0),0))),"—")} -> -2.0% | M14: {=IFERROR(IF(4>COUNTIF('DONNÉES BRUTES'!C$3:C$42,"Technologie"),"",INDEX('DONNÉES BRUTES'!Q$3:Q$42,MATCH(LARGE(IF('DONNÉES BRUTES'!C$3:C$42="Technologie",'DONNÉES BRUTES'!AB$3:AB$42+(ROW('DONNÉES BRUTES'!A$3:A$42)-ROW('DONNÉES BRUTES'!A$3))/1000,0),4),IF('DONNÉES BRUTES'!C$3:C$42="Technologie",'DONNÉES BRUTES'!AB$3:AB$42+(ROW('DONNÉES BRUTES'!A$3:A$42)-ROW('DONNÉES BRUTES'!A$3))/1000,0),0))),"—")} -> +6.0% | N14: {=IFERROR(IF(4>COUNTIF('DONNÉES BRUTES'!C$3:C$42,"Technologie"),"",INDEX('DONNÉES BRUTES'!S$3:S$42,MATCH(LARGE(IF('DONNÉES BRUTES'!C$3:C$42="Technologie",'DONNÉES BRUTES'!AB$3:AB$42+(ROW('DONNÉES BRUTES'!A$3:A$42)-ROW('DONNÉES BRUTES'!A$3))/1000,0),4),IF('DONNÉES BRUTES'!C$3:C$42="Technologie",'DONNÉES BRUTES'!AB$3:AB$42+(ROW('DONNÉES BRUTES'!A$3:A$42)-ROW('DONNÉES BRUTES'!A$3))/1000,0),0))),"—")} -> 1.7 | O14: {=IFERROR(IF(4>COUNTIF('DONNÉES BRUTES'!C$3:C$42,"Technologie"),"",INDEX('DONNÉES BRUTES'!T$3:T$42,MATCH(LARGE(IF('DONNÉES BRUTES'!C$3:C$42="Technologie",'DONNÉES BRUTES'!AB$3:AB$42+(ROW('DONNÉES BRUTES'!A$3:A$42)-ROW('DONNÉES BRUTES'!A$3))/1000,0),4),IF('DONNÉES BRUTES'!C$3:C$42="Technologie",'DONNÉES BRUTES'!AB$3:AB$42+(ROW('DONNÉES BRUTES'!A$3:A$42)-ROW('DONNÉES BRUTES'!A$3))/1000,0),0))),"—")} -> 1.6x | P14: {=IFERROR(IF(4>COUNTIF('DONNÉES BRUTES'!C$3:C$42,"Technologie"),"",INDEX('DONNÉES BRUTES'!U$3:U$42,MATCH(LARGE(IF('DONNÉES BRUTES'!C$3:C$42="Technologie",'DONNÉES BRUTES'!AB$3:AB$42+(ROW('DONNÉES BRUTES'!A$3:A$42)-ROW('DONNÉES BRUTES'!A$3))/1000,0),4),IF('DONNÉES BRUTES'!C$3:C$42="Technologie",'DONNÉES BRUTES'!AB$3:AB$42+(ROW('DONNÉES BRUTES'!A$3:A$42)-ROW('DONNÉES BRUTES'!A$3))/1000,0),0))),"—")} -> 3.37 | Q14: {=IFERROR(IF(4>COUNTIF('DONNÉES BRUTES'!C$3:C$42,"Technologie"),"",INDEX('DONNÉES BRUTES'!AD$3:AD$42,MATCH(LARGE(IF('DONNÉES BRUTES'!C$3:C$42="Technologie",'DONNÉES BRUTES'!AB$3:AB$42+(ROW('DONNÉES BRUTES'!A$3:A$42)-ROW('DONNÉES BRUTES'!A$3))/1000,0),4),IF('DONNÉES BRUTES'!C$3:C$42="Technologie",'DONNÉES BRUTES'!AB$3:AB$42+(ROW('DONNÉES BRUTES'!A$3:A$42)-ROW('DONNÉES BRUTES'!A$3))/1000,0),0))),"—")} -> Neutre
C15: {=IFERROR(IF(5>COUNTIF('DONNÉES BRUTES'!C$3:C$42,"Technologie"),"",INDEX('DONNÉES BRUTES'!A$3:A$42,MATCH(LARGE(IF('DONNÉES BRUTES'!C$3:C$42="Technologie",'DONNÉES BRUTES'!AB$3:AB$42+(ROW('DONNÉES BRUTES'!A$3:A$42)-ROW('DONNÉES BRUTES'!A$3))/1000,0),5),IF('DONNÉES BRUTES'!C$3:C$42="Technologie",'DONNÉES BRUTES'!AB$3:AB$42+(ROW('DONNÉES BRUTES'!A$3:A$42)-ROW('DONNÉES BRUTES'!A$3))/1000,0),0))),"—")} | D15: {=IFERROR(IF(5>COUNTIF('DONNÉES BRUTES'!C$3:C$42,"Technologie"),"",INDEX('DONNÉES BRUTES'!B$3:B$42,MATCH(LARGE(IF('DONNÉES BRUTES'!C$3:C$42="Technologie",'DONNÉES BRUTES'!AB$3:AB$42+(ROW('DONNÉES BRUTES'!A$3:A$42)-ROW('DONNÉES BRUTES'!A$3))/1000,0),5),IF('DONNÉES BRUTES'!C$3:C$42="Technologie",'DONNÉES BRUTES'!AB$3:AB$42+(ROW('DONNÉES BRUTES'!A$3:A$42)-ROW('DONNÉES BRUTES'!A$3))/1000,0),0))),"—")} | E15: {=IFERROR(IF(5>COUNTIF('DONNÉES BRUTES'!C$3:C$42,"Technologie"),"",INT(LARGE(IF('DONNÉES BRUTES'!C$3:C$42="Technologie",'DONNÉES BRUTES'!AB$3:AB$42+(ROW('DONNÉES BRUTES'!A$3:A$42)-ROW('DONNÉES BRUTES'!A$3))/1000,0),5))&"/100"),"—")} | F15: {=IFERROR(IF(5>COUNTIF('DONNÉES BRUTES'!C$3:C$42,"Technologie"),"",INDEX('DONNÉES BRUTES'!Y$3:Y$42,MATCH(LARGE(IF('DONNÉES BRUTES'!C$3:C$42="Technologie",'DONNÉES BRUTES'!AB$3:AB$42+(ROW('DONNÉES BRUTES'!A$3:A$42)-ROW('DONNÉES BRUTES'!A$3))/1000,0),5),IF('DONNÉES BRUTES'!C$3:C$42="Technologie",'DONNÉES BRUTES'!AB$3:AB$42+(ROW('DONNÉES BRUTES'!A$3:A$42)-ROW('DONNÉES BRUTES'!A$3))/1000,0),0))),"—")} | G15: {=IFERROR(IF(5>COUNTIF('DONNÉES BRUTES'!C$3:C$42,"Technologie"),"",INDEX('DONNÉES BRUTES'!Z$3:Z$42,MATCH(LARGE(IF('DONNÉES BRUTES'!C$3:C$42="Technologie",'DONNÉES BRUTES'!AB$3:AB$42+(ROW('DONNÉES BRUTES'!A$3:A$42)-ROW('DONNÉES BRUTES'!A$3))/1000,0),5),IF('DONNÉES BRUTES'!C$3:C$42="Technologie",'DONNÉES BRUTES'!AB$3:AB$42+(ROW('DONNÉES BRUTES'!A$3:A$42)-ROW('DONNÉES BRUTES'!A$3))/1000,0),0))),"—")} | H15: {=IFERROR(IF(5>COUNTIF('DONNÉES BRUTES'!C$3:C$42,"Technologie"),"",INDEX('DONNÉES BRUTES'!AA$3:AA$42,MATCH(LARGE(IF('DONNÉES BRUTES'!C$3:C$42="Technologie",'DONNÉES BRUTES'!AB$3:AB$42+(ROW('DONNÉES BRUTES'!A$3:A$42)-ROW('DONNÉES BRUTES'!A$3))/1000,0),5),IF('DONNÉES BRUTES'!C$3:C$42="Technologie",'DONNÉES BRUTES'!AB$3:AB$42+(ROW('DONNÉES BRUTES'!A$3:A$42)-ROW('DONNÉES BRUTES'!A$3))/1000,0),0))),"—")} | I15: {=IFERROR(IF(5>COUNTIF('DONNÉES BRUTES'!C$3:C$42,"Technologie"),"",INDEX('DONNÉES BRUTES'!M$3:M$42,MATCH(LARGE(IF('DONNÉES BRUTES'!C$3:C$42="Technologie",'DONNÉES BRUTES'!AB$3:AB$42+(ROW('DONNÉES BRUTES'!A$3:A$42)-ROW('DONNÉES BRUTES'!A$3))/1000,0),5),IF('DONNÉES BRUTES'!C$3:C$42="Technologie",'DONNÉES BRUTES'!AB$3:AB$42+(ROW('DONNÉES BRUTES'!A$3:A$42)-ROW('DONNÉES BRUTES'!A$3))/1000,0),0))),"—")} | J15: {=IFERROR(IF(5>COUNTIF('DONNÉES BRUTES'!C$3:C$42,"Technologie"),"",INDEX('DONNÉES BRUTES'!N$3:N$42,MATCH(LARGE(IF('DONNÉES BRUTES'!C$3:C$42="Technologie",'DONNÉES BRUTES'!AB$3:AB$42+(ROW('DONNÉES BRUTES'!A$3:A$42)-ROW('DONNÉES BRUTES'!A$3))/1000,0),5),IF('DONNÉES BRUTES'!C$3:C$42="Technologie",'DONNÉES BRUTES'!AB$3:AB$42+(ROW('DONNÉES BRUTES'!A$3:A$42)-ROW('DONNÉES BRUTES'!A$3))/1000,0),0))),"—")} | K15: {=IFERROR(IF(5>COUNTIF('DONNÉES BRUTES'!C$3:C$42,"Technologie"),"",INDEX('DONNÉES BRUTES'!O$3:O$42,MATCH(LARGE(IF('DONNÉES BRUTES'!C$3:C$42="Technologie",'DONNÉES BRUTES'!AB$3:AB$42+(ROW('DONNÉES BRUTES'!A$3:A$42)-ROW('DONNÉES BRUTES'!A$3))/1000,0),5),IF('DONNÉES BRUTES'!C$3:C$42="Technologie",'DONNÉES BRUTES'!AB$3:AB$42+(ROW('DONNÉES BRUTES'!A$3:A$42)-ROW('DONNÉES BRUTES'!A$3))/1000,0),0))),"—")} | L15: {=IFERROR(IF(5>COUNTIF('DONNÉES BRUTES'!C$3:C$42,"Technologie"),"",INDEX('DONNÉES BRUTES'!P$3:P$42,MATCH(LARGE(IF('DONNÉES BRUTES'!C$3:C$42="Technologie",'DONNÉES BRUTES'!AB$3:AB$42+(ROW('DONNÉES BRUTES'!A$3:A$42)-ROW('DONNÉES BRUTES'!A$3))/1000,0),5),IF('DONNÉES BRUTES'!C$3:C$42="Technologie",'DONNÉES BRUTES'!AB$3:AB$42+(ROW('DONNÉES BRUTES'!A$3:A$42)-ROW('DONNÉES BRUTES'!A$3))/1000,0),0))),"—")} | M15: {=IFERROR(IF(5>COUNTIF('DONNÉES BRUTES'!C$3:C$42,"Technologie"),"",INDEX('DONNÉES BRUTES'!Q$3:Q$42,MATCH(LARGE(IF('DONNÉES BRUTES'!C$3:C$42="Technologie",'DONNÉES BRUTES'!AB$3:AB$42+(ROW('DONNÉES BRUTES'!A$3:A$42)-ROW('DONNÉES BRUTES'!A$3))/1000,0),5),IF('DONNÉES BRUTES'!C$3:C$42="Technologie",'DONNÉES BRUTES'!AB$3:AB$42+(ROW('DONNÉES BRUTES'!A$3:A$42)-ROW('DONNÉES BRUTES'!A$3))/1000,0),0))),"—")} | N15: {=IFERROR(IF(5>COUNTIF('DONNÉES BRUTES'!C$3:C$42,"Technologie"),"",INDEX('DONNÉES BRUTES'!S$3:S$42,MATCH(LARGE(IF('DONNÉES BRUTES'!C$3:C$42="Technologie",'DONNÉES BRUTES'!AB$3:AB$42+(ROW('DONNÉES BRUTES'!A$3:A$42)-ROW('DONNÉES BRUTES'!A$3))/1000,0),5),IF('DONNÉES BRUTES'!C$3:C$42="Technologie",'DONNÉES BRUTES'!AB$3:AB$42+(ROW('DONNÉES BRUTES'!A$3:A$42)-ROW('DONNÉES BRUTES'!A$3))/1000,0),0))),"—")} | O15: {=IFERROR(IF(5>COUNTIF('DONNÉES BRUTES'!C$3:C$42,"Technologie"),"",INDEX('DONNÉES BRUTES'!T$3:T$42,MATCH(LARGE(IF('DONNÉES BRUTES'!C$3:C$42="Technologie",'DONNÉES BRUTES'!AB$3:AB$42+(ROW('DONNÉES BRUTES'!A$3:A$42)-ROW('DONNÉES BRUTES'!A$3))/1000,0),5),IF('DONNÉES BRUTES'!C$3:C$42="Technologie",'DONNÉES BRUTES'!AB$3:AB$42+(ROW('DONNÉES BRUTES'!A$3:A$42)-ROW('DONNÉES BRUTES'!A$3))/1000,0),0))),"—")} | P15: {=IFERROR(IF(5>COUNTIF('DONNÉES BRUTES'!C$3:C$42,"Technologie"),"",INDEX('DONNÉES BRUTES'!U$3:U$42,MATCH(LARGE(IF('DONNÉES BRUTES'!C$3:C$42="Technologie",'DONNÉES BRUTES'!AB$3:AB$42+(ROW('DONNÉES BRUTES'!A$3:A$42)-ROW('DONNÉES BRUTES'!A$3))/1000,0),5),IF('DONNÉES BRUTES'!C$3:C$42="Technologie",'DONNÉES BRUTES'!AB$3:AB$42+(ROW('DONNÉES BRUTES'!A$3:A$42)-ROW('DONNÉES BRUTES'!A$3))/1000,0),0))),"—")} | Q15: {=IFERROR(IF(5>COUNTIF('DONNÉES BRUTES'!C$3:C$42,"Technologie"),"",INDEX('DONNÉES BRUTES'!AD$3:AD$42,MATCH(LARGE(IF('DONNÉES BRUTES'!C$3:C$42="Technologie",'DONNÉES BRUTES'!AB$3:AB$42+(ROW('DONNÉES BRUTES'!A$3:A$42)-ROW('DONNÉES BRUTES'!A$3))/1000,0),5),IF('DONNÉES BRUTES'!C$3:C$42="Technologie",'DONNÉES BRUTES'!AB$3:AB$42+(ROW('DONNÉES BRUTES'!A$3:A$42)-ROW('DONNÉES BRUTES'!A$3))/1000,0),0))),"—")}
C16: {=IFERROR(IF(6>COUNTIF('DONNÉES BRUTES'!C$3:C$42,"Technologie"),"",INDEX('DONNÉES BRUTES'!A$3:A$42,MATCH(LARGE(IF('DONNÉES BRUTES'!C$3:C$42="Technologie",'DONNÉES BRUTES'!AB$3:AB$42+(ROW('DONNÉES BRUTES'!A$3:A$42)-ROW('DONNÉES BRUTES'!A$3))/1000,0),6),IF('DONNÉES BRUTES'!C$3:C$42="Technologie",'DONNÉES BRUTES'!AB$3:AB$42+(ROW('DONNÉES BRUTES'!A$3:A$42)-ROW('DONNÉES BRUTES'!A$3))/1000,0),0))),"—")} | D16: {=IFERROR(IF(6>COUNTIF('DONNÉES BRUTES'!C$3:C$42,"Technologie"),"",INDEX('DONNÉES BRUTES'!B$3:B$42,MATCH(LARGE(IF('DONNÉES BRUTES'!C$3:C$42="Technologie",'DONNÉES BRUTES'!AB$3:AB$42+(ROW('DONNÉES BRUTES'!A$3:A$42)-ROW('DONNÉES BRUTES'!A$3))/1000,0),6),IF('DONNÉES BRUTES'!C$3:C$42="Technologie",'DONNÉES BRUTES'!AB$3:AB$42+(ROW('DONNÉES BRUTES'!A$3:A$42)-ROW('DONNÉES BRUTES'!A$3))/1000,0),0))),"—")} | E16: {=IFERROR(IF(6>COUNTIF('DONNÉES BRUTES'!C$3:C$42,"Technologie"),"",INT(LARGE(IF('DONNÉES BRUTES'!C$3:C$42="Technologie",'DONNÉES BRUTES'!AB$3:AB$42+(ROW('DONNÉES BRUTES'!A$3:A$42)-ROW('DONNÉES BRUTES'!A$3))/1000,0),6))&"/100"),"—")} | F16: {=IFERROR(IF(6>COUNTIF('DONNÉES BRUTES'!C$3:C$42,"Technologie"),"",INDEX('DONNÉES BRUTES'!Y$3:Y$42,MATCH(LARGE(IF('DONNÉES BRUTES'!C$3:C$42="Technologie",'DONNÉES BRUTES'!AB$3:AB$42+(ROW('DONNÉES BRUTES'!A$3:A$42)-ROW('DONNÉES BRUTES'!A$3))/1000,0),6),IF('DONNÉES BRUTES'!C$3:C$42="Technologie",'DONNÉES BRUTES'!AB$3:AB$42+(ROW('DONNÉES BRUTES'!A$3:A$42)-ROW('DONNÉES BRUTES'!A$3))/1000,0),0))),"—")} | G16: {=IFERROR(IF(6>COUNTIF('DONNÉES BRUTES'!C$3:C$42,"Technologie"),"",INDEX('DONNÉES BRUTES'!Z$3:Z$42,MATCH(LARGE(IF('DONNÉES BRUTES'!C$3:C$42="Technologie",'DONNÉES BRUTES'!AB$3:AB$42+(ROW('DONNÉES BRUTES'!A$3:A$42)-ROW('DONNÉES BRUTES'!A$3))/1000,0),6),IF('DONNÉES BRUTES'!C$3:C$42="Technologie",'DONNÉES BRUTES'!AB$3:AB$42+(ROW('DONNÉES BRUTES'!A$3:A$42)-ROW('DONNÉES BRUTES'!A$3))/1000,0),0))),"—")} | H16: {=IFERROR(IF(6>COUNTIF('DONNÉES BRUTES'!C$3:C$42,"Technologie"),"",INDEX('DONNÉES BRUTES'!AA$3:AA$42,MATCH(LARGE(IF('DONNÉES BRUTES'!C$3:C$42="Technologie",'DONNÉES BRUTES'!AB$3:AB$42+(ROW('DONNÉES BRUTES'!A$3:A$42)-ROW('DONNÉES BRUTES'!A$3))/1000,0),6),IF('DONNÉES BRUTES'!C$3:C$42="Technologie",'DONNÉES BRUTES'!AB$3:AB$42+(ROW('DONNÉES BRUTES'!A$3:A$42)-ROW('DONNÉES BRUTES'!A$3))/1000,0),0))),"—")} | I16: {=IFERROR(IF(6>COUNTIF('DONNÉES BRUTES'!C$3:C$42,"Technologie"),"",INDEX('DONNÉES BRUTES'!M$3:M$42,MATCH(LARGE(IF('DONNÉES BRUTES'!C$3:C$42="Technologie",'DONNÉES BRUTES'!AB$3:AB$42+(ROW('DONNÉES BRUTES'!A$3:A$42)-ROW('DONNÉES BRUTES'!A$3))/1000,0),6),IF('DONNÉES BRUTES'!C$3:C$42="Technologie",'DONNÉES BRUTES'!AB$3:AB$42+(ROW('DONNÉES BRUTES'!A$3:A$42)-ROW('DONNÉES BRUTES'!A$3))/1000,0),0))),"—")} | J16: {=IFERROR(IF(6>COUNTIF('DONNÉES BRUTES'!C$3:C$42,"Technologie"),"",INDEX('DONNÉES BRUTES'!N$3:N$42,MATCH(LARGE(IF('DONNÉES BRUTES'!C$3:C$42="Technologie",'DONNÉES BRUTES'!AB$3:AB$42+(ROW('DONNÉES BRUTES'!A$3:A$42)-ROW('DONNÉES BRUTES'!A$3))/1000,0),6),IF('DONNÉES BRUTES'!C$3:C$42="Technologie",'DONNÉES BRUTES'!AB$3:AB$42+(ROW('DONNÉES BRUTES'!A$3:A$42)-ROW('DONNÉES BRUTES'!A$3))/1000,0),0))),"—")} | K16: {=IFERROR(IF(6>COUNTIF('DONNÉES BRUTES'!C$3:C$42,"Technologie"),"",INDEX('DONNÉES BRUTES'!O$3:O$42,MATCH(LARGE(IF('DONNÉES BRUTES'!C$3:C$42="Technologie",'DONNÉES BRUTES'!AB$3:AB$42+(ROW('DONNÉES BRUTES'!A$3:A$42)-ROW('DONNÉES BRUTES'!A$3))/1000,0),6),IF('DONNÉES BRUTES'!C$3:C$42="Technologie",'DONNÉES BRUTES'!AB$3:AB$42+(ROW('DONNÉES BRUTES'!A$3:A$42)-ROW('DONNÉES BRUTES'!A$3))/1000,0),0))),"—")} | L16: {=IFERROR(IF(6>COUNTIF('DONNÉES BRUTES'!C$3:C$42,"Technologie"),"",INDEX('DONNÉES BRUTES'!P$3:P$42,MATCH(LARGE(IF('DONNÉES BRUTES'!C$3:C$42="Technologie",'DONNÉES BRUTES'!AB$3:AB$42+(ROW('DONNÉES BRUTES'!A$3:A$42)-ROW('DONNÉES BRUTES'!A$3))/1000,0),6),IF('DONNÉES BRUTES'!C$3:C$42="Technologie",'DONNÉES BRUTES'!AB$3:AB$42+(ROW('DONNÉES BRUTES'!A$3:A$42)-ROW('DONNÉES BRUTES'!A$3))/1000,0),0))),"—")} | M16: {=IFERROR(IF(6>COUNTIF('DONNÉES BRUTES'!C$3:C$42,"Technologie"),"",INDEX('DONNÉES BRUTES'!Q$3:Q$42,MATCH(LARGE(IF('DONNÉES BRUTES'!C$3:C$42="Technologie",'DONNÉES BRUTES'!AB$3:AB$42+(ROW('DONNÉES BRUTES'!A$3:A$42)-ROW('DONNÉES BRUTES'!A$3))/1000,0),6),IF('DONNÉES BRUTES'!C$3:C$42="Technologie",'DONNÉES BRUTES'!AB$3:AB$42+(ROW('DONNÉES BRUTES'!A$3:A$42)-ROW('DONNÉES BRUTES'!A$3))/1000,0),0))),"—")} | N16: {=IFERROR(IF(6>COUNTIF('DONNÉES BRUTES'!C$3:C$42,"Technologie"),"",INDEX('DONNÉES BRUTES'!S$3:S$42,MATCH(LARGE(IF('DONNÉES BRUTES'!C$3:C$42="Technologie",'DONNÉES BRUTES'!AB$3:AB$42+(ROW('DONNÉES BRUTES'!A$3:A$42)-ROW('DONNÉES BRUTES'!A$3))/1000,0),6),IF('DONNÉES BRUTES'!C$3:C$42="Technologie",'DONNÉES BRUTES'!AB$3:AB$42+(ROW('DONNÉES BRUTES'!A$3:A$42)-ROW('DONNÉES BRUTES'!A$3))/1000,0),0))),"—")} | O16: {=IFERROR(IF(6>COUNTIF('DONNÉES BRUTES'!C$3:C$42,"Technologie"),"",INDEX('DONNÉES BRUTES'!T$3:T$42,MATCH(LARGE(IF('DONNÉES BRUTES'!C$3:C$42="Technologie",'DONNÉES BRUTES'!AB$3:AB$42+(ROW('DONNÉES BRUTES'!A$3:A$42)-ROW('DONNÉES BRUTES'!A$3))/1000,0),6),IF('DONNÉES BRUTES'!C$3:C$42="Technologie",'DONNÉES BRUTES'!AB$3:AB$42+(ROW('DONNÉES BRUTES'!A$3:A$42)-ROW('DONNÉES BRUTES'!A$3))/1000,0),0))),"—")} | P16: {=IFERROR(IF(6>COUNTIF('DONNÉES BRUTES'!C$3:C$42,"Technologie"),"",INDEX('DONNÉES BRUTES'!U$3:U$42,MATCH(LARGE(IF('DONNÉES BRUTES'!C$3:C$42="Technologie",'DONNÉES BRUTES'!AB$3:AB$42+(ROW('DONNÉES BRUTES'!A$3:A$42)-ROW('DONNÉES BRUTES'!A$3))/1000,0),6),IF('DONNÉES BRUTES'!C$3:C$42="Technologie",'DONNÉES BRUTES'!AB$3:AB$42+(ROW('DONNÉES BRUTES'!A$3:A$42)-ROW('DONNÉES BRUTES'!A$3))/1000,0),0))),"—")} | Q16: {=IFERROR(IF(6>COUNTIF('DONNÉES BRUTES'!C$3:C$42,"Technologie"),"",INDEX('DONNÉES BRUTES'!AD$3:AD$42,MATCH(LARGE(IF('DONNÉES BRUTES'!C$3:C$42="Technologie",'DONNÉES BRUTES'!AB$3:AB$42+(ROW('DONNÉES BRUTES'!A$3:A$42)-ROW('DONNÉES BRUTES'!A$3))/1000,0),6),IF('DONNÉES BRUTES'!C$3:C$42="Technologie",'DONNÉES BRUTES'!AB$3:AB$42+(ROW('DONNÉES BRUTES'!A$3:A$42)-ROW('DONNÉES BRUTES'!A$3))/1000,0),0))),"—")}
C17: {=IFERROR(IF(7>COUNTIF('DONNÉES BRUTES'!C$3:C$42,"Technologie"),"",INDEX('DONNÉES BRUTES'!A$3:A$42,MATCH(LARGE(IF('DONNÉES BRUTES'!C$3:C$42="Technologie",'DONNÉES BRUTES'!AB$3:AB$42+(ROW('DONNÉES BRUTES'!A$3:A$42)-ROW('DONNÉES BRUTES'!A$3))/1000,0),7),IF('DONNÉES BRUTES'!C$3:C$42="Technologie",'DONNÉES BRUTES'!AB$3:AB$42+(ROW('DONNÉES BRUTES'!A$3:A$42)-ROW('DONNÉES BRUTES'!A$3))/1000,0),0))),"—")} | D17: {=IFERROR(IF(7>COUNTIF('DONNÉES BRUTES'!C$3:C$42,"Technologie"),"",INDEX('DONNÉES BRUTES'!B$3:B$42,MATCH(LARGE(IF('DONNÉES BRUTES'!C$3:C$42="Technologie",'DONNÉES BRUTES'!AB$3:AB$42+(ROW('DONNÉES BRUTES'!A$3:A$42)-ROW('DONNÉES BRUTES'!A$3))/1000,0),7),IF('DONNÉES BRUTES'!C$3:C$42="Technologie",'DONNÉES BRUTES'!AB$3:AB$42+(ROW('DONNÉES BRUTES'!A$3:A$42)-ROW('DONNÉES BRUTES'!A$3))/1000,0),0))),"—")} | E17: {=IFERROR(IF(7>COUNTIF('DONNÉES BRUTES'!C$3:C$42,"Technologie"),"",INT(LARGE(IF('DONNÉES BRUTES'!C$3:C$42="Technologie",'DONNÉES BRUTES'!AB$3:AB$42+(ROW('DONNÉES BRUTES'!A$3:A$42)-ROW('DONNÉES BRUTES'!A$3))/1000,0),7))&"/100"),"—")} | F17: {=IFERROR(IF(7>COUNTIF('DONNÉES BRUTES'!C$3:C$42,"Technologie"),"",INDEX('DONNÉES BRUTES'!Y$3:Y$42,MATCH(LARGE(IF('DONNÉES BRUTES'!C$3:C$42="Technologie",'DONNÉES BRUTES'!AB$3:AB$42+(ROW('DONNÉES BRUTES'!A$3:A$42)-ROW('DONNÉES BRUTES'!A$3))/1000,0),7),IF('DONNÉES BRUTES'!C$3:C$42="Technologie",'DONNÉES BRUTES'!AB$3:AB$42+(ROW('DONNÉES BRUTES'!A$3:A$42)-ROW('DONNÉES BRUTES'!A$3))/1000,0),0))),"—")} | G17: {=IFERROR(IF(7>COUNTIF('DONNÉES BRUTES'!C$3:C$42,"Technologie"),"",INDEX('DONNÉES BRUTES'!Z$3:Z$42,MATCH(LARGE(IF('DONNÉES BRUTES'!C$3:C$42="Technologie",'DONNÉES BRUTES'!AB$3:AB$42+(ROW('DONNÉES BRUTES'!A$3:A$42)-ROW('DONNÉES BRUTES'!A$3))/1000,0),7),IF('DONNÉES BRUTES'!C$3:C$42="Technologie",'DONNÉES BRUTES'!AB$3:AB$42+(ROW('DONNÉES BRUTES'!A$3:A$42)-ROW('DONNÉES BRUTES'!A$3))/1000,0),0))),"—")} | H17: {=IFERROR(IF(7>COUNTIF('DONNÉES BRUTES'!C$3:C$42,"Technologie"),"",INDEX('DONNÉES BRUTES'!AA$3:AA$42,MATCH(LARGE(IF('DONNÉES BRUTES'!C$3:C$42="Technologie",'DONNÉES BRUTES'!AB$3:AB$42+(ROW('DONNÉES BRUTES'!A$3:A$42)-ROW('DONNÉES BRUTES'!A$3))/1000,0),7),IF('DONNÉES BRUTES'!C$3:C$42="Technologie",'DONNÉES BRUTES'!AB$3:AB$42+(ROW('DONNÉES BRUTES'!A$3:A$42)-ROW('DONNÉES BRUTES'!A$3))/1000,0),0))),"—")} | I17: {=IFERROR(IF(7>COUNTIF('DONNÉES BRUTES'!C$3:C$42,"Technologie"),"",INDEX('DONNÉES BRUTES'!M$3:M$42,MATCH(LARGE(IF('DONNÉES BRUTES'!C$3:C$42="Technologie",'DONNÉES BRUTES'!AB$3:AB$42+(ROW('DONNÉES BRUTES'!A$3:A$42)-ROW('DONNÉES BRUTES'!A$3))/1000,0),7),IF('DONNÉES BRUTES'!C$3:C$42="Technologie",'DONNÉES BRUTES'!AB$3:AB$42+(ROW('DONNÉES BRUTES'!A$3:A$42)-ROW('DONNÉES BRUTES'!A$3))/1000,0),0))),"—")} | J17: {=IFERROR(IF(7>COUNTIF('DONNÉES BRUTES'!C$3:C$42,"Technologie"),"",INDEX('DONNÉES BRUTES'!N$3:N$42,MATCH(LARGE(IF('DONNÉES BRUTES'!C$3:C$42="Technologie",'DONNÉES BRUTES'!AB$3:AB$42+(ROW('DONNÉES BRUTES'!A$3:A$42)-ROW('DONNÉES BRUTES'!A$3))/1000,0),7),IF('DONNÉES BRUTES'!C$3:C$42="Technologie",'DONNÉES BRUTES'!AB$3:AB$42+(ROW('DONNÉES BRUTES'!A$3:A$42)-ROW('DONNÉES BRUTES'!A$3))/1000,0),0))),"—")} | K17: {=IFERROR(IF(7>COUNTIF('DONNÉES BRUTES'!C$3:C$42,"Technologie"),"",INDEX('DONNÉES BRUTES'!O$3:O$42,MATCH(LARGE(IF('DONNÉES BRUTES'!C$3:C$42="Technologie",'DONNÉES BRUTES'!AB$3:AB$42+(ROW('DONNÉES BRUTES'!A$3:A$42)-ROW('DONNÉES BRUTES'!A$3))/1000,0),7),IF('DONNÉES BRUTES'!C$3:C$42="Technologie",'DONNÉES BRUTES'!AB$3:AB$42+(ROW('DONNÉES BRUTES'!A$3:A$42)-ROW('DONNÉES BRUTES'!A$3))/1000,0),0))),"—")} | L17: {=IFERROR(IF(7>COUNTIF('DONNÉES BRUTES'!C$3:C$42,"Technologie"),"",INDEX('DONNÉES BRUTES'!P$3:P$42,MATCH(LARGE(IF('DONNÉES BRUTES'!C$3:C$42="Technologie",'DONNÉES BRUTES'!AB$3:AB$42+(ROW('DONNÉES BRUTES'!A$3:A$42)-ROW('DONNÉES BRUTES'!A$3))/1000,0),7),IF('DONNÉES BRUTES'!C$3:C$42="Technologie",'DONNÉES BRUTES'!AB$3:AB$42+(ROW('DONNÉES BRUTES'!A$3:A$42)-ROW('DONNÉES BRUTES'!A$3))/1000,0),0))),"—")} | M17: {=IFERROR(IF(7>COUNTIF('DONNÉES BRUTES'!C$3:C$42,"Technologie"),"",INDEX('DONNÉES BRUTES'!Q$3:Q$42,MATCH(LARGE(IF('DONNÉES BRUTES'!C$3:C$42="Technologie",'DONNÉES BRUTES'!AB$3:AB$42+(ROW('DONNÉES BRUTES'!A$3:A$42)-ROW('DONNÉES BRUTES'!A$3))/1000,0),7),IF('DONNÉES BRUTES'!C$3:C$42="Technologie",'DONNÉES BRUTES'!AB$3:AB$42+(ROW('DONNÉES BRUTES'!A$3:A$42)-ROW('DONNÉES BRUTES'!A$3))/1000,0),0))),"—")} | N17: {=IFERROR(IF(7>COUNTIF('DONNÉES BRUTES'!C$3:C$42,"Technologie"),"",INDEX('DONNÉES BRUTES'!S$3:S$42,MATCH(LARGE(IF('DONNÉES BRUTES'!C$3:C$42="Technologie",'DONNÉES BRUTES'!AB$3:AB$42+(ROW('DONNÉES BRUTES'!A$3:A$42)-ROW('DONNÉES BRUTES'!A$3))/1000,0),7),IF('DONNÉES BRUTES'!C$3:C$42="Technologie",'DONNÉES BRUTES'!AB$3:AB$42+(ROW('DONNÉES BRUTES'!A$3:A$42)-ROW('DONNÉES BRUTES'!A$3))/1000,0),0))),"—")} | O17: {=IFERROR(IF(7>COUNTIF('DONNÉES BRUTES'!C$3:C$42,"Technologie"),"",INDEX('DONNÉES BRUTES'!T$3:T$42,MATCH(LARGE(IF('DONNÉES BRUTES'!C$3:C$42="Technologie",'DONNÉES BRUTES'!AB$3:AB$42+(ROW('DONNÉES BRUTES'!A$3:A$42)-ROW('DONNÉES BRUTES'!A$3))/1000,0),7),IF('DONNÉES BRUTES'!C$3:C$42="Technologie",'DONNÉES BRUTES'!AB$3:AB$42+(ROW('DONNÉES BRUTES'!A$3:A$42)-ROW('DONNÉES BRUTES'!A$3))/1000,0),0))),"—")} | P17: {=IFERROR(IF(7>COUNTIF('DONNÉES BRUTES'!C$3:C$42,"Technologie"),"",INDEX('DONNÉES BRUTES'!U$3:U$42,MATCH(LARGE(IF('DONNÉES BRUTES'!C$3:C$42="Technologie",'DONNÉES BRUTES'!AB$3:AB$42+(ROW('DONNÉES BRUTES'!A$3:A$42)-ROW('DONNÉES BRUTES'!A$3))/1000,0),7),IF('DONNÉES BRUTES'!C$3:C$42="Technologie",'DONNÉES BRUTES'!AB$3:AB$42+(ROW('DONNÉES BRUTES'!A$3:A$42)-ROW('DONNÉES BRUTES'!A$3))/1000,0),0))),"—")} | Q17: {=IFERROR(IF(7>COUNTIF('DONNÉES BRUTES'!C$3:C$42,"Technologie"),"",INDEX('DONNÉES BRUTES'!AD$3:AD$42,MATCH(LARGE(IF('DONNÉES BRUTES'!C$3:C$42="Technologie",'DONNÉES BRUTES'!AB$3:AB$42+(ROW('DONNÉES BRUTES'!A$3:A$42)-ROW('DONNÉES BRUTES'!A$3))/1000,0),7),IF('DONNÉES BRUTES'!C$3:C$42="Technologie",'DONNÉES BRUTES'!AB$3:AB$42+(ROW('DONNÉES BRUTES'!A$3:A$42)-ROW('DONNÉES BRUTES'!A$3))/1000,0),0))),"—")}
C18: {=IFERROR(IF(8>COUNTIF('DONNÉES BRUTES'!C$3:C$42,"Technologie"),"",INDEX('DONNÉES BRUTES'!A$3:A$42,MATCH(LARGE(IF('DONNÉES BRUTES'!C$3:C$42="Technologie",'DONNÉES BRUTES'!AB$3:AB$42+(ROW('DONNÉES BRUTES'!A$3:A$42)-ROW('DONNÉES BRUTES'!A$3))/1000,0),8),IF('DONNÉES BRUTES'!C$3:C$42="Technologie",'DONNÉES BRUTES'!AB$3:AB$42+(ROW('DONNÉES BRUTES'!A$3:A$42)-ROW('DONNÉES BRUTES'!A$3))/1000,0),0))),"—")} | D18: {=IFERROR(IF(8>COUNTIF('DONNÉES BRUTES'!C$3:C$42,"Technologie"),"",INDEX('DONNÉES BRUTES'!B$3:B$42,MATCH(LARGE(IF('DONNÉES BRUTES'!C$3:C$42="Technologie",'DONNÉES BRUTES'!AB$3:AB$42+(ROW('DONNÉES BRUTES'!A$3:A$42)-ROW('DONNÉES BRUTES'!A$3))/1000,0),8),IF('DONNÉES BRUTES'!C$3:C$42="Technologie",'DONNÉES BRUTES'!AB$3:AB$42+(ROW('DONNÉES BRUTES'!A$3:A$42)-ROW('DONNÉES BRUTES'!A$3))/1000,0),0))),"—")} | E18: {=IFERROR(IF(8>COUNTIF('DONNÉES BRUTES'!C$3:C$42,"Technologie"),"",INT(LARGE(IF('DONNÉES BRUTES'!C$3:C$42="Technologie",'DONNÉES BRUTES'!AB$3:AB$42+(ROW('DONNÉES BRUTES'!A$3:A$42)-ROW('DONNÉES BRUTES'!A$3))/1000,0),8))&"/100"),"—")} | F18: {=IFERROR(IF(8>COUNTIF('DONNÉES BRUTES'!C$3:C$42,"Technologie"),"",INDEX('DONNÉES BRUTES'!Y$3:Y$42,MATCH(LARGE(IF('DONNÉES BRUTES'!C$3:C$42="Technologie",'DONNÉES BRUTES'!AB$3:AB$42+(ROW('DONNÉES BRUTES'!A$3:A$42)-ROW('DONNÉES BRUTES'!A$3))/1000,0),8),IF('DONNÉES BRUTES'!C$3:C$42="Technologie",'DONNÉES BRUTES'!AB$3:AB$42+(ROW('DONNÉES BRUTES'!A$3:A$42)-ROW('DONNÉES BRUTES'!A$3))/1000,0),0))),"—")} | G18: {=IFERROR(IF(8>COUNTIF('DONNÉES BRUTES'!C$3:C$42,"Technologie"),"",INDEX('DONNÉES BRUTES'!Z$3:Z$42,MATCH(LARGE(IF('DONNÉES BRUTES'!C$3:C$42="Technologie",'DONNÉES BRUTES'!AB$3:AB$42+(ROW('DONNÉES BRUTES'!A$3:A$42)-ROW('DONNÉES BRUTES'!A$3))/1000,0),8),IF('DONNÉES BRUTES'!C$3:C$42="Technologie",'DONNÉES BRUTES'!AB$3:AB$42+(ROW('DONNÉES BRUTES'!A$3:A$42)-ROW('DONNÉES BRUTES'!A$3))/1000,0),0))),"—")} | H18: {=IFERROR(IF(8>COUNTIF('DONNÉES BRUTES'!C$3:C$42,"Technologie"),"",INDEX('DONNÉES BRUTES'!AA$3:AA$42,MATCH(LARGE(IF('DONNÉES BRUTES'!C$3:C$42="Technologie",'DONNÉES BRUTES'!AB$3:AB$42+(ROW('DONNÉES BRUTES'!A$3:A$42)-ROW('DONNÉES BRUTES'!A$3))/1000,0),8),IF('DONNÉES BRUTES'!C$3:C$42="Technologie",'DONNÉES BRUTES'!AB$3:AB$42+(ROW('DONNÉES BRUTES'!A$3:A$42)-ROW('DONNÉES BRUTES'!A$3))/1000,0),0))),"—")} | I18: {=IFERROR(IF(8>COUNTIF('DONNÉES BRUTES'!C$3:C$42,"Technologie"),"",INDEX('DONNÉES BRUTES'!M$3:M$42,MATCH(LARGE(IF('DONNÉES BRUTES'!C$3:C$42="Technologie",'DONNÉES BRUTES'!AB$3:AB$42+(ROW('DONNÉES BRUTES'!A$3:A$42)-ROW('DONNÉES BRUTES'!A$3))/1000,0),8),IF('DONNÉES BRUTES'!C$3:C$42="Technologie",'DONNÉES BRUTES'!AB$3:AB$42+(ROW('DONNÉES BRUTES'!A$3:A$42)-ROW('DONNÉES BRUTES'!A$3))/1000,0),0))),"—")} | J18: {=IFERROR(IF(8>COUNTIF('DONNÉES BRUTES'!C$3:C$42,"Technologie"),"",INDEX('DONNÉES BRUTES'!N$3:N$42,MATCH(LARGE(IF('DONNÉES BRUTES'!C$3:C$42="Technologie",'DONNÉES BRUTES'!AB$3:AB$42+(ROW('DONNÉES BRUTES'!A$3:A$42)-ROW('DONNÉES BRUTES'!A$3))/1000,0),8),IF('DONNÉES BRUTES'!C$3:C$42="Technologie",'DONNÉES BRUTES'!AB$3:AB$42+(ROW('DONNÉES BRUTES'!A$3:A$42)-ROW('DONNÉES BRUTES'!A$3))/1000,0),0))),"—")} | K18: {=IFERROR(IF(8>COUNTIF('DONNÉES BRUTES'!C$3:C$42,"Technologie"),"",INDEX('DONNÉES BRUTES'!O$3:O$42,MATCH(LARGE(IF('DONNÉES BRUTES'!C$3:C$42="Technologie",'DONNÉES BRUTES'!AB$3:AB$42+(ROW('DONNÉES BRUTES'!A$3:A$42)-ROW('DONNÉES BRUTES'!A$3))/1000,0),8),IF('DONNÉES BRUTES'!C$3:C$42="Technologie",'DONNÉES BRUTES'!AB$3:AB$42+(ROW('DONNÉES BRUTES'!A$3:A$42)-ROW('DONNÉES BRUTES'!A$3))/1000,0),0))),"—")} | L18: {=IFERROR(IF(8>COUNTIF('DONNÉES BRUTES'!C$3:C$42,"Technologie"),"",INDEX('DONNÉES BRUTES'!P$3:P$42,MATCH(LARGE(IF('DONNÉES BRUTES'!C$3:C$42="Technologie",'DONNÉES BRUTES'!AB$3:AB$42+(ROW('DONNÉES BRUTES'!A$3:A$42)-ROW('DONNÉES BRUTES'!A$3))/1000,0),8),IF('DONNÉES BRUTES'!C$3:C$42="Technologie",'DONNÉES BRUTES'!AB$3:AB$42+(ROW('DONNÉES BRUTES'!A$3:A$42)-ROW('DONNÉES BRUTES'!A$3))/1000,0),0))),"—")} | M18: {=IFERROR(IF(8>COUNTIF('DONNÉES BRUTES'!C$3:C$42,"Technologie"),"",INDEX('DONNÉES BRUTES'!Q$3:Q$42,MATCH(LARGE(IF('DONNÉES BRUTES'!C$3:C$42="Technologie",'DONNÉES BRUTES'!AB$3:AB$42+(ROW('DONNÉES BRUTES'!A$3:A$42)-ROW('DONNÉES BRUTES'!A$3))/1000,0),8),IF('DONNÉES BRUTES'!C$3:C$42="Technologie",'DONNÉES BRUTES'!AB$3:AB$42+(ROW('DONNÉES BRUTES'!A$3:A$42)-ROW('DONNÉES BRUTES'!A$3))/1000,0),0))),"—")} | N18: {=IFERROR(IF(8>COUNTIF('DONNÉES BRUTES'!C$3:C$42,"Technologie"),"",INDEX('DONNÉES BRUTES'!S$3:S$42,MATCH(LARGE(IF('DONNÉES BRUTES'!C$3:C$42="Technologie",'DONNÉES BRUTES'!AB$3:AB$42+(ROW('DONNÉES BRUTES'!A$3:A$42)-ROW('DONNÉES BRUTES'!A$3))/1000,0),8),IF('DONNÉES BRUTES'!C$3:C$42="Technologie",'DONNÉES BRUTES'!AB$3:AB$42+(ROW('DONNÉES BRUTES'!A$3:A$42)-ROW('DONNÉES BRUTES'!A$3))/1000,0),0))),"—")} | O18: {=IFERROR(IF(8>COUNTIF('DONNÉES BRUTES'!C$3:C$42,"Technologie"),"",INDEX('DONNÉES BRUTES'!T$3:T$42,MATCH(LARGE(IF('DONNÉES BRUTES'!C$3:C$42="Technologie",'DONNÉES BRUTES'!AB$3:AB$42+(ROW('DONNÉES BRUTES'!A$3:A$42)-ROW('DONNÉES BRUTES'!A$3))/1000,0),8),IF('DONNÉES BRUTES'!C$3:C$42="Technologie",'DONNÉES BRUTES'!AB$3:AB$42+(ROW('DONNÉES BRUTES'!A$3:A$42)-ROW('DONNÉES BRUTES'!A$3))/1000,0),0))),"—")} | P18: {=IFERROR(IF(8>COUNTIF('DONNÉES BRUTES'!C$3:C$42,"Technologie"),"",INDEX('DONNÉES BRUTES'!U$3:U$42,MATCH(LARGE(IF('DONNÉES BRUTES'!C$3:C$42="Technologie",'DONNÉES BRUTES'!AB$3:AB$42+(ROW('DONNÉES BRUTES'!A$3:A$42)-ROW('DONNÉES BRUTES'!A$3))/1000,0),8),IF('DONNÉES BRUTES'!C$3:C$42="Technologie",'DONNÉES BRUTES'!AB$3:AB$42+(ROW('DONNÉES BRUTES'!A$3:A$42)-ROW('DONNÉES BRUTES'!A$3))/1000,0),0))),"—")} | Q18: {=IFERROR(IF(8>COUNTIF('DONNÉES BRUTES'!C$3:C$42,"Technologie"),"",INDEX('DONNÉES BRUTES'!AD$3:AD$42,MATCH(LARGE(IF('DONNÉES BRUTES'!C$3:C$42="Technologie",'DONNÉES BRUTES'!AB$3:AB$42+(ROW('DONNÉES BRUTES'!A$3:A$42)-ROW('DONNÉES BRUTES'!A$3))/1000,0),8),IF('DONNÉES BRUTES'!C$3:C$42="Technologie",'DONNÉES BRUTES'!AB$3:AB$42+(ROW('DONNÉES BRUTES'!A$3:A$42)-ROW('DONNÉES BRUTES'!A$3))/1000,0),0))),"—")}
C19: {=IFERROR(IF(9>COUNTIF('DONNÉES BRUTES'!C$3:C$42,"Technologie"),"",INDEX('DONNÉES BRUTES'!A$3:A$42,MATCH(LARGE(IF('DONNÉES BRUTES'!C$3:C$42="Technologie",'DONNÉES BRUTES'!AB$3:AB$42+(ROW('DONNÉES BRUTES'!A$3:A$42)-ROW('DONNÉES BRUTES'!A$3))/1000,0),9),IF('DONNÉES BRUTES'!C$3:C$42="Technologie",'DONNÉES BRUTES'!AB$3:AB$42+(ROW('DONNÉES BRUTES'!A$3:A$42)-ROW('DONNÉES BRUTES'!A$3))/1000,0),0))),"—")} | D19: {=IFERROR(IF(9>COUNTIF('DONNÉES BRUTES'!C$3:C$42,"Technologie"),"",INDEX('DONNÉES BRUTES'!B$3:B$42,MATCH(LARGE(IF('DONNÉES BRUTES'!C$3:C$42="Technologie",'DONNÉES BRUTES'!AB$3:AB$42+(ROW('DONNÉES BRUTES'!A$3:A$42)-ROW('DONNÉES BRUTES'!A$3))/1000,0),9),IF('DONNÉES BRUTES'!C$3:C$42="Technologie",'DONNÉES BRUTES'!AB$3:AB$42+(ROW('DONNÉES BRUTES'!A$3:A$42)-ROW('DONNÉES BRUTES'!A$3))/1000,0),0))),"—")} | E19: {=IFERROR(IF(9>COUNTIF('DONNÉES BRUTES'!C$3:C$42,"Technologie"),"",INT(LARGE(IF('DONNÉES BRUTES'!C$3:C$42="Technologie",'DONNÉES BRUTES'!AB$3:AB$42+(ROW('DONNÉES BRUTES'!A$3:A$42)-ROW('DONNÉES BRUTES'!A$3))/1000,0),9))&"/100"),"—")} | F19: {=IFERROR(IF(9>COUNTIF('DONNÉES BRUTES'!C$3:C$42,"Technologie"),"",INDEX('DONNÉES BRUTES'!Y$3:Y$42,MATCH(LARGE(IF('DONNÉES BRUTES'!C$3:C$42="Technologie",'DONNÉES BRUTES'!AB$3:AB$42+(ROW('DONNÉES BRUTES'!A$3:A$42)-ROW('DONNÉES BRUTES'!A$3))/1000,0),9),IF('DONNÉES BRUTES'!C$3:C$42="Technologie",'DONNÉES BRUTES'!AB$3:AB$42+(ROW('DONNÉES BRUTES'!A$3:A$42)-ROW('DONNÉES BRUTES'!A$3))/1000,0),0))),"—")} | G19: {=IFERROR(IF(9>COUNTIF('DONNÉES BRUTES'!C$3:C$42,"Technologie"),"",INDEX('DONNÉES BRUTES'!Z$3:Z$42,MATCH(LARGE(IF('DONNÉES BRUTES'!C$3:C$42="Technologie",'DONNÉES BRUTES'!AB$3:AB$42+(ROW('DONNÉES BRUTES'!A$3:A$42)-ROW('DONNÉES BRUTES'!A$3))/1000,0),9),IF('DONNÉES BRUTES'!C$3:C$42="Technologie",'DONNÉES BRUTES'!AB$3:AB$42+(ROW('DONNÉES BRUTES'!A$3:A$42)-ROW('DONNÉES BRUTES'!A$3))/1000,0),0))),"—")} | H19: {=IFERROR(IF(9>COUNTIF('DONNÉES BRUTES'!C$3:C$42,"Technologie"),"",INDEX('DONNÉES BRUTES'!AA$3:AA$42,MATCH(LARGE(IF('DONNÉES BRUTES'!C$3:C$42="Technologie",'DONNÉES BRUTES'!AB$3:AB$42+(ROW('DONNÉES BRUTES'!A$3:A$42)-ROW('DONNÉES BRUTES'!A$3))/1000,0),9),IF('DONNÉES BRUTES'!C$3:C$42="Technologie",'DONNÉES BRUTES'!AB$3:AB$42+(ROW('DONNÉES BRUTES'!A$3:A$42)-ROW('DONNÉES BRUTES'!A$3))/1000,0),0))),"—")} | I19: {=IFERROR(IF(9>COUNTIF('DONNÉES BRUTES'!C$3:C$42,"Technologie"),"",INDEX('DONNÉES BRUTES'!M$3:M$42,MATCH(LARGE(IF('DONNÉES BRUTES'!C$3:C$42="Technologie",'DONNÉES BRUTES'!AB$3:AB$42+(ROW('DONNÉES BRUTES'!A$3:A$42)-ROW('DONNÉES BRUTES'!A$3))/1000,0),9),IF('DONNÉES BRUTES'!C$3:C$42="Technologie",'DONNÉES BRUTES'!AB$3:AB$42+(ROW('DONNÉES BRUTES'!A$3:A$42)-ROW('DONNÉES BRUTES'!A$3))/1000,0),0))),"—")} | J19: {=IFERROR(IF(9>COUNTIF('DONNÉES BRUTES'!C$3:C$42,"Technologie"),"",INDEX('DONNÉES BRUTES'!N$3:N$42,MATCH(LARGE(IF('DONNÉES BRUTES'!C$3:C$42="Technologie",'DONNÉES BRUTES'!AB$3:AB$42+(ROW('DONNÉES BRUTES'!A$3:A$42)-ROW('DONNÉES BRUTES'!A$3))/1000,0),9),IF('DONNÉES BRUTES'!C$3:C$42="Technologie",'DONNÉES BRUTES'!AB$3:AB$42+(ROW('DONNÉES BRUTES'!A$3:A$42)-ROW('DONNÉES BRUTES'!A$3))/1000,0),0))),"—")} | K19: {=IFERROR(IF(9>COUNTIF('DONNÉES BRUTES'!C$3:C$42,"Technologie"),"",INDEX('DONNÉES BRUTES'!O$3:O$42,MATCH(LARGE(IF('DONNÉES BRUTES'!C$3:C$42="Technologie",'DONNÉES BRUTES'!AB$3:AB$42+(ROW('DONNÉES BRUTES'!A$3:A$42)-ROW('DONNÉES BRUTES'!A$3))/1000,0),9),IF('DONNÉES BRUTES'!C$3:C$42="Technologie",'DONNÉES BRUTES'!AB$3:AB$42+(ROW('DONNÉES BRUTES'!A$3:A$42)-ROW('DONNÉES BRUTES'!A$3))/1000,0),0))),"—")} | L19: {=IFERROR(IF(9>COUNTIF('DONNÉES BRUTES'!C$3:C$42,"Technologie"),"",INDEX('DONNÉES BRUTES'!P$3:P$42,MATCH(LARGE(IF('DONNÉES BRUTES'!C$3:C$42="Technologie",'DONNÉES BRUTES'!AB$3:AB$42+(ROW('DONNÉES BRUTES'!A$3:A$42)-ROW('DONNÉES BRUTES'!A$3))/1000,0),9),IF('DONNÉES BRUTES'!C$3:C$42="Technologie",'DONNÉES BRUTES'!AB$3:AB$42+(ROW('DONNÉES BRUTES'!A$3:A$42)-ROW('DONNÉES BRUTES'!A$3))/1000,0),0))),"—")} | M19: {=IFERROR(IF(9>COUNTIF('DONNÉES BRUTES'!C$3:C$42,"Technologie"),"",INDEX('DONNÉES BRUTES'!Q$3:Q$42,MATCH(LARGE(IF('DONNÉES BRUTES'!C$3:C$42="Technologie",'DONNÉES BRUTES'!AB$3:AB$42+(ROW('DONNÉES BRUTES'!A$3:A$42)-ROW('DONNÉES BRUTES'!A$3))/1000,0),9),IF('DONNÉES BRUTES'!C$3:C$42="Technologie",'DONNÉES BRUTES'!AB$3:AB$42+(ROW('DONNÉES BRUTES'!A$3:A$42)-ROW('DONNÉES BRUTES'!A$3))/1000,0),0))),"—")} | N19: {=IFERROR(IF(9>COUNTIF('DONNÉES BRUTES'!C$3:C$42,"Technologie"),"",INDEX('DONNÉES BRUTES'!S$3:S$42,MATCH(LARGE(IF('DONNÉES BRUTES'!C$3:C$42="Technologie",'DONNÉES BRUTES'!AB$3:AB$42+(ROW('DONNÉES BRUTES'!A$3:A$42)-ROW('DONNÉES BRUTES'!A$3))/1000,0),9),IF('DONNÉES BRUTES'!C$3:C$42="Technologie",'DONNÉES BRUTES'!AB$3:AB$42+(ROW('DONNÉES BRUTES'!A$3:A$42)-ROW('DONNÉES BRUTES'!A$3))/1000,0),0))),"—")} | O19: {=IFERROR(IF(9>COUNTIF('DONNÉES BRUTES'!C$3:C$42,"Technologie"),"",INDEX('DONNÉES BRUTES'!T$3:T$42,MATCH(LARGE(IF('DONNÉES BRUTES'!C$3:C$42="Technologie",'DONNÉES BRUTES'!AB$3:AB$42+(ROW('DONNÉES BRUTES'!A$3:A$42)-ROW('DONNÉES BRUTES'!A$3))/1000,0),9),IF('DONNÉES BRUTES'!C$3:C$42="Technologie",'DONNÉES BRUTES'!AB$3:AB$42+(ROW('DONNÉES BRUTES'!A$3:A$42)-ROW('DONNÉES BRUTES'!A$3))/1000,0),0))),"—")} | P19: {=IFERROR(IF(9>COUNTIF('DONNÉES BRUTES'!C$3:C$42,"Technologie"),"",INDEX('DONNÉES BRUTES'!U$3:U$42,MATCH(LARGE(IF('DONNÉES BRUTES'!C$3:C$42="Technologie",'DONNÉES BRUTES'!AB$3:AB$42+(ROW('DONNÉES BRUTES'!A$3:A$42)-ROW('DONNÉES BRUTES'!A$3))/1000,0),9),IF('DONNÉES BRUTES'!C$3:C$42="Technologie",'DONNÉES BRUTES'!AB$3:AB$42+(ROW('DONNÉES BRUTES'!A$3:A$42)-ROW('DONNÉES BRUTES'!A$3))/1000,0),0))),"—")} | Q19: {=IFERROR(IF(9>COUNTIF('DONNÉES BRUTES'!C$3:C$42,"Technologie"),"",INDEX('DONNÉES BRUTES'!AD$3:AD$42,MATCH(LARGE(IF('DONNÉES BRUTES'!C$3:C$42="Technologie",'DONNÉES BRUTES'!AB$3:AB$42+(ROW('DONNÉES BRUTES'!A$3:A$42)-ROW('DONNÉES BRUTES'!A$3))/1000,0),9),IF('DONNÉES BRUTES'!C$3:C$42="Technologie",'DONNÉES BRUTES'!AB$3:AB$42+(ROW('DONNÉES BRUTES'!A$3:A$42)-ROW('DONNÉES BRUTES'!A$3))/1000,0),0))),"—")}
C20: {=IFERROR(IF(10>COUNTIF('DONNÉES BRUTES'!C$3:C$42,"Technologie"),"",INDEX('DONNÉES BRUTES'!A$3:A$42,MATCH(LARGE(IF('DONNÉES BRUTES'!C$3:C$42="Technologie",'DONNÉES BRUTES'!AB$3:AB$42+(ROW('DONNÉES BRUTES'!A$3:A$42)-ROW('DONNÉES BRUTES'!A$3))/1000,0),10),IF('DONNÉES BRUTES'!C$3:C$42="Technologie",'DONNÉES BRUTES'!AB$3:AB$42+(ROW('DONNÉES BRUTES'!A$3:A$42)-ROW('DONNÉES BRUTES'!A$3))/1000,0),0))),"—")} | D20: {=IFERROR(IF(10>COUNTIF('DONNÉES BRUTES'!C$3:C$42,"Technologie"),"",INDEX('DONNÉES BRUTES'!B$3:B$42,MATCH(LARGE(IF('DONNÉES BRUTES'!C$3:C$42="Technologie",'DONNÉES BRUTES'!AB$3:AB$42+(ROW('DONNÉES BRUTES'!A$3:A$42)-ROW('DONNÉES BRUTES'!A$3))/1000,0),10),IF('DONNÉES BRUTES'!C$3:C$42="Technologie",'DONNÉES BRUTES'!AB$3:AB$42+(ROW('DONNÉES BRUTES'!A$3:A$42)-ROW('DONNÉES BRUTES'!A$3))/1000,0),0))),"—")} | E20: {=IFERROR(IF(10>COUNTIF('DONNÉES BRUTES'!C$3:C$42,"Technologie"),"",INT(LARGE(IF('DONNÉES BRUTES'!C$3:C$42="Technologie",'DONNÉES BRUTES'!AB$3:AB$42+(ROW('DONNÉES BRUTES'!A$3:A$42)-ROW('DONNÉES BRUTES'!A$3))/1000,0),10))&"/100"),"—")} | F20: {=IFERROR(IF(10>COUNTIF('DONNÉES BRUTES'!C$3:C$42,"Technologie"),"",INDEX('DONNÉES BRUTES'!Y$3:Y$42,MATCH(LARGE(IF('DONNÉES BRUTES'!C$3:C$42="Technologie",'DONNÉES BRUTES'!AB$3:AB$42+(ROW('DONNÉES BRUTES'!A$3:A$42)-ROW('DONNÉES BRUTES'!A$3))/1000,0),10),IF('DONNÉES BRUTES'!C$3:C$42="Technologie",'DONNÉES BRUTES'!AB$3:AB$42+(ROW('DONNÉES BRUTES'!A$3:A$42)-ROW('DONNÉES BRUTES'!A$3))/1000,0),0))),"—")} | G20: {=IFERROR(IF(10>COUNTIF('DONNÉES BRUTES'!C$3:C$42,"Technologie"),"",INDEX('DONNÉES BRUTES'!Z$3:Z$42,MATCH(LARGE(IF('DONNÉES BRUTES'!C$3:C$42="Technologie",'DONNÉES BRUTES'!AB$3:AB$42+(ROW('DONNÉES BRUTES'!A$3:A$42)-ROW('DONNÉES BRUTES'!A$3))/1000,0),10),IF('DONNÉES BRUTES'!C$3:C$42="Technologie",'DONNÉES BRUTES'!AB$3:AB$42+(ROW('DONNÉES BRUTES'!A$3:A$42)-ROW('DONNÉES BRUTES'!A$3))/1000,0),0))),"—")} | H20: {=IFERROR(IF(10>COUNTIF('DONNÉES BRUTES'!C$3:C$42,"Technologie"),"",INDEX('DONNÉES BRUTES'!AA$3:AA$42,MATCH(LARGE(IF('DONNÉES BRUTES'!C$3:C$42="Technologie",'DONNÉES BRUTES'!AB$3:AB$42+(ROW('DONNÉES BRUTES'!A$3:A$42)-ROW('DONNÉES BRUTES'!A$3))/1000,0),10),IF('DONNÉES BRUTES'!C$3:C$42="Technologie",'DONNÉES BRUTES'!AB$3:AB$42+(ROW('DONNÉES BRUTES'!A$3:A$42)-ROW('DONNÉES BRUTES'!A$3))/1000,0),0))),"—")} | I20: {=IFERROR(IF(10>COUNTIF('DONNÉES BRUTES'!C$3:C$42,"Technologie"),"",INDEX('DONNÉES BRUTES'!M$3:M$42,MATCH(LARGE(IF('DONNÉES BRUTES'!C$3:C$42="Technologie",'DONNÉES BRUTES'!AB$3:AB$42+(ROW('DONNÉES BRUTES'!A$3:A$42)-ROW('DONNÉES BRUTES'!A$3))/1000,0),10),IF('DONNÉES BRUTES'!C$3:C$42="Technologie",'DONNÉES BRUTES'!AB$3:AB$42+(ROW('DONNÉES BRUTES'!A$3:A$42)-ROW('DONNÉES BRUTES'!A$3))/1000,0),0))),"—")} | J20: {=IFERROR(IF(10>COUNTIF('DONNÉES BRUTES'!C$3:C$42,"Technologie"),"",INDEX('DONNÉES BRUTES'!N$3:N$42,MATCH(LARGE(IF('DONNÉES BRUTES'!C$3:C$42="Technologie",'DONNÉES BRUTES'!AB$3:AB$42+(ROW('DONNÉES BRUTES'!A$3:A$42)-ROW('DONNÉES BRUTES'!A$3))/1000,0),10),IF('DONNÉES BRUTES'!C$3:C$42="Technologie",'DONNÉES BRUTES'!AB$3:AB$42+(ROW('DONNÉES BRUTES'!A$3:A$42)-ROW('DONNÉES BRUTES'!A$3))/1000,0),0))),"—")} | K20: {=IFERROR(IF(10>COUNTIF('DONNÉES BRUTES'!C$3:C$42,"Technologie"),"",INDEX('DONNÉES BRUTES'!O$3:O$42,MATCH(LARGE(IF('DONNÉES BRUTES'!C$3:C$42="Technologie",'DONNÉES BRUTES'!AB$3:AB$42+(ROW('DONNÉES BRUTES'!A$3:A$42)-ROW('DONNÉES BRUTES'!A$3))/1000,0),10),IF('DONNÉES BRUTES'!C$3:C$42="Technologie",'DONNÉES BRUTES'!AB$3:AB$42+(ROW('DONNÉES BRUTES'!A$3:A$42)-ROW('DONNÉES BRUTES'!A$3))/1000,0),0))),"—")} | L20: {=IFERROR(IF(10>COUNTIF('DONNÉES BRUTES'!C$3:C$42,"Technologie"),"",INDEX('DONNÉES BRUTES'!P$3:P$42,MATCH(LARGE(IF('DONNÉES BRUTES'!C$3:C$42="Technologie",'DONNÉES BRUTES'!AB$3:AB$42+(ROW('DONNÉES BRUTES'!A$3:A$42)-ROW('DONNÉES BRUTES'!A$3))/1000,0),10),IF('DONNÉES BRUTES'!C$3:C$42="Technologie",'DONNÉES BRUTES'!AB$3:AB$42+(ROW('DONNÉES BRUTES'!A$3:A$42)-ROW('DONNÉES BRUTES'!A$3))/1000,0),0))),"—")} | M20: {=IFERROR(IF(10>COUNTIF('DONNÉES BRUTES'!C$3:C$42,"Technologie"),"",INDEX('DONNÉES BRUTES'!Q$3:Q$42,MATCH(LARGE(IF('DONNÉES BRUTES'!C$3:C$42="Technologie",'DONNÉES BRUTES'!AB$3:AB$42+(ROW('DONNÉES BRUTES'!A$3:A$42)-ROW('DONNÉES BRUTES'!A$3))/1000,0),10),IF('DONNÉES BRUTES'!C$3:C$42="Technologie",'DONNÉES BRUTES'!AB$3:AB$42+(ROW('DONNÉES BRUTES'!A$3:A$42)-ROW('DONNÉES BRUTES'!A$3))/1000,0),0))),"—")} | N20: {=IFERROR(IF(10>COUNTIF('DONNÉES BRUTES'!C$3:C$42,"Technologie"),"",INDEX('DONNÉES BRUTES'!S$3:S$42,MATCH(LARGE(IF('DONNÉES BRUTES'!C$3:C$42="Technologie",'DONNÉES BRUTES'!AB$3:AB$42+(ROW('DONNÉES BRUTES'!A$3:A$42)-ROW('DONNÉES BRUTES'!A$3))/1000,0),10),IF('DONNÉES BRUTES'!C$3:C$42="Technologie",'DONNÉES BRUTES'!AB$3:AB$42+(ROW('DONNÉES BRUTES'!A$3:A$42)-ROW('DONNÉES BRUTES'!A$3))/1000,0),0))),"—")} | O20: {=IFERROR(IF(10>COUNTIF('DONNÉES BRUTES'!C$3:C$42,"Technologie"),"",INDEX('DONNÉES BRUTES'!T$3:T$42,MATCH(LARGE(IF('DONNÉES BRUTES'!C$3:C$42="Technologie",'DONNÉES BRUTES'!AB$3:AB$42+(ROW('DONNÉES BRUTES'!A$3:A$42)-ROW('DONNÉES BRUTES'!A$3))/1000,0),10),IF('DONNÉES BRUTES'!C$3:C$42="Technologie",'DONNÉES BRUTES'!AB$3:AB$42+(ROW('DONNÉES BRUTES'!A$3:A$42)-ROW('DONNÉES BRUTES'!A$3))/1000,0),0))),"—")} | P20: {=IFERROR(IF(10>COUNTIF('DONNÉES BRUTES'!C$3:C$42,"Technologie"),"",INDEX('DONNÉES BRUTES'!U$3:U$42,MATCH(LARGE(IF('DONNÉES BRUTES'!C$3:C$42="Technologie",'DONNÉES BRUTES'!AB$3:AB$42+(ROW('DONNÉES BRUTES'!A$3:A$42)-ROW('DONNÉES BRUTES'!A$3))/1000,0),10),IF('DONNÉES BRUTES'!C$3:C$42="Technologie",'DONNÉES BRUTES'!AB$3:AB$42+(ROW('DONNÉES BRUTES'!A$3:A$42)-ROW('DONNÉES BRUTES'!A$3))/1000,0),0))),"—")} | Q20: {=IFERROR(IF(10>COUNTIF('DONNÉES BRUTES'!C$3:C$42,"Technologie"),"",INDEX('DONNÉES BRUTES'!AD$3:AD$42,MATCH(LARGE(IF('DONNÉES BRUTES'!C$3:C$42="Technologie",'DONNÉES BRUTES'!AB$3:AB$42+(ROW('DONNÉES BRUTES'!A$3:A$42)-ROW('DONNÉES BRUTES'!A$3))/1000,0),10),IF('DONNÉES BRUTES'!C$3:C$42="Technologie",'DONNÉES BRUTES'!AB$3:AB$42+(ROW('DONNÉES BRUTES'!A$3:A$42)-ROW('DONNÉES BRUTES'!A$3))/1000,0),0))),"—")}
C21: {=IFERROR(IF(11>COUNTIF('DONNÉES BRUTES'!C$3:C$42,"Technologie"),"",INDEX('DONNÉES BRUTES'!A$3:A$42,MATCH(LARGE(IF('DONNÉES BRUTES'!C$3:C$42="Technologie",'DONNÉES BRUTES'!AB$3:AB$42+(ROW('DONNÉES BRUTES'!A$3:A$42)-ROW('DONNÉES BRUTES'!A$3))/1000,0),11),IF('DONNÉES BRUTES'!C$3:C$42="Technologie",'DONNÉES BRUTES'!AB$3:AB$42+(ROW('DONNÉES BRUTES'!A$3:A$42)-ROW('DONNÉES BRUTES'!A$3))/1000,0),0))),"—")} | D21: {=IFERROR(IF(11>COUNTIF('DONNÉES BRUTES'!C$3:C$42,"Technologie"),"",INDEX('DONNÉES BRUTES'!B$3:B$42,MATCH(LARGE(IF('DONNÉES BRUTES'!C$3:C$42="Technologie",'DONNÉES BRUTES'!AB$3:AB$42+(ROW('DONNÉES BRUTES'!A$3:A$42)-ROW('DONNÉES BRUTES'!A$3))/1000,0),11),IF('DONNÉES BRUTES'!C$3:C$42="Technologie",'DONNÉES BRUTES'!AB$3:AB$42+(ROW('DONNÉES BRUTES'!A$3:A$42)-ROW('DONNÉES BRUTES'!A$3))/1000,0),0))),"—")} | E21: {=IFERROR(IF(11>COUNTIF('DONNÉES BRUTES'!C$3:C$42,"Technologie"),"",INT(LARGE(IF('DONNÉES BRUTES'!C$3:C$42="Technologie",'DONNÉES BRUTES'!AB$3:AB$42+(ROW('DONNÉES BRUTES'!A$3:A$42)-ROW('DONNÉES BRUTES'!A$3))/1000,0),11))&"/100"),"—")} | F21: {=IFERROR(IF(11>COUNTIF('DONNÉES BRUTES'!C$3:C$42,"Technologie"),"",INDEX('DONNÉES BRUTES'!Y$3:Y$42,MATCH(LARGE(IF('DONNÉES BRUTES'!C$3:C$42="Technologie",'DONNÉES BRUTES'!AB$3:AB$42+(ROW('DONNÉES BRUTES'!A$3:A$42)-ROW('DONNÉES BRUTES'!A$3))/1000,0),11),IF('DONNÉES BRUTES'!C$3:C$42="Technologie",'DONNÉES BRUTES'!AB$3:AB$42+(ROW('DONNÉES BRUTES'!A$3:A$42)-ROW('DONNÉES BRUTES'!A$3))/1000,0),0))),"—")} | G21: {=IFERROR(IF(11>COUNTIF('DONNÉES BRUTES'!C$3:C$42,"Technologie"),"",INDEX('DONNÉES BRUTES'!Z$3:Z$42,MATCH(LARGE(IF('DONNÉES BRUTES'!C$3:C$42="Technologie",'DONNÉES BRUTES'!AB$3:AB$42+(ROW('DONNÉES BRUTES'!A$3:A$42)-ROW('DONNÉES BRUTES'!A$3))/1000,0),11),IF('DONNÉES BRUTES'!C$3:C$42="Technologie",'DONNÉES BRUTES'!AB$3:AB$42+(ROW('DONNÉES BRUTES'!A$3:A$42)-ROW('DONNÉES BRUTES'!A$3))/1000,0),0))),"—")} | H21: {=IFERROR(IF(11>COUNTIF('DONNÉES BRUTES'!C$3:C$42,"Technologie"),"",INDEX('DONNÉES BRUTES'!AA$3:AA$42,MATCH(LARGE(IF('DONNÉES BRUTES'!C$3:C$42="Technologie",'DONNÉES BRUTES'!AB$3:AB$42+(ROW('DONNÉES BRUTES'!A$3:A$42)-ROW('DONNÉES BRUTES'!A$3))/1000,0),11),IF('DONNÉES BRUTES'!C$3:C$42="Technologie",'DONNÉES BRUTES'!AB$3:AB$42+(ROW('DONNÉES BRUTES'!A$3:A$42)-ROW('DONNÉES BRUTES'!A$3))/1000,0),0))),"—")} | I21: {=IFERROR(IF(11>COUNTIF('DONNÉES BRUTES'!C$3:C$42,"Technologie"),"",INDEX('DONNÉES BRUTES'!M$3:M$42,MATCH(LARGE(IF('DONNÉES BRUTES'!C$3:C$42="Technologie",'DONNÉES BRUTES'!AB$3:AB$42+(ROW('DONNÉES BRUTES'!A$3:A$42)-ROW('DONNÉES BRUTES'!A$3))/1000,0),11),IF('DONNÉES BRUTES'!C$3:C$42="Technologie",'DONNÉES BRUTES'!AB$3:AB$42+(ROW('DONNÉES BRUTES'!A$3:A$42)-ROW('DONNÉES BRUTES'!A$3))/1000,0),0))),"—")} | J21: {=IFERROR(IF(11>COUNTIF('DONNÉES BRUTES'!C$3:C$42,"Technologie"),"",INDEX('DONNÉES BRUTES'!N$3:N$42,MATCH(LARGE(IF('DONNÉES BRUTES'!C$3:C$42="Technologie",'DONNÉES BRUTES'!AB$3:AB$42+(ROW('DONNÉES BRUTES'!A$3:A$42)-ROW('DONNÉES BRUTES'!A$3))/1000,0),11),IF('DONNÉES BRUTES'!C$3:C$42="Technologie",'DONNÉES BRUTES'!AB$3:AB$42+(ROW('DONNÉES BRUTES'!A$3:A$42)-ROW('DONNÉES BRUTES'!A$3))/1000,0),0))),"—")} | K21: {=IFERROR(IF(11>COUNTIF('DONNÉES BRUTES'!C$3:C$42,"Technologie"),"",INDEX('DONNÉES BRUTES'!O$3:O$42,MATCH(LARGE(IF('DONNÉES BRUTES'!C$3:C$42="Technologie",'DONNÉES BRUTES'!AB$3:AB$42+(ROW('DONNÉES BRUTES'!A$3:A$42)-ROW('DONNÉES BRUTES'!A$3))/1000,0),11),IF('DONNÉES BRUTES'!C$3:C$42="Technologie",'DONNÉES BRUTES'!AB$3:AB$42+(ROW('DONNÉES BRUTES'!A$3:A$42)-ROW('DONNÉES BRUTES'!A$3))/1000,0),0))),"—")} | L21: {=IFERROR(IF(11>COUNTIF('DONNÉES BRUTES'!C$3:C$42,"Technologie"),"",INDEX('DONNÉES BRUTES'!P$3:P$42,MATCH(LARGE(IF('DONNÉES BRUTES'!C$3:C$42="Technologie",'DONNÉES BRUTES'!AB$3:AB$42+(ROW('DONNÉES BRUTES'!A$3:A$42)-ROW('DONNÉES BRUTES'!A$3))/1000,0),11),IF('DONNÉES BRUTES'!C$3:C$42="Technologie",'DONNÉES BRUTES'!AB$3:AB$42+(ROW('DONNÉES BRUTES'!A$3:A$42)-ROW('DONNÉES BRUTES'!A$3))/1000,0),0))),"—")} | M21: {=IFERROR(IF(11>COUNTIF('DONNÉES BRUTES'!C$3:C$42,"Technologie"),"",INDEX('DONNÉES BRUTES'!Q$3:Q$42,MATCH(LARGE(IF('DONNÉES BRUTES'!C$3:C$42="Technologie",'DONNÉES BRUTES'!AB$3:AB$42+(ROW('DONNÉES BRUTES'!A$3:A$42)-ROW('DONNÉES BRUTES'!A$3))/1000,0),11),IF('DONNÉES BRUTES'!C$3:C$42="Technologie",'DONNÉES BRUTES'!AB$3:AB$42+(ROW('DONNÉES BRUTES'!A$3:A$42)-ROW('DONNÉES BRUTES'!A$3))/1000,0),0))),"—")} | N21: {=IFERROR(IF(11>COUNTIF('DONNÉES BRUTES'!C$3:C$42,"Technologie"),"",INDEX('DONNÉES BRUTES'!S$3:S$42,MATCH(LARGE(IF('DONNÉES BRUTES'!C$3:C$42="Technologie",'DONNÉES BRUTES'!AB$3:AB$42+(ROW('DONNÉES BRUTES'!A$3:A$42)-ROW('DONNÉES BRUTES'!A$3))/1000,0),11),IF('DONNÉES BRUTES'!C$3:C$42="Technologie",'DONNÉES BRUTES'!AB$3:AB$42+(ROW('DONNÉES BRUTES'!A$3:A$42)-ROW('DONNÉES BRUTES'!A$3))/1000,0),0))),"—")} | O21: {=IFERROR(IF(11>COUNTIF('DONNÉES BRUTES'!C$3:C$42,"Technologie"),"",INDEX('DONNÉES BRUTES'!T$3:T$42,MATCH(LARGE(IF('DONNÉES BRUTES'!C$3:C$42="Technologie",'DONNÉES BRUTES'!AB$3:AB$42+(ROW('DONNÉES BRUTES'!A$3:A$42)-ROW('DONNÉES BRUTES'!A$3))/1000,0),11),IF('DONNÉES BRUTES'!C$3:C$42="Technologie",'DONNÉES BRUTES'!AB$3:AB$42+(ROW('DONNÉES BRUTES'!A$3:A$42)-ROW('DONNÉES BRUTES'!A$3))/1000,0),0))),"—")} | P21: {=IFERROR(IF(11>COUNTIF('DONNÉES BRUTES'!C$3:C$42,"Technologie"),"",INDEX('DONNÉES BRUTES'!U$3:U$42,MATCH(LARGE(IF('DONNÉES BRUTES'!C$3:C$42="Technologie",'DONNÉES BRUTES'!AB$3:AB$42+(ROW('DONNÉES BRUTES'!A$3:A$42)-ROW('DONNÉES BRUTES'!A$3))/1000,0),11),IF('DONNÉES BRUTES'!C$3:C$42="Technologie",'DONNÉES BRUTES'!AB$3:AB$42+(ROW('DONNÉES BRUTES'!A$3:A$42)-ROW('DONNÉES BRUTES'!A$3))/1000,0),0))),"—")} | Q21: {=IFERROR(IF(11>COUNTIF('DONNÉES BRUTES'!C$3:C$42,"Technologie"),"",INDEX('DONNÉES BRUTES'!AD$3:AD$42,MATCH(LARGE(IF('DONNÉES BRUTES'!C$3:C$42="Technologie",'DONNÉES BRUTES'!AB$3:AB$42+(ROW('DONNÉES BRUTES'!A$3:A$42)-ROW('DONNÉES BRUTES'!A$3))/1000,0),11),IF('DONNÉES BRUTES'!C$3:C$42="Technologie",'DONNÉES BRUTES'!AB$3:AB$42+(ROW('DONNÉES BRUTES'!A$3:A$42)-ROW('DONNÉES BRUTES'!A$3))/1000,0),0))),"—")}
C22: {=IFERROR(IF(12>COUNTIF('DONNÉES BRUTES'!C$3:C$42,"Technologie"),"",INDEX('DONNÉES BRUTES'!A$3:A$42,MATCH(LARGE(IF('DONNÉES BRUTES'!C$3:C$42="Technologie",'DONNÉES BRUTES'!AB$3:AB$42+(ROW('DONNÉES BRUTES'!A$3:A$42)-ROW('DONNÉES BRUTES'!A$3))/1000,0),12),IF('DONNÉES BRUTES'!C$3:C$42="Technologie",'DONNÉES BRUTES'!AB$3:AB$42+(ROW('DONNÉES BRUTES'!A$3:A$42)-ROW('DONNÉES BRUTES'!A$3))/1000,0),0))),"—")} | D22: {=IFERROR(IF(12>COUNTIF('DONNÉES BRUTES'!C$3:C$42,"Technologie"),"",INDEX('DONNÉES BRUTES'!B$3:B$42,MATCH(LARGE(IF('DONNÉES BRUTES'!C$3:C$42="Technologie",'DONNÉES BRUTES'!AB$3:AB$42+(ROW('DONNÉES BRUTES'!A$3:A$42)-ROW('DONNÉES BRUTES'!A$3))/1000,0),12),IF('DONNÉES BRUTES'!C$3:C$42="Technologie",'DONNÉES BRUTES'!AB$3:AB$42+(ROW('DONNÉES BRUTES'!A$3:A$42)-ROW('DONNÉES BRUTES'!A$3))/1000,0),0))),"—")} | E22: {=IFERROR(IF(12>COUNTIF('DONNÉES BRUTES'!C$3:C$42,"Technologie"),"",INT(LARGE(IF('DONNÉES BRUTES'!C$3:C$42="Technologie",'DONNÉES BRUTES'!AB$3:AB$42+(ROW('DONNÉES BRUTES'!A$3:A$42)-ROW('DONNÉES BRUTES'!A$3))/1000,0),12))&"/100"),"—")} | F22: {=IFERROR(IF(12>COUNTIF('DONNÉES BRUTES'!C$3:C$42,"Technologie"),"",INDEX('DONNÉES BRUTES'!Y$3:Y$42,MATCH(LARGE(IF('DONNÉES BRUTES'!C$3:C$42="Technologie",'DONNÉES BRUTES'!AB$3:AB$42+(ROW('DONNÉES BRUTES'!A$3:A$42)-ROW('DONNÉES BRUTES'!A$3))/1000,0),12),IF('DONNÉES BRUTES'!C$3:C$42="Technologie",'DONNÉES BRUTES'!AB$3:AB$42+(ROW('DONNÉES BRUTES'!A$3:A$42)-ROW('DONNÉES BRUTES'!A$3))/1000,0),0))),"—")} | G22: {=IFERROR(IF(12>COUNTIF('DONNÉES BRUTES'!C$3:C$42,"Technologie"),"",INDEX('DONNÉES BRUTES'!Z$3:Z$42,MATCH(LARGE(IF('DONNÉES BRUTES'!C$3:C$42="Technologie",'DONNÉES BRUTES'!AB$3:AB$42+(ROW('DONNÉES BRUTES'!A$3:A$42)-ROW('DONNÉES BRUTES'!A$3))/1000,0),12),IF('DONNÉES BRUTES'!C$3:C$42="Technologie",'DONNÉES BRUTES'!AB$3:AB$42+(ROW('DONNÉES BRUTES'!A$3:A$42)-ROW('DONNÉES BRUTES'!A$3))/1000,0),0))),"—")} | H22: {=IFERROR(IF(12>COUNTIF('DONNÉES BRUTES'!C$3:C$42,"Technologie"),"",INDEX('DONNÉES BRUTES'!AA$3:AA$42,MATCH(LARGE(IF('DONNÉES BRUTES'!C$3:C$42="Technologie",'DONNÉES BRUTES'!AB$3:AB$42+(ROW('DONNÉES BRUTES'!A$3:A$42)-ROW('DONNÉES BRUTES'!A$3))/1000,0),12),IF('DONNÉES BRUTES'!C$3:C$42="Technologie",'DONNÉES BRUTES'!AB$3:AB$42+(ROW('DONNÉES BRUTES'!A$3:A$42)-ROW('DONNÉES BRUTES'!A$3))/1000,0),0))),"—")} | I22: {=IFERROR(IF(12>COUNTIF('DONNÉES BRUTES'!C$3:C$42,"Technologie"),"",INDEX('DONNÉES BRUTES'!M$3:M$42,MATCH(LARGE(IF('DONNÉES BRUTES'!C$3:C$42="Technologie",'DONNÉES BRUTES'!AB$3:AB$42+(ROW('DONNÉES BRUTES'!A$3:A$42)-ROW('DONNÉES BRUTES'!A$3))/1000,0),12),IF('DONNÉES BRUTES'!C$3:C$42="Technologie",'DONNÉES BRUTES'!AB$3:AB$42+(ROW('DONNÉES BRUTES'!A$3:A$42)-ROW('DONNÉES BRUTES'!A$3))/1000,0),0))),"—")} | J22: {=IFERROR(IF(12>COUNTIF('DONNÉES BRUTES'!C$3:C$42,"Technologie"),"",INDEX('DONNÉES BRUTES'!N$3:N$42,MATCH(LARGE(IF('DONNÉES BRUTES'!C$3:C$42="Technologie",'DONNÉES BRUTES'!AB$3:AB$42+(ROW('DONNÉES BRUTES'!A$3:A$42)-ROW('DONNÉES BRUTES'!A$3))/1000,0),12),IF('DONNÉES BRUTES'!C$3:C$42="Technologie",'DONNÉES BRUTES'!AB$3:AB$42+(ROW('DONNÉES BRUTES'!A$3:A$42)-ROW('DONNÉES BRUTES'!A$3))/1000,0),0))),"—")} | K22: {=IFERROR(IF(12>COUNTIF('DONNÉES BRUTES'!C$3:C$42,"Technologie"),"",INDEX('DONNÉES BRUTES'!O$3:O$42,MATCH(LARGE(IF('DONNÉES BRUTES'!C$3:C$42="Technologie",'DONNÉES BRUTES'!AB$3:AB$42+(ROW('DONNÉES BRUTES'!A$3:A$42)-ROW('DONNÉES BRUTES'!A$3))/1000,0),12),IF('DONNÉES BRUTES'!C$3:C$42="Technologie",'DONNÉES BRUTES'!AB$3:AB$42+(ROW('DONNÉES BRUTES'!A$3:A$42)-ROW('DONNÉES BRUTES'!A$3))/1000,0),0))),"—")} | L22: {=IFERROR(IF(12>COUNTIF('DONNÉES BRUTES'!C$3:C$42,"Technologie"),"",INDEX('DONNÉES BRUTES'!P$3:P$42,MATCH(LARGE(IF('DONNÉES BRUTES'!C$3:C$42="Technologie",'DONNÉES BRUTES'!AB$3:AB$42+(ROW('DONNÉES BRUTES'!A$3:A$42)-ROW('DONNÉES BRUTES'!A$3))/1000,0),12),IF('DONNÉES BRUTES'!C$3:C$42="Technologie",'DONNÉES BRUTES'!AB$3:AB$42+(ROW('DONNÉES BRUTES'!A$3:A$42)-ROW('DONNÉES BRUTES'!A$3))/1000,0),0))),"—")} | M22: {=IFERROR(IF(12>COUNTIF('DONNÉES BRUTES'!C$3:C$42,"Technologie"),"",INDEX('DONNÉES BRUTES'!Q$3:Q$42,MATCH(LARGE(IF('DONNÉES BRUTES'!C$3:C$42="Technologie",'DONNÉES BRUTES'!AB$3:AB$42+(ROW('DONNÉES BRUTES'!A$3:A$42)-ROW('DONNÉES BRUTES'!A$3))/1000,0),12),IF('DONNÉES BRUTES'!C$3:C$42="Technologie",'DONNÉES BRUTES'!AB$3:AB$42+(ROW('DONNÉES BRUTES'!A$3:A$42)-ROW('DONNÉES BRUTES'!A$3))/1000,0),0))),"—")} | N22: {=IFERROR(IF(12>COUNTIF('DONNÉES BRUTES'!C$3:C$42,"Technologie"),"",INDEX('DONNÉES BRUTES'!S$3:S$42,MATCH(LARGE(IF('DONNÉES BRUTES'!C$3:C$42="Technologie",'DONNÉES BRUTES'!AB$3:AB$42+(ROW('DONNÉES BRUTES'!A$3:A$42)-ROW('DONNÉES BRUTES'!A$3))/1000,0),12),IF('DONNÉES BRUTES'!C$3:C$42="Technologie",'DONNÉES BRUTES'!AB$3:AB$42+(ROW('DONNÉES BRUTES'!A$3:A$42)-ROW('DONNÉES BRUTES'!A$3))/1000,0),0))),"—")} | O22: {=IFERROR(IF(12>COUNTIF('DONNÉES BRUTES'!C$3:C$42,"Technologie"),"",INDEX('DONNÉES BRUTES'!T$3:T$42,MATCH(LARGE(IF('DONNÉES BRUTES'!C$3:C$42="Technologie",'DONNÉES BRUTES'!AB$3:AB$42+(ROW('DONNÉES BRUTES'!A$3:A$42)-ROW('DONNÉES BRUTES'!A$3))/1000,0),12),IF('DONNÉES BRUTES'!C$3:C$42="Technologie",'DONNÉES BRUTES'!AB$3:AB$42+(ROW('DONNÉES BRUTES'!A$3:A$42)-ROW('DONNÉES BRUTES'!A$3))/1000,0),0))),"—")} | P22: {=IFERROR(IF(12>COUNTIF('DONNÉES BRUTES'!C$3:C$42,"Technologie"),"",INDEX('DONNÉES BRUTES'!U$3:U$42,MATCH(LARGE(IF('DONNÉES BRUTES'!C$3:C$42="Technologie",'DONNÉES BRUTES'!AB$3:AB$42+(ROW('DONNÉES BRUTES'!A$3:A$42)-ROW('DONNÉES BRUTES'!A$3))/1000,0),12),IF('DONNÉES BRUTES'!C$3:C$42="Technologie",'DONNÉES BRUTES'!AB$3:AB$42+(ROW('DONNÉES BRUTES'!A$3:A$42)-ROW('DONNÉES BRUTES'!A$3))/1000,0),0))),"—")} | Q22: {=IFERROR(IF(12>COUNTIF('DONNÉES BRUTES'!C$3:C$42,"Technologie"),"",INDEX('DONNÉES BRUTES'!AD$3:AD$42,MATCH(LARGE(IF('DONNÉES BRUTES'!C$3:C$42="Technologie",'DONNÉES BRUTES'!AB$3:AB$42+(ROW('DONNÉES BRUTES'!A$3:A$42)-ROW('DONNÉES BRUTES'!A$3))/1000,0),12),IF('DONNÉES BRUTES'!C$3:C$42="Technologie",'DONNÉES BRUTES'!AB$3:AB$42+(ROW('DONNÉES BRUTES'!A$3:A$42)-ROW('DONNÉES BRUTES'!A$3))/1000,0),0))),"—")}
C23: {=IFERROR(IF(13>COUNTIF('DONNÉES BRUTES'!C$3:C$42,"Technologie"),"",INDEX('DONNÉES BRUTES'!A$3:A$42,MATCH(LARGE(IF('DONNÉES BRUTES'!C$3:C$42="Technologie",'DONNÉES BRUTES'!AB$3:AB$42+(ROW('DONNÉES BRUTES'!A$3:A$42)-ROW('DONNÉES BRUTES'!A$3))/1000,0),13),IF('DONNÉES BRUTES'!C$3:C$42="Technologie",'DONNÉES BRUTES'!AB$3:AB$42+(ROW('DONNÉES BRUTES'!A$3:A$42)-ROW('DONNÉES BRUTES'!A$3))/1000,0),0))),"—")} | D23: {=IFERROR(IF(13>COUNTIF('DONNÉES BRUTES'!C$3:C$42,"Technologie"),"",INDEX('DONNÉES BRUTES'!B$3:B$42,MATCH(LARGE(IF('DONNÉES BRUTES'!C$3:C$42="Technologie",'DONNÉES BRUTES'!AB$3:AB$42+(ROW('DONNÉES BRUTES'!A$3:A$42)-ROW('DONNÉES BRUTES'!A$3))/1000,0),13),IF('DONNÉES BRUTES'!C$3:C$42="Technologie",'DONNÉES BRUTES'!AB$3:AB$42+(ROW('DONNÉES BRUTES'!A$3:A$42)-ROW('DONNÉES BRUTES'!A$3))/1000,0),0))),"—")} | E23: {=IFERROR(IF(13>COUNTIF('DONNÉES BRUTES'!C$3:C$42,"Technologie"),"",INT(LARGE(IF('DONNÉES BRUTES'!C$3:C$42="Technologie",'DONNÉES BRUTES'!AB$3:AB$42+(ROW('DONNÉES BRUTES'!A$3:A$42)-ROW('DONNÉES BRUTES'!A$3))/1000,0),13))&"/100"),"—")} | F23: {=IFERROR(IF(13>COUNTIF('DONNÉES BRUTES'!C$3:C$42,"Technologie"),"",INDEX('DONNÉES BRUTES'!Y$3:Y$42,MATCH(LARGE(IF('DONNÉES BRUTES'!C$3:C$42="Technologie",'DONNÉES BRUTES'!AB$3:AB$42+(ROW('DONNÉES BRUTES'!A$3:A$42)-ROW('DONNÉES BRUTES'!A$3))/1000,0),13),IF('DONNÉES BRUTES'!C$3:C$42="Technologie",'DONNÉES BRUTES'!AB$3:AB$42+(ROW('DONNÉES BRUTES'!A$3:A$42)-ROW('DONNÉES BRUTES'!A$3))/1000,0),0))),"—")} | G23: {=IFERROR(IF(13>COUNTIF('DONNÉES BRUTES'!C$3:C$42,"Technologie"),"",INDEX('DONNÉES BRUTES'!Z$3:Z$42,MATCH(LARGE(IF('DONNÉES BRUTES'!C$3:C$42="Technologie",'DONNÉES BRUTES'!AB$3:AB$42+(ROW('DONNÉES BRUTES'!A$3:A$42)-ROW('DONNÉES BRUTES'!A$3))/1000,0),13),IF('DONNÉES BRUTES'!C$3:C$42="Technologie",'DONNÉES BRUTES'!AB$3:AB$42+(ROW('DONNÉES BRUTES'!A$3:A$42)-ROW('DONNÉES BRUTES'!A$3))/1000,0),0))),"—")} | H23: {=IFERROR(IF(13>COUNTIF('DONNÉES BRUTES'!C$3:C$42,"Technologie"),"",INDEX('DONNÉES BRUTES'!AA$3:AA$42,MATCH(LARGE(IF('DONNÉES BRUTES'!C$3:C$42="Technologie",'DONNÉES BRUTES'!AB$3:AB$42+(ROW('DONNÉES BRUTES'!A$3:A$42)-ROW('DONNÉES BRUTES'!A$3))/1000,0),13),IF('DONNÉES BRUTES'!C$3:C$42="Technologie",'DONNÉES BRUTES'!AB$3:AB$42+(ROW('DONNÉES BRUTES'!A$3:A$42)-ROW('DONNÉES BRUTES'!A$3))/1000,0),0))),"—")} | I23: {=IFERROR(IF(13>COUNTIF('DONNÉES BRUTES'!C$3:C$42,"Technologie"),"",INDEX('DONNÉES BRUTES'!M$3:M$42,MATCH(LARGE(IF('DONNÉES BRUTES'!C$3:C$42="Technologie",'DONNÉES BRUTES'!AB$3:AB$42+(ROW('DONNÉES BRUTES'!A$3:A$42)-ROW('DONNÉES BRUTES'!A$3))/1000,0),13),IF('DONNÉES BRUTES'!C$3:C$42="Technologie",'DONNÉES BRUTES'!AB$3:AB$42+(ROW('DONNÉES BRUTES'!A$3:A$42)-ROW('DONNÉES BRUTES'!A$3))/1000,0),0))),"—")} | J23: {=IFERROR(IF(13>COUNTIF('DONNÉES BRUTES'!C$3:C$42,"Technologie"),"",INDEX('DONNÉES BRUTES'!N$3:N$42,MATCH(LARGE(IF('DONNÉES BRUTES'!C$3:C$42="Technologie",'DONNÉES BRUTES'!AB$3:AB$42+(ROW('DONNÉES BRUTES'!A$3:A$42)-ROW('DONNÉES BRUTES'!A$3))/1000,0),13),IF('DONNÉES BRUTES'!C$3:C$42="Technologie",'DONNÉES BRUTES'!AB$3:AB$42+(ROW('DONNÉES BRUTES'!A$3:A$42)-ROW('DONNÉES BRUTES'!A$3))/1000,0),0))),"—")} | K23: {=IFERROR(IF(13>COUNTIF('DONNÉES BRUTES'!C$3:C$42,"Technologie"),"",INDEX('DONNÉES BRUTES'!O$3:O$42,MATCH(LARGE(IF('DONNÉES BRUTES'!C$3:C$42="Technologie",'DONNÉES BRUTES'!AB$3:AB$42+(ROW('DONNÉES BRUTES'!A$3:A$42)-ROW('DONNÉES BRUTES'!A$3))/1000,0),13),IF('DONNÉES BRUTES'!C$3:C$42="Technologie",'DONNÉES BRUTES'!AB$3:AB$42+(ROW('DONNÉES BRUTES'!A$3:A$42)-ROW('DONNÉES BRUTES'!A$3))/1000,0),0))),"—")} | L23: {=IFERROR(IF(13>COUNTIF('DONNÉES BRUTES'!C$3:C$42,"Technologie"),"",INDEX('DONNÉES BRUTES'!P$3:P$42,MATCH(LARGE(IF('DONNÉES BRUTES'!C$3:C$42="Technologie",'DONNÉES BRUTES'!AB$3:AB$42+(ROW('DONNÉES BRUTES'!A$3:A$42)-ROW('DONNÉES BRUTES'!A$3))/1000,0),13),IF('DONNÉES BRUTES'!C$3:C$42="Technologie",'DONNÉES BRUTES'!AB$3:AB$42+(ROW('DONNÉES BRUTES'!A$3:A$42)-ROW('DONNÉES BRUTES'!A$3))/1000,0),0))),"—")} | M23: {=IFERROR(IF(13>COUNTIF('DONNÉES BRUTES'!C$3:C$42,"Technologie"),"",INDEX('DONNÉES BRUTES'!Q$3:Q$42,MATCH(LARGE(IF('DONNÉES BRUTES'!C$3:C$42="Technologie",'DONNÉES BRUTES'!AB$3:AB$42+(ROW('DONNÉES BRUTES'!A$3:A$42)-ROW('DONNÉES BRUTES'!A$3))/1000,0),13),IF('DONNÉES BRUTES'!C$3:C$42="Technologie",'DONNÉES BRUTES'!AB$3:AB$42+(ROW('DONNÉES BRUTES'!A$3:A$42)-ROW('DONNÉES BRUTES'!A$3))/1000,0),0))),"—")} | N23: {=IFERROR(IF(13>COUNTIF('DONNÉES BRUTES'!C$3:C$42,"Technologie"),"",INDEX('DONNÉES BRUTES'!S$3:S$42,MATCH(LARGE(IF('DONNÉES BRUTES'!C$3:C$42="Technologie",'DONNÉES BRUTES'!AB$3:AB$42+(ROW('DONNÉES BRUTES'!A$3:A$42)-ROW('DONNÉES BRUTES'!A$3))/1000,0),13),IF('DONNÉES BRUTES'!C$3:C$42="Technologie",'DONNÉES BRUTES'!AB$3:AB$42+(ROW('DONNÉES BRUTES'!A$3:A$42)-ROW('DONNÉES BRUTES'!A$3))/1000,0),0))),"—")} | O23: {=IFERROR(IF(13>COUNTIF('DONNÉES BRUTES'!C$3:C$42,"Technologie"),"",INDEX('DONNÉES BRUTES'!T$3:T$42,MATCH(LARGE(IF('DONNÉES BRUTES'!C$3:C$42="Technologie",'DONNÉES BRUTES'!AB$3:AB$42+(ROW('DONNÉES BRUTES'!A$3:A$42)-ROW('DONNÉES BRUTES'!A$3))/1000,0),13),IF('DONNÉES BRUTES'!C$3:C$42="Technologie",'DONNÉES BRUTES'!AB$3:AB$42+(ROW('DONNÉES BRUTES'!A$3:A$42)-ROW('DONNÉES BRUTES'!A$3))/1000,0),0))),"—")} | P23: {=IFERROR(IF(13>COUNTIF('DONNÉES BRUTES'!C$3:C$42,"Technologie"),"",INDEX('DONNÉES BRUTES'!U$3:U$42,MATCH(LARGE(IF('DONNÉES BRUTES'!C$3:C$42="Technologie",'DONNÉES BRUTES'!AB$3:AB$42+(ROW('DONNÉES BRUTES'!A$3:A$42)-ROW('DONNÉES BRUTES'!A$3))/1000,0),13),IF('DONNÉES BRUTES'!C$3:C$42="Technologie",'DONNÉES BRUTES'!AB$3:AB$42+(ROW('DONNÉES BRUTES'!A$3:A$42)-ROW('DONNÉES BRUTES'!A$3))/1000,0),0))),"—")} | Q23: {=IFERROR(IF(13>COUNTIF('DONNÉES BRUTES'!C$3:C$42,"Technologie"),"",INDEX('DONNÉES BRUTES'!AD$3:AD$42,MATCH(LARGE(IF('DONNÉES BRUTES'!C$3:C$42="Technologie",'DONNÉES BRUTES'!AB$3:AB$42+(ROW('DONNÉES BRUTES'!A$3:A$42)-ROW('DONNÉES BRUTES'!A$3))/1000,0),13),IF('DONNÉES BRUTES'!C$3:C$42="Technologie",'DONNÉES BRUTES'!AB$3:AB$42+(ROW('DONNÉES BRUTES'!A$3:A$42)-ROW('DONNÉES BRUTES'!A$3))/1000,0),0))),"—")}
C24: {=IFERROR(IF(14>COUNTIF('DONNÉES BRUTES'!C$3:C$42,"Technologie"),"",INDEX('DONNÉES BRUTES'!A$3:A$42,MATCH(LARGE(IF('DONNÉES BRUTES'!C$3:C$42="Technologie",'DONNÉES BRUTES'!AB$3:AB$42+(ROW('DONNÉES BRUTES'!A$3:A$42)-ROW('DONNÉES BRUTES'!A$3))/1000,0),14),IF('DONNÉES BRUTES'!C$3:C$42="Technologie",'DONNÉES BRUTES'!AB$3:AB$42+(ROW('DONNÉES BRUTES'!A$3:A$42)-ROW('DONNÉES BRUTES'!A$3))/1000,0),0))),"—")} | D24: {=IFERROR(IF(14>COUNTIF('DONNÉES BRUTES'!C$3:C$42,"Technologie"),"",INDEX('DONNÉES BRUTES'!B$3:B$42,MATCH(LARGE(IF('DONNÉES BRUTES'!C$3:C$42="Technologie",'DONNÉES BRUTES'!AB$3:AB$42+(ROW('DONNÉES BRUTES'!A$3:A$42)-ROW('DONNÉES BRUTES'!A$3))/1000,0),14),IF('DONNÉES BRUTES'!C$3:C$42="Technologie",'DONNÉES BRUTES'!AB$3:AB$42+(ROW('DONNÉES BRUTES'!A$3:A$42)-ROW('DONNÉES BRUTES'!A$3))/1000,0),0))),"—")} | E24: {=IFERROR(IF(14>COUNTIF('DONNÉES BRUTES'!C$3:C$42,"Technologie"),"",INT(LARGE(IF('DONNÉES BRUTES'!C$3:C$42="Technologie",'DONNÉES BRUTES'!AB$3:AB$42+(ROW('DONNÉES BRUTES'!A$3:A$42)-ROW('DONNÉES BRUTES'!A$3))/1000,0),14))&"/100"),"—")} | F24: {=IFERROR(IF(14>COUNTIF('DONNÉES BRUTES'!C$3:C$42,"Technologie"),"",INDEX('DONNÉES BRUTES'!Y$3:Y$42,MATCH(LARGE(IF('DONNÉES BRUTES'!C$3:C$42="Technologie",'DONNÉES BRUTES'!AB$3:AB$42+(ROW('DONNÉES BRUTES'!A$3:A$42)-ROW('DONNÉES BRUTES'!A$3))/1000,0),14),IF('DONNÉES BRUTES'!C$3:C$42="Technologie",'DONNÉES BRUTES'!AB$3:AB$42+(ROW('DONNÉES BRUTES'!A$3:A$42)-ROW('DONNÉES BRUTES'!A$3))/1000,0),0))),"—")} | G24: {=IFERROR(IF(14>COUNTIF('DONNÉES BRUTES'!C$3:C$42,"Technologie"),"",INDEX('DONNÉES BRUTES'!Z$3:Z$42,MATCH(LARGE(IF('DONNÉES BRUTES'!C$3:C$42="Technologie",'DONNÉES BRUTES'!AB$3:AB$42+(ROW('DONNÉES BRUTES'!A$3:A$42)-ROW('DONNÉES BRUTES'!A$3))/1000,0),14),IF('DONNÉES BRUTES'!C$3:C$42="Technologie",'DONNÉES BRUTES'!AB$3:AB$42+(ROW('DONNÉES BRUTES'!A$3:A$42)-ROW('DONNÉES BRUTES'!A$3))/1000,0),0))),"—")} | H24: {=IFERROR(IF(14>COUNTIF('DONNÉES BRUTES'!C$3:C$42,"Technologie"),"",INDEX('DONNÉES BRUTES'!AA$3:AA$42,MATCH(LARGE(IF('DONNÉES BRUTES'!C$3:C$42="Technologie",'DONNÉES BRUTES'!AB$3:AB$42+(ROW('DONNÉES BRUTES'!A$3:A$42)-ROW('DONNÉES BRUTES'!A$3))/1000,0),14),IF('DONNÉES BRUTES'!C$3:C$42="Technologie",'DONNÉES BRUTES'!AB$3:AB$42+(ROW('DONNÉES BRUTES'!A$3:A$42)-ROW('DONNÉES BRUTES'!A$3))/1000,0),0))),"—")} | I24: {=IFERROR(IF(14>COUNTIF('DONNÉES BRUTES'!C$3:C$42,"Technologie"),"",INDEX('DONNÉES BRUTES'!M$3:M$42,MATCH(LARGE(IF('DONNÉES BRUTES'!C$3:C$42="Technologie",'DONNÉES BRUTES'!AB$3:AB$42+(ROW('DONNÉES BRUTES'!A$3:A$42)-ROW('DONNÉES BRUTES'!A$3))/1000,0),14),IF('DONNÉES BRUTES'!C$3:C$42="Technologie",'DONNÉES BRUTES'!AB$3:AB$42+(ROW('DONNÉES BRUTES'!A$3:A$42)-ROW('DONNÉES BRUTES'!A$3))/1000,0),0))),"—")} | J24: {=IFERROR(IF(14>COUNTIF('DONNÉES BRUTES'!C$3:C$42,"Technologie"),"",INDEX('DONNÉES BRUTES'!N$3:N$42,MATCH(LARGE(IF('DONNÉES BRUTES'!C$3:C$42="Technologie",'DONNÉES BRUTES'!AB$3:AB$42+(ROW('DONNÉES BRUTES'!A$3:A$42)-ROW('DONNÉES BRUTES'!A$3))/1000,0),14),IF('DONNÉES BRUTES'!C$3:C$42="Technologie",'DONNÉES BRUTES'!AB$3:AB$42+(ROW('DONNÉES BRUTES'!A$3:A$42)-ROW('DONNÉES BRUTES'!A$3))/1000,0),0))),"—")} | K24: {=IFERROR(IF(14>COUNTIF('DONNÉES BRUTES'!C$3:C$42,"Technologie"),"",INDEX('DONNÉES BRUTES'!O$3:O$42,MATCH(LARGE(IF('DONNÉES BRUTES'!C$3:C$42="Technologie",'DONNÉES BRUTES'!AB$3:AB$42+(ROW('DONNÉES BRUTES'!A$3:A$42)-ROW('DONNÉES BRUTES'!A$3))/1000,0),14),IF('DONNÉES BRUTES'!C$3:C$42="Technologie",'DONNÉES BRUTES'!AB$3:AB$42+(ROW('DONNÉES BRUTES'!A$3:A$42)-ROW('DONNÉES BRUTES'!A$3))/1000,0),0))),"—")} | L24: {=IFERROR(IF(14>COUNTIF('DONNÉES BRUTES'!C$3:C$42,"Technologie"),"",INDEX('DONNÉES BRUTES'!P$3:P$42,MATCH(LARGE(IF('DONNÉES BRUTES'!C$3:C$42="Technologie",'DONNÉES BRUTES'!AB$3:AB$42+(ROW('DONNÉES BRUTES'!A$3:A$42)-ROW('DONNÉES BRUTES'!A$3))/1000,0),14),IF('DONNÉES BRUTES'!C$3:C$42="Technologie",'DONNÉES BRUTES'!AB$3:AB$42+(ROW('DONNÉES BRUTES'!A$3:A$42)-ROW('DONNÉES BRUTES'!A$3))/1000,0),0))),"—")} | M24: {=IFERROR(IF(14>COUNTIF('DONNÉES BRUTES'!C$3:C$42,"Technologie"),"",INDEX('DONNÉES BRUTES'!Q$3:Q$42,MATCH(LARGE(IF('DONNÉES BRUTES'!C$3:C$42="Technologie",'DONNÉES BRUTES'!AB$3:AB$42+(ROW('DONNÉES BRUTES'!A$3:A$42)-ROW('DONNÉES BRUTES'!A$3))/1000,0),14),IF('DONNÉES BRUTES'!C$3:C$42="Technologie",'DONNÉES BRUTES'!AB$3:AB$42+(ROW('DONNÉES BRUTES'!A$3:A$42)-ROW('DONNÉES BRUTES'!A$3))/1000,0),0))),"—")} | N24: {=IFERROR(IF(14>COUNTIF('DONNÉES BRUTES'!C$3:C$42,"Technologie"),"",INDEX('DONNÉES BRUTES'!S$3:S$42,MATCH(LARGE(IF('DONNÉES BRUTES'!C$3:C$42="Technologie",'DONNÉES BRUTES'!AB$3:AB$42+(ROW('DONNÉES BRUTES'!A$3:A$42)-ROW('DONNÉES BRUTES'!A$3))/1000,0),14),IF('DONNÉES BRUTES'!C$3:C$42="Technologie",'DONNÉES BRUTES'!AB$3:AB$42+(ROW('DONNÉES BRUTES'!A$3:A$42)-ROW('DONNÉES BRUTES'!A$3))/1000,0),0))),"—")} | O24: {=IFERROR(IF(14>COUNTIF('DONNÉES BRUTES'!C$3:C$42,"Technologie"),"",INDEX('DONNÉES BRUTES'!T$3:T$42,MATCH(LARGE(IF('DONNÉES BRUTES'!C$3:C$42="Technologie",'DONNÉES BRUTES'!AB$3:AB$42+(ROW('DONNÉES BRUTES'!A$3:A$42)-ROW('DONNÉES BRUTES'!A$3))/1000,0),14),IF('DONNÉES BRUTES'!C$3:C$42="Technologie",'DONNÉES BRUTES'!AB$3:AB$42+(ROW('DONNÉES BRUTES'!A$3:A$42)-ROW('DONNÉES BRUTES'!A$3))/1000,0),0))),"—")} | P24: {=IFERROR(IF(14>COUNTIF('DONNÉES BRUTES'!C$3:C$42,"Technologie"),"",INDEX('DONNÉES BRUTES'!U$3:U$42,MATCH(LARGE(IF('DONNÉES BRUTES'!C$3:C$42="Technologie",'DONNÉES BRUTES'!AB$3:AB$42+(ROW('DONNÉES BRUTES'!A$3:A$42)-ROW('DONNÉES BRUTES'!A$3))/1000,0),14),IF('DONNÉES BRUTES'!C$3:C$42="Technologie",'DONNÉES BRUTES'!AB$3:AB$42+(ROW('DONNÉES BRUTES'!A$3:A$42)-ROW('DONNÉES BRUTES'!A$3))/1000,0),0))),"—")} | Q24: {=IFERROR(IF(14>COUNTIF('DONNÉES BRUTES'!C$3:C$42,"Technologie"),"",INDEX('DONNÉES BRUTES'!AD$3:AD$42,MATCH(LARGE(IF('DONNÉES BRUTES'!C$3:C$42="Technologie",'DONNÉES BRUTES'!AB$3:AB$42+(ROW('DONNÉES BRUTES'!A$3:A$42)-ROW('DONNÉES BRUTES'!A$3))/1000,0),14),IF('DONNÉES BRUTES'!C$3:C$42="Technologie",'DONNÉES BRUTES'!AB$3:AB$42+(ROW('DONNÉES BRUTES'!A$3:A$42)-ROW('DONNÉES BRUTES'!A$3))/1000,0),0))),"—")}
C25: {=IFERROR(IF(15>COUNTIF('DONNÉES BRUTES'!C$3:C$42,"Technologie"),"",INDEX('DONNÉES BRUTES'!A$3:A$42,MATCH(LARGE(IF('DONNÉES BRUTES'!C$3:C$42="Technologie",'DONNÉES BRUTES'!AB$3:AB$42+(ROW('DONNÉES BRUTES'!A$3:A$42)-ROW('DONNÉES BRUTES'!A$3))/1000,0),15),IF('DONNÉES BRUTES'!C$3:C$42="Technologie",'DONNÉES BRUTES'!AB$3:AB$42+(ROW('DONNÉES BRUTES'!A$3:A$42)-ROW('DONNÉES BRUTES'!A$3))/1000,0),0))),"—")} | D25: {=IFERROR(IF(15>COUNTIF('DONNÉES BRUTES'!C$3:C$42,"Technologie"),"",INDEX('DONNÉES BRUTES'!B$3:B$42,MATCH(LARGE(IF('DONNÉES BRUTES'!C$3:C$42="Technologie",'DONNÉES BRUTES'!AB$3:AB$42+(ROW('DONNÉES BRUTES'!A$3:A$42)-ROW('DONNÉES BRUTES'!A$3))/1000,0),15),IF('DONNÉES BRUTES'!C$3:C$42="Technologie",'DONNÉES BRUTES'!AB$3:AB$42+(ROW('DONNÉES BRUTES'!A$3:A$42)-ROW('DONNÉES BRUTES'!A$3))/1000,0),0))),"—")} | E25: {=IFERROR(IF(15>COUNTIF('DONNÉES BRUTES'!C$3:C$42,"Technologie"),"",INT(LARGE(IF('DONNÉES BRUTES'!C$3:C$42="Technologie",'DONNÉES BRUTES'!AB$3:AB$42+(ROW('DONNÉES BRUTES'!A$3:A$42)-ROW('DONNÉES BRUTES'!A$3))/1000,0),15))&"/100"),"—")} | F25: {=IFERROR(IF(15>COUNTIF('DONNÉES BRUTES'!C$3:C$42,"Technologie"),"",INDEX('DONNÉES BRUTES'!Y$3:Y$42,MATCH(LARGE(IF('DONNÉES BRUTES'!C$3:C$42="Technologie",'DONNÉES BRUTES'!AB$3:AB$42+(ROW('DONNÉES BRUTES'!A$3:A$42)-ROW('DONNÉES BRUTES'!A$3))/1000,0),15),IF('DONNÉES BRUTES'!C$3:C$42="Technologie",'DONNÉES BRUTES'!AB$3:AB$42+(ROW('DONNÉES BRUTES'!A$3:A$42)-ROW('DONNÉES BRUTES'!A$3))/1000,0),0))),"—")} | G25: {=IFERROR(IF(15>COUNTIF('DONNÉES BRUTES'!C$3:C$42,"Technologie"),"",INDEX('DONNÉES BRUTES'!Z$3:Z$42,MATCH(LARGE(IF('DONNÉES BRUTES'!C$3:C$42="Technologie",'DONNÉES BRUTES'!AB$3:AB$42+(ROW('DONNÉES BRUTES'!A$3:A$42)-ROW('DONNÉES BRUTES'!A$3))/1000,0),15),IF('DONNÉES BRUTES'!C$3:C$42="Technologie",'DONNÉES BRUTES'!AB$3:AB$42+(ROW('DONNÉES BRUTES'!A$3:A$42)-ROW('DONNÉES BRUTES'!A$3))/1000,0),0))),"—")} | H25: {=IFERROR(IF(15>COUNTIF('DONNÉES BRUTES'!C$3:C$42,"Technologie"),"",INDEX('DONNÉES BRUTES'!AA$3:AA$42,MATCH(LARGE(IF('DONNÉES BRUTES'!C$3:C$42="Technologie",'DONNÉES BRUTES'!AB$3:AB$42+(ROW('DONNÉES BRUTES'!A$3:A$42)-ROW('DONNÉES BRUTES'!A$3))/1000,0),15),IF('DONNÉES BRUTES'!C$3:C$42="Technologie",'DONNÉES BRUTES'!AB$3:AB$42+(ROW('DONNÉES BRUTES'!A$3:A$42)-ROW('DONNÉES BRUTES'!A$3))/1000,0),0))),"—")} | I25: {=IFERROR(IF(15>COUNTIF('DONNÉES BRUTES'!C$3:C$42,"Technologie"),"",INDEX('DONNÉES BRUTES'!M$3:M$42,MATCH(LARGE(IF('DONNÉES BRUTES'!C$3:C$42="Technologie",'DONNÉES BRUTES'!AB$3:AB$42+(ROW('DONNÉES BRUTES'!A$3:A$42)-ROW('DONNÉES BRUTES'!A$3))/1000,0),15),IF('DONNÉES BRUTES'!C$3:C$42="Technologie",'DONNÉES BRUTES'!AB$3:AB$42+(ROW('DONNÉES BRUTES'!A$3:A$42)-ROW('DONNÉES BRUTES'!A$3))/1000,0),0))),"—")} | J25: {=IFERROR(IF(15>COUNTIF('DONNÉES BRUTES'!C$3:C$42,"Technologie"),"",INDEX('DONNÉES BRUTES'!N$3:N$42,MATCH(LARGE(IF('DONNÉES BRUTES'!C$3:C$42="Technologie",'DONNÉES BRUTES'!AB$3:AB$42+(ROW('DONNÉES BRUTES'!A$3:A$42)-ROW('DONNÉES BRUTES'!A$3))/1000,0),15),IF('DONNÉES BRUTES'!C$3:C$42="Technologie",'DONNÉES BRUTES'!AB$3:AB$42+(ROW('DONNÉES BRUTES'!A$3:A$42)-ROW('DONNÉES BRUTES'!A$3))/1000,0),0))),"—")} | K25: {=IFERROR(IF(15>COUNTIF('DONNÉES BRUTES'!C$3:C$42,"Technologie"),"",INDEX('DONNÉES BRUTES'!O$3:O$42,MATCH(LARGE(IF('DONNÉES BRUTES'!C$3:C$42="Technologie",'DONNÉES BRUTES'!AB$3:AB$42+(ROW('DONNÉES BRUTES'!A$3:A$42)-ROW('DONNÉES BRUTES'!A$3))/1000,0),15),IF('DONNÉES BRUTES'!C$3:C$42="Technologie",'DONNÉES BRUTES'!AB$3:AB$42+(ROW('DONNÉES BRUTES'!A$3:A$42)-ROW('DONNÉES BRUTES'!A$3))/1000,0),0))),"—")} | L25: {=IFERROR(IF(15>COUNTIF('DONNÉES BRUTES'!C$3:C$42,"Technologie"),"",INDEX('DONNÉES BRUTES'!P$3:P$42,MATCH(LARGE(IF('DONNÉES BRUTES'!C$3:C$42="Technologie",'DONNÉES BRUTES'!AB$3:AB$42+(ROW('DONNÉES BRUTES'!A$3:A$42)-ROW('DONNÉES BRUTES'!A$3))/1000,0),15),IF('DONNÉES BRUTES'!C$3:C$42="Technologie",'DONNÉES BRUTES'!AB$3:AB$42+(ROW('DONNÉES BRUTES'!A$3:A$42)-ROW('DONNÉES BRUTES'!A$3))/1000,0),0))),"—")} | M25: {=IFERROR(IF(15>COUNTIF('DONNÉES BRUTES'!C$3:C$42,"Technologie"),"",INDEX('DONNÉES BRUTES'!Q$3:Q$42,MATCH(LARGE(IF('DONNÉES BRUTES'!C$3:C$42="Technologie",'DONNÉES BRUTES'!AB$3:AB$42+(ROW('DONNÉES BRUTES'!A$3:A$42)-ROW('DONNÉES BRUTES'!A$3))/1000,0),15),IF('DONNÉES BRUTES'!C$3:C$42="Technologie",'DONNÉES BRUTES'!AB$3:AB$42+(ROW('DONNÉES BRUTES'!A$3:A$42)-ROW('DONNÉES BRUTES'!A$3))/1000,0),0))),"—")} | N25: {=IFERROR(IF(15>COUNTIF('DONNÉES BRUTES'!C$3:C$42,"Technologie"),"",INDEX('DONNÉES BRUTES'!S$3:S$42,MATCH(LARGE(IF('DONNÉES BRUTES'!C$3:C$42="Technologie",'DONNÉES BRUTES'!AB$3:AB$42+(ROW('DONNÉES BRUTES'!A$3:A$42)-ROW('DONNÉES BRUTES'!A$3))/1000,0),15),IF('DONNÉES BRUTES'!C$3:C$42="Technologie",'DONNÉES BRUTES'!AB$3:AB$42+(ROW('DONNÉES BRUTES'!A$3:A$42)-ROW('DONNÉES BRUTES'!A$3))/1000,0),0))),"—")} | O25: {=IFERROR(IF(15>COUNTIF('DONNÉES BRUTES'!C$3:C$42,"Technologie"),"",INDEX('DONNÉES BRUTES'!T$3:T$42,MATCH(LARGE(IF('DONNÉES BRUTES'!C$3:C$42="Technologie",'DONNÉES BRUTES'!AB$3:AB$42+(ROW('DONNÉES BRUTES'!A$3:A$42)-ROW('DONNÉES BRUTES'!A$3))/1000,0),15),IF('DONNÉES BRUTES'!C$3:C$42="Technologie",'DONNÉES BRUTES'!AB$3:AB$42+(ROW('DONNÉES BRUTES'!A$3:A$42)-ROW('DONNÉES BRUTES'!A$3))/1000,0),0))),"—")} | P25: {=IFERROR(IF(15>COUNTIF('DONNÉES BRUTES'!C$3:C$42,"Technologie"),"",INDEX('DONNÉES BRUTES'!U$3:U$42,MATCH(LARGE(IF('DONNÉES BRUTES'!C$3:C$42="Technologie",'DONNÉES BRUTES'!AB$3:AB$42+(ROW('DONNÉES BRUTES'!A$3:A$42)-ROW('DONNÉES BRUTES'!A$3))/1000,0),15),IF('DONNÉES BRUTES'!C$3:C$42="Technologie",'DONNÉES BRUTES'!AB$3:AB$42+(ROW('DONNÉES BRUTES'!A$3:A$42)-ROW('DONNÉES BRUTES'!A$3))/1000,0),0))),"—")} | Q25: {=IFERROR(IF(15>COUNTIF('DONNÉES BRUTES'!C$3:C$42,"Technologie"),"",INDEX('DONNÉES BRUTES'!AD$3:AD$42,MATCH(LARGE(IF('DONNÉES BRUTES'!C$3:C$42="Technologie",'DONNÉES BRUTES'!AB$3:AB$42+(ROW('DONNÉES BRUTES'!A$3:A$42)-ROW('DONNÉES BRUTES'!A$3))/1000,0),15),IF('DONNÉES BRUTES'!C$3:C$42="Technologie",'DONNÉES BRUTES'!AB$3:AB$42+(ROW('DONNÉES BRUTES'!A$3:A$42)-ROW('DONNÉES BRUTES'!A$3))/1000,0),0))),"—")}
S28: Société | T28: Score | U28: Growth | V28: Quality | W28: Momentum | Y28: Société | Z28: Growth | AA28: Quality | AB28: Momentum
S29: =IF(D11="","",LEFT(D11,14)) -> ASML Holding N | T29: =IF(E11="","",IFERROR(VALUE(LEFT(E11,FIND("/",E11)-1)),0)) -> 75 | U29: =IF(ISNUMBER(F11),F11,0) -> 92 | V29: =IF(ISNUMBER(G11),G11,0) -> 86 | W29: =IF(ISNUMBER(H11),H11,0) -> 98 | X29: =IF(ISNUMBER(F11),F11,"") -> 92 | Y29: =IF(ISNUMBER(G11),G11,"") -> 86 | Z29: =IF(ISNUMBER(H11),H11,"") -> 98 | AA29: 100 | AB29: 74
S30: =IF(D12="","",LEFT(D12,14)) -> SAP SE | T30: =IF(E12="","",IFERROR(VALUE(LEFT(E12,FIND("/",E12)-1)),0)) -> 62 | U30: =IF(ISNUMBER(F12),F12,0) -> 78 | V30: =IF(ISNUMBER(G12),G12,0) -> 80 | W30: =IF(ISNUMBER(H12),H12,0) -> 0 | X30: =IF(ISNUMBER(F12),F12,"") -> 78 | Y30: =IF(ISNUMBER(G12),G12,"") -> 80 | Z30: =IF(ISNUMBER(H12),H12,"") -> 0 | AA30: 36 | AB30: 87
S31: =IF(D13="","",LEFT(D13,14)) -> Nokia Oyj | T31: =IF(E13="","",IFERROR(VALUE(LEFT(E13,FIND("/",E13)-1)),0)) -> 46 | U31: =IF(ISNUMBER(F13),F13,0) -> 29 | V31: =IF(ISNUMBER(G13),G13,0) -> 57 | W31: =IF(ISNUMBER(H13),H13,0) -> 94 | X31: =IF(ISNUMBER(F13),F13,"") -> 29 | Y31: =IF(ISNUMBER(G13),G13,"") -> 57 | Z31: =IF(ISNUMBER(H13),H13,"") -> 94 | AA31: 44 | AB31: 0
S32: =IF(D14="","",LEFT(D14,14)) -> Infineon Techn | T32: =IF(E14="","",IFERROR(VALUE(LEFT(E14,FIND("/",E14)-1)),0)) -> 40 | U32: =IF(ISNUMBER(F14),F14,0) -> 32 | V32: =IF(ISNUMBER(G14),G14,0) -> 59 | W32: =IF(ISNUMBER(H14),H14,0) -> 57 | X32: =IF(ISNUMBER(F14),F14,"") -> 32 | Y32: =IF(ISNUMBER(G14),G14,"") -> 59 | Z32: =IF(ISNUMBER(H14),H14,"") -> 57 | AA32: 0 | AB32: 5

Sheet CONSUMER DISC.
B1: ="FinSight IA · Consumer Disc. · CAC 40 · "&COUNTIF('DONNÉES BRUTES'!C$3:C$42,"Conso. Cycl.")&" sociétés · 12/04/2026" -> FinSight IA · Consumer Disc. · CAC 40 · 7 sociétés · 12/04/2026
B2: Zoom sectoriel · Ratios clés · Score FinSight · Usage confidentiel
C5: 7 | E5: 47/100 | H5: {=LEFT(IFERROR(INDEX('DONNÉES BRUTES'!B$3:B$42,MATCH(LARGE(IF('DONNÉES BRUTES'!C$3:C$42="Conso. Cycl.",'DONNÉES BRUTES'!AB$3:AB$42+(ROW('DONNÉES BRUTES'!A$3:A$42)-ROW('DONNÉES BRUTES'!A$3))/1000,0),1),IF('DONNÉES BRUTES'!C$3:C$42="Conso. Cycl.",'DONNÉES BRUTES'!AB$3:AB$42+(ROW('DONNÉES BRUTES'!A$3:A$42)-ROW('DONNÉES BRUTES'!A$3))/1000,0),0)),"—"),18)} -> Hermès Internation | L5: 0.272 | N5: {=IFERROR(ROUND(MEDIAN(IF('DONNÉES BRUTES'!C$3:C$42="Conso. Cycl.",IF(ISNUMBER('DONNÉES BRUTES'!Y$3:Y$42),'DONNÉES BRUTES'!Y$3:Y$42))),0),"—")} -> 61 | P5: Surpondérer
C6: Sociétés | E6: Score moyen | H6: Meilleure société | L6: Mg. EBITDA Méd. | N6: Score Growth Méd. | P6: Signal
B8: ="ANALYSE DÉTAILLÉE · "&UPPER("Conso. Cycl.")&" · "&COUNTIF('DONNÉES BRUTES'!C$3:C$42,"Conso. Cycl.")&" sociétés · Triée par Score Global" -> ANALYSE DÉTAILLÉE · CONSO. CYCL. · 7 sociétés · Triée par Score Global
B10: # | C10: Ticker | D10: Société | E10: Score | F10: Gr. | G10: Qual. | H10: Mom. | I10: Mg. Brute | J10: Mg. EBITDA | K10: Mg. Nette | L10: Croiss. Rev. | M10: ROE | N10: Curr. R. | O10: ND/EBITDA | P10: Altman Z | Q10: Signal
