Workbook
Name LBO_ELIGIBLE: 'LBO MODEL'!$C$74
Name LBO_EQUITY_ENTRY: 'LBO MODEL'!$C$81
Name LBO_EQUITY_EXIT: 'LBO MODEL'!$C$82
Name LBO_IRR_BASE: 'LBO MODEL'!$C$76
Name LBO_IRR_BEAR: 'LBO MODEL'!#REF!
Name LBO_IRR_BULL: 'LBO MODEL'!#REF!
Name LBO_LEVERAGE_EXIT: 'LBO MODEL'!$C$80
Name LBO_MEGA_FLAG: 'LBO MODEL'!$C$75
Name LBO_MOIC_BASE: 'LBO MODEL'!#REF!

Sheet LBO MODEL
A1: FinSight | I1: LBO MODEL — Leveraged Buyout Analysis
B3: MODÈLE LBO
B4: Modèle institutionnel mid-market · calculs sur 5 ans · toutes hypothèses paramétrables (cellules jaunes)
B5: METRIC | D5: Y0 (LTM) | E5: Y1 / 2026F | F5: Y2 / 2027F | G5: Y3 / 2028F | H5: Y4 / 2029F | I5: Y5 / 2030F
B6: PROFIL & ÉLIGIBILITÉ
B7: =IF(AND(INPUT!H30>0,IFERROR(INPUT!H30/INPUT!H9,0)>0.15,IFERROR(DCF!H49/INPUT!H30,0)>0.6,IFERROR((INPUT!H54+INPUT!H48-INPUT!H34)/INPUT!H30,99)<3.5)," ✓ PROFIL LBO-ABLE — Société éligible aux critères d'un LBO mid-market standard"," ✗ PROFIL NON ÉLIGIBLE — Voir critères ci-dessous pour les freins identifiés")
B8: =IF(IFERROR(INPUT!H30/INPUT!H9,0)>0.15,"✓ Marge EBITDA > 15%","✗ Marge EBITDA < 15%") | D8: =IF(IFERROR(DCF!H49/INPUT!H30,0)>0.6,"✓ Cash conv. > 60%","✗ Cash conv. < 60%") | F8: =IF(IFERROR((INPUT!H54+INPUT!H48-INPUT!H34)/INPUT!H30,99)<3.5,"✓ Levier net < 3,5x","✗ Levier net > 3,5x") | H8: =IF(INPUT!H30>0,"✓ EBITDA positif","✗ EBITDA négatif")
B9: =IF(INPUT!H98>100000000," ⚠⚠ SCÉNARIO THÉORIQUE — EV > 100 Md$, taille hors marché LBO historique",IF(INPUT!H98>50000000," ⚠ MEGA-DEAL — EV entre 50 et 100 Md$, syndicate requis",""))
B11: HYPOTHÈSES D'ENTRÉE — cellules jaunes paramétrables
B12: Société | D12: =IFERROR(TRIM(MID(STOCK_DATA!A1,14,FIND("(",STOCK_DATA!A1)-15)),"") | F12: Multiple d'entrée (× EBITDA) | H12: 14
B13: Ticker | D13: =IFERROR(MID(STOCK_DATA!A1,SEARCH("(",STOCK_DATA!A1)+1,SEARCH(")",STOCK_DATA!A1)-SEARCH("(",STOCK_DATA!A1)-1),"") | F13: Leverage total (× EBITDA) | H13: 5
B14: Revenue LTM ($M) | D14: =INPUT!H9 | F14: · dont Senior TLB | H14: 3.5
B15: EBITDA LTM ($M) | D15: =INPUT!H30 | F15: · dont Mezzanine | H15: 1.5
B16: Marge EBITDA LTM | D16: =IFERROR(INPUT!H30/INPUT!H9,0) | F16: Coût Senior TLB | H16: 0.08
B17: EV (marché) / EBITDA LTM | D17: =IFERROR(INPUT!H98/INPUT!H30,0) | F17: Coût Mezzanine (cash+PIK) | H17: 0.1
B18: Net Debt / EBITDA (actuel) | D18: =IFERROR((INPUT!H54+INPUT!H48-INPUT!H34)/INPUT!H30,0) | F18: Multiple de sortie (× EBITDA Y5) | H18: 14
F19: Période de détention (années) | H19: 5
F20: Transaction fees (% EV) | H20: 0.025
F21: Cash minimum BS (% EV) | H21: 0.05
B24: PROJECTIONS EBITDA & FCF (Y0 → Y5)
B25: Revenue | C25: ($M) | D25: =_LBO_CALC!H6 | E25: =_LBO_CALC!I6 | F25: =_LBO_CALC!J6 | G25: =_LBO_CALC!K6 | H25: =_LBO_CALC!L6 | I25: =_LBO_CALC!M6
B26: EBITDA | C26: ($M) | D26: =_LBO_CALC!H7 | E26: =_LBO_CALC!I7 | F26: =_LBO_CALC!J7 | G26: =_LBO_CALC!K7 | H26: =_LBO_CALC!L7 | I26: =_LBO_CALC!M7
B27: Marge EBITDA | C27: (%) | D27: =IFERROR(D26/D25,0) | E27: =IFERROR(E26/E25,0) | F27: =IFERROR(F26/F25,0) | G27: =IFERROR(G26/G25,0) | H27: =IFERROR(H26/H25,0) | I27: =IFERROR(I26/I25,0)
B28: D&A | C28: ($M) | D28: =_LBO_CALC!H8 | E28: =_LBO_CALC!I8 | F28: =_LBO_CALC!J8 | G28: =_LBO_CALC!K8 | H28: =_LBO_CALC!L8 | I28: =_LBO_CALC!M8
B29: EBIT | C29: ($M) | D29: =_LBO_CALC!H9 | E29: =_LBO_CALC!I9 | F29: =_LBO_CALC!J9 | G29: =_LBO_CALC!K9 | H29: =_LBO_CALC!L9 | I29: =_LBO_CALC!M9
B30: CapEx | C30: ($M) | D30: =_LBO_CALC!H10 | E30: =_LBO_CALC!I10 | F30: =_LBO_CALC!J10 | G30: =_LBO_CALC!K10 | H30: =_LBO_CALC!L10 | I30: =_LBO_CALC!M10
B31: Δ Working Capital | C31: ($M) | D31: =_LBO_CALC!H11 | E31: =_LBO_CALC!I11 | F31: =_LBO_CALC!J11 | G31: =_LBO_CALC!K11 | H31: =_LBO_CALC!L11 | I31: =_LBO_CALC!M11
B32: FCF Unlevered (pré-dette) | C32: ($M) | D32: =_LBO_CALC!H12 | E32: =_LBO_CALC!I12 | F32: =_LBO_CALC!J12 | G32: =_LBO_CALC!K12 | H32: =_LBO_CALC!L12 | I32: =_LBO_CALC!M12
B34: DETTE SCHEDULE COMPLET — Senior TLB + Mezzanine
B35: SENIOR TERM LOAN B
B36: Beginning balance | C36: ($M) | D36: =_LBO_CALC!H16 | E36: =_LBO_CALC!I16 | F36: =_LBO_CALC!J16 | G36: =_LBO_CALC!K16 | H36: =_LBO_CALC!L16 | I36: =_LBO_CALC!M16
B37: Amortissement obligatoire (1%) | C37: ($M) | D37: — | E37: =_LBO_CALC!I17 | F37: =_LBO_CALC!J17 | G37: =_LBO_CALC!K17 | H37: =_LBO_CALC!L17 | I37: =_LBO_CALC!M17
B38: Cash sweep (75% FCF excédentaire) | C38: ($M) | D38: — | E38: =_LBO_CALC!I18 | F38: =_LBO_CALC!J18 | G38: =_LBO_CALC!K18 | H38: =_LBO_CALC!L18 | I38: =_LBO_CALC!M18
B39: Ending balance | C39: ($M) | D39: =_LBO_CALC!H19 | E39: =_LBO_CALC!I19 | F39: =_LBO_CALC!J19 | G39: =_LBO_CALC!K19 | H39: =_LBO_CALC!L19 | I39: =_LBO_CALC!M19
B40: Intérêts TLB | C40: ($M) | D40: — | E40: =_LBO_CALC!I20 | F40: =_LBO_CALC!J20 | G40: =_LBO_CALC!K20 | H40: =_LBO_CALC!L20 | I40: =_LBO_CALC!M20
B41: MEZZANINE
B42: Beginning balance | C42: ($M) | D42: =_LBO_CALC!H23 | E42: =_LBO_CALC!I23 | F42: =_LBO_CALC!J23 | G42: =_LBO_CALC!K23 | H42: =_LBO_CALC!L23 | I42: =_LBO_CALC!M23
B43: Intérêts PIK capitalisés (5%) | C43: ($M) | D43: — | E43: =_LBO_CALC!I24 | F43: =_LBO_CALC!J24 | G43: =_LBO_CALC!K24 | H43: =_LBO_CALC!L24 | I43: =_LBO_CALC!M24
B44: Ending balance | C44: ($M) | D44: =_LBO_CALC!H26 | E44: =_LBO_CALC!I26 | F44: =_LBO_CALC!J26 | G44: =_LBO_CALC!K26 | H44: =_LBO_CALC!L26 | I44: =_LBO_CALC!M26
B45: Intérêts Mezz (cash 5%) | C45: ($M) | D45: — | E45: =_LBO_CALC!I27 | F45: =_LBO_CALC!J27 | G45: =_LBO_CALC!K27 | H45: =_LBO_CALC!L27 | I45: =_LBO_CALC!M27
B46: TOTAL INTÉRÊTS | C46: ($M) | D46: — | E46: =_LBO_CALC!I29 | F46: =_LBO_CALC!J29 | G46: =_LBO_CALC!K29 | H46: =_LBO_CALC!L29 | I46: =_LBO_CALC!M29
B47: Net Debt (Senior + Mezz − Cash) | C47: ($M) | D47: =_LBO_CALC!H30 | E47: =_LBO_CALC!I30 | F47: =_LBO_CALC!J30 | G47: =_LBO_CALC!K30 | H47: =_LBO_CALC!L30 | I47: =_LBO_CALC!M30
B48: Total Leverage (× EBITDA) | C48: (×) | D48: =_LBO_CALC!H31 | E48: =_LBO_CALC!I31 | F48: =_LBO_CALC!J31 | G48: =_LBO_CALC!K31 | H48: =_LBO_CALC!L31 | I48: =_LBO_CALC!M31
B49: ICR (EBIT / Intérêts) | C49: (×) | D49: — | E49: =_LBO_CALC!I32 | F49: =_LBO_CALC!J32 | G49: =_LBO_CALC!K32 | H49: =_LBO_CALC!L32 | I49: =_LBO_CALC!M32
B51: FCF LEVERED & TAX SHIELD — PE-grade (post-intérêts, post-tax)
B52: Tax Shield (intérêts déductibles) | C52: ($M) | D52: — | E52: =_LBO_CALC!I35 | F52: =_LBO_CALC!J35 | G52: =_LBO_CALC!K35 | H52: =_LBO_CALC!L35 | I52: =_LBO_CALC!M35
B53: EBT levé (EBIT + Intérêts) | C53: ($M) | D53: — | E53: =_LBO_CALC!I36 | F53: =_LBO_CALC!J36 | G53: =_LBO_CALC!K36 | H53: =_LBO_CALC!L36 | I53: =_LBO_CALC!M36
B54: Impôt cash (sur EBT levé) | C54: ($M) | D54: — | E54: =_LBO_CALC!I37 | F54: =_LBO_CALC!J37 | G54: =_LBO_CALC!K37 | H54: =_LBO_CALC!L37 | I54: =_LBO_CALC!M37
B55: FCF Levé (post-intérêts, post-tax) | C55: ($M) | D55: — | E55: =_LBO_CALC!I39 | F55: =_LBO_CALC!J39 | G55: =_LBO_CALC!K39 | H55: =_LBO_CALC!L39 | I55: =_LBO_CALC!M39
B57: COVENANT TESTING — Seuils bancaires imposés
B58: Levier covenant (max imposé, step-down) | C58: (×) | D58: — | E58: =_LBO_CALC!I42 | F58: =_LBO_CALC!J42 | G58: =_LBO_CALC!K42 | H58: =_LBO_CALC!L42 | I58: =_LBO_CALC!M42
B59: Levier réel (× EBITDA) | C59: (×) | D59: =_LBO_CALC!H43 | E59: =_LBO_CALC!I43 | F59: =_LBO_CALC!J43 | G59: =_LBO_CALC!K43 | H59: =_LBO_CALC!L43 | I59: =_LBO_CALC!M43
B60: Levier covenant ✓ / ✗ | D60: — | E60: =_LBO_CALC!I46 | F60: =_LBO_CALC!J46 | G60: =_LBO_CALC!K46 | H60: =_LBO_CALC!L46 | I60: =_LBO_CALC!M46
B61: ICR covenant (min imposé = 2.0×) | C61: (×) | D61: — | E61: 2 | F61: 2 | G61: 2 | H61: 2 | I61: =_LBO_CALC!M44
B62: ICR réel (EBIT / Intérêts) | C62: (×) | D62: — | E62: =_LBO_CALC!I45 | F62: =_LBO_CALC!J45 | G62: =_LBO_CALC!K45 | H62: =_LBO_CALC!L45 | I62: =_LBO_CALC!M45
B63: ICR covenant ✓ / ✗ | E63: =IF(E62>=E61,"✓ PASS","✗ BREACH") | F63: =IF(F62>=F61,"✓ PASS","✗ BREACH") | G63: =IF(G62>=G61,"✓ PASS","✗ BREACH") | H63: =IF(H62>=H61,"✓ PASS","✗ BREACH") | I63: =IF(I62>=I61,"✓ PASS","✗ BREACH")
B64: SOURCES | C64: ($M) | D64: Montant | E64: % Total | G64: USES | I64: Montant
B65: Sponsor Equity | D65: =_LBO_CALC!N56 | E65: =IFERROR(D65/(D65+D66+D67),0) | G65: Purchase price (equity) | I65: =H12*INPUT!H30-(INPUT!H54+INPUT!H48-INPUT!H34)
B66: Senior Term Loan B | D66: =H14*INPUT!H30 | E66: =IFERROR(D66/(D65+D66+D67),0) | G66: Refinancement dette existante | I66: =INPUT!H54+INPUT!H48
B67: Mezzanine | D67: =H15*INPUT!H30 | E67: =IFERROR(D67/(D65+D66+D67),0) | G67: Transaction fees | I67: =H12*INPUT!H30*H20
G68: Cash minimum sur BS | I68: =H12*INPUT!H30*H21
B69: TOTAL SOURCES | D69: =D65+D66+D67 | E69: =IFERROR(D69/D69,1) | G69: TOTAL USES | I69: =SUM(I65:I68)
B71: RETURNS BASE CASE — Sortie Y5
B72: Equity entry sponsor | D72: =_LBO_CALC!N56
B73: EV sortie (Y5, × mult. sortie) | D73: =_LBO_CALC!M48
B74: Net Debt exit (Y5) | D74: =_LBO_CALC!M30
B75: Equity exit (Y5) | D75: =_LBO_CALC!N61
C77: IRR Sponsor | G77: MOIC | K77: Money-back period | L77: =IF(_LBO_CALC!N62<=0,"N/A",IF(LN(2)/LN(1+_LBO_CALC!N62)>H19*2,">"&TEXT(H19*2,"0")&" ans",ROUND(LN(2)/LN(1+_LBO_CALC!N62),1)&" ans"))
C78: =_LBO_CALC!N62 | G78: =_LBO_CALC!N63
C79: Base Case | G79: Base Case
B80: SENSIBILITÉ IRR — Multiple d'entrée × Multiple de sortie
B81: ↓ Mult. entrée / Mult. sortie → | E81: =H18+(-2) | F81: =H18+(-1) | G81: =H18+(0) | H81: =H18+(1) | I81: =H18+(2)
B82: =H12+(-2) | E82: =IFERROR(((_LBO_CALC!$M$7*(H18+(-2))-_LBO_CALC!$M$30)/MAX(1,(H12+(-2))*INPUT!$H$30*(1+H20+H21)+INPUT!$H$34-H13*INPUT!$H$30))^(1/H19)-1,0) | F82: =IFERROR(((_LBO_CALC!$M$7*(H18+(-1))-_LBO_CALC!$M$30)/MAX(1,(H12+(-2))*INPUT!$H$30*(1+H20+H21)+INPUT!$H$34-H13*INPUT!$H$30))^(1/H19)-1,0) | G82: =IFERROR(((_LBO_CALC!$M$7*(H18+(0))-_LBO_CALC!$M$30)/MAX(1,(H12+(-2))*INPUT!$H$30*(1+H20+H21)+INPUT!$H$34-H13*INPUT!$H$30))^(1/H19)-1,0) | H82: =IFERROR(((_LBO_CALC!$M$7*(H18+(1))-_LBO_CALC!$M$30)/MAX(1,(H12+(-2))*INPUT!$H$30*(1+H20+H21)+INPUT!$H$34-H13*INPUT!$H$30))^(1/H19)-1,0) | I82: =IFERROR(((_LBO_CALC!$M$7*(H18+(2))-_LBO_CALC!$M$30)/MAX(1,(H12+(-2))*INPUT!$H$30*(1+H20+H21)+INPUT!$H$34-H13*INPUT!$H$30))^(1/H19)-1,0)
B83: =H12+(-1) | E83: =IFERROR(((_LBO_CALC!$M$7*(H18+(-2))-_LBO_CALC!$M$30)/MAX(1,(H12+(-1))*INPUT!$H$30*(1+H20+H21)+INPUT!$H$34-H13*INPUT!$H$30))^(1/H19)-1,0) | F83: =IFERROR(((_LBO_CALC!$M$7*(H18+(-1))-_LBO_CALC!$M$30)/MAX(1,(H12+(-1))*INPUT!$H$30*(1+H20+H21)+INPUT!$H$34-H13*INPUT!$H$30))^(1/H19)-1,0) | G83: =IFERROR(((_LBO_CALC!$M$7*(H18+(0))-_LBO_CALC!$M$30)/MAX(1,(H12+(-1))*INPUT!$H$30*(1+H20+H21)+INPUT!$H$34-H13*INPUT!$H$30))^(1/H19)-1,0) | H83: =IFERROR(((_LBO_CALC!$M$7*(H18+(1))-_LBO_CALC!$M$30)/MAX(1,(H12+(-1))*INPUT!$H$30*(1+H20+H21)+INPUT!$H$34-H13*INPUT!$H$30))^(1/H19)-1,0) | I83: =IFERROR(((_LBO_CALC!$M$7*(H18+(2))-_LBO_CALC!$M$30)/MAX(1,(H12+(-1))*INPUT!$H$30*(1+H20+H21)+INPUT!$H$34-H13*INPUT!$H$30))^(1/H19)-1,0)
B84: =H12+(0) | E84: =IFERROR(((_LBO_CALC!$M$7*(H18+(-2))-_LBO_CALC!$M$30)/MAX(1,H12*INPUT!$H$30*(1+H20+H21)+INPUT!$H$34-H13*INPUT!$H$30))^(1/H19)-1,0) | F84: =IFERROR(((_LBO_CALC!$M$7*(H18+(-1))-_LBO_CALC!$M$30)/MAX(1,H12*INPUT!$H$30*(1+H20+H21)+INPUT!$H$34-H13*INPUT!$H$30))^(1/H19)-1,0) | G84: =IFERROR(((_LBO_CALC!$M$7*(H18+(0))-_LBO_CALC!$M$30)/MAX(1,H12*INPUT!$H$30*(1+H20+H21)+INPUT!$H$34-H13*INPUT!$H$30))^(1/H19)-1,0) | H84: =IFERROR(((_LBO_CALC!$M$7*(H18+(1))-_LBO_CALC!$M$30)/MAX(1,H12*INPUT!$H$30*(1+H20+H21)+INPUT!$H$34-H13*INPUT!$H$30))^(1/H19)-1,0) | I84: =IFERROR(((_LBO_CALC!$M$7*(H18+(2))-_LBO_CALC!$M$30)/MAX(1,H12*INPUT!$H$30*(1+H20+H21)+INPUT!$H$34-H13*INPUT!$H$30))^(1/H19)-1,0)
B85: =H12+(1) | E85: =IFERROR(((_LBO_CALC!$M$7*(H18+(-2))-_LBO_CALC!$M$30)/MAX(1,(H12+(1))*INPUT!$H$30*(1+H20+H21)+INPUT!$H$34-H13*INPUT!$H$30))^(1/H19)-1,0) | F85: =IFERROR(((_LBO_CALC!$M$7*(H18+(-1))-_LBO_CALC!$M$30)/MAX(1,(H12+(1))*INPUT!$H$30*(1+H20+H21)+INPUT!$H$34-H13*INPUT!$H$30))^(1/H19)-1,0) | G85: =IFERROR(((_LBO_CALC!$M$7*(H18+(0))-_LBO_CALC!$M$30)/MAX(1,(H12+(1))*INPUT!$H$30*(1+H20+H21)+INPUT!$H$34-H13*INPUT!$H$30))^(1/H19)-1,0) | H85: =IFERROR(((_LBO_CALC!$M$7*(H18+(1))-_LBO_CALC!$M$30)/MAX(1,(H12+(1))*INPUT!$H$30*(1+H20+H21)+INPUT!$H$34-H13*INPUT!$H$30))^(1/H19)-1,0) | I85: =IFERROR(((_LBO_CALC!$M$7*(H18+(2))-_LBO_CALC!$M$30)/MAX(1,(H12+(1))*INPUT!$H$30*(1+H20+H21)+INPUT!$H$34-H13*INPUT!$H$30))^(1/H19)-1,0)
B86: =H12+(2) | E86: =IFERROR(((_LBO_CALC!$M$7*(H18+(-2))-_LBO_CALC!$M$30)/MAX(1,(H12+(2))*INPUT!$H$30*(1+H20+H21)+INPUT!$H$34-H13*INPUT!$H$30))^(1/H19)-1,0) | F86: =IFERROR(((_LBO_CALC!$M$7*(H18+(-1))-_LBO_CALC!$M$30)/MAX(1,(H12+(2))*INPUT!$H$30*(1+H20+H21)+INPUT!$H$34-H13*INPUT!$H$30))^(1/H19)-1,0) | G86: =IFERROR(((_LBO_CALC!$M$7*(H18+(0))-_LBO_CALC!$M$30)/MAX(1,(H12+(2))*INPUT!$H$30*(1+H20+H21)+INPUT!$H$34-H13*INPUT!$H$30))^(1/H19)-1,0) | H86: =IFERROR(((_LBO_CALC!$M$7*(H18+(1))-_LBO_CALC!$M$30)/MAX(1,(H12+(2))*INPUT!$H$30*(1+H20+H21)+INPUT!$H$34-H13*INPUT!$H$30))^(1/H19)-1,0) | I86: =IFERROR(((_LBO_CALC!$M$7*(H18+(2))-_LBO_CALC!$M$30)/MAX(1,(H12+(2))*INPUT!$H$30*(1+H20+H21)+INPUT!$H$34-H13*INPUT!$H$30))^(1/H19)-1,0)
B88: SCÉNARIOS — Bull / Base / Bear
B89: Métrique | E89: BULL | G89: BASE | I89: BEAR
B90: IRR Sponsor | C90: (%) | E90: =_LBO_CALC!P66 | G90: =_LBO_CALC!P67 | I90: =_LBO_CALC!P68
B91: MOIC | C91: (×) | E91: =_LBO_CALC!Q66 | G91: =_LBO_CALC!Q67 | I91: =_LBO_CALC!Q68
B92: Leverage exit | C92: (×) | E92: =_LBO_CALC!R66 | G92: =_LBO_CALC!R67 | I92: =_LBO_CALC!R68
B93: ICR exit (EBIT/Int) | C93: (×) | E93: =_LBO_CALC!S66 | G93: =_LBO_CALC!S67 | I93: =_LBO_CALC!S68
B96: LBO_ELIGIBLE | D96: =IF(AND(INPUT!H30>0,IFERROR(INPUT!H30/INPUT!H9,0)>0.15,IFERROR(DCF!H49/INPUT!H30,0)>0.6,IFERROR((INPUT!H54+INPUT!H48-INPUT!H34)/INPUT!H30,99)<3.5),"OUI","NON")
B97: LBO_IRR_BASE | D97: =_LBO_CALC!N62
B98: LBO_MOIC_BASE | D98: =_LBO_CALC!N63
B99: LBO_IRR_BULL | D99: =_LBO_CALC!P66
B100: LBO_IRR_BEAR | D100: =_LBO_CALC!P68
B101: LBO_LEVERAGE_EXIT | D101: =_LBO_CALC!R67
B102: LBO_EQUITY_ENTRY | D102: =_LBO_CALC!N56
B103: LBO_EQUITY_EXIT | D103: =_LBO_CALC!N61
B105: Méthodologie complète : voir slide méthodologie société. Calculs détaillés dans l'onglet _LBO_CALC (masqué — démasquer pour audit).
K107: Année | L107: Levier (×EBITDA)
K108: Y0 | L108: =D48
K109: Y1 | L109: =E48
K110: Y2 | L110: =F48
K111: Y3 | L111: =G48
K112: Y4 | L112: =H48
K113: Y5 | L113: =I48
K117: Scénario | L117: IRR
...

Sheet _LBO_CALC
B1: FinSight — LBO Calculation Engine (JPM/GS-grade)
B2: Onglet masqué — démasquer pour audit complet du modèle.
B4: 1. PROJECTIONS DÉTAILLÉES Y0-Y5 (référence DCF)
B5: ($000) | H5: Y0 (LTM) | I5: Y1 | J5: Y2 | K5: Y3 | L5: Y4 | M5: Y5
B6: Revenue | H6: =DCF!H9 | I6: =DCF!I9 | J6: =DCF!J9 | K6: =DCF!K9 | L6: =DCF!L9 | M6: =DCF!M9
B7: EBITDA | H7: =DCF!H15 | I7: =DCF!I15 | J7: =DCF!J15 | K7: =DCF!K15 | L7: =DCF!L15 | M7: =DCF!M15
B8: D&A | H8: =DCF!H17 | I8: =DCF!I17 | J8: =DCF!J17 | K8: =DCF!K17 | L8: =DCF!L17 | M8: =DCF!M17
B9: EBIT | H9: =DCF!H18 | I9: =DCF!I18 | J9: =DCF!J18 | K9: =DCF!K18 | L9: =DCF!L18 | M9: =DCF!M18
B10: CapEx | H10: =DCF!H47 | I10: =DCF!I47 | J10: =DCF!J47 | K10: =DCF!K47 | L10: =DCF!L47 | M10: =DCF!M47
B11: Δ Working Capital | H11: =DCF!H48 | I11: =DCF!I48 | J11: =DCF!J48 | K11: =DCF!K48 | L11: =DCF!L48 | M11: =DCF!M48
B12: FCF Unlevered (Pre-Debt) | H12: =DCF!H49 | I12: =DCF!I49 | J12: =DCF!J49 | K12: =DCF!K49 | L12: =DCF!L49 | M12: =DCF!M49
B14: 2. DEBT SCHEDULE COMPLET (Senior TLB + Mezzanine)
B15: SENIOR TERM LOAN B
B16: Beginning balance | H16: ='LBO MODEL'!H14*INPUT!H30 | I16: =H19 | J16: =I19 | K16: =J19 | L16: =K19 | M16: =L19
B17: Mandatory amortization (1%) | I17: =-MIN(I16*0.01,I16) | J17: =-MIN(J16*0.01,J16) | K17: =-MIN(K16*0.01,K16) | L17: =-MIN(L16*0.01,L16) | M17: =-MIN(M16*0.01,M16)
B18: Cash sweep (75% excess FCF) | I18: =-MIN(I16+I17,MAX(0,I39*0.75)) | J18: =-MIN(J16+J17,MAX(0,J39*0.75)) | K18: =-MIN(K16+K17,MAX(0,K39*0.75)) | L18: =-MIN(L16+L17,MAX(0,L39*0.75)) | M18: =-MIN(M16+M17,MAX(0,M39*0.75))
B19: Ending balance | H19: =H16 | I19: =I16+I17+I18 | J19: =J16+J17+J18 | K19: =K16+K17+K18 | L19: =L16+L17+L18 | M19: =M16+M17+M18
B20: Interest expense (TLB) | I20: =-I16*'LBO MODEL'!$H$16 | J20: =-J16*'LBO MODEL'!$H$16 | K20: =-K16*'LBO MODEL'!$H$16 | L20: =-L16*'LBO MODEL'!$H$16 | M20: =-M16*'LBO MODEL'!$H$16
B22: MEZZANINE
B23: Beginning balance | H23: ='LBO MODEL'!H15*INPUT!H30 | I23: =H26 | J23: =I26 | K23: =J26 | L23: =K26 | M23: =L26
B24: PIK interest (5% capitalisé) | I24: =I23*0.05 | J24: =J23*0.05 | K24: =K23*0.05 | L24: =L23*0.05 | M24: =M23*0.05
B25: Bullet repayment (Y5) | M25: =-(M23+M24)
B26: Ending balance | H26: =H23 | I26: =I23+I24 | J26: =J23+J24 | K26: =K23+K24 | L26: =L23+L24 | M26: =M23+M24+M25
B27: Interest expense Mezz (cash 5%) | I27: =-I23*0.05 | J27: =-J23*0.05 | K27: =-K23*0.05 | L27: =-L23*0.05 | M27: =-M23*0.05
B29: TOTAL INTEREST EXPENSE | I29: =I20+I27 | J29: =J20+J27 | K29: =K20+K27 | L29: =L20+L27 | M29: =M20+M27
B30: Net Debt (Senior + Mezz - Cash) | H30: =H19+H26 | I30: =I19+I26 | J30: =J19+J26 | K30: =K19+K26 | L30: =L19+L26 | M30: =M19+M26
B31: Total Leverage (× EBITDA) | H31: =IFERROR(H30/H7,0) | I31: =IFERROR(I30/I7,0) | J31: =IFERROR(J30/J7,0) | K31: =IFERROR(K30/K7,0) | L31: =IFERROR(L30/L7,0) | M31: =IFERROR(M30/M7,0)
B32: Interest Coverage (EBIT/Int) | I32: =IFERROR(-I9/I29,0) | J32: =IFERROR(-J9/J29,0) | K32: =IFERROR(-K9/K29,0) | L32: =IFERROR(-L9/L29,0) | M32: =IFERROR(-M9/M29,0)
B33: 3. FCF LEVERED & TAX SHIELD (PE-grade — post-intérêts, post-tax)
H34: Y0 (LTM) | I34: Y1 | J34: Y2 | K34: Y3 | L34: Y4 | M34: Y5
B35: Tax Shield (intérêts × taux d'imposition) | H35: 0 | I35: =-I29*INPUT!$H$104 | J35: =-J29*INPUT!$H$104 | K35: =-K29*INPUT!$H$104 | L35: =-L29*INPUT!$H$104 | M35: =-M29*INPUT!$H$104
B36: EBT levered (EBIT + Intérêts) | H36: 0 | I36: =I9+I29 | J36: =J9+J29 | K36: =K9+K29 | L36: =L9+L29 | M36: =M9+M29
B37: Impôt cash (EBT × taux, si positif) | H37: 0 | I37: =-MAX(0,I36)*INPUT!$H$104 | J37: =-MAX(0,J36)*INPUT!$H$104 | K37: =-MAX(0,K36)*INPUT!$H$104 | L37: =-MAX(0,L36)*INPUT!$H$104 | M37: =-MAX(0,M36)*INPUT!$H$104
B38: NOPAT levered (EBT + Impôt cash) | H38: 0 | I38: =I36+I37 | J38: =J36+J37 | K38: =K36+K37 | L38: =L36+L37 | M38: =M36+M37
B39: FCF Levered (post-intérêts, post-tax) | H39: 0 | I39: =I38-I8+I10+I11 | J39: =J38-J8+J10+J11 | K39: =K38-K8+K10+K11 | L39: =L38-L8+L10+L11 | M39: =M38-M8+M10+M11
B40: Cash disponible pour service dette | H40: 0 | I40: =MAX(0,I39) | J40: =MAX(0,J39) | K40: =MAX(0,K39) | L40: =MAX(0,L39) | M40: =MAX(0,M39)
B41: COVENANT TESTING — Seuils bancaires
B42: Levier covenant (seuil max imposé par banques) | H42: N/A | I42: 6.5 | J42: 6 | K42: 5.5 | L42: 5 | M42: 4.5
B43: Levier réel (× EBITDA) | H43: =IFERROR(H30/H7,0) | I43: =IFERROR(I30/I7,0) | J43: =IFERROR(J30/J7,0) | K43: =IFERROR(K30/K7,0) | L43: =IFERROR(L30/L7,0) | M43: =IFERROR(M30/M7,0)
B44: ICR covenant (seuil min imposé par banques) | M44: 2
B45: ICR réel (EBIT / Intérêts) | H45: N/A | I45: =IFERROR(-I9/I29,0) | J45: =IFERROR(-J9/J29,0) | K45: =IFERROR(-K9/K29,0) | L45: =IFERROR(-L9/L29,0) | M45: =IFERROR(-M9/M29,0)
B46: Levier covenant ✓ / ✗ | H46: — | I46: =IF(I43<=I42,"✓ PASS","✗ BREACH") | J46: =IF(J43<=J42,"✓ PASS","✗ BREACH") | K46: =IF(K43<=K42,"✓ PASS","✗ BREACH") | L46: =IF(L43<=L42,"✓ PASS","✗ BREACH") | M46: =IF(M43<=M42,"✓ PASS","✗ BREACH")
B47: ICR covenant ✓ / ✗ | H47: — | I47: =IF(I45>=I44,"✓ PASS","✗ BREACH") | J47: =IF(J45>=J44,"✓ PASS","✗ BREACH") | K47: =IF(K45>=K44,"✓ PASS","✗ BREACH") | L47: =IF(L45>=L44,"✓ PASS","✗ BREACH") | M47: =IF(M45>=M44,"✓ PASS","✗ BREACH")
B48: EV exit (EBITDA × Multiple) | M48: =M7*'LBO MODEL'!$H$18
B49: − Net Debt at exit | M49: =-M30
B50: Equity exit (EV − Net Debt) | M50: =M48+M49
M56: EQUITY ENTRY | N56: ='LBO MODEL'!H12*INPUT!H30*(1+'LBO MODEL'!H20+'LBO MODEL'!H21)+INPUT!H34-('LBO MODEL'!H14+'LBO MODEL'!H15)*INPUT!H30
M59: EBITDA Y5 | N59: =M7
M60: NET DEBT Y5 | N60: =M30
M61: EQUITY EXIT | N61: =M50
M62: IRR BASE | N62: =IFERROR((N61/N56)^(1/'LBO MODEL'!H19)-1,0)
M63: MOIC BASE | N63: =IFERROR(N61/N56,0)
B65: 4. SCÉNARIOS BULL / BASE / BEAR (formules paramétrées) | M65: Scénario | P65: IRR | Q65: MOIC | R65: Lvg exit | S65: ICR exit
M66: BULL (rev +15%, marge +200bps, exit +1x) | P66: =IFERROR(((N59*1.15*('LBO MODEL'!$H$18+1)-N60*0.7)/N56)^(1/'LBO MODEL'!H19)-1,0) | Q66: =IFERROR((N59*1.15*('LBO MODEL'!$H$18+1)-N60*0.7)/N56,0) | R66: =M31*0.5 | S66: =M32*1.5
M67: BASE (hypothèses centrales) | P67: =N62 | Q67: =N63 | R67: =M31 | S67: =M32
M68: BEAR (rev -15%, marge -200bps, exit -1x) | P68: =IFERROR(((N59*0.85*('LBO MODEL'!$H$18-1)-N60*1.3)/N56)^(1/'LBO MODEL'!H19)-1,0) | Q68: =IFERROR((N59*0.85*('LBO MODEL'!$H$18-1)-N60*1.3)/N56,0) | R68: =M31*1.8 | S68: =M32*0.5
