Workbook

Sheet DASHBOARD
A1: FinSight IA · Tableau de Bord — Screening CAC 40 · 22/03/2026 | R1: Confidentiel · Usage interne
D3: =COUNTA('DONNÉES BRUTES'!A:A)-2 -> 40 | J3: {=COUNTA(_xlfn.UNIQUE(_xlfn._xlws.FILTER('DONNÉES BRUTES'!C3:C42,'DONNÉES BRUTES'!C3:C42<>"")))} -> 12 | P3: =_xlfn.XLOOKUP(MAX('DONNÉES BRUTES'!AB3:AB42),'DONNÉES BRUTES'!AB3:AB42,'DONNÉES BRUTES'!A3:A42)&" — "&MAX('DONNÉES BRUTES'!AB3:AB42)&"/100" -> RMS.PA — 75/100 | V3: 01/04/2026
D4: SOCIÉTÉS ANALYSÉES | J4: SECTEURS COUVERTS | P4: MEILLEUR SCORE GLOBAL | V4: DATE D'ANALYSE
B6: TOP 5 · Classements par Facteur d'Investissement
B7: # | C7: Ticker | D7: Société | E7: Score | F7: Mét. | H7: # | I7: Ticker | J7: Société | K7: Score | L7: Mét. | N7: # | O7: Ticker | P7: Société | Q7: Score | R7: Mét. | T7: # | U7: Ticker | V7: Société | W7: Score | X7: Mét.
B8: 1 | C8: {=IFERROR(INDEX('DONNÉES BRUTES'!A$3:A$42,MATCH(_xlfn.AGGREGATE(14,6,'DONNÉES BRUTES'!AB$3:AB$42*1000+(40-ROW('DONNÉES BRUTES'!AB$3:AB$42)+ROW('DONNÉES BRUTES'!AB$3)),1),'DONNÉES BRUTES'!AB$3:AB$42*1000+(40-ROW('DONNÉES BRUTES'!AB$3:AB$42)+ROW('DONNÉES BRUTES'!AB$3)),0)),"—")} -> RMS.PA | D8: {=IFERROR(LEFT(INDEX('DONNÉES BRUTES'!B$3:B$42,MATCH(_xlfn.AGGREGATE(14,6,'DONNÉES BRUTES'!AB$3:AB$42*1000+(40-ROW('DONNÉES BRUTES'!AB$3:AB$42)+ROW('DONNÉES BRUTES'!AB$3)),1),'DONNÉES BRUTES'!AB$3:AB$42*1000+(40-ROW('DONNÉES BRUTES'!AB$3:AB$42)+ROW('DONNÉES BRUTES'!AB$3)),0)),18),"—")} -> Hermès Internation | E8: {=IFERROR(INT(_xlfn.AGGREGATE(14,6,'DONNÉES BRUTES'!AB$3:AB$42*1000+(40-ROW('DONNÉES BRUTES'!AB$3:AB$42)+ROW('DONNÉES BRUTES'!AB$3)),1)/1000)&"/100","—")} -> 75/100 | F8: {=IFERROR(INDEX('DONNÉES BRUTES'!I$3:I$42,MATCH(_xlfn.AGGREGATE(14,6,'DONNÉES BRUTES'!AB$3:AB$42*1000+(40-ROW('DONNÉES BRUTES'!AB$3:AB$42)+ROW('DONNÉES BRUTES'!AB$3)),1),'DONNÉES BRUTES'!AB$3:AB$42*1000+(40-ROW('DONNÉES BRUTES'!AB$3:AB$42)+ROW('DONNÉES BRUTES'!AB$3)),0)),"—")} -> — | H8: 1 | I8: {=IFERROR(INDEX('DONNÉES BRUTES'!A$3:A$42,MATCH(_xlfn.AGGREGATE(14,6,'DONNÉES BRUTES'!Y$3:Y$42*1000+(40-ROW('DONNÉES BRUTES'!Y$3:Y$42)+ROW('DONNÉES BRUTES'!Y$3)),1),'DONNÉES BRUTES'!Y$3:Y$42*1000+(40-ROW('DONNÉES BRUTES'!Y$3:Y$42)+ROW('DONNÉES BRUTES'!Y$3)),0)),"—")} -> SAF.PA | J8: {=IFERROR(LEFT(INDEX('DONNÉES BRUTES'!B$3:B$42,MATCH(_xlfn.AGGREGATE(14,6,'DONNÉES BRUTES'!Y$3:Y$42*1000+(40-ROW('DONNÉES BRUTES'!Y$3:Y$42)+ROW('DONNÉES BRUTES'!Y$3)),1),'DONNÉES BRUTES'!Y$3:Y$42*1000+(40-ROW('DONNÉES BRUTES'!Y$3:Y$42)+ROW('DONNÉES BRUTES'!Y$3)),0)),18),"—")} -> Safran SA | K8: {=IFERROR(INT(_xlfn.AGGREGATE(14,6,'DONNÉES BRUTES'!Y$3:Y$42*1000+(40-ROW('DONNÉES BRUTES'!Y$3:Y$42)+ROW('DONNÉES BRUTES'!Y$3)),1)/1000)&"/100","—")} -> 100/100 | L8: {=IFERROR(INDEX('DONNÉES BRUTES'!P$3:P$42,MATCH(_xlfn.AGGREGATE(14,6,'DONNÉES BRUTES'!Y$3:Y$42*1000+(40-ROW('DONNÉES BRUTES'!Y$3:Y$42)+ROW('DONNÉES BRUTES'!Y$3)),1),'DONNÉES BRUTES'!Y$3:Y$42*1000+(40-ROW('DONNÉES BRUTES'!Y$3:Y$42)+ROW('DONNÉES BRUTES'!Y$3)),0)),"—")} -> +12.5% | N8: 1 | O8: {=IFERROR(INDEX('DONNÉES BRUTES'!A$3:A$42,MATCH(_xlfn.AGGREGATE(14,6,'DONNÉES BRUTES'!Z$3:Z$42*1000+(40-ROW('DONNÉES BRUTES'!Z$3:Z$42)+ROW('DONNÉES BRUTES'!Z$3)),1),'DONNÉES BRUTES'!Z$3:Z$42*1000+(40-ROW('DONNÉES BRUTES'!Z$3:Z$42)+ROW('DONNÉES BRUTES'!Z$3)),0)),"—")} -> DSY.PA | P8: {=IFERROR(LEFT(INDEX('DONNÉES BRUTES'!B$3:B$42,MATCH(_xlfn.AGGREGATE(14,6,'DONNÉES BRUTES'!Z$3:Z$42*1000+(40-ROW('DONNÉES BRUTES'!Z$3:Z$42)+ROW('DONNÉES BRUTES'!Z$3)),1),'DONNÉES BRUTES'!Z$3:Z$42*1000+(40-ROW('DONNÉES BRUTES'!Z$3:Z$42)+ROW('DONNÉES BRUTES'!Z$3)),0)),18),"—")} -> Dassault Systèmes | Q8: {=IFERROR(INT(_xlfn.AGGREGATE(14,6,'DONNÉES BRUTES'!Z$3:Z$42*1000+(40-ROW('DONNÉES BRUTES'!Z$3:Z$42)+ROW('DONNÉES BRUTES'!Z$3)),1)/1000)&"/100","—")} -> 100/100 | R8: {=IFERROR(INDEX('DONNÉES BRUTES'!U$3:U$42,MATCH(_xlfn.AGGREGATE(14,6,'DONNÉES BRUTES'!Z$3:Z$42*1000+(40-ROW('DONNÉES BRUTES'!Z$3:Z$42)+ROW('DONNÉES BRUTES'!Z$3)),1),'DONNÉES BRUTES'!Z$3:Z$42*1000+(40-ROW('DONNÉES BRUTES'!Z$3:Z$42)+ROW('DONNÉES BRUTES'!Z$3)),0)),"—")} -> — | T8: 1 | U8: {=IFERROR(INDEX('DONNÉES BRUTES'!A$3:A$42,MATCH(_xlfn.AGGREGATE(14,6,'DONNÉES BRUTES'!AA$3:AA$42*1000+(40-ROW('DONNÉES BRUTES'!AA$3:AA$42)+ROW('DONNÉES BRUTES'!AA$3)),1),'DONNÉES BRUTES'!AA$3:AA$42*1000+(40-ROW('DONNÉES BRUTES'!AA$3:AA$42)+ROW('DONNÉES BRUTES'!AA$3)),0)),"—")} -> ALO.PA | V8: {=IFERROR(LEFT(INDEX('DONNÉES BRUTES'!B$3:B$42,MATCH(_xlfn.AGGREGATE(14,6,'DONNÉES BRUTES'!AA$3:AA$42*1000+(40-ROW('DONNÉES BRUTES'!AA$3:AA$42)+ROW('DONNÉES BRUTES'!AA$3)),1),'DONNÉES BRUTES'!AA$3:AA$42*1000+(40-ROW('DONNÉES BRUTES'!AA$3:AA$42)+ROW('DONNÉES BRUTES'!AA$3)),0)),18),"—")} -> Alstom SA | W8: {=IFERROR(INT(_xlfn.AGGREGATE(14,6,'DONNÉES BRUTES'!AA$3:AA$42*1000+(40-ROW('DONNÉES BRUTES'!AA$3:AA$42)+ROW('DONNÉES BRUTES'!AA$3)),1)/1000)&"/100","—")} -> 100/100 | X8: {=IFERROR(INDEX('DONNÉES BRUTES'!P$3:P$42,MATCH(_xlfn.AGGREGATE(14,6,'DONNÉES BRUTES'!AA$3:AA$42*1000+(40-ROW('DONNÉES BRUTES'!AA$3:AA$42)+ROW('DONNÉES BRUTES'!AA$3)),1),'DONNÉES BRUTES'!AA$3:AA$42*1000+(40-ROW('DONNÉES BRUTES'!AA$3:AA$42)+ROW('DONNÉES BRUTES'!AA$3)),0)),"—")} -> +4.9%
B9: 2 | C9: {=IFERROR(INDEX('DONNÉES BRUTES'!A$3:A$42,MATCH(_xlfn.AGGREGATE(14,6,'DONNÉES BRUTES'!AB$3:AB$42*1000+(40-ROW('DONNÉES BRUTES'!AB$3:AB$42)+ROW('DONNÉES BRUTES'!AB$3)),2),'DONNÉES BRUTES'!AB$3:AB$42*1000+(40-ROW('DONNÉES BRUTES'!AB$3:AB$42)+ROW('DONNÉES BRUTES'!AB$3)),0)),"—")} -> AI.PA | D9: {=IFERROR(LEFT(INDEX('DONNÉES BRUTES'!B$3:B$42,MATCH(_xlfn.AGGREGATE(14,6,'DONNÉES BRUTES'!AB$3:AB$42*1000+(40-ROW('DONNÉES BRUTES'!AB$3:AB$42)+ROW('DONNÉES BRUTES'!AB$3)),2),'DONNÉES BRUTES'!AB$3:AB$42*1000+(40-ROW('DONNÉES BRUTES'!AB$3:AB$42)+ROW('DONNÉES BRUTES'!AB$3)),0)),18),"—")} -> L'Air Liquide S.A. | E9: {=IFERROR(INT(_xlfn.AGGREGATE(14,6,'DONNÉES BRUTES'!AB$3:AB$42*1000+(40-ROW('DONNÉES BRUTES'!AB$3:AB$42)+ROW('DONNÉES BRUTES'!AB$3)),2)/1000)&"/100","—")} -> 74/100 | F9: {=IFERROR(INDEX('DONNÉES BRUTES'!I$3:I$42,MATCH(_xlfn.AGGREGATE(14,6,'DONNÉES BRUTES'!AB$3:AB$42*1000+(40-ROW('DONNÉES BRUTES'!AB$3:AB$42)+ROW('DONNÉES BRUTES'!AB$3)),2),'DONNÉES BRUTES'!AB$3:AB$42*1000+(40-ROW('DONNÉES BRUTES'!AB$3:AB$42)+ROW('DONNÉES BRUTES'!AB$3)),0)),"—")} -> — | H9: 2 | I9: {=IFERROR(INDEX('DONNÉES BRUTES'!A$3:A$42,MATCH(_xlfn.AGGREGATE(14,6,'DONNÉES BRUTES'!Y$3:Y$42*1000+(40-ROW('DONNÉES BRUTES'!Y$3:Y$42)+ROW('DONNÉES BRUTES'!Y$3)),2),'DONNÉES BRUTES'!Y$3:Y$42*1000+(40-ROW('DONNÉES BRUTES'!Y$3:Y$42)+ROW('DONNÉES BRUTES'!Y$3)),0)),"—")} -> VIV.PA | J9: {=IFERROR(LEFT(INDEX('DONNÉES BRUTES'!B$3:B$42,MATCH(_xlfn.AGGREGATE(14,6,'DONNÉES BRUTES'!Y$3:Y$42*1000+(40-ROW('DONNÉES BRUTES'!Y$3:Y$42)+ROW('DONNÉES BRUTES'!Y$3)),2),'DONNÉES BRUTES'!Y$3:Y$42*1000+(40-ROW('DONNÉES BRUTES'!Y$3:Y$42)+ROW('DONNÉES BRUTES'!Y$3)),0)),18),"—")} -> Vivendi SE | K9: {=IFERROR(INT(_xlfn.AGGREGATE(14,6,'DONNÉES BRUTES'!Y$3:Y$42*1000+(40-ROW('DONNÉES BRUTES'!Y$3:Y$42)+ROW('DONNÉES BRUTES'!Y$3)),2)/1000)&"/100","—")} -> 97/100 | L9: {=IFERROR(INDEX('DONNÉES BRUTES'!P$3:P$42,MATCH(_xlfn.AGGREGATE(14,6,'DONNÉES BRUTES'!Y$3:Y$42*1000+(40-ROW('DONNÉES BRUTES'!Y$3:Y$42)+ROW('DONNÉES BRUTES'!Y$3)),2),'DONNÉES BRUTES'!Y$3:Y$42*1000+(40-ROW('DONNÉES BRUTES'!Y$3:Y$42)+ROW('DONNÉES BRUTES'!Y$3)),0)),"—")} -> +3.4% | N9: 2 | O9: {=IFERROR(INDEX('DONNÉES BRUTES'!A$3:A$42,MATCH(_xlfn.AGGREGATE(14,6,'DONNÉES BRUTES'!Z$3:Z$42*1000+(40-ROW('DONNÉES BRUTES'!Z$3:Z$42)+ROW('DONNÉES BRUTES'!Z$3)),2),'DONNÉES BRUTES'!Z$3:Z$42*1000+(40-ROW('DONNÉES BRUTES'!Z$3:Z$42)+ROW('DONNÉES BRUTES'!Z$3)),0)),"—")} -> SAN.PA | P9: {=IFERROR(LEFT(INDEX('DONNÉES BRUTES'!B$3:B$42,MATCH(_xlfn.AGGREGATE(14,6,'DONNÉES BRUTES'!Z$3:Z$42*1000+(40-ROW('DONNÉES BRUTES'!Z$3:Z$42)+ROW('DONNÉES BRUTES'!Z$3)),2),'DONNÉES BRUTES'!Z$3:Z$42*1000+(40-ROW('DONNÉES BRUTES'!Z$3:Z$42)+ROW('DONNÉES BRUTES'!Z$3)),0)),18),"—")} -> Sanofi | Q9: {=IFERROR(INT(_xlfn.AGGREGATE(14,6,'DONNÉES BRUTES'!Z$3:Z$42*1000+(40-ROW('DONNÉES BRUTES'!Z$3:Z$42)+ROW('DONNÉES BRUTES'!Z$3)),2)/1000)&"/100","—")} -> 97/100 | R9: {=IFERROR(INDEX('DONNÉES BRUTES'!U$3:U$42,MATCH(_xlfn.AGGREGATE(14,6,'DONNÉES BRUTES'!Z$3:Z$42*1000+(40-ROW('DONNÉES BRUTES'!Z$3:Z$42)+ROW('DONNÉES BRUTES'!Z$3)),2),'DONNÉES BRUTES'!Z$3:Z$42*1000+(40-ROW('DONNÉES BRUTES'!Z$3:Z$42)+ROW('DONNÉES BRUTES'!Z$3)),0)),"—")} -> — | T9: 2 | U9: {=IFERROR(INDEX('DONNÉES BRUTES'!A$3:A$42,MATCH(_xlfn.AGGREGATE(14,6,'DONNÉES BRUTES'!AA$3:AA$42*1000+(40-ROW('DONNÉES BRUTES'!AA$3:AA$42)+ROW('DONNÉES BRUTES'!AA$3)),2),'DONNÉES BRUTES'!AA$3:AA$42*1000+(40-ROW('DONNÉES BRUTES'!AA$3:AA$42)+ROW('DONNÉES BRUTES'!AA$3)),0)),"—")} -> AIR.PA | V9: {=IFERROR(LEFT(INDEX('DONNÉES BRUTES'!B$3:B$42,MATCH(_xlfn.AGGREGATE(14,6,'DONNÉES BRUTES'!AA$3:AA$42*1000+(40-ROW('DONNÉES BRUTES'!AA$3:AA$42)+ROW('DONNÉES BRUTES'!AA$3)),2),'DONNÉES BRUTES'!AA$3:AA$42*1000+(40-ROW('DONNÉES BRUTES'!AA$3:AA$42)+ROW('DONNÉES BRUTES'!AA$3)),0)),18),"—")} -> Airbus SE | W9: {=IFERROR(INT(_xlfn.AGGREGATE(14,6,'DONNÉES BRUTES'!AA$3:AA$42*1000+(40-ROW('DONNÉES BRUTES'!AA$3:AA$42)+ROW('DONNÉES BRUTES'!AA$3)),2)/1000)&"/100","—")} -> 97/100 | X9: {=IFERROR(INDEX('DONNÉES BRUTES'!P$3:P$42,MATCH(_xlfn.AGGREGATE(14,6,'DONNÉES BRUTES'!AA$3:AA$42*1000+(40-ROW('DONNÉES BRUTES'!AA$3:AA$42)+ROW('DONNÉES BRUTES'!AA$3)),2),'DONNÉES BRUTES'!AA$3:AA$42*1000+(40-ROW('DONNÉES BRUTES'!AA$3:AA$42)+ROW('DONNÉES BRUTES'!AA$3)),0)),"—")} -> +6.1%
B10: 3 | C10: {=IFERROR(INDEX('DONNÉES BRUTES'!A$3:A$42,MATCH(_xlfn.AGGREGATE(14,6,'DONNÉES BRUTES'!AB$3:AB$42*1000+(40-ROW('DONNÉES BRUTES'!AB$3:AB$42)+ROW('DONNÉES BRUTES'!AB$3)),3),'DONNÉES BRUTES'!AB$3:AB$42*1000+(40-ROW('DONNÉES BRUTES'!AB$3:AB$42)+ROW('DONNÉES BRUTES'!AB$3)),0)),"—")} -> DSY.PA | D10: {=IFERROR(LEFT(INDEX('DONNÉES BRUTES'!B$3:B$42,MATCH(_xlfn.AGGREGATE(14,6,'DONNÉES BRUTES'!AB$3:AB$42*1000+(40-ROW('DONNÉES BRUTES'!AB$3:AB$42)+ROW('DONNÉES BRUTES'!AB$3)),3),'DONNÉES BRUTES'!AB$3:AB$42*1000+(40-ROW('DONNÉES BRUTES'!AB$3:AB$42)+ROW('DONNÉES BRUTES'!AB$3)),0)),18),"—")} -> Dassault Systèmes | E10: {=IFERROR(INT(_xlfn.AGGREGATE(14,6,'DONNÉES BRUTES'!AB$3:AB$42*1000+(40-ROW('DONNÉES BRUTES'!AB$3:AB$42)+ROW('DONNÉES BRUTES'!AB$3)),3)/1000)&"/100","—")} -> 72/100 | F10: {=IFERROR(INDEX('DONNÉES BRUTES'!I$3:I$42,MATCH(_xlfn.AGGREGATE(14,6,'DONNÉES BRUTES'!AB$3:AB$42*1000+(40-ROW('DONNÉES BRUTES'!AB$3:AB$42)+ROW('DONNÉES BRUTES'!AB$3)),3),'DONNÉES BRUTES'!AB$3:AB$42*1000+(40-ROW('DONNÉES BRUTES'!AB$3:AB$42)+ROW('DONNÉES BRUTES'!AB$3)),0)),"—")} -> — | H10: 3 | I10: {=IFERROR(INDEX('DONNÉES BRUTES'!A$3:A$42,MATCH(_xlfn.AGGREGATE(14,6,'DONNÉES BRUTES'!Y$3:Y$42*1000+(40-ROW('DONNÉES BRUTES'!Y$3:Y$42)+ROW('DONNÉES BRUTES'!Y$3)),3),'DONNÉES BRUTES'!Y$3:Y$42*1000+(40-ROW('DONNÉES BRUTES'!Y$3:Y$42)+ROW('DONNÉES BRUTES'!Y$3)),0)),"—")} -> ALO.PA | J10: {=IFERROR(LEFT(INDEX('DONNÉES BRUTES'!B$3:B$42,MATCH(_xlfn.AGGREGATE(14,6,'DONNÉES BRUTES'!Y$3:Y$42*1000+(40-ROW('DONNÉES BRUTES'!Y$3:Y$42)+ROW('DONNÉES BRUTES'!Y$3)),3),'DONNÉES BRUTES'!Y$3:Y$42*1000+(40-ROW('DONNÉES BRUTES'!Y$3:Y$42)+ROW('DONNÉES BRUTES'!Y$3)),0)),18),"—")} -> Alstom SA | K10: {=IFERROR(INT(_xlfn.AGGREGATE(14,6,'DONNÉES BRUTES'!Y$3:Y$42*1000+(40-ROW('DONNÉES BRUTES'!Y$3:Y$42)+ROW('DONNÉES BRUTES'!Y$3)),3)/1000)&"/100","—")} -> 95/100 | L10: {=IFERROR(INDEX('DONNÉES BRUTES'!P$3:P$42,MATCH(_xlfn.AGGREGATE(14,6,'DONNÉES BRUTES'!Y$3:Y$42*1000+(40-ROW('DONNÉES BRUTES'!Y$3:Y$42)+ROW('DONNÉES BRUTES'!Y$3)),3),'DONNÉES BRUTES'!Y$3:Y$42*1000+(40-ROW('DONNÉES BRUTES'!Y$3:Y$42)+ROW('DONNÉES BRUTES'!Y$3)),0)),"—")} -> +4.9% | N10: 3 | O10: {=IFERROR(INDEX('DONNÉES BRUTES'!A$3:A$42,MATCH(_xlfn.AGGREGATE(14,6,'DONNÉES BRUTES'!Z$3:Z$42*1000+(40-ROW('DONNÉES BRUTES'!Z$3:Z$42)+ROW('DONNÉES BRUTES'!Z$3)),3),'DONNÉES BRUTES'!Z$3:Z$42*1000+(40-ROW('DONNÉES BRUTES'!Z$3:Z$42)+ROW('DONNÉES BRUTES'!Z$3)),0)),"—")} -> URW.PA | P10: {=IFERROR(LEFT(INDEX('DONNÉES BRUTES'!B$3:B$42,MATCH(_xlfn.AGGREGATE(14,6,'DONNÉES BRUTES'!Z$3:Z$42*1000+(40-ROW('DONNÉES BRUTES'!Z$3:Z$42)+ROW('DONNÉES BRUTES'!Z$3)),3),'DONNÉES BRUTES'!Z$3:Z$42*1000+(40-ROW('DONNÉES BRUTES'!Z$3:Z$42)+ROW('DONNÉES BRUTES'!Z$3)),0)),18),"—")} -> Unibail-Rodamco-We | Q10: {=IFERROR(INT(_xlfn.AGGREGATE(14,6,'DONNÉES BRUTES'!Z$3:Z$42*1000+(40-ROW('DONNÉES BRUTES'!Z$3:Z$42)+ROW('DONNÉES BRUTES'!Z$3)),3)/1000)&"/100","—")} -> 95/100 | R10: {=IFERROR(INDEX('DONNÉES BRUTES'!U$3:U$42,MATCH(_xlfn.AGGREGATE(14,6,'DONNÉES BRUTES'!Z$3:Z$42*1000+(40-ROW('DONNÉES BRUTES'!Z$3:Z$42)+ROW('DONNÉES BRUTES'!Z$3)),3),'DONNÉES BRUTES'!Z$3:Z$42*1000+(40-ROW('DONNÉES BRUTES'!Z$3:Z$42)+ROW('DONNÉES BRUTES'!Z$3)),0)),"—")} -> 1.22 | T10: 3 | U10: {=IFERROR(INDEX('DONNÉES BRUTES'!A$3:A$42,MATCH(_xlfn.AGGREGATE(14,6,'DONNÉES BRUTES'!AA$3:AA$42*1000+(40-ROW('DONNÉES BRUTES'!AA$3:AA$42)+ROW('DONNÉES BRUTES'!AA$3)),3),'DONNÉES BRUTES'!AA$3:AA$42*1000+(40-ROW('DONNÉES BRUTES'!AA$3:AA$42)+ROW('DONNÉES BRUTES'!AA$3)),0)),"—")} -> BNP.PA | V10: {=IFERROR(LEFT(INDEX('DONNÉES BRUTES'!B$3:B$42,MATCH(_xlfn.AGGREGATE(14,6,'DONNÉES BRUTES'!AA$3:AA$42*1000+(40-ROW('DONNÉES BRUTES'!AA$3:AA$42)+ROW('DONNÉES BRUTES'!AA$3)),3),'DONNÉES BRUTES'!AA$3:AA$42*1000+(40-ROW('DONNÉES BRUTES'!AA$3:AA$42)+ROW('DONNÉES BRUTES'!AA$3)),0)),18),"—")} -> BNP Paribas SA | W10: {=IFERROR(INT(_xlfn.AGGREGATE(14,6,'DONNÉES BRUTES'!AA$3:AA$42*1000+(40-ROW('DONNÉES BRUTES'!AA$3:AA$42)+ROW('DONNÉES BRUTES'!AA$3)),3)/1000)&"/100","—")} -> 95/100 | X10: {=IFERROR(INDEX('DONNÉES BRUTES'!P$3:P$42,MATCH(_xlfn.AGGREGATE(14,6,'DONNÉES BRUTES'!AA$3:AA$42*1000+(40-ROW('DONNÉES BRUTES'!AA$3:AA$42)+ROW('DONNÉES BRUTES'!AA$3)),3),'DONNÉES BRUTES'!AA$3:AA$42*1000+(40-ROW('DONNÉES BRUTES'!AA$3:AA$42)+ROW('DONNÉES BRUTES'!AA$3)),0)),"—")} -> +4.5%
B11: 4 | C11: {=IFERROR(INDEX('DONNÉES BRUTES'!A$3:A$42,MATCH(_xlfn.AGGREGATE(14,6,'DONNÉES BRUTES'!AB$3:AB$42*1000+(40-ROW('DONNÉES BRUTES'!AB$3:AB$42)+ROW('DONNÉES BRUTES'!AB$3)),4),'DONNÉES BRUTES'!AB$3:AB$42*1000+(40-ROW('DONNÉES BRUTES'!AB$3:AB$42)+ROW('DONNÉES BRUTES'!AB$3)),0)),"—")} -> ERF.PA | D11: {=IFERROR(LEFT(INDEX('DONNÉES BRUTES'!B$3:B$42,MATCH(_xlfn.AGGREGATE(14,6,'DONNÉES BRUTES'!AB$3:AB$42*1000+(40-ROW('DONNÉES BRUTES'!AB$3:AB$42)+ROW('DONNÉES BRUTES'!AB$3)),4),'DONNÉES BRUTES'!AB$3:AB$42*1000+(40-ROW('DONNÉES BRUTES'!AB$3:AB$42)+ROW('DONNÉES BRUTES'!AB$3)),0)),18),"—")} -> Eurofins Scientifi | E11: {=IFERROR(INT(_xlfn.AGGREGATE(14,6,'DONNÉES BRUTES'!AB$3:AB$42*1000+(40-ROW('DONNÉES BRUTES'!AB$3:AB$42)+ROW('DONNÉES BRUTES'!AB$3)),4)/1000)&"/100","—")} -> 72/100 | F11: {=IFERROR(INDEX('DONNÉES BRUTES'!I$3:I$42,MATCH(_xlfn.AGGREGATE(14,6,'DONNÉES BRUTES'!AB$3:AB$42*1000+(40-ROW('DONNÉES BRUTES'!AB$3:AB$42)+ROW('DONNÉES BRUTES'!AB$3)),4),'DONNÉES BRUTES'!AB$3:AB$42*1000+(40-ROW('DONNÉES BRUTES'!AB$3:AB$42)+ROW('DONNÉES BRUTES'!AB$3)),0)),"—")} -> — | H11: 4 | I11: {=IFERROR(INDEX('DONNÉES BRUTES'!A$3:A$42,MATCH(_xlfn.AGGREGATE(14,6,'DONNÉES BRUTES'!Y$3:Y$42*1000+(40-ROW('DONNÉES BRUTES'!Y$3:Y$42)+ROW('DONNÉES BRUTES'!Y$3)),4),'DONNÉES BRUTES'!Y$3:Y$42*1000+(40-ROW('DONNÉES BRUTES'!Y$3:Y$42)+ROW('DONNÉES BRUTES'!Y$3)),0)),"—")} -> URW.PA | J11: {=IFERROR(LEFT(INDEX('DONNÉES BRUTES'!B$3:B$42,MATCH(_xlfn.AGGREGATE(14,6,'DONNÉES BRUTES'!Y$3:Y$42*1000+(40-ROW('DONNÉES BRUTES'!Y$3:Y$42)+ROW('DONNÉES BRUTES'!Y$3)),4),'DONNÉES BRUTES'!Y$3:Y$42*1000+(40-ROW('DONNÉES BRUTES'!Y$3:Y$42)+ROW('DONNÉES BRUTES'!Y$3)),0)),18),"—")} -> Unibail-Rodamco-We | K11: {=IFERROR(INT(_xlfn.AGGREGATE(14,6,'DONNÉES BRUTES'!Y$3:Y$42*1000+(40-ROW('DONNÉES BRUTES'!Y$3:Y$42)+ROW('DONNÉES BRUTES'!Y$3)),4)/1000)&"/100","—")} -> 92/100 | L11: {=IFERROR(INDEX('DONNÉES BRUTES'!P$3:P$42,MATCH(_xlfn.AGGREGATE(14,6,'DONNÉES BRUTES'!Y$3:Y$42*1000+(40-ROW('DONNÉES BRUTES'!Y$3:Y$42)+ROW('DONNÉES BRUTES'!Y$3)),4),'DONNÉES BRUTES'!Y$3:Y$42*1000+(40-ROW('DONNÉES BRUTES'!Y$3:Y$42)+ROW('DONNÉES BRUTES'!Y$3)),0)),"—")} -> -6.1% | N11: 4 | O11: {=IFERROR(INDEX('DONNÉES BRUTES'!A$3:A$42,MATCH(_xlfn.AGGREGATE(14,6,'DONNÉES BRUTES'!Z$3:Z$42*1000+(40-ROW('DONNÉES BRUTES'!Z$3:Z$42)+ROW('DONNÉES BRUTES'!Z$3)),4),'DONNÉES BRUTES'!Z$3:Z$42*1000+(40-ROW('DONNÉES BRUTES'!Z$3:Z$42)+ROW('DONNÉES BRUTES'!Z$3)),0)),"—")} -> ACA.PA | P11: {=IFERROR(LEFT(INDEX('DONNÉES BRUTES'!B$3:B$42,MATCH(_xlfn.AGGREGATE(14,6,'DONNÉES BRUTES'!Z$3:Z$42*1000+(40-ROW('DONNÉES BRUTES'!Z$3:Z$42)+ROW('DONNÉES BRUTES'!Z$3)),4),'DONNÉES BRUTES'!Z$3:Z$42*1000+(40-ROW('DONNÉES BRUTES'!Z$3:Z$42)+ROW('DONNÉES BRUTES'!Z$3)),0)),18),"—")} -> Crédit Agricole S. | Q11: {=IFERROR(INT(_xlfn.AGGREGATE(14,6,'DONNÉES BRUTES'!Z$3:Z$42*1000+(40-ROW('DONNÉES BRUTES'!Z$3:Z$42)+ROW('DONNÉES BRUTES'!Z$3)),4)/1000)&"/100","—")} -> 92/100 | R11: {=IFERROR(INDEX('DONNÉES BRUTES'!U$3:U$42,MATCH(_xlfn.AGGREGATE(14,6,'DONNÉES BRUTES'!Z$3:Z$42*1000+(40-ROW('DONNÉES BRUTES'!Z$3:Z$42)+ROW('DONNÉES BRUTES'!Z$3)),4),'DONNÉES BRUTES'!Z$3:Z$42*1000+(40-ROW('DONNÉES BRUTES'!Z$3:Z$42)+ROW('DONNÉES BRUTES'!Z$3)),0)),"—")} -> — | T11: 4 | U11: {=IFERROR(INDEX('DONNÉES BRUTES'!A$3:A$42,MATCH(_xlfn.AGGREGATE(14,6,'DONNÉES BRUTES'!AA$3:AA$42*1000+(40-ROW('DONNÉES BRUTES'!AA$3:AA$42)+ROW('DONNÉES BRUTES'!AA$3)),4),'DONNÉES BRUTES'!AA$3:AA$42*1000+(40-ROW('DONNÉES BRUTES'!AA$3:AA$42)+ROW('DONNÉES BRUTES'!AA$3)),0)),"—")} -> CS.PA | V11: {=IFERROR(LEFT(INDEX('DONNÉES BRUTES'!B$3:B$42,MATCH(_xlfn.AGGREGATE(14,6,'DONNÉES BRUTES'!AA$3:AA$42*1000+(40-ROW('DONNÉES BRUTES'!AA$3:AA$42)+ROW('DONNÉES BRUTES'!AA$3)),4),'DONNÉES BRUTES'!AA$3:AA$42*1000+(40-ROW('DONNÉES BRUTES'!AA$3:AA$42)+ROW('DONNÉES BRUTES'!AA$3)),0)),18),"—")} -> AXA SA | W11: {=IFERROR(INT(_xlfn.AGGREGATE(14,6,'DONNÉES BRUTES'!AA$3:AA$42*1000+(40-ROW('DONNÉES BRUTES'!AA$3:AA$42)+ROW('DONNÉES BRUTES'!AA$3)),4)/1000)&"/100","—")} -> 92/100 | X11: {=IFERROR(INDEX('DONNÉES BRUTES'!P$3:P$42,MATCH(_xlfn.AGGREGATE(14,6,'DONNÉES BRUTES'!AA$3:AA$42*1000+(40-ROW('DONNÉES BRUTES'!AA$3:AA$42)+ROW('DONNÉES BRUTES'!AA$3)),4),'DONNÉES BRUTES'!AA$3:AA$42*1000+(40-ROW('DONNÉES BRUTES'!AA$3:AA$42)+ROW('DONNÉES BRUTES'!AA$3)),0)),"—")} -> +5.7%
B12: 5 | C12: {=IFERROR(INDEX('DONNÉES BRUTES'!A$3:A$42,MATCH(_xlfn.AGGREGATE(14,6,'DONNÉES BRUTES'!AB$3:AB$42*1000+(40-ROW('DONNÉES BRUTES'!AB$3:AB$42)+ROW('DONNÉES BRUTES'!AB$3)),5),'DONNÉES BRUTES'!AB$3:AB$42*1000+(40-ROW('DONNÉES BRUTES'!AB$3:AB$42)+ROW('DONNÉES BRUTES'!AB$3)),0)),"—")} -> SAN.PA | D12: {=IFERROR(LEFT(INDEX('DONNÉES BRUTES'!B$3:B$42,MATCH(_xlfn.AGGREGATE(14,6,'DONNÉES BRUTES'!AB$3:AB$42*1000+(40-ROW('DONNÉES BRUTES'!AB$3:AB$42)+ROW('DONNÉES BRUTES'!AB$3)),5),'DONNÉES BRUTES'!AB$3:AB$42*1000+(40-ROW('DONNÉES BRUTES'!AB$3:AB$42)+ROW('DONNÉES BRUTES'!AB$3)),0)),18),"—")} -> Sanofi | E12: {=IFERROR(INT(_xlfn.AGGREGATE(14,6,'DONNÉES BRUTES'!AB$3:AB$42*1000+(40-ROW('DONNÉES BRUTES'!AB$3:AB$42)+ROW('DONNÉES BRUTES'!AB$3)),5)/1000)&"/100","—")} -> 72/100 | F12: {=IFERROR(INDEX('DONNÉES BRUTES'!I$3:I$42,MATCH(_xlfn.AGGREGATE(14,6,'DONNÉES BRUTES'!AB$3:AB$42*1000+(40-ROW('DONNÉES BRUTES'!AB$3:AB$42)+ROW('DONNÉES BRUTES'!AB$3)),5),'DONNÉES BRUTES'!AB$3:AB$42*1000+(40-ROW('DONNÉES BRUTES'!AB$3:AB$42)+ROW('DONNÉES BRUTES'!AB$3)),0)),"—")} -> — | H12: 5 | I12: {=IFERROR(INDEX('DONNÉES BRUTES'!A$3:A$42,MATCH(_xlfn.AGGREGATE(14,6,'DONNÉES BRUTES'!Y$3:Y$42*1000+(40-ROW('DONNÉES BRUTES'!Y$3:Y$42)+ROW('DONNÉES BRUTES'!Y$3)),5),'DONNÉES BRUTES'!Y$3:Y$42*1000+(40-ROW('DONNÉES BRUTES'!Y$3:Y$42)+ROW('DONNÉES BRUTES'!Y$3)),0)),"—")} -> HO.PA | J12: {=IFERROR(LEFT(INDEX('DONNÉES BRUTES'!B$3:B$42,MATCH(_xlfn.AGGREGATE(14,6,'DONNÉES BRUTES'!Y$3:Y$42*1000+(40-ROW('DONNÉES BRUTES'!Y$3:Y$42)+ROW('DONNÉES BRUTES'!Y$3)),5),'DONNÉES BRUTES'!Y$3:Y$42*1000+(40-ROW('DONNÉES BRUTES'!Y$3:Y$42)+ROW('DONNÉES BRUTES'!Y$3)),0)),18),"—")} -> Thales S.A. | K12: {=IFERROR(INT(_xlfn.AGGREGATE(14,6,'DONNÉES BRUTES'!Y$3:Y$42*1000+(40-ROW('DONNÉES BRUTES'!Y$3:Y$42)+ROW('DONNÉES BRUTES'!Y$3)),5)/1000)&"/100","—")} -> 89/100 | L12: {=IFERROR(INDEX('DONNÉES BRUTES'!P$3:P$42,MATCH(_xlfn.AGGREGATE(14,6,'DONNÉES BRUTES'!Y$3:Y$42*1000+(40-ROW('DONNÉES BRUTES'!Y$3:Y$42)+ROW('DONNÉES BRUTES'!Y$3)),5),'DONNÉES BRUTES'!Y$3:Y$42*1000+(40-ROW('DONNÉES BRUTES'!Y$3:Y$42)+ROW('DONNÉES BRUTES'!Y$3)),0)),"—")} -> +7.6% | N12: 5 | O12: {=IFERROR(INDEX('DONNÉES BRUTES'!A$3:A$42,MATCH(_xlfn.AGGREGATE(14,6,'DONNÉES BRUTES'!Z$3:Z$42*1000+(40-ROW('DONNÉES BRUTES'!Z$3:Z$42)+ROW('DONNÉES BRUTES'!Z$3)),5),'DONNÉES BRUTES'!Z$3:Z$42*1000+(40-ROW('DONNÉES BRUTES'!Z$3:Z$42)+ROW('DONNÉES BRUTES'!Z$3)),0)),"—")} -> RMS.PA | P12: {=IFERROR(LEFT(INDEX('DONNÉES BRUTES'!B$3:B$42,MATCH(_xlfn.AGGREGATE(14,6,'DONNÉES BRUTES'!Z$3:Z$42*1000+(40-ROW('DONNÉES BRUTES'!Z$3:Z$42)+ROW('DONNÉES BRUTES'!Z$3)),5),'DONNÉES BRUTES'!Z$3:Z$42*1000+(40-ROW('DONNÉES BRUTES'!Z$3:Z$42)+ROW('DONNÉES BRUTES'!Z$3)),0)),18),"—")} -> Hermès Internation | Q12: {=IFERROR(INT(_xlfn.AGGREGATE(14,6,'DONNÉES BRUTES'!Z$3:Z$42*1000+(40-ROW('DONNÉES BRUTES'!Z$3:Z$42)+ROW('DONNÉES BRUTES'!Z$3)),5)/1000)&"/100","—")} -> 90/100 | R12: {=IFERROR(INDEX('DONNÉES BRUTES'!U$3:U$42,MATCH(_xlfn.AGGREGATE(14,6,'DONNÉES BRUTES'!Z$3:Z$42*1000+(40-ROW('DONNÉES BRUTES'!Z$3:Z$42)+ROW('DONNÉES BRUTES'!Z$3)),5),'DONNÉES BRUTES'!Z$3:Z$42*1000+(40-ROW('DONNÉES BRUTES'!Z$3:Z$42)+ROW('DONNÉES BRUTES'!Z$3)),0)),"—")} -> 9.47 | T12: 5 | U12: {=IFERROR(INDEX('DONNÉES BRUTES'!A$3:A$42,MATCH(_xlfn.AGGREGATE(14,6,'DONNÉES BRUTES'!AA$3:AA$42*1000+(40-ROW('DONNÉES BRUTES'!AA$3:AA$42)+ROW('DONNÉES BRUTES'!AA$3)),5),'DONNÉES BRUTES'!AA$3:AA$42*1000+(40-ROW('DONNÉES BRUTES'!AA$3:AA$42)+ROW('DONNÉES BRUTES'!AA$3)),0)),"—")} -> AI.PA | V12: {=IFERROR(LEFT(INDEX('DONNÉES BRUTES'!B$3:B$42,MATCH(_xlfn.AGGREGATE(14,6,'DONNÉES BRUTES'!AA$3:AA$42*1000+(40-ROW('DONNÉES BRUTES'!AA$3:AA$42)+ROW('DONNÉES BRUTES'!AA$3)),5),'DONNÉES BRUTES'!AA$3:AA$42*1000+(40-ROW('DONNÉES BRUTES'!AA$3:AA$42)+ROW('DONNÉES BRUTES'!AA$3)),0)),18),"—")} -> L'Air Liquide S.A. | W12: {=IFERROR(INT(_xlfn.AGGREGATE(14,6,'DONNÉES BRUTES'!AA$3:AA$42*1000+(40-ROW('DONNÉES BRUTES'!AA$3:AA$42)+ROW('DONNÉES BRUTES'!AA$3)),5)/1000)&"/100","—")} -> 90/100 | X12: {=IFERROR(INDEX('DONNÉES BRUTES'!P$3:P$42,MATCH(_xlfn.AGGREGATE(14,6,'DONNÉES BRUTES'!AA$3:AA$42*1000+(40-ROW('DONNÉES BRUTES'!AA$3:AA$42)+ROW('DONNÉES BRUTES'!AA$3)),5),'DONNÉES BRUTES'!AA$3:AA$42*1000+(40-ROW('DONNÉES BRUTES'!AA$3:AA$42)+ROW('DONNÉES BRUTES'!AA$3)),0)),"—")} -> -0.4%
B14: TOP 10 GLOBAL · Score Composite · Value / Growth / Quality / Momentum
B15: # | C15: Ticker | D15: Société | E15: Secteur | F15: Score | H15: Growth | I15: Quality | J15: Momentum | K15: Mg.EBITDA | L15: Croiss. | N15: Next Earn. | R15: Signal
B16: 1 | C16: {=IFERROR(INDEX('DONNÉES BRUTES'!A$3:A$42,MATCH(_xlfn.AGGREGATE(14,6,'DONNÉES BRUTES'!AB$3:AB$42*1000+(40-ROW('DONNÉES BRUTES'!AB$3:AB$42)+ROW('DONNÉES BRUTES'!AB$3)),1),'DONNÉES BRUTES'!AB$3:AB$42*1000+(40-ROW('DONNÉES BRUTES'!AB$3:AB$42)+ROW('DONNÉES BRUTES'!AB$3)),0)),"—")} -> RMS.PA | D16: {=IFERROR(LEFT(IFERROR(INDEX('DONNÉES BRUTES'!B$3:B$42,MATCH(_xlfn.AGGREGATE(14,6,'DONNÉES BRUTES'!AB$3:AB$42*1000+(40-ROW('DONNÉES BRUTES'!AB$3:AB$42)+ROW('DONNÉES BRUTES'!AB$3)),1),'DONNÉES BRUTES'!AB$3:AB$42*1000+(40-ROW('DONNÉES BRUTES'!AB$3:AB$42)+ROW('DONNÉES BRUTES'!AB$3)),0)),"—"),18),"—")} -> Hermès Internation | E16: {=IFERROR(INDEX('DONNÉES BRUTES'!C$3:C$42,MATCH(_xlfn.AGGREGATE(14,6,'DONNÉES BRUTES'!AB$3:AB$42*1000+(40-ROW('DONNÉES BRUTES'!AB$3:AB$42)+ROW('DONNÉES BRUTES'!AB$3)),1),'DONNÉES BRUTES'!AB$3:AB$42*1000+(40-ROW('DONNÉES BRUTES'!AB$3:AB$42)+ROW('DONNÉES BRUTES'!AB$3)),0)),"—")} -> Consumer Disc. | F16: {=IFERROR(INT(_xlfn.AGGREGATE(14,6,'DONNÉES BRUTES'!AB$3:AB$42*1000+(40-ROW('DONNÉES BRUTES'!AB$3:AB$42)+ROW('DONNÉES BRUTES'!AB$3)),1)/1000)&"/100","—")} -> 75/100 | H16: {=IFERROR(INDEX('DONNÉES BRUTES'!Y$3:Y$42,MATCH(_xlfn.AGGREGATE(14,6,'DONNÉES BRUTES'!AB$3:AB$42*1000+(40-ROW('DONNÉES BRUTES'!AB$3:AB$42)+ROW('DONNÉES BRUTES'!AB$3)),1),'DONNÉES BRUTES'!AB$3:AB$42*1000+(40-ROW('DONNÉES BRUTES'!AB$3:AB$42)+ROW('DONNÉES BRUTES'!AB$3)),0)),"—")} -> 74 | I16: {=IFERROR(INDEX('DONNÉES BRUTES'!Z$3:Z$42,MATCH(_xlfn.AGGREGATE(14,6,'DONNÉES BRUTES'!AB$3:AB$42*1000+(40-ROW('DONNÉES BRUTES'!AB$3:AB$42)+ROW('DONNÉES BRUTES'!AB$3)),1),'DONNÉES BRUTES'!AB$3:AB$42*1000+(40-ROW('DONNÉES BRUTES'!AB$3:AB$42)+ROW('DONNÉES BRUTES'!AB$3)),0)),"—")} -> 90 | J16: {=IFERROR(INDEX('DONNÉES BRUTES'!AA$3:AA$42,MATCH(_xlfn.AGGREGATE(14,6,'DONNÉES BRUTES'!AB$3:AB$42*1000+(40-ROW('DONNÉES BRUTES'!AB$3:AB$42)+ROW('DONNÉES BRUTES'!AB$3)),1),'DONNÉES BRUTES'!AB$3:AB$42*1000+(40-ROW('DONNÉES BRUTES'!AB$3:AB$42)+ROW('DONNÉES BRUTES'!AB$3)),0)),"—")} -> 62 | K16: {=IFERROR(INDEX('DONNÉES BRUTES'!N$3:N$42,MATCH(_xlfn.AGGREGATE(14,6,'DONNÉES BRUTES'!AB$3:AB$42*1000+(40-ROW('DONNÉES BRUTES'!AB$3:AB$42)+ROW('DONNÉES BRUTES'!AB$3)),1),'DONNÉES BRUTES'!AB$3:AB$42*1000+(40-ROW('DONNÉES BRUTES'!AB$3:AB$42)+ROW('DONNÉES BRUTES'!AB$3)),0)),"—")} -> 46.8% | L16: {=IFERROR(INDEX('DONNÉES BRUTES'!P$3:P$42,MATCH(_xlfn.AGGREGATE(14,6,'DONNÉES BRUTES'!AB$3:AB$42*1000+(40-ROW('DONNÉES BRUTES'!AB$3:AB$42)+ROW('DONNÉES BRUTES'!AB$3)),1),'DONNÉES BRUTES'!AB$3:AB$42*1000+(40-ROW('DONNÉES BRUTES'!AB$3:AB$42)+ROW('DONNÉES BRUTES'!AB$3)),0)),"—")} -> +5.5% | N16: {=IFERROR(INDEX('DONNÉES BRUTES'!AC$3:AC$42,MATCH(_xlfn.AGGREGATE(14,6,'DONNÉES BRUTES'!AB$3:AB$42*1000+(40-ROW('DONNÉES BRUTES'!AB$3:AB$42)+ROW('DONNÉES BRUTES'!AB$3)),1),'DONNÉES BRUTES'!AB$3:AB$42*1000+(40-ROW('DONNÉES BRUTES'!AB$3:AB$42)+ROW('DONNÉES BRUTES'!AB$3)),0)),"—")} -> — | R16: {=IFERROR(INDEX('DONNÉES BRUTES'!AD$3:AD$42,MATCH(_xlfn.AGGREGATE(14,6,'DONNÉES BRUTES'!AB$3:AB$42*1000+(40-ROW('DONNÉES BRUTES'!AB$3:AB$42)+ROW('DONNÉES BRUTES'!AB$3)),1),'DONNÉES BRUTES'!AB$3:AB$42*1000+(40-ROW('DONNÉES BRUTES'!AB$3:AB$42)+ROW('DONNÉES BRUTES'!AB$3)),0)),"—")} -> Surpondérer
B17: 2 | C17: {=IFERROR(INDEX('DONNÉES BRUTES'!A$3:A$42,MATCH(_xlfn.AGGREGATE(14,6,'DONNÉES BRUTES'!AB$3:AB$42*1000+(40-ROW('DONNÉES BRUTES'!AB$3:AB$42)+ROW('DONNÉES BRUTES'!AB$3)),2),'DONNÉES BRUTES'!AB$3:AB$42*1000+(40-ROW('DONNÉES BRUTES'!AB$3:AB$42)+ROW('DONNÉES BRUTES'!AB$3)),0)),"—")} -> AI.PA | D17: {=IFERROR(LEFT(IFERROR(INDEX('DONNÉES BRUTES'!B$3:B$42,MATCH(_xlfn.AGGREGATE(14,6,'DONNÉES BRUTES'!AB$3:AB$42*1000+(40-ROW('DONNÉES BRUTES'!AB$3:AB$42)+ROW('DONNÉES BRUTES'!AB$3)),2),'DONNÉES BRUTES'!AB$3:AB$42*1000+(40-ROW('DONNÉES BRUTES'!AB$3:AB$42)+ROW('DONNÉES BRUTES'!AB$3)),0)),"—"),18),"—")} -> L'Air Liquide S.A. | E17: {=IFERROR(INDEX('DONNÉES BRUTES'!C$3:C$42,MATCH(_xlfn.AGGREGATE(14,6,'DONNÉES BRUTES'!AB$3:AB$42*1000+(40-ROW('DONNÉES BRUTES'!AB$3:AB$42)+ROW('DONNÉES BRUTES'!AB$3)),2),'DONNÉES BRUTES'!AB$3:AB$42*1000+(40-ROW('DONNÉES BRUTES'!AB$3:AB$42)+ROW('DONNÉES BRUTES'!AB$3)),0)),"—")} -> Materials | F17: {=IFERROR(INT(_xlfn.AGGREGATE(14,6,'DONNÉES BRUTES'!AB$3:AB$42*1000+(40-ROW('DONNÉES BRUTES'!AB$3:AB$42)+ROW('DONNÉES BRUTES'!AB$3)),2)/1000)&"/100","—")} -> 74/100 | H17: {=IFERROR(INDEX('DONNÉES BRUTES'!Y$3:Y$42,MATCH(_xlfn.AGGREGATE(14,6,'DONNÉES BRUTES'!AB$3:AB$42*1000+(40-ROW('DONNÉES BRUTES'!AB$3:AB$42)+ROW('DONNÉES BRUTES'!AB$3)),2),'DONNÉES BRUTES'!AB$3:AB$42*1000+(40-ROW('DONNÉES BRUTES'!AB$3:AB$42)+ROW('DONNÉES BRUTES'!AB$3)),0)),"—")} -> 55 | I17: {=IFERROR(INDEX('DONNÉES BRUTES'!Z$3:Z$42,MATCH(_xlfn.AGGREGATE(14,6,'DONNÉES BRUTES'!AB$3:AB$42*1000+(40-ROW('DONNÉES BRUTES'!AB$3:AB$42)+ROW('DONNÉES BRUTES'!AB$3)),2),'DONNÉES BRUTES'!AB$3:AB$42*1000+(40-ROW('DONNÉES BRUTES'!AB$3:AB$42)+ROW('DONNÉES BRUTES'!AB$3)),0)),"—")} -> 77 | J17: {=IFERROR(INDEX('DONNÉES BRUTES'!AA$3:AA$42,MATCH(_xlfn.AGGREGATE(14,6,'DONNÉES BRUTES'!AB$3:AB$42*1000+(40-ROW('DONNÉES BRUTES'!AB$3:AB$42)+ROW('DONNÉES BRUTES'!AB$3)),2),'DONNÉES BRUTES'!AB$3:AB$42*1000+(40-ROW('DONNÉES BRUTES'!AB$3:AB$42)+ROW('DONNÉES BRUTES'!AB$3)),0)),"—")} -> 90 | K17: {=IFERROR(INDEX('DONNÉES BRUTES'!N$3:N$42,MATCH(_xlfn.AGGREGATE(14,6,'DONNÉES BRUTES'!AB$3:AB$42*1000+(40-ROW('DONNÉES BRUTES'!AB$3:AB$42)+ROW('DONNÉES BRUTES'!AB$3)),2),'DONNÉES BRUTES'!AB$3:AB$42*1000+(40-ROW('DONNÉES BRUTES'!AB$3:AB$42)+ROW('DONNÉES BRUTES'!AB$3)),0)),"—")} -> 27.9% | L17: {=IFERROR(INDEX('DONNÉES BRUTES'!P$3:P$42,MATCH(_xlfn.AGGREGATE(14,6,'DONNÉES BRUTES'!AB$3:AB$42*1000+(40-ROW('DONNÉES BRUTES'!AB$3:AB$42)+ROW('DONNÉES BRUTES'!AB$3)),2),'DONNÉES BRUTES'!AB$3:AB$42*1000+(40-ROW('DONNÉES BRUTES'!AB$3:AB$42)+ROW('DONNÉES BRUTES'!AB$3)),0)),"—")} -> -0.4% | N17: {=IFERROR(INDEX('DONNÉES BRUTES'!AC$3:AC$42,MATCH(_xlfn.AGGREGATE(14,6,'DONNÉES BRUTES'!AB$3:AB$42*1000+(40-ROW('DONNÉES BRUTES'!AB$3:AB$42)+ROW('DONNÉES BRUTES'!AB$3)),2),'DONNÉES BRUTES'!AB$3:AB$42*1000+(40-ROW('DONNÉES BRUTES'!AB$3:AB$42)+ROW('DONNÉES BRUTES'!AB$3)),0)),"—")} -> — | R17: {=IFERROR(INDEX('DONNÉES BRUTES'!AD$3:AD$42,MATCH(_xlfn.AGGREGATE(14,6,'DONNÉES BRUTES'!AB$3:AB$42*1000+(40-ROW('DONNÉES BRUTES'!AB$3:AB$42)+ROW('DONNÉES BRUTES'!AB$3)),2),'DONNÉES BRUTES'!AB$3:AB$42*1000+(40-ROW('DONNÉES BRUTES'!AB$3:AB$42)+ROW('DONNÉES BRUTES'!AB$3)),0)),"—")} -> Neutre
B18: 3 | C18: {=IFERROR(INDEX('DONNÉES BRUTES'!A$3:A$42,MATCH(_xlfn.AGGREGATE(14,6,'DONNÉES BRUTES'!AB$3:AB$42*1000+(40-ROW('DONNÉES BRUTES'!AB$3:AB$42)+ROW('DONNÉES BRUTES'!AB$3)),3),'DONNÉES BRUTES'!AB$3:AB$42*1000+(40-ROW('DONNÉES BRUTES'!AB$3:AB$42)+ROW('DONNÉES BRUTES'!AB$3)),0)),"—")} -> DSY.PA | D18: {=IFERROR(LEFT(IFERROR(INDEX('DONNÉES BRUTES'!B$3:B$42,MATCH(_xlfn.AGGREGATE(14,6,'DONNÉES BRUTES'!AB$3:AB$42*1000+(40-ROW('DONNÉES BRUTES'!AB$3:AB$42)+ROW('DONNÉES BRUTES'!AB$3)),3),'DONNÉES BRUTES'!AB$3:AB$42*1000+(40-ROW('DONNÉES BRUTES'!AB$3:AB$42)+ROW('DONNÉES BRUTES'!AB$3)),0)),"—"),18),"—")} -> Dassault Systèmes | E18: {=IFERROR(INDEX('DONNÉES BRUTES'!C$3:C$42,MATCH(_xlfn.AGGREGATE(14,6,'DONNÉES BRUTES'!AB$3:AB$42*1000+(40-ROW('DONNÉES BRUTES'!AB$3:AB$42)+ROW('DONNÉES BRUTES'!AB$3)),3),'DONNÉES BRUTES'!AB$3:AB$42*1000+(40-ROW('DONNÉES BRUTES'!AB$3:AB$42)+ROW('DONNÉES BRUTES'!AB$3)),0)),"—")} -> Technology | F18: {=IFERROR(INT(_xlfn.AGGREGATE(14,6,'DONNÉES BRUTES'!AB$3:AB$42*1000+(40-ROW('DONNÉES BRUTES'!AB$3:AB$42)+ROW('DONNÉES BRUTES'!AB$3)),3)/1000)&"/100","—")} -> 72/100 | H18: {=IFERROR(INDEX('DONNÉES BRUTES'!Y$3:Y$42,MATCH(_xlfn.AGGREGATE(14,6,'DONNÉES BRUTES'!AB$3:AB$42*1000+(40-ROW('DONNÉES BRUTES'!AB$3:AB$42)+ROW('DONNÉES BRUTES'!AB$3)),3),'DONNÉES BRUTES'!AB$3:AB$42*1000+(40-ROW('DONNÉES BRUTES'!AB$3:AB$42)+ROW('DONNÉES BRUTES'!AB$3)),0)),"—")} -> 42 | I18: {=IFERROR(INDEX('DONNÉES BRUTES'!Z$3:Z$42,MATCH(_xlfn.AGGREGATE(14,6,'DONNÉES BRUTES'!AB$3:AB$42*1000+(40-ROW('DONNÉES BRUTES'!AB$3:AB$42)+ROW('DONNÉES BRUTES'!AB$3)),3),'DONNÉES BRUTES'!AB$3:AB$42*1000+(40-ROW('DONNÉES BRUTES'!AB$3:AB$42)+ROW('DONNÉES BRUTES'!AB$3)),0)),"—")} -> 100 | J18: {=IFERROR(INDEX('DONNÉES BRUTES'!AA$3:AA$42,MATCH(_xlfn.AGGREGATE(14,6,'DONNÉES BRUTES'!AB$3:AB$42*1000+(40-ROW('DONNÉES BRUTES'!AB$3:AB$42)+ROW('DONNÉES BRUTES'!AB$3)),3),'DONNÉES BRUTES'!AB$3:AB$42*1000+(40-ROW('DONNÉES BRUTES'!AB$3:AB$42)+ROW('DONNÉES BRUTES'!AB$3)),0)),"—")} -> 74 | K18: {=IFERROR(INDEX('DONNÉES BRUTES'!N$3:N$42,MATCH(_xlfn.AGGREGATE(14,6,'DONNÉES BRUTES'!AB$3:AB$42*1000+(40-ROW('DONNÉES BRUTES'!AB$3:AB$42)+ROW('DONNÉES BRUTES'!AB$3)),3),'DONNÉES BRUTES'!AB$3:AB$42*1000+(40-ROW('DONNÉES BRUTES'!AB$3:AB$42)+ROW('DONNÉES BRUTES'!AB$3)),0)),"—")} -> 30.4% | L18: {=IFERROR(INDEX('DONNÉES BRUTES'!P$3:P$42,MATCH(_xlfn.AGGREGATE(14,6,'DONNÉES BRUTES'!AB$3:AB$42*1000+(40-ROW('DONNÉES BRUTES'!AB$3:AB$42)+ROW('DONNÉES BRUTES'!AB$3)),3),'DONNÉES BRUTES'!AB$3:AB$42*1000+(40-ROW('DONNÉES BRUTES'!AB$3:AB$42)+ROW('DONNÉES BRUTES'!AB$3)),0)),"—")} -> +0.4% | N18: {=IFERROR(INDEX('DONNÉES BRUTES'!AC$3:AC$42,MATCH(_xlfn.AGGREGATE(14,6,'DONNÉES BRUTES'!AB$3:AB$42*1000+(40-ROW('DONNÉES BRUTES'!AB$3:AB$42)+ROW('DONNÉES BRUTES'!AB$3)),3),'DONNÉES BRUTES'!AB$3:AB$42*1000+(40-ROW('DONNÉES BRUTES'!AB$3:AB$42)+ROW('DONNÉES BRUTES'!AB$3)),0)),"—")} -> 2026-04-23 | R18: {=IFERROR(INDEX('DONNÉES BRUTES'!AD$3:AD$42,MATCH(_xlfn.AGGREGATE(14,6,'DONNÉES BRUTES'!AB$3:AB$42*1000+(40-ROW('DONNÉES BRUTES'!AB$3:AB$42)+ROW('DONNÉES BRUTES'!AB$3)),3),'DONNÉES BRUTES'!AB$3:AB$42*1000+(40-ROW('DONNÉES BRUTES'!AB$3:AB$42)+ROW('DONNÉES BRUTES'!AB$3)),0)),"—")} -> Neutre
B19: 4 | C19: {=IFERROR(INDEX('DONNÉES BRUTES'!A$3:A$42,MATCH(_xlfn.AGGREGATE(14,6,'DONNÉES BRUTES'!AB$3:AB$42*1000+(40-ROW('DONNÉES BRUTES'!AB$3:AB$42)+ROW('DONNÉES BRUTES'!AB$3)),4),'DONNÉES BRUTES'!AB$3:AB$42*1000+(40-ROW('DONNÉES BRUTES'!AB$3:AB$42)+ROW('DONNÉES BRUTES'!AB$3)),0)),"—")} -> ERF.PA | D19: {=IFERROR(LEFT(IFERROR(INDEX('DONNÉES BRUTES'!B$3:B$42,MATCH(_xlfn.AGGREGATE(14,6,'DONNÉES BRUTES'!AB$3:AB$42*1000+(40-ROW('DONNÉES BRUTES'!AB$3:AB$42)+ROW('DONNÉES BRUTES'!AB$3)),4),'DONNÉES BRUTES'!AB$3:AB$42*1000+(40-ROW('DONNÉES BRUTES'!AB$3:AB$42)+ROW('DONNÉES BRUTES'!AB$3)),0)),"—"),18),"—")} -> Eurofins Scientifi | E19: {=IFERROR(INDEX('DONNÉES BRUTES'!C$3:C$42,MATCH(_xlfn.AGGREGATE(14,6,'DONNÉES BRUTES'!AB$3:AB$42*1000+(40-ROW('DONNÉES BRUTES'!AB$3:AB$42)+ROW('DONNÉES BRUTES'!AB$3)),4),'DONNÉES BRUTES'!AB$3:AB$42*1000+(40-ROW('DONNÉES BRUTES'!AB$3:AB$42)+ROW('DONNÉES BRUTES'!AB$3)),0)),"—")} -> Healthcare | F19: {=IFERROR(INT(_xlfn.AGGREGATE(14,6,'DONNÉES BRUTES'!AB$3:AB$42*1000+(40-ROW('DONNÉES BRUTES'!AB$3:AB$42)+ROW('DONNÉES BRUTES'!AB$3)),4)/1000)&"/100","—")} -> 72/100 | H19: {=IFERROR(INDEX('DONNÉES BRUTES'!Y$3:Y$42,MATCH(_xlfn.AGGREGATE(14,6,'DONNÉES BRUTES'!AB$3:AB$42*1000+(40-ROW('DONNÉES BRUTES'!AB$3:AB$42)+ROW('DONNÉES BRUTES'!AB$3)),4),'DONNÉES BRUTES'!AB$3:AB$42*1000+(40-ROW('DONNÉES BRUTES'!AB$3:AB$42)+ROW('DONNÉES BRUTES'!AB$3)),0)),"—")} -> 76 | I19: {=IFERROR(INDEX('DONNÉES BRUTES'!Z$3:Z$42,MATCH(_xlfn.AGGREGATE(14,6,'DONNÉES BRUTES'!AB$3:AB$42*1000+(40-ROW('DONNÉES BRUTES'!AB$3:AB$42)+ROW('DONNÉES BRUTES'!AB$3)),4),'DONNÉES BRUTES'!AB$3:AB$42*1000+(40-ROW('DONNÉES BRUTES'!AB$3:AB$42)+ROW('DONNÉES BRUTES'!AB$3)),0)),"—")} -> 72 | J19: {=IFERROR(INDEX('DONNÉES BRUTES'!AA$3:AA$42,MATCH(_xlfn.AGGREGATE(14,6,'DONNÉES BRUTES'!AB$3:AB$42*1000+(40-ROW('DONNÉES BRUTES'!AB$3:AB$42)+ROW('DONNÉES BRUTES'!AB$3)),4),'DONNÉES BRUTES'!AB$3:AB$42*1000+(40-ROW('DONNÉES BRUTES'!AB$3:AB$42)+ROW('DONNÉES BRUTES'!AB$3)),0)),"—")} -> 67 | K19: {=IFERROR(INDEX('DONNÉES BRUTES'!N$3:N$42,MATCH(_xlfn.AGGREGATE(14,6,'DONNÉES BRUTES'!AB$3:AB$42*1000+(40-ROW('DONNÉES BRUTES'!AB$3:AB$42)+ROW('DONNÉES BRUTES'!AB$3)),4),'DONNÉES BRUTES'!AB$3:AB$42*1000+(40-ROW('DONNÉES BRUTES'!AB$3:AB$42)+ROW('DONNÉES BRUTES'!AB$3)),0)),"—")} -> 21.0% | L19: {=IFERROR(INDEX('DONNÉES BRUTES'!P$3:P$42,MATCH(_xlfn.AGGREGATE(14,6,'DONNÉES BRUTES'!AB$3:AB$42*1000+(40-ROW('DONNÉES BRUTES'!AB$3:AB$42)+ROW('DONNÉES BRUTES'!AB$3)),4),'DONNÉES BRUTES'!AB$3:AB$42*1000+(40-ROW('DONNÉES BRUTES'!AB$3:AB$42)+ROW('DONNÉES BRUTES'!AB$3)),0)),"—")} -> +5.0% | N19: {=IFERROR(INDEX('DONNÉES BRUTES'!AC$3:AC$42,MATCH(_xlfn.AGGREGATE(14,6,'DONNÉES BRUTES'!AB$3:AB$42*1000+(40-ROW('DONNÉES BRUTES'!AB$3:AB$42)+ROW('DONNÉES BRUTES'!AB$3)),4),'DONNÉES BRUTES'!AB$3:AB$42*1000+(40-ROW('DONNÉES BRUTES'!AB$3:AB$42)+ROW('DONNÉES BRUTES'!AB$3)),0)),"—")} -> — | R19: {=IFERROR(INDEX('DONNÉES BRUTES'!AD$3:AD$42,MATCH(_xlfn.AGGREGATE(14,6,'DONNÉES BRUTES'!AB$3:AB$42*1000+(40-ROW('DONNÉES BRUTES'!AB$3:AB$42)+ROW('DONNÉES BRUTES'!AB$3)),4),'DONNÉES BRUTES'!AB$3:AB$42*1000+(40-ROW('DONNÉES BRUTES'!AB$3:AB$42)+ROW('DONNÉES BRUTES'!AB$3)),0)),"—")} -> Neutre
B20: 5 | C20: {=IFERROR(INDEX('DONNÉES BRUTES'!A$3:A$42,MATCH(_xlfn.AGGREGATE(14,6,'DONNÉES BRUTES'!AB$3:AB$42*1000+(40-ROW('DONNÉES BRUTES'!AB$3:AB$42)+ROW('DONNÉES BRUTES'!AB$3)),5),'DONNÉES BRUTES'!AB$3:AB$42*1000+(40-ROW('DONNÉES BRUTES'!AB$3:AB$42)+ROW('DONNÉES BRUTES'!AB$3)),0)),"—")} -> SAN.PA | D20: {=IFERROR(LEFT(IFERROR(INDEX('DONNÉES BRUTES'!B$3:B$42,MATCH(_xlfn.AGGREGATE(14,6,'DONNÉES BRUTES'!AB$3:AB$42*1000+(40-ROW('DONNÉES BRUTES'!AB$3:AB$42)+ROW('DONNÉES BRUTES'!AB$3)),5),'DONNÉES BRUTES'!AB$3:AB$42*1000+(40-ROW('DONNÉES BRUTES'!AB$3:AB$42)+ROW('DONNÉES BRUTES'!AB$3)),0)),"—"),18),"—")} -> Sanofi | E20: {=IFERROR(INDEX('DONNÉES BRUTES'!C$3:C$42,MATCH(_xlfn.AGGREGATE(14,6,'DONNÉES BRUTES'!AB$3:AB$42*1000+(40-ROW('DONNÉES BRUTES'!AB$3:AB$42)+ROW('DONNÉES BRUTES'!AB$3)),5),'DONNÉES BRUTES'!AB$3:AB$42*1000+(40-ROW('DONNÉES BRUTES'!AB$3:AB$42)+ROW('DONNÉES BRUTES'!AB$3)),0)),"—")} -> Healthcare | F20: {=IFERROR(INT(_xlfn.AGGREGATE(14,6,'DONNÉES BRUTES'!AB$3:AB$42*1000+(40-ROW('DONNÉES BRUTES'!AB$3:AB$42)+ROW('DONNÉES BRUTES'!AB$3)),5)/1000)&"/100","—")} -> 72/100 | H20: {=IFERROR(INDEX('DONNÉES BRUTES'!Y$3:Y$42,MATCH(_xlfn.AGGREGATE(14,6,'DONNÉES BRUTES'!AB$3:AB$42*1000+(40-ROW('DONNÉES BRUTES'!AB$3:AB$42)+ROW('DONNÉES BRUTES'!AB$3)),5),'DONNÉES BRUTES'!AB$3:AB$42*1000+(40-ROW('DONNÉES BRUTES'!AB$3:AB$42)+ROW('DONNÉES BRUTES'!AB$3)),0)),"—")} -> 87 | I20: {=IFERROR(INDEX('DONNÉES BRUTES'!Z$3:Z$42,MATCH(_xlfn.AGGREGATE(14,6,'DONNÉES BRUTES'!AB$3:AB$42*1000+(40-ROW('DONNÉES BRUTES'!AB$3:AB$42)+ROW('DONNÉES BRUTES'!AB$3)),5),'DONNÉES BRUTES'!AB$3:AB$42*1000+(40-ROW('DONNÉES BRUTES'!AB$3:AB$42)+ROW('DONNÉES BRUTES'!AB$3)),0)),"—")} -> 97 | J20: {=IFERROR(INDEX('DONNÉES BRUTES'!AA$3:AA$42,MATCH(_xlfn.AGGREGATE(14,6,'DONNÉES BRUTES'!AB$3:AB$42*1000+(40-ROW('DONNÉES BRUTES'!AB$3:AB$42)+ROW('DONNÉES BRUTES'!AB$3)),5),'DONNÉES BRUTES'!AB$3:AB$42*1000+(40-ROW('DONNÉES BRUTES'!AB$3:AB$42)+ROW('DONNÉES BRUTES'!AB$3)),0)),"—")} -> 31 | K20: {=IFERROR(INDEX('DONNÉES BRUTES'!N$3:N$42,MATCH(_xlfn.AGGREGATE(14,6,'DONNÉES BRUTES'!AB$3:AB$42*1000+(40-ROW('DONNÉES BRUTES'!AB$3:AB$42)+ROW('DONNÉES BRUTES'!AB$3)),5),'DONNÉES BRUTES'!AB$3:AB$42*1000+(40-ROW('DONNÉES BRUTES'!AB$3:AB$42)+ROW('DONNÉES BRUTES'!AB$3)),0)),"—")} -> 26.7% | L20: {=IFERROR(INDEX('DONNÉES BRUTES'!P$3:P$42,MATCH(_xlfn.AGGREGATE(14,6,'DONNÉES BRUTES'!AB$3:AB$42*1000+(40-ROW('DONNÉES BRUTES'!AB$3:AB$42)+ROW('DONNÉES BRUTES'!AB$3)),5),'DONNÉES BRUTES'!AB$3:AB$42*1000+(40-ROW('DONNÉES BRUTES'!AB$3:AB$42)+ROW('DONNÉES BRUTES'!AB$3)),0)),"—")} -> +5.5% | N20: {=IFERROR(INDEX('DONNÉES BRUTES'!AC$3:AC$42,MATCH(_xlfn.AGGREGATE(14,6,'DONNÉES BRUTES'!AB$3:AB$42*1000+(40-ROW('DONNÉES BRUTES'!AB$3:AB$42)+ROW('DONNÉES BRUTES'!AB$3)),5),'DONNÉES BRUTES'!AB$3:AB$42*1000+(40-ROW('DONNÉES BRUTES'!AB$3:AB$42)+ROW('DONNÉES BRUTES'!AB$3)),0)),"—")} -> 2026-04-23 | R20: {=IFERROR(INDEX('DONNÉES BRUTES'!AD$3:AD$42,MATCH(_xlfn.AGGREGATE(14,6,'DONNÉES BRUTES'!AB$3:AB$42*1000+(40-ROW('DONNÉES BRUTES'!AB$3:AB$42)+ROW('DONNÉES BRUTES'!AB$3)),5),'DONNÉES BRUTES'!AB$3:AB$42*1000+(40-ROW('DONNÉES BRUTES'!AB$3:AB$42)+ROW('DONNÉES BRUTES'!AB$3)),0)),"—")} -> Neutre
B21: 6 | C21: {=IFERROR(INDEX('DONNÉES BRUTES'!A$3:A$42,MATCH(_xlfn.AGGREGATE(14,6,'DONNÉES BRUTES'!AB$3:AB$42*1000+(40-ROW('DONNÉES BRUTES'!AB$3:AB$42)+ROW('DONNÉES BRUTES'!AB$3)),6),'DONNÉES BRUTES'!AB$3:AB$42*1000+(40-ROW('DONNÉES BRUTES'!AB$3:AB$42)+ROW('DONNÉES BRUTES'!AB$3)),0)),"—")} -> ALO.PA | D21: {=IFERROR(LEFT(IFERROR(INDEX('DONNÉES BRUTES'!B$3:B$42,MATCH(_xlfn.AGGREGATE(14,6,'DONNÉES BRUTES'!AB$3:AB$42*1000+(40-ROW('DONNÉES BRUTES'!AB$3:AB$42)+ROW('DONNÉES BRUTES'!AB$3)),6),'DONNÉES BRUTES'!AB$3:AB$42*1000+(40-ROW('DONNÉES BRUTES'!AB$3:AB$42)+ROW('DONNÉES BRUTES'!AB$3)),0)),"—"),18),"—")} -> Alstom SA | E21: {=IFERROR(INDEX('DONNÉES BRUTES'!C$3:C$42,MATCH(_xlfn.AGGREGATE(14,6,'DONNÉES BRUTES'!AB$3:AB$42*1000+(40-ROW('DONNÉES BRUTES'!AB$3:AB$42)+ROW('DONNÉES BRUTES'!AB$3)),6),'DONNÉES BRUTES'!AB$3:AB$42*1000+(40-ROW('DONNÉES BRUTES'!AB$3:AB$42)+ROW('DONNÉES BRUTES'!AB$3)),0)),"—")} -> Industrials | F21: {=IFERROR(INT(_xlfn.AGGREGATE(14,6,'DONNÉES BRUTES'!AB$3:AB$42*1000+(40-ROW('DONNÉES BRUTES'!AB$3:AB$42)+ROW('DONNÉES BRUTES'!AB$3)),6)/1000)&"/100","—")} -> 70/100 | H21: {=IFERROR(INDEX('DONNÉES BRUTES'!Y$3:Y$42,MATCH(_xlfn.AGGREGATE(14,6,'DONNÉES BRUTES'!AB$3:AB$42*1000+(40-ROW('DONNÉES BRUTES'!AB$3:AB$42)+ROW('DONNÉES BRUTES'!AB$3)),6),'DONNÉES BRUTES'!AB$3:AB$42*1000+(40-ROW('DONNÉES BRUTES'!AB$3:AB$42)+ROW('DONNÉES BRUTES'!AB$3)),0)),"—")} -> 95 | I21: {=IFERROR(INDEX('DONNÉES BRUTES'!Z$3:Z$42,MATCH(_xlfn.AGGREGATE(14,6,'DONNÉES BRUTES'!AB$3:AB$42*1000+(40-ROW('DONNÉES BRUTES'!AB$3:AB$42)+ROW('DONNÉES BRUTES'!AB$3)),6),'DONNÉES BRUTES'!AB$3:AB$42*1000+(40-ROW('DONNÉES BRUTES'!AB$3:AB$42)+ROW('DONNÉES BRUTES'!AB$3)),0)),"—")} -> 15 | J21: {=IFERROR(INDEX('DONNÉES BRUTES'!AA$3:AA$42,MATCH(_xlfn.AGGREGATE(14,6,'DONNÉES BRUTES'!AB$3:AB$42*1000+(40-ROW('DONNÉES BRUTES'!AB$3:AB$42)+ROW('DONNÉES BRUTES'!AB$3)),6),'DONNÉES BRUTES'!AB$3:AB$42*1000+(40-ROW('DONNÉES BRUTES'!AB$3:AB$42)+ROW('DONNÉES BRUTES'!AB$3)),0)),"—")} -> 100 | K21: {=IFERROR(INDEX('DONNÉES BRUTES'!N$3:N$42,MATCH(_xlfn.AGGREGATE(14,6,'DONNÉES BRUTES'!AB$3:AB$42*1000+(40-ROW('DONNÉES BRUTES'!AB$3:AB$42)+ROW('DONNÉES BRUTES'!AB$3)),6),'DONNÉES BRUTES'!AB$3:AB$42*1000+(40-ROW('DONNÉES BRUTES'!AB$3:AB$42)+ROW('DONNÉES BRUTES'!AB$3)),0)),"—")} -> 6.8% | L21: {=IFERROR(INDEX('DONNÉES BRUTES'!P$3:P$42,MATCH(_xlfn.AGGREGATE(14,6,'DONNÉES BRUTES'!AB$3:AB$42*1000+(40-ROW('DONNÉES BRUTES'!AB$3:AB$42)+ROW('DONNÉES BRUTES'!AB$3)),6),'DONNÉES BRUTES'!AB$3:AB$42*1000+(40-ROW('DONNÉES BRUTES'!AB$3:AB$42)+ROW('DONNÉES BRUTES'!AB$3)),0)),"—")} -> +4.9% | N21: {=IFERROR(INDEX('DONNÉES BRUTES'!AC$3:AC$42,MATCH(_xlfn.AGGREGATE(14,6,'DONNÉES BRUTES'!AB$3:AB$42*1000+(40-ROW('DONNÉES BRUTES'!AB$3:AB$42)+ROW('DONNÉES BRUTES'!AB$3)),6),'DONNÉES BRUTES'!AB$3:AB$42*1000+(40-ROW('DONNÉES BRUTES'!AB$3:AB$42)+ROW('DONNÉES BRUTES'!AB$3)),0)),"—")} -> 2026-05-13 | R21: {=IFERROR(INDEX('DONNÉES BRUTES'!AD$3:AD$42,MATCH(_xlfn.AGGREGATE(14,6,'DONNÉES BRUTES'!AB$3:AB$42*1000+(40-ROW('DONNÉES BRUTES'!AB$3:AB$42)+ROW('DONNÉES BRUTES'!AB$3)),6),'DONNÉES BRUTES'!AB$3:AB$42*1000+(40-ROW('DONNÉES BRUTES'!AB$3:AB$42)+ROW('DONNÉES BRUTES'!AB$3)),0)),"—")} -> Neutre
B22: 7 | C22: {=IFERROR(INDEX('DONNÉES BRUTES'!A$3:A$42,MATCH(_xlfn.AGGREGATE(14,6,'DONNÉES BRUTES'!AB$3:AB$42*1000+(40-ROW('DONNÉES BRUTES'!AB$3:AB$42)+ROW('DONNÉES BRUTES'!AB$3)),7),'DONNÉES BRUTES'!AB$3:AB$42*1000+(40-ROW('DONNÉES BRUTES'!AB$3:AB$42)+ROW('DONNÉES BRUTES'!AB$3)),0)),"—")} -> URW.PA | D22: {=IFERROR(LEFT(IFERROR(INDEX('DONNÉES BRUTES'!B$3:B$42,MATCH(_xlfn.AGGREGATE(14,6,'DONNÉES BRUTES'!AB$3:AB$42*1000+(40-ROW('DONNÉES BRUTES'!AB$3:AB$42)+ROW('DONNÉES BRUTES'!AB$3)),7),'DONNÉES BRUTES'!AB$3:AB$42*1000+(40-ROW('DONNÉES BRUTES'!AB$3:AB$42)+ROW('DONNÉES BRUTES'!AB$3)),0)),"—"),18),"—")} -> Unibail-Rodamco-We | E22: {=IFERROR(INDEX('DONNÉES BRUTES'!C$3:C$42,MATCH(_xlfn.AGGREGATE(14,6,'DONNÉES BRUTES'!AB$3:AB$42*1000+(40-ROW('DONNÉES BRUTES'!AB$3:AB$42)+ROW('DONNÉES BRUTES'!AB$3)),7),'DONNÉES BRUTES'!AB$3:AB$42*1000+(40-ROW('DONNÉES BRUTES'!AB$3:AB$42)+ROW('DONNÉES BRUTES'!AB$3)),0)),"—")} -> Real Estate | F22: {=IFERROR(INT(_xlfn.AGGREGATE(14,6,'DONNÉES BRUTES'!AB$3:AB$42*1000+(40-ROW('DONNÉES BRUTES'!AB$3:AB$42)+ROW('DONNÉES BRUTES'!AB$3)),7)/1000)&"/100","—")} -> 69/100 | H22: {=IFERROR(INDEX('DONNÉES BRUTES'!Y$3:Y$42,MATCH(_xlfn.AGGREGATE(14,6,'DONNÉES BRUTES'!AB$3:AB$42*1000+(40-ROW('DONNÉES BRUTES'!AB$3:AB$42)+ROW('DONNÉES BRUTES'!AB$3)),7),'DONNÉES BRUTES'!AB$3:AB$42*1000+(40-ROW('DONNÉES BRUTES'!AB$3:AB$42)+ROW('DONNÉES BRUTES'!AB$3)),0)),"—")} -> 92 | I22: {=IFERROR(INDEX('DONNÉES BRUTES'!Z$3:Z$42,MATCH(_xlfn.AGGREGATE(14,6,'DONNÉES BRUTES'!AB$3:AB$42*1000+(40-ROW('DONNÉES BRUTES'!AB$3:AB$42)+ROW('DONNÉES BRUTES'!AB$3)),7),'DONNÉES BRUTES'!AB$3:AB$42*1000+(40-ROW('DONNÉES BRUTES'!AB$3:AB$42)+ROW('DONNÉES BRUTES'!AB$3)),0)),"—")} -> 95 | J22: {=IFERROR(INDEX('DONNÉES BRUTES'!AA$3:AA$42,MATCH(_xlfn.AGGREGATE(14,6,'DONNÉES BRUTES'!AB$3:AB$42*1000+(40-ROW('DONNÉES BRUTES'!AB$3:AB$42)+ROW('DONNÉES BRUTES'!AB$3)),7),'DONNÉES BRUTES'!AB$3:AB$42*1000+(40-ROW('DONNÉES BRUTES'!AB$3:AB$42)+ROW('DONNÉES BRUTES'!AB$3)),0)),"—")} -> 21 | K22: {=IFERROR(INDEX('DONNÉES BRUTES'!N$3:N$42,MATCH(_xlfn.AGGREGATE(14,6,'DONNÉES BRUTES'!AB$3:AB$42*1000+(40-ROW('DONNÉES BRUTES'!AB$3:AB$42)+ROW('DONNÉES BRUTES'!AB$3)),7),'DONNÉES BRUTES'!AB$3:AB$42*1000+(40-ROW('DONNÉES BRUTES'!AB$3:AB$42)+ROW('DONNÉES BRUTES'!AB$3)),0)),"—")} -> 89.1% | L22: {=IFERROR(INDEX('DONNÉES BRUTES'!P$3:P$42,MATCH(_xlfn.AGGREGATE(14,6,'DONNÉES BRUTES'!AB$3:AB$42*1000+(40-ROW('DONNÉES BRUTES'!AB$3:AB$42)+ROW('DONNÉES BRUTES'!AB$3)),7),'DONNÉES BRUTES'!AB$3:AB$42*1000+(40-ROW('DONNÉES BRUTES'!AB$3:AB$42)+ROW('DONNÉES BRUTES'!AB$3)),0)),"—")} -> -6.1% | N22: {=IFERROR(INDEX('DONNÉES BRUTES'!AC$3:AC$42,MATCH(_xlfn.AGGREGATE(14,6,'DONNÉES BRUTES'!AB$3:AB$42*1000+(40-ROW('DONNÉES BRUTES'!AB$3:AB$42)+ROW('DONNÉES BRUTES'!AB$3)),7),'DONNÉES BRUTES'!AB$3:AB$42*1000+(40-ROW('DONNÉES BRUTES'!AB$3:AB$42)+ROW('DONNÉES BRUTES'!AB$3)),0)),"—")} -> — | R22: {=IFERROR(INDEX('DONNÉES BRUTES'!AD$3:AD$42,MATCH(_xlfn.AGGREGATE(14,6,'DONNÉES BRUTES'!AB$3:AB$42*1000+(40-ROW('DONNÉES BRUTES'!AB$3:AB$42)+ROW('DONNÉES BRUTES'!AB$3)),7),'DONNÉES BRUTES'!AB$3:AB$42*1000+(40-ROW('DONNÉES BRUTES'!AB$3:AB$42)+ROW('DONNÉES BRUTES'!AB$3)),0)),"—")} -> Neutre
B23: 8 | C23: {=IFERROR(INDEX('DONNÉES BRUTES'!A$3:A$42,MATCH(_xlfn.AGGREGATE(14,6,'DONNÉES BRUTES'!AB$3:AB$42*1000+(40-ROW('DONNÉES BRUTES'!AB$3:AB$42)+ROW('DONNÉES BRUTES'!AB$3)),8),'DONNÉES BRUTES'!AB$3:AB$42*1000+(40-ROW('DONNÉES BRUTES'!AB$3:AB$42)+ROW('DONNÉES BRUTES'!AB$3)),0)),"—")} -> AIR.PA | D23: {=IFERROR(LEFT(IFERROR(INDEX('DONNÉES BRUTES'!B$3:B$42,MATCH(_xlfn.AGGREGATE(14,6,'DONNÉES BRUTES'!AB$3:AB$42*1000+(40-ROW('DONNÉES BRUTES'!AB$3:AB$42)+ROW('DONNÉES BRUTES'!AB$3)),8),'DONNÉES BRUTES'!AB$3:AB$42*1000+(40-ROW('DONNÉES BRUTES'!AB$3:AB$42)+ROW('DONNÉES BRUTES'!AB$3)),0)),"—"),18),"—")} -> Airbus SE | E23: {=IFERROR(INDEX('DONNÉES BRUTES'!C$3:C$42,MATCH(_xlfn.AGGREGATE(14,6,'DONNÉES BRUTES'!AB$3:AB$42*1000+(40-ROW('DONNÉES BRUTES'!AB$3:AB$42)+ROW('DONNÉES BRUTES'!AB$3)),8),'DONNÉES BRUTES'!AB$3:AB$42*1000+(40-ROW('DONNÉES BRUTES'!AB$3:AB$42)+ROW('DONNÉES BRUTES'!AB$3)),0)),"—")} -> Industrials | F23: {=IFERROR(INT(_xlfn.AGGREGATE(14,6,'DONNÉES BRUTES'!AB$3:AB$42*1000+(40-ROW('DONNÉES BRUTES'!AB$3:AB$42)+ROW('DONNÉES BRUTES'!AB$3)),8)/1000)&"/100","—")} -> 68/100 | H23: {=IFERROR(INDEX('DONNÉES BRUTES'!Y$3:Y$42,MATCH(_xlfn.AGGREGATE(14,6,'DONNÉES BRUTES'!AB$3:AB$42*1000+(40-ROW('DONNÉES BRUTES'!AB$3:AB$42)+ROW('DONNÉES BRUTES'!AB$3)),8),'DONNÉES BRUTES'!AB$3:AB$42*1000+(40-ROW('DONNÉES BRUTES'!AB$3:AB$42)+ROW('DONNÉES BRUTES'!AB$3)),0)),"—")} -> 84 | I23: {=IFERROR(INDEX('DONNÉES BRUTES'!Z$3:Z$42,MATCH(_xlfn.AGGREGATE(14,6,'DONNÉES BRUTES'!AB$3:AB$42*1000+(40-ROW('DONNÉES BRUTES'!AB$3:AB$42)+ROW('DONNÉES BRUTES'!AB$3)),8),'DONNÉES BRUTES'!AB$3:AB$42*1000+(40-ROW('DONNÉES BRUTES'!AB$3:AB$42)+ROW('DONNÉES BRUTES'!AB$3)),0)),"—")} -> 23 | J23: {=IFERROR(INDEX('DONNÉES BRUTES'!AA$3:AA$42,MATCH(_xlfn.AGGREGATE(14,6,'DONNÉES BRUTES'!AB$3:AB$42*1000+(40-ROW('DONNÉES BRUTES'!AB$3:AB$42)+ROW('DONNÉES BRUTES'!AB$3)),8),'DONNÉES BRUTES'!AB$3:AB$42*1000+(40-ROW('DONNÉES BRUTES'!AB$3:AB$42)+ROW('DONNÉES BRUTES'!AB$3)),0)),"—")} -> 97 | K23: {=IFERROR(INDEX('DONNÉES BRUTES'!N$3:N$42,MATCH(_xlfn.AGGREGATE(14,6,'DONNÉES BRUTES'!AB$3:AB$42*1000+(40-ROW('DONNÉES BRUTES'!AB$3:AB$42)+ROW('DONNÉES BRUTES'!AB$3)),8),'DONNÉES BRUTES'!AB$3:AB$42*1000+(40-ROW('DONNÉES BRUTES'!AB$3:AB$42)+ROW('DONNÉES BRUTES'!AB$3)),0)),"—")} -> 14.0% | L23: {=IFERROR(INDEX('DONNÉES BRUTES'!P$3:P$42,MATCH(_xlfn.AGGREGATE(14,6,'DONNÉES BRUTES'!AB$3:AB$42*1000+(40-ROW('DONNÉES BRUTES'!AB$3:AB$42)+ROW('DONNÉES BRUTES'!AB$3)),8),'DONNÉES BRUTES'!AB$3:AB$42*1000+(40-ROW('DONNÉES BRUTES'!AB$3:AB$42)+ROW('DONNÉES BRUTES'!AB$3)),0)),"—")} -> +6.1% | N23: {=IFERROR(INDEX('DONNÉES BRUTES'!AC$3:AC$42,MATCH(_xlfn.AGGREGATE(14,6,'DONNÉES BRUTES'!AB$3:AB$42*1000+(40-ROW('DONNÉES BRUTES'!AB$3:AB$42)+ROW('DONNÉES BRUTES'!AB$3)),8),'DONNÉES BRUTES'!AB$3:AB$42*1000+(40-ROW('DONNÉES BRUTES'!AB$3:AB$42)+ROW('DONNÉES BRUTES'!AB$3)),0)),"—")} -> 2026-04-28 | R23: {=IFERROR(INDEX('DONNÉES BRUTES'!AD$3:AD$42,MATCH(_xlfn.AGGREGATE(14,6,'DONNÉES BRUTES'!AB$3:AB$42*1000+(40-ROW('DONNÉES BRUTES'!AB$3:AB$42)+ROW('DONNÉES BRUTES'!AB$3)),8),'DONNÉES BRUTES'!AB$3:AB$42*1000+(40-ROW('DONNÉES BRUTES'!AB$3:AB$42)+ROW('DONNÉES BRUTES'!AB$3)),0)),"—")} -> Neutre
B24: 9 | C24: {=IFERROR(INDEX('DONNÉES BRUTES'!A$3:A$42,MATCH(_xlfn.AGGREGATE(14,6,'DONNÉES BRUTES'!AB$3:AB$42*1000+(40-ROW('DONNÉES BRUTES'!AB$3:AB$42)+ROW('DONNÉES BRUTES'!AB$3)),9),'DONNÉES BRUTES'!AB$3:AB$42*1000+(40-ROW('DONNÉES BRUTES'!AB$3:AB$42)+ROW('DONNÉES BRUTES'!AB$3)),0)),"—")} -> SAF.PA | D24: {=IFERROR(LEFT(IFERROR(INDEX('DONNÉES BRUTES'!B$3:B$42,MATCH(_xlfn.AGGREGATE(14,6,'DONNÉES BRUTES'!AB$3:AB$42*1000+(40-ROW('DONNÉES BRUTES'!AB$3:AB$42)+ROW('DONNÉES BRUTES'!AB$3)),9),'DONNÉES BRUTES'!AB$3:AB$42*1000+(40-ROW('DONNÉES BRUTES'!AB$3:AB$42)+ROW('DONNÉES BRUTES'!AB$3)),0)),"—"),18),"—")} -> Safran SA | E24: {=IFERROR(INDEX('DONNÉES BRUTES'!C$3:C$42,MATCH(_xlfn.AGGREGATE(14,6,'DONNÉES BRUTES'!AB$3:AB$42*1000+(40-ROW('DONNÉES BRUTES'!AB$3:AB$42)+ROW('DONNÉES BRUTES'!AB$3)),9),'DONNÉES BRUTES'!AB$3:AB$42*1000+(40-ROW('DONNÉES BRUTES'!AB$3:AB$42)+ROW('DONNÉES BRUTES'!AB$3)),0)),"—")} -> Industrials | F24: {=IFERROR(INT(_xlfn.AGGREGATE(14,6,'DONNÉES BRUTES'!AB$3:AB$42*1000+(40-ROW('DONNÉES BRUTES'!AB$3:AB$42)+ROW('DONNÉES BRUTES'!AB$3)),9)/1000)&"/100","—")} -> 68/100 | H24: {=IFERROR(INDEX('DONNÉES BRUTES'!Y$3:Y$42,MATCH(_xlfn.AGGREGATE(14,6,'DONNÉES BRUTES'!AB$3:AB$42*1000+(40-ROW('DONNÉES BRUTES'!AB$3:AB$42)+ROW('DONNÉES BRUTES'!AB$3)),9),'DONNÉES BRUTES'!AB$3:AB$42*1000+(40-ROW('DONNÉES BRUTES'!AB$3:AB$42)+ROW('DONNÉES BRUTES'!AB$3)),0)),"—")} -> 100 | I24: {=IFERROR(INDEX('DONNÉES BRUTES'!Z$3:Z$42,MATCH(_xlfn.AGGREGATE(14,6,'DONNÉES BRUTES'!AB$3:AB$42*1000+(40-ROW('DONNÉES BRUTES'!AB$3:AB$42)+ROW('DONNÉES BRUTES'!AB$3)),9),'DONNÉES BRUTES'!AB$3:AB$42*1000+(40-ROW('DONNÉES BRUTES'!AB$3:AB$42)+ROW('DONNÉES BRUTES'!AB$3)),0)),"—")} -> 67 | J24: {=IFERROR(INDEX('DONNÉES BRUTES'!AA$3:AA$42,MATCH(_xlfn.AGGREGATE(14,6,'DONNÉES BRUTES'!AB$3:AB$42*1000+(40-ROW('DONNÉES BRUTES'!AB$3:AB$42)+ROW('DONNÉES BRUTES'!AB$3)),9),'DONNÉES BRUTES'!AB$3:AB$42*1000+(40-ROW('DONNÉES BRUTES'!AB$3:AB$42)+ROW('DONNÉES BRUTES'!AB$3)),0)),"—")} -> 38 | K24: {=IFERROR(INDEX('DONNÉES BRUTES'!N$3:N$42,MATCH(_xlfn.AGGREGATE(14,6,'DONNÉES BRUTES'!AB$3:AB$42*1000+(40-ROW('DONNÉES BRUTES'!AB$3:AB$42)+ROW('DONNÉES BRUTES'!AB$3)),9),'DONNÉES BRUTES'!AB$3:AB$42*1000+(40-ROW('DONNÉES BRUTES'!AB$3:AB$42)+ROW('DONNÉES BRUTES'!AB$3)),0)),"—")} -> 39.2% | L24: {=IFERROR(INDEX('DONNÉES BRUTES'!P$3:P$42,MATCH(_xlfn.AGGREGATE(14,6,'DONNÉES BRUTES'!AB$3:AB$42*1000+(40-ROW('DONNÉES BRUTES'!AB$3:AB$42)+ROW('DONNÉES BRUTES'!AB$3)),9),'DONNÉES BRUTES'!AB$3:AB$42*1000+(40-ROW('DONNÉES BRUTES'!AB$3:AB$42)+ROW('DONNÉES BRUTES'!AB$3)),0)),"—")} -> +12.5% | N24: {=IFERROR(INDEX('DONNÉES BRUTES'!AC$3:AC$42,MATCH(_xlfn.AGGREGATE(14,6,'DONNÉES BRUTES'!AB$3:AB$42*1000+(40-ROW('DONNÉES BRUTES'!AB$3:AB$42)+ROW('DONNÉES BRUTES'!AB$3)),9),'DONNÉES BRUTES'!AB$3:AB$42*1000+(40-ROW('DONNÉES BRUTES'!AB$3:AB$42)+ROW('DONNÉES BRUTES'!AB$3)),0)),"—")} -> — | R24: {=IFERROR(INDEX('DONNÉES BRUTES'!AD$3:AD$42,MATCH(_xlfn.AGGREGATE(14,6,'DONNÉES BRUTES'!AB$3:AB$42*1000+(40-ROW('DONNÉES BRUTES'!AB$3:AB$42)+ROW('DONNÉES BRUTES'!AB$3)),9),'DONNÉES BRUTES'!AB$3:AB$42*1000+(40-ROW('DONNÉES BRUTES'!AB$3:AB$42)+ROW('DONNÉES BRUTES'!AB$3)),0)),"—")} -> Neutre
B25: 10 | C25: {=IFERROR(INDEX('DONNÉES BRUTES'!A$3:A$42,MATCH(_xlfn.AGGREGATE(14,6,'DONNÉES BRUTES'!AB$3:AB$42*1000+(40-ROW('DONNÉES BRUTES'!AB$3:AB$42)+ROW('DONNÉES BRUTES'!AB$3)),10),'DONNÉES BRUTES'!AB$3:AB$42*1000+(40-ROW('DONNÉES BRUTES'!AB$3:AB$42)+ROW('DONNÉES BRUTES'!AB$3)),0)),"—")} -> ACA.PA | D25: {=IFERROR(LEFT(IFERROR(INDEX('DONNÉES BRUTES'!B$3:B$42,MATCH(_xlfn.AGGREGATE(14,6,'DONNÉES BRUTES'!AB$3:AB$42*1000+(40-ROW('DONNÉES BRUTES'!AB$3:AB$42)+ROW('DONNÉES BRUTES'!AB$3)),10),'DONNÉES BRUTES'!AB$3:AB$42*1000+(40-ROW('DONNÉES BRUTES'!AB$3:AB$42)+ROW('DONNÉES BRUTES'!AB$3)),0)),"—"),18),"—")} -> Crédit Agricole S. | E25: {=IFERROR(INDEX('DONNÉES BRUTES'!C$3:C$42,MATCH(_xlfn.AGGREGATE(14,6,'DONNÉES BRUTES'!AB$3:AB$42*1000+(40-ROW('DONNÉES BRUTES'!AB$3:AB$42)+ROW('DONNÉES BRUTES'!AB$3)),10),'DONNÉES BRUTES'!AB$3:AB$42*1000+(40-ROW('DONNÉES BRUTES'!AB$3:AB$42)+ROW('DONNÉES BRUTES'!AB$3)),0)),"—")} -> Financials | F25: {=IFERROR(INT(_xlfn.AGGREGATE(14,6,'DONNÉES BRUTES'!AB$3:AB$42*1000+(40-ROW('DONNÉES BRUTES'!AB$3:AB$42)+ROW('DONNÉES BRUTES'!AB$3)),10)/1000)&"/100","—")} -> 65/100 | H25: {=IFERROR(INDEX('DONNÉES BRUTES'!Y$3:Y$42,MATCH(_xlfn.AGGREGATE(14,6,'DONNÉES BRUTES'!AB$3:AB$42*1000+(40-ROW('DONNÉES BRUTES'!AB$3:AB$42)+ROW('DONNÉES BRUTES'!AB$3)),10),'DONNÉES BRUTES'!AB$3:AB$42*1000+(40-ROW('DONNÉES BRUTES'!AB$3:AB$42)+ROW('DONNÉES BRUTES'!AB$3)),0)),"—")} -> 21 | I25: {=IFERROR(INDEX('DONNÉES BRUTES'!Z$3:Z$42,MATCH(_xlfn.AGGREGATE(14,6,'DONNÉES BRUTES'!AB$3:AB$42*1000+(40-ROW('DONNÉES BRUTES'!AB$3:AB$42)+ROW('DONNÉES BRUTES'!AB$3)),10),'DONNÉES BRUTES'!AB$3:AB$42*1000+(40-ROW('DONNÉES BRUTES'!AB$3:AB$42)+ROW('DONNÉES BRUTES'!AB$3)),0)),"—")} -> 92 | J25: {=IFERROR(INDEX('DONNÉES BRUTES'!AA$3:AA$42,MATCH(_xlfn.AGGREGATE(14,6,'DONNÉES BRUTES'!AB$3:AB$42*1000+(40-ROW('DONNÉES BRUTES'!AB$3:AB$42)+ROW('DONNÉES BRUTES'!AB$3)),10),'DONNÉES BRUTES'!AB$3:AB$42*1000+(40-ROW('DONNÉES BRUTES'!AB$3:AB$42)+ROW('DONNÉES BRUTES'!AB$3)),0)),"—")} -> 82 | K25: {=IFERROR(INDEX('DONNÉES BRUTES'!N$3:N$42,MATCH(_xlfn.AGGREGATE(14,6,'DONNÉES BRUTES'!AB$3:AB$42*1000+(40-ROW('DONNÉES BRUTES'!AB$3:AB$42)+ROW('DONNÉES BRUTES'!AB$3)),10),'DONNÉES BRUTES'!AB$3:AB$42*1000+(40-ROW('DONNÉES BRUTES'!AB$3:AB$42)+ROW('DONNÉES BRUTES'!AB$3)),0)),"—")} -> 192.6% | L25: {=IFERROR(INDEX('DONNÉES BRUTES'!P$3:P$42,MATCH(_xlfn.AGGREGATE(14,6,'DONNÉES BRUTES'!AB$3:AB$42*1000+(40-ROW('DONNÉES BRUTES'!AB$3:AB$42)+ROW('DONNÉES BRUTES'!AB$3)),10),'DONNÉES BRUTES'!AB$3:AB$42*1000+(40-ROW('DONNÉES BRUTES'!AB$3:AB$42)+ROW('DONNÉES BRUTES'!AB$3)),0)),"—")} -> +3.7% | N25: {=IFERROR(INDEX('DONNÉES BRUTES'!AC$3:AC$42,MATCH(_xlfn.AGGREGATE(14,6,'DONNÉES BRUTES'!AB$3:AB$42*1000+(40-ROW('DONNÉES BRUTES'!AB$3:AB$42)+ROW('DONNÉES BRUTES'!AB$3)),10),'DONNÉES BRUTES'!AB$3:AB$42*1000+(40-ROW('DONNÉES BRUTES'!AB$3:AB$42)+ROW('DONNÉES BRUTES'!AB$3)),0)),"—")} -> 2026-04-30 | R25: {=IFERROR(INDEX('DONNÉES BRUTES'!AD$3:AD$42,MATCH(_xlfn.AGGREGATE(14,6,'DONNÉES BRUTES'!AB$3:AB$42*1000+(40-ROW('DONNÉES BRUTES'!AB$3:AB$42)+ROW('DONNÉES BRUTES'!AB$3)),10),'DONNÉES BRUTES'!AB$3:AB$42*1000+(40-ROW('DONNÉES BRUTES'!AB$3:AB$42)+ROW('DONNÉES BRUTES'!AB$3)),0)),"—")} -> Neutre
B26: FinSight IA · Données issues de Supabase/Python · Scores calculés sur métriques Value, Growth, Quality, Momentum · Usage confidentiel

Sheet VALUE
A1: FinSight IA · Analyse VALUE · CAC 40 · 22/03/2026 | O1: Société | P1: Score Global | Q1: Signal
A2: Usage confidentiel · Calculs Python/NumPy depuis cache Supabase | O2: =IF(B4<>"—",LEFT(C4,20),"—") -> Hermès International | P2: =IF(E4<>"—",VALUE(LEFT(E4,FIND("/",E4)-1)),"") -> 75
A3: Rang | B3: Ticker | C3: Société | D3: Secteur | E3: Score | F3: EV/EBITDA | G3: EV/Revenue | H3: P/E | I3: Marge Brute | J3: Marge EBITDA | K3: Altman Z | L3: FCF Yield | M3: Décote DCF estimée | O3: =IF(B5<>"—",LEFT(C5,20),"—") -> L'Air Liquide S.A. | P3: =IF(E5<>"—",VALUE(LEFT(E5,FIND("/",E5)-1)),"") -> 74
A4: 1 | B4: {=IFERROR(INDEX('DONNÉES BRUTES'!A$3:A$42,MATCH(_xlfn.AGGREGATE(14,6,'DONNÉES BRUTES'!AB$3:AB$42+ROW('DONNÉES BRUTES'!AB$3:AB$42)/1000,1),'DONNÉES BRUTES'!AB$3:AB$42+ROW('DONNÉES BRUTES'!AB$3:AB$42)/1000,0)),"—")} -> RMS.PA | C4: {=IFERROR(INDEX('DONNÉES BRUTES'!B$3:B$42,MATCH(_xlfn.AGGREGATE(14,6,'DONNÉES BRUTES'!AB$3:AB$42+ROW('DONNÉES BRUTES'!AB$3:AB$42)/1000,1),'DONNÉES BRUTES'!AB$3:AB$42+ROW('DONNÉES BRUTES'!AB$3:AB$42)/1000,0)),"—")} -> Hermès International Société en commandite par actions | D4: {=IFERROR(INDEX('DONNÉES BRUTES'!C$3:C$42,MATCH(_xlfn.AGGREGATE(14,6,'DONNÉES BRUTES'!AB$3:AB$42+ROW('DONNÉES BRUTES'!AB$3:AB$42)/1000,1),'DONNÉES BRUTES'!AB$3:AB$42+ROW('DONNÉES BRUTES'!AB$3:AB$42)/1000,0)),"—")} -> Consumer Disc. | E4: {=IFERROR(INDEX('DONNÉES BRUTES'!AB$3:AB$42,MATCH(_xlfn.AGGREGATE(14,6,'DONNÉES BRUTES'!AB$3:AB$42+ROW('DONNÉES BRUTES'!AB$3:AB$42)/1000,1),'DONNÉES BRUTES'!AB$3:AB$42+ROW('DONNÉES BRUTES'!AB$3:AB$42)/1000,0))&"/100","—")} -> 75/100 | F4: {=IFERROR(INDEX('DONNÉES BRUTES'!I$3:I$42,MATCH(_xlfn.AGGREGATE(14,6,'DONNÉES BRUTES'!AB$3:AB$42+ROW('DONNÉES BRUTES'!AB$3:AB$42)/1000,1),'DONNÉES BRUTES'!AB$3:AB$42+ROW('DONNÉES BRUTES'!AB$3:AB$42)/1000,0)),"—")} -> — | G4: {=IFERROR(INDEX('DONNÉES BRUTES'!J$3:J$42,MATCH(_xlfn.AGGREGATE(14,6,'DONNÉES BRUTES'!AB$3:AB$42+ROW('DONNÉES BRUTES'!AB$3:AB$42)/1000,1),'DONNÉES BRUTES'!AB$3:AB$42+ROW('DONNÉES BRUTES'!AB$3:AB$42)/1000,0)),"—")} -> — | H4: {=IFERROR(INDEX('DONNÉES BRUTES'!K$3:K$42,MATCH(_xlfn.AGGREGATE(14,6,'DONNÉES BRUTES'!AB$3:AB$42+ROW('DONNÉES BRUTES'!AB$3:AB$42)/1000,1),'DONNÉES BRUTES'!AB$3:AB$42+ROW('DONNÉES BRUTES'!AB$3:AB$42)/1000,0)),"—")} -> — | I4: {=IFERROR(INDEX('DONNÉES BRUTES'!M$3:M$42,MATCH(_xlfn.AGGREGATE(14,6,'DONNÉES BRUTES'!AB$3:AB$42+ROW('DONNÉES BRUTES'!AB$3:AB$42)/1000,1),'DONNÉES BRUTES'!AB$3:AB$42+ROW('DONNÉES BRUTES'!AB$3:AB$42)/1000,0)),"—")} -> 71.1% | J4: {=IFERROR(INDEX('DONNÉES BRUTES'!N$3:N$42,MATCH(_xlfn.AGGREGATE(14,6,'DONNÉES BRUTES'!AB$3:AB$42+ROW('DONNÉES BRUTES'!AB$3:AB$42)/1000,1),'DONNÉES BRUTES'!AB$3:AB$42+ROW('DONNÉES BRUTES'!AB$3:AB$42)/1000,0)),"—")} -> 46.8% | K4: {=IFERROR(INDEX('DONNÉES BRUTES'!U$3:U$42,MATCH(_xlfn.AGGREGATE(14,6,'DONNÉES BRUTES'!AB$3:AB$42+ROW('DONNÉES BRUTES'!AB$3:AB$42)/1000,1),'DONNÉES BRUTES'!AB$3:AB$42+ROW('DONNÉES BRUTES'!AB$3:AB$42)/1000,0)),"—")} -> 9.47 | L4: — | M4: {=IFERROR(INDEX('DONNÉES BRUTES'!AD$3:AD$42,MATCH(_xlfn.AGGREGATE(14,6,'DONNÉES BRUTES'!AB$3:AB$42+ROW('DONNÉES BRUTES'!AB$3:AB$42)/1000,1),'DONNÉES BRUTES'!AB$3:AB$42+ROW('DONNÉES BRUTES'!AB$3:AB$42)/1000,0)),"—")} -> Surpondérer | O4: =IF(B6<>"—",LEFT(C6,20),"—") -> Sanofi | P4: =IF(E6<>"—",VALUE(LEFT(E6,FIND("/",E6)-1)),"") -> 72
A5: 2 | B5: {=IFERROR(INDEX('DONNÉES BRUTES'!A$3:A$42,MATCH(_xlfn.AGGREGATE(14,6,'DONNÉES BRUTES'!AB$3:AB$42+ROW('DONNÉES BRUTES'!AB$3:AB$42)/1000,2),'DONNÉES BRUTES'!AB$3:AB$42+ROW('DONNÉES BRUTES'!AB$3:AB$42)/1000,0)),"—")} -> AI.PA | C5: {=IFERROR(INDEX('DONNÉES BRUTES'!B$3:B$42,MATCH(_xlfn.AGGREGATE(14,6,'DONNÉES BRUTES'!AB$3:AB$42+ROW('DONNÉES BRUTES'!AB$3:AB$42)/1000,2),'DONNÉES BRUTES'!AB$3:AB$42+ROW('DONNÉES BRUTES'!AB$3:AB$42)/1000,0)),"—")} -> L'Air Liquide S.A. | D5: {=IFERROR(INDEX('DONNÉES BRUTES'!C$3:C$42,MATCH(_xlfn.AGGREGATE(14,6,'DONNÉES BRUTES'!AB$3:AB$42+ROW('DONNÉES BRUTES'!AB$3:AB$42)/1000,2),'DONNÉES BRUTES'!AB$3:AB$42+ROW('DONNÉES BRUTES'!AB$3:AB$42)/1000,0)),"—")} -> Materials | E5: {=IFERROR(INDEX('DONNÉES BRUTES'!AB$3:AB$42,MATCH(_xlfn.AGGREGATE(14,6,'DONNÉES BRUTES'!AB$3:AB$42+ROW('DONNÉES BRUTES'!AB$3:AB$42)/1000,2),'DONNÉES BRUTES'!AB$3:AB$42+ROW('DONNÉES BRUTES'!AB$3:AB$42)/1000,0))&"/100","—")} -> 74/100 | F5: {=IFERROR(INDEX('DONNÉES BRUTES'!I$3:I$42,MATCH(_xlfn.AGGREGATE(14,6,'DONNÉES BRUTES'!AB$3:AB$42+ROW('DONNÉES BRUTES'!AB$3:AB$42)/1000,2),'DONNÉES BRUTES'!AB$3:AB$42+ROW('DONNÉES BRUTES'!AB$3:AB$42)/1000,0)),"—")} -> — | G5: {=IFERROR(INDEX('DONNÉES BRUTES'!J$3:J$42,MATCH(_xlfn.AGGREGATE(14,6,'DONNÉES BRUTES'!AB$3:AB$42+ROW('DONNÉES BRUTES'!AB$3:AB$42)/1000,2),'DONNÉES BRUTES'!AB$3:AB$42+ROW('DONNÉES BRUTES'!AB$3:AB$42)/1000,0)),"—")} -> — | H5: {=IFERROR(INDEX('DONNÉES BRUTES'!K$3:K$42,MATCH(_xlfn.AGGREGATE(14,6,'DONNÉES BRUTES'!AB$3:AB$42+ROW('DONNÉES BRUTES'!AB$3:AB$42)/1000,2),'DONNÉES BRUTES'!AB$3:AB$42+ROW('DONNÉES BRUTES'!AB$3:AB$42)/1000,0)),"—")} -> — | I5: {=IFERROR(INDEX('DONNÉES BRUTES'!M$3:M$42,MATCH(_xlfn.AGGREGATE(14,6,'DONNÉES BRUTES'!AB$3:AB$42+ROW('DONNÉES BRUTES'!AB$3:AB$42)/1000,2),'DONNÉES BRUTES'!AB$3:AB$42+ROW('DONNÉES BRUTES'!AB$3:AB$42)/1000,0)),"—")} -> 64.2% | J5: {=IFERROR(INDEX('DONNÉES BRUTES'!N$3:N$42,MATCH(_xlfn.AGGREGATE(14,6,'DONNÉES BRUTES'!AB$3:AB$42+ROW('DONNÉES BRUTES'!AB$3:AB$42)/1000,2),'DONNÉES BRUTES'!AB$3:AB$42+ROW('DONNÉES BRUTES'!AB$3:AB$42)/1000,0)),"—")} -> 27.9% | K5: {=IFERROR(INDEX('DONNÉES BRUTES'!U$3:U$42,MATCH(_xlfn.AGGREGATE(14,6,'DONNÉES BRUTES'!AB$3:AB$42+ROW('DONNÉES BRUTES'!AB$3:AB$42)/1000,2),'DONNÉES BRUTES'!AB$3:AB$42+ROW('DONNÉES BRUTES'!AB$3:AB$42)/1000,0)),"—")} -> 3.26 | L5: — | M5: {=IFERROR(INDEX('DONNÉES BRUTES'!AD$3:AD$42,MATCH(_xlfn.AGGREGATE(14,6,'DONNÉES BRUTES'!AB$3:AB$42+ROW('DONNÉES BRUTES'!AB$3:AB$42)/1000,2),'DONNÉES BRUTES'!AB$3:AB$42+ROW('DONNÉES BRUTES'!AB$3:AB$42)/1000,0)),"—")} -> Neutre | O5: =IF(B7<>"—",LEFT(C7,20),"—") -> Eurofins Scientific | P5: =IF(E7<>"—",VALUE(LEFT(E7,FIND("/",E7)-1)),"") -> 72
A6: 3 | B6: {=IFERROR(INDEX('DONNÉES BRUTES'!A$3:A$42,MATCH(_xlfn.AGGREGATE(14,6,'DONNÉES BRUTES'!AB$3:AB$42+ROW('DONNÉES BRUTES'!AB$3:AB$42)/1000,3),'DONNÉES BRUTES'!AB$3:AB$42+ROW('DONNÉES BRUTES'!AB$3:AB$42)/1000,0)),"—")} -> SAN.PA | C6: {=IFERROR(INDEX('DONNÉES BRUTES'!B$3:B$42,MATCH(_xlfn.AGGREGATE(14,6,'DONNÉES BRUTES'!AB$3:AB$42+ROW('DONNÉES BRUTES'!AB$3:AB$42)/1000,3),'DONNÉES BRUTES'!AB$3:AB$42+ROW('DONNÉES BRUTES'!AB$3:AB$42)/1000,0)),"—")} -> Sanofi | D6: {=IFERROR(INDEX('DONNÉES BRUTES'!C$3:C$42,MATCH(_xlfn.AGGREGATE(14,6,'DONNÉES BRUTES'!AB$3:AB$42+ROW('DONNÉES BRUTES'!AB$3:AB$42)/1000,3),'DONNÉES BRUTES'!AB$3:AB$42+ROW('DONNÉES BRUTES'!AB$3:AB$42)/1000,0)),"—")} -> Healthcare | E6: {=IFERROR(INDEX('DONNÉES BRUTES'!AB$3:AB$42,MATCH(_xlfn.AGGREGATE(14,6,'DONNÉES BRUTES'!AB$3:AB$42+ROW('DONNÉES BRUTES'!AB$3:AB$42)/1000,3),'DONNÉES BRUTES'!AB$3:AB$42+ROW('DONNÉES BRUTES'!AB$3:AB$42)/1000,0))&"/100","—")} -> 72/100 | F6: {=IFERROR(INDEX('DONNÉES BRUTES'!I$3:I$42,MATCH(_xlfn.AGGREGATE(14,6,'DONNÉES BRUTES'!AB$3:AB$42+ROW('DONNÉES BRUTES'!AB$3:AB$42)/1000,3),'DONNÉES BRUTES'!AB$3:AB$42+ROW('DONNÉES BRUTES'!AB$3:AB$42)/1000,0)),"—")} -> — | G6: {=IFERROR(INDEX('DONNÉES BRUTES'!J$3:J$42,MATCH(_xlfn.AGGREGATE(14,6,'DONNÉES BRUTES'!AB$3:AB$42+ROW('DONNÉES BRUTES'!AB$3:AB$42)/1000,3),'DONNÉES BRUTES'!AB$3:AB$42+ROW('DONNÉES BRUTES'!AB$3:AB$42)/1000,0)),"—")} -> — | H6: {=IFERROR(INDEX('DONNÉES BRUTES'!K$3:K$42,MATCH(_xlfn.AGGREGATE(14,6,'DONNÉES BRUTES'!AB$3:AB$42+ROW('DONNÉES BRUTES'!AB$3:AB$42)/1000,3),'DONNÉES BRUTES'!AB$3:AB$42+ROW('DONNÉES BRUTES'!AB$3:AB$42)/1000,0)),"—")} -> — | I6: {=IFERROR(INDEX('DONNÉES BRUTES'!M$3:M$42,MATCH(_xlfn.AGGREGATE(14,6,'DONNÉES BRUTES'!AB$3:AB$42+ROW('DONNÉES BRUTES'!AB$3:AB$42)/1000,3),'DONNÉES BRUTES'!AB$3:AB$42+ROW('DONNÉES BRUTES'!AB$3:AB$42)/1000,0)),"—")} -> 72.1% | J6: {=IFERROR(INDEX('DONNÉES BRUTES'!N$3:N$42,MATCH(_xlfn.AGGREGATE(14,6,'DONNÉES BRUTES'!AB$3:AB$42+ROW('DONNÉES BRUTES'!AB$3:AB$42)/1000,3),'DONNÉES BRUTES'!AB$3:AB$42+ROW('DONNÉES BRUTES'!AB$3:AB$42)/1000,0)),"—")} -> 26.7% | K6: {=IFERROR(INDEX('DONNÉES BRUTES'!U$3:U$42,MATCH(_xlfn.AGGREGATE(14,6,'DONNÉES BRUTES'!AB$3:AB$42+ROW('DONNÉES BRUTES'!AB$3:AB$42)/1000,3),'DONNÉES BRUTES'!AB$3:AB$42+ROW('DONNÉES BRUTES'!AB$3:AB$42)/1000,0)),"—")} -> — | L6: — | M6: {=IFERROR(INDEX('DONNÉES BRUTES'!AD$3:AD$42,MATCH(_xlfn.AGGREGATE(14,6,'DONNÉES BRUTES'!AB$3:AB$42+ROW('DONNÉES BRUTES'!AB$3:AB$42)/1000,3),'DONNÉES BRUTES'!AB$3:AB$42+ROW('DONNÉES BRUTES'!AB$3:AB$42)/1000,0)),"—")} -> Neutre | O6: =IF(B8<>"—",LEFT(C8,20),"—") -> Dassault Systèmes SE | P6: =IF(E8<>"—",VALUE(LEFT(E8,FIND("/",E8)-1)),"") -> 72
A7: 4 | B7: {=IFERROR(INDEX('DONNÉES BRUTES'!A$3:A$42,MATCH(_xlfn.AGGREGATE(14,6,'DONNÉES BRUTES'!AB$3:AB$42+ROW('DONNÉES BRUTES'!AB$3:AB$42)/1000,4),'DONNÉES BRUTES'!AB$3:AB$42+ROW('DONNÉES BRUTES'!AB$3:AB$42)/1000,0)),"—")} -> ERF.PA | C7: {=IFERROR(INDEX('DONNÉES BRUTES'!B$3:B$42,MATCH(_xlfn.AGGREGATE(14,6,'DONNÉES BRUTES'!AB$3:AB$42+ROW('DONNÉES BRUTES'!AB$3:AB$42)/1000,4),'DONNÉES BRUTES'!AB$3:AB$42+ROW('DONNÉES BRUTES'!AB$3:AB$42)/1000,0)),"—")} -> Eurofins Scientific SE | D7: {=IFERROR(INDEX('DONNÉES BRUTES'!C$3:C$42,MATCH(_xlfn.AGGREGATE(14,6,'DONNÉES BRUTES'!AB$3:AB$42+ROW('DONNÉES BRUTES'!AB$3:AB$42)/1000,4),'DONNÉES BRUTES'!AB$3:AB$42+ROW('DONNÉES BRUTES'!AB$3:AB$42)/1000,0)),"—")} -> Healthcare | E7: {=IFERROR(INDEX('DONNÉES BRUTES'!AB$3:AB$42,MATCH(_xlfn.AGGREGATE(14,6,'DONNÉES BRUTES'!AB$3:AB$42+ROW('DONNÉES BRUTES'!AB$3:AB$42)/1000,4),'DONNÉES BRUTES'!AB$3:AB$42+ROW('DONNÉES BRUTES'!AB$3:AB$42)/1000,0))&"/100","—")} -> 72/100 | F7: {=IFERROR(INDEX('DONNÉES BRUTES'!I$3:I$42,MATCH(_xlfn.AGGREGATE(14,6,'DONNÉES BRUTES'!AB$3:AB$42+ROW('DONNÉES BRUTES'!AB$3:AB$42)/1000,4),'DONNÉES BRUTES'!AB$3:AB$42+ROW('DONNÉES BRUTES'!AB$3:AB$42)/1000,0)),"—")} -> — | G7: {=IFERROR(INDEX('DONNÉES BRUTES'!J$3:J$42,MATCH(_xlfn.AGGREGATE(14,6,'DONNÉES BRUTES'!AB$3:AB$42+ROW('DONNÉES BRUTES'!AB$3:AB$42)/1000,4),'DONNÉES BRUTES'!AB$3:AB$42+ROW('DONNÉES BRUTES'!AB$3:AB$42)/1000,0)),"—")} -> — | H7: {=IFERROR(INDEX('DONNÉES BRUTES'!K$3:K$42,MATCH(_xlfn.AGGREGATE(14,6,'DONNÉES BRUTES'!AB$3:AB$42+ROW('DONNÉES BRUTES'!AB$3:AB$42)/1000,4),'DONNÉES BRUTES'!AB$3:AB$42+ROW('DONNÉES BRUTES'!AB$3:AB$42)/1000,0)),"—")} -> — | I7: {=IFERROR(INDEX('DONNÉES BRUTES'!M$3:M$42,MATCH(_xlfn.AGGREGATE(14,6,'DONNÉES BRUTES'!AB$3:AB$42+ROW('DONNÉES BRUTES'!AB$3:AB$42)/1000,4),'DONNÉES BRUTES'!AB$3:AB$42+ROW('DONNÉES BRUTES'!AB$3:AB$42)/1000,0)),"—")} -> 68.1% | J7: {=IFERROR(INDEX('DONNÉES BRUTES'!N$3:N$42,MATCH(_xlfn.AGGREGATE(14,6,'DONNÉES BRUTES'!AB$3:AB$42+ROW('DONNÉES BRUTES'!AB$3:AB$42)/1000,4),'DONNÉES BRUTES'!AB$3:AB$42+ROW('DONNÉES BRUTES'!AB$3:AB$42)/1000,0)),"—")} -> 21.0% | K7: {=IFERROR(INDEX('DONNÉES BRUTES'!U$3:U$42,MATCH(_xlfn.AGGREGATE(14,6,'DONNÉES BRUTES'!AB$3:AB$42+ROW('DONNÉES BRUTES'!AB$3:AB$42)/1000,4),'DONNÉES BRUTES'!AB$3:AB$42+ROW('DONNÉES BRUTES'!AB$3:AB$42)/1000,0)),"—")} -> 2.27 | L7: — | M7: {=IFERROR(INDEX('DONNÉES BRUTES'!AD$3:AD$42,MATCH(_xlfn.AGGREGATE(14,6,'DONNÉES BRUTES'!AB$3:AB$42+ROW('DONNÉES BRUTES'!AB$3:AB$42)/1000,4),'DONNÉES BRUTES'!AB$3:AB$42+ROW('DONNÉES BRUTES'!AB$3:AB$42)/1000,0)),"—")} -> Neutre | O7: =IF(B9<>"—",LEFT(C9,20),"—") -> Alstom SA | P7: =IF(E9<>"—",VALUE(LEFT(E9,FIND("/",E9)-1)),"") -> 70
A8: 5 | B8: {=IFERROR(INDEX('DONNÉES BRUTES'!A$3:A$42,MATCH(_xlfn.AGGREGATE(14,6,'DONNÉES BRUTES'!AB$3:AB$42+ROW('DONNÉES BRUTES'!AB$3:AB$42)/1000,5),'DONNÉES BRUTES'!AB$3:AB$42+ROW('DONNÉES BRUTES'!AB$3:AB$42)/1000,0)),"—")} -> DSY.PA | C8: {=IFERROR(INDEX('DONNÉES BRUTES'!B$3:B$42,MATCH(_xlfn.AGGREGATE(14,6,'DONNÉES BRUTES'!AB$3:AB$42+ROW('DONNÉES BRUTES'!AB$3:AB$42)/1000,5),'DONNÉES BRUTES'!AB$3:AB$42+ROW('DONNÉES BRUTES'!AB$3:AB$42)/1000,0)),"—")} -> Dassault Systèmes SE | D8: {=IFERROR(INDEX('DONNÉES BRUTES'!C$3:C$42,MATCH(_xlfn.AGGREGATE(14,6,'DONNÉES BRUTES'!AB$3:AB$42+ROW('DONNÉES BRUTES'!AB$3:AB$42)/1000,5),'DONNÉES BRUTES'!AB$3:AB$42+ROW('DONNÉES BRUTES'!AB$3:AB$42)/1000,0)),"—")} -> Technology | E8: {=IFERROR(INDEX('DONNÉES BRUTES'!AB$3:AB$42,MATCH(_xlfn.AGGREGATE(14,6,'DONNÉES BRUTES'!AB$3:AB$42+ROW('DONNÉES BRUTES'!AB$3:AB$42)/1000,5),'DONNÉES BRUTES'!AB$3:AB$42+ROW('DONNÉES BRUTES'!AB$3:AB$42)/1000,0))&"/100","—")} -> 72/100 | F8: {=IFERROR(INDEX('DONNÉES BRUTES'!I$3:I$42,MATCH(_xlfn.AGGREGATE(14,6,'DONNÉES BRUTES'!AB$3:AB$42+ROW('DONNÉES BRUTES'!AB$3:AB$42)/1000,5),'DONNÉES BRUTES'!AB$3:AB$42+ROW('DONNÉES BRUTES'!AB$3:AB$42)/1000,0)),"—")} -> — | G8: {=IFERROR(INDEX('DONNÉES BRUTES'!J$3:J$42,MATCH(_xlfn.AGGREGATE(14,6,'DONNÉES BRUTES'!AB$3:AB$42+ROW('DONNÉES BRUTES'!AB$3:AB$42)/1000,5),'DONNÉES BRUTES'!AB$3:AB$42+ROW('DONNÉES BRUTES'!AB$3:AB$42)/1000,0)),"—")} -> — | H8: {=IFERROR(INDEX('DONNÉES BRUTES'!K$3:K$42,MATCH(_xlfn.AGGREGATE(14,6,'DONNÉES BRUTES'!AB$3:AB$42+ROW('DONNÉES BRUTES'!AB$3:AB$42)/1000,5),'DONNÉES BRUTES'!AB$3:AB$42+ROW('DONNÉES BRUTES'!AB$3:AB$42)/1000,0)),"—")} -> — | I8: {=IFERROR(INDEX('DONNÉES BRUTES'!M$3:M$42,MATCH(_xlfn.AGGREGATE(14,6,'DONNÉES BRUTES'!AB$3:AB$42+ROW('DONNÉES BRUTES'!AB$3:AB$42)/1000,5),'DONNÉES BRUTES'!AB$3:AB$42+ROW('DONNÉES BRUTES'!AB$3:AB$42)/1000,0)),"—")} -> 83.7% | J8: {=IFERROR(INDEX('DONNÉES BRUTES'!N$3:N$42,MATCH(_xlfn.AGGREGATE(14,6,'DONNÉES BRUTES'!AB$3:AB$42+ROW('DONNÉES BRUTES'!AB$3:AB$42)/1000,5),'DONNÉES BRUTES'!AB$3:AB$42+ROW('DONNÉES BRUTES'!AB$3:AB$42)/1000,0)),"—")} -> 30.4% | K8: {=IFERROR(INDEX('DONNÉES BRUTES'!U$3:U$42,MATCH(_xlfn.AGGREGATE(14,6,'DONNÉES BRUTES'!AB$3:AB$42+ROW('DONNÉES BRUTES'!AB$3:AB$42)/1000,5),'DONNÉES BRUTES'!AB$3:AB$42+ROW('DONNÉES BRUTES'!AB$3:AB$42)/1000,0)),"—")} -> — | L8: — | M8: {=IFERROR(INDEX('DONNÉES BRUTES'!AD$3:AD$42,MATCH(_xlfn.AGGREGATE(14,6,'DONNÉES BRUTES'!AB$3:AB$42+ROW('DONNÉES BRUTES'!AB$3:AB$42)/1000,5),'DONNÉES BRUTES'!AB$3:AB$42+ROW('DONNÉES BRUTES'!AB$3:AB$42)/1000,0)),"—")} -> Neutre | O8: =IF(B10<>"—",LEFT(C10,20),"—") -> Unibail-Rodamco-West | P8: =IF(E10<>"—",VALUE(LEFT(E10,FIND("/",E10)-1)),"") -> 69
A9: 6 | B9: {=IFERROR(INDEX('DONNÉES BRUTES'!A$3:A$42,MATCH(_xlfn.AGGREGATE(14,6,'DONNÉES BRUTES'!AB$3:AB$42+ROW('DONNÉES BRUTES'!AB$3:AB$42)/1000,6),'DONNÉES BRUTES'!AB$3:AB$42+ROW('DONNÉES BRUTES'!AB$3:AB$42)/1000,0)),"—")} -> ALO.PA | C9: {=IFERROR(INDEX('DONNÉES BRUTES'!B$3:B$42,MATCH(_xlfn.AGGREGATE(14,6,'DONNÉES BRUTES'!AB$3:AB$42+ROW('DONNÉES BRUTES'!AB$3:AB$42)/1000,6),'DONNÉES BRUTES'!AB$3:AB$42+ROW('DONNÉES BRUTES'!AB$3:AB$42)/1000,0)),"—")} -> Alstom SA | D9: {=IFERROR(INDEX('DONNÉES BRUTES'!C$3:C$42,MATCH(_xlfn.AGGREGATE(14,6,'DONNÉES BRUTES'!AB$3:AB$42+ROW('DONNÉES BRUTES'!AB$3:AB$42)/1000,6),'DONNÉES BRUTES'!AB$3:AB$42+ROW('DONNÉES BRUTES'!AB$3:AB$42)/1000,0)),"—")} -> Industrials | E9: {=IFERROR(INDEX('DONNÉES BRUTES'!AB$3:AB$42,MATCH(_xlfn.AGGREGATE(14,6,'DONNÉES BRUTES'!AB$3:AB$42+ROW('DONNÉES BRUTES'!AB$3:AB$42)/1000,6),'DONNÉES BRUTES'!AB$3:AB$42+ROW('DONNÉES BRUTES'!AB$3:AB$42)/1000,0))&"/100","—")} -> 70/100 | F9: {=IFERROR(INDEX('DONNÉES BRUTES'!I$3:I$42,MATCH(_xlfn.AGGREGATE(14,6,'DONNÉES BRUTES'!AB$3:AB$42+ROW('DONNÉES BRUTES'!AB$3:AB$42)/1000,6),'DONNÉES BRUTES'!AB$3:AB$42+ROW('DONNÉES BRUTES'!AB$3:AB$42)/1000,0)),"—")} -> — | G9: {=IFERROR(INDEX('DONNÉES BRUTES'!J$3:J$42,MATCH(_xlfn.AGGREGATE(14,6,'DONNÉES BRUTES'!AB$3:AB$42+ROW('DONNÉES BRUTES'!AB$3:AB$42)/1000,6),'DONNÉES BRUTES'!AB$3:AB$42+ROW('DONNÉES BRUTES'!AB$3:AB$42)/1000,0)),"—")} -> — | H9: {=IFERROR(INDEX('DONNÉES BRUTES'!K$3:K$42,MATCH(_xlfn.AGGREGATE(14,6,'DONNÉES BRUTES'!AB$3:AB$42+ROW('DONNÉES BRUTES'!AB$3:AB$42)/1000,6),'DONNÉES BRUTES'!AB$3:AB$42+ROW('DONNÉES BRUTES'!AB$3:AB$42)/1000,0)),"—")} -> — | I9: {=IFERROR(INDEX('DONNÉES BRUTES'!M$3:M$42,MATCH(_xlfn.AGGREGATE(14,6,'DONNÉES BRUTES'!AB$3:AB$42+ROW('DONNÉES BRUTES'!AB$3:AB$42)/1000,6),'DONNÉES BRUTES'!AB$3:AB$42+ROW('DONNÉES BRUTES'!AB$3:AB$42)/1000,0)),"—")} -> 12.5% | J9: {=IFERROR(INDEX('DONNÉES BRUTES'!N$3:N$42,MATCH(_xlfn.AGGREGATE(14,6,'DONNÉES BRUTES'!AB$3:AB$42+ROW('DONNÉES BRUTES'!AB$3:AB$42)/1000,6),'DONNÉES BRUTES'!AB$3:AB$42+ROW('DONNÉES BRUTES'!AB$3:AB$42)/1000,0)),"—")} -> 6.8% | K9: {=IFERROR(INDEX('DONNÉES BRUTES'!U$3:U$42,MATCH(_xlfn.AGGREGATE(14,6,'DONNÉES BRUTES'!AB$3:AB$42+ROW('DONNÉES BRUTES'!AB$3:AB$42)/1000,6),'DONNÉES BRUTES'!AB$3:AB$42+ROW('DONNÉES BRUTES'!AB$3:AB$42)/1000,0)),"—")} -> 0.49 | L9: — | M9: {=IFERROR(INDEX('DONNÉES BRUTES'!AD$3:AD$42,MATCH(_xlfn.AGGREGATE(14,6,'DONNÉES BRUTES'!AB$3:AB$42+ROW('DONNÉES BRUTES'!AB$3:AB$42)/1000,6),'DONNÉES BRUTES'!AB$3:AB$42+ROW('DONNÉES BRUTES'!AB$3:AB$42)/1000,0)),"—")} -> Neutre | O9: =IF(B11<>"—",LEFT(C11,20),"—") -> Safran SA | P9: =IF(E11<>"—",VALUE(LEFT(E11,FIND("/",E11)-1)),"") -> 68
A10: 7 | B10: {=IFERROR(INDEX('DONNÉES BRUTES'!A$3:A$42,MATCH(_xlfn.AGGREGATE(14,6,'DONNÉES BRUTES'!AB$3:AB$42+ROW('DONNÉES BRUTES'!AB$3:AB$42)/1000,7),'DONNÉES BRUTES'!AB$3:AB$42+ROW('DONNÉES BRUTES'!AB$3:AB$42)/1000,0)),"—")} -> URW.PA | C10: {=IFERROR(INDEX('DONNÉES BRUTES'!B$3:B$42,MATCH(_xlfn.AGGREGATE(14,6,'DONNÉES BRUTES'!AB$3:AB$42+ROW('DONNÉES BRUTES'!AB$3:AB$42)/1000,7),'DONNÉES BRUTES'!AB$3:AB$42+ROW('DONNÉES BRUTES'!AB$3:AB$42)/1000,0)),"—")} -> Unibail-Rodamco-Westfield SE | D10: {=IFERROR(INDEX('DONNÉES BRUTES'!C$3:C$42,MATCH(_xlfn.AGGREGATE(14,6,'DONNÉES BRUTES'!AB$3:AB$42+ROW('DONNÉES BRUTES'!AB$3:AB$42)/1000,7),'DONNÉES BRUTES'!AB$3:AB$42+ROW('DONNÉES BRUTES'!AB$3:AB$42)/1000,0)),"—")} -> Real Estate | E10: {=IFERROR(INDEX('DONNÉES BRUTES'!AB$3:AB$42,MATCH(_xlfn.AGGREGATE(14,6,'DONNÉES BRUTES'!AB$3:AB$42+ROW('DONNÉES BRUTES'!AB$3:AB$42)/1000,7),'DONNÉES BRUTES'!AB$3:AB$42+ROW('DONNÉES BRUTES'!AB$3:AB$42)/1000,0))&"/100","—")} -> 69/100 | F10: {=IFERROR(INDEX('DONNÉES BRUTES'!I$3:I$42,MATCH(_xlfn.AGGREGATE(14,6,'DONNÉES BRUTES'!AB$3:AB$42+ROW('DONNÉES BRUTES'!AB$3:AB$42)/1000,7),'DONNÉES BRUTES'!AB$3:AB$42+ROW('DONNÉES BRUTES'!AB$3:AB$42)/1000,0)),"—")} -> — | G10: {=IFERROR(INDEX('DONNÉES BRUTES'!J$3:J$42,MATCH(_xlfn.AGGREGATE(14,6,'DONNÉES BRUTES'!AB$3:AB$42+ROW('DONNÉES BRUTES'!AB$3:AB$42)/1000,7),'DONNÉES BRUTES'!AB$3:AB$42+ROW('DONNÉES BRUTES'!AB$3:AB$42)/1000,0)),"—")} -> — | H10: {=IFERROR(INDEX('DONNÉES BRUTES'!K$3:K$42,MATCH(_xlfn.AGGREGATE(14,6,'DONNÉES BRUTES'!AB$3:AB$42+ROW('DONNÉES BRUTES'!AB$3:AB$42)/1000,7),'DONNÉES BRUTES'!AB$3:AB$42+ROW('DONNÉES BRUTES'!AB$3:AB$42)/1000,0)),"—")} -> — | I10: {=IFERROR(INDEX('DONNÉES BRUTES'!M$3:M$42,MATCH(_xlfn.AGGREGATE(14,6,'DONNÉES BRUTES'!AB$3:AB$42+ROW('DONNÉES BRUTES'!AB$3:AB$42)/1000,7),'DONNÉES BRUTES'!AB$3:AB$42+ROW('DONNÉES BRUTES'!AB$3:AB$42)/1000,0)),"—")} -> 64.6% | J10: {=IFERROR(INDEX('DONNÉES BRUTES'!N$3:N$42,MATCH(_xlfn.AGGREGATE(14,6,'DONNÉES BRUTES'!AB$3:AB$42+ROW('DONNÉES BRUTES'!AB$3:AB$42)/1000,7),'DONNÉES BRUTES'!AB$3:AB$42+ROW('DONNÉES BRUTES'!AB$3:AB$42)/1000,0)),"—")} -> 89.1% | K10: {=IFERROR(INDEX('DONNÉES BRUTES'!U$3:U$42,MATCH(_xlfn.AGGREGATE(14,6,'DONNÉES BRUTES'!AB$3:AB$42+ROW('DONNÉES BRUTES'!AB$3:AB$42)/1000,7),'DONNÉES BRUTES'!AB$3:AB$42+ROW('DONNÉES BRUTES'!AB$3:AB$42)/1000,0)),"—")} -> 1.22 | L10: — | M10: {=IFERROR(INDEX('DONNÉES BRUTES'!AD$3:AD$42,MATCH(_xlfn.AGGREGATE(14,6,'DONNÉES BRUTES'!AB$3:AB$42+ROW('DONNÉES BRUTES'!AB$3:AB$42)/1000,7),'DONNÉES BRUTES'!AB$3:AB$42+ROW('DONNÉES BRUTES'!AB$3:AB$42)/1000,0)),"—")} -> Neutre | O10: =IF(B12<>"—",LEFT(C12,20),"—") -> Airbus SE | P10: =IF(E12<>"—",VALUE(LEFT(E12,FIND("/",E12)-1)),"") -> 68
A11: 8 | B11: {=IFERROR(INDEX('DONNÉES BRUTES'!A$3:A$42,MATCH(_xlfn.AGGREGATE(14,6,'DONNÉES BRUTES'!AB$3:AB$42+ROW('DONNÉES BRUTES'!AB$3:AB$42)/1000,8),'DONNÉES BRUTES'!AB$3:AB$42+ROW('DONNÉES BRUTES'!AB$3:AB$42)/1000,0)),"—")} -> SAF.PA | C11: {=IFERROR(INDEX('DONNÉES BRUTES'!B$3:B$42,MATCH(_xlfn.AGGREGATE(14,6,'DONNÉES BRUTES'!AB$3:AB$42+ROW('DONNÉES BRUTES'!AB$3:AB$42)/1000,8),'DONNÉES BRUTES'!AB$3:AB$42+ROW('DONNÉES BRUTES'!AB$3:AB$42)/1000,0)),"—")} -> Safran SA | D11: {=IFERROR(INDEX('DONNÉES BRUTES'!C$3:C$42,MATCH(_xlfn.AGGREGATE(14,6,'DONNÉES BRUTES'!AB$3:AB$42+ROW('DONNÉES BRUTES'!AB$3:AB$42)/1000,8),'DONNÉES BRUTES'!AB$3:AB$42+ROW('DONNÉES BRUTES'!AB$3:AB$42)/1000,0)),"—")} -> Industrials | E11: {=IFERROR(INDEX('DONNÉES BRUTES'!AB$3:AB$42,MATCH(_xlfn.AGGREGATE(14,6,'DONNÉES BRUTES'!AB$3:AB$42+ROW('DONNÉES BRUTES'!AB$3:AB$42)/1000,8),'DONNÉES BRUTES'!AB$3:AB$42+ROW('DONNÉES BRUTES'!AB$3:AB$42)/1000,0))&"/100","—")} -> 68/100 | F11: {=IFERROR(INDEX('DONNÉES BRUTES'!I$3:I$42,MATCH(_xlfn.AGGREGATE(14,6,'DONNÉES BRUTES'!AB$3:AB$42+ROW('DONNÉES BRUTES'!AB$3:AB$42)/1000,8),'DONNÉES BRUTES'!AB$3:AB$42+ROW('DONNÉES BRUTES'!AB$3:AB$42)/1000,0)),"—")} -> — | G11: {=IFERROR(INDEX('DONNÉES BRUTES'!J$3:J$42,MATCH(_xlfn.AGGREGATE(14,6,'DONNÉES BRUTES'!AB$3:AB$42+ROW('DONNÉES BRUTES'!AB$3:AB$42)/1000,8),'DONNÉES BRUTES'!AB$3:AB$42+ROW('DONNÉES BRUTES'!AB$3:AB$42)/1000,0)),"—")} -> — | H11: {=IFERROR(INDEX('DONNÉES BRUTES'!K$3:K$42,MATCH(_xlfn.AGGREGATE(14,6,'DONNÉES BRUTES'!AB$3:AB$42+ROW('DONNÉES BRUTES'!AB$3:AB$42)/1000,8),'DONNÉES BRUTES'!AB$3:AB$42+ROW('DONNÉES BRUTES'!AB$3:AB$42)/1000,0)),"—")} -> — | I11: {=IFERROR(INDEX('DONNÉES BRUTES'!M$3:M$42,MATCH(_xlfn.AGGREGATE(14,6,'DONNÉES BRUTES'!AB$3:AB$42+ROW('DONNÉES BRUTES'!AB$3:AB$42)/1000,8),'DONNÉES BRUTES'!AB$3:AB$42+ROW('DONNÉES BRUTES'!AB$3:AB$42)/1000,0)),"—")} -> 46.9% | J11: {=IFERROR(INDEX('DONNÉES BRUTES'!N$3:N$42,MATCH(_xlfn.AGGREGATE(14,6,'DONNÉES BRUTES'!AB$3:AB$42+ROW('DONNÉES BRUTES'!AB$3:AB$42)/1000,8),'DONNÉES BRUTES'!AB$3:AB$42+ROW('DONNÉES BRUTES'!AB$3:AB$42)/1000,0)),"—")} -> 39.2% | K11: {=IFERROR(INDEX('DONNÉES BRUTES'!U$3:U$42,MATCH(_xlfn.AGGREGATE(14,6,'DONNÉES BRUTES'!AB$3:AB$42+ROW('DONNÉES BRUTES'!AB$3:AB$42)/1000,8),'DONNÉES BRUTES'!AB$3:AB$42+ROW('DONNÉES BRUTES'!AB$3:AB$42)/1000,0)),"—")} -> 1.54 | L11: — | M11: {=IFERROR(INDEX('DONNÉES BRUTES'!AD$3:AD$42,MATCH(_xlfn.AGGREGATE(14,6,'DONNÉES BRUTES'!AB$3:AB$42+ROW('DONNÉES BRUTES'!AB$3:AB$42)/1000,8),'DONNÉES BRUTES'!AB$3:AB$42+ROW('DONNÉES BRUTES'!AB$3:AB$42)/1000,0)),"—")} -> Neutre | O11: =IF(B13<>"—",LEFT(C13,20),"—") -> Crédit Agricole S.A. | P11: =IF(E13<>"—",VALUE(LEFT(E13,FIND("/",E13)-1)),"") -> 65
A12: 9 | B12: {=IFERROR(INDEX('DONNÉES BRUTES'!A$3:A$42,MATCH(_xlfn.AGGREGATE(14,6,'DONNÉES BRUTES'!AB$3:AB$42+ROW('DONNÉES BRUTES'!AB$3:AB$42)/1000,9),'DONNÉES BRUTES'!AB$3:AB$42+ROW('DONNÉES BRUTES'!AB$3:AB$42)/1000,0)),"—")} -> AIR.PA | C12: {=IFERROR(INDEX('DONNÉES BRUTES'!B$3:B$42,MATCH(_xlfn.AGGREGATE(14,6,'DONNÉES BRUTES'!AB$3:AB$42+ROW('DONNÉES BRUTES'!AB$3:AB$42)/1000,9),'DONNÉES BRUTES'!AB$3:AB$42+ROW('DONNÉES BRUTES'!AB$3:AB$42)/1000,0)),"—")} -> Airbus SE | D12: {=IFERROR(INDEX('DONNÉES BRUTES'!C$3:C$42,MATCH(_xlfn.AGGREGATE(14,6,'DONNÉES BRUTES'!AB$3:AB$42+ROW('DONNÉES BRUTES'!AB$3:AB$42)/1000,9),'DONNÉES BRUTES'!AB$3:AB$42+ROW('DONNÉES BRUTES'!AB$3:AB$42)/1000,0)),"—")} -> Industrials | E12: {=IFERROR(INDEX('DONNÉES BRUTES'!AB$3:AB$42,MATCH(_xlfn.AGGREGATE(14,6,'DONNÉES BRUTES'!AB$3:AB$42+ROW('DONNÉES BRUTES'!AB$3:AB$42)/1000,9),'DONNÉES BRUTES'!AB$3:AB$42+ROW('DONNÉES BRUTES'!AB$3:AB$42)/1000,0))&"/100","—")} -> 68/100 | F12: {=IFERROR(INDEX('DONNÉES BRUTES'!I$3:I$42,MATCH(_xlfn.AGGREGATE(14,6,'DONNÉES BRUTES'!AB$3:AB$42+ROW('DONNÉES BRUTES'!AB$3:AB$42)/1000,9),'DONNÉES BRUTES'!AB$3:AB$42+ROW('DONNÉES BRUTES'!AB$3:AB$42)/1000,0)),"—")} -> — | G12: {=IFERROR(INDEX('DONNÉES BRUTES'!J$3:J$42,MATCH(_xlfn.AGGREGATE(14,6,'DONNÉES BRUTES'!AB$3:AB$42+ROW('DONNÉES BRUTES'!AB$3:AB$42)/1000,9),'DONNÉES BRUTES'!AB$3:AB$42+ROW('DONNÉES BRUTES'!AB$3:AB$42)/1000,0)),"—")} -> — | H12: {=IFERROR(INDEX('DONNÉES BRUTES'!K$3:K$42,MATCH(_xlfn.AGGREGATE(14,6,'DONNÉES BRUTES'!AB$3:AB$42+ROW('DONNÉES BRUTES'!AB$3:AB$42)/1000,9),'DONNÉES BRUTES'!AB$3:AB$42+ROW('DONNÉES BRUTES'!AB$3:AB$42)/1000,0)),"—")} -> — | I12: {=IFERROR(INDEX('DONNÉES BRUTES'!M$3:M$42,MATCH(_xlfn.AGGREGATE(14,6,'DONNÉES BRUTES'!AB$3:AB$42+ROW('DONNÉES BRUTES'!AB$3:AB$42)/1000,9),'DONNÉES BRUTES'!AB$3:AB$42+ROW('DONNÉES BRUTES'!AB$3:AB$42)/1000,0)),"—")} -> 14.9% | J12: {=IFERROR(INDEX('DONNÉES BRUTES'!N$3:N$42,MATCH(_xlfn.AGGREGATE(14,6,'DONNÉES BRUTES'!AB$3:AB$42+ROW('DONNÉES BRUTES'!AB$3:AB$42)/1000,9),'DONNÉES BRUTES'!AB$3:AB$42+ROW('DONNÉES BRUTES'!AB$3:AB$42)/1000,0)),"—")} -> 14.0% | K12: {=IFERROR(INDEX('DONNÉES BRUTES'!U$3:U$42,MATCH(_xlfn.AGGREGATE(14,6,'DONNÉES BRUTES'!AB$3:AB$42+ROW('DONNÉES BRUTES'!AB$3:AB$42)/1000,9),'DONNÉES BRUTES'!AB$3:AB$42+ROW('DONNÉES BRUTES'!AB$3:AB$42)/1000,0)),"—")} -> 1.64 | L12: — | M12: {=IFERROR(INDEX('DONNÉES BRUTES'!AD$3:AD$42,MATCH(_xlfn.AGGREGATE(14,6,'DONNÉES BRUTES'!AB$3:AB$42+ROW('DONNÉES BRUTES'!AB$3:AB$42)/1000,9),'DONNÉES BRUTES'!AB$3:AB$42+ROW('DONNÉES BRUTES'!AB$3:AB$42)/1000,0)),"—")} -> Neutre | O12: =IF(B14<>"—",LEFT(C14,20),"—") -> Legrand SA | P12: =IF(E14<>"—",VALUE(LEFT(E14,FIND("/",E14)-1)),"") -> 64
A13: 10 | B13: {=IFERROR(INDEX('DONNÉES BRUTES'!A$3:A$42,MATCH(_xlfn.AGGREGATE(14,6,'DONNÉES BRUTES'!AB$3:AB$42+ROW('DONNÉES BRUTES'!AB$3:AB$42)/1000,10),'DONNÉES BRUTES'!AB$3:AB$42+ROW('DONNÉES BRUTES'!AB$3:AB$42)/1000,0)),"—")} -> ACA.PA | C13: {=IFERROR(INDEX('DONNÉES BRUTES'!B$3:B$42,MATCH(_xlfn.AGGREGATE(14,6,'DONNÉES BRUTES'!AB$3:AB$42+ROW('DONNÉES BRUTES'!AB$3:AB$42)/1000,10),'DONNÉES BRUTES'!AB$3:AB$42+ROW('DONNÉES BRUTES'!AB$3:AB$42)/1000,0)),"—")} -> Crédit Agricole S.A. | D13: {=IFERROR(INDEX('DONNÉES BRUTES'!C$3:C$42,MATCH(_xlfn.AGGREGATE(14,6,'DONNÉES BRUTES'!AB$3:AB$42+ROW('DONNÉES BRUTES'!AB$3:AB$42)/1000,10),'DONNÉES BRUTES'!AB$3:AB$42+ROW('DONNÉES BRUTES'!AB$3:AB$42)/1000,0)),"—")} -> Financials | E13: {=IFERROR(INDEX('DONNÉES BRUTES'!AB$3:AB$42,MATCH(_xlfn.AGGREGATE(14,6,'DONNÉES BRUTES'!AB$3:AB$42+ROW('DONNÉES BRUTES'!AB$3:AB$42)/1000,10),'DONNÉES BRUTES'!AB$3:AB$42+ROW('DONNÉES BRUTES'!AB$3:AB$42)/1000,0))&"/100","—")} -> 65/100 | F13: {=IFERROR(INDEX('DONNÉES BRUTES'!I$3:I$42,MATCH(_xlfn.AGGREGATE(14,6,'DONNÉES BRUTES'!AB$3:AB$42+ROW('DONNÉES BRUTES'!AB$3:AB$42)/1000,10),'DONNÉES BRUTES'!AB$3:AB$42+ROW('DONNÉES BRUTES'!AB$3:AB$42)/1000,0)),"—")} -> — | G13: {=IFERROR(INDEX('DONNÉES BRUTES'!J$3:J$42,MATCH(_xlfn.AGGREGATE(14,6,'DONNÉES BRUTES'!AB$3:AB$42+ROW('DONNÉES BRUTES'!AB$3:AB$42)/1000,10),'DONNÉES BRUTES'!AB$3:AB$42+ROW('DONNÉES BRUTES'!AB$3:AB$42)/1000,0)),"—")} -> — | H13: {=IFERROR(INDEX('DONNÉES BRUTES'!K$3:K$42,MATCH(_xlfn.AGGREGATE(14,6,'DONNÉES BRUTES'!AB$3:AB$42+ROW('DONNÉES BRUTES'!AB$3:AB$42)/1000,10),'DONNÉES BRUTES'!AB$3:AB$42+ROW('DONNÉES BRUTES'!AB$3:AB$42)/1000,0)),"—")} -> — | I13: {=IFERROR(INDEX('DONNÉES BRUTES'!M$3:M$42,MATCH(_xlfn.AGGREGATE(14,6,'DONNÉES BRUTES'!AB$3:AB$42+ROW('DONNÉES BRUTES'!AB$3:AB$42)/1000,10),'DONNÉES BRUTES'!AB$3:AB$42+ROW('DONNÉES BRUTES'!AB$3:AB$42)/1000,0)),"—")} -> — | J13: {=IFERROR(INDEX('DONNÉES BRUTES'!N$3:N$42,MATCH(_xlfn.AGGREGATE(14,6,'DONNÉES BRUTES'!AB$3:AB$42+ROW('DONNÉES BRUTES'!AB$3:AB$42)/1000,10),'DONNÉES BRUTES'!AB$3:AB$42+ROW('DONNÉES BRUTES'!AB$3:AB$42)/1000,0)),"—")} -> 192.6% | K13: {=IFERROR(INDEX('DONNÉES BRUTES'!U$3:U$42,MATCH(_xlfn.AGGREGATE(14,6,'DONNÉES BRUTES'!AB$3:AB$42+ROW('DONNÉES BRUTES'!AB$3:AB$42)/1000,10),'DONNÉES BRUTES'!AB$3:AB$42+ROW('DONNÉES BRUTES'!AB$3:AB$42)/1000,0)),"—")} -> — | L13: — | M13: {=IFERROR(INDEX('DONNÉES BRUTES'!AD$3:AD$42,MATCH(_xlfn.AGGREGATE(14,6,'DONNÉES BRUTES'!AB$3:AB$42+ROW('DONNÉES BRUTES'!AB$3:AB$42)/1000,10),'DONNÉES BRUTES'!AB$3:AB$42+ROW('DONNÉES BRUTES'!AB$3:AB$42)/1000,0)),"—")} -> Neutre | O13: =IF(B15<>"—",LEFT(C15,20),"—") -> L'Oréal S.A. | P13: =IF(E15<>"—",VALUE(LEFT(E15,FIND("/",E15)-1)),"") -> 64
A14: 11 | B14: {=IFERROR(INDEX('DONNÉES BRUTES'!A$3:A$42,MATCH(_xlfn.AGGREGATE(14,6,'DONNÉES BRUTES'!AB$3:AB$42+ROW('DONNÉES BRUTES'!AB$3:AB$42)/1000,11),'DONNÉES BRUTES'!AB$3:AB$42+ROW('DONNÉES BRUTES'!AB$3:AB$42)/1000,0)),"—")} -> LR.PA | C14: {=IFERROR(INDEX('DONNÉES BRUTES'!B$3:B$42,MATCH(_xlfn.AGGREGATE(14,6,'DONNÉES BRUTES'!AB$3:AB$42+ROW('DONNÉES BRUTES'!AB$3:AB$42)/1000,11),'DONNÉES BRUTES'!AB$3:AB$42+ROW('DONNÉES BRUTES'!AB$3:AB$42)/1000,0)),"—")} -> Legrand SA | D14: {=IFERROR(INDEX('DONNÉES BRUTES'!C$3:C$42,MATCH(_xlfn.AGGREGATE(14,6,'DONNÉES BRUTES'!AB$3:AB$42+ROW('DONNÉES BRUTES'!AB$3:AB$42)/1000,11),'DONNÉES BRUTES'!AB$3:AB$42+ROW('DONNÉES BRUTES'!AB$3:AB$42)/1000,0)),"—")} -> Industrials | E14: {=IFERROR(INDEX('DONNÉES BRUTES'!AB$3:AB$42,MATCH(_xlfn.AGGREGATE(14,6,'DONNÉES BRUTES'!AB$3:AB$42+ROW('DONNÉES BRUTES'!AB$3:AB$42)/1000,11),'DONNÉES BRUTES'!AB$3:AB$42+ROW('DONNÉES BRUTES'!AB$3:AB$42)/1000,0))&"/100","—")} -> 64/100 | F14: {=IFERROR(INDEX('DONNÉES BRUTES'!I$3:I$42,MATCH(_xlfn.AGGREGATE(14,6,'DONNÉES BRUTES'!AB$3:AB$42+ROW('DONNÉES BRUTES'!AB$3:AB$42)/1000,11),'DONNÉES BRUTES'!AB$3:AB$42+ROW('DONNÉES BRUTES'!AB$3:AB$42)/1000,0)),"—")} -> — | G14: {=IFERROR(INDEX('DONNÉES BRUTES'!J$3:J$42,MATCH(_xlfn.AGGREGATE(14,6,'DONNÉES BRUTES'!AB$3:AB$42+ROW('DONNÉES BRUTES'!AB$3:AB$42)/1000,11),'DONNÉES BRUTES'!AB$3:AB$42+ROW('DONNÉES BRUTES'!AB$3:AB$42)/1000,0)),"—")} -> — | H14: {=IFERROR(INDEX('DONNÉES BRUTES'!K$3:K$42,MATCH(_xlfn.AGGREGATE(14,6,'DONNÉES BRUTES'!AB$3:AB$42+ROW('DONNÉES BRUTES'!AB$3:AB$42)/1000,11),'DONNÉES BRUTES'!AB$3:AB$42+ROW('DONNÉES BRUTES'!AB$3:AB$42)/1000,0)),"—")} -> — | I14: {=IFERROR(INDEX('DONNÉES BRUTES'!M$3:M$42,MATCH(_xlfn.AGGREGATE(14,6,'DONNÉES BRUTES'!AB$3:AB$42+ROW('DONNÉES BRUTES'!AB$3:AB$42)/1000,11),'DONNÉES BRUTES'!AB$3:AB$42+ROW('DONNÉES BRUTES'!AB$3:AB$42)/1000,0)),"—")} -> 50.8% | J14: {=IFERROR(INDEX('DONNÉES BRUTES'!N$3:N$42,MATCH(_xlfn.AGGREGATE(14,6,'DONNÉES BRUTES'!AB$3:AB$42+ROW('DONNÉES BRUTES'!AB$3:AB$42)/1000,11),'DONNÉES BRUTES'!AB$3:AB$42+ROW('DONNÉES BRUTES'!AB$3:AB$42)/1000,0)),"—")} -> 23.9% | K14: {=IFERROR(INDEX('DONNÉES BRUTES'!U$3:U$42,MATCH(_xlfn.AGGREGATE(14,6,'DONNÉES BRUTES'!AB$3:AB$42+ROW('DONNÉES BRUTES'!AB$3:AB$42)/1000,11),'DONNÉES BRUTES'!AB$3:AB$42+ROW('DONNÉES BRUTES'!AB$3:AB$42)/1000,0)),"—")} -> 3.78 | L14: — | M14: {=IFERROR(INDEX('DONNÉES BRUTES'!AD$3:AD$42,MATCH(_xlfn.AGGREGATE(14,6,'DONNÉES BRUTES'!AB$3:AB$42+ROW('DONNÉES BRUTES'!AB$3:AB$42)/1000,11),'DONNÉES BRUTES'!AB$3:AB$42+ROW('DONNÉES BRUTES'!AB$3:AB$42)/1000,0)),"—")} -> Neutre | O14: =IF(B16<>"—",LEFT(C16,20),"—") -> EssilorLuxottica Soc | P14: =IF(E16<>"—",VALUE(LEFT(E16,FIND("/",E16)-1)),"") -> 64
A15: 12 | B15: {=IFERROR(INDEX('DONNÉES BRUTES'!A$3:A$42,MATCH(_xlfn.AGGREGATE(14,6,'DONNÉES BRUTES'!AB$3:AB$42+ROW('DONNÉES BRUTES'!AB$3:AB$42)/1000,12),'DONNÉES BRUTES'!AB$3:AB$42+ROW('DONNÉES BRUTES'!AB$3:AB$42)/1000,0)),"—")} -> OR.PA | C15: {=IFERROR(INDEX('DONNÉES BRUTES'!B$3:B$42,MATCH(_xlfn.AGGREGATE(14,6,'DONNÉES BRUTES'!AB$3:AB$42+ROW('DONNÉES BRUTES'!AB$3:AB$42)/1000,12),'DONNÉES BRUTES'!AB$3:AB$42+ROW('DONNÉES BRUTES'!AB$3:AB$42)/1000,0)),"—")} -> L'Oréal S.A. | D15: {=IFERROR(INDEX('DONNÉES BRUTES'!C$3:C$42,MATCH(_xlfn.AGGREGATE(14,6,'DONNÉES BRUTES'!AB$3:AB$42+ROW('DONNÉES BRUTES'!AB$3:AB$42)/1000,12),'DONNÉES BRUTES'!AB$3:AB$42+ROW('DONNÉES BRUTES'!AB$3:AB$42)/1000,0)),"—")} -> Consumer Staples | E15: {=IFERROR(INDEX('DONNÉES BRUTES'!AB$3:AB$42,MATCH(_xlfn.AGGREGATE(14,6,'DONNÉES BRUTES'!AB$3:AB$42+ROW('DONNÉES BRUTES'!AB$3:AB$42)/1000,12),'DONNÉES BRUTES'!AB$3:AB$42+ROW('DONNÉES BRUTES'!AB$3:AB$42)/1000,0))&"/100","—")} -> 64/100 | F15: {=IFERROR(INDEX('DONNÉES BRUTES'!I$3:I$42,MATCH(_xlfn.AGGREGATE(14,6,'DONNÉES BRUTES'!AB$3:AB$42+ROW('DONNÉES BRUTES'!AB$3:AB$42)/1000,12),'DONNÉES BRUTES'!AB$3:AB$42+ROW('DONNÉES BRUTES'!AB$3:AB$42)/1000,0)),"—")} -> — | G15: {=IFERROR(INDEX('DONNÉES BRUTES'!J$3:J$42,MATCH(_xlfn.AGGREGATE(14,6,'DONNÉES BRUTES'!AB$3:AB$42+ROW('DONNÉES BRUTES'!AB$3:AB$42)/1000,12),'DONNÉES BRUTES'!AB$3:AB$42+ROW('DONNÉES BRUTES'!AB$3:AB$42)/1000,0)),"—")} -> — | H15: {=IFERROR(INDEX('DONNÉES BRUTES'!K$3:K$42,MATCH(_xlfn.AGGREGATE(14,6,'DONNÉES BRUTES'!AB$3:AB$42+ROW('DONNÉES BRUTES'!AB$3:AB$42)/1000,12),'DONNÉES BRUTES'!AB$3:AB$42+ROW('DONNÉES BRUTES'!AB$3:AB$42)/1000,0)),"—")} -> — | I15: {=IFERROR(INDEX('DONNÉES BRUTES'!M$3:M$42,MATCH(_xlfn.AGGREGATE(14,6,'DONNÉES BRUTES'!AB$3:AB$42+ROW('DONNÉES BRUTES'!AB$3:AB$42)/1000,12),'DONNÉES BRUTES'!AB$3:AB$42+ROW('DONNÉES BRUTES'!AB$3:AB$42)/1000,0)),"—")} -> 74.3% | J15: {=IFERROR(INDEX('DONNÉES BRUTES'!N$3:N$42,MATCH(_xlfn.AGGREGATE(14,6,'DONNÉES BRUTES'!AB$3:AB$42+ROW('DONNÉES BRUTES'!AB$3:AB$42)/1000,12),'DONNÉES BRUTES'!AB$3:AB$42+ROW('DONNÉES BRUTES'!AB$3:AB$42)/1000,0)),"—")} -> 24.3% | K15: {=IFERROR(INDEX('DONNÉES BRUTES'!U$3:U$42,MATCH(_xlfn.AGGREGATE(14,6,'DONNÉES BRUTES'!AB$3:AB$42+ROW('DONNÉES BRUTES'!AB$3:AB$42)/1000,12),'DONNÉES BRUTES'!AB$3:AB$42+ROW('DONNÉES BRUTES'!AB$3:AB$42)/1000,0)),"—")} -> 3.38 | L15: — | M15: {=IFERROR(INDEX('DONNÉES BRUTES'!AD$3:AD$42,MATCH(_xlfn.AGGREGATE(14,6,'DONNÉES BRUTES'!AB$3:AB$42+ROW('DONNÉES BRUTES'!AB$3:AB$42)/1000,12),'DONNÉES BRUTES'!AB$3:AB$42+ROW('DONNÉES BRUTES'!AB$3:AB$42)/1000,0)),"—")} -> Neutre | O15: =IF(B17<>"—",LEFT(C17,20),"—") -> AXA SA | P15: =IF(E17<>"—",VALUE(LEFT(E17,FIND("/",E17)-1)),"") -> 64
A16: 13 | B16: {=IFERROR(INDEX('DONNÉES BRUTES'!A$3:A$42,MATCH(_xlfn.AGGREGATE(14,6,'DONNÉES BRUTES'!AB$3:AB$42+ROW('DONNÉES BRUTES'!AB$3:AB$42)/1000,13),'DONNÉES BRUTES'!AB$3:AB$42+ROW('DONNÉES BRUTES'!AB$3:AB$42)/1000,0)),"—")} -> EL.PA | C16: {=IFERROR(INDEX('DONNÉES BRUTES'!B$3:B$42,MATCH(_xlfn.AGGREGATE(14,6,'DONNÉES BRUTES'!AB$3:AB$42+ROW('DONNÉES BRUTES'!AB$3:AB$42)/1000,13),'DONNÉES BRUTES'!AB$3:AB$42+ROW('DONNÉES BRUTES'!AB$3:AB$42)/1000,0)),"—")} -> EssilorLuxottica Société anonyme | D16: {=IFERROR(INDEX('DONNÉES BRUTES'!C$3:C$42,MATCH(_xlfn.AGGREGATE(14,6,'DONNÉES BRUTES'!AB$3:AB$42+ROW('DONNÉES BRUTES'!AB$3:AB$42)/1000,13),'DONNÉES BRUTES'!AB$3:AB$42+ROW('DONNÉES BRUTES'!AB$3:AB$42)/1000,0)),"—")} -> Healthcare | E16: {=IFERROR(INDEX('DONNÉES BRUTES'!AB$3:AB$42,MATCH(_xlfn.AGGREGATE(14,6,'DONNÉES BRUTES'!AB$3:AB$42+ROW('DONNÉES BRUTES'!AB$3:AB$42)/1000,13),'DONNÉES BRUTES'!AB$3:AB$42+ROW('DONNÉES BRUTES'!AB$3:AB$42)/1000,0))&"/100","—")} -> 64/100 | F16: {=IFERROR(INDEX('DONNÉES BRUTES'!I$3:I$42,MATCH(_xlfn.AGGREGATE(14,6,'DONNÉES BRUTES'!AB$3:AB$42+ROW('DONNÉES BRUTES'!AB$3:AB$42)/1000,13),'DONNÉES BRUTES'!AB$3:AB$42+ROW('DONNÉES BRUTES'!AB$3:AB$42)/1000,0)),"—")} -> — | G16: {=IFERROR(INDEX('DONNÉES BRUTES'!J$3:J$42,MATCH(_xlfn.AGGREGATE(14,6,'DONNÉES BRUTES'!AB$3:AB$42+ROW('DONNÉES BRUTES'!AB$3:AB$42)/1000,13),'DONNÉES BRUTES'!AB$3:AB$42+ROW('DONNÉES BRUTES'!AB$3:AB$42)/1000,0)),"—")} -> — | H16: {=IFERROR(INDEX('DONNÉES BRUTES'!K$3:K$42,MATCH(_xlfn.AGGREGATE(14,6,'DONNÉES BRUTES'!AB$3:AB$42+ROW('DONNÉES BRUTES'!AB$3:AB$42)/1000,13),'DONNÉES BRUTES'!AB$3:AB$42+ROW('DONNÉES BRUTES'!AB$3:AB$42)/1000,0)),"—")} -> — | I16: {=IFERROR(INDEX('DONNÉES BRUTES'!M$3:M$42,MATCH(_xlfn.AGGREGATE(14,6,'DONNÉES BRUTES'!AB$3:AB$42+ROW('DONNÉES BRUTES'!AB$3:AB$42)/1000,13),'DONNÉES BRUTES'!AB$3:AB$42+ROW('DONNÉES BRUTES'!AB$3:AB$42)/1000,0)),"—")} -> 60.6% | J16: {=IFERROR(INDEX('DONNÉES BRUTES'!N$3:N$42,MATCH(_xlfn.AGGREGATE(14,6,'DONNÉES BRUTES'!AB$3:AB$42+ROW('DONNÉES BRUTES'!AB$3:AB$42)/1000,13),'DONNÉES BRUTES'!AB$3:AB$42+ROW('DONNÉES BRUTES'!AB$3:AB$42)/1000,0)),"—")} -> 23.2% | K16: {=IFERROR(INDEX('DONNÉES BRUTES'!U$3:U$42,MATCH(_xlfn.AGGREGATE(14,6,'DONNÉES BRUTES'!AB$3:AB$42+ROW('DONNÉES BRUTES'!AB$3:AB$42)/1000,13),'DONNÉES BRUTES'!AB$3:AB$42+ROW('DONNÉES BRUTES'!AB$3:AB$42)/1000,0)),"—")} -> 2.27 | L16: — | M16: {=IFERROR(INDEX('DONNÉES BRUTES'!AD$3:AD$42,MATCH(_xlfn.AGGREGATE(14,6,'DONNÉES BRUTES'!AB$3:AB$42+ROW('DONNÉES BRUTES'!AB$3:AB$42)/1000,13),'DONNÉES BRUTES'!AB$3:AB$42+ROW('DONNÉES BRUTES'!AB$3:AB$42)/1000,0)),"—")} -> Neutre | O16: =IF(B18<>"—",LEFT(C18,20),"—") -> BNP Paribas SA | P16: =IF(E18<>"—",VALUE(LEFT(E18,FIND("/",E18)-1)),"") -> 62
A17: 14 | B17: {=IFERROR(INDEX('DONNÉES BRUTES'!A$3:A$42,MATCH(_xlfn.AGGREGATE(14,6,'DONNÉES BRUTES'!AB$3:AB$42+ROW('DONNÉES BRUTES'!AB$3:AB$42)/1000,14),'DONNÉES BRUTES'!AB$3:AB$42+ROW('DONNÉES BRUTES'!AB$3:AB$42)/1000,0)),"—")} -> CS.PA | C17: {=IFERROR(INDEX('DONNÉES BRUTES'!B$3:B$42,MATCH(_xlfn.AGGREGATE(14,6,'DONNÉES BRUTES'!AB$3:AB$42+ROW('DONNÉES BRUTES'!AB$3:AB$42)/1000,14),'DONNÉES BRUTES'!AB$3:AB$42+ROW('DONNÉES BRUTES'!AB$3:AB$42)/1000,0)),"—")} -> AXA SA | D17: {=IFERROR(INDEX('DONNÉES BRUTES'!C$3:C$42,MATCH(_xlfn.AGGREGATE(14,6,'DONNÉES BRUTES'!AB$3:AB$42+ROW('DONNÉES BRUTES'!AB$3:AB$42)/1000,14),'DONNÉES BRUTES'!AB$3:AB$42+ROW('DONNÉES BRUTES'!AB$3:AB$42)/1000,0)),"—")} -> Financials | E17: {=IFERROR(INDEX('DONNÉES BRUTES'!AB$3:AB$42,MATCH(_xlfn.AGGREGATE(14,6,'DONNÉES BRUTES'!AB$3:AB$42+ROW('DONNÉES BRUTES'!AB$3:AB$42)/1000,14),'DONNÉES BRUTES'!AB$3:AB$42+ROW('DONNÉES BRUTES'!AB$3:AB$42)/1000,0))&"/100","—")} -> 64/100 | F17: {=IFERROR(INDEX('DONNÉES BRUTES'!I$3:I$42,MATCH(_xlfn.AGGREGATE(14,6,'DONNÉES BRUTES'!AB$3:AB$42+ROW('DONNÉES BRUTES'!AB$3:AB$42)/1000,14),'DONNÉES BRUTES'!AB$3:AB$42+ROW('DONNÉES BRUTES'!AB$3:AB$42)/1000,0)),"—")} -> — | G17: {=IFERROR(INDEX('DONNÉES BRUTES'!J$3:J$42,MATCH(_xlfn.AGGREGATE(14,6,'DONNÉES BRUTES'!AB$3:AB$42+ROW('DONNÉES BRUTES'!AB$3:AB$42)/1000,14),'DONNÉES BRUTES'!AB$3:AB$42+ROW('DONNÉES BRUTES'!AB$3:AB$42)/1000,0)),"—")} -> — | H17: {=IFERROR(INDEX('DONNÉES BRUTES'!K$3:K$42,MATCH(_xlfn.AGGREGATE(14,6,'DONNÉES BRUTES'!AB$3:AB$42+ROW('DONNÉES BRUTES'!AB$3:AB$42)/1000,14),'DONNÉES BRUTES'!AB$3:AB$42+ROW('DONNÉES BRUTES'!AB$3:AB$42)/1000,0)),"—")} -> — | I17: {=IFERROR(INDEX('DONNÉES BRUTES'!M$3:M$42,MATCH(_xlfn.AGGREGATE(14,6,'DONNÉES BRUTES'!AB$3:AB$42+ROW('DONNÉES BRUTES'!AB$3:AB$42)/1000,14),'DONNÉES BRUTES'!AB$3:AB$42+ROW('DONNÉES BRUTES'!AB$3:AB$42)/1000,0)),"—")} -> — | J17: {=IFERROR(INDEX('DONNÉES BRUTES'!N$3:N$42,MATCH(_xlfn.AGGREGATE(14,6,'DONNÉES BRUTES'!AB$3:AB$42+ROW('DONNÉES BRUTES'!AB$3:AB$42)/1000,14),'DONNÉES BRUTES'!AB$3:AB$42+ROW('DONNÉES BRUTES'!AB$3:AB$42)/1000,0)),"—")} -> — | K17: {=IFERROR(INDEX('DONNÉES BRUTES'!U$3:U$42,MATCH(_xlfn.AGGREGATE(14,6,'DONNÉES BRUTES'!AB$3:AB$42+ROW('DONNÉES BRUTES'!AB$3:AB$42)/1000,14),'DONNÉES BRUTES'!AB$3:AB$42+ROW('DONNÉES BRUTES'!AB$3:AB$42)/1000,0)),"—")} -> — | L17: — | M17: {=IFERROR(INDEX('DONNÉES BRUTES'!AD$3:AD$42,MATCH(_xlfn.AGGREGATE(14,6,'DONNÉES BRUTES'!AB$3:AB$42+ROW('DONNÉES BRUTES'!AB$3:AB$42)/1000,14),'DONNÉES BRUTES'!AB$3:AB$42+ROW('DONNÉES BRUTES'!AB$3:AB$42)/1000,0)),"—")} -> Neutre
A18: 15 | B18: {=IFERROR(INDEX('DONNÉES BRUTES'!A$3:A$42,MATCH(_xlfn.AGGREGATE(14,6,'DONNÉES BRUTES'!AB$3:AB$42+ROW('DONNÉES BRUTES'!AB$3:AB$42)/1000,15),'DONNÉES BRUTES'!AB$3:AB$42+ROW('DONNÉES BRUTES'!AB$3:AB$42)/1000,0)),"—")} -> BNP.PA | C18: {=IFERROR(INDEX('DONNÉES BRUTES'!B$3:B$42,MATCH(_xlfn.AGGREGATE(14,6,'DONNÉES BRUTES'!AB$3:AB$42+ROW('DONNÉES BRUTES'!AB$3:AB$42)/1000,15),'DONNÉES BRUTES'!AB$3:AB$42+ROW('DONNÉES BRUTES'!AB$3:AB$42)/1000,0)),"—")} -> BNP Paribas SA | D18: {=IFERROR(INDEX('DONNÉES BRUTES'!C$3:C$42,MATCH(_xlfn.AGGREGATE(14,6,'DONNÉES BRUTES'!AB$3:AB$42+ROW('DONNÉES BRUTES'!AB$3:AB$42)/1000,15),'DONNÉES BRUTES'!AB$3:AB$42+ROW('DONNÉES BRUTES'!AB$3:AB$42)/1000,0)),"—")} -> Financials | E18: {=IFERROR(INDEX('DONNÉES BRUTES'!AB$3:AB$42,MATCH(_xlfn.AGGREGATE(14,6,'DONNÉES BRUTES'!AB$3:AB$42+ROW('DONNÉES BRUTES'!AB$3:AB$42)/1000,15),'DONNÉES BRUTES'!AB$3:AB$42+ROW('DONNÉES BRUTES'!AB$3:AB$42)/1000,0))&"/100","—")} -> 62/100 | F18: {=IFERROR(INDEX('DONNÉES BRUTES'!I$3:I$42,MATCH(_xlfn.AGGREGATE(14,6,'DONNÉES BRUTES'!AB$3:AB$42+ROW('DONNÉES BRUTES'!AB$3:AB$42)/1000,15),'DONNÉES BRUTES'!AB$3:AB$42+ROW('DONNÉES BRUTES'!AB$3:AB$42)/1000,0)),"—")} -> — | G18: {=IFERROR(INDEX('DONNÉES BRUTES'!J$3:J$42,MATCH(_xlfn.AGGREGATE(14,6,'DONNÉES BRUTES'!AB$3:AB$42+ROW('DONNÉES BRUTES'!AB$3:AB$42)/1000,15),'DONNÉES BRUTES'!AB$3:AB$42+ROW('DONNÉES BRUTES'!AB$3:AB$42)/1000,0)),"—")} -> — | H18: {=IFERROR(INDEX('DONNÉES BRUTES'!K$3:K$42,MATCH(_xlfn.AGGREGATE(14,6,'DONNÉES BRUTES'!AB$3:AB$42+ROW('DONNÉES BRUTES'!AB$3:AB$42)/1000,15),'DONNÉES BRUTES'!AB$3:AB$42+ROW('DONNÉES BRUTES'!AB$3:AB$42)/1000,0)),"—")} -> — | I18: {=IFERROR(INDEX('DONNÉES BRUTES'!M$3:M$42,MATCH(_xlfn.AGGREGATE(14,6,'DONNÉES BRUTES'!AB$3:AB$42+ROW('DONNÉES BRUTES'!AB$3:AB$42)/1000,15),'DONNÉES BRUTES'!AB$3:AB$42+ROW('DONNÉES BRUTES'!AB$3:AB$42)/1000,0)),"—")} -> — | J18: {=IFERROR(INDEX('DONNÉES BRUTES'!N$3:N$42,MATCH(_xlfn.AGGREGATE(14,6,'DONNÉES BRUTES'!AB$3:AB$42+ROW('DONNÉES BRUTES'!AB$3:AB$42)/1000,15),'DONNÉES BRUTES'!AB$3:AB$42+ROW('DONNÉES BRUTES'!AB$3:AB$42)/1000,0)),"—")} -> 108.7% | K18: {=IFERROR(INDEX('DONNÉES BRUTES'!U$3:U$42,MATCH(_xlfn.AGGREGATE(14,6,'DONNÉES BRUTES'!AB$3:AB$42+ROW('DONNÉES BRUTES'!AB$3:AB$42)/1000,15),'DONNÉES BRUTES'!AB$3:AB$42+ROW('DONNÉES BRUTES'!AB$3:AB$42)/1000,0)),"—")} -> — | L18: — | M18: {=IFERROR(INDEX('DONNÉES BRUTES'!AD$3:AD$42,MATCH(_xlfn.AGGREGATE(14,6,'DONNÉES BRUTES'!AB$3:AB$42+ROW('DONNÉES BRUTES'!AB$3:AB$42)/1000,15),'DONNÉES BRUTES'!AB$3:AB$42+ROW('DONNÉES BRUTES'!AB$3:AB$42)/1000,0)),"—")} -> Neutre

Sheet GROWTH
A1: FinSight IA · Analyse GROWTH · CAC 40 · 22/03/2026 | O1: Société | P1: Score Gr
A2: Usage confidentiel · Calculs Python/NumPy depuis cache Supabase | O2: =IF(B4<>"—",LEFT(C4,18),"—") -> Safran SA | P2: =IF(E4<>"—",VALUE(LEFT(E4,FIND("/",E4)-1)),"") -> 100
A3: Rang | B3: Ticker | C3: Société | D3: Secteur | E3: Score | F3: Croissance Rev. YoY | G3: Marge EBITDA | H3: Marge Nette | I3: ROE | J3: Croissance EPS | K3: Révisions Analystes | L3: Signal | O3: =IF(B5<>"—",LEFT(C5,18),"—") -> Vivendi SE | P3: =IF(E5<>"—",VALUE(LEFT(E5,FIND("/",E5)-1)),"") -> 97
A4: 1 | B4: {=IFERROR(INDEX('DONNÉES BRUTES'!A$3:A$42,MATCH(_xlfn.AGGREGATE(14,6,'DONNÉES BRUTES'!Y$3:Y$42+ROW('DONNÉES BRUTES'!Y$3:Y$42)/1000,1),'DONNÉES BRUTES'!Y$3:Y$42+ROW('DONNÉES BRUTES'!Y$3:Y$42)/1000,0)),"—")} -> SAF.PA | C4: {=IFERROR(INDEX('DONNÉES BRUTES'!B$3:B$42,MATCH(_xlfn.AGGREGATE(14,6,'DONNÉES BRUTES'!Y$3:Y$42+ROW('DONNÉES BRUTES'!Y$3:Y$42)/1000,1),'DONNÉES BRUTES'!Y$3:Y$42+ROW('DONNÉES BRUTES'!Y$3:Y$42)/1000,0)),"—")} -> Safran SA | D4: {=IFERROR(INDEX('DONNÉES BRUTES'!C$3:C$42,MATCH(_xlfn.AGGREGATE(14,6,'DONNÉES BRUTES'!Y$3:Y$42+ROW('DONNÉES BRUTES'!Y$3:Y$42)/1000,1),'DONNÉES BRUTES'!Y$3:Y$42+ROW('DONNÉES BRUTES'!Y$3:Y$42)/1000,0)),"—")} -> Industrials | E4: {=IFERROR(INDEX('DONNÉES BRUTES'!Y$3:Y$42,MATCH(_xlfn.AGGREGATE(14,6,'DONNÉES BRUTES'!Y$3:Y$42+ROW('DONNÉES BRUTES'!Y$3:Y$42)/1000,1),'DONNÉES BRUTES'!Y$3:Y$42+ROW('DONNÉES BRUTES'!Y$3:Y$42)/1000,0))&"/100","—")} -> 100/100 | F4: {=IFERROR(INDEX('DONNÉES BRUTES'!P$3:P$42,MATCH(_xlfn.AGGREGATE(14,6,'DONNÉES BRUTES'!Y$3:Y$42+ROW('DONNÉES BRUTES'!Y$3:Y$42)/1000,1),'DONNÉES BRUTES'!Y$3:Y$42+ROW('DONNÉES BRUTES'!Y$3:Y$42)/1000,0)),"—")} -> +12.5% | G4: {=IFERROR(INDEX('DONNÉES BRUTES'!N$3:N$42,MATCH(_xlfn.AGGREGATE(14,6,'DONNÉES BRUTES'!Y$3:Y$42+ROW('DONNÉES BRUTES'!Y$3:Y$42)/1000,1),'DONNÉES BRUTES'!Y$3:Y$42+ROW('DONNÉES BRUTES'!Y$3:Y$42)/1000,0)),"—")} -> 39.2% | H4: {=IFERROR(INDEX('DONNÉES BRUTES'!O$3:O$42,MATCH(_xlfn.AGGREGATE(14,6,'DONNÉES BRUTES'!Y$3:Y$42+ROW('DONNÉES BRUTES'!Y$3:Y$42)/1000,1),'DONNÉES BRUTES'!Y$3:Y$42+ROW('DONNÉES BRUTES'!Y$3:Y$42)/1000,0)),"—")} -> 23.0% | I4: {=IFERROR(INDEX('DONNÉES BRUTES'!Q$3:Q$42,MATCH(_xlfn.AGGREGATE(14,6,'DONNÉES BRUTES'!Y$3:Y$42+ROW('DONNÉES BRUTES'!Y$3:Y$42)/1000,1),'DONNÉES BRUTES'!Y$3:Y$42+ROW('DONNÉES BRUTES'!Y$3:Y$42)/1000,0)),"—")} -> +48.4% | J4: — | K4: — | L4: {=IFERROR(INDEX('DONNÉES BRUTES'!AD$3:AD$42,MATCH(_xlfn.AGGREGATE(14,6,'DONNÉES BRUTES'!Y$3:Y$42+ROW('DONNÉES BRUTES'!Y$3:Y$42)/1000,1),'DONNÉES BRUTES'!Y$3:Y$42+ROW('DONNÉES BRUTES'!Y$3:Y$42)/1000,0)),"—")} -> Neutre | O4: =IF(B6<>"—",LEFT(C6,18),"—") -> Alstom SA | P4: =IF(E6<>"—",VALUE(LEFT(E6,FIND("/",E6)-1)),"") -> 95
A5: 2 | B5: {=IFERROR(INDEX('DONNÉES BRUTES'!A$3:A$42,MATCH(_xlfn.AGGREGATE(14,6,'DONNÉES BRUTES'!Y$3:Y$42+ROW('DONNÉES BRUTES'!Y$3:Y$42)/1000,2),'DONNÉES BRUTES'!Y$3:Y$42+ROW('DONNÉES BRUTES'!Y$3:Y$42)/1000,0)),"—")} -> VIV.PA | C5: {=IFERROR(INDEX('DONNÉES BRUTES'!B$3:B$42,MATCH(_xlfn.AGGREGATE(14,6,'DONNÉES BRUTES'!Y$3:Y$42+ROW('DONNÉES BRUTES'!Y$3:Y$42)/1000,2),'DONNÉES BRUTES'!Y$3:Y$42+ROW('DONNÉES BRUTES'!Y$3:Y$42)/1000,0)),"—")} -> Vivendi SE | D5: {=IFERROR(INDEX('DONNÉES BRUTES'!C$3:C$42,MATCH(_xlfn.AGGREGATE(14,6,'DONNÉES BRUTES'!Y$3:Y$42+ROW('DONNÉES BRUTES'!Y$3:Y$42)/1000,2),'DONNÉES BRUTES'!Y$3:Y$42+ROW('DONNÉES BRUTES'!Y$3:Y$42)/1000,0)),"—")} -> Comm. Services | E5: {=IFERROR(INDEX('DONNÉES BRUTES'!Y$3:Y$42,MATCH(_xlfn.AGGREGATE(14,6,'DONNÉES BRUTES'!Y$3:Y$42+ROW('DONNÉES BRUTES'!Y$3:Y$42)/1000,2),'DONNÉES BRUTES'!Y$3:Y$42+ROW('DONNÉES BRUTES'!Y$3:Y$42)/1000,0))&"/100","—")} -> 97/100 | F5: {=IFERROR(INDEX('DONNÉES BRUTES'!P$3:P$42,MATCH(_xlfn.AGGREGATE(14,6,'DONNÉES BRUTES'!Y$3:Y$42+ROW('DONNÉES BRUTES'!Y$3:Y$42)/1000,2),'DONNÉES BRUTES'!Y$3:Y$42+ROW('DONNÉES BRUTES'!Y$3:Y$42)/1000,0)),"—")} -> +3.4% | G5: {=IFERROR(INDEX('DONNÉES BRUTES'!N$3:N$42,MATCH(_xlfn.AGGREGATE(14,6,'DONNÉES BRUTES'!Y$3:Y$42+ROW('DONNÉES BRUTES'!Y$3:Y$42)/1000,2),'DONNÉES BRUTES'!Y$3:Y$42+ROW('DONNÉES BRUTES'!Y$3:Y$42)/1000,0)),"—")} -> 54.4% | H5: {=IFERROR(INDEX('DONNÉES BRUTES'!O$3:O$42,MATCH(_xlfn.AGGREGATE(14,6,'DONNÉES BRUTES'!Y$3:Y$42+ROW('DONNÉES BRUTES'!Y$3:Y$42)/1000,2),'DONNÉES BRUTES'!Y$3:Y$42+ROW('DONNÉES BRUTES'!Y$3:Y$42)/1000,0)),"—")} -> 6.5% | I5: {=IFERROR(INDEX('DONNÉES BRUTES'!Q$3:Q$42,MATCH(_xlfn.AGGREGATE(14,6,'DONNÉES BRUTES'!Y$3:Y$42+ROW('DONNÉES BRUTES'!Y$3:Y$42)/1000,2),'DONNÉES BRUTES'!Y$3:Y$42+ROW('DONNÉES BRUTES'!Y$3:Y$42)/1000,0)),"—")} -> +0.4% | J5: — | K5: — | L5: {=IFERROR(INDEX('DONNÉES BRUTES'!AD$3:AD$42,MATCH(_xlfn.AGGREGATE(14,6,'DONNÉES BRUTES'!Y$3:Y$42+ROW('DONNÉES BRUTES'!Y$3:Y$42)/1000,2),'DONNÉES BRUTES'!Y$3:Y$42+ROW('DONNÉES BRUTES'!Y$3:Y$42)/1000,0)),"—")} -> Sous-pondérer | O5: =IF(B7<>"—",LEFT(C7,18),"—") -> Unibail-Rodamco-We | P5: =IF(E7<>"—",VALUE(LEFT(E7,FIND("/",E7)-1)),"") -> 92
A6: 3 | B6: {=IFERROR(INDEX('DONNÉES BRUTES'!A$3:A$42,MATCH(_xlfn.AGGREGATE(14,6,'DONNÉES BRUTES'!Y$3:Y$42+ROW('DONNÉES BRUTES'!Y$3:Y$42)/1000,3),'DONNÉES BRUTES'!Y$3:Y$42+ROW('DONNÉES BRUTES'!Y$3:Y$42)/1000,0)),"—")} -> ALO.PA | C6: {=IFERROR(INDEX('DONNÉES BRUTES'!B$3:B$42,MATCH(_xlfn.AGGREGATE(14,6,'DONNÉES BRUTES'!Y$3:Y$42+ROW('DONNÉES BRUTES'!Y$3:Y$42)/1000,3),'DONNÉES BRUTES'!Y$3:Y$42+ROW('DONNÉES BRUTES'!Y$3:Y$42)/1000,0)),"—")} -> Alstom SA | D6: {=IFERROR(INDEX('DONNÉES BRUTES'!C$3:C$42,MATCH(_xlfn.AGGREGATE(14,6,'DONNÉES BRUTES'!Y$3:Y$42+ROW('DONNÉES BRUTES'!Y$3:Y$42)/1000,3),'DONNÉES BRUTES'!Y$3:Y$42+ROW('DONNÉES BRUTES'!Y$3:Y$42)/1000,0)),"—")} -> Industrials | E6: {=IFERROR(INDEX('DONNÉES BRUTES'!Y$3:Y$42,MATCH(_xlfn.AGGREGATE(14,6,'DONNÉES BRUTES'!Y$3:Y$42+ROW('DONNÉES BRUTES'!Y$3:Y$42)/1000,3),'DONNÉES BRUTES'!Y$3:Y$42+ROW('DONNÉES BRUTES'!Y$3:Y$42)/1000,0))&"/100","—")} -> 95/100 | F6: {=IFERROR(INDEX('DONNÉES BRUTES'!P$3:P$42,MATCH(_xlfn.AGGREGATE(14,6,'DONNÉES BRUTES'!Y$3:Y$42+ROW('DONNÉES BRUTES'!Y$3:Y$42)/1000,3),'DONNÉES BRUTES'!Y$3:Y$42+ROW('DONNÉES BRUTES'!Y$3:Y$42)/1000,0)),"—")} -> +4.9% | G6: {=IFERROR(INDEX('DONNÉES BRUTES'!N$3:N$42,MATCH(_xlfn.AGGREGATE(14,6,'DONNÉES BRUTES'!Y$3:Y$42+ROW('DONNÉES BRUTES'!Y$3:Y$42)/1000,3),'DONNÉES BRUTES'!Y$3:Y$42+ROW('DONNÉES BRUTES'!Y$3:Y$42)/1000,0)),"—")} -> 6.8% | H6: {=IFERROR(INDEX('DONNÉES BRUTES'!O$3:O$42,MATCH(_xlfn.AGGREGATE(14,6,'DONNÉES BRUTES'!Y$3:Y$42+ROW('DONNÉES BRUTES'!Y$3:Y$42)/1000,3),'DONNÉES BRUTES'!Y$3:Y$42+ROW('DONNÉES BRUTES'!Y$3:Y$42)/1000,0)),"—")} -> 0.8% | I6: {=IFERROR(INDEX('DONNÉES BRUTES'!Q$3:Q$42,MATCH(_xlfn.AGGREGATE(14,6,'DONNÉES BRUTES'!Y$3:Y$42+ROW('DONNÉES BRUTES'!Y$3:Y$42)/1000,3),'DONNÉES BRUTES'!Y$3:Y$42+ROW('DONNÉES BRUTES'!Y$3:Y$42)/1000,0)),"—")} -> +1.4% | J6: — | K6: — | L6: {=IFERROR(INDEX('DONNÉES BRUTES'!AD$3:AD$42,MATCH(_xlfn.AGGREGATE(14,6,'DONNÉES BRUTES'!Y$3:Y$42+ROW('DONNÉES BRUTES'!Y$3:Y$42)/1000,3),'DONNÉES BRUTES'!Y$3:Y$42+ROW('DONNÉES BRUTES'!Y$3:Y$42)/1000,0)),"—")} -> Neutre | O6: =IF(B8<>"—",LEFT(C8,18),"—") -> Thales S.A. | P6: =IF(E8<>"—",VALUE(LEFT(E8,FIND("/",E8)-1)),"") -> 89
A7: 4 | B7: {=IFERROR(INDEX('DONNÉES BRUTES'!A$3:A$42,MATCH(_xlfn.AGGREGATE(14,6,'DONNÉES BRUTES'!Y$3:Y$42+ROW('DONNÉES BRUTES'!Y$3:Y$42)/1000,4),'DONNÉES BRUTES'!Y$3:Y$42+ROW('DONNÉES BRUTES'!Y$3:Y$42)/1000,0)),"—")} -> URW.PA | C7: {=IFERROR(INDEX('DONNÉES BRUTES'!B$3:B$42,MATCH(_xlfn.AGGREGATE(14,6,'DONNÉES BRUTES'!Y$3:Y$42+ROW('DONNÉES BRUTES'!Y$3:Y$42)/1000,4),'DONNÉES BRUTES'!Y$3:Y$42+ROW('DONNÉES BRUTES'!Y$3:Y$42)/1000,0)),"—")} -> Unibail-Rodamco-Westfield SE | D7: {=IFERROR(INDEX('DONNÉES BRUTES'!C$3:C$42,MATCH(_xlfn.AGGREGATE(14,6,'DONNÉES BRUTES'!Y$3:Y$42+ROW('DONNÉES BRUTES'!Y$3:Y$42)/1000,4),'DONNÉES BRUTES'!Y$3:Y$42+ROW('DONNÉES BRUTES'!Y$3:Y$42)/1000,0)),"—")} -> Real Estate | E7: {=IFERROR(INDEX('DONNÉES BRUTES'!Y$3:Y$42,MATCH(_xlfn.AGGREGATE(14,6,'DONNÉES BRUTES'!Y$3:Y$42+ROW('DONNÉES BRUTES'!Y$3:Y$42)/1000,4),'DONNÉES BRUTES'!Y$3:Y$42+ROW('DONNÉES BRUTES'!Y$3:Y$42)/1000,0))&"/100","—")} -> 92/100 | F7: {=IFERROR(INDEX('DONNÉES BRUTES'!P$3:P$42,MATCH(_xlfn.AGGREGATE(14,6,'DONNÉES BRUTES'!Y$3:Y$42+ROW('DONNÉES BRUTES'!Y$3:Y$42)/1000,4),'DONNÉES BRUTES'!Y$3:Y$42+ROW('DONNÉES BRUTES'!Y$3:Y$42)/1000,0)),"—")} -> -6.1% | G7: {=IFERROR(INDEX('DONNÉES BRUTES'!N$3:N$42,MATCH(_xlfn.AGGREGATE(14,6,'DONNÉES BRUTES'!Y$3:Y$42+ROW('DONNÉES BRUTES'!Y$3:Y$42)/1000,4),'DONNÉES BRUTES'!Y$3:Y$42+ROW('DONNÉES BRUTES'!Y$3:Y$42)/1000,0)),"—")} -> 89.1% | H7: {=IFERROR(INDEX('DONNÉES BRUTES'!O$3:O$42,MATCH(_xlfn.AGGREGATE(14,6,'DONNÉES BRUTES'!Y$3:Y$42+ROW('DONNÉES BRUTES'!Y$3:Y$42)/1000,4),'DONNÉES BRUTES'!Y$3:Y$42+ROW('DONNÉES BRUTES'!Y$3:Y$42)/1000,0)),"—")} -> 41.5% | I7: {=IFERROR(INDEX('DONNÉES BRUTES'!Q$3:Q$42,MATCH(_xlfn.AGGREGATE(14,6,'DONNÉES BRUTES'!Y$3:Y$42+ROW('DONNÉES BRUTES'!Y$3:Y$42)/1000,4),'DONNÉES BRUTES'!Y$3:Y$42+ROW('DONNÉES BRUTES'!Y$3:Y$42)/1000,0)),"—")} -> +7.2% | J7: — | K7: — | L7: {=IFERROR(INDEX('DONNÉES BRUTES'!AD$3:AD$42,MATCH(_xlfn.AGGREGATE(14,6,'DONNÉES BRUTES'!Y$3:Y$42+ROW('DONNÉES BRUTES'!Y$3:Y$42)/1000,4),'DONNÉES BRUTES'!Y$3:Y$42+ROW('DONNÉES BRUTES'!Y$3:Y$42)/1000,0)),"—")} -> Neutre | O7: =IF(B9<>"—",LEFT(C9,18),"—") -> Sanofi | P7: =IF(E9<>"—",VALUE(LEFT(E9,FIND("/",E9)-1)),"") -> 87
A8: 5 | B8: {=IFERROR(INDEX('DONNÉES BRUTES'!A$3:A$42,MATCH(_xlfn.AGGREGATE(14,6,'DONNÉES BRUTES'!Y$3:Y$42+ROW('DONNÉES BRUTES'!Y$3:Y$42)/1000,5),'DONNÉES BRUTES'!Y$3:Y$42+ROW('DONNÉES BRUTES'!Y$3:Y$42)/1000,0)),"—")} -> HO.PA | C8: {=IFERROR(INDEX('DONNÉES BRUTES'!B$3:B$42,MATCH(_xlfn.AGGREGATE(14,6,'DONNÉES BRUTES'!Y$3:Y$42+ROW('DONNÉES BRUTES'!Y$3:Y$42)/1000,5),'DONNÉES BRUTES'!Y$3:Y$42+ROW('DONNÉES BRUTES'!Y$3:Y$42)/1000,0)),"—")} -> Thales S.A. | D8: {=IFERROR(INDEX('DONNÉES BRUTES'!C$3:C$42,MATCH(_xlfn.AGGREGATE(14,6,'DONNÉES BRUTES'!Y$3:Y$42+ROW('DONNÉES BRUTES'!Y$3:Y$42)/1000,5),'DONNÉES BRUTES'!Y$3:Y$42+ROW('DONNÉES BRUTES'!Y$3:Y$42)/1000,0)),"—")} -> Industrials | E8: {=IFERROR(INDEX('DONNÉES BRUTES'!Y$3:Y$42,MATCH(_xlfn.AGGREGATE(14,6,'DONNÉES BRUTES'!Y$3:Y$42+ROW('DONNÉES BRUTES'!Y$3:Y$42)/1000,5),'DONNÉES BRUTES'!Y$3:Y$42+ROW('DONNÉES BRUTES'!Y$3:Y$42)/1000,0))&"/100","—")} -> 89/100 | F8: {=IFERROR(INDEX('DONNÉES BRUTES'!P$3:P$42,MATCH(_xlfn.AGGREGATE(14,6,'DONNÉES BRUTES'!Y$3:Y$42+ROW('DONNÉES BRUTES'!Y$3:Y$42)/1000,5),'DONNÉES BRUTES'!Y$3:Y$42+ROW('DONNÉES BRUTES'!Y$3:Y$42)/1000,0)),"—")} -> +7.6% | G8: {=IFERROR(INDEX('DONNÉES BRUTES'!N$3:N$42,MATCH(_xlfn.AGGREGATE(14,6,'DONNÉES BRUTES'!Y$3:Y$42+ROW('DONNÉES BRUTES'!Y$3:Y$42)/1000,5),'DONNÉES BRUTES'!Y$3:Y$42+ROW('DONNÉES BRUTES'!Y$3:Y$42)/1000,0)),"—")} -> 15.4% | H8: {=IFERROR(INDEX('DONNÉES BRUTES'!O$3:O$42,MATCH(_xlfn.AGGREGATE(14,6,'DONNÉES BRUTES'!Y$3:Y$42+ROW('DONNÉES BRUTES'!Y$3:Y$42)/1000,5),'DONNÉES BRUTES'!Y$3:Y$42+ROW('DONNÉES BRUTES'!Y$3:Y$42)/1000,0)),"—")} -> 7.6% | I8: {=IFERROR(INDEX('DONNÉES BRUTES'!Q$3:Q$42,MATCH(_xlfn.AGGREGATE(14,6,'DONNÉES BRUTES'!Y$3:Y$42+ROW('DONNÉES BRUTES'!Y$3:Y$42)/1000,5),'DONNÉES BRUTES'!Y$3:Y$42+ROW('DONNÉES BRUTES'!Y$3:Y$42)/1000,0)),"—")} -> +21.0% | J8: — | K8: — | L8: {=IFERROR(INDEX('DONNÉES BRUTES'!AD$3:AD$42,MATCH(_xlfn.AGGREGATE(14,6,'DONNÉES BRUTES'!Y$3:Y$42+ROW('DONNÉES BRUTES'!Y$3:Y$42)/1000,5),'DONNÉES BRUTES'!Y$3:Y$42+ROW('DONNÉES BRUTES'!Y$3:Y$42)/1000,0)),"—")} -> Sous-pondérer | O8: =IF(B10<>"—",LEFT(C10,18),"—") -> Airbus SE | P8: =IF(E10<>"—",VALUE(LEFT(E10,FIND("/",E10)-1)),"") -> 84
A9: 6 | B9: {=IFERROR(INDEX('DONNÉES BRUTES'!A$3:A$42,MATCH(_xlfn.AGGREGATE(14,6,'DONNÉES BRUTES'!Y$3:Y$42+ROW('DONNÉES BRUTES'!Y$3:Y$42)/1000,6),'DONNÉES BRUTES'!Y$3:Y$42+ROW('DONNÉES BRUTES'!Y$3:Y$42)/1000,0)),"—")} -> SAN.PA | C9: {=IFERROR(INDEX('DONNÉES BRUTES'!B$3:B$42,MATCH(_xlfn.AGGREGATE(14,6,'DONNÉES BRUTES'!Y$3:Y$42+ROW('DONNÉES BRUTES'!Y$3:Y$42)/1000,6),'DONNÉES BRUTES'!Y$3:Y$42+ROW('DONNÉES BRUTES'!Y$3:Y$42)/1000,0)),"—")} -> Sanofi | D9: {=IFERROR(INDEX('DONNÉES BRUTES'!C$3:C$42,MATCH(_xlfn.AGGREGATE(14,6,'DONNÉES BRUTES'!Y$3:Y$42+ROW('DONNÉES BRUTES'!Y$3:Y$42)/1000,6),'DONNÉES BRUTES'!Y$3:Y$42+ROW('DONNÉES BRUTES'!Y$3:Y$42)/1000,0)),"—")} -> Healthcare | E9: {=IFERROR(INDEX('DONNÉES BRUTES'!Y$3:Y$42,MATCH(_xlfn.AGGREGATE(14,6,'DONNÉES BRUTES'!Y$3:Y$42+ROW('DONNÉES BRUTES'!Y$3:Y$42)/1000,6),'DONNÉES BRUTES'!Y$3:Y$42+ROW('DONNÉES BRUTES'!Y$3:Y$42)/1000,0))&"/100","—")} -> 87/100 | F9: {=IFERROR(INDEX('DONNÉES BRUTES'!P$3:P$42,MATCH(_xlfn.AGGREGATE(14,6,'DONNÉES BRUTES'!Y$3:Y$42+ROW('DONNÉES BRUTES'!Y$3:Y$42)/1000,6),'DONNÉES BRUTES'!Y$3:Y$42+ROW('DONNÉES BRUTES'!Y$3:Y$42)/1000,0)),"—")} -> +5.5% | G9: {=IFERROR(INDEX('DONNÉES BRUTES'!N$3:N$42,MATCH(_xlfn.AGGREGATE(14,6,'DONNÉES BRUTES'!Y$3:Y$42+ROW('DONNÉES BRUTES'!Y$3:Y$42)/1000,6),'DONNÉES BRUTES'!Y$3:Y$42+ROW('DONNÉES BRUTES'!Y$3:Y$42)/1000,0)),"—")} -> 26.7% | H9: {=IFERROR(INDEX('DONNÉES BRUTES'!O$3:O$42,MATCH(_xlfn.AGGREGATE(14,6,'DONNÉES BRUTES'!Y$3:Y$42+ROW('DONNÉES BRUTES'!Y$3:Y$42)/1000,6),'DONNÉES BRUTES'!Y$3:Y$42+ROW('DONNÉES BRUTES'!Y$3:Y$42)/1000,0)),"—")} -> 16.7% | I9: {=IFERROR(INDEX('DONNÉES BRUTES'!Q$3:Q$42,MATCH(_xlfn.AGGREGATE(14,6,'DONNÉES BRUTES'!Y$3:Y$42+ROW('DONNÉES BRUTES'!Y$3:Y$42)/1000,6),'DONNÉES BRUTES'!Y$3:Y$42+ROW('DONNÉES BRUTES'!Y$3:Y$42)/1000,0)),"—")} -> +10.9% | J9: — | K9: — | L9: {=IFERROR(INDEX('DONNÉES BRUTES'!AD$3:AD$42,MATCH(_xlfn.AGGREGATE(14,6,'DONNÉES BRUTES'!Y$3:Y$42+ROW('DONNÉES BRUTES'!Y$3:Y$42)/1000,6),'DONNÉES BRUTES'!Y$3:Y$42+ROW('DONNÉES BRUTES'!Y$3:Y$42)/1000,0)),"—")} -> Neutre | O9: =IF(B11<>"—",LEFT(C11,18),"—") -> Legrand SA | P9: =IF(E11<>"—",VALUE(LEFT(E11,FIND("/",E11)-1)),"") -> 82
A10: 7 | B10: {=IFERROR(INDEX('DONNÉES BRUTES'!A$3:A$42,MATCH(_xlfn.AGGREGATE(14,6,'DONNÉES BRUTES'!Y$3:Y$42+ROW('DONNÉES BRUTES'!Y$3:Y$42)/1000,7),'DONNÉES BRUTES'!Y$3:Y$42+ROW('DONNÉES BRUTES'!Y$3:Y$42)/1000,0)),"—")} -> AIR.PA | C10: {=IFERROR(INDEX('DONNÉES BRUTES'!B$3:B$42,MATCH(_xlfn.AGGREGATE(14,6,'DONNÉES BRUTES'!Y$3:Y$42+ROW('DONNÉES BRUTES'!Y$3:Y$42)/1000,7),'DONNÉES BRUTES'!Y$3:Y$42+ROW('DONNÉES BRUTES'!Y$3:Y$42)/1000,0)),"—")} -> Airbus SE | D10: {=IFERROR(INDEX('DONNÉES BRUTES'!C$3:C$42,MATCH(_xlfn.AGGREGATE(14,6,'DONNÉES BRUTES'!Y$3:Y$42+ROW('DONNÉES BRUTES'!Y$3:Y$42)/1000,7),'DONNÉES BRUTES'!Y$3:Y$42+ROW('DONNÉES BRUTES'!Y$3:Y$42)/1000,0)),"—")} -> Industrials | E10: {=IFERROR(INDEX('DONNÉES BRUTES'!Y$3:Y$42,MATCH(_xlfn.AGGREGATE(14,6,'DONNÉES BRUTES'!Y$3:Y$42+ROW('DONNÉES BRUTES'!Y$3:Y$42)/1000,7),'DONNÉES BRUTES'!Y$3:Y$42+ROW('DONNÉES BRUTES'!Y$3:Y$42)/1000,0))&"/100","—")} -> 84/100 | F10: {=IFERROR(INDEX('DONNÉES BRUTES'!P$3:P$42,MATCH(_xlfn.AGGREGATE(14,6,'DONNÉES BRUTES'!Y$3:Y$42+ROW('DONNÉES BRUTES'!Y$3:Y$42)/1000,7),'DONNÉES BRUTES'!Y$3:Y$42+ROW('DONNÉES BRUTES'!Y$3:Y$42)/1000,0)),"—")} -> +6.1% | G10: {=IFERROR(INDEX('DONNÉES BRUTES'!N$3:N$42,MATCH(_xlfn.AGGREGATE(14,6,'DONNÉES BRUTES'!Y$3:Y$42+ROW('DONNÉES BRUTES'!Y$3:Y$42)/1000,7),'DONNÉES BRUTES'!Y$3:Y$42+ROW('DONNÉES BRUTES'!Y$3:Y$42)/1000,0)),"—")} -> 14.0% | H10: {=IFERROR(INDEX('DONNÉES BRUTES'!O$3:O$42,MATCH(_xlfn.AGGREGATE(14,6,'DONNÉES BRUTES'!Y$3:Y$42+ROW('DONNÉES BRUTES'!Y$3:Y$42)/1000,7),'DONNÉES BRUTES'!Y$3:Y$42+ROW('DONNÉES BRUTES'!Y$3:Y$42)/1000,0)),"—")} -> 7.1% | I10: {=IFERROR(INDEX('DONNÉES BRUTES'!Q$3:Q$42,MATCH(_xlfn.AGGREGATE(14,6,'DONNÉES BRUTES'!Y$3:Y$42+ROW('DONNÉES BRUTES'!Y$3:Y$42)/1000,7),'DONNÉES BRUTES'!Y$3:Y$42+ROW('DONNÉES BRUTES'!Y$3:Y$42)/1000,0)),"—")} -> +20.0% | J10: — | K10: — | L10: {=IFERROR(INDEX('DONNÉES BRUTES'!AD$3:AD$42,MATCH(_xlfn.AGGREGATE(14,6,'DONNÉES BRUTES'!Y$3:Y$42+ROW('DONNÉES BRUTES'!Y$3:Y$42)/1000,7),'DONNÉES BRUTES'!Y$3:Y$42+ROW('DONNÉES BRUTES'!Y$3:Y$42)/1000,0)),"—")} -> Neutre | O10: =IF(B12<>"—",LEFT(C12,18),"—") -> ArcelorMittal S.A. | P10: =IF(E12<>"—",VALUE(LEFT(E12,FIND("/",E12)-1)),"") -> 79
A11: 8 | B11: {=IFERROR(INDEX('DONNÉES BRUTES'!A$3:A$42,MATCH(_xlfn.AGGREGATE(14,6,'DONNÉES BRUTES'!Y$3:Y$42+ROW('DONNÉES BRUTES'!Y$3:Y$42)/1000,8),'DONNÉES BRUTES'!Y$3:Y$42+ROW('DONNÉES BRUTES'!Y$3:Y$42)/1000,0)),"—")} -> LR.PA | C11: {=IFERROR(INDEX('DONNÉES BRUTES'!B$3:B$42,MATCH(_xlfn.AGGREGATE(14,6,'DONNÉES BRUTES'!Y$3:Y$42+ROW('DONNÉES BRUTES'!Y$3:Y$42)/1000,8),'DONNÉES BRUTES'!Y$3:Y$42+ROW('DONNÉES BRUTES'!Y$3:Y$42)/1000,0)),"—")} -> Legrand SA | D11: {=IFERROR(INDEX('DONNÉES BRUTES'!C$3:C$42,MATCH(_xlfn.AGGREGATE(14,6,'DONNÉES BRUTES'!Y$3:Y$42+ROW('DONNÉES BRUTES'!Y$3:Y$42)/1000,8),'DONNÉES BRUTES'!Y$3:Y$42+ROW('DONNÉES BRUTES'!Y$3:Y$42)/1000,0)),"—")} -> Industrials | E11: {=IFERROR(INDEX('DONNÉES BRUTES'!Y$3:Y$42,MATCH(_xlfn.AGGREGATE(14,6,'DONNÉES BRUTES'!Y$3:Y$42+ROW('DONNÉES BRUTES'!Y$3:Y$42)/1000,8),'DONNÉES BRUTES'!Y$3:Y$42+ROW('DONNÉES BRUTES'!Y$3:Y$42)/1000,0))&"/100","—")} -> 82/100 | F11: {=IFERROR(INDEX('DONNÉES BRUTES'!P$3:P$42,MATCH(_xlfn.AGGREGATE(14,6,'DONNÉES BRUTES'!Y$3:Y$42+ROW('DONNÉES BRUTES'!Y$3:Y$42)/1000,8),'DONNÉES BRUTES'!Y$3:Y$42+ROW('DONNÉES BRUTES'!Y$3:Y$42)/1000,0)),"—")} -> +9.6% | G11: {=IFERROR(INDEX('DONNÉES BRUTES'!N$3:N$42,MATCH(_xlfn.AGGREGATE(14,6,'DONNÉES BRUTES'!Y$3:Y$42+ROW('DONNÉES BRUTES'!Y$3:Y$42)/1000,8),'DONNÉES BRUTES'!Y$3:Y$42+ROW('DONNÉES BRUTES'!Y$3:Y$42)/1000,0)),"—")} -> 23.9% | H11: {=IFERROR(INDEX('DONNÉES BRUTES'!O$3:O$42,MATCH(_xlfn.AGGREGATE(14,6,'DONNÉES BRUTES'!Y$3:Y$42+ROW('DONNÉES BRUTES'!Y$3:Y$42)/1000,8),'DONNÉES BRUTES'!Y$3:Y$42+ROW('DONNÉES BRUTES'!Y$3:Y$42)/1000,0)),"—")} -> 13.1% | I11: {=IFERROR(INDEX('DONNÉES BRUTES'!Q$3:Q$42,MATCH(_xlfn.AGGREGATE(14,6,'DONNÉES BRUTES'!Y$3:Y$42+ROW('DONNÉES BRUTES'!Y$3:Y$42)/1000,8),'DONNÉES BRUTES'!Y$3:Y$42+ROW('DONNÉES BRUTES'!Y$3:Y$42)/1000,0)),"—")} -> +17.1% | J11: — | K11: — | L11: {=IFERROR(INDEX('DONNÉES BRUTES'!AD$3:AD$42,MATCH(_xlfn.AGGREGATE(14,6,'DONNÉES BRUTES'!Y$3:Y$42+ROW('DONNÉES BRUTES'!Y$3:Y$42)/1000,8),'DONNÉES BRUTES'!Y$3:Y$42+ROW('DONNÉES BRUTES'!Y$3:Y$42)/1000,0)),"—")} -> Neutre | O11: =IF(B13<>"—",LEFT(C13,18),"—") -> Eurofins Scientifi | P11: =IF(E13<>"—",VALUE(LEFT(E13,FIND("/",E13)-1)),"") -> 76
A12: 9 | B12: {=IFERROR(INDEX('DONNÉES BRUTES'!A$3:A$42,MATCH(_xlfn.AGGREGATE(14,6,'DONNÉES BRUTES'!Y$3:Y$42+ROW('DONNÉES BRUTES'!Y$3:Y$42)/1000,9),'DONNÉES BRUTES'!Y$3:Y$42+ROW('DONNÉES BRUTES'!Y$3:Y$42)/1000,0)),"—")} -> MT.AS | C12: {=IFERROR(INDEX('DONNÉES BRUTES'!B$3:B$42,MATCH(_xlfn.AGGREGATE(14,6,'DONNÉES BRUTES'!Y$3:Y$42+ROW('DONNÉES BRUTES'!Y$3:Y$42)/1000,9),'DONNÉES BRUTES'!Y$3:Y$42+ROW('DONNÉES BRUTES'!Y$3:Y$42)/1000,0)),"—")} -> ArcelorMittal S.A. | D12: {=IFERROR(INDEX('DONNÉES BRUTES'!C$3:C$42,MATCH(_xlfn.AGGREGATE(14,6,'DONNÉES BRUTES'!Y$3:Y$42+ROW('DONNÉES BRUTES'!Y$3:Y$42)/1000,9),'DONNÉES BRUTES'!Y$3:Y$42+ROW('DONNÉES BRUTES'!Y$3:Y$42)/1000,0)),"—")} -> Materials | E12: {=IFERROR(INDEX('DONNÉES BRUTES'!Y$3:Y$42,MATCH(_xlfn.AGGREGATE(14,6,'DONNÉES BRUTES'!Y$3:Y$42+ROW('DONNÉES BRUTES'!Y$3:Y$42)/1000,9),'DONNÉES BRUTES'!Y$3:Y$42+ROW('DONNÉES BRUTES'!Y$3:Y$42)/1000,0))&"/100","—")} -> 79/100 | F12: {=IFERROR(INDEX('DONNÉES BRUTES'!P$3:P$42,MATCH(_xlfn.AGGREGATE(14,6,'DONNÉES BRUTES'!Y$3:Y$42+ROW('DONNÉES BRUTES'!Y$3:Y$42)/1000,9),'DONNÉES BRUTES'!Y$3:Y$42+ROW('DONNÉES BRUTES'!Y$3:Y$42)/1000,0)),"—")} -> -1.7% | G12: {=IFERROR(INDEX('DONNÉES BRUTES'!N$3:N$42,MATCH(_xlfn.AGGREGATE(14,6,'DONNÉES BRUTES'!Y$3:Y$42+ROW('DONNÉES BRUTES'!Y$3:Y$42)/1000,9),'DONNÉES BRUTES'!Y$3:Y$42+ROW('DONNÉES BRUTES'!Y$3:Y$42)/1000,0)),"—")} -> 11.6% | H12: {=IFERROR(INDEX('DONNÉES BRUTES'!O$3:O$42,MATCH(_xlfn.AGGREGATE(14,6,'DONNÉES BRUTES'!Y$3:Y$42+ROW('DONNÉES BRUTES'!Y$3:Y$42)/1000,9),'DONNÉES BRUTES'!Y$3:Y$42+ROW('DONNÉES BRUTES'!Y$3:Y$42)/1000,0)),"—")} -> 5.1% | I12: {=IFERROR(INDEX('DONNÉES BRUTES'!Q$3:Q$42,MATCH(_xlfn.AGGREGATE(14,6,'DONNÉES BRUTES'!Y$3:Y$42+ROW('DONNÉES BRUTES'!Y$3:Y$42)/1000,9),'DONNÉES BRUTES'!Y$3:Y$42+ROW('DONNÉES BRUTES'!Y$3:Y$42)/1000,0)),"—")} -> +5.8% | J12: — | K12: — | L12: {=IFERROR(INDEX('DONNÉES BRUTES'!AD$3:AD$42,MATCH(_xlfn.AGGREGATE(14,6,'DONNÉES BRUTES'!Y$3:Y$42+ROW('DONNÉES BRUTES'!Y$3:Y$42)/1000,9),'DONNÉES BRUTES'!Y$3:Y$42+ROW('DONNÉES BRUTES'!Y$3:Y$42)/1000,0)),"—")} -> Sous-pondérer
A13: 10 | B13: {=IFERROR(INDEX('DONNÉES BRUTES'!A$3:A$42,MATCH(_xlfn.AGGREGATE(14,6,'DONNÉES BRUTES'!Y$3:Y$42+ROW('DONNÉES BRUTES'!Y$3:Y$42)/1000,10),'DONNÉES BRUTES'!Y$3:Y$42+ROW('DONNÉES BRUTES'!Y$3:Y$42)/1000,0)),"—")} -> ERF.PA | C13: {=IFERROR(INDEX('DONNÉES BRUTES'!B$3:B$42,MATCH(_xlfn.AGGREGATE(14,6,'DONNÉES BRUTES'!Y$3:Y$42+ROW('DONNÉES BRUTES'!Y$3:Y$42)/1000,10),'DONNÉES BRUTES'!Y$3:Y$42+ROW('DONNÉES BRUTES'!Y$3:Y$42)/1000,0)),"—")} -> Eurofins Scientific SE | D13: {=IFERROR(INDEX('DONNÉES BRUTES'!C$3:C$42,MATCH(_xlfn.AGGREGATE(14,6,'DONNÉES BRUTES'!Y$3:Y$42+ROW('DONNÉES BRUTES'!Y$3:Y$42)/1000,10),'DONNÉES BRUTES'!Y$3:Y$42+ROW('DONNÉES BRUTES'!Y$3:Y$42)/1000,0)),"—")} -> Healthcare | E13: {=IFERROR(INDEX('DONNÉES BRUTES'!Y$3:Y$42,MATCH(_xlfn.AGGREGATE(14,6,'DONNÉES BRUTES'!Y$3:Y$42+ROW('DONNÉES BRUTES'!Y$3:Y$42)/1000,10),'DONNÉES BRUTES'!Y$3:Y$42+ROW('DONNÉES BRUTES'!Y$3:Y$42)/1000,0))&"/100","—")} -> 76/100 | F13: {=IFERROR(INDEX('DONNÉES BRUTES'!P$3:P$42,MATCH(_xlfn.AGGREGATE(14,6,'DONNÉES BRUTES'!Y$3:Y$42+ROW('DONNÉES BRUTES'!Y$3:Y$42)/1000,10),'DONNÉES BRUTES'!Y$3:Y$42+ROW('DONNÉES BRUTES'!Y$3:Y$42)/1000,0)),"—")} -> +5.0% | G13: {=IFERROR(INDEX('DONNÉES BRUTES'!N$3:N$42,MATCH(_xlfn.AGGREGATE(14,6,'DONNÉES BRUTES'!Y$3:Y$42+ROW('DONNÉES BRUTES'!Y$3:Y$42)/1000,10),'DONNÉES BRUTES'!Y$3:Y$42+ROW('DONNÉES BRUTES'!Y$3:Y$42)/1000,0)),"—")} -> 21.0% | H13: {=IFERROR(INDEX('DONNÉES BRUTES'!O$3:O$42,MATCH(_xlfn.AGGREGATE(14,6,'DONNÉES BRUTES'!Y$3:Y$42+ROW('DONNÉES BRUTES'!Y$3:Y$42)/1000,10),'DONNÉES BRUTES'!Y$3:Y$42+ROW('DONNÉES BRUTES'!Y$3:Y$42)/1000,0)),"—")} -> 6.5% | I13: {=IFERROR(INDEX('DONNÉES BRUTES'!Q$3:Q$42,MATCH(_xlfn.AGGREGATE(14,6,'DONNÉES BRUTES'!Y$3:Y$42+ROW('DONNÉES BRUTES'!Y$3:Y$42)/1000,10),'DONNÉES BRUTES'!Y$3:Y$42+ROW('DONNÉES BRUTES'!Y$3:Y$42)/1000,0)),"—")} -> +10.5% | J13: — | K13: — | L13: {=IFERROR(INDEX('DONNÉES BRUTES'!AD$3:AD$42,MATCH(_xlfn.AGGREGATE(14,6,'DONNÉES BRUTES'!Y$3:Y$42+ROW('DONNÉES BRUTES'!Y$3:Y$42)/1000,10),'DONNÉES BRUTES'!Y$3:Y$42+ROW('DONNÉES BRUTES'!Y$3:Y$42)/1000,0)),"—")} -> Neutre
A14: 11 | B14: {=IFERROR(INDEX('DONNÉES BRUTES'!A$3:A$42,MATCH(_xlfn.AGGREGATE(14,6,'DONNÉES BRUTES'!Y$3:Y$42+ROW('DONNÉES BRUTES'!Y$3:Y$42)/1000,11),'DONNÉES BRUTES'!Y$3:Y$42+ROW('DONNÉES BRUTES'!Y$3:Y$42)/1000,0)),"—")} -> RMS.PA | C14: {=IFERROR(INDEX('DONNÉES BRUTES'!B$3:B$42,MATCH(_xlfn.AGGREGATE(14,6,'DONNÉES BRUTES'!Y$3:Y$42+ROW('DONNÉES BRUTES'!Y$3:Y$42)/1000,11),'DONNÉES BRUTES'!Y$3:Y$42+ROW('DONNÉES BRUTES'!Y$3:Y$42)/1000,0)),"—")} -> Hermès International Société en commandite par actions | D14: {=IFERROR(INDEX('DONNÉES BRUTES'!C$3:C$42,MATCH(_xlfn.AGGREGATE(14,6,'DONNÉES BRUTES'!Y$3:Y$42+ROW('DONNÉES BRUTES'!Y$3:Y$42)/1000,11),'DONNÉES BRUTES'!Y$3:Y$42+ROW('DONNÉES BRUTES'!Y$3:Y$42)/1000,0)),"—")} -> Consumer Disc. | E14: {=IFERROR(INDEX('DONNÉES BRUTES'!Y$3:Y$42,MATCH(_xlfn.AGGREGATE(14,6,'DONNÉES BRUTES'!Y$3:Y$42+ROW('DONNÉES BRUTES'!Y$3:Y$42)/1000,11),'DONNÉES BRUTES'!Y$3:Y$42+ROW('DONNÉES BRUTES'!Y$3:Y$42)/1000,0))&"/100","—")} -> 74/100 | F14: {=IFERROR(INDEX('DONNÉES BRUTES'!P$3:P$42,MATCH(_xlfn.AGGREGATE(14,6,'DONNÉES BRUTES'!Y$3:Y$42+ROW('DONNÉES BRUTES'!Y$3:Y$42)/1000,11),'DONNÉES BRUTES'!Y$3:Y$42+ROW('DONNÉES BRUTES'!Y$3:Y$42)/1000,0)),"—")} -> +5.5% | G14: {=IFERROR(INDEX('DONNÉES BRUTES'!N$3:N$42,MATCH(_xlfn.AGGREGATE(14,6,'DONNÉES BRUTES'!Y$3:Y$42+ROW('DONNÉES BRUTES'!Y$3:Y$42)/1000,11),'DONNÉES BRUTES'!Y$3:Y$42+ROW('DONNÉES BRUTES'!Y$3:Y$42)/1000,0)),"—")} -> 46.8% | H14: {=IFERROR(INDEX('DONNÉES BRUTES'!O$3:O$42,MATCH(_xlfn.AGGREGATE(14,6,'DONNÉES BRUTES'!Y$3:Y$42+ROW('DONNÉES BRUTES'!Y$3:Y$42)/1000,11),'DONNÉES BRUTES'!Y$3:Y$42+ROW('DONNÉES BRUTES'!Y$3:Y$42)/1000,0)),"—")} -> 28.3% | I14: {=IFERROR(INDEX('DONNÉES BRUTES'!Q$3:Q$42,MATCH(_xlfn.AGGREGATE(14,6,'DONNÉES BRUTES'!Y$3:Y$42+ROW('DONNÉES BRUTES'!Y$3:Y$42)/1000,11),'DONNÉES BRUTES'!Y$3:Y$42+ROW('DONNÉES BRUTES'!Y$3:Y$42)/1000,0)),"—")} -> +24.0% | J14: — | K14: — | L14: {=IFERROR(INDEX('DONNÉES BRUTES'!AD$3:AD$42,MATCH(_xlfn.AGGREGATE(14,6,'DONNÉES BRUTES'!Y$3:Y$42+ROW('DONNÉES BRUTES'!Y$3:Y$42)/1000,11),'DONNÉES BRUTES'!Y$3:Y$42+ROW('DONNÉES BRUTES'!Y$3:Y$42)/1000,0)),"—")} -> Surpondérer
A15: 12 | B15: {=IFERROR(INDEX('DONNÉES BRUTES'!A$3:A$42,MATCH(_xlfn.AGGREGATE(14,6,'DONNÉES BRUTES'!Y$3:Y$42+ROW('DONNÉES BRUTES'!Y$3:Y$42)/1000,12),'DONNÉES BRUTES'!Y$3:Y$42+ROW('DONNÉES BRUTES'!Y$3:Y$42)/1000,0)),"—")} -> CS.PA | C15: {=IFERROR(INDEX('DONNÉES BRUTES'!B$3:B$42,MATCH(_xlfn.AGGREGATE(14,6,'DONNÉES BRUTES'!Y$3:Y$42+ROW('DONNÉES BRUTES'!Y$3:Y$42)/1000,12),'DONNÉES BRUTES'!Y$3:Y$42+ROW('DONNÉES BRUTES'!Y$3:Y$42)/1000,0)),"—")} -> AXA SA | D15: {=IFERROR(INDEX('DONNÉES BRUTES'!C$3:C$42,MATCH(_xlfn.AGGREGATE(14,6,'DONNÉES BRUTES'!Y$3:Y$42+ROW('DONNÉES BRUTES'!Y$3:Y$42)/1000,12),'DONNÉES BRUTES'!Y$3:Y$42+ROW('DONNÉES BRUTES'!Y$3:Y$42)/1000,0)),"—")} -> Financials | E15: {=IFERROR(INDEX('DONNÉES BRUTES'!Y$3:Y$42,MATCH(_xlfn.AGGREGATE(14,6,'DONNÉES BRUTES'!Y$3:Y$42+ROW('DONNÉES BRUTES'!Y$3:Y$42)/1000,12),'DONNÉES BRUTES'!Y$3:Y$42+ROW('DONNÉES BRUTES'!Y$3:Y$42)/1000,0))&"/100","—")} -> 71/100 | F15: {=IFERROR(INDEX('DONNÉES BRUTES'!P$3:P$42,MATCH(_xlfn.AGGREGATE(14,6,'DONNÉES BRUTES'!Y$3:Y$42+ROW('DONNÉES BRUTES'!Y$3:Y$42)/1000,12),'DONNÉES BRUTES'!Y$3:Y$42+ROW('DONNÉES BRUTES'!Y$3:Y$42)/1000,0)),"—")} -> +5.7% | G15: {=IFERROR(INDEX('DONNÉES BRUTES'!N$3:N$42,MATCH(_xlfn.AGGREGATE(14,6,'DONNÉES BRUTES'!Y$3:Y$42+ROW('DONNÉES BRUTES'!Y$3:Y$42)/1000,12),'DONNÉES BRUTES'!Y$3:Y$42+ROW('DONNÉES BRUTES'!Y$3:Y$42)/1000,0)),"—")} -> — | H15: {=IFERROR(INDEX('DONNÉES BRUTES'!O$3:O$42,MATCH(_xlfn.AGGREGATE(14,6,'DONNÉES BRUTES'!Y$3:Y$42+ROW('DONNÉES BRUTES'!Y$3:Y$42)/1000,12),'DONNÉES BRUTES'!Y$3:Y$42+ROW('DONNÉES BRUTES'!Y$3:Y$42)/1000,0)),"—")} -> 7.6% | I15: {=IFERROR(INDEX('DONNÉES BRUTES'!Q$3:Q$42,MATCH(_xlfn.AGGREGATE(14,6,'DONNÉES BRUTES'!Y$3:Y$42+ROW('DONNÉES BRUTES'!Y$3:Y$42)/1000,12),'DONNÉES BRUTES'!Y$3:Y$42+ROW('DONNÉES BRUTES'!Y$3:Y$42)/1000,0)),"—")} -> +15.8% | J15: — | K15: — | L15: {=IFERROR(INDEX('DONNÉES BRUTES'!AD$3:AD$42,MATCH(_xlfn.AGGREGATE(14,6,'DONNÉES BRUTES'!Y$3:Y$42+ROW('DONNÉES BRUTES'!Y$3:Y$42)/1000,12),'DONNÉES BRUTES'!Y$3:Y$42+ROW('DONNÉES BRUTES'!Y$3:Y$42)/1000,0)),"—")} -> Neutre
A16: 13 | B16: {=IFERROR(INDEX('DONNÉES BRUTES'!A$3:A$42,MATCH(_xlfn.AGGREGATE(14,6,'DONNÉES BRUTES'!Y$3:Y$42+ROW('DONNÉES BRUTES'!Y$3:Y$42)/1000,13),'DONNÉES BRUTES'!Y$3:Y$42+ROW('DONNÉES BRUTES'!Y$3:Y$42)/1000,0)),"—")} -> DG.PA | C16: {=IFERROR(INDEX('DONNÉES BRUTES'!B$3:B$42,MATCH(_xlfn.AGGREGATE(14,6,'DONNÉES BRUTES'!Y$3:Y$42+ROW('DONNÉES BRUTES'!Y$3:Y$42)/1000,13),'DONNÉES BRUTES'!Y$3:Y$42+ROW('DONNÉES BRUTES'!Y$3:Y$42)/1000,0)),"—")} -> Vinci SA | D16: {=IFERROR(INDEX('DONNÉES BRUTES'!C$3:C$42,MATCH(_xlfn.AGGREGATE(14,6,'DONNÉES BRUTES'!Y$3:Y$42+ROW('DONNÉES BRUTES'!Y$3:Y$42)/1000,13),'DONNÉES BRUTES'!Y$3:Y$42+ROW('DONNÉES BRUTES'!Y$3:Y$42)/1000,0)),"—")} -> Industrials | E16: {=IFERROR(INDEX('DONNÉES BRUTES'!Y$3:Y$42,MATCH(_xlfn.AGGREGATE(14,6,'DONNÉES BRUTES'!Y$3:Y$42+ROW('DONNÉES BRUTES'!Y$3:Y$42)/1000,13),'DONNÉES BRUTES'!Y$3:Y$42+ROW('DONNÉES BRUTES'!Y$3:Y$42)/1000,0))&"/100","—")} -> 68/100 | F16: {=IFERROR(INDEX('DONNÉES BRUTES'!P$3:P$42,MATCH(_xlfn.AGGREGATE(14,6,'DONNÉES BRUTES'!Y$3:Y$42+ROW('DONNÉES BRUTES'!Y$3:Y$42)/1000,13),'DONNÉES BRUTES'!Y$3:Y$42+ROW('DONNÉES BRUTES'!Y$3:Y$42)/1000,0)),"—")} -> +4.0% | G16: {=IFERROR(INDEX('DONNÉES BRUTES'!N$3:N$42,MATCH(_xlfn.AGGREGATE(14,6,'DONNÉES BRUTES'!Y$3:Y$42+ROW('DONNÉES BRUTES'!Y$3:Y$42)/1000,13),'DONNÉES BRUTES'!Y$3:Y$42+ROW('DONNÉES BRUTES'!Y$3:Y$42)/1000,0)),"—")} -> 18.0% | H16: {=IFERROR(INDEX('DONNÉES BRUTES'!O$3:O$42,MATCH(_xlfn.AGGREGATE(14,6,'DONNÉES BRUTES'!Y$3:Y$42+ROW('DONNÉES BRUTES'!Y$3:Y$42)/1000,13),'DONNÉES BRUTES'!Y$3:Y$42+ROW('DONNÉES BRUTES'!Y$3:Y$42)/1000,0)),"—")} -> 6.5% | I16: {=IFERROR(INDEX('DONNÉES BRUTES'!Q$3:Q$42,MATCH(_xlfn.AGGREGATE(14,6,'DONNÉES BRUTES'!Y$3:Y$42+ROW('DONNÉES BRUTES'!Y$3:Y$42)/1000,13),'DONNÉES BRUTES'!Y$3:Y$42+ROW('DONNÉES BRUTES'!Y$3:Y$42)/1000,0)),"—")} -> +15.9% | J16: — | K16: — | L16: {=IFERROR(INDEX('DONNÉES BRUTES'!AD$3:AD$42,MATCH(_xlfn.AGGREGATE(14,6,'DONNÉES BRUTES'!Y$3:Y$42+ROW('DONNÉES BRUTES'!Y$3:Y$42)/1000,13),'DONNÉES BRUTES'!Y$3:Y$42+ROW('DONNÉES BRUTES'!Y$3:Y$42)/1000,0)),"—")} -> Sous-pondérer
A17: 14 | B17: {=IFERROR(INDEX('DONNÉES BRUTES'!A$3:A$42,MATCH(_xlfn.AGGREGATE(14,6,'DONNÉES BRUTES'!Y$3:Y$42+ROW('DONNÉES BRUTES'!Y$3:Y$42)/1000,14),'DONNÉES BRUTES'!Y$3:Y$42+ROW('DONNÉES BRUTES'!Y$3:Y$42)/1000,0)),"—")} -> SU.PA | C17: {=IFERROR(INDEX('DONNÉES BRUTES'!B$3:B$42,MATCH(_xlfn.AGGREGATE(14,6,'DONNÉES BRUTES'!Y$3:Y$42+ROW('DONNÉES BRUTES'!Y$3:Y$42)/1000,14),'DONNÉES BRUTES'!Y$3:Y$42+ROW('DONNÉES BRUTES'!Y$3:Y$42)/1000,0)),"—")} -> Schneider Electric S.E. | D17: {=IFERROR(INDEX('DONNÉES BRUTES'!C$3:C$42,MATCH(_xlfn.AGGREGATE(14,6,'DONNÉES BRUTES'!Y$3:Y$42+ROW('DONNÉES BRUTES'!Y$3:Y$42)/1000,14),'DONNÉES BRUTES'!Y$3:Y$42+ROW('DONNÉES BRUTES'!Y$3:Y$42)/1000,0)),"—")} -> Industrials | E17: {=IFERROR(INDEX('DONNÉES BRUTES'!Y$3:Y$42,MATCH(_xlfn.AGGREGATE(14,6,'DONNÉES BRUTES'!Y$3:Y$42+ROW('DONNÉES BRUTES'!Y$3:Y$42)/1000,14),'DONNÉES BRUTES'!Y$3:Y$42+ROW('DONNÉES BRUTES'!Y$3:Y$42)/1000,0))&"/100","—")} -> 66/100 | F17: {=IFERROR(INDEX('DONNÉES BRUTES'!P$3:P$42,MATCH(_xlfn.AGGREGATE(14,6,'DONNÉES BRUTES'!Y$3:Y$42+ROW('DONNÉES BRUTES'!Y$3:Y$42)/1000,14),'DONNÉES BRUTES'!Y$3:Y$42+ROW('DONNÉES BRUTES'!Y$3:Y$42)/1000,0)),"—")} -> +5.2% | G17: {=IFERROR(INDEX('DONNÉES BRUTES'!N$3:N$42,MATCH(_xlfn.AGGREGATE(14,6,'DONNÉES BRUTES'!Y$3:Y$42+ROW('DONNÉES BRUTES'!Y$3:Y$42)/1000,14),'DONNÉES BRUTES'!Y$3:Y$42+ROW('DONNÉES BRUTES'!Y$3:Y$42)/1000,0)),"—")} -> 20.9% | H17: {=IFERROR(INDEX('DONNÉES BRUTES'!O$3:O$42,MATCH(_xlfn.AGGREGATE(14,6,'DONNÉES BRUTES'!Y$3:Y$42+ROW('DONNÉES BRUTES'!Y$3:Y$42)/1000,14),'DONNÉES BRUTES'!Y$3:Y$42+ROW('DONNÉES BRUTES'!Y$3:Y$42)/1000,0)),"—")} -> 10.4% | I17: {=IFERROR(INDEX('DONNÉES BRUTES'!Q$3:Q$42,MATCH(_xlfn.AGGREGATE(14,6,'DONNÉES BRUTES'!Y$3:Y$42+ROW('DONNÉES BRUTES'!Y$3:Y$42)/1000,14),'DONNÉES BRUTES'!Y$3:Y$42+ROW('DONNÉES BRUTES'!Y$3:Y$42)/1000,0)),"—")} -> +17.2% | J17: — | K17: — | L17: {=IFERROR(INDEX('DONNÉES BRUTES'!AD$3:AD$42,MATCH(_xlfn.AGGREGATE(14,6,'DONNÉES BRUTES'!Y$3:Y$42+ROW('DONNÉES BRUTES'!Y$3:Y$42)/1000,14),'DONNÉES BRUTES'!Y$3:Y$42+ROW('DONNÉES BRUTES'!Y$3:Y$42)/1000,0)),"—")} -> Neutre
A18: 15 | B18: {=IFERROR(INDEX('DONNÉES BRUTES'!A$3:A$42,MATCH(_xlfn.AGGREGATE(14,6,'DONNÉES BRUTES'!Y$3:Y$42+ROW('DONNÉES BRUTES'!Y$3:Y$42)/1000,15),'DONNÉES BRUTES'!Y$3:Y$42+ROW('DONNÉES BRUTES'!Y$3:Y$42)/1000,0)),"—")} -> CA.PA | C18: {=IFERROR(INDEX('DONNÉES BRUTES'!B$3:B$42,MATCH(_xlfn.AGGREGATE(14,6,'DONNÉES BRUTES'!Y$3:Y$42+ROW('DONNÉES BRUTES'!Y$3:Y$42)/1000,15),'DONNÉES BRUTES'!Y$3:Y$42+ROW('DONNÉES BRUTES'!Y$3:Y$42)/1000,0)),"—")} -> Carrefour SA | D18: {=IFERROR(INDEX('DONNÉES BRUTES'!C$3:C$42,MATCH(_xlfn.AGGREGATE(14,6,'DONNÉES BRUTES'!Y$3:Y$42+ROW('DONNÉES BRUTES'!Y$3:Y$42)/1000,15),'DONNÉES BRUTES'!Y$3:Y$42+ROW('DONNÉES BRUTES'!Y$3:Y$42)/1000,0)),"—")} -> Consumer Staples | E18: {=IFERROR(INDEX('DONNÉES BRUTES'!Y$3:Y$42,MATCH(_xlfn.AGGREGATE(14,6,'DONNÉES BRUTES'!Y$3:Y$42+ROW('DONNÉES BRUTES'!Y$3:Y$42)/1000,15),'DONNÉES BRUTES'!Y$3:Y$42+ROW('DONNÉES BRUTES'!Y$3:Y$42)/1000,0))&"/100","—")} -> 63/100 | F18: {=IFERROR(INDEX('DONNÉES BRUTES'!P$3:P$42,MATCH(_xlfn.AGGREGATE(14,6,'DONNÉES BRUTES'!Y$3:Y$42+ROW('DONNÉES BRUTES'!Y$3:Y$42)/1000,15),'DONNÉES BRUTES'!Y$3:Y$42+ROW('DONNÉES BRUTES'!Y$3:Y$42)/1000,0)),"—")} -> +0.7% | G18: {=IFERROR(INDEX('DONNÉES BRUTES'!N$3:N$42,MATCH(_xlfn.AGGREGATE(14,6,'DONNÉES BRUTES'!Y$3:Y$42+ROW('DONNÉES BRUTES'!Y$3:Y$42)/1000,15),'DONNÉES BRUTES'!Y$3:Y$42+ROW('DONNÉES BRUTES'!Y$3:Y$42)/1000,0)),"—")} -> 5.6% | H18: {=IFERROR(INDEX('DONNÉES BRUTES'!O$3:O$42,MATCH(_xlfn.AGGREGATE(14,6,'DONNÉES BRUTES'!Y$3:Y$42+ROW('DONNÉES BRUTES'!Y$3:Y$42)/1000,15),'DONNÉES BRUTES'!Y$3:Y$42+ROW('DONNÉES BRUTES'!Y$3:Y$42)/1000,0)),"—")} -> 0.4% | I18: {=IFERROR(INDEX('DONNÉES BRUTES'!Q$3:Q$42,MATCH(_xlfn.AGGREGATE(14,6,'DONNÉES BRUTES'!Y$3:Y$42+ROW('DONNÉES BRUTES'!Y$3:Y$42)/1000,15),'DONNÉES BRUTES'!Y$3:Y$42+ROW('DONNÉES BRUTES'!Y$3:Y$42)/1000,0)),"—")} -> +2.9% | J18: — | K18: — | L18: {=IFERROR(INDEX('DONNÉES BRUTES'!AD$3:AD$42,MATCH(_xlfn.AGGREGATE(14,6,'DONNÉES BRUTES'!Y$3:Y$42+ROW('DONNÉES BRUTES'!Y$3:Y$42)/1000,15),'DONNÉES BRUTES'!Y$3:Y$42+ROW('DONNÉES BRUTES'!Y$3:Y$42)/1000,0)),"—")} -> Neutre

Sheet QUALITY
A1: FinSight IA · Analyse QUALITY · CAC 40 · 22/03/2026 | O1: Société | P1: Score Qual | Q1: Altman Z | R1: Beneish M
A2: Usage confidentiel · Calculs Python/NumPy depuis cache Supabase | O2: =IF(B4<>"—",LEFT(C4,15),"—") -> Dassault Systèm | P2: =IF(E4<>"—",VALUE(LEFT(E4,FIND("/",E4)-1)),"") -> 100 | Q2: =IF(F4<>"—",F4,"") | R2: =IF(H4<>"—",H4,"") -> -3.10
A3: Rang | B3: Ticker | C3: Société | D3: Secteur | E3: Score | F3: Altman Z-Score | G3: Signal Z | H3: Beneish M | I3: Signal M | J3: Marge EBITDA | K3: ROE | L3: Interest Coverage | M3: Current Ratio | O3: =IF(B5<>"—",LEFT(C5,15),"—") -> Sanofi | P3: =IF(E5<>"—",VALUE(LEFT(E5,FIND("/",E5)-1)),"") -> 97 | Q3: =IF(F5<>"—",F5,"") | R3: =IF(H5<>"—",H5,"") -> -3.00
A4: 1 | B4: {=IFERROR(INDEX('DONNÉES BRUTES'!A$3:A$42,MATCH(_xlfn.AGGREGATE(14,6,'DONNÉES BRUTES'!Z$3:Z$42+ROW('DONNÉES BRUTES'!Z$3:Z$42)/1000,1),'DONNÉES BRUTES'!Z$3:Z$42+ROW('DONNÉES BRUTES'!Z$3:Z$42)/1000,0)),"—")} -> DSY.PA | C4: {=IFERROR(INDEX('DONNÉES BRUTES'!B$3:B$42,MATCH(_xlfn.AGGREGATE(14,6,'DONNÉES BRUTES'!Z$3:Z$42+ROW('DONNÉES BRUTES'!Z$3:Z$42)/1000,1),'DONNÉES BRUTES'!Z$3:Z$42+ROW('DONNÉES BRUTES'!Z$3:Z$42)/1000,0)),"—")} -> Dassault Systèmes SE | D4: {=IFERROR(INDEX('DONNÉES BRUTES'!C$3:C$42,MATCH(_xlfn.AGGREGATE(14,6,'DONNÉES BRUTES'!Z$3:Z$42+ROW('DONNÉES BRUTES'!Z$3:Z$42)/1000,1),'DONNÉES BRUTES'!Z$3:Z$42+ROW('DONNÉES BRUTES'!Z$3:Z$42)/1000,0)),"—")} -> Technology | E4: {=IFERROR(INDEX('DONNÉES BRUTES'!Z$3:Z$42,MATCH(_xlfn.AGGREGATE(14,6,'DONNÉES BRUTES'!Z$3:Z$42+ROW('DONNÉES BRUTES'!Z$3:Z$42)/1000,1),'DONNÉES BRUTES'!Z$3:Z$42+ROW('DONNÉES BRUTES'!Z$3:Z$42)/1000,0))&"/100","—")} -> 100/100 | F4: {=IFERROR(INDEX('DONNÉES BRUTES'!U$3:U$42,MATCH(_xlfn.AGGREGATE(14,6,'DONNÉES BRUTES'!Z$3:Z$42+ROW('DONNÉES BRUTES'!Z$3:Z$42)/1000,1),'DONNÉES BRUTES'!Z$3:Z$42+ROW('DONNÉES BRUTES'!Z$3:Z$42)/1000,0)),"—")} -> — | G4: — | H4: {=IFERROR(INDEX('DONNÉES BRUTES'!V$3:V$42,MATCH(_xlfn.AGGREGATE(14,6,'DONNÉES BRUTES'!Z$3:Z$42+ROW('DONNÉES BRUTES'!Z$3:Z$42)/1000,1),'DONNÉES BRUTES'!Z$3:Z$42+ROW('DONNÉES BRUTES'!Z$3:Z$42)/1000,0)),"—")} -> -3.10 | I4: — | J4: {=IFERROR(INDEX('DONNÉES BRUTES'!N$3:N$42,MATCH(_xlfn.AGGREGATE(14,6,'DONNÉES BRUTES'!Z$3:Z$42+ROW('DONNÉES BRUTES'!Z$3:Z$42)/1000,1),'DONNÉES BRUTES'!Z$3:Z$42+ROW('DONNÉES BRUTES'!Z$3:Z$42)/1000,0)),"—")} -> 30.4% | K4: {=IFERROR(INDEX('DONNÉES BRUTES'!Q$3:Q$42,MATCH(_xlfn.AGGREGATE(14,6,'DONNÉES BRUTES'!Z$3:Z$42+ROW('DONNÉES BRUTES'!Z$3:Z$42)/1000,1),'DONNÉES BRUTES'!Z$3:Z$42+ROW('DONNÉES BRUTES'!Z$3:Z$42)/1000,0)),"—")} -> +13.6% | L4: — | M4: {=IFERROR(INDEX('DONNÉES BRUTES'!S$3:S$42,MATCH(_xlfn.AGGREGATE(14,6,'DONNÉES BRUTES'!Z$3:Z$42+ROW('DONNÉES BRUTES'!Z$3:Z$42)/1000,1),'DONNÉES BRUTES'!Z$3:Z$42+ROW('DONNÉES BRUTES'!Z$3:Z$42)/1000,0)),"—")} -> 1.60 | O4: =IF(B6<>"—",LEFT(C6,15),"—") -> Unibail-Rodamco | P4: =IF(E6<>"—",VALUE(LEFT(E6,FIND("/",E6)-1)),"") -> 95 | Q4: =IF(F6<>"—",F6,"") -> 1.22 | R4: =IF(H6<>"—",H6,"") -> -2.60
A5: 2 | B5: {=IFERROR(INDEX('DONNÉES BRUTES'!A$3:A$42,MATCH(_xlfn.AGGREGATE(14,6,'DONNÉES BRUTES'!Z$3:Z$42+ROW('DONNÉES BRUTES'!Z$3:Z$42)/1000,2),'DONNÉES BRUTES'!Z$3:Z$42+ROW('DONNÉES BRUTES'!Z$3:Z$42)/1000,0)),"—")} -> SAN.PA | C5: {=IFERROR(INDEX('DONNÉES BRUTES'!B$3:B$42,MATCH(_xlfn.AGGREGATE(14,6,'DONNÉES BRUTES'!Z$3:Z$42+ROW('DONNÉES BRUTES'!Z$3:Z$42)/1000,2),'DONNÉES BRUTES'!Z$3:Z$42+ROW('DONNÉES BRUTES'!Z$3:Z$42)/1000,0)),"—")} -> Sanofi | D5: {=IFERROR(INDEX('DONNÉES BRUTES'!C$3:C$42,MATCH(_xlfn.AGGREGATE(14,6,'DONNÉES BRUTES'!Z$3:Z$42+ROW('DONNÉES BRUTES'!Z$3:Z$42)/1000,2),'DONNÉES BRUTES'!Z$3:Z$42+ROW('DONNÉES BRUTES'!Z$3:Z$42)/1000,0)),"—")} -> Healthcare | E5: {=IFERROR(INDEX('DONNÉES BRUTES'!Z$3:Z$42,MATCH(_xlfn.AGGREGATE(14,6,'DONNÉES BRUTES'!Z$3:Z$42+ROW('DONNÉES BRUTES'!Z$3:Z$42)/1000,2),'DONNÉES BRUTES'!Z$3:Z$42+ROW('DONNÉES BRUTES'!Z$3:Z$42)/1000,0))&"/100","—")} -> 97/100 | F5: {=IFERROR(INDEX('DONNÉES BRUTES'!U$3:U$42,MATCH(_xlfn.AGGREGATE(14,6,'DONNÉES BRUTES'!Z$3:Z$42+ROW('DONNÉES BRUTES'!Z$3:Z$42)/1000,2),'DONNÉES BRUTES'!Z$3:Z$42+ROW('DONNÉES BRUTES'!Z$3:Z$42)/1000,0)),"—")} -> — | G5: — | H5: {=IFERROR(INDEX('DONNÉES BRUTES'!V$3:V$42,MATCH(_xlfn.AGGREGATE(14,6,'DONNÉES BRUTES'!Z$3:Z$42+ROW('DONNÉES BRUTES'!Z$3:Z$42)/1000,2),'DONNÉES BRUTES'!Z$3:Z$42+ROW('DONNÉES BRUTES'!Z$3:Z$42)/1000,0)),"—")} -> -3.00 | I5: — | J5: {=IFERROR(INDEX('DONNÉES BRUTES'!N$3:N$42,MATCH(_xlfn.AGGREGATE(14,6,'DONNÉES BRUTES'!Z$3:Z$42+ROW('DONNÉES BRUTES'!Z$3:Z$42)/1000,2),'DONNÉES BRUTES'!Z$3:Z$42+ROW('DONNÉES BRUTES'!Z$3:Z$42)/1000,0)),"—")} -> 26.7% | K5: {=IFERROR(INDEX('DONNÉES BRUTES'!Q$3:Q$42,MATCH(_xlfn.AGGREGATE(14,6,'DONNÉES BRUTES'!Z$3:Z$42+ROW('DONNÉES BRUTES'!Z$3:Z$42)/1000,2),'DONNÉES BRUTES'!Z$3:Z$42+ROW('DONNÉES BRUTES'!Z$3:Z$42)/1000,0)),"—")} -> +10.9% | L5: — | M5: {=IFERROR(INDEX('DONNÉES BRUTES'!S$3:S$42,MATCH(_xlfn.AGGREGATE(14,6,'DONNÉES BRUTES'!Z$3:Z$42+ROW('DONNÉES BRUTES'!Z$3:Z$42)/1000,2),'DONNÉES BRUTES'!Z$3:Z$42+ROW('DONNÉES BRUTES'!Z$3:Z$42)/1000,0)),"—")} -> 1.09 | O5: =IF(B7<>"—",LEFT(C7,15),"—") -> Crédit Agricole | P5: =IF(E7<>"—",VALUE(LEFT(E7,FIND("/",E7)-1)),"") -> 92 | Q5: =IF(F7<>"—",F7,"") | R5: =IF(H7<>"—",H7,"")
A6: 3 | B6: {=IFERROR(INDEX('DONNÉES BRUTES'!A$3:A$42,MATCH(_xlfn.AGGREGATE(14,6,'DONNÉES BRUTES'!Z$3:Z$42+ROW('DONNÉES BRUTES'!Z$3:Z$42)/1000,3),'DONNÉES BRUTES'!Z$3:Z$42+ROW('DONNÉES BRUTES'!Z$3:Z$42)/1000,0)),"—")} -> URW.PA | C6: {=IFERROR(INDEX('DONNÉES BRUTES'!B$3:B$42,MATCH(_xlfn.AGGREGATE(14,6,'DONNÉES BRUTES'!Z$3:Z$42+ROW('DONNÉES BRUTES'!Z$3:Z$42)/1000,3),'DONNÉES BRUTES'!Z$3:Z$42+ROW('DONNÉES BRUTES'!Z$3:Z$42)/1000,0)),"—")} -> Unibail-Rodamco-Westfield SE | D6: {=IFERROR(INDEX('DONNÉES BRUTES'!C$3:C$42,MATCH(_xlfn.AGGREGATE(14,6,'DONNÉES BRUTES'!Z$3:Z$42+ROW('DONNÉES BRUTES'!Z$3:Z$42)/1000,3),'DONNÉES BRUTES'!Z$3:Z$42+ROW('DONNÉES BRUTES'!Z$3:Z$42)/1000,0)),"—")} -> Real Estate | E6: {=IFERROR(INDEX('DONNÉES BRUTES'!Z$3:Z$42,MATCH(_xlfn.AGGREGATE(14,6,'DONNÉES BRUTES'!Z$3:Z$42+ROW('DONNÉES BRUTES'!Z$3:Z$42)/1000,3),'DONNÉES BRUTES'!Z$3:Z$42+ROW('DONNÉES BRUTES'!Z$3:Z$42)/1000,0))&"/100","—")} -> 95/100 | F6: {=IFERROR(INDEX('DONNÉES BRUTES'!U$3:U$42,MATCH(_xlfn.AGGREGATE(14,6,'DONNÉES BRUTES'!Z$3:Z$42+ROW('DONNÉES BRUTES'!Z$3:Z$42)/1000,3),'DONNÉES BRUTES'!Z$3:Z$42+ROW('DONNÉES BRUTES'!Z$3:Z$42)/1000,0)),"—")} -> 1.22 | G6: — | H6: {=IFERROR(INDEX('DONNÉES BRUTES'!V$3:V$42,MATCH(_xlfn.AGGREGATE(14,6,'DONNÉES BRUTES'!Z$3:Z$42+ROW('DONNÉES BRUTES'!Z$3:Z$42)/1000,3),'DONNÉES BRUTES'!Z$3:Z$42+ROW('DONNÉES BRUTES'!Z$3:Z$42)/1000,0)),"—")} -> -2.60 | I6: — | J6: {=IFERROR(INDEX('DONNÉES BRUTES'!N$3:N$42,MATCH(_xlfn.AGGREGATE(14,6,'DONNÉES BRUTES'!Z$3:Z$42+ROW('DONNÉES BRUTES'!Z$3:Z$42)/1000,3),'DONNÉES BRUTES'!Z$3:Z$42+ROW('DONNÉES BRUTES'!Z$3:Z$42)/1000,0)),"—")} -> 89.1% | K6: {=IFERROR(INDEX('DONNÉES BRUTES'!Q$3:Q$42,MATCH(_xlfn.AGGREGATE(14,6,'DONNÉES BRUTES'!Z$3:Z$42+ROW('DONNÉES BRUTES'!Z$3:Z$42)/1000,3),'DONNÉES BRUTES'!Z$3:Z$42+ROW('DONNÉES BRUTES'!Z$3:Z$42)/1000,0)),"—")} -> +7.2% | L6: — | M6: {=IFERROR(INDEX('DONNÉES BRUTES'!S$3:S$42,MATCH(_xlfn.AGGREGATE(14,6,'DONNÉES BRUTES'!Z$3:Z$42+ROW('DONNÉES BRUTES'!Z$3:Z$42)/1000,3),'DONNÉES BRUTES'!Z$3:Z$42+ROW('DONNÉES BRUTES'!Z$3:Z$42)/1000,0)),"—")} -> 1.27 | O6: =IF(B8<>"—",LEFT(C8,15),"—") -> Hermès Internat | P6: =IF(E8<>"—",VALUE(LEFT(E8,FIND("/",E8)-1)),"") -> 90 | Q6: =IF(F8<>"—",F8,"") -> 9.47 | R6: =IF(H8<>"—",H8,"") -> -3.21
A7: 4 | B7: {=IFERROR(INDEX('DONNÉES BRUTES'!A$3:A$42,MATCH(_xlfn.AGGREGATE(14,6,'DONNÉES BRUTES'!Z$3:Z$42+ROW('DONNÉES BRUTES'!Z$3:Z$42)/1000,4),'DONNÉES BRUTES'!Z$3:Z$42+ROW('DONNÉES BRUTES'!Z$3:Z$42)/1000,0)),"—")} -> ACA.PA | C7: {=IFERROR(INDEX('DONNÉES BRUTES'!B$3:B$42,MATCH(_xlfn.AGGREGATE(14,6,'DONNÉES BRUTES'!Z$3:Z$42+ROW('DONNÉES BRUTES'!Z$3:Z$42)/1000,4),'DONNÉES BRUTES'!Z$3:Z$42+ROW('DONNÉES BRUTES'!Z$3:Z$42)/1000,0)),"—")} -> Crédit Agricole S.A. | D7: {=IFERROR(INDEX('DONNÉES BRUTES'!C$3:C$42,MATCH(_xlfn.AGGREGATE(14,6,'DONNÉES BRUTES'!Z$3:Z$42+ROW('DONNÉES BRUTES'!Z$3:Z$42)/1000,4),'DONNÉES BRUTES'!Z$3:Z$42+ROW('DONNÉES BRUTES'!Z$3:Z$42)/1000,0)),"—")} -> Financials | E7: {=IFERROR(INDEX('DONNÉES BRUTES'!Z$3:Z$42,MATCH(_xlfn.AGGREGATE(14,6,'DONNÉES BRUTES'!Z$3:Z$42+ROW('DONNÉES BRUTES'!Z$3:Z$42)/1000,4),'DONNÉES BRUTES'!Z$3:Z$42+ROW('DONNÉES BRUTES'!Z$3:Z$42)/1000,0))&"/100","—")} -> 92/100 | F7: {=IFERROR(INDEX('DONNÉES BRUTES'!U$3:U$42,MATCH(_xlfn.AGGREGATE(14,6,'DONNÉES BRUTES'!Z$3:Z$42+ROW('DONNÉES BRUTES'!Z$3:Z$42)/1000,4),'DONNÉES BRUTES'!Z$3:Z$42+ROW('DONNÉES BRUTES'!Z$3:Z$42)/1000,0)),"—")} -> — | G7: — | H7: {=IFERROR(INDEX('DONNÉES BRUTES'!V$3:V$42,MATCH(_xlfn.AGGREGATE(14,6,'DONNÉES BRUTES'!Z$3:Z$42+ROW('DONNÉES BRUTES'!Z$3:Z$42)/1000,4),'DONNÉES BRUTES'!Z$3:Z$42+ROW('DONNÉES BRUTES'!Z$3:Z$42)/1000,0)),"—")} -> — | I7: — | J7: {=IFERROR(INDEX('DONNÉES BRUTES'!N$3:N$42,MATCH(_xlfn.AGGREGATE(14,6,'DONNÉES BRUTES'!Z$3:Z$42+ROW('DONNÉES BRUTES'!Z$3:Z$42)/1000,4),'DONNÉES BRUTES'!Z$3:Z$42+ROW('DONNÉES BRUTES'!Z$3:Z$42)/1000,0)),"—")} -> 192.6% | K7: {=IFERROR(INDEX('DONNÉES BRUTES'!Q$3:Q$42,MATCH(_xlfn.AGGREGATE(14,6,'DONNÉES BRUTES'!Z$3:Z$42+ROW('DONNÉES BRUTES'!Z$3:Z$42)/1000,4),'DONNÉES BRUTES'!Z$3:Z$42+ROW('DONNÉES BRUTES'!Z$3:Z$42)/1000,0)),"—")} -> +9.1% | L7: — | M7: {=IFERROR(INDEX('DONNÉES BRUTES'!S$3:S$42,MATCH(_xlfn.AGGREGATE(14,6,'DONNÉES BRUTES'!Z$3:Z$42+ROW('DONNÉES BRUTES'!Z$3:Z$42)/1000,4),'DONNÉES BRUTES'!Z$3:Z$42+ROW('DONNÉES BRUTES'!Z$3:Z$42)/1000,0)),"—")} -> — | O7: =IF(B9<>"—",LEFT(C9,15),"—") -> Kering SA | P7: =IF(E9<>"—",VALUE(LEFT(E9,FIND("/",E9)-1)),"") -> 87 | Q7: =IF(F9<>"—",F9,"") | R7: =IF(H9<>"—",H9,"") -> -3.32
A8: 5 | B8: {=IFERROR(INDEX('DONNÉES BRUTES'!A$3:A$42,MATCH(_xlfn.AGGREGATE(14,6,'DONNÉES BRUTES'!Z$3:Z$42+ROW('DONNÉES BRUTES'!Z$3:Z$42)/1000,5),'DONNÉES BRUTES'!Z$3:Z$42+ROW('DONNÉES BRUTES'!Z$3:Z$42)/1000,0)),"—")} -> RMS.PA | C8: {=IFERROR(INDEX('DONNÉES BRUTES'!B$3:B$42,MATCH(_xlfn.AGGREGATE(14,6,'DONNÉES BRUTES'!Z$3:Z$42+ROW('DONNÉES BRUTES'!Z$3:Z$42)/1000,5),'DONNÉES BRUTES'!Z$3:Z$42+ROW('DONNÉES BRUTES'!Z$3:Z$42)/1000,0)),"—")} -> Hermès International Société en commandite par actions | D8: {=IFERROR(INDEX('DONNÉES BRUTES'!C$3:C$42,MATCH(_xlfn.AGGREGATE(14,6,'DONNÉES BRUTES'!Z$3:Z$42+ROW('DONNÉES BRUTES'!Z$3:Z$42)/1000,5),'DONNÉES BRUTES'!Z$3:Z$42+ROW('DONNÉES BRUTES'!Z$3:Z$42)/1000,0)),"—")} -> Consumer Disc. | E8: {=IFERROR(INDEX('DONNÉES BRUTES'!Z$3:Z$42,MATCH(_xlfn.AGGREGATE(14,6,'DONNÉES BRUTES'!Z$3:Z$42+ROW('DONNÉES BRUTES'!Z$3:Z$42)/1000,5),'DONNÉES BRUTES'!Z$3:Z$42+ROW('DONNÉES BRUTES'!Z$3:Z$42)/1000,0))&"/100","—")} -> 90/100 | F8: {=IFERROR(INDEX('DONNÉES BRUTES'!U$3:U$42,MATCH(_xlfn.AGGREGATE(14,6,'DONNÉES BRUTES'!Z$3:Z$42+ROW('DONNÉES BRUTES'!Z$3:Z$42)/1000,5),'DONNÉES BRUTES'!Z$3:Z$42+ROW('DONNÉES BRUTES'!Z$3:Z$42)/1000,0)),"—")} -> 9.47 | G8: — | H8: {=IFERROR(INDEX('DONNÉES BRUTES'!V$3:V$42,MATCH(_xlfn.AGGREGATE(14,6,'DONNÉES BRUTES'!Z$3:Z$42+ROW('DONNÉES BRUTES'!Z$3:Z$42)/1000,5),'DONNÉES BRUTES'!Z$3:Z$42+ROW('DONNÉES BRUTES'!Z$3:Z$42)/1000,0)),"—")} -> -3.21 | I8: — | J8: {=IFERROR(INDEX('DONNÉES BRUTES'!N$3:N$42,MATCH(_xlfn.AGGREGATE(14,6,'DONNÉES BRUTES'!Z$3:Z$42+ROW('DONNÉES BRUTES'!Z$3:Z$42)/1000,5),'DONNÉES BRUTES'!Z$3:Z$42+ROW('DONNÉES BRUTES'!Z$3:Z$42)/1000,0)),"—")} -> 46.8% | K8: {=IFERROR(INDEX('DONNÉES BRUTES'!Q$3:Q$42,MATCH(_xlfn.AGGREGATE(14,6,'DONNÉES BRUTES'!Z$3:Z$42+ROW('DONNÉES BRUTES'!Z$3:Z$42)/1000,5),'DONNÉES BRUTES'!Z$3:Z$42+ROW('DONNÉES BRUTES'!Z$3:Z$42)/1000,0)),"—")} -> +24.0% | L8: — | M8: {=IFERROR(INDEX('DONNÉES BRUTES'!S$3:S$42,MATCH(_xlfn.AGGREGATE(14,6,'DONNÉES BRUTES'!Z$3:Z$42+ROW('DONNÉES BRUTES'!Z$3:Z$42)/1000,5),'DONNÉES BRUTES'!Z$3:Z$42+ROW('DONNÉES BRUTES'!Z$3:Z$42)/1000,0)),"—")} -> 4.99 | O8: =IF(B10<>"—",LEFT(C10,15),"—") -> L'Oréal S.A. | P8: =IF(E10<>"—",VALUE(LEFT(E10,FIND("/",E10)-1)),"") -> 85 | Q8: =IF(F10<>"—",F10,"") -> 3.38 | R8: =IF(H10<>"—",H10,"") -> -3.16
A9: 6 | B9: {=IFERROR(INDEX('DONNÉES BRUTES'!A$3:A$42,MATCH(_xlfn.AGGREGATE(14,6,'DONNÉES BRUTES'!Z$3:Z$42+ROW('DONNÉES BRUTES'!Z$3:Z$42)/1000,6),'DONNÉES BRUTES'!Z$3:Z$42+ROW('DONNÉES BRUTES'!Z$3:Z$42)/1000,0)),"—")} -> KER.PA | C9: {=IFERROR(INDEX('DONNÉES BRUTES'!B$3:B$42,MATCH(_xlfn.AGGREGATE(14,6,'DONNÉES BRUTES'!Z$3:Z$42+ROW('DONNÉES BRUTES'!Z$3:Z$42)/1000,6),'DONNÉES BRUTES'!Z$3:Z$42+ROW('DONNÉES BRUTES'!Z$3:Z$42)/1000,0)),"—")} -> Kering SA | D9: {=IFERROR(INDEX('DONNÉES BRUTES'!C$3:C$42,MATCH(_xlfn.AGGREGATE(14,6,'DONNÉES BRUTES'!Z$3:Z$42+ROW('DONNÉES BRUTES'!Z$3:Z$42)/1000,6),'DONNÉES BRUTES'!Z$3:Z$42+ROW('DONNÉES BRUTES'!Z$3:Z$42)/1000,0)),"—")} -> Consumer Disc. | E9: {=IFERROR(INDEX('DONNÉES BRUTES'!Z$3:Z$42,MATCH(_xlfn.AGGREGATE(14,6,'DONNÉES BRUTES'!Z$3:Z$42+ROW('DONNÉES BRUTES'!Z$3:Z$42)/1000,6),'DONNÉES BRUTES'!Z$3:Z$42+ROW('DONNÉES BRUTES'!Z$3:Z$42)/1000,0))&"/100","—")} -> 87/100 | F9: {=IFERROR(INDEX('DONNÉES BRUTES'!U$3:U$42,MATCH(_xlfn.AGGREGATE(14,6,'DONNÉES BRUTES'!Z$3:Z$42+ROW('DONNÉES BRUTES'!Z$3:Z$42)/1000,6),'DONNÉES BRUTES'!Z$3:Z$42+ROW('DONNÉES BRUTES'!Z$3:Z$42)/1000,0)),"—")} -> — | G9: — | H9: {=IFERROR(INDEX('DONNÉES BRUTES'!V$3:V$42,MATCH(_xlfn.AGGREGATE(14,6,'DONNÉES BRUTES'!Z$3:Z$42+ROW('DONNÉES BRUTES'!Z$3:Z$42)/1000,6),'DONNÉES BRUTES'!Z$3:Z$42+ROW('DONNÉES BRUTES'!Z$3:Z$42)/1000,0)),"—")} -> -3.32 | I9: — | J9: {=IFERROR(INDEX('DONNÉES BRUTES'!N$3:N$42,MATCH(_xlfn.AGGREGATE(14,6,'DONNÉES BRUTES'!Z$3:Z$42+ROW('DONNÉES BRUTES'!Z$3:Z$42)/1000,6),'DONNÉES BRUTES'!Z$3:Z$42+ROW('DONNÉES BRUTES'!Z$3:Z$42)/1000,0)),"—")} -> 25.0% | K9: {=IFERROR(INDEX('DONNÉES BRUTES'!Q$3:Q$42,MATCH(_xlfn.AGGREGATE(14,6,'DONNÉES BRUTES'!Z$3:Z$42+ROW('DONNÉES BRUTES'!Z$3:Z$42)/1000,6),'DONNÉES BRUTES'!Z$3:Z$42+ROW('DONNÉES BRUTES'!Z$3:Z$42)/1000,0)),"—")} -> +0.5% | L9: — | M9: {=IFERROR(INDEX('DONNÉES BRUTES'!S$3:S$42,MATCH(_xlfn.AGGREGATE(14,6,'DONNÉES BRUTES'!Z$3:Z$42+ROW('DONNÉES BRUTES'!Z$3:Z$42)/1000,6),'DONNÉES BRUTES'!Z$3:Z$42+ROW('DONNÉES BRUTES'!Z$3:Z$42)/1000,0)),"—")} -> 1.99 | O9: =IF(B11<>"—",LEFT(C11,15),"—") -> Bureau Veritas | P9: =IF(E11<>"—",VALUE(LEFT(E11,FIND("/",E11)-1)),"") -> 82 | Q9: =IF(F11<>"—",F11,"") -> 3.10 | R9: =IF(H11<>"—",H11,"") -> -3.04
A10: 7 | B10: {=IFERROR(INDEX('DONNÉES BRUTES'!A$3:A$42,MATCH(_xlfn.AGGREGATE(14,6,'DONNÉES BRUTES'!Z$3:Z$42+ROW('DONNÉES BRUTES'!Z$3:Z$42)/1000,7),'DONNÉES BRUTES'!Z$3:Z$42+ROW('DONNÉES BRUTES'!Z$3:Z$42)/1000,0)),"—")} -> OR.PA | C10: {=IFERROR(INDEX('DONNÉES BRUTES'!B$3:B$42,MATCH(_xlfn.AGGREGATE(14,6,'DONNÉES BRUTES'!Z$3:Z$42+ROW('DONNÉES BRUTES'!Z$3:Z$42)/1000,7),'DONNÉES BRUTES'!Z$3:Z$42+ROW('DONNÉES BRUTES'!Z$3:Z$42)/1000,0)),"—")} -> L'Oréal S.A. | D10: {=IFERROR(INDEX('DONNÉES BRUTES'!C$3:C$42,MATCH(_xlfn.AGGREGATE(14,6,'DONNÉES BRUTES'!Z$3:Z$42+ROW('DONNÉES BRUTES'!Z$3:Z$42)/1000,7),'DONNÉES BRUTES'!Z$3:Z$42+ROW('DONNÉES BRUTES'!Z$3:Z$42)/1000,0)),"—")} -> Consumer Staples | E10: {=IFERROR(INDEX('DONNÉES BRUTES'!Z$3:Z$42,MATCH(_xlfn.AGGREGATE(14,6,'DONNÉES BRUTES'!Z$3:Z$42+ROW('DONNÉES BRUTES'!Z$3:Z$42)/1000,7),'DONNÉES BRUTES'!Z$3:Z$42+ROW('DONNÉES BRUTES'!Z$3:Z$42)/1000,0))&"/100","—")} -> 85/100 | F10: {=IFERROR(INDEX('DONNÉES BRUTES'!U$3:U$42,MATCH(_xlfn.AGGREGATE(14,6,'DONNÉES BRUTES'!Z$3:Z$42+ROW('DONNÉES BRUTES'!Z$3:Z$42)/1000,7),'DONNÉES BRUTES'!Z$3:Z$42+ROW('DONNÉES BRUTES'!Z$3:Z$42)/1000,0)),"—")} -> 3.38 | G10: — | H10: {=IFERROR(INDEX('DONNÉES BRUTES'!V$3:V$42,MATCH(_xlfn.AGGREGATE(14,6,'DONNÉES BRUTES'!Z$3:Z$42+ROW('DONNÉES BRUTES'!Z$3:Z$42)/1000,7),'DONNÉES BRUTES'!Z$3:Z$42+ROW('DONNÉES BRUTES'!Z$3:Z$42)/1000,0)),"—")} -> -3.16 | I10: — | J10: {=IFERROR(INDEX('DONNÉES BRUTES'!N$3:N$42,MATCH(_xlfn.AGGREGATE(14,6,'DONNÉES BRUTES'!Z$3:Z$42+ROW('DONNÉES BRUTES'!Z$3:Z$42)/1000,7),'DONNÉES BRUTES'!Z$3:Z$42+ROW('DONNÉES BRUTES'!Z$3:Z$42)/1000,0)),"—")} -> 24.3% | K10: {=IFERROR(INDEX('DONNÉES BRUTES'!Q$3:Q$42,MATCH(_xlfn.AGGREGATE(14,6,'DONNÉES BRUTES'!Z$3:Z$42+ROW('DONNÉES BRUTES'!Z$3:Z$42)/1000,7),'DONNÉES BRUTES'!Z$3:Z$42+ROW('DONNÉES BRUTES'!Z$3:Z$42)/1000,0)),"—")} -> +17.5% | L10: — | M10: {=IFERROR(INDEX('DONNÉES BRUTES'!S$3:S$42,MATCH(_xlfn.AGGREGATE(14,6,'DONNÉES BRUTES'!Z$3:Z$42+ROW('DONNÉES BRUTES'!Z$3:Z$42)/1000,7),'DONNÉES BRUTES'!Z$3:Z$42+ROW('DONNÉES BRUTES'!Z$3:Z$42)/1000,0)),"—")} -> 1.44 | O10: =IF(B12<>"—",LEFT(C12,15),"—") -> LVMH Moët Henne | P10: =IF(E12<>"—",VALUE(LEFT(E12,FIND("/",E12)-1)),"") -> 79 | Q10: =IF(F12<>"—",F12,"") -> 2.88 | R10: =IF(H12<>"—",H12,"") -> -3.19
A11: 8 | B11: {=IFERROR(INDEX('DONNÉES BRUTES'!A$3:A$42,MATCH(_xlfn.AGGREGATE(14,6,'DONNÉES BRUTES'!Z$3:Z$42+ROW('DONNÉES BRUTES'!Z$3:Z$42)/1000,8),'DONNÉES BRUTES'!Z$3:Z$42+ROW('DONNÉES BRUTES'!Z$3:Z$42)/1000,0)),"—")} -> BVI.PA | C11: {=IFERROR(INDEX('DONNÉES BRUTES'!B$3:B$42,MATCH(_xlfn.AGGREGATE(14,6,'DONNÉES BRUTES'!Z$3:Z$42+ROW('DONNÉES BRUTES'!Z$3:Z$42)/1000,8),'DONNÉES BRUTES'!Z$3:Z$42+ROW('DONNÉES BRUTES'!Z$3:Z$42)/1000,0)),"—")} -> Bureau Veritas SA | D11: {=IFERROR(INDEX('DONNÉES BRUTES'!C$3:C$42,MATCH(_xlfn.AGGREGATE(14,6,'DONNÉES BRUTES'!Z$3:Z$42+ROW('DONNÉES BRUTES'!Z$3:Z$42)/1000,8),'DONNÉES BRUTES'!Z$3:Z$42+ROW('DONNÉES BRUTES'!Z$3:Z$42)/1000,0)),"—")} -> Industrials | E11: {=IFERROR(INDEX('DONNÉES BRUTES'!Z$3:Z$42,MATCH(_xlfn.AGGREGATE(14,6,'DONNÉES BRUTES'!Z$3:Z$42+ROW('DONNÉES BRUTES'!Z$3:Z$42)/1000,8),'DONNÉES BRUTES'!Z$3:Z$42+ROW('DONNÉES BRUTES'!Z$3:Z$42)/1000,0))&"/100","—")} -> 82/100 | F11: {=IFERROR(INDEX('DONNÉES BRUTES'!U$3:U$42,MATCH(_xlfn.AGGREGATE(14,6,'DONNÉES BRUTES'!Z$3:Z$42+ROW('DONNÉES BRUTES'!Z$3:Z$42)/1000,8),'DONNÉES BRUTES'!Z$3:Z$42+ROW('DONNÉES BRUTES'!Z$3:Z$42)/1000,0)),"—")} -> 3.10 | G11: — | H11: {=IFERROR(INDEX('DONNÉES BRUTES'!V$3:V$42,MATCH(_xlfn.AGGREGATE(14,6,'DONNÉES BRUTES'!Z$3:Z$42+ROW('DONNÉES BRUTES'!Z$3:Z$42)/1000,8),'DONNÉES BRUTES'!Z$3:Z$42+ROW('DONNÉES BRUTES'!Z$3:Z$42)/1000,0)),"—")} -> -3.04 | I11: — | J11: {=IFERROR(INDEX('DONNÉES BRUTES'!N$3:N$42,MATCH(_xlfn.AGGREGATE(14,6,'DONNÉES BRUTES'!Z$3:Z$42+ROW('DONNÉES BRUTES'!Z$3:Z$42)/1000,8),'DONNÉES BRUTES'!Z$3:Z$42+ROW('DONNÉES BRUTES'!Z$3:Z$42)/1000,0)),"—")} -> 19.6% | K11: {=IFERROR(INDEX('DONNÉES BRUTES'!Q$3:Q$42,MATCH(_xlfn.AGGREGATE(14,6,'DONNÉES BRUTES'!Z$3:Z$42+ROW('DONNÉES BRUTES'!Z$3:Z$42)/1000,8),'DONNÉES BRUTES'!Z$3:Z$42+ROW('DONNÉES BRUTES'!Z$3:Z$42)/1000,0)),"—")} -> +34.4% | L11: — | M11: {=IFERROR(INDEX('DONNÉES BRUTES'!S$3:S$42,MATCH(_xlfn.AGGREGATE(14,6,'DONNÉES BRUTES'!Z$3:Z$42+ROW('DONNÉES BRUTES'!Z$3:Z$42)/1000,8),'DONNÉES BRUTES'!Z$3:Z$42+ROW('DONNÉES BRUTES'!Z$3:Z$42)/1000,0)),"—")} -> 1.53 | O11: =IF(B13<>"—",LEFT(C13,15),"—") -> L'Air Liquide S | P11: =IF(E13<>"—",VALUE(LEFT(E13,FIND("/",E13)-1)),"") -> 77 | Q11: =IF(F13<>"—",F13,"") -> 3.26 | R11: =IF(H13<>"—",H13,"") -> -3.19
A12: 9 | B12: {=IFERROR(INDEX('DONNÉES BRUTES'!A$3:A$42,MATCH(_xlfn.AGGREGATE(14,6,'DONNÉES BRUTES'!Z$3:Z$42+ROW('DONNÉES BRUTES'!Z$3:Z$42)/1000,9),'DONNÉES BRUTES'!Z$3:Z$42+ROW('DONNÉES BRUTES'!Z$3:Z$42)/1000,0)),"—")} -> MC.PA | C12: {=IFERROR(INDEX('DONNÉES BRUTES'!B$3:B$42,MATCH(_xlfn.AGGREGATE(14,6,'DONNÉES BRUTES'!Z$3:Z$42+ROW('DONNÉES BRUTES'!Z$3:Z$42)/1000,9),'DONNÉES BRUTES'!Z$3:Z$42+ROW('DONNÉES BRUTES'!Z$3:Z$42)/1000,0)),"—")} -> LVMH Moët Hennessy - Louis Vuitton, Société Européenne | D12: {=IFERROR(INDEX('DONNÉES BRUTES'!C$3:C$42,MATCH(_xlfn.AGGREGATE(14,6,'DONNÉES BRUTES'!Z$3:Z$42+ROW('DONNÉES BRUTES'!Z$3:Z$42)/1000,9),'DONNÉES BRUTES'!Z$3:Z$42+ROW('DONNÉES BRUTES'!Z$3:Z$42)/1000,0)),"—")} -> Consumer Disc. | E12: {=IFERROR(INDEX('DONNÉES BRUTES'!Z$3:Z$42,MATCH(_xlfn.AGGREGATE(14,6,'DONNÉES BRUTES'!Z$3:Z$42+ROW('DONNÉES BRUTES'!Z$3:Z$42)/1000,9),'DONNÉES BRUTES'!Z$3:Z$42+ROW('DONNÉES BRUTES'!Z$3:Z$42)/1000,0))&"/100","—")} -> 79/100 | F12: {=IFERROR(INDEX('DONNÉES BRUTES'!U$3:U$42,MATCH(_xlfn.AGGREGATE(14,6,'DONNÉES BRUTES'!Z$3:Z$42+ROW('DONNÉES BRUTES'!Z$3:Z$42)/1000,9),'DONNÉES BRUTES'!Z$3:Z$42+ROW('DONNÉES BRUTES'!Z$3:Z$42)/1000,0)),"—")} -> 2.88 | G12: — | H12: {=IFERROR(INDEX('DONNÉES BRUTES'!V$3:V$42,MATCH(_xlfn.AGGREGATE(14,6,'DONNÉES BRUTES'!Z$3:Z$42+ROW('DONNÉES BRUTES'!Z$3:Z$42)/1000,9),'DONNÉES BRUTES'!Z$3:Z$42+ROW('DONNÉES BRUTES'!Z$3:Z$42)/1000,0)),"—")} -> -3.19 | I12: — | J12: {=IFERROR(INDEX('DONNÉES BRUTES'!N$3:N$42,MATCH(_xlfn.AGGREGATE(14,6,'DONNÉES BRUTES'!Z$3:Z$42+ROW('DONNÉES BRUTES'!Z$3:Z$42)/1000,9),'DONNÉES BRUTES'!Z$3:Z$42+ROW('DONNÉES BRUTES'!Z$3:Z$42)/1000,0)),"—")} -> 32.0% | K12: {=IFERROR(INDEX('DONNÉES BRUTES'!Q$3:Q$42,MATCH(_xlfn.AGGREGATE(14,6,'DONNÉES BRUTES'!Z$3:Z$42+ROW('DONNÉES BRUTES'!Z$3:Z$42)/1000,9),'DONNÉES BRUTES'!Z$3:Z$42+ROW('DONNÉES BRUTES'!Z$3:Z$42)/1000,0)),"—")} -> +16.1% | L12: — | M12: {=IFERROR(INDEX('DONNÉES BRUTES'!S$3:S$42,MATCH(_xlfn.AGGREGATE(14,6,'DONNÉES BRUTES'!Z$3:Z$42+ROW('DONNÉES BRUTES'!Z$3:Z$42)/1000,9),'DONNÉES BRUTES'!Z$3:Z$42+ROW('DONNÉES BRUTES'!Z$3:Z$42)/1000,0)),"—")} -> 1.58
A13: 10 | B13: {=IFERROR(INDEX('DONNÉES BRUTES'!A$3:A$42,MATCH(_xlfn.AGGREGATE(14,6,'DONNÉES BRUTES'!Z$3:Z$42+ROW('DONNÉES BRUTES'!Z$3:Z$42)/1000,10),'DONNÉES BRUTES'!Z$3:Z$42+ROW('DONNÉES BRUTES'!Z$3:Z$42)/1000,0)),"—")} -> AI.PA | C13: {=IFERROR(INDEX('DONNÉES BRUTES'!B$3:B$42,MATCH(_xlfn.AGGREGATE(14,6,'DONNÉES BRUTES'!Z$3:Z$42+ROW('DONNÉES BRUTES'!Z$3:Z$42)/1000,10),'DONNÉES BRUTES'!Z$3:Z$42+ROW('DONNÉES BRUTES'!Z$3:Z$42)/1000,0)),"—")} -> L'Air Liquide S.A. | D13: {=IFERROR(INDEX('DONNÉES BRUTES'!C$3:C$42,MATCH(_xlfn.AGGREGATE(14,6,'DONNÉES BRUTES'!Z$3:Z$42+ROW('DONNÉES BRUTES'!Z$3:Z$42)/1000,10),'DONNÉES BRUTES'!Z$3:Z$42+ROW('DONNÉES BRUTES'!Z$3:Z$42)/1000,0)),"—")} -> Materials | E13: {=IFERROR(INDEX('DONNÉES BRUTES'!Z$3:Z$42,MATCH(_xlfn.AGGREGATE(14,6,'DONNÉES BRUTES'!Z$3:Z$42+ROW('DONNÉES BRUTES'!Z$3:Z$42)/1000,10),'DONNÉES BRUTES'!Z$3:Z$42+ROW('DONNÉES BRUTES'!Z$3:Z$42)/1000,0))&"/100","—")} -> 77/100 | F13: {=IFERROR(INDEX('DONNÉES BRUTES'!U$3:U$42,MATCH(_xlfn.AGGREGATE(14,6,'DONNÉES BRUTES'!Z$3:Z$42+ROW('DONNÉES BRUTES'!Z$3:Z$42)/1000,10),'DONNÉES BRUTES'!Z$3:Z$42+ROW('DONNÉES BRUTES'!Z$3:Z$42)/1000,0)),"—")} -> 3.26 | G13: — | H13: {=IFERROR(INDEX('DONNÉES BRUTES'!V$3:V$42,MATCH(_xlfn.AGGREGATE(14,6,'DONNÉES BRUTES'!Z$3:Z$42+ROW('DONNÉES BRUTES'!Z$3:Z$42)/1000,10),'DONNÉES BRUTES'!Z$3:Z$42+ROW('DONNÉES BRUTES'!Z$3:Z$42)/1000,0)),"—")} -> -3.19 | I13: — | J13: {=IFERROR(INDEX('DONNÉES BRUTES'!N$3:N$42,MATCH(_xlfn.AGGREGATE(14,6,'DONNÉES BRUTES'!Z$3:Z$42+ROW('DONNÉES BRUTES'!Z$3:Z$42)/1000,10),'DONNÉES BRUTES'!Z$3:Z$42+ROW('DONNÉES BRUTES'!Z$3:Z$42)/1000,0)),"—")} -> 27.9% | K13: {=IFERROR(INDEX('DONNÉES BRUTES'!Q$3:Q$42,MATCH(_xlfn.AGGREGATE(14,6,'DONNÉES BRUTES'!Z$3:Z$42+ROW('DONNÉES BRUTES'!Z$3:Z$42)/1000,10),'DONNÉES BRUTES'!Z$3:Z$42+ROW('DONNÉES BRUTES'!Z$3:Z$42)/1000,0)),"—")} -> +13.4% | L13: — | M13: {=IFERROR(INDEX('DONNÉES BRUTES'!S$3:S$42,MATCH(_xlfn.AGGREGATE(14,6,'DONNÉES BRUTES'!Z$3:Z$42+ROW('DONNÉES BRUTES'!Z$3:Z$42)/1000,10),'DONNÉES BRUTES'!Z$3:Z$42+ROW('DONNÉES BRUTES'!Z$3:Z$42)/1000,0)),"—")} -> 1.17
A14: 11 | B14: {=IFERROR(INDEX('DONNÉES BRUTES'!A$3:A$42,MATCH(_xlfn.AGGREGATE(14,6,'DONNÉES BRUTES'!Z$3:Z$42+ROW('DONNÉES BRUTES'!Z$3:Z$42)/1000,11),'DONNÉES BRUTES'!Z$3:Z$42+ROW('DONNÉES BRUTES'!Z$3:Z$42)/1000,0)),"—")} -> RI.PA | C14: {=IFERROR(INDEX('DONNÉES BRUTES'!B$3:B$42,MATCH(_xlfn.AGGREGATE(14,6,'DONNÉES BRUTES'!Z$3:Z$42+ROW('DONNÉES BRUTES'!Z$3:Z$42)/1000,11),'DONNÉES BRUTES'!Z$3:Z$42+ROW('DONNÉES BRUTES'!Z$3:Z$42)/1000,0)),"—")} -> Pernod Ricard SA | D14: {=IFERROR(INDEX('DONNÉES BRUTES'!C$3:C$42,MATCH(_xlfn.AGGREGATE(14,6,'DONNÉES BRUTES'!Z$3:Z$42+ROW('DONNÉES BRUTES'!Z$3:Z$42)/1000,11),'DONNÉES BRUTES'!Z$3:Z$42+ROW('DONNÉES BRUTES'!Z$3:Z$42)/1000,0)),"—")} -> Consumer Staples | E14: {=IFERROR(INDEX('DONNÉES BRUTES'!Z$3:Z$42,MATCH(_xlfn.AGGREGATE(14,6,'DONNÉES BRUTES'!Z$3:Z$42+ROW('DONNÉES BRUTES'!Z$3:Z$42)/1000,11),'DONNÉES BRUTES'!Z$3:Z$42+ROW('DONNÉES BRUTES'!Z$3:Z$42)/1000,0))&"/100","—")} -> 74/100 | F14: {=IFERROR(INDEX('DONNÉES BRUTES'!U$3:U$42,MATCH(_xlfn.AGGREGATE(14,6,'DONNÉES BRUTES'!Z$3:Z$42+ROW('DONNÉES BRUTES'!Z$3:Z$42)/1000,11),'DONNÉES BRUTES'!Z$3:Z$42+ROW('DONNÉES BRUTES'!Z$3:Z$42)/1000,0)),"—")} -> 3.35 | G14: — | H14: {=IFERROR(INDEX('DONNÉES BRUTES'!V$3:V$42,MATCH(_xlfn.AGGREGATE(14,6,'DONNÉES BRUTES'!Z$3:Z$42+ROW('DONNÉES BRUTES'!Z$3:Z$42)/1000,11),'DONNÉES BRUTES'!Z$3:Z$42+ROW('DONNÉES BRUTES'!Z$3:Z$42)/1000,0)),"—")} -> -3.11 | I14: — | J14: {=IFERROR(INDEX('DONNÉES BRUTES'!N$3:N$42,MATCH(_xlfn.AGGREGATE(14,6,'DONNÉES BRUTES'!Z$3:Z$42+ROW('DONNÉES BRUTES'!Z$3:Z$42)/1000,11),'DONNÉES BRUTES'!Z$3:Z$42+ROW('DONNÉES BRUTES'!Z$3:Z$42)/1000,0)),"—")} -> 29.1% | K14: {=IFERROR(INDEX('DONNÉES BRUTES'!Q$3:Q$42,MATCH(_xlfn.AGGREGATE(14,6,'DONNÉES BRUTES'!Z$3:Z$42+ROW('DONNÉES BRUTES'!Z$3:Z$42)/1000,11),'DONNÉES BRUTES'!Z$3:Z$42+ROW('DONNÉES BRUTES'!Z$3:Z$42)/1000,0)),"—")} -> +10.7% | L14: — | M14: {=IFERROR(INDEX('DONNÉES BRUTES'!S$3:S$42,MATCH(_xlfn.AGGREGATE(14,6,'DONNÉES BRUTES'!Z$3:Z$42+ROW('DONNÉES BRUTES'!Z$3:Z$42)/1000,11),'DONNÉES BRUTES'!Z$3:Z$42+ROW('DONNÉES BRUTES'!Z$3:Z$42)/1000,0)),"—")} -> 1.92
A15: 12 | B15: {=IFERROR(INDEX('DONNÉES BRUTES'!A$3:A$42,MATCH(_xlfn.AGGREGATE(14,6,'DONNÉES BRUTES'!Z$3:Z$42+ROW('DONNÉES BRUTES'!Z$3:Z$42)/1000,12),'DONNÉES BRUTES'!Z$3:Z$42+ROW('DONNÉES BRUTES'!Z$3:Z$42)/1000,0)),"—")} -> ERF.PA | C15: {=IFERROR(INDEX('DONNÉES BRUTES'!B$3:B$42,MATCH(_xlfn.AGGREGATE(14,6,'DONNÉES BRUTES'!Z$3:Z$42+ROW('DONNÉES BRUTES'!Z$3:Z$42)/1000,12),'DONNÉES BRUTES'!Z$3:Z$42+ROW('DONNÉES BRUTES'!Z$3:Z$42)/1000,0)),"—")} -> Eurofins Scientific SE | D15: {=IFERROR(INDEX('DONNÉES BRUTES'!C$3:C$42,MATCH(_xlfn.AGGREGATE(14,6,'DONNÉES BRUTES'!Z$3:Z$42+ROW('DONNÉES BRUTES'!Z$3:Z$42)/1000,12),'DONNÉES BRUTES'!Z$3:Z$42+ROW('DONNÉES BRUTES'!Z$3:Z$42)/1000,0)),"—")} -> Healthcare | E15: {=IFERROR(INDEX('DONNÉES BRUTES'!Z$3:Z$42,MATCH(_xlfn.AGGREGATE(14,6,'DONNÉES BRUTES'!Z$3:Z$42+ROW('DONNÉES BRUTES'!Z$3:Z$42)/1000,12),'DONNÉES BRUTES'!Z$3:Z$42+ROW('DONNÉES BRUTES'!Z$3:Z$42)/1000,0))&"/100","—")} -> 72/100 | F15: {=IFERROR(INDEX('DONNÉES BRUTES'!U$3:U$42,MATCH(_xlfn.AGGREGATE(14,6,'DONNÉES BRUTES'!Z$3:Z$42+ROW('DONNÉES BRUTES'!Z$3:Z$42)/1000,12),'DONNÉES BRUTES'!Z$3:Z$42+ROW('DONNÉES BRUTES'!Z$3:Z$42)/1000,0)),"—")} -> 2.27 | G15: — | H15: {=IFERROR(INDEX('DONNÉES BRUTES'!V$3:V$42,MATCH(_xlfn.AGGREGATE(14,6,'DONNÉES BRUTES'!Z$3:Z$42+ROW('DONNÉES BRUTES'!Z$3:Z$42)/1000,12),'DONNÉES BRUTES'!Z$3:Z$42+ROW('DONNÉES BRUTES'!Z$3:Z$42)/1000,0)),"—")} -> -3.13 | I15: — | J15: {=IFERROR(INDEX('DONNÉES BRUTES'!N$3:N$42,MATCH(_xlfn.AGGREGATE(14,6,'DONNÉES BRUTES'!Z$3:Z$42+ROW('DONNÉES BRUTES'!Z$3:Z$42)/1000,12),'DONNÉES BRUTES'!Z$3:Z$42+ROW('DONNÉES BRUTES'!Z$3:Z$42)/1000,0)),"—")} -> 21.0% | K15: {=IFERROR(INDEX('DONNÉES BRUTES'!Q$3:Q$42,MATCH(_xlfn.AGGREGATE(14,6,'DONNÉES BRUTES'!Z$3:Z$42+ROW('DONNÉES BRUTES'!Z$3:Z$42)/1000,12),'DONNÉES BRUTES'!Z$3:Z$42+ROW('DONNÉES BRUTES'!Z$3:Z$42)/1000,0)),"—")} -> +10.5% | L15: — | M15: {=IFERROR(INDEX('DONNÉES BRUTES'!S$3:S$42,MATCH(_xlfn.AGGREGATE(14,6,'DONNÉES BRUTES'!Z$3:Z$42+ROW('DONNÉES BRUTES'!Z$3:Z$42)/1000,12),'DONNÉES BRUTES'!Z$3:Z$42+ROW('DONNÉES BRUTES'!Z$3:Z$42)/1000,0)),"—")} -> 1.09
A16: 13 | B16: {=IFERROR(INDEX('DONNÉES BRUTES'!A$3:A$42,MATCH(_xlfn.AGGREGATE(14,6,'DONNÉES BRUTES'!Z$3:Z$42+ROW('DONNÉES BRUTES'!Z$3:Z$42)/1000,13),'DONNÉES BRUTES'!Z$3:Z$42+ROW('DONNÉES BRUTES'!Z$3:Z$42)/1000,0)),"—")} -> SU.PA | C16: {=IFERROR(INDEX('DONNÉES BRUTES'!B$3:B$42,MATCH(_xlfn.AGGREGATE(14,6,'DONNÉES BRUTES'!Z$3:Z$42+ROW('DONNÉES BRUTES'!Z$3:Z$42)/1000,13),'DONNÉES BRUTES'!Z$3:Z$42+ROW('DONNÉES BRUTES'!Z$3:Z$42)/1000,0)),"—")} -> Schneider Electric S.E. | D16: {=IFERROR(INDEX('DONNÉES BRUTES'!C$3:C$42,MATCH(_xlfn.AGGREGATE(14,6,'DONNÉES BRUTES'!Z$3:Z$42+ROW('DONNÉES BRUTES'!Z$3:Z$42)/1000,13),'DONNÉES BRUTES'!Z$3:Z$42+ROW('DONNÉES BRUTES'!Z$3:Z$42)/1000,0)),"—")} -> Industrials | E16: {=IFERROR(INDEX('DONNÉES BRUTES'!Z$3:Z$42,MATCH(_xlfn.AGGREGATE(14,6,'DONNÉES BRUTES'!Z$3:Z$42+ROW('DONNÉES BRUTES'!Z$3:Z$42)/1000,13),'DONNÉES BRUTES'!Z$3:Z$42+ROW('DONNÉES BRUTES'!Z$3:Z$42)/1000,0))&"/100","—")} -> 69/100 | F16: {=IFERROR(INDEX('DONNÉES BRUTES'!U$3:U$42,MATCH(_xlfn.AGGREGATE(14,6,'DONNÉES BRUTES'!Z$3:Z$42+ROW('DONNÉES BRUTES'!Z$3:Z$42)/1000,13),'DONNÉES BRUTES'!Z$3:Z$42+ROW('DONNÉES BRUTES'!Z$3:Z$42)/1000,0)),"—")} -> — | G16: — | H16: {=IFERROR(INDEX('DONNÉES BRUTES'!V$3:V$42,MATCH(_xlfn.AGGREGATE(14,6,'DONNÉES BRUTES'!Z$3:Z$42+ROW('DONNÉES BRUTES'!Z$3:Z$42)/1000,13),'DONNÉES BRUTES'!Z$3:Z$42+ROW('DONNÉES BRUTES'!Z$3:Z$42)/1000,0)),"—")} -> -3.08 | I16: — | J16: {=IFERROR(INDEX('DONNÉES BRUTES'!N$3:N$42,MATCH(_xlfn.AGGREGATE(14,6,'DONNÉES BRUTES'!Z$3:Z$42+ROW('DONNÉES BRUTES'!Z$3:Z$42)/1000,13),'DONNÉES BRUTES'!Z$3:Z$42+ROW('DONNÉES BRUTES'!Z$3:Z$42)/1000,0)),"—")} -> 20.9% | K16: {=IFERROR(INDEX('DONNÉES BRUTES'!Q$3:Q$42,MATCH(_xlfn.AGGREGATE(14,6,'DONNÉES BRUTES'!Z$3:Z$42+ROW('DONNÉES BRUTES'!Z$3:Z$42)/1000,13),'DONNÉES BRUTES'!Z$3:Z$42+ROW('DONNÉES BRUTES'!Z$3:Z$42)/1000,0)),"—")} -> +17.2% | L16: — | M16: {=IFERROR(INDEX('DONNÉES BRUTES'!S$3:S$42,MATCH(_xlfn.AGGREGATE(14,6,'DONNÉES BRUTES'!Z$3:Z$42+ROW('DONNÉES BRUTES'!Z$3:Z$42)/1000,13),'DONNÉES BRUTES'!Z$3:Z$42+ROW('DONNÉES BRUTES'!Z$3:Z$42)/1000,0)),"—")} -> 1.19
A17: 14 | B17: {=IFERROR(INDEX('DONNÉES BRUTES'!A$3:A$42,MATCH(_xlfn.AGGREGATE(14,6,'DONNÉES BRUTES'!Z$3:Z$42+ROW('DONNÉES BRUTES'!Z$3:Z$42)/1000,14),'DONNÉES BRUTES'!Z$3:Z$42+ROW('DONNÉES BRUTES'!Z$3:Z$42)/1000,0)),"—")} -> SAF.PA | C17: {=IFERROR(INDEX('DONNÉES BRUTES'!B$3:B$42,MATCH(_xlfn.AGGREGATE(14,6,'DONNÉES BRUTES'!Z$3:Z$42+ROW('DONNÉES BRUTES'!Z$3:Z$42)/1000,14),'DONNÉES BRUTES'!Z$3:Z$42+ROW('DONNÉES BRUTES'!Z$3:Z$42)/1000,0)),"—")} -> Safran SA | D17: {=IFERROR(INDEX('DONNÉES BRUTES'!C$3:C$42,MATCH(_xlfn.AGGREGATE(14,6,'DONNÉES BRUTES'!Z$3:Z$42+ROW('DONNÉES BRUTES'!Z$3:Z$42)/1000,14),'DONNÉES BRUTES'!Z$3:Z$42+ROW('DONNÉES BRUTES'!Z$3:Z$42)/1000,0)),"—")} -> Industrials | E17: {=IFERROR(INDEX('DONNÉES BRUTES'!Z$3:Z$42,MATCH(_xlfn.AGGREGATE(14,6,'DONNÉES BRUTES'!Z$3:Z$42+ROW('DONNÉES BRUTES'!Z$3:Z$42)/1000,14),'DONNÉES BRUTES'!Z$3:Z$42+ROW('DONNÉES BRUTES'!Z$3:Z$42)/1000,0))&"/100","—")} -> 67/100 | F17: {=IFERROR(INDEX('DONNÉES BRUTES'!U$3:U$42,MATCH(_xlfn.AGGREGATE(14,6,'DONNÉES BRUTES'!Z$3:Z$42+ROW('DONNÉES BRUTES'!Z$3:Z$42)/1000,14),'DONNÉES BRUTES'!Z$3:Z$42+ROW('DONNÉES BRUTES'!Z$3:Z$42)/1000,0)),"—")} -> 1.54 | G17: — | H17: {=IFERROR(INDEX('DONNÉES BRUTES'!V$3:V$42,MATCH(_xlfn.AGGREGATE(14,6,'DONNÉES BRUTES'!Z$3:Z$42+ROW('DONNÉES BRUTES'!Z$3:Z$42)/1000,14),'DONNÉES BRUTES'!Z$3:Z$42+ROW('DONNÉES BRUTES'!Z$3:Z$42)/1000,0)),"—")} -> -2.91 | I17: — | J17: {=IFERROR(INDEX('DONNÉES BRUTES'!N$3:N$42,MATCH(_xlfn.AGGREGATE(14,6,'DONNÉES BRUTES'!Z$3:Z$42+ROW('DONNÉES BRUTES'!Z$3:Z$42)/1000,14),'DONNÉES BRUTES'!Z$3:Z$42+ROW('DONNÉES BRUTES'!Z$3:Z$42)/1000,0)),"—")} -> 39.2% | K17: {=IFERROR(INDEX('DONNÉES BRUTES'!Q$3:Q$42,MATCH(_xlfn.AGGREGATE(14,6,'DONNÉES BRUTES'!Z$3:Z$42+ROW('DONNÉES BRUTES'!Z$3:Z$42)/1000,14),'DONNÉES BRUTES'!Z$3:Z$42+ROW('DONNÉES BRUTES'!Z$3:Z$42)/1000,0)),"—")} -> +48.4% | L17: — | M17: {=IFERROR(INDEX('DONNÉES BRUTES'!S$3:S$42,MATCH(_xlfn.AGGREGATE(14,6,'DONNÉES BRUTES'!Z$3:Z$42+ROW('DONNÉES BRUTES'!Z$3:Z$42)/1000,14),'DONNÉES BRUTES'!Z$3:Z$42+ROW('DONNÉES BRUTES'!Z$3:Z$42)/1000,0)),"—")} -> 0.93
A18: 15 | B18: {=IFERROR(INDEX('DONNÉES BRUTES'!A$3:A$42,MATCH(_xlfn.AGGREGATE(14,6,'DONNÉES BRUTES'!Z$3:Z$42+ROW('DONNÉES BRUTES'!Z$3:Z$42)/1000,15),'DONNÉES BRUTES'!Z$3:Z$42+ROW('DONNÉES BRUTES'!Z$3:Z$42)/1000,0)),"—")} -> BNP.PA | C18: {=IFERROR(INDEX('DONNÉES BRUTES'!B$3:B$42,MATCH(_xlfn.AGGREGATE(14,6,'DONNÉES BRUTES'!Z$3:Z$42+ROW('DONNÉES BRUTES'!Z$3:Z$42)/1000,15),'DONNÉES BRUTES'!Z$3:Z$42+ROW('DONNÉES BRUTES'!Z$3:Z$42)/1000,0)),"—")} -> BNP Paribas SA | D18: {=IFERROR(INDEX('DONNÉES BRUTES'!C$3:C$42,MATCH(_xlfn.AGGREGATE(14,6,'DONNÉES BRUTES'!Z$3:Z$42+ROW('DONNÉES BRUTES'!Z$3:Z$42)/1000,15),'DONNÉES BRUTES'!Z$3:Z$42+ROW('DONNÉES BRUTES'!Z$3:Z$42)/1000,0)),"—")} -> Financials | E18: {=IFERROR(INDEX('DONNÉES BRUTES'!Z$3:Z$42,MATCH(_xlfn.AGGREGATE(14,6,'DONNÉES BRUTES'!Z$3:Z$42+ROW('DONNÉES BRUTES'!Z$3:Z$42)/1000,15),'DONNÉES BRUTES'!Z$3:Z$42+ROW('DONNÉES BRUTES'!Z$3:Z$42)/1000,0))&"/100","—")} -> 64/100 | F18: {=IFERROR(INDEX('DONNÉES BRUTES'!U$3:U$42,MATCH(_xlfn.AGGREGATE(14,6,'DONNÉES BRUTES'!Z$3:Z$42+ROW('DONNÉES BRUTES'!Z$3:Z$42)/1000,15),'DONNÉES BRUTES'!Z$3:Z$42+ROW('DONNÉES BRUTES'!Z$3:Z$42)/1000,0)),"—")} -> — | G18: — | H18: {=IFERROR(INDEX('DONNÉES BRUTES'!V$3:V$42,MATCH(_xlfn.AGGREGATE(14,6,'DONNÉES BRUTES'!Z$3:Z$42+ROW('DONNÉES BRUTES'!Z$3:Z$42)/1000,15),'DONNÉES BRUTES'!Z$3:Z$42+ROW('DONNÉES BRUTES'!Z$3:Z$42)/1000,0)),"—")} -> — | I18: — | J18: {=IFERROR(INDEX('DONNÉES BRUTES'!N$3:N$42,MATCH(_xlfn.AGGREGATE(14,6,'DONNÉES BRUTES'!Z$3:Z$42+ROW('DONNÉES BRUTES'!Z$3:Z$42)/1000,15),'DONNÉES BRUTES'!Z$3:Z$42+ROW('DONNÉES BRUTES'!Z$3:Z$42)/1000,0)),"—")} -> 108.7% | K18: {=IFERROR(INDEX('DONNÉES BRUTES'!Q$3:Q$42,MATCH(_xlfn.AGGREGATE(14,6,'DONNÉES BRUTES'!Z$3:Z$42+ROW('DONNÉES BRUTES'!Z$3:Z$42)/1000,15),'DONNÉES BRUTES'!Z$3:Z$42+ROW('DONNÉES BRUTES'!Z$3:Z$42)/1000,0)),"—")} -> +9.7% | L18: — | M18: {=IFERROR(INDEX('DONNÉES BRUTES'!S$3:S$42,MATCH(_xlfn.AGGREGATE(14,6,'DONNÉES BRUTES'!Z$3:Z$42+ROW('DONNÉES BRUTES'!Z$3:Z$42)/1000,15),'DONNÉES BRUTES'!Z$3:Z$42+ROW('DONNÉES BRUTES'!Z$3:Z$42)/1000,0)),"—")} -> —

Sheet MOMENTUM
A1: FinSight IA · Analyse MOMENTUM · CAC 40 · 22/03/2026 | O1: Société | P1: Score Mom
A2: Usage confidentiel · Calculs Python/NumPy depuis cache Supabase | O2: =IF(B4<>"—",LEFT(C4,18),"—") -> Alstom SA | P2: =IF(E4<>"—",VALUE(LEFT(E4,FIND("/",E4)-1)),"") -> 100
A3: Rang | B3: Ticker | C3: Société | D3: Secteur | E3: Score | F3: Momentum 52W | G3: Cours actuel (€) | H3: Mkt Cap (Mds€) | I3: Score Global | J3: Next Earnings | K3: Signal | O3: =IF(B5<>"—",LEFT(C5,18),"—") -> Airbus SE | P3: =IF(E5<>"—",VALUE(LEFT(E5,FIND("/",E5)-1)),"") -> 97
A4: 1 | B4: {=IFERROR(INDEX('DONNÉES BRUTES'!A$3:A$42,MATCH(_xlfn.AGGREGATE(14,6,'DONNÉES BRUTES'!AA$3:AA$42+ROW('DONNÉES BRUTES'!AA$3:AA$42)/1000,1),'DONNÉES BRUTES'!AA$3:AA$42+ROW('DONNÉES BRUTES'!AA$3:AA$42)/1000,0)),"—")} -> ALO.PA | C4: {=IFERROR(INDEX('DONNÉES BRUTES'!B$3:B$42,MATCH(_xlfn.AGGREGATE(14,6,'DONNÉES BRUTES'!AA$3:AA$42+ROW('DONNÉES BRUTES'!AA$3:AA$42)/1000,1),'DONNÉES BRUTES'!AA$3:AA$42+ROW('DONNÉES BRUTES'!AA$3:AA$42)/1000,0)),"—")} -> Alstom SA | D4: {=IFERROR(INDEX('DONNÉES BRUTES'!C$3:C$42,MATCH(_xlfn.AGGREGATE(14,6,'DONNÉES BRUTES'!AA$3:AA$42+ROW('DONNÉES BRUTES'!AA$3:AA$42)/1000,1),'DONNÉES BRUTES'!AA$3:AA$42+ROW('DONNÉES BRUTES'!AA$3:AA$42)/1000,0)),"—")} -> Industrials | E4: {=IFERROR(INDEX('DONNÉES BRUTES'!AA$3:AA$42,MATCH(_xlfn.AGGREGATE(14,6,'DONNÉES BRUTES'!AA$3:AA$42+ROW('DONNÉES BRUTES'!AA$3:AA$42)/1000,1),'DONNÉES BRUTES'!AA$3:AA$42+ROW('DONNÉES BRUTES'!AA$3:AA$42)/1000,0))&"/100","—")} -> 100/100 | F4: {=IFERROR(INDEX('DONNÉES BRUTES'!W$3:W$42,MATCH(_xlfn.AGGREGATE(14,6,'DONNÉES BRUTES'!AA$3:AA$42+ROW('DONNÉES BRUTES'!AA$3:AA$42)/1000,1),'DONNÉES BRUTES'!AA$3:AA$42+ROW('DONNÉES BRUTES'!AA$3:AA$42)/1000,0)),"—")} -> nan% | G4: {=IFERROR(INDEX('DONNÉES BRUTES'!D$3:D$42,MATCH(_xlfn.AGGREGATE(14,6,'DONNÉES BRUTES'!AA$3:AA$42+ROW('DONNÉES BRUTES'!AA$3:AA$42)/1000,1),'DONNÉES BRUTES'!AA$3:AA$42+ROW('DONNÉES BRUTES'!AA$3:AA$42)/1000,0)),"—")} -> — | H4: {=IFERROR(INDEX('DONNÉES BRUTES'!E$3:E$42,MATCH(_xlfn.AGGREGATE(14,6,'DONNÉES BRUTES'!AA$3:AA$42+ROW('DONNÉES BRUTES'!AA$3:AA$42)/1000,1),'DONNÉES BRUTES'!AA$3:AA$42+ROW('DONNÉES BRUTES'!AA$3:AA$42)/1000,0)),"—")} -> — | I4: {=IFERROR(INDEX('DONNÉES BRUTES'!AB$3:AB$42,MATCH(_xlfn.AGGREGATE(14,6,'DONNÉES BRUTES'!AA$3:AA$42+ROW('DONNÉES BRUTES'!AA$3:AA$42)/1000,1),'DONNÉES BRUTES'!AA$3:AA$42+ROW('DONNÉES BRUTES'!AA$3:AA$42)/1000,0)),"—")} -> 70 | J4: {=IFERROR(INDEX('DONNÉES BRUTES'!AC$3:AC$42,MATCH(_xlfn.AGGREGATE(14,6,'DONNÉES BRUTES'!AA$3:AA$42+ROW('DONNÉES BRUTES'!AA$3:AA$42)/1000,1),'DONNÉES BRUTES'!AA$3:AA$42+ROW('DONNÉES BRUTES'!AA$3:AA$42)/1000,0)),"—")} -> 2026-05-13 | K4: {=IFERROR(INDEX('DONNÉES BRUTES'!AD$3:AD$42,MATCH(_xlfn.AGGREGATE(14,6,'DONNÉES BRUTES'!AA$3:AA$42+ROW('DONNÉES BRUTES'!AA$3:AA$42)/1000,1),'DONNÉES BRUTES'!AA$3:AA$42+ROW('DONNÉES BRUTES'!AA$3:AA$42)/1000,0)),"—")} -> Neutre | O4: =IF(B6<>"—",LEFT(C6,18),"—") -> BNP Paribas SA | P4: =IF(E6<>"—",VALUE(LEFT(E6,FIND("/",E6)-1)),"") -> 95
A5: 2 | B5: {=IFERROR(INDEX('DONNÉES BRUTES'!A$3:A$42,MATCH(_xlfn.AGGREGATE(14,6,'DONNÉES BRUTES'!AA$3:AA$42+ROW('DONNÉES BRUTES'!AA$3:AA$42)/1000,2),'DONNÉES BRUTES'!AA$3:AA$42+ROW('DONNÉES BRUTES'!AA$3:AA$42)/1000,0)),"—")} -> AIR.PA | C5: {=IFERROR(INDEX('DONNÉES BRUTES'!B$3:B$42,MATCH(_xlfn.AGGREGATE(14,6,'DONNÉES BRUTES'!AA$3:AA$42+ROW('DONNÉES BRUTES'!AA$3:AA$42)/1000,2),'DONNÉES BRUTES'!AA$3:AA$42+ROW('DONNÉES BRUTES'!AA$3:AA$42)/1000,0)),"—")} -> Airbus SE | D5: {=IFERROR(INDEX('DONNÉES BRUTES'!C$3:C$42,MATCH(_xlfn.AGGREGATE(14,6,'DONNÉES BRUTES'!AA$3:AA$42+ROW('DONNÉES BRUTES'!AA$3:AA$42)/1000,2),'DONNÉES BRUTES'!AA$3:AA$42+ROW('DONNÉES BRUTES'!AA$3:AA$42)/1000,0)),"—")} -> Industrials | E5: {=IFERROR(INDEX('DONNÉES BRUTES'!AA$3:AA$42,MATCH(_xlfn.AGGREGATE(14,6,'DONNÉES BRUTES'!AA$3:AA$42+ROW('DONNÉES BRUTES'!AA$3:AA$42)/1000,2),'DONNÉES BRUTES'!AA$3:AA$42+ROW('DONNÉES BRUTES'!AA$3:AA$42)/1000,0))&"/100","—")} -> 97/100 | F5: {=IFERROR(INDEX('DONNÉES BRUTES'!W$3:W$42,MATCH(_xlfn.AGGREGATE(14,6,'DONNÉES BRUTES'!AA$3:AA$42+ROW('DONNÉES BRUTES'!AA$3:AA$42)/1000,2),'DONNÉES BRUTES'!AA$3:AA$42+ROW('DONNÉES BRUTES'!AA$3:AA$42)/1000,0)),"—")} -> nan% | G5: {=IFERROR(INDEX('DONNÉES BRUTES'!D$3:D$42,MATCH(_xlfn.AGGREGATE(14,6,'DONNÉES BRUTES'!AA$3:AA$42+ROW('DONNÉES BRUTES'!AA$3:AA$42)/1000,2),'DONNÉES BRUTES'!AA$3:AA$42+ROW('DONNÉES BRUTES'!AA$3:AA$42)/1000,0)),"—")} -> — | H5: {=IFERROR(INDEX('DONNÉES BRUTES'!E$3:E$42,MATCH(_xlfn.AGGREGATE(14,6,'DONNÉES BRUTES'!AA$3:AA$42+ROW('DONNÉES BRUTES'!AA$3:AA$42)/1000,2),'DONNÉES BRUTES'!AA$3:AA$42+ROW('DONNÉES BRUTES'!AA$3:AA$42)/1000,0)),"—")} -> — | I5: {=IFERROR(INDEX('DONNÉES BRUTES'!AB$3:AB$42,MATCH(_xlfn.AGGREGATE(14,6,'DONNÉES BRUTES'!AA$3:AA$42+ROW('DONNÉES BRUTES'!AA$3:AA$42)/1000,2),'DONNÉES BRUTES'!AA$3:AA$42+ROW('DONNÉES BRUTES'!AA$3:AA$42)/1000,0)),"—")} -> 68 | J5: {=IFERROR(INDEX('DONNÉES BRUTES'!AC$3:AC$42,MATCH(_xlfn.AGGREGATE(14,6,'DONNÉES BRUTES'!AA$3:AA$42+ROW('DONNÉES BRUTES'!AA$3:AA$42)/1000,2),'DONNÉES BRUTES'!AA$3:AA$42+ROW('DONNÉES BRUTES'!AA$3:AA$42)/1000,0)),"—")} -> 2026-04-28 | K5: {=IFERROR(INDEX('DONNÉES BRUTES'!AD$3:AD$42,MATCH(_xlfn.AGGREGATE(14,6,'DONNÉES BRUTES'!AA$3:AA$42+ROW('DONNÉES BRUTES'!AA$3:AA$42)/1000,2),'DONNÉES BRUTES'!AA$3:AA$42+ROW('DONNÉES BRUTES'!AA$3:AA$42)/1000,0)),"—")} -> Neutre | O5: =IF(B7<>"—",LEFT(C7,18),"—") -> AXA SA | P5: =IF(E7<>"—",VALUE(LEFT(E7,FIND("/",E7)-1)),"") -> 92
A6: 3 | B6: {=IFERROR(INDEX('DONNÉES BRUTES'!A$3:A$42,MATCH(_xlfn.AGGREGATE(14,6,'DONNÉES BRUTES'!AA$3:AA$42+ROW('DONNÉES BRUTES'!AA$3:AA$42)/1000,3),'DONNÉES BRUTES'!AA$3:AA$42+ROW('DONNÉES BRUTES'!AA$3:AA$42)/1000,0)),"—")} -> BNP.PA | C6: {=IFERROR(INDEX('DONNÉES BRUTES'!B$3:B$42,MATCH(_xlfn.AGGREGATE(14,6,'DONNÉES BRUTES'!AA$3:AA$42+ROW('DONNÉES BRUTES'!AA$3:AA$42)/1000,3),'DONNÉES BRUTES'!AA$3:AA$42+ROW('DONNÉES BRUTES'!AA$3:AA$42)/1000,0)),"—")} -> BNP Paribas SA | D6: {=IFERROR(INDEX('DONNÉES BRUTES'!C$3:C$42,MATCH(_xlfn.AGGREGATE(14,6,'DONNÉES BRUTES'!AA$3:AA$42+ROW('DONNÉES BRUTES'!AA$3:AA$42)/1000,3),'DONNÉES BRUTES'!AA$3:AA$42+ROW('DONNÉES BRUTES'!AA$3:AA$42)/1000,0)),"—")} -> Financials | E6: {=IFERROR(INDEX('DONNÉES BRUTES'!AA$3:AA$42,MATCH(_xlfn.AGGREGATE(14,6,'DONNÉES BRUTES'!AA$3:AA$42+ROW('DONNÉES BRUTES'!AA$3:AA$42)/1000,3),'DONNÉES BRUTES'!AA$3:AA$42+ROW('DONNÉES BRUTES'!AA$3:AA$42)/1000,0))&"/100","—")} -> 95/100 | F6: {=IFERROR(INDEX('DONNÉES BRUTES'!W$3:W$42,MATCH(_xlfn.AGGREGATE(14,6,'DONNÉES BRUTES'!AA$3:AA$42+ROW('DONNÉES BRUTES'!AA$3:AA$42)/1000,3),'DONNÉES BRUTES'!AA$3:AA$42+ROW('DONNÉES BRUTES'!AA$3:AA$42)/1000,0)),"—")} -> nan% | G6: {=IFERROR(INDEX('DONNÉES BRUTES'!D$3:D$42,MATCH(_xlfn.AGGREGATE(14,6,'DONNÉES BRUTES'!AA$3:AA$42+ROW('DONNÉES BRUTES'!AA$3:AA$42)/1000,3),'DONNÉES BRUTES'!AA$3:AA$42+ROW('DONNÉES BRUTES'!AA$3:AA$42)/1000,0)),"—")} -> — | H6: {=IFERROR(INDEX('DONNÉES BRUTES'!E$3:E$42,MATCH(_xlfn.AGGREGATE(14,6,'DONNÉES BRUTES'!AA$3:AA$42+ROW('DONNÉES BRUTES'!AA$3:AA$42)/1000,3),'DONNÉES BRUTES'!AA$3:AA$42+ROW('DONNÉES BRUTES'!AA$3:AA$42)/1000,0)),"—")} -> — | I6: {=IFERROR(INDEX('DONNÉES BRUTES'!AB$3:AB$42,MATCH(_xlfn.AGGREGATE(14,6,'DONNÉES BRUTES'!AA$3:AA$42+ROW('DONNÉES BRUTES'!AA$3:AA$42)/1000,3),'DONNÉES BRUTES'!AA$3:AA$42+ROW('DONNÉES BRUTES'!AA$3:AA$42)/1000,0)),"—")} -> 62 | J6: {=IFERROR(INDEX('DONNÉES BRUTES'!AC$3:AC$42,MATCH(_xlfn.AGGREGATE(14,6,'DONNÉES BRUTES'!AA$3:AA$42+ROW('DONNÉES BRUTES'!AA$3:AA$42)/1000,3),'DONNÉES BRUTES'!AA$3:AA$42+ROW('DONNÉES BRUTES'!AA$3:AA$42)/1000,0)),"—")} -> 2026-04-30 | K6: {=IFERROR(INDEX('DONNÉES BRUTES'!AD$3:AD$42,MATCH(_xlfn.AGGREGATE(14,6,'DONNÉES BRUTES'!AA$3:AA$42+ROW('DONNÉES BRUTES'!AA$3:AA$42)/1000,3),'DONNÉES BRUTES'!AA$3:AA$42+ROW('DONNÉES BRUTES'!AA$3:AA$42)/1000,0)),"—")} -> Neutre | O6: =IF(B8<>"—",LEFT(C8,18),"—") -> L'Air Liquide S.A. | P6: =IF(E8<>"—",VALUE(LEFT(E8,FIND("/",E8)-1)),"") -> 90
A7: 4 | B7: {=IFERROR(INDEX('DONNÉES BRUTES'!A$3:A$42,MATCH(_xlfn.AGGREGATE(14,6,'DONNÉES BRUTES'!AA$3:AA$42+ROW('DONNÉES BRUTES'!AA$3:AA$42)/1000,4),'DONNÉES BRUTES'!AA$3:AA$42+ROW('DONNÉES BRUTES'!AA$3:AA$42)/1000,0)),"—")} -> CS.PA | C7: {=IFERROR(INDEX('DONNÉES BRUTES'!B$3:B$42,MATCH(_xlfn.AGGREGATE(14,6,'DONNÉES BRUTES'!AA$3:AA$42+ROW('DONNÉES BRUTES'!AA$3:AA$42)/1000,4),'DONNÉES BRUTES'!AA$3:AA$42+ROW('DONNÉES BRUTES'!AA$3:AA$42)/1000,0)),"—")} -> AXA SA | D7: {=IFERROR(INDEX('DONNÉES BRUTES'!C$3:C$42,MATCH(_xlfn.AGGREGATE(14,6,'DONNÉES BRUTES'!AA$3:AA$42+ROW('DONNÉES BRUTES'!AA$3:AA$42)/1000,4),'DONNÉES BRUTES'!AA$3:AA$42+ROW('DONNÉES BRUTES'!AA$3:AA$42)/1000,0)),"—")} -> Financials | E7: {=IFERROR(INDEX('DONNÉES BRUTES'!AA$3:AA$42,MATCH(_xlfn.AGGREGATE(14,6,'DONNÉES BRUTES'!AA$3:AA$42+ROW('DONNÉES BRUTES'!AA$3:AA$42)/1000,4),'DONNÉES BRUTES'!AA$3:AA$42+ROW('DONNÉES BRUTES'!AA$3:AA$42)/1000,0))&"/100","—")} -> 92/100 | F7: {=IFERROR(INDEX('DONNÉES BRUTES'!W$3:W$42,MATCH(_xlfn.AGGREGATE(14,6,'DONNÉES BRUTES'!AA$3:AA$42+ROW('DONNÉES BRUTES'!AA$3:AA$42)/1000,4),'DONNÉES BRUTES'!AA$3:AA$42+ROW('DONNÉES BRUTES'!AA$3:AA$42)/1000,0)),"—")} -> nan% | G7: {=IFERROR(INDEX('DONNÉES BRUTES'!D$3:D$42,MATCH(_xlfn.AGGREGATE(14,6,'DONNÉES BRUTES'!AA$3:AA$42+ROW('DONNÉES BRUTES'!AA$3:AA$42)/1000,4),'DONNÉES BRUTES'!AA$3:AA$42+ROW('DONNÉES BRUTES'!AA$3:AA$42)/1000,0)),"—")} -> — | H7: {=IFERROR(INDEX('DONNÉES BRUTES'!E$3:E$42,MATCH(_xlfn.AGGREGATE(14,6,'DONNÉES BRUTES'!AA$3:AA$42+ROW('DONNÉES BRUTES'!AA$3:AA$42)/1000,4),'DONNÉES BRUTES'!AA$3:AA$42+ROW('DONNÉES BRUTES'!AA$3:AA$42)/1000,0)),"—")} -> — | I7: {=IFERROR(INDEX('DONNÉES BRUTES'!AB$3:AB$42,MATCH(_xlfn.AGGREGATE(14,6,'DONNÉES BRUTES'!AA$3:AA$42+ROW('DONNÉES BRUTES'!AA$3:AA$42)/1000,4),'DONNÉES BRUTES'!AA$3:AA$42+ROW('DONNÉES BRUTES'!AA$3:AA$42)/1000,0)),"—")} -> 64 | J7: {=IFERROR(INDEX('DONNÉES BRUTES'!AC$3:AC$42,MATCH(_xlfn.AGGREGATE(14,6,'DONNÉES BRUTES'!AA$3:AA$42+ROW('DONNÉES BRUTES'!AA$3:AA$42)/1000,4),'DONNÉES BRUTES'!AA$3:AA$42+ROW('DONNÉES BRUTES'!AA$3:AA$42)/1000,0)),"—")} -> — | K7: {=IFERROR(INDEX('DONNÉES BRUTES'!AD$3:AD$42,MATCH(_xlfn.AGGREGATE(14,6,'DONNÉES BRUTES'!AA$3:AA$42+ROW('DONNÉES BRUTES'!AA$3:AA$42)/1000,4),'DONNÉES BRUTES'!AA$3:AA$42+ROW('DONNÉES BRUTES'!AA$3:AA$42)/1000,0)),"—")} -> Neutre | O7: =IF(B9<>"—",LEFT(C9,18),"—") -> Capgemini SE | P7: =IF(E9<>"—",VALUE(LEFT(E9,FIND("/",E9)-1)),"") -> 87
A8: 5 | B8: {=IFERROR(INDEX('DONNÉES BRUTES'!A$3:A$42,MATCH(_xlfn.AGGREGATE(14,6,'DONNÉES BRUTES'!AA$3:AA$42+ROW('DONNÉES BRUTES'!AA$3:AA$42)/1000,5),'DONNÉES BRUTES'!AA$3:AA$42+ROW('DONNÉES BRUTES'!AA$3:AA$42)/1000,0)),"—")} -> AI.PA | C8: {=IFERROR(INDEX('DONNÉES BRUTES'!B$3:B$42,MATCH(_xlfn.AGGREGATE(14,6,'DONNÉES BRUTES'!AA$3:AA$42+ROW('DONNÉES BRUTES'!AA$3:AA$42)/1000,5),'DONNÉES BRUTES'!AA$3:AA$42+ROW('DONNÉES BRUTES'!AA$3:AA$42)/1000,0)),"—")} -> L'Air Liquide S.A. | D8: {=IFERROR(INDEX('DONNÉES BRUTES'!C$3:C$42,MATCH(_xlfn.AGGREGATE(14,6,'DONNÉES BRUTES'!AA$3:AA$42+ROW('DONNÉES BRUTES'!AA$3:AA$42)/1000,5),'DONNÉES BRUTES'!AA$3:AA$42+ROW('DONNÉES BRUTES'!AA$3:AA$42)/1000,0)),"—")} -> Materials | E8: {=IFERROR(INDEX('DONNÉES BRUTES'!AA$3:AA$42,MATCH(_xlfn.AGGREGATE(14,6,'DONNÉES BRUTES'!AA$3:AA$42+ROW('DONNÉES BRUTES'!AA$3:AA$42)/1000,5),'DONNÉES BRUTES'!AA$3:AA$42+ROW('DONNÉES BRUTES'!AA$3:AA$42)/1000,0))&"/100","—")} -> 90/100 | F8: {=IFERROR(INDEX('DONNÉES BRUTES'!W$3:W$42,MATCH(_xlfn.AGGREGATE(14,6,'DONNÉES BRUTES'!AA$3:AA$42+ROW('DONNÉES BRUTES'!AA$3:AA$42)/1000,5),'DONNÉES BRUTES'!AA$3:AA$42+ROW('DONNÉES BRUTES'!AA$3:AA$42)/1000,0)),"—")} -> nan% | G8: {=IFERROR(INDEX('DONNÉES BRUTES'!D$3:D$42,MATCH(_xlfn.AGGREGATE(14,6,'DONNÉES BRUTES'!AA$3:AA$42+ROW('DONNÉES BRUTES'!AA$3:AA$42)/1000,5),'DONNÉES BRUTES'!AA$3:AA$42+ROW('DONNÉES BRUTES'!AA$3:AA$42)/1000,0)),"—")} -> — | H8: {=IFERROR(INDEX('DONNÉES BRUTES'!E$3:E$42,MATCH(_xlfn.AGGREGATE(14,6,'DONNÉES BRUTES'!AA$3:AA$42+ROW('DONNÉES BRUTES'!AA$3:AA$42)/1000,5),'DONNÉES BRUTES'!AA$3:AA$42+ROW('DONNÉES BRUTES'!AA$3:AA$42)/1000,0)),"—")} -> — | I8: {=IFERROR(INDEX('DONNÉES BRUTES'!AB$3:AB$42,MATCH(_xlfn.AGGREGATE(14,6,'DONNÉES BRUTES'!AA$3:AA$42+ROW('DONNÉES BRUTES'!AA$3:AA$42)/1000,5),'DONNÉES BRUTES'!AA$3:AA$42+ROW('DONNÉES BRUTES'!AA$3:AA$42)/1000,0)),"—")} -> 74 | J8: {=IFERROR(INDEX('DONNÉES BRUTES'!AC$3:AC$42,MATCH(_xlfn.AGGREGATE(14,6,'DONNÉES BRUTES'!AA$3:AA$42+ROW('DONNÉES BRUTES'!AA$3:AA$42)/1000,5),'DONNÉES BRUTES'!AA$3:AA$42+ROW('DONNÉES BRUTES'!AA$3:AA$42)/1000,0)),"—")} -> — | K8: {=IFERROR(INDEX('DONNÉES BRUTES'!AD$3:AD$42,MATCH(_xlfn.AGGREGATE(14,6,'DONNÉES BRUTES'!AA$3:AA$42+ROW('DONNÉES BRUTES'!AA$3:AA$42)/1000,5),'DONNÉES BRUTES'!AA$3:AA$42+ROW('DONNÉES BRUTES'!AA$3:AA$42)/1000,0)),"—")} -> Neutre | O8: =IF(B10<>"—",LEFT(C10,18),"—") -> Carrefour SA | P8: =IF(E10<>"—",VALUE(LEFT(E10,FIND("/",E10)-1)),"") -> 85
A9: 6 | B9: {=IFERROR(INDEX('DONNÉES BRUTES'!A$3:A$42,MATCH(_xlfn.AGGREGATE(14,6,'DONNÉES BRUTES'!AA$3:AA$42+ROW('DONNÉES BRUTES'!AA$3:AA$42)/1000,6),'DONNÉES BRUTES'!AA$3:AA$42+ROW('DONNÉES BRUTES'!AA$3:AA$42)/1000,0)),"—")} -> CAP.PA | C9: {=IFERROR(INDEX('DONNÉES BRUTES'!B$3:B$42,MATCH(_xlfn.AGGREGATE(14,6,'DONNÉES BRUTES'!AA$3:AA$42+ROW('DONNÉES BRUTES'!AA$3:AA$42)/1000,6),'DONNÉES BRUTES'!AA$3:AA$42+ROW('DONNÉES BRUTES'!AA$3:AA$42)/1000,0)),"—")} -> Capgemini SE | D9: {=IFERROR(INDEX('DONNÉES BRUTES'!C$3:C$42,MATCH(_xlfn.AGGREGATE(14,6,'DONNÉES BRUTES'!AA$3:AA$42+ROW('DONNÉES BRUTES'!AA$3:AA$42)/1000,6),'DONNÉES BRUTES'!AA$3:AA$42+ROW('DONNÉES BRUTES'!AA$3:AA$42)/1000,0)),"—")} -> Technology | E9: {=IFERROR(INDEX('DONNÉES BRUTES'!AA$3:AA$42,MATCH(_xlfn.AGGREGATE(14,6,'DONNÉES BRUTES'!AA$3:AA$42+ROW('DONNÉES BRUTES'!AA$3:AA$42)/1000,6),'DONNÉES BRUTES'!AA$3:AA$42+ROW('DONNÉES BRUTES'!AA$3:AA$42)/1000,0))&"/100","—")} -> 87/100 | F9: {=IFERROR(INDEX('DONNÉES BRUTES'!W$3:W$42,MATCH(_xlfn.AGGREGATE(14,6,'DONNÉES BRUTES'!AA$3:AA$42+ROW('DONNÉES BRUTES'!AA$3:AA$42)/1000,6),'DONNÉES BRUTES'!AA$3:AA$42+ROW('DONNÉES BRUTES'!AA$3:AA$42)/1000,0)),"—")} -> nan% | G9: {=IFERROR(INDEX('DONNÉES BRUTES'!D$3:D$42,MATCH(_xlfn.AGGREGATE(14,6,'DONNÉES BRUTES'!AA$3:AA$42+ROW('DONNÉES BRUTES'!AA$3:AA$42)/1000,6),'DONNÉES BRUTES'!AA$3:AA$42+ROW('DONNÉES BRUTES'!AA$3:AA$42)/1000,0)),"—")} -> — | H9: {=IFERROR(INDEX('DONNÉES BRUTES'!E$3:E$42,MATCH(_xlfn.AGGREGATE(14,6,'DONNÉES BRUTES'!AA$3:AA$42+ROW('DONNÉES BRUTES'!AA$3:AA$42)/1000,6),'DONNÉES BRUTES'!AA$3:AA$42+ROW('DONNÉES BRUTES'!AA$3:AA$42)/1000,0)),"—")} -> — | I9: {=IFERROR(INDEX('DONNÉES BRUTES'!AB$3:AB$42,MATCH(_xlfn.AGGREGATE(14,6,'DONNÉES BRUTES'!AA$3:AA$42+ROW('DONNÉES BRUTES'!AA$3:AA$42)/1000,6),'DONNÉES BRUTES'!AA$3:AA$42+ROW('DONNÉES BRUTES'!AA$3:AA$42)/1000,0)),"—")} -> 53 | J9: {=IFERROR(INDEX('DONNÉES BRUTES'!AC$3:AC$42,MATCH(_xlfn.AGGREGATE(14,6,'DONNÉES BRUTES'!AA$3:AA$42+ROW('DONNÉES BRUTES'!AA$3:AA$42)/1000,6),'DONNÉES BRUTES'!AA$3:AA$42+ROW('DONNÉES BRUTES'!AA$3:AA$42)/1000,0)),"—")} -> — | K9: {=IFERROR(INDEX('DONNÉES BRUTES'!AD$3:AD$42,MATCH(_xlfn.AGGREGATE(14,6,'DONNÉES BRUTES'!AA$3:AA$42+ROW('DONNÉES BRUTES'!AA$3:AA$42)/1000,6),'DONNÉES BRUTES'!AA$3:AA$42+ROW('DONNÉES BRUTES'!AA$3:AA$42)/1000,0)),"—")} -> Sous-pondérer | O9: =IF(B11<>"—",LEFT(C11,18),"—") -> Crédit Agricole S. | P9: =IF(E11<>"—",VALUE(LEFT(E11,FIND("/",E11)-1)),"") -> 82
A10: 7 | B10: {=IFERROR(INDEX('DONNÉES BRUTES'!A$3:A$42,MATCH(_xlfn.AGGREGATE(14,6,'DONNÉES BRUTES'!AA$3:AA$42+ROW('DONNÉES BRUTES'!AA$3:AA$42)/1000,7),'DONNÉES BRUTES'!AA$3:AA$42+ROW('DONNÉES BRUTES'!AA$3:AA$42)/1000,0)),"—")} -> CA.PA | C10: {=IFERROR(INDEX('DONNÉES BRUTES'!B$3:B$42,MATCH(_xlfn.AGGREGATE(14,6,'DONNÉES BRUTES'!AA$3:AA$42+ROW('DONNÉES BRUTES'!AA$3:AA$42)/1000,7),'DONNÉES BRUTES'!AA$3:AA$42+ROW('DONNÉES BRUTES'!AA$3:AA$42)/1000,0)),"—")} -> Carrefour SA | D10: {=IFERROR(INDEX('DONNÉES BRUTES'!C$3:C$42,MATCH(_xlfn.AGGREGATE(14,6,'DONNÉES BRUTES'!AA$3:AA$42+ROW('DONNÉES BRUTES'!AA$3:AA$42)/1000,7),'DONNÉES BRUTES'!AA$3:AA$42+ROW('DONNÉES BRUTES'!AA$3:AA$42)/1000,0)),"—")} -> Consumer Staples | E10: {=IFERROR(INDEX('DONNÉES BRUTES'!AA$3:AA$42,MATCH(_xlfn.AGGREGATE(14,6,'DONNÉES BRUTES'!AA$3:AA$42+ROW('DONNÉES BRUTES'!AA$3:AA$42)/1000,7),'DONNÉES BRUTES'!AA$3:AA$42+ROW('DONNÉES BRUTES'!AA$3:AA$42)/1000,0))&"/100","—")} -> 85/100 | F10: {=IFERROR(INDEX('DONNÉES BRUTES'!W$3:W$42,MATCH(_xlfn.AGGREGATE(14,6,'DONNÉES BRUTES'!AA$3:AA$42+ROW('DONNÉES BRUTES'!AA$3:AA$42)/1000,7),'DONNÉES BRUTES'!AA$3:AA$42+ROW('DONNÉES BRUTES'!AA$3:AA$42)/1000,0)),"—")} -> nan% | G10: {=IFERROR(INDEX('DONNÉES BRUTES'!D$3:D$42,MATCH(_xlfn.AGGREGATE(14,6,'DONNÉES BRUTES'!AA$3:AA$42+ROW('DONNÉES BRUTES'!AA$3:AA$42)/1000,7),'DONNÉES BRUTES'!AA$3:AA$42+ROW('DONNÉES BRUTES'!AA$3:AA$42)/1000,0)),"—")} -> — | H10: {=IFERROR(INDEX('DONNÉES BRUTES'!E$3:E$42,MATCH(_xlfn.AGGREGATE(14,6,'DONNÉES BRUTES'!AA$3:AA$42+ROW('DONNÉES BRUTES'!AA$3:AA$42)/1000,7),'DONNÉES BRUTES'!AA$3:AA$42+ROW('DONNÉES BRUTES'!AA$3:AA$42)/1000,0)),"—")} -> — | I10: {=IFERROR(INDEX('DONNÉES BRUTES'!AB$3:AB$42,MATCH(_xlfn.AGGREGATE(14,6,'DONNÉES BRUTES'!AA$3:AA$42+ROW('DONNÉES BRUTES'!AA$3:AA$42)/1000,7),'DONNÉES BRUTES'!AA$3:AA$42+ROW('DONNÉES BRUTES'!AA$3:AA$42)/1000,0)),"—")} -> 58 | J10: {=IFERROR(INDEX('DONNÉES BRUTES'!AC$3:AC$42,MATCH(_xlfn.AGGREGATE(14,6,'DONNÉES BRUTES'!AA$3:AA$42+ROW('DONNÉES BRUTES'!AA$3:AA$42)/1000,7),'DONNÉES BRUTES'!AA$3:AA$42+ROW('DONNÉES BRUTES'!AA$3:AA$42)/1000,0)),"—")} -> — | K10: {=IFERROR(INDEX('DONNÉES BRUTES'!AD$3:AD$42,MATCH(_xlfn.AGGREGATE(14,6,'DONNÉES BRUTES'!AA$3:AA$42+ROW('DONNÉES BRUTES'!AA$3:AA$42)/1000,7),'DONNÉES BRUTES'!AA$3:AA$42+ROW('DONNÉES BRUTES'!AA$3:AA$42)/1000,0)),"—")} -> Neutre | O10: =IF(B12<>"—",LEFT(C12,18),"—") -> Bouygues SA | P10: =IF(E12<>"—",VALUE(LEFT(E12,FIND("/",E12)-1)),"") -> 79
A11: 8 | B11: {=IFERROR(INDEX('DONNÉES BRUTES'!A$3:A$42,MATCH(_xlfn.AGGREGATE(14,6,'DONNÉES BRUTES'!AA$3:AA$42+ROW('DONNÉES BRUTES'!AA$3:AA$42)/1000,8),'DONNÉES BRUTES'!AA$3:AA$42+ROW('DONNÉES BRUTES'!AA$3:AA$42)/1000,0)),"—")} -> ACA.PA | C11: {=IFERROR(INDEX('DONNÉES BRUTES'!B$3:B$42,MATCH(_xlfn.AGGREGATE(14,6,'DONNÉES BRUTES'!AA$3:AA$42+ROW('DONNÉES BRUTES'!AA$3:AA$42)/1000,8),'DONNÉES BRUTES'!AA$3:AA$42+ROW('DONNÉES BRUTES'!AA$3:AA$42)/1000,0)),"—")} -> Crédit Agricole S.A. | D11: {=IFERROR(INDEX('DONNÉES BRUTES'!C$3:C$42,MATCH(_xlfn.AGGREGATE(14,6,'DONNÉES BRUTES'!AA$3:AA$42+ROW('DONNÉES BRUTES'!AA$3:AA$42)/1000,8),'DONNÉES BRUTES'!AA$3:AA$42+ROW('DONNÉES BRUTES'!AA$3:AA$42)/1000,0)),"—")} -> Financials | E11: {=IFERROR(INDEX('DONNÉES BRUTES'!AA$3:AA$42,MATCH(_xlfn.AGGREGATE(14,6,'DONNÉES BRUTES'!AA$3:AA$42+ROW('DONNÉES BRUTES'!AA$3:AA$42)/1000,8),'DONNÉES BRUTES'!AA$3:AA$42+ROW('DONNÉES BRUTES'!AA$3:AA$42)/1000,0))&"/100","—")} -> 82/100 | F11: {=IFERROR(INDEX('DONNÉES BRUTES'!W$3:W$42,MATCH(_xlfn.AGGREGATE(14,6,'DONNÉES BRUTES'!AA$3:AA$42+ROW('DONNÉES BRUTES'!AA$3:AA$42)/1000,8),'DONNÉES BRUTES'!AA$3:AA$42+ROW('DONNÉES BRUTES'!AA$3:AA$42)/1000,0)),"—")} -> nan% | G11: {=IFERROR(INDEX('DONNÉES BRUTES'!D$3:D$42,MATCH(_xlfn.AGGREGATE(14,6,'DONNÉES BRUTES'!AA$3:AA$42+ROW('DONNÉES BRUTES'!AA$3:AA$42)/1000,8),'DONNÉES BRUTES'!AA$3:AA$42+ROW('DONNÉES BRUTES'!AA$3:AA$42)/1000,0)),"—")} -> — | H11: {=IFERROR(INDEX('DONNÉES BRUTES'!E$3:E$42,MATCH(_xlfn.AGGREGATE(14,6,'DONNÉES BRUTES'!AA$3:AA$42+ROW('DONNÉES BRUTES'!AA$3:AA$42)/1000,8),'DONNÉES BRUTES'!AA$3:AA$42+ROW('DONNÉES BRUTES'!AA$3:AA$42)/1000,0)),"—")} -> — | I11: {=IFERROR(INDEX('DONNÉES BRUTES'!AB$3:AB$42,MATCH(_xlfn.AGGREGATE(14,6,'DONNÉES BRUTES'!AA$3:AA$42+ROW('DONNÉES BRUTES'!AA$3:AA$42)/1000,8),'DONNÉES BRUTES'!AA$3:AA$42+ROW('DONNÉES BRUTES'!AA$3:AA$42)/1000,0)),"—")} -> 65 | J11: {=IFERROR(INDEX('DONNÉES BRUTES'!AC$3:AC$42,MATCH(_xlfn.AGGREGATE(14,6,'DONNÉES BRUTES'!AA$3:AA$42+ROW('DONNÉES BRUTES'!AA$3:AA$42)/1000,8),'DONNÉES BRUTES'!AA$3:AA$42+ROW('DONNÉES BRUTES'!AA$3:AA$42)/1000,0)),"—")} -> 2026-04-30 | K11: {=IFERROR(INDEX('DONNÉES BRUTES'!AD$3:AD$42,MATCH(_xlfn.AGGREGATE(14,6,'DONNÉES BRUTES'!AA$3:AA$42+ROW('DONNÉES BRUTES'!AA$3:AA$42)/1000,8),'DONNÉES BRUTES'!AA$3:AA$42+ROW('DONNÉES BRUTES'!AA$3:AA$42)/1000,0)),"—")} -> Neutre | O11: =IF(B13<>"—",LEFT(C13,18),"—") -> Danone S.A. | P11: =IF(E13<>"—",VALUE(LEFT(E13,FIND("/",E13)-1)),"") -> 77
A12: 9 | B12: {=IFERROR(INDEX('DONNÉES BRUTES'!A$3:A$42,MATCH(_xlfn.AGGREGATE(14,6,'DONNÉES BRUTES'!AA$3:AA$42+ROW('DONNÉES BRUTES'!AA$3:AA$42)/1000,9),'DONNÉES BRUTES'!AA$3:AA$42+ROW('DONNÉES BRUTES'!AA$3:AA$42)/1000,0)),"—")} -> EN.PA | C12: {=IFERROR(INDEX('DONNÉES BRUTES'!B$3:B$42,MATCH(_xlfn.AGGREGATE(14,6,'DONNÉES BRUTES'!AA$3:AA$42+ROW('DONNÉES BRUTES'!AA$3:AA$42)/1000,9),'DONNÉES BRUTES'!AA$3:AA$42+ROW('DONNÉES BRUTES'!AA$3:AA$42)/1000,0)),"—")} -> Bouygues SA | D12: {=IFERROR(INDEX('DONNÉES BRUTES'!C$3:C$42,MATCH(_xlfn.AGGREGATE(14,6,'DONNÉES BRUTES'!AA$3:AA$42+ROW('DONNÉES BRUTES'!AA$3:AA$42)/1000,9),'DONNÉES BRUTES'!AA$3:AA$42+ROW('DONNÉES BRUTES'!AA$3:AA$42)/1000,0)),"—")} -> Industrials | E12: {=IFERROR(INDEX('DONNÉES BRUTES'!AA$3:AA$42,MATCH(_xlfn.AGGREGATE(14,6,'DONNÉES BRUTES'!AA$3:AA$42+ROW('DONNÉES BRUTES'!AA$3:AA$42)/1000,9),'DONNÉES BRUTES'!AA$3:AA$42+ROW('DONNÉES BRUTES'!AA$3:AA$42)/1000,0))&"/100","—")} -> 79/100 | F12: {=IFERROR(INDEX('DONNÉES BRUTES'!W$3:W$42,MATCH(_xlfn.AGGREGATE(14,6,'DONNÉES BRUTES'!AA$3:AA$42+ROW('DONNÉES BRUTES'!AA$3:AA$42)/1000,9),'DONNÉES BRUTES'!AA$3:AA$42+ROW('DONNÉES BRUTES'!AA$3:AA$42)/1000,0)),"—")} -> nan% | G12: {=IFERROR(INDEX('DONNÉES BRUTES'!D$3:D$42,MATCH(_xlfn.AGGREGATE(14,6,'DONNÉES BRUTES'!AA$3:AA$42+ROW('DONNÉES BRUTES'!AA$3:AA$42)/1000,9),'DONNÉES BRUTES'!AA$3:AA$42+ROW('DONNÉES BRUTES'!AA$3:AA$42)/1000,0)),"—")} -> — | H12: {=IFERROR(INDEX('DONNÉES BRUTES'!E$3:E$42,MATCH(_xlfn.AGGREGATE(14,6,'DONNÉES BRUTES'!AA$3:AA$42+ROW('DONNÉES BRUTES'!AA$3:AA$42)/1000,9),'DONNÉES BRUTES'!AA$3:AA$42+ROW('DONNÉES BRUTES'!AA$3:AA$42)/1000,0)),"—")} -> — | I12: {=IFERROR(INDEX('DONNÉES BRUTES'!AB$3:AB$42,MATCH(_xlfn.AGGREGATE(14,6,'DONNÉES BRUTES'!AA$3:AA$42+ROW('DONNÉES BRUTES'!AA$3:AA$42)/1000,9),'DONNÉES BRUTES'!AA$3:AA$42+ROW('DONNÉES BRUTES'!AA$3:AA$42)/1000,0)),"—")} -> 57 | J12: {=IFERROR(INDEX('DONNÉES BRUTES'!AC$3:AC$42,MATCH(_xlfn.AGGREGATE(14,6,'DONNÉES BRUTES'!AA$3:AA$42+ROW('DONNÉES BRUTES'!AA$3:AA$42)/1000,9),'DONNÉES BRUTES'!AA$3:AA$42+ROW('DONNÉES BRUTES'!AA$3:AA$42)/1000,0)),"—")} -> 2026-05-07 | K12: {=IFERROR(INDEX('DONNÉES BRUTES'!AD$3:AD$42,MATCH(_xlfn.AGGREGATE(14,6,'DONNÉES BRUTES'!AA$3:AA$42+ROW('DONNÉES BRUTES'!AA$3:AA$42)/1000,9),'DONNÉES BRUTES'!AA$3:AA$42+ROW('DONNÉES BRUTES'!AA$3:AA$42)/1000,0)),"—")} -> Neutre
A13: 10 | B13: {=IFERROR(INDEX('DONNÉES BRUTES'!A$3:A$42,MATCH(_xlfn.AGGREGATE(14,6,'DONNÉES BRUTES'!AA$3:AA$42+ROW('DONNÉES BRUTES'!AA$3:AA$42)/1000,10),'DONNÉES BRUTES'!AA$3:AA$42+ROW('DONNÉES BRUTES'!AA$3:AA$42)/1000,0)),"—")} -> BN.PA | C13: {=IFERROR(INDEX('DONNÉES BRUTES'!B$3:B$42,MATCH(_xlfn.AGGREGATE(14,6,'DONNÉES BRUTES'!AA$3:AA$42+ROW('DONNÉES BRUTES'!AA$3:AA$42)/1000,10),'DONNÉES BRUTES'!AA$3:AA$42+ROW('DONNÉES BRUTES'!AA$3:AA$42)/1000,0)),"—")} -> Danone S.A. | D13: {=IFERROR(INDEX('DONNÉES BRUTES'!C$3:C$42,MATCH(_xlfn.AGGREGATE(14,6,'DONNÉES BRUTES'!AA$3:AA$42+ROW('DONNÉES BRUTES'!AA$3:AA$42)/1000,10),'DONNÉES BRUTES'!AA$3:AA$42+ROW('DONNÉES BRUTES'!AA$3:AA$42)/1000,0)),"—")} -> Consumer Staples | E13: {=IFERROR(INDEX('DONNÉES BRUTES'!AA$3:AA$42,MATCH(_xlfn.AGGREGATE(14,6,'DONNÉES BRUTES'!AA$3:AA$42+ROW('DONNÉES BRUTES'!AA$3:AA$42)/1000,10),'DONNÉES BRUTES'!AA$3:AA$42+ROW('DONNÉES BRUTES'!AA$3:AA$42)/1000,0))&"/100","—")} -> 77/100 | F13: {=IFERROR(INDEX('DONNÉES BRUTES'!W$3:W$42,MATCH(_xlfn.AGGREGATE(14,6,'DONNÉES BRUTES'!AA$3:AA$42+ROW('DONNÉES BRUTES'!AA$3:AA$42)/1000,10),'DONNÉES BRUTES'!AA$3:AA$42+ROW('DONNÉES BRUTES'!AA$3:AA$42)/1000,0)),"—")} -> nan% | G13: {=IFERROR(INDEX('DONNÉES BRUTES'!D$3:D$42,MATCH(_xlfn.AGGREGATE(14,6,'DONNÉES BRUTES'!AA$3:AA$42+ROW('DONNÉES BRUTES'!AA$3:AA$42)/1000,10),'DONNÉES BRUTES'!AA$3:AA$42+ROW('DONNÉES BRUTES'!AA$3:AA$42)/1000,0)),"—")} -> — | H13: {=IFERROR(INDEX('DONNÉES BRUTES'!E$3:E$42,MATCH(_xlfn.AGGREGATE(14,6,'DONNÉES BRUTES'!AA$3:AA$42+ROW('DONNÉES BRUTES'!AA$3:AA$42)/1000,10),'DONNÉES BRUTES'!AA$3:AA$42+ROW('DONNÉES BRUTES'!AA$3:AA$42)/1000,0)),"—")} -> — | I13: {=IFERROR(INDEX('DONNÉES BRUTES'!AB$3:AB$42,MATCH(_xlfn.AGGREGATE(14,6,'DONNÉES BRUTES'!AA$3:AA$42+ROW('DONNÉES BRUTES'!AA$3:AA$42)/1000,10),'DONNÉES BRUTES'!AA$3:AA$42+ROW('DONNÉES BRUTES'!AA$3:AA$42)/1000,0)),"—")} -> 52 | J13: {=IFERROR(INDEX('DONNÉES BRUTES'!AC$3:AC$42,MATCH(_xlfn.AGGREGATE(14,6,'DONNÉES BRUTES'!AA$3:AA$42+ROW('DONNÉES BRUTES'!AA$3:AA$42)/1000,10),'DONNÉES BRUTES'!AA$3:AA$42+ROW('DONNÉES BRUTES'!AA$3:AA$42)/1000,0)),"—")} -> — | K13: {=IFERROR(INDEX('DONNÉES BRUTES'!AD$3:AD$42,MATCH(_xlfn.AGGREGATE(14,6,'DONNÉES BRUTES'!AA$3:AA$42+ROW('DONNÉES BRUTES'!AA$3:AA$42)/1000,10),'DONNÉES BRUTES'!AA$3:AA$42+ROW('DONNÉES BRUTES'!AA$3:AA$42)/1000,0)),"—")} -> Sous-pondérer
A14: 11 | B14: {=IFERROR(INDEX('DONNÉES BRUTES'!A$3:A$42,MATCH(_xlfn.AGGREGATE(14,6,'DONNÉES BRUTES'!AA$3:AA$42+ROW('DONNÉES BRUTES'!AA$3:AA$42)/1000,11),'DONNÉES BRUTES'!AA$3:AA$42+ROW('DONNÉES BRUTES'!AA$3:AA$42)/1000,0)),"—")} -> DSY.PA | C14: {=IFERROR(INDEX('DONNÉES BRUTES'!B$3:B$42,MATCH(_xlfn.AGGREGATE(14,6,'DONNÉES BRUTES'!AA$3:AA$42+ROW('DONNÉES BRUTES'!AA$3:AA$42)/1000,11),'DONNÉES BRUTES'!AA$3:AA$42+ROW('DONNÉES BRUTES'!AA$3:AA$42)/1000,0)),"—")} -> Dassault Systèmes SE | D14: {=IFERROR(INDEX('DONNÉES BRUTES'!C$3:C$42,MATCH(_xlfn.AGGREGATE(14,6,'DONNÉES BRUTES'!AA$3:AA$42+ROW('DONNÉES BRUTES'!AA$3:AA$42)/1000,11),'DONNÉES BRUTES'!AA$3:AA$42+ROW('DONNÉES BRUTES'!AA$3:AA$42)/1000,0)),"—")} -> Technology | E14: {=IFERROR(INDEX('DONNÉES BRUTES'!AA$3:AA$42,MATCH(_xlfn.AGGREGATE(14,6,'DONNÉES BRUTES'!AA$3:AA$42+ROW('DONNÉES BRUTES'!AA$3:AA$42)/1000,11),'DONNÉES BRUTES'!AA$3:AA$42+ROW('DONNÉES BRUTES'!AA$3:AA$42)/1000,0))&"/100","—")} -> 74/100 | F14: {=IFERROR(INDEX('DONNÉES BRUTES'!W$3:W$42,MATCH(_xlfn.AGGREGATE(14,6,'DONNÉES BRUTES'!AA$3:AA$42+ROW('DONNÉES BRUTES'!AA$3:AA$42)/1000,11),'DONNÉES BRUTES'!AA$3:AA$42+ROW('DONNÉES BRUTES'!AA$3:AA$42)/1000,0)),"—")} -> nan% | G14: {=IFERROR(INDEX('DONNÉES BRUTES'!D$3:D$42,MATCH(_xlfn.AGGREGATE(14,6,'DONNÉES BRUTES'!AA$3:AA$42+ROW('DONNÉES BRUTES'!AA$3:AA$42)/1000,11),'DONNÉES BRUTES'!AA$3:AA$42+ROW('DONNÉES BRUTES'!AA$3:AA$42)/1000,0)),"—")} -> — | H14: {=IFERROR(INDEX('DONNÉES BRUTES'!E$3:E$42,MATCH(_xlfn.AGGREGATE(14,6,'DONNÉES BRUTES'!AA$3:AA$42+ROW('DONNÉES BRUTES'!AA$3:AA$42)/1000,11),'DONNÉES BRUTES'!AA$3:AA$42+ROW('DONNÉES BRUTES'!AA$3:AA$42)/1000,0)),"—")} -> — | I14: {=IFERROR(INDEX('DONNÉES BRUTES'!AB$3:AB$42,MATCH(_xlfn.AGGREGATE(14,6,'DONNÉES BRUTES'!AA$3:AA$42+ROW('DONNÉES BRUTES'!AA$3:AA$42)/1000,11),'DONNÉES BRUTES'!AA$3:AA$42+ROW('DONNÉES BRUTES'!AA$3:AA$42)/1000,0)),"—")} -> 72 | J14: {=IFERROR(INDEX('DONNÉES BRUTES'!AC$3:AC$42,MATCH(_xlfn.AGGREGATE(14,6,'DONNÉES BRUTES'!AA$3:AA$42+ROW('DONNÉES BRUTES'!AA$3:AA$42)/1000,11),'DONNÉES BRUTES'!AA$3:AA$42+ROW('DONNÉES BRUTES'!AA$3:AA$42)/1000,0)),"—")} -> 2026-04-23 | K14: {=IFERROR(INDEX('DONNÉES BRUTES'!AD$3:AD$42,MATCH(_xlfn.AGGREGATE(14,6,'DONNÉES BRUTES'!AA$3:AA$42+ROW('DONNÉES BRUTES'!AA$3:AA$42)/1000,11),'DONNÉES BRUTES'!AA$3:AA$42+ROW('DONNÉES BRUTES'!AA$3:AA$42)/1000,0)),"—")} -> Neutre
A15: 12 | B15: {=IFERROR(INDEX('DONNÉES BRUTES'!A$3:A$42,MATCH(_xlfn.AGGREGATE(14,6,'DONNÉES BRUTES'!AA$3:AA$42+ROW('DONNÉES BRUTES'!AA$3:AA$42)/1000,12),'DONNÉES BRUTES'!AA$3:AA$42+ROW('DONNÉES BRUTES'!AA$3:AA$42)/1000,0)),"—")} -> ENGI.PA | C15: {=IFERROR(INDEX('DONNÉES BRUTES'!B$3:B$42,MATCH(_xlfn.AGGREGATE(14,6,'DONNÉES BRUTES'!AA$3:AA$42+ROW('DONNÉES BRUTES'!AA$3:AA$42)/1000,12),'DONNÉES BRUTES'!AA$3:AA$42+ROW('DONNÉES BRUTES'!AA$3:AA$42)/1000,0)),"—")} -> Engie SA | D15: {=IFERROR(INDEX('DONNÉES BRUTES'!C$3:C$42,MATCH(_xlfn.AGGREGATE(14,6,'DONNÉES BRUTES'!AA$3:AA$42+ROW('DONNÉES BRUTES'!AA$3:AA$42)/1000,12),'DONNÉES BRUTES'!AA$3:AA$42+ROW('DONNÉES BRUTES'!AA$3:AA$42)/1000,0)),"—")} -> Utilities | E15: {=IFERROR(INDEX('DONNÉES BRUTES'!AA$3:AA$42,MATCH(_xlfn.AGGREGATE(14,6,'DONNÉES BRUTES'!AA$3:AA$42+ROW('DONNÉES BRUTES'!AA$3:AA$42)/1000,12),'DONNÉES BRUTES'!AA$3:AA$42+ROW('DONNÉES BRUTES'!AA$3:AA$42)/1000,0))&"/100","—")} -> 72/100 | F15: {=IFERROR(INDEX('DONNÉES BRUTES'!W$3:W$42,MATCH(_xlfn.AGGREGATE(14,6,'DONNÉES BRUTES'!AA$3:AA$42+ROW('DONNÉES BRUTES'!AA$3:AA$42)/1000,12),'DONNÉES BRUTES'!AA$3:AA$42+ROW('DONNÉES BRUTES'!AA$3:AA$42)/1000,0)),"—")} -> nan% | G15: {=IFERROR(INDEX('DONNÉES BRUTES'!D$3:D$42,MATCH(_xlfn.AGGREGATE(14,6,'DONNÉES BRUTES'!AA$3:AA$42+ROW('DONNÉES BRUTES'!AA$3:AA$42)/1000,12),'DONNÉES BRUTES'!AA$3:AA$42+ROW('DONNÉES BRUTES'!AA$3:AA$42)/1000,0)),"—")} -> — | H15: {=IFERROR(INDEX('DONNÉES BRUTES'!E$3:E$42,MATCH(_xlfn.AGGREGATE(14,6,'DONNÉES BRUTES'!AA$3:AA$42+ROW('DONNÉES BRUTES'!AA$3:AA$42)/1000,12),'DONNÉES BRUTES'!AA$3:AA$42+ROW('DONNÉES BRUTES'!AA$3:AA$42)/1000,0)),"—")} -> — | I15: {=IFERROR(INDEX('DONNÉES BRUTES'!AB$3:AB$42,MATCH(_xlfn.AGGREGATE(14,6,'DONNÉES BRUTES'!AA$3:AA$42+ROW('DONNÉES BRUTES'!AA$3:AA$42)/1000,12),'DONNÉES BRUTES'!AA$3:AA$42+ROW('DONNÉES BRUTES'!AA$3:AA$42)/1000,0)),"—")} -> 46 | J15: {=IFERROR(INDEX('DONNÉES BRUTES'!AC$3:AC$42,MATCH(_xlfn.AGGREGATE(14,6,'DONNÉES BRUTES'!AA$3:AA$42+ROW('DONNÉES BRUTES'!AA$3:AA$42)/1000,12),'DONNÉES BRUTES'!AA$3:AA$42+ROW('DONNÉES BRUTES'!AA$3:AA$42)/1000,0)),"—")} -> 2026-05-07 | K15: {=IFERROR(INDEX('DONNÉES BRUTES'!AD$3:AD$42,MATCH(_xlfn.AGGREGATE(14,6,'DONNÉES BRUTES'!AA$3:AA$42+ROW('DONNÉES BRUTES'!AA$3:AA$42)/1000,12),'DONNÉES BRUTES'!AA$3:AA$42+ROW('DONNÉES BRUTES'!AA$3:AA$42)/1000,0)),"—")} -> Sous-pondérer
A16: 13 | B16: {=IFERROR(INDEX('DONNÉES BRUTES'!A$3:A$42,MATCH(_xlfn.AGGREGATE(14,6,'DONNÉES BRUTES'!AA$3:AA$42+ROW('DONNÉES BRUTES'!AA$3:AA$42)/1000,13),'DONNÉES BRUTES'!AA$3:AA$42+ROW('DONNÉES BRUTES'!AA$3:AA$42)/1000,0)),"—")} -> EL.PA | C16: {=IFERROR(INDEX('DONNÉES BRUTES'!B$3:B$42,MATCH(_xlfn.AGGREGATE(14,6,'DONNÉES BRUTES'!AA$3:AA$42+ROW('DONNÉES BRUTES'!AA$3:AA$42)/1000,13),'DONNÉES BRUTES'!AA$3:AA$42+ROW('DONNÉES BRUTES'!AA$3:AA$42)/1000,0)),"—")} -> EssilorLuxottica Société anonyme | D16: {=IFERROR(INDEX('DONNÉES BRUTES'!C$3:C$42,MATCH(_xlfn.AGGREGATE(14,6,'DONNÉES BRUTES'!AA$3:AA$42+ROW('DONNÉES BRUTES'!AA$3:AA$42)/1000,13),'DONNÉES BRUTES'!AA$3:AA$42+ROW('DONNÉES BRUTES'!AA$3:AA$42)/1000,0)),"—")} -> Healthcare | E16: {=IFERROR(INDEX('DONNÉES BRUTES'!AA$3:AA$42,MATCH(_xlfn.AGGREGATE(14,6,'DONNÉES BRUTES'!AA$3:AA$42+ROW('DONNÉES BRUTES'!AA$3:AA$42)/1000,13),'DONNÉES BRUTES'!AA$3:AA$42+ROW('DONNÉES BRUTES'!AA$3:AA$42)/1000,0))&"/100","—")} -> 69/100 | F16: {=IFERROR(INDEX('DONNÉES BRUTES'!W$3:W$42,MATCH(_xlfn.AGGREGATE(14,6,'DONNÉES BRUTES'!AA$3:AA$42+ROW('DONNÉES BRUTES'!AA$3:AA$42)/1000,13),'DONNÉES BRUTES'!AA$3:AA$42+ROW('DONNÉES BRUTES'!AA$3:AA$42)/1000,0)),"—")} -> nan% | G16: {=IFERROR(INDEX('DONNÉES BRUTES'!D$3:D$42,MATCH(_xlfn.AGGREGATE(14,6,'DONNÉES BRUTES'!AA$3:AA$42+ROW('DONNÉES BRUTES'!AA$3:AA$42)/1000,13),'DONNÉES BRUTES'!AA$3:AA$42+ROW('DONNÉES BRUTES'!AA$3:AA$42)/1000,0)),"—")} -> — | H16: {=IFERROR(INDEX('DONNÉES BRUTES'!E$3:E$42,MATCH(_xlfn.AGGREGATE(14,6,'DONNÉES BRUTES'!AA$3:AA$42+ROW('DONNÉES BRUTES'!AA$3:AA$42)/1000,13),'DONNÉES BRUTES'!AA$3:AA$42+ROW('DONNÉES BRUTES'!AA$3:AA$42)/1000,0)),"—")} -> — | I16: {=IFERROR(INDEX('DONNÉES BRUTES'!AB$3:AB$42,MATCH(_xlfn.AGGREGATE(14,6,'DONNÉES BRUTES'!AA$3:AA$42+ROW('DONNÉES BRUTES'!AA$3:AA$42)/1000,13),'DONNÉES BRUTES'!AA$3:AA$42+ROW('DONNÉES BRUTES'!AA$3:AA$42)/1000,0)),"—")} -> 64 | J16: {=IFERROR(INDEX('DONNÉES BRUTES'!AC$3:AC$42,MATCH(_xlfn.AGGREGATE(14,6,'DONNÉES BRUTES'!AA$3:AA$42+ROW('DONNÉES BRUTES'!AA$3:AA$42)/1000,13),'DONNÉES BRUTES'!AA$3:AA$42+ROW('DONNÉES BRUTES'!AA$3:AA$42)/1000,0)),"—")} -> — | K16: {=IFERROR(INDEX('DONNÉES BRUTES'!AD$3:AD$42,MATCH(_xlfn.AGGREGATE(14,6,'DONNÉES BRUTES'!AA$3:AA$42+ROW('DONNÉES BRUTES'!AA$3:AA$42)/1000,13),'DONNÉES BRUTES'!AA$3:AA$42+ROW('DONNÉES BRUTES'!AA$3:AA$42)/1000,0)),"—")} -> Neutre
A17: 14 | B17: {=IFERROR(INDEX('DONNÉES BRUTES'!A$3:A$42,MATCH(_xlfn.AGGREGATE(14,6,'DONNÉES BRUTES'!AA$3:AA$42+ROW('DONNÉES BRUTES'!AA$3:AA$42)/1000,14),'DONNÉES BRUTES'!AA$3:AA$42+ROW('DONNÉES BRUTES'!AA$3:AA$42)/1000,0)),"—")} -> ERF.PA | C17: {=IFERROR(INDEX('DONNÉES BRUTES'!B$3:B$42,MATCH(_xlfn.AGGREGATE(14,6,'DONNÉES BRUTES'!AA$3:AA$42+ROW('DONNÉES BRUTES'!AA$3:AA$42)/1000,14),'DONNÉES BRUTES'!AA$3:AA$42+ROW('DONNÉES BRUTES'!AA$3:AA$42)/1000,0)),"—")} -> Eurofins Scientific SE | D17: {=IFERROR(INDEX('DONNÉES BRUTES'!C$3:C$42,MATCH(_xlfn.AGGREGATE(14,6,'DONNÉES BRUTES'!AA$3:AA$42+ROW('DONNÉES BRUTES'!AA$3:AA$42)/1000,14),'DONNÉES BRUTES'!AA$3:AA$42+ROW('DONNÉES BRUTES'!AA$3:AA$42)/1000,0)),"—")} -> Healthcare | E17: {=IFERROR(INDEX('DONNÉES BRUTES'!AA$3:AA$42,MATCH(_xlfn.AGGREGATE(14,6,'DONNÉES BRUTES'!AA$3:AA$42+ROW('DONNÉES BRUTES'!AA$3:AA$42)/1000,14),'DONNÉES BRUTES'!AA$3:AA$42+ROW('DONNÉES BRUTES'!AA$3:AA$42)/1000,0))&"/100","—")} -> 67/100 | F17: {=IFERROR(INDEX('DONNÉES BRUTES'!W$3:W$42,MATCH(_xlfn.AGGREGATE(14,6,'DONNÉES BRUTES'!AA$3:AA$42+ROW('DONNÉES BRUTES'!AA$3:AA$42)/1000,14),'DONNÉES BRUTES'!AA$3:AA$42+ROW('DONNÉES BRUTES'!AA$3:AA$42)/1000,0)),"—")} -> nan% | G17: {=IFERROR(INDEX('DONNÉES BRUTES'!D$3:D$42,MATCH(_xlfn.AGGREGATE(14,6,'DONNÉES BRUTES'!AA$3:AA$42+ROW('DONNÉES BRUTES'!AA$3:AA$42)/1000,14),'DONNÉES BRUTES'!AA$3:AA$42+ROW('DONNÉES BRUTES'!AA$3:AA$42)/1000,0)),"—")} -> — | H17: {=IFERROR(INDEX('DONNÉES BRUTES'!E$3:E$42,MATCH(_xlfn.AGGREGATE(14,6,'DONNÉES BRUTES'!AA$3:AA$42+ROW('DONNÉES BRUTES'!AA$3:AA$42)/1000,14),'DONNÉES BRUTES'!AA$3:AA$42+ROW('DONNÉES BRUTES'!AA$3:AA$42)/1000,0)),"—")} -> — | I17: {=IFERROR(INDEX('DONNÉES BRUTES'!AB$3:AB$42,MATCH(_xlfn.AGGREGATE(14,6,'DONNÉES BRUTES'!AA$3:AA$42+ROW('DONNÉES BRUTES'!AA$3:AA$42)/1000,14),'DONNÉES BRUTES'!AA$3:AA$42+ROW('DONNÉES BRUTES'!AA$3:AA$42)/1000,0)),"—")} -> 72 | J17: {=IFERROR(INDEX('DONNÉES BRUTES'!AC$3:AC$42,MATCH(_xlfn.AGGREGATE(14,6,'DONNÉES BRUTES'!AA$3:AA$42+ROW('DONNÉES BRUTES'!AA$3:AA$42)/1000,14),'DONNÉES BRUTES'!AA$3:AA$42+ROW('DONNÉES BRUTES'!AA$3:AA$42)/1000,0)),"—")} -> — | K17: {=IFERROR(INDEX('DONNÉES BRUTES'!AD$3:AD$42,MATCH(_xlfn.AGGREGATE(14,6,'DONNÉES BRUTES'!AA$3:AA$42+ROW('DONNÉES BRUTES'!AA$3:AA$42)/1000,14),'DONNÉES BRUTES'!AA$3:AA$42+ROW('DONNÉES BRUTES'!AA$3:AA$42)/1000,0)),"—")} -> Neutre
A18: 15 | B18: {=IFERROR(INDEX('DONNÉES BRUTES'!A$3:A$42,MATCH(_xlfn.AGGREGATE(14,6,'DONNÉES BRUTES'!AA$3:AA$42+ROW('DONNÉES BRUTES'!AA$3:AA$42)/1000,15),'DONNÉES BRUTES'!AA$3:AA$42+ROW('DONNÉES BRUTES'!AA$3:AA$42)/1000,0)),"—")} -> KER.PA | C18: {=IFERROR(INDEX('DONNÉES BRUTES'!B$3:B$42,MATCH(_xlfn.AGGREGATE(14,6,'DONNÉES BRUTES'!AA$3:AA$42+ROW('DONNÉES BRUTES'!AA$3:AA$42)/1000,15),'DONNÉES BRUTES'!AA$3:AA$42+ROW('DONNÉES BRUTES'!AA$3:AA$42)/1000,0)),"—")} -> Kering SA | D18: {=IFERROR(INDEX('DONNÉES BRUTES'!C$3:C$42,MATCH(_xlfn.AGGREGATE(14,6,'DONNÉES BRUTES'!AA$3:AA$42+ROW('DONNÉES BRUTES'!AA$3:AA$42)/1000,15),'DONNÉES BRUTES'!AA$3:AA$42+ROW('DONNÉES BRUTES'!AA$3:AA$42)/1000,0)),"—")} -> Consumer Disc. | E18: {=IFERROR(INDEX('DONNÉES BRUTES'!AA$3:AA$42,MATCH(_xlfn.AGGREGATE(14,6,'DONNÉES BRUTES'!AA$3:AA$42+ROW('DONNÉES BRUTES'!AA$3:AA$42)/1000,15),'DONNÉES BRUTES'!AA$3:AA$42+ROW('DONNÉES BRUTES'!AA$3:AA$42)/1000,0))&"/100","—")} -> 64/100 | F18: {=IFERROR(INDEX('DONNÉES BRUTES'!W$3:W$42,MATCH(_xlfn.AGGREGATE(14,6,'DONNÉES BRUTES'!AA$3:AA$42+ROW('DONNÉES BRUTES'!AA$3:AA$42)/1000,15),'DONNÉES BRUTES'!AA$3:AA$42+ROW('DONNÉES BRUTES'!AA$3:AA$42)/1000,0)),"—")} -> nan% | G18: {=IFERROR(INDEX('DONNÉES BRUTES'!D$3:D$42,MATCH(_xlfn.AGGREGATE(14,6,'DONNÉES BRUTES'!AA$3:AA$42+ROW('DONNÉES BRUTES'!AA$3:AA$42)/1000,15),'DONNÉES BRUTES'!AA$3:AA$42+ROW('DONNÉES BRUTES'!AA$3:AA$42)/1000,0)),"—")} -> — | H18: {=IFERROR(INDEX('DONNÉES BRUTES'!E$3:E$42,MATCH(_xlfn.AGGREGATE(14,6,'DONNÉES BRUTES'!AA$3:AA$42+ROW('DONNÉES BRUTES'!AA$3:AA$42)/1000,15),'DONNÉES BRUTES'!AA$3:AA$42+ROW('DONNÉES BRUTES'!AA$3:AA$42)/1000,0)),"—")} -> — | I18: {=IFERROR(INDEX('DONNÉES BRUTES'!AB$3:AB$42,MATCH(_xlfn.AGGREGATE(14,6,'DONNÉES BRUTES'!AA$3:AA$42+ROW('DONNÉES BRUTES'!AA$3:AA$42)/1000,15),'DONNÉES BRUTES'!AA$3:AA$42+ROW('DONNÉES BRUTES'!AA$3:AA$42)/1000,0)),"—")} -> 55 | J18: {=IFERROR(INDEX('DONNÉES BRUTES'!AC$3:AC$42,MATCH(_xlfn.AGGREGATE(14,6,'DONNÉES BRUTES'!AA$3:AA$42+ROW('DONNÉES BRUTES'!AA$3:AA$42)/1000,15),'DONNÉES BRUTES'!AA$3:AA$42+ROW('DONNÉES BRUTES'!AA$3:AA$42)/1000,0)),"—")} -> — | K18: {=IFERROR(INDEX('DONNÉES BRUTES'!AD$3:AD$42,MATCH(_xlfn.AGGREGATE(14,6,'DONNÉES BRUTES'!AA$3:AA$42+ROW('DONNÉES BRUTES'!AA$3:AA$42)/1000,15),'DONNÉES BRUTES'!AA$3:AA$42+ROW('DONNÉES BRUTES'!AA$3:AA$42)/1000,0)),"—")} -> Neutre

Sheet PAR SECTEUR
B1: FinSight IA · CAC 40 — Vue Macro Sectorielle | H1: 22/03/2026 | L1: Secteur | M1: Score
A2: Usage confidentiel · Calculs Python/NumPy depuis cache Supabase | L2: Healthcare | M2: 72
B3: Scoring composite Value / Growth / Quality / Momentum · Métriques médianes par secteur · Usage confidentiel | L3: Real Estate | M3: 69
L4: Financials | M4: 63
B5: SCORECARD SECTORIELLE · Score composite, métriques médianes, signal d'investissement — CAC 40 | L5: Industrials | M5: 57
L6: Consumer Staples | M6: 55
B7: Secteur | C7: # Soc. | D7: Score | E7: Score (indicateur) | F7: Top Société | G7: Mg. EBITDA | H7: Croiss. Rev. | I7: Altman Z | J7: Signal | L7: Consumer Disc. | M7: 54
B8: Consumer Disc. | C8: 5 | D8: 54 | E8: █████░░░░░ | F8: Hermès International | G8: 0.25 | H8: -0.021 | I8: 1.68 | J8: Sous-pondérer | L8: Materials | M8: 53
B9: Materials | C9: 2 | D9: 53 | E9: █████░░░░░ | F9: L'Air Liquide | G9: 0.198 | H9: -0.011 | I9: 3.58 | J9: Sous-pondérer | L9: Comm. Services | M9: 38
B10: Technology | C10: 4 | D10: 35 | E10: ████░░░░░░ | F10: Dassault Systèmes | G10: 0.166 | H10: -0.014 | I10: 2.44 | J10: Sous-pondérer | L10: Technology | M10: 36
B11: Healthcare | C11: 3 | D11: 72 | E11: ███████░░░ | F11: Eurofins Scientific | G11: 0.232 | H11: 0.055 | I11: 2.27 | J11: Neutre | L11: Energy | M11: 18
B12: Industrials | C12: 11 | D12: 57 | E12: ██████░░░░ | F12: Alstom SA | G12: 0.162 | H12: 0.049 | I12: 1.03 | J12: Neutre | L12: Utilities | M12: 46
B13: Real Estate | C13: 1 | D13: 69 | E13: ███████░░░ | F13: Unibail-Rodamco-WE | G13: 0.891 | H13: -0.061 | I13: 1.22 | J13: Neutre | L13: Secteur | M13: Mg EBITDA Méd.
B14: Financials | C14: 4 | D14: 63 | E14: ██████░░░░ | F14: Crédit Agricole | G14: 1.087 | H14: 0.041 | I14: — | J14: Neutre | L14: Financials | M14: 103.4
B15: Consumer Stapl. | C15: 4 | D15: 55 | E15: ██████░░░░ | F15: L'Oréal | G15: 0.202 | H15: 0.002 | I15: 3.35 | J15: Neutre | L15: Real Estate | M15: 89.1
L16: Consumer Disc. | M16: 28.3
B17: CAC 40 — Total | C17: 40 | D17: 57 | F17: Médiane | G17: 0.25 | H17: 0.017 | L17: Healthcare | M17: 23.2
L18: Materials | M18: 22.7
B19: COMPOSITION DÉTAIL · Nb sociétés, score moyen, orientation — données pour allocation | L19: Consumer Staples | M19: 16.1
H20: Technology | I20: 19.6
B21: Secteur | C21: Nb Soc. | D21: Score Moyen | E21: Score (barre) | F21: Orientation | H21: Industrials | I21: 15.7
B22: Consumer Disc. | C22: 5 | D22: 54/100 | E22: █████░░░░░ | F22: → Neutre | H22: Utilities | I22: 20
B23: Materials | C23: 2 | D23: 53/100 | E23: █████░░░░░ | F23: → Neutre | H23: Comm. Services | I23: 27.2
B24: Technology | C24: 4 | D24: 35/100 | E24: ████░░░░░░ | F24: ↓ Négatif
B25: Healthcare | C25: 3 | D25: 72/100 | E25: ███████░░░ | F25: ↑ Positif | H25: Secteur | I25: Nb Soc.
B26: Industrials | C26: 11 | D26: 57/100 | E26: ██████░░░░ | F26: → Neutre | H26: Industrials | I26: 11
B27: Real Estate | C27: 1 | D27: 69/100 | E27: ███████░░░ | F27: ↑ Positif | H27: Consumer Disc. | I27: 5
B28: Financials | C28: 4 | D28: 63/100 | E28: ██████░░░░ | F28: ↑ Positif | H28: Consumer Staples | I28: 4
B29: Consumer Stapl. | C29: 4 | D29: 55/100 | E29: ██████░░░░ | F29: → Neutre | H29: Technology | I29: 4
H30: Financials | I30: 4
L31: Healthcare | M31: 3
B32: FinSight IA · Analyse sectorielle CAC 40 · Scores calculés sur métriques quantitatives · Ne constitue pas un conseil en investissement | L32: Comm. Services | M32: 3
L33: Materials | M33: 2
L34: Real Estate | M34: 1
L35: Energy | M35: 1
L36: Utilities | M36: 1

Sheet SECTOR OVERVIEW
