Workbook

Sheet SYNTHÈSE
A1: FinSight | C1: COMPARATIF SECTORIEL — Technologie vs Santé
A2: ="Données : "&COUNTA(DATA_TECH!A4:A200)&" valeurs Technologie · "&COUNTA(DATA_HC!A4:A200)&" valeurs Santé · Médiane sectorielle · Toutes formules dynamiques"
A4: TABLEAU COMPARATIF — MÉDIANES SECTORIELLES
A5: INDICATEUR | B5: DESCRIPTION | C5: TECHNOLOGIE | D5: SANTÉ | E5: Δ ABSOLU | F5: Δ % | G5: AVANTAGE
A6: Nb valeurs | B6: Taille de l'échantillon | C6: =COUNTA(DATA_TECH!A4:A200) | D6: =COUNTA(DATA_HC!A4:A200) | E6: =C6-D6 | F6: ="" | G6: =IF(C6>D6,"Technologie","Santé")
A7: Score FinSight médian | B7: Qualité fondamentale agrégée (0–100) | C7: =AGRÉGATS!D6 | D7: =AGRÉGATS!D15 | E7: =C7-D7 | F7: =IFERROR(TEXT((C7-D7)/D7*100,"0.0")&"%","—") | G7: =IF(C7>D7,"✓ Technologie","✓ Santé")
A8: Marge EBITDA médiane | B8: Profitabilité opérationnelle | C8: =AGRÉGATS!D7/100 | D8: =AGRÉGATS!D16/100 | E8: =C8-D8 | F8: =IFERROR(TEXT((C8-D8)/D8*100,"0.0")&"%","—") | G8: =IF(C8>D8,"✓ Technologie","✓ Santé")
A9: P/E médian | B9: Valorisation bénéfices (×) | C9: =AGRÉGATS!D8 | D9: =AGRÉGATS!D17 | E9: =C9-D9 | F9: =IFERROR(TEXT((C9-D9)/D9*100,"0.0")&"%","—") | G9: =IF(C9>D9,"Prime Technologie","Prime Santé")
A10: EV/EBITDA médian | B10: Valorisation hors structure (×) | C10: =AGRÉGATS!D9 | D10: =AGRÉGATS!D18 | E10: =C10-D10 | F10: =IFERROR(TEXT((C10-D10)/D10*100,"0.0")&"%","—") | G10: =IF(C10>D10,"Prime Technologie","Prime Santé")
A11: ROE médian | B11: Rentabilité des fonds propres | C11: =AGRÉGATS!D10/100 | D11: =AGRÉGATS!D19/100 | E11: =C11-D11 | F11: =IFERROR(TEXT((C11-D11)/D11*100,"0.0")&"%","—") | G11: =IF(C11>D11,"✓ Technologie","✓ Santé")
A12: Croiss. revenus médiane | B12: Dynamique commerciale YoY | C12: =AGRÉGATS!D11/100 | D12: =AGRÉGATS!D20/100 | E12: =C12-D12 | F12: =IFERROR(TEXT((C12-D12)/D12*100,"0.0")&"%","—") | G12: =IF(C12>D12,"✓ Technologie","✓ Santé")
A14: STATISTIQUES AVANCÉES — DISPERSION & AMPLITUDE SECTORIELLES
A15: INDICATEUR | B15: TECHNOLOGIE Médiane | C15: TECHNOLOGIE Moyenne | D15: TECHNOLOGIE Min | E15: TECHNOLOGIE Max | F15: SANTÉ Médiane | G15: SANTÉ Min | H15: SANTÉ Max | I15: Δ Médiane
A16: Score FinSight | B16: =AGRÉGATS!D6 | C16: =AGRÉGATS!E6 | D16: =AGRÉGATS!F6 | E16: =AGRÉGATS!G6 | F16: =AGRÉGATS!D15 | G16: =AGRÉGATS!F15 | H16: =AGRÉGATS!G15 | I16: =B16-F16
A17: Marge EBITDA | B17: =AGRÉGATS!D7/100 | C17: =AGRÉGATS!E7/100 | D17: =AGRÉGATS!F7/100 | E17: =AGRÉGATS!G7/100 | F17: =AGRÉGATS!D16/100 | G17: =AGRÉGATS!F16/100 | H17: =AGRÉGATS!G16/100 | I17: =B17-F17
A18: P/E | B18: =AGRÉGATS!D8 | C18: =AGRÉGATS!E8 | D18: =AGRÉGATS!F8 | E18: =AGRÉGATS!G8 | F18: =AGRÉGATS!D17 | G18: =AGRÉGATS!F17 | H18: =AGRÉGATS!G17 | I18: =B18-F18
A19: EV/EBITDA | B19: =AGRÉGATS!D9 | C19: =AGRÉGATS!E9 | D19: =AGRÉGATS!F9 | E19: =AGRÉGATS!G9 | F19: =AGRÉGATS!D18 | G19: =AGRÉGATS!F18 | H19: =AGRÉGATS!G18 | I19: =B19-F19
A20: ROE | B20: =AGRÉGATS!D10/100 | C20: =AGRÉGATS!E10/100 | D20: =AGRÉGATS!F10/100 | E20: =AGRÉGATS!G10/100 | F20: =AGRÉGATS!D19/100 | G20: =AGRÉGATS!F19/100 | H20: =AGRÉGATS!G19/100 | I20: =B20-F20
A21: Croiss. Rev. | B21: =AGRÉGATS!D11/100 | C21: =AGRÉGATS!E11/100 | D21: =AGRÉGATS!F11/100 | E21: =AGRÉGATS!G11/100 | F21: =AGRÉGATS!D20/100 | G21: =AGRÉGATS!F20/100 | H21: =AGRÉGATS!G20/100 | I21: =B21-F21
A23: TOP PERFORMERS — N°1 PAR SECTEUR (Score FinSight)
A24: SECTEUR | B24: TICKER | C24: SOCIÉTÉ | D24: SCORE | E24: MARGE EBITDA | F24: ROE | G24: CROISS. REV.
A25: Technologie | B25: =TOP_TECH!B5 | C25: =TOP_TECH!C5 | D25: =TOP_TECH!D5 | E25: =TOP_TECH!G5/100 | F25: =TOP_TECH!H5/100 | G25: =TOP_TECH!I5/100
A26: Santé | B26: =TOP_HC!B5 | C26: =TOP_HC!C5 | D26: =TOP_HC!D5 | E26: =TOP_HC!G5/100 | F26: =TOP_HC!H5/100 | G26: =TOP_HC!I5/100
A28: MÉDIANES PONDÉRÉES PAR SCORE FINSIGHT — Valeurs de qualité supérieure surpondérées
A29: Les médianes pondérées donnent plus de poids aux valeurs avec un Score FinSight élevé (SUMPRODUCT Score × KPI / SUM Score)
A30: INDICATEUR | B30: MG EBITDA pondérée | C30: P/E pondéré | D30: EV/EBITDA pondéré | E30: ROE pondéré | F30: CROISS. REV. pondérée
A31: Technologie (pondérée) | B31: {=IFERROR(SUMPRODUCT((DATA_TECH!$C$4:$C$91)*(DATA_TECH!F4:F91)*(ISNUMBER(DATA_TECH!F4:F91)))/SUMPRODUCT((DATA_TECH!$C$4:$C$91)*(ISNUMBER(DATA_TECH!F4:F91))),"")} | C31: {=IFERROR(SUMPRODUCT((DATA_TECH!$C$4:$C$91)*(DATA_TECH!D4:D91)*(ISNUMBER(DATA_TECH!D4:D91)))/SUMPRODUCT((DATA_TECH!$C$4:$C$91)*(ISNUMBER(DATA_TECH!D4:D91))),"")} | D31: {=IFERROR(SUMPRODUCT((DATA_TECH!$C$4:$C$91)*(DATA_TECH!E4:E91)*(ISNUMBER(DATA_TECH!E4:E91)))/SUMPRODUCT((DATA_TECH!$C$4:$C$91)*(ISNUMBER(DATA_TECH!E4:E91))),"")} | E31: {=IFERROR(SUMPRODUCT((DATA_TECH!$C$4:$C$91)*(DATA_TECH!G4:G91)*(ISNUMBER(DATA_TECH!G4:G91)))/SUMPRODUCT((DATA_TECH!$C$4:$C$91)*(ISNUMBER(DATA_TECH!G4:G91))),"")} | F31: {=IFERROR(SUMPRODUCT((DATA_TECH!$C$4:$C$91)*(DATA_TECH!H4:H91)*(ISNUMBER(DATA_TECH!H4:H91)))/SUMPRODUCT((DATA_TECH!$C$4:$C$91)*(ISNUMBER(DATA_TECH!H4:H91))),"")}
A32: Santé (pondérée) | B32: {=IFERROR(SUMPRODUCT((DATA_HC!$C$4:$C$9)*(DATA_HC!F4:F9)*(ISNUMBER(DATA_HC!F4:F9)))/SUMPRODUCT((DATA_HC!$C$4:$C$9)*(ISNUMBER(DATA_HC!F4:F9))),"")} | C32: {=IFERROR(SUMPRODUCT((DATA_HC!$C$4:$C$9)*(DATA_HC!D4:D9)*(ISNUMBER(DATA_HC!D4:D9)))/SUMPRODUCT((DATA_HC!$C$4:$C$9)*(ISNUMBER(DATA_HC!D4:D9))),"")} | D32: {=IFERROR(SUMPRODUCT((DATA_HC!$C$4:$C$9)*(DATA_HC!E4:E9)*(ISNUMBER(DATA_HC!E4:E9)))/SUMPRODUCT((DATA_HC!$C$4:$C$9)*(ISNUMBER(DATA_HC!E4:E9))),"")} | E32: {=IFERROR(SUMPRODUCT((DATA_HC!$C$4:$C$9)*(DATA_HC!G4:G9)*(ISNUMBER(DATA_HC!G4:G9)))/SUMPRODUCT((DATA_HC!$C$4:$C$9)*(ISNUMBER(DATA_HC!G4:G9))),"")} | F32: {=IFERROR(SUMPRODUCT((DATA_HC!$C$4:$C$9)*(DATA_HC!H4:H9)*(ISNUMBER(DATA_HC!H4:H9)))/SUMPRODUCT((DATA_HC!$C$4:$C$9)*(ISNUMBER(DATA_HC!H4:H9))),"")}

Sheet AGRÉGATS
A1: FinSight | C1: AGRÉGATS — Statistiques comparatives Technologie vs Santé
A2: Médiane · Moyenne · Min · Max · Écart-type — liés à DATA_TECH (88 valeurs) et DATA_HC (6 valeurs)
A4: TECHNOLOGIE — 10 valeurs
A5: SECTEUR | B5: INDICATEUR | C5: N | D5: MÉDIANE | E5: MOYENNE | F5: MIN | G5: MAX | H5: ÉCART-TYPE | I5: Q1 (25e) | J5: Q3 (75e) | K5: IQR
A6: Technologie | B6: Score FinSight | C6: =COUNT(DATA_TECH!C4:C200) | D6: =MEDIAN(DATA_TECH!C4:C200) | E6: =AVERAGE(DATA_TECH!C4:C200) | F6: =MIN(DATA_TECH!C4:C200) | G6: =MAX(DATA_TECH!C4:C200) | H6: =STDEV(DATA_TECH!C4:C200) | I6: =QUARTILE(DATA_TECH!C4:C200,1) | J6: =QUARTILE(DATA_TECH!C4:C200,3) | K6: =J6-I6
A7: Technologie | B7: Marge EBITDA | C7: =COUNT(DATA_TECH!F4:F200) | D7: =MEDIAN(DATA_TECH!F4:F200) | E7: =AVERAGE(DATA_TECH!F4:F200) | F7: =MIN(DATA_TECH!F4:F200) | G7: =MAX(DATA_TECH!F4:F200) | H7: =STDEV(DATA_TECH!F4:F200) | I7: =QUARTILE(DATA_TECH!F4:F200,1) | J7: =QUARTILE(DATA_TECH!F4:F200,3) | K7: =J7-I7
A8: Technologie | B8: P/E | C8: =COUNT(DATA_TECH!D4:D200) | D8: =MEDIAN(DATA_TECH!D4:D200) | E8: =AVERAGE(DATA_TECH!D4:D200) | F8: =MIN(DATA_TECH!D4:D200) | G8: =MAX(DATA_TECH!D4:D200) | H8: =STDEV(DATA_TECH!D4:D200) | I8: =QUARTILE(DATA_TECH!D4:D200,1) | J8: =QUARTILE(DATA_TECH!D4:D200,3) | K8: =J8-I8
A9: Technologie | B9: EV/EBITDA | C9: =COUNT(DATA_TECH!E4:E200) | D9: =MEDIAN(DATA_TECH!E4:E200) | E9: =AVERAGE(DATA_TECH!E4:E200) | F9: =MIN(DATA_TECH!E4:E200) | G9: =MAX(DATA_TECH!E4:E200) | H9: =STDEV(DATA_TECH!E4:E200) | I9: =QUARTILE(DATA_TECH!E4:E200,1) | J9: =QUARTILE(DATA_TECH!E4:E200,3) | K9: =J9-I9
A10: Technologie | B10: ROE | C10: =COUNT(DATA_TECH!G4:G200) | D10: =MEDIAN(DATA_TECH!G4:G200) | E10: =AVERAGE(DATA_TECH!G4:G200) | F10: =MIN(DATA_TECH!G4:G200) | G10: =MAX(DATA_TECH!G4:G200) | H10: =STDEV(DATA_TECH!G4:G200) | I10: =QUARTILE(DATA_TECH!G4:G200,1) | J10: =QUARTILE(DATA_TECH!G4:G200,3) | K10: =J10-I10
A11: Technologie | B11: Croiss. Revenus | C11: =COUNT(DATA_TECH!H4:H200) | D11: =MEDIAN(DATA_TECH!H4:H200) | E11: =AVERAGE(DATA_TECH!H4:H200) | F11: =MIN(DATA_TECH!H4:H200) | G11: =MAX(DATA_TECH!H4:H200) | H11: =STDEV(DATA_TECH!H4:H200) | I11: =QUARTILE(DATA_TECH!H4:H200,1) | J11: =QUARTILE(DATA_TECH!H4:H200,3) | K11: =J11-I11
A13: SANTÉ — 6 valeurs
A14: SECTEUR | B14: INDICATEUR | C14: N | D14: MÉDIANE | E14: MOYENNE | F14: MIN | G14: MAX | H14: ÉCART-TYPE | I14: Q1 (25e) | J14: Q3 (75e) | K14: IQR
A15: Santé | B15: Score FinSight | C15: =COUNT(DATA_HC!C4:C200) | D15: =MEDIAN(DATA_HC!C4:C200) | E15: =AVERAGE(DATA_HC!C4:C200) | F15: =MIN(DATA_HC!C4:C200) | G15: =MAX(DATA_HC!C4:C200) | H15: =STDEV(DATA_HC!C4:C200) | I15: =QUARTILE(DATA_HC!C4:C200,1) | J15: =QUARTILE(DATA_HC!C4:C200,3) | K15: =J15-I15
A16: Santé | B16: Marge EBITDA | C16: =COUNT(DATA_HC!F4:F200) | D16: =MEDIAN(DATA_HC!F4:F200) | E16: =AVERAGE(DATA_HC!F4:F200) | F16: =MIN(DATA_HC!F4:F200) | G16: =MAX(DATA_HC!F4:F200) | H16: =STDEV(DATA_HC!F4:F200) | I16: =QUARTILE(DATA_HC!F4:F200,1) | J16: =QUARTILE(DATA_HC!F4:F200,3) | K16: =J16-I16
A17: Santé | B17: P/E | C17: =COUNT(DATA_HC!D4:D200) | D17: =MEDIAN(DATA_HC!D4:D200) | E17: =AVERAGE(DATA_HC!D4:D200) | F17: =MIN(DATA_HC!D4:D200) | G17: =MAX(DATA_HC!D4:D200) | H17: =STDEV(DATA_HC!D4:D200) | I17: =QUARTILE(DATA_HC!D4:D200,1) | J17: =QUARTILE(DATA_HC!D4:D200,3) | K17: =J17-I17
A18: Santé | B18: EV/EBITDA | C18: =COUNT(DATA_HC!E4:E200) | D18: =MEDIAN(DATA_HC!E4:E200) | E18: =AVERAGE(DATA_HC!E4:E200) | F18: =MIN(DATA_HC!E4:E200) | G18: =MAX(DATA_HC!E4:E200) | H18: =STDEV(DATA_HC!E4:E200) | I18: =QUARTILE(DATA_HC!E4:E200,1) | J18: =QUARTILE(DATA_HC!E4:E200,3) | K18: =J18-I18
A19: Santé | B19: ROE | C19: =COUNT(DATA_HC!G4:G200) | D19: =MEDIAN(DATA_HC!G4:G200) | E19: =AVERAGE(DATA_HC!G4:G200) | F19: =MIN(DATA_HC!G4:G200) | G19: =MAX(DATA_HC!G4:G200) | H19: =STDEV(DATA_HC!G4:G200) | I19: =QUARTILE(DATA_HC!G4:G200,1) | J19: =QUARTILE(DATA_HC!G4:G200,3) | K19: =J19-I19
A20: Santé | B20: Croiss. Revenus | C20: =COUNT(DATA_HC!H4:H200) | D20: =MEDIAN(DATA_HC!H4:H200) | E20: =AVERAGE(DATA_HC!H4:H200) | F20: =MIN(DATA_HC!H4:H200) | G20: =MAX(DATA_HC!H4:H200) | H20: =STDEV(DATA_HC!H4:H200) | I20: =QUARTILE(DATA_HC!H4:H200,1) | J20: =QUARTILE(DATA_HC!H4:H200,3) | K20: =J20-I20
A22: DELTA — Différentiel Technologie vs Santé (Tech − HC)
A23: COMPARAISON | B23: INDICATEUR | C23: — | D23: Δ MÉDIANE | E23: Δ MOYENNE | F23: Δ MIN | G23: Δ MAX | H23: Δ ÉCART-TYPE
A24: Technologie vs Santé | B24: Score FinSight | C24: — | D24: =D6-D15 | E24: =E6-E15 | F24: =F6-F15 | G24: =G6-G15 | H24: =H6-H15
A25: Technologie vs Santé | B25: Marge EBITDA | C25: — | D25: =D7-D16 | E25: =E7-E16 | F25: =F7-F16 | G25: =G7-G16 | H25: =H7-H16
A26: Technologie vs Santé | B26: P/E | C26: — | D26: =D8-D17 | E26: =E8-E17 | F26: =F8-F17 | G26: =G8-G17 | H26: =H8-H17
A27: Technologie vs Santé | B27: EV/EBITDA | C27: — | D27: =D9-D18 | E27: =E9-E18 | F27: =F9-F18 | G27: =G9-G18 | H27: =H9-H18
A28: Technologie vs Santé | B28: ROE | C28: — | D28: =D10-D19 | E28: =E10-E19 | F28: =F10-F19 | G28: =G10-G19 | H28: =H10-H19
A29: Technologie vs Santé | B29: Croiss. Revenus | C29: — | D29: =D11-D20 | E29: =E11-E20 | F29: =F11-F20 | G29: =G11-G20 | H29: =H11-H20

Sheet TOP_TECH
A1: FinSight | C1: TOP TECH — Classement dynamique Technologie par Score FinSight (Top 20)
A2: Classement calculé dynamiquement via LARGE / INDEX / MATCH depuis DATA_TECH · Se met à jour automatiquement
A3: TOP 20 — TECHNOLOGIE
A4: RANG | B4: TICKER | C4: SOCIÉTÉ | D4: SCORE | E4: P/E | F4: EV/EBITDA | G4: MG EBITDA | H4: ROE | I4: CROISS. REV.
A5: 1 | B5: =IFERROR(INDEX(DATA_TECH!$A$4:$A$200,MATCH(LARGE(DATA_TECH!$C$4:$C$200,1),DATA_TECH!$C$4:$C$200,0)),"") | C5: =IFERROR(INDEX(DATA_TECH!$B$4:$B$200,MATCH(LARGE(DATA_TECH!$C$4:$C$200,1),DATA_TECH!$C$4:$C$200,0)),"") | D5: =LARGE(DATA_TECH!$C$4:$C$200,1) | E5: =IFERROR(INDEX(DATA_TECH!$D$4:$D$200,MATCH(LARGE(DATA_TECH!$C$4:$C$200,1),DATA_TECH!$C$4:$C$200,0)),"") | F5: =IFERROR(INDEX(DATA_TECH!$E$4:$E$200,MATCH(LARGE(DATA_TECH!$C$4:$C$200,1),DATA_TECH!$C$4:$C$200,0)),"") | G5: =IFERROR(INDEX(DATA_TECH!$F$4:$F$200,MATCH(LARGE(DATA_TECH!$C$4:$C$200,1),DATA_TECH!$C$4:$C$200,0)),"") | H5: =IFERROR(INDEX(DATA_TECH!$G$4:$G$200,MATCH(LARGE(DATA_TECH!$C$4:$C$200,1),DATA_TECH!$C$4:$C$200,0)),"") | I5: =IFERROR(INDEX(DATA_TECH!$H$4:$H$200,MATCH(LARGE(DATA_TECH!$C$4:$C$200,1),DATA_TECH!$C$4:$C$200,0)),"")
A6: 2 | B6: =IFERROR(INDEX(DATA_TECH!$A$4:$A$200,MATCH(LARGE(DATA_TECH!$C$4:$C$200,2),DATA_TECH!$C$4:$C$200,0)),"") | C6: =IFERROR(INDEX(DATA_TECH!$B$4:$B$200,MATCH(LARGE(DATA_TECH!$C$4:$C$200,2),DATA_TECH!$C$4:$C$200,0)),"") | D6: =LARGE(DATA_TECH!$C$4:$C$200,2) | E6: =IFERROR(INDEX(DATA_TECH!$D$4:$D$200,MATCH(LARGE(DATA_TECH!$C$4:$C$200,2),DATA_TECH!$C$4:$C$200,0)),"") | F6: =IFERROR(INDEX(DATA_TECH!$E$4:$E$200,MATCH(LARGE(DATA_TECH!$C$4:$C$200,2),DATA_TECH!$C$4:$C$200,0)),"") | G6: =IFERROR(INDEX(DATA_TECH!$F$4:$F$200,MATCH(LARGE(DATA_TECH!$C$4:$C$200,2),DATA_TECH!$C$4:$C$200,0)),"") | H6: =IFERROR(INDEX(DATA_TECH!$G$4:$G$200,MATCH(LARGE(DATA_TECH!$C$4:$C$200,2),DATA_TECH!$C$4:$C$200,0)),"") | I6: =IFERROR(INDEX(DATA_TECH!$H$4:$H$200,MATCH(LARGE(DATA_TECH!$C$4:$C$200,2),DATA_TECH!$C$4:$C$200,0)),"")
A7: 3 | B7: =IFERROR(INDEX(DATA_TECH!$A$4:$A$200,MATCH(LARGE(DATA_TECH!$C$4:$C$200,3),DATA_TECH!$C$4:$C$200,0)),"") | C7: =IFERROR(INDEX(DATA_TECH!$B$4:$B$200,MATCH(LARGE(DATA_TECH!$C$4:$C$200,3),DATA_TECH!$C$4:$C$200,0)),"") | D7: =LARGE(DATA_TECH!$C$4:$C$200,3) | E7: =IFERROR(INDEX(DATA_TECH!$D$4:$D$200,MATCH(LARGE(DATA_TECH!$C$4:$C$200,3),DATA_TECH!$C$4:$C$200,0)),"") | F7: =IFERROR(INDEX(DATA_TECH!$E$4:$E$200,MATCH(LARGE(DATA_TECH!$C$4:$C$200,3),DATA_TECH!$C$4:$C$200,0)),"") | G7: =IFERROR(INDEX(DATA_TECH!$F$4:$F$200,MATCH(LARGE(DATA_TECH!$C$4:$C$200,3),DATA_TECH!$C$4:$C$200,0)),"") | H7: =IFERROR(INDEX(DATA_TECH!$G$4:$G$200,MATCH(LARGE(DATA_TECH!$C$4:$C$200,3),DATA_TECH!$C$4:$C$200,0)),"") | I7: =IFERROR(INDEX(DATA_TECH!$H$4:$H$200,MATCH(LARGE(DATA_TECH!$C$4:$C$200,3),DATA_TECH!$C$4:$C$200,0)),"")
A8: 4 | B8: =IFERROR(INDEX(DATA_TECH!$A$4:$A$200,MATCH(LARGE(DATA_TECH!$C$4:$C$200,4),DATA_TECH!$C$4:$C$200,0)),"") | C8: =IFERROR(INDEX(DATA_TECH!$B$4:$B$200,MATCH(LARGE(DATA_TECH!$C$4:$C$200,4),DATA_TECH!$C$4:$C$200,0)),"") | D8: =LARGE(DATA_TECH!$C$4:$C$200,4) | E8: =IFERROR(INDEX(DATA_TECH!$D$4:$D$200,MATCH(LARGE(DATA_TECH!$C$4:$C$200,4),DATA_TECH!$C$4:$C$200,0)),"") | F8: =IFERROR(INDEX(DATA_TECH!$E$4:$E$200,MATCH(LARGE(DATA_TECH!$C$4:$C$200,4),DATA_TECH!$C$4:$C$200,0)),"") | G8: =IFERROR(INDEX(DATA_TECH!$F$4:$F$200,MATCH(LARGE(DATA_TECH!$C$4:$C$200,4),DATA_TECH!$C$4:$C$200,0)),"") | H8: =IFERROR(INDEX(DATA_TECH!$G$4:$G$200,MATCH(LARGE(DATA_TECH!$C$4:$C$200,4),DATA_TECH!$C$4:$C$200,0)),"") | I8: =IFERROR(INDEX(DATA_TECH!$H$4:$H$200,MATCH(LARGE(DATA_TECH!$C$4:$C$200,4),DATA_TECH!$C$4:$C$200,0)),"")
A9: 5 | B9: =IFERROR(INDEX(DATA_TECH!$A$4:$A$200,MATCH(LARGE(DATA_TECH!$C$4:$C$200,5),DATA_TECH!$C$4:$C$200,0)),"") | C9: =IFERROR(INDEX(DATA_TECH!$B$4:$B$200,MATCH(LARGE(DATA_TECH!$C$4:$C$200,5),DATA_TECH!$C$4:$C$200,0)),"") | D9: =LARGE(DATA_TECH!$C$4:$C$200,5) | E9: =IFERROR(INDEX(DATA_TECH!$D$4:$D$200,MATCH(LARGE(DATA_TECH!$C$4:$C$200,5),DATA_TECH!$C$4:$C$200,0)),"") | F9: =IFERROR(INDEX(DATA_TECH!$E$4:$E$200,MATCH(LARGE(DATA_TECH!$C$4:$C$200,5),DATA_TECH!$C$4:$C$200,0)),"") | G9: =IFERROR(INDEX(DATA_TECH!$F$4:$F$200,MATCH(LARGE(DATA_TECH!$C$4:$C$200,5),DATA_TECH!$C$4:$C$200,0)),"") | H9: =IFERROR(INDEX(DATA_TECH!$G$4:$G$200,MATCH(LARGE(DATA_TECH!$C$4:$C$200,5),DATA_TECH!$C$4:$C$200,0)),"") | I9: =IFERROR(INDEX(DATA_TECH!$H$4:$H$200,MATCH(LARGE(DATA_TECH!$C$4:$C$200,5),DATA_TECH!$C$4:$C$200,0)),"")
A10: 6 | B10: =IFERROR(INDEX(DATA_TECH!$A$4:$A$200,MATCH(LARGE(DATA_TECH!$C$4:$C$200,6),DATA_TECH!$C$4:$C$200,0)),"") | C10: =IFERROR(INDEX(DATA_TECH!$B$4:$B$200,MATCH(LARGE(DATA_TECH!$C$4:$C$200,6),DATA_TECH!$C$4:$C$200,0)),"") | D10: =LARGE(DATA_TECH!$C$4:$C$200,6) | E10: =IFERROR(INDEX(DATA_TECH!$D$4:$D$200,MATCH(LARGE(DATA_TECH!$C$4:$C$200,6),DATA_TECH!$C$4:$C$200,0)),"") | F10: =IFERROR(INDEX(DATA_TECH!$E$4:$E$200,MATCH(LARGE(DATA_TECH!$C$4:$C$200,6),DATA_TECH!$C$4:$C$200,0)),"") | G10: =IFERROR(INDEX(DATA_TECH!$F$4:$F$200,MATCH(LARGE(DATA_TECH!$C$4:$C$200,6),DATA_TECH!$C$4:$C$200,0)),"") | H10: =IFERROR(INDEX(DATA_TECH!$G$4:$G$200,MATCH(LARGE(DATA_TECH!$C$4:$C$200,6),DATA_TECH!$C$4:$C$200,0)),"") | I10: =IFERROR(INDEX(DATA_TECH!$H$4:$H$200,MATCH(LARGE(DATA_TECH!$C$4:$C$200,6),DATA_TECH!$C$4:$C$200,0)),"")
A11: 7 | B11: =IFERROR(INDEX(DATA_TECH!$A$4:$A$200,MATCH(LARGE(DATA_TECH!$C$4:$C$200,7),DATA_TECH!$C$4:$C$200,0)),"") | C11: =IFERROR(INDEX(DATA_TECH!$B$4:$B$200,MATCH(LARGE(DATA_TECH!$C$4:$C$200,7),DATA_TECH!$C$4:$C$200,0)),"") | D11: =LARGE(DATA_TECH!$C$4:$C$200,7) | E11: =IFERROR(INDEX(DATA_TECH!$D$4:$D$200,MATCH(LARGE(DATA_TECH!$C$4:$C$200,7),DATA_TECH!$C$4:$C$200,0)),"") | F11: =IFERROR(INDEX(DATA_TECH!$E$4:$E$200,MATCH(LARGE(DATA_TECH!$C$4:$C$200,7),DATA_TECH!$C$4:$C$200,0)),"") | G11: =IFERROR(INDEX(DATA_TECH!$F$4:$F$200,MATCH(LARGE(DATA_TECH!$C$4:$C$200,7),DATA_TECH!$C$4:$C$200,0)),"") | H11: =IFERROR(INDEX(DATA_TECH!$G$4:$G$200,MATCH(LARGE(DATA_TECH!$C$4:$C$200,7),DATA_TECH!$C$4:$C$200,0)),"") | I11: =IFERROR(INDEX(DATA_TECH!$H$4:$H$200,MATCH(LARGE(DATA_TECH!$C$4:$C$200,7),DATA_TECH!$C$4:$C$200,0)),"")
A12: 8 | B12: =IFERROR(INDEX(DATA_TECH!$A$4:$A$200,MATCH(LARGE(DATA_TECH!$C$4:$C$200,8),DATA_TECH!$C$4:$C$200,0)),"") | C12: =IFERROR(INDEX(DATA_TECH!$B$4:$B$200,MATCH(LARGE(DATA_TECH!$C$4:$C$200,8),DATA_TECH!$C$4:$C$200,0)),"") | D12: =LARGE(DATA_TECH!$C$4:$C$200,8) | E12: =IFERROR(INDEX(DATA_TECH!$D$4:$D$200,MATCH(LARGE(DATA_TECH!$C$4:$C$200,8),DATA_TECH!$C$4:$C$200,0)),"") | F12: =IFERROR(INDEX(DATA_TECH!$E$4:$E$200,MATCH(LARGE(DATA_TECH!$C$4:$C$200,8),DATA_TECH!$C$4:$C$200,0)),"") | G12: =IFERROR(INDEX(DATA_TECH!$F$4:$F$200,MATCH(LARGE(DATA_TECH!$C$4:$C$200,8),DATA_TECH!$C$4:$C$200,0)),"") | H12: =IFERROR(INDEX(DATA_TECH!$G$4:$G$200,MATCH(LARGE(DATA_TECH!$C$4:$C$200,8),DATA_TECH!$C$4:$C$200,0)),"") | I12: =IFERROR(INDEX(DATA_TECH!$H$4:$H$200,MATCH(LARGE(DATA_TECH!$C$4:$C$200,8),DATA_TECH!$C$4:$C$200,0)),"")
A13: 9 | B13: =IFERROR(INDEX(DATA_TECH!$A$4:$A$200,MATCH(LARGE(DATA_TECH!$C$4:$C$200,9),DATA_TECH!$C$4:$C$200,0)),"") | C13: =IFERROR(INDEX(DATA_TECH!$B$4:$B$200,MATCH(LARGE(DATA_TECH!$C$4:$C$200,9),DATA_TECH!$C$4:$C$200,0)),"") | D13: =LARGE(DATA_TECH!$C$4:$C$200,9) | E13: =IFERROR(INDEX(DATA_TECH!$D$4:$D$200,MATCH(LARGE(DATA_TECH!$C$4:$C$200,9),DATA_TECH!$C$4:$C$200,0)),"") | F13: =IFERROR(INDEX(DATA_TECH!$E$4:$E$200,MATCH(LARGE(DATA_TECH!$C$4:$C$200,9),DATA_TECH!$C$4:$C$200,0)),"") | G13: =IFERROR(INDEX(DATA_TECH!$F$4:$F$200,MATCH(LARGE(DATA_TECH!$C$4:$C$200,9),DATA_TECH!$C$4:$C$200,0)),"") | H13: =IFERROR(INDEX(DATA_TECH!$G$4:$G$200,MATCH(LARGE(DATA_TECH!$C$4:$C$200,9),DATA_TECH!$C$4:$C$200,0)),"") | I13: =IFERROR(INDEX(DATA_TECH!$H$4:$H$200,MATCH(LARGE(DATA_TECH!$C$4:$C$200,9),DATA_TECH!$C$4:$C$200,0)),"")
A14: 10 | B14: =IFERROR(INDEX(DATA_TECH!$A$4:$A$200,MATCH(LARGE(DATA_TECH!$C$4:$C$200,10),DATA_TECH!$C$4:$C$200,0)),"") | C14: =IFERROR(INDEX(DATA_TECH!$B$4:$B$200,MATCH(LARGE(DATA_TECH!$C$4:$C$200,10),DATA_TECH!$C$4:$C$200,0)),"") | D14: =LARGE(DATA_TECH!$C$4:$C$200,10) | E14: =IFERROR(INDEX(DATA_TECH!$D$4:$D$200,MATCH(LARGE(DATA_TECH!$C$4:$C$200,10),DATA_TECH!$C$4:$C$200,0)),"") | F14: =IFERROR(INDEX(DATA_TECH!$E$4:$E$200,MATCH(LARGE(DATA_TECH!$C$4:$C$200,10),DATA_TECH!$C$4:$C$200,0)),"") | G14: =IFERROR(INDEX(DATA_TECH!$F$4:$F$200,MATCH(LARGE(DATA_TECH!$C$4:$C$200,10),DATA_TECH!$C$4:$C$200,0)),"") | H14: =IFERROR(INDEX(DATA_TECH!$G$4:$G$200,MATCH(LARGE(DATA_TECH!$C$4:$C$200,10),DATA_TECH!$C$4:$C$200,0)),"") | I14: =IFERROR(INDEX(DATA_TECH!$H$4:$H$200,MATCH(LARGE(DATA_TECH!$C$4:$C$200,10),DATA_TECH!$C$4:$C$200,0)),"")
A15: 11 | B15: =IFERROR(INDEX(DATA_TECH!$A$4:$A$200,MATCH(LARGE(DATA_TECH!$C$4:$C$200,11),DATA_TECH!$C$4:$C$200,0)),"") | C15: =IFERROR(INDEX(DATA_TECH!$B$4:$B$200,MATCH(LARGE(DATA_TECH!$C$4:$C$200,11),DATA_TECH!$C$4:$C$200,0)),"") | D15: =LARGE(DATA_TECH!$C$4:$C$200,11) | E15: =IFERROR(INDEX(DATA_TECH!$D$4:$D$200,MATCH(LARGE(DATA_TECH!$C$4:$C$200,11),DATA_TECH!$C$4:$C$200,0)),"") | F15: =IFERROR(INDEX(DATA_TECH!$E$4:$E$200,MATCH(LARGE(DATA_TECH!$C$4:$C$200,11),DATA_TECH!$C$4:$C$200,0)),"") | G15: =IFERROR(INDEX(DATA_TECH!$F$4:$F$200,MATCH(LARGE(DATA_TECH!$C$4:$C$200,11),DATA_TECH!$C$4:$C$200,0)),"") | H15: =IFERROR(INDEX(DATA_TECH!$G$4:$G$200,MATCH(LARGE(DATA_TECH!$C$4:$C$200,11),DATA_TECH!$C$4:$C$200,0)),"") | I15: =IFERROR(INDEX(DATA_TECH!$H$4:$H$200,MATCH(LARGE(DATA_TECH!$C$4:$C$200,11),DATA_TECH!$C$4:$C$200,0)),"")
A16: 12 | B16: =IFERROR(INDEX(DATA_TECH!$A$4:$A$200,MATCH(LARGE(DATA_TECH!$C$4:$C$200,12),DATA_TECH!$C$4:$C$200,0)),"") | C16: =IFERROR(INDEX(DATA_TECH!$B$4:$B$200,MATCH(LARGE(DATA_TECH!$C$4:$C$200,12),DATA_TECH!$C$4:$C$200,0)),"") | D16: =LARGE(DATA_TECH!$C$4:$C$200,12) | E16: =IFERROR(INDEX(DATA_TECH!$D$4:$D$200,MATCH(LARGE(DATA_TECH!$C$4:$C$200,12),DATA_TECH!$C$4:$C$200,0)),"") | F16: =IFERROR(INDEX(DATA_TECH!$E$4:$E$200,MATCH(LARGE(DATA_TECH!$C$4:$C$200,12),DATA_TECH!$C$4:$C$200,0)),"") | G16: =IFERROR(INDEX(DATA_TECH!$F$4:$F$200,MATCH(LARGE(DATA_TECH!$C$4:$C$200,12),DATA_TECH!$C$4:$C$200,0)),"") | H16: =IFERROR(INDEX(DATA_TECH!$G$4:$G$200,MATCH(LARGE(DATA_TECH!$C$4:$C$200,12),DATA_TECH!$C$4:$C$200,0)),"") | I16: =IFERROR(INDEX(DATA_TECH!$H$4:$H$200,MATCH(LARGE(DATA_TECH!$C$4:$C$200,12),DATA_TECH!$C$4:$C$200,0)),"")
A17: 13 | B17: =IFERROR(INDEX(DATA_TECH!$A$4:$A$200,MATCH(LARGE(DATA_TECH!$C$4:$C$200,13),DATA_TECH!$C$4:$C$200,0)),"") | C17: =IFERROR(INDEX(DATA_TECH!$B$4:$B$200,MATCH(LARGE(DATA_TECH!$C$4:$C$200,13),DATA_TECH!$C$4:$C$200,0)),"") | D17: =LARGE(DATA_TECH!$C$4:$C$200,13) | E17: =IFERROR(INDEX(DATA_TECH!$D$4:$D$200,MATCH(LARGE(DATA_TECH!$C$4:$C$200,13),DATA_TECH!$C$4:$C$200,0)),"") | F17: =IFERROR(INDEX(DATA_TECH!$E$4:$E$200,MATCH(LARGE(DATA_TECH!$C$4:$C$200,13),DATA_TECH!$C$4:$C$200,0)),"") | G17: =IFERROR(INDEX(DATA_TECH!$F$4:$F$200,MATCH(LARGE(DATA_TECH!$C$4:$C$200,13),DATA_TECH!$C$4:$C$200,0)),"") | H17: =IFERROR(INDEX(DATA_TECH!$G$4:$G$200,MATCH(LARGE(DATA_TECH!$C$4:$C$200,13),DATA_TECH!$C$4:$C$200,0)),"") | I17: =IFERROR(INDEX(DATA_TECH!$H$4:$H$200,MATCH(LARGE(DATA_TECH!$C$4:$C$200,13),DATA_TECH!$C$4:$C$200,0)),"")
A18: 14 | B18: =IFERROR(INDEX(DATA_TECH!$A$4:$A$200,MATCH(LARGE(DATA_TECH!$C$4:$C$200,14),DATA_TECH!$C$4:$C$200,0)),"") | C18: =IFERROR(INDEX(DATA_TECH!$B$4:$B$200,MATCH(LARGE(DATA_TECH!$C$4:$C$200,14),DATA_TECH!$C$4:$C$200,0)),"") | D18: =LARGE(DATA_TECH!$C$4:$C$200,14) | E18: =IFERROR(INDEX(DATA_TECH!$D$4:$D$200,MATCH(LARGE(DATA_TECH!$C$4:$C$200,14),DATA_TECH!$C$4:$C$200,0)),"") | F18: =IFERROR(INDEX(DATA_TECH!$E$4:$E$200,MATCH(LARGE(DATA_TECH!$C$4:$C$200,14),DATA_TECH!$C$4:$C$200,0)),"") | G18: =IFERROR(INDEX(DATA_TECH!$F$4:$F$200,MATCH(LARGE(DATA_TECH!$C$4:$C$200,14),DATA_TECH!$C$4:$C$200,0)),"") | H18: =IFERROR(INDEX(DATA_TECH!$G$4:$G$200,MATCH(LARGE(DATA_TECH!$C$4:$C$200,14),DATA_TECH!$C$4:$C$200,0)),"") | I18: =IFERROR(INDEX(DATA_TECH!$H$4:$H$200,MATCH(LARGE(DATA_TECH!$C$4:$C$200,14),DATA_TECH!$C$4:$C$200,0)),"")
A19: 15 | B19: =IFERROR(INDEX(DATA_TECH!$A$4:$A$200,MATCH(LARGE(DATA_TECH!$C$4:$C$200,15),DATA_TECH!$C$4:$C$200,0)),"") | C19: =IFERROR(INDEX(DATA_TECH!$B$4:$B$200,MATCH(LARGE(DATA_TECH!$C$4:$C$200,15),DATA_TECH!$C$4:$C$200,0)),"") | D19: =LARGE(DATA_TECH!$C$4:$C$200,15) | E19: =IFERROR(INDEX(DATA_TECH!$D$4:$D$200,MATCH(LARGE(DATA_TECH!$C$4:$C$200,15),DATA_TECH!$C$4:$C$200,0)),"") | F19: =IFERROR(INDEX(DATA_TECH!$E$4:$E$200,MATCH(LARGE(DATA_TECH!$C$4:$C$200,15),DATA_TECH!$C$4:$C$200,0)),"") | G19: =IFERROR(INDEX(DATA_TECH!$F$4:$F$200,MATCH(LARGE(DATA_TECH!$C$4:$C$200,15),DATA_TECH!$C$4:$C$200,0)),"") | H19: =IFERROR(INDEX(DATA_TECH!$G$4:$G$200,MATCH(LARGE(DATA_TECH!$C$4:$C$200,15),DATA_TECH!$C$4:$C$200,0)),"") | I19: =IFERROR(INDEX(DATA_TECH!$H$4:$H$200,MATCH(LARGE(DATA_TECH!$C$4:$C$200,15),DATA_TECH!$C$4:$C$200,0)),"")
A20: 16 | B20: =IFERROR(INDEX(DATA_TECH!$A$4:$A$200,MATCH(LARGE(DATA_TECH!$C$4:$C$200,16),DATA_TECH!$C$4:$C$200,0)),"") | C20: =IFERROR(INDEX(DATA_TECH!$B$4:$B$200,MATCH(LARGE(DATA_TECH!$C$4:$C$200,16),DATA_TECH!$C$4:$C$200,0)),"") | D20: =LARGE(DATA_TECH!$C$4:$C$200,16) | E20: =IFERROR(INDEX(DATA_TECH!$D$4:$D$200,MATCH(LARGE(DATA_TECH!$C$4:$C$200,16),DATA_TECH!$C$4:$C$200,0)),"") | F20: =IFERROR(INDEX(DATA_TECH!$E$4:$E$200,MATCH(LARGE(DATA_TECH!$C$4:$C$200,16),DATA_TECH!$C$4:$C$200,0)),"") | G20: =IFERROR(INDEX(DATA_TECH!$F$4:$F$200,MATCH(LARGE(DATA_TECH!$C$4:$C$200,16),DATA_TECH!$C$4:$C$200,0)),"") | H20: =IFERROR(INDEX(DATA_TECH!$G$4:$G$200,MATCH(LARGE(DATA_TECH!$C$4:$C$200,16),DATA_TECH!$C$4:$C$200,0)),"") | I20: =IFERROR(INDEX(DATA_TECH!$H$4:$H$200,MATCH(LARGE(DATA_TECH!$C$4:$C$200,16),DATA_TECH!$C$4:$C$200,0)),"")
A21: 17 | B21: =IFERROR(INDEX(DATA_TECH!$A$4:$A$200,MATCH(LARGE(DATA_TECH!$C$4:$C$200,17),DATA_TECH!$C$4:$C$200,0)),"") | C21: =IFERROR(INDEX(DATA_TECH!$B$4:$B$200,MATCH(LARGE(DATA_TECH!$C$4:$C$200,17),DATA_TECH!$C$4:$C$200,0)),"") | D21: =LARGE(DATA_TECH!$C$4:$C$200,17) | E21: =IFERROR(INDEX(DATA_TECH!$D$4:$D$200,MATCH(LARGE(DATA_TECH!$C$4:$C$200,17),DATA_TECH!$C$4:$C$200,0)),"") | F21: =IFERROR(INDEX(DATA_TECH!$E$4:$E$200,MATCH(LARGE(DATA_TECH!$C$4:$C$200,17),DATA_TECH!$C$4:$C$200,0)),"") | G21: =IFERROR(INDEX(DATA_TECH!$F$4:$F$200,MATCH(LARGE(DATA_TECH!$C$4:$C$200,17),DATA_TECH!$C$4:$C$200,0)),"") | H21: =IFERROR(INDEX(DATA_TECH!$G$4:$G$200,MATCH(LARGE(DATA_TECH!$C$4:$C$200,17),DATA_TECH!$C$4:$C$200,0)),"") | I21: =IFERROR(INDEX(DATA_TECH!$H$4:$H$200,MATCH(LARGE(DATA_TECH!$C$4:$C$200,17),DATA_TECH!$C$4:$C$200,0)),"")
A22: 18 | B22: =IFERROR(INDEX(DATA_TECH!$A$4:$A$200,MATCH(LARGE(DATA_TECH!$C$4:$C$200,18),DATA_TECH!$C$4:$C$200,0)),"") | C22: =IFERROR(INDEX(DATA_TECH!$B$4:$B$200,MATCH(LARGE(DATA_TECH!$C$4:$C$200,18),DATA_TECH!$C$4:$C$200,0)),"") | D22: =LARGE(DATA_TECH!$C$4:$C$200,18) | E22: =IFERROR(INDEX(DATA_TECH!$D$4:$D$200,MATCH(LARGE(DATA_TECH!$C$4:$C$200,18),DATA_TECH!$C$4:$C$200,0)),"") | F22: =IFERROR(INDEX(DATA_TECH!$E$4:$E$200,MATCH(LARGE(DATA_TECH!$C$4:$C$200,18),DATA_TECH!$C$4:$C$200,0)),"") | G22: =IFERROR(INDEX(DATA_TECH!$F$4:$F$200,MATCH(LARGE(DATA_TECH!$C$4:$C$200,18),DATA_TECH!$C$4:$C$200,0)),"") | H22: =IFERROR(INDEX(DATA_TECH!$G$4:$G$200,MATCH(LARGE(DATA_TECH!$C$4:$C$200,18),DATA_TECH!$C$4:$C$200,0)),"") | I22: =IFERROR(INDEX(DATA_TECH!$H$4:$H$200,MATCH(LARGE(DATA_TECH!$C$4:$C$200,18),DATA_TECH!$C$4:$C$200,0)),"")
A23: 19 | B23: =IFERROR(INDEX(DATA_TECH!$A$4:$A$200,MATCH(LARGE(DATA_TECH!$C$4:$C$200,19),DATA_TECH!$C$4:$C$200,0)),"") | C23: =IFERROR(INDEX(DATA_TECH!$B$4:$B$200,MATCH(LARGE(DATA_TECH!$C$4:$C$200,19),DATA_TECH!$C$4:$C$200,0)),"") | D23: =LARGE(DATA_TECH!$C$4:$C$200,19) | E23: =IFERROR(INDEX(DATA_TECH!$D$4:$D$200,MATCH(LARGE(DATA_TECH!$C$4:$C$200,19),DATA_TECH!$C$4:$C$200,0)),"") | F23: =IFERROR(INDEX(DATA_TECH!$E$4:$E$200,MATCH(LARGE(DATA_TECH!$C$4:$C$200,19),DATA_TECH!$C$4:$C$200,0)),"") | G23: =IFERROR(INDEX(DATA_TECH!$F$4:$F$200,MATCH(LARGE(DATA_TECH!$C$4:$C$200,19),DATA_TECH!$C$4:$C$200,0)),"") | H23: =IFERROR(INDEX(DATA_TECH!$G$4:$G$200,MATCH(LARGE(DATA_TECH!$C$4:$C$200,19),DATA_TECH!$C$4:$C$200,0)),"") | I23: =IFERROR(INDEX(DATA_TECH!$H$4:$H$200,MATCH(LARGE(DATA_TECH!$C$4:$C$200,19),DATA_TECH!$C$4:$C$200,0)),"")
A24: 20 | B24: =IFERROR(INDEX(DATA_TECH!$A$4:$A$200,MATCH(LARGE(DATA_TECH!$C$4:$C$200,20),DATA_TECH!$C$4:$C$200,0)),"") | C24: =IFERROR(INDEX(DATA_TECH!$B$4:$B$200,MATCH(LARGE(DATA_TECH!$C$4:$C$200,20),DATA_TECH!$C$4:$C$200,0)),"") | D24: =LARGE(DATA_TECH!$C$4:$C$200,20) | E24: =IFERROR(INDEX(DATA_TECH!$D$4:$D$200,MATCH(LARGE(DATA_TECH!$C$4:$C$200,20),DATA_TECH!$C$4:$C$200,0)),"") | F24: =IFERROR(INDEX(DATA_TECH!$E$4:$E$200,MATCH(LARGE(DATA_TECH!$C$4:$C$200,20),DATA_TECH!$C$4:$C$200,0)),"") | G24: =IFERROR(INDEX(DATA_TECH!$F$4:$F$200,MATCH(LARGE(DATA_TECH!$C$4:$C$200,20),DATA_TECH!$C$4:$C$200,0)),"") | H24: =IFERROR(INDEX(DATA_TECH!$G$4:$G$200,MATCH(LARGE(DATA_TECH!$C$4:$C$200,20),DATA_TECH!$C$4:$C$200,0)),"") | I24: =IFERROR(INDEX(DATA_TECH!$H$4:$H$200,MATCH(LARGE(DATA_TECH!$C$4:$C$200,20),DATA_TECH!$C$4:$C$200,0)),"")

Sheet TOP_HC
A1: FinSight | C1: TOP HC — Classement dynamique Santé par Score FinSight
A2: Classement calculé dynamiquement via LARGE / INDEX / MATCH depuis DATA_HC · 6 entités
A3: TOUTES VALEURS — SANTÉ (classées par Score)
A4: RANG | B4: TICKER | C4: SOCIÉTÉ | D4: SCORE | E4: P/E | F4: EV/EBITDA | G4: MG EBITDA | H4: ROE | I4: CROISS. REV.
A5: 1 | B5: =IFERROR(INDEX(DATA_HC!$A$4:$A$200,MATCH(LARGE(DATA_HC!$C$4:$C$200,1),DATA_HC!$C$4:$C$200,0)),"") | C5: =IFERROR(INDEX(DATA_HC!$B$4:$B$200,MATCH(LARGE(DATA_HC!$C$4:$C$200,1),DATA_HC!$C$4:$C$200,0)),"") | D5: =LARGE(DATA_HC!$C$4:$C$200,1) | E5: =IFERROR(INDEX(DATA_HC!$D$4:$D$200,MATCH(LARGE(DATA_HC!$C$4:$C$200,1),DATA_HC!$C$4:$C$200,0)),"") | F5: =IFERROR(INDEX(DATA_HC!$E$4:$E$200,MATCH(LARGE(DATA_HC!$C$4:$C$200,1),DATA_HC!$C$4:$C$200,0)),"") | G5: =IFERROR(INDEX(DATA_HC!$F$4:$F$200,MATCH(LARGE(DATA_HC!$C$4:$C$200,1),DATA_HC!$C$4:$C$200,0)),"") | H5: =IFERROR(INDEX(DATA_HC!$G$4:$G$200,MATCH(LARGE(DATA_HC!$C$4:$C$200,1),DATA_HC!$C$4:$C$200,0)),"") | I5: =IFERROR(INDEX(DATA_HC!$H$4:$H$200,MATCH(LARGE(DATA_HC!$C$4:$C$200,1),DATA_HC!$C$4:$C$200,0)),"")
A6: 2 | B6: =IFERROR(INDEX(DATA_HC!$A$4:$A$200,MATCH(LARGE(DATA_HC!$C$4:$C$200,2),DATA_HC!$C$4:$C$200,0)),"") | C6: =IFERROR(INDEX(DATA_HC!$B$4:$B$200,MATCH(LARGE(DATA_HC!$C$4:$C$200,2),DATA_HC!$C$4:$C$200,0)),"") | D6: =LARGE(DATA_HC!$C$4:$C$200,2) | E6: =IFERROR(INDEX(DATA_HC!$D$4:$D$200,MATCH(LARGE(DATA_HC!$C$4:$C$200,2),DATA_HC!$C$4:$C$200,0)),"") | F6: =IFERROR(INDEX(DATA_HC!$E$4:$E$200,MATCH(LARGE(DATA_HC!$C$4:$C$200,2),DATA_HC!$C$4:$C$200,0)),"") | G6: =IFERROR(INDEX(DATA_HC!$F$4:$F$200,MATCH(LARGE(DATA_HC!$C$4:$C$200,2),DATA_HC!$C$4:$C$200,0)),"") | H6: =IFERROR(INDEX(DATA_HC!$G$4:$G$200,MATCH(LARGE(DATA_HC!$C$4:$C$200,2),DATA_HC!$C$4:$C$200,0)),"") | I6: =IFERROR(INDEX(DATA_HC!$H$4:$H$200,MATCH(LARGE(DATA_HC!$C$4:$C$200,2),DATA_HC!$C$4:$C$200,0)),"")
A7: 3 | B7: =IFERROR(INDEX(DATA_HC!$A$4:$A$200,MATCH(LARGE(DATA_HC!$C$4:$C$200,3),DATA_HC!$C$4:$C$200,0)),"") | C7: =IFERROR(INDEX(DATA_HC!$B$4:$B$200,MATCH(LARGE(DATA_HC!$C$4:$C$200,3),DATA_HC!$C$4:$C$200,0)),"") | D7: =LARGE(DATA_HC!$C$4:$C$200,3) | E7: =IFERROR(INDEX(DATA_HC!$D$4:$D$200,MATCH(LARGE(DATA_HC!$C$4:$C$200,3),DATA_HC!$C$4:$C$200,0)),"") | F7: =IFERROR(INDEX(DATA_HC!$E$4:$E$200,MATCH(LARGE(DATA_HC!$C$4:$C$200,3),DATA_HC!$C$4:$C$200,0)),"") | G7: =IFERROR(INDEX(DATA_HC!$F$4:$F$200,MATCH(LARGE(DATA_HC!$C$4:$C$200,3),DATA_HC!$C$4:$C$200,0)),"") | H7: =IFERROR(INDEX(DATA_HC!$G$4:$G$200,MATCH(LARGE(DATA_HC!$C$4:$C$200,3),DATA_HC!$C$4:$C$200,0)),"") | I7: =IFERROR(INDEX(DATA_HC!$H$4:$H$200,MATCH(LARGE(DATA_HC!$C$4:$C$200,3),DATA_HC!$C$4:$C$200,0)),"")
A8: 4 | B8: =IFERROR(INDEX(DATA_HC!$A$4:$A$200,MATCH(LARGE(DATA_HC!$C$4:$C$200,4),DATA_HC!$C$4:$C$200,0)),"") | C8: =IFERROR(INDEX(DATA_HC!$B$4:$B$200,MATCH(LARGE(DATA_HC!$C$4:$C$200,4),DATA_HC!$C$4:$C$200,0)),"") | D8: =IFERROR(LARGE(DATA_HC!$C$4:$C$200,4),"—") | E8: =IFERROR(INDEX(DATA_HC!$D$4:$D$200,MATCH(LARGE(DATA_HC!$C$4:$C$200,4),DATA_HC!$C$4:$C$200,0)),"") | F8: =IFERROR(INDEX(DATA_HC!$E$4:$E$200,MATCH(LARGE(DATA_HC!$C$4:$C$200,4),DATA_HC!$C$4:$C$200,0)),"") | G8: =IFERROR(INDEX(DATA_HC!$F$4:$F$200,MATCH(LARGE(DATA_HC!$C$4:$C$200,4),DATA_HC!$C$4:$C$200,0)),"") | H8: =IFERROR(INDEX(DATA_HC!$G$4:$G$200,MATCH(LARGE(DATA_HC!$C$4:$C$200,4),DATA_HC!$C$4:$C$200,0)),"") | I8: =IFERROR(INDEX(DATA_HC!$H$4:$H$200,MATCH(LARGE(DATA_HC!$C$4:$C$200,4),DATA_HC!$C$4:$C$200,0)),"")
A9: 5 | B9: =IFERROR(INDEX(DATA_HC!$A$4:$A$200,MATCH(LARGE(DATA_HC!$C$4:$C$200,5),DATA_HC!$C$4:$C$200,0)),"") | C9: =IFERROR(INDEX(DATA_HC!$B$4:$B$200,MATCH(LARGE(DATA_HC!$C$4:$C$200,5),DATA_HC!$C$4:$C$200,0)),"") | D9: =IFERROR(LARGE(DATA_HC!$C$4:$C$200,5),"—") | E9: =IFERROR(INDEX(DATA_HC!$D$4:$D$200,MATCH(LARGE(DATA_HC!$C$4:$C$200,5),DATA_HC!$C$4:$C$200,0)),"") | F9: =IFERROR(INDEX(DATA_HC!$E$4:$E$200,MATCH(LARGE(DATA_HC!$C$4:$C$200,5),DATA_HC!$C$4:$C$200,0)),"") | G9: =IFERROR(INDEX(DATA_HC!$F$4:$F$200,MATCH(LARGE(DATA_HC!$C$4:$C$200,5),DATA_HC!$C$4:$C$200,0)),"") | H9: =IFERROR(INDEX(DATA_HC!$G$4:$G$200,MATCH(LARGE(DATA_HC!$C$4:$C$200,5),DATA_HC!$C$4:$C$200,0)),"") | I9: =IFERROR(INDEX(DATA_HC!$H$4:$H$200,MATCH(LARGE(DATA_HC!$C$4:$C$200,5),DATA_HC!$C$4:$C$200,0)),"")
A10: 6 | B10: =IFERROR(INDEX(DATA_HC!$A$4:$A$200,MATCH(LARGE(DATA_HC!$C$4:$C$200,6),DATA_HC!$C$4:$C$200,0)),"") | C10: =IFERROR(INDEX(DATA_HC!$B$4:$B$200,MATCH(LARGE(DATA_HC!$C$4:$C$200,6),DATA_HC!$C$4:$C$200,0)),"") | D10: =IFERROR(LARGE(DATA_HC!$C$4:$C$200,6),"—") | E10: =IFERROR(INDEX(DATA_HC!$D$4:$D$200,MATCH(LARGE(DATA_HC!$C$4:$C$200,6),DATA_HC!$C$4:$C$200,0)),"") | F10: =IFERROR(INDEX(DATA_HC!$E$4:$E$200,MATCH(LARGE(DATA_HC!$C$4:$C$200,6),DATA_HC!$C$4:$C$200,0)),"") | G10: =IFERROR(INDEX(DATA_HC!$F$4:$F$200,MATCH(LARGE(DATA_HC!$C$4:$C$200,6),DATA_HC!$C$4:$C$200,0)),"") | H10: =IFERROR(INDEX(DATA_HC!$G$4:$G$200,MATCH(LARGE(DATA_HC!$C$4:$C$200,6),DATA_HC!$C$4:$C$200,0)),"") | I10: =IFERROR(INDEX(DATA_HC!$H$4:$H$200,MATCH(LARGE(DATA_HC!$C$4:$C$200,6),DATA_HC!$C$4:$C$200,0)),"")

Sheet DATA_TECH
A1: FinSight | C1: DATA TECH — Données brutes Technologie · 88 valeurs | J1: Technologie
A2: Source : FinSight IA · Univers Technologie S&P500 / Nasdaq / Europe · Données au 12.04.2026
A3: TICKER | B3: SOCIÉTÉ | C3: SCORE FINSIGHT | D3: P/E | E3: EV/EBITDA | F3: MARGE EBITDA | G3: ROE | H3: CROISS. REV.
A4: GOOGL | B4: Alphabet Inc. | C4: 75 | D4: 14.7 | E4: 10.8 | F4: 44.9 | G4: 31.8 | H4: 15.1 | I4: =RANK.EQ(C4,$C$4:$C$9999,0)+COUNTIF($C$5:C4,C4)-1
A5: NVDA | B5: NVIDIA Corporation | C5: 67 | D5: 39.8 | E5: 33 | F5: 66.9 | G5: 76.3 | H5: 65.5 | I5: =RANK.EQ(C5,$C$4:$C$9999,0)+COUNTIF($C$5:C5,C5)-1
A6: META | B6: Meta Platforms, Inc. | C6: 64 | D6: 24 | E6: 13.9 | F6: 52.6 | G6: 27.8 | H6: 22.2 | I6: =RANK.EQ(C6,$C$4:$C$9999,0)+COUNTIF($C$5:C6,C6)-1
A7: INTC | B7: Intel Corporation | C7: 64 | E7: 24.6 | F7: 27.2 | G7: -20 | H7: -50 | I7: =RANK.EQ(C7,$C$4:$C$9999,0)+COUNTIF($C$5:C7,C7)-1
A8: ADBE | B8: Adobe Inc. | C8: 58 | D8: 13.4 | E8: 9.8 | F8: 41.3 | G8: 61.3 | H8: 10.5 | I8: =RANK.EQ(C8,$C$4:$C$9999,0)+COUNTIF($C$5:C8,C8)-1
A9: MSFT | B9: Microsoft Corporation | C9: 47 | D9: 28.7 | E9: 18.3 | F9: 56.9 | G9: 29.6 | H9: 14.9 | I9: =RANK.EQ(C9,$C$4:$C$9999,0)+COUNTIF($C$5:C9,C9)-1
A10: CRM | B10: Salesforce, Inc. | C10: 44 | D10: 21.2 | E10: 13.2 | F10: 30.2 | G10: 12.6 | H10: 9.6 | I10: =RANK.EQ(C10,$C$4:$C$9999,0)+COUNTIF($C$5:C10,C10)-1
A11: CSCO | B11: Cisco Systems, Inc. | C11: 30 | D11: 32 | E11: 22.3 | F11: 27.4 | G11: 21.7 | H11: 5.3 | I11: =RANK.EQ(C11,$C$4:$C$9999,0)+COUNTIF($C$5:C11,C11)-1
A12: AAPL | B12: Apple Inc. | C12: 25 | D12: 33.9 | E12: 26.7 | F12: 34.8 | G12: 151.9 | H12: 6.4 | I12: =RANK.EQ(C12,$C$4:$C$9999,0)+COUNTIF($C$5:C12,C12)-1
A13: ORCL | B13: Oracle Corporation | C13: 25 | D13: 37.6 | E13: 23 | F13: 41.7 | G13: 60.8 | H13: 8.4 | I13: =RANK.EQ(C13,$C$4:$C$9999,0)+COUNTIF($C$5:C13,C13)-1

Sheet DATA_HC
A1: FinSight | C1: DATA HC — Données brutes Santé · 6 valeurs | I1: Santé
A2: Source : FinSight IA · Univers Santé · Benchmark sectoriel · Données au 12.04.2026
A3: TICKER | B3: SOCIÉTÉ | C3: SCORE FINSIGHT | D3: P/E | E3: EV/EBITDA | F3: MARGE EBITDA | G3: ROE | H3: CROISS. REV.
A4: JNJ | B4: Johnson & Johnson | C4: 75 | D4: 21.6 | E4: 14.8 | F4: 43.6 | G4: 32.9 | H4: 6
A5: MRK | B5: Merck & Co., Inc. | C5: 75 | D5: 16.2 | E5: 11.7 | F5: 43.5 | G5: 34.7 | H5: 130
A6: LLY | B6: Eli Lilly and Company | C6: 65 | D6: 39.9 | E6: 27.1 | F6: 48.6 | G6: 77.8 | H6: 44.7
A7: PFE | B7: Pfizer Inc. | C7: 40 | D7: 19.8 | E7: 12.9 | F7: 26.8 | G7: 9 | H7: -160
A8: ABBV | B8: AbbVie Inc. | C8: 25 | D8: 88 | E8: 24.6 | F8: 28.8 | G8: -129.2 | H8: 8.6
A9: UNH | B9: UnitedHealth Group Incorporated | C9: 20 | D9: 23.7 | E9: 14.7 | F9: 5.2 | G9: 12.8 | H9: 11.8
