Workbook

Sheet DASHBOARD
B1: FinSight IA · Énergie Screening — Tableau de Bord
C3: =COUNTA('DONNÉES BRUTES'!A$3:A$90) -> 88 | H3: =ROUND(AVERAGE('DONNÉES BRUTES'!AB$3:AB$90),0)&"/100" -> 53/100 | L3: =IFERROR(_xlfn.XLOOKUP(MAX('DONNÉES BRUTES'!AB$3:AB$90),'DONNÉES BRUTES'!AB$3:AB$90,'DONNÉES BRUTES'!A$3:A$90)&" — "&MAX('DONNÉES BRUTES'!AB$3:AB$90)&"/100","—") -> ENI.MI — 79/100 | Q3: 16/04/2026
C4: SOCIÉTÉS ANALYSÉES | H4: SCORE MOYEN SECTEUR | L4: MEILLEUR SCORE GLOBAL | Q4: DATE D'ANALYSE
B6: TOP 5 · Classements par Facteur · Growth | H6: Quality | N6: Momentum
B7: # | C7: Ticker | D7: Société | E7: Score | F7: Croiss. Rev | H7: # | I7: Ticker | J7: Société | K7: Score | L7: Altman Z | N7: # | O7: Ticker | P7: Société | Q7: Score | R7: Mom 52W
B8: 1 | C8: =IFERROR(INDEX('DONNÉES BRUTES'!A$3:A$90,MATCH(LARGE('DONNÉES BRUTES'!Y$3:Y$90,1),'DONNÉES BRUTES'!Y$3:Y$90,0)),"—") -> EXE | D8: =IFERROR(_xlfn.XLOOKUP(C8,'DONNÉES BRUTES'!A$3:A$90,'DONNÉES BRUTES'!B$3:B$90),"—") -> Expand Energy Corporation | E8: =IFERROR(_xlfn.XLOOKUP(C8,'DONNÉES BRUTES'!A$3:A$90,'DONNÉES BRUTES'!Y$3:Y$90)&"/100","—") -> 100/100 | F8: =IFERROR(_xlfn.XLOOKUP(C8,'DONNÉES BRUTES'!A$3:A$90,'DONNÉES BRUTES'!P$3:P$90),"—") -> 1.888 | H8: 1 | I8: =IFERROR(INDEX('DONNÉES BRUTES'!A$3:A$90,MATCH(LARGE('DONNÉES BRUTES'!Z$3:Z$90,1),'DONNÉES BRUTES'!Z$3:Z$90,0)),"—") -> TPL | J8: =IFERROR(_xlfn.XLOOKUP(I8,'DONNÉES BRUTES'!A$3:A$90,'DONNÉES BRUTES'!B$3:B$90),"—") -> Texas Pacific Land Corporation | K8: =IFERROR(_xlfn.XLOOKUP(I8,'DONNÉES BRUTES'!A$3:A$90,'DONNÉES BRUTES'!Z$3:Z$90)&"/100","—") -> 91/100 | L8: =IFERROR(_xlfn.XLOOKUP(I8,'DONNÉES BRUTES'!A$3:A$90,'DONNÉES BRUTES'!U$3:U$90),"—") -> 16.05 | N8: 1 | O8: =IFERROR(_xlfn.XLOOKUP(LARGE('DONNÉES BRUTES'!AA$3:AA$90,1),'DONNÉES BRUTES'!AA$3:AA$90,'DONNÉES BRUTES'!A$3:A$90),"—") -> APA | P8: =IFERROR(_xlfn.XLOOKUP(O8,'DONNÉES BRUTES'!A$3:A$90,'DONNÉES BRUTES'!B$3:B$90),"—") -> APA Corporation | Q8: =IFERROR(_xlfn.XLOOKUP(O8,'DONNÉES BRUTES'!A$3:A$90,'DONNÉES BRUTES'!AA$3:AA$90)&"/100","—") -> 100/100 | R8: =IFERROR(_xlfn.XLOOKUP(O8,'DONNÉES BRUTES'!A$3:A$90,'DONNÉES BRUTES'!W$3:W$90),"—") -> +129.6%
B9: 2 | C9: {=IFERROR(INDEX('DONNÉES BRUTES'!A$3:A$90,MATCH(1,('DONNÉES BRUTES'!Y$3:Y$90=LARGE('DONNÉES BRUTES'!Y$3:Y$90,2))*(COUNTIF(C$8:C8,'DONNÉES BRUTES'!A$3:A$90)=0)*('DONNÉES BRUTES'!A$3:A$90<>""),0)),"—")} -> EQT | D9: =IFERROR(_xlfn.XLOOKUP(C9,'DONNÉES BRUTES'!A$3:A$90,'DONNÉES BRUTES'!B$3:B$90),"—") -> EQT Corporation | E9: =IFERROR(_xlfn.XLOOKUP(C9,'DONNÉES BRUTES'!A$3:A$90,'DONNÉES BRUTES'!Y$3:Y$90)&"/100","—") -> 96/100 | F9: =IFERROR(_xlfn.XLOOKUP(C9,'DONNÉES BRUTES'!A$3:A$90,'DONNÉES BRUTES'!P$3:P$90),"—") -> 0.6 | H9: 2 | I9: {=IFERROR(INDEX('DONNÉES BRUTES'!A$3:A$90,MATCH(1,('DONNÉES BRUTES'!Z$3:Z$90=LARGE('DONNÉES BRUTES'!Z$3:Z$90,2))*(COUNTIF(I$8:I8,'DONNÉES BRUTES'!A$3:A$90)=0)*('DONNÉES BRUTES'!A$3:A$90<>""),0)),"—")} -> AMAT | J9: =IFERROR(_xlfn.XLOOKUP(I9,'DONNÉES BRUTES'!A$3:A$90,'DONNÉES BRUTES'!B$3:B$90),"—") -> Applied Materials, Inc. | K9: =IFERROR(_xlfn.XLOOKUP(I9,'DONNÉES BRUTES'!A$3:A$90,'DONNÉES BRUTES'!Z$3:Z$90)&"/100","—") -> 91/100 | L9: =IFERROR(_xlfn.XLOOKUP(I9,'DONNÉES BRUTES'!A$3:A$90,'DONNÉES BRUTES'!U$3:U$90),"—") -> 10.40 | N9: 2 | O9: =IFERROR(_xlfn.XLOOKUP(LARGE('DONNÉES BRUTES'!AA$3:AA$90,2),'DONNÉES BRUTES'!AA$3:AA$90,'DONNÉES BRUTES'!A$3:A$90),"—") -> APA | P9: =IFERROR(_xlfn.XLOOKUP(O9,'DONNÉES BRUTES'!A$3:A$90,'DONNÉES BRUTES'!B$3:B$90),"—") -> APA Corporation | Q9: =IFERROR(_xlfn.XLOOKUP(O9,'DONNÉES BRUTES'!A$3:A$90,'DONNÉES BRUTES'!AA$3:AA$90)&"/100","—") -> 100/100 | R9: =IFERROR(_xlfn.XLOOKUP(O9,'DONNÉES BRUTES'!A$3:A$90,'DONNÉES BRUTES'!W$3:W$90),"—") -> +129.6%
B10: 3 | C10: {=IFERROR(INDEX('DONNÉES BRUTES'!A$3:A$90,MATCH(1,('DONNÉES BRUTES'!Y$3:Y$90>=LARGE('DONNÉES BRUTES'!Y$3:Y$90,3))*(COUNTIF(C$8:C9,'DONNÉES BRUTES'!A$3:A$90)=0)*('DONNÉES BRUTES'!A$3:A$90<>""),0)),"—")} -> ENI.MI | D10: =IFERROR(_xlfn.XLOOKUP(C10,'DONNÉES BRUTES'!A$3:A$90,'DONNÉES BRUTES'!B$3:B$90),"—") -> Eni S.p.A. | E10: =IFERROR(_xlfn.XLOOKUP(C10,'DONNÉES BRUTES'!A$3:A$90,'DONNÉES BRUTES'!Y$3:Y$90)&"/100","—") -> —/100 | F10: =IFERROR(_xlfn.XLOOKUP(C10,'DONNÉES BRUTES'!A$3:A$90,'DONNÉES BRUTES'!P$3:P$90),"—") -> — | H10: 3 | I10: {=IFERROR(INDEX('DONNÉES BRUTES'!A$3:A$90,MATCH(1,('DONNÉES BRUTES'!Z$3:Z$90>=LARGE('DONNÉES BRUTES'!Z$3:Z$90,3))*(COUNTIF(I$8:I9,'DONNÉES BRUTES'!A$3:A$90)=0)*('DONNÉES BRUTES'!A$3:A$90<>""),0)),"—")} -> FTNT | J10: =IFERROR(_xlfn.XLOOKUP(I10,'DONNÉES BRUTES'!A$3:A$90,'DONNÉES BRUTES'!B$3:B$90),"—") -> Fortinet, Inc. | K10: =IFERROR(_xlfn.XLOOKUP(I10,'DONNÉES BRUTES'!A$3:A$90,'DONNÉES BRUTES'!Z$3:Z$90)&"/100","—") -> 91/100 | L10: =IFERROR(_xlfn.XLOOKUP(I10,'DONNÉES BRUTES'!A$3:A$90,'DONNÉES BRUTES'!U$3:U$90),"—") -> 2.02 | N10: 3 | O10: =IFERROR(_xlfn.XLOOKUP(LARGE('DONNÉES BRUTES'!AA$3:AA$90,3),'DONNÉES BRUTES'!AA$3:AA$90,'DONNÉES BRUTES'!A$3:A$90),"—") -> CIEN | P10: =IFERROR(_xlfn.XLOOKUP(O10,'DONNÉES BRUTES'!A$3:A$90,'DONNÉES BRUTES'!B$3:B$90),"—") -> Ciena Corporation | Q10: =IFERROR(_xlfn.XLOOKUP(O10,'DONNÉES BRUTES'!A$3:A$90,'DONNÉES BRUTES'!AA$3:AA$90)&"/100","—") -> 98/100 | R10: =IFERROR(_xlfn.XLOOKUP(O10,'DONNÉES BRUTES'!A$3:A$90,'DONNÉES BRUTES'!W$3:W$90),"—") -> +454.6%
B11: 4 | C11: {=IFERROR(INDEX('DONNÉES BRUTES'!A$3:A$90,MATCH(1,('DONNÉES BRUTES'!Y$3:Y$90>=LARGE('DONNÉES BRUTES'!Y$3:Y$90,4))*(COUNTIF(C$8:C10,'DONNÉES BRUTES'!A$3:A$90)=0)*('DONNÉES BRUTES'!A$3:A$90<>""),0)),"—")} -> CTRA | D11: =IFERROR(_xlfn.XLOOKUP(C11,'DONNÉES BRUTES'!A$3:A$90,'DONNÉES BRUTES'!B$3:B$90),"—") -> Coterra Energy Inc. | E11: =IFERROR(_xlfn.XLOOKUP(C11,'DONNÉES BRUTES'!A$3:A$90,'DONNÉES BRUTES'!Y$3:Y$90)&"/100","—") -> 92/100 | F11: =IFERROR(_xlfn.XLOOKUP(C11,'DONNÉES BRUTES'!A$3:A$90,'DONNÉES BRUTES'!P$3:P$90),"—") -> 0.401 | H11: 4 | I11: {=IFERROR(INDEX('DONNÉES BRUTES'!A$3:A$90,MATCH(1,('DONNÉES BRUTES'!Z$3:Z$90>=LARGE('DONNÉES BRUTES'!Z$3:Z$90,4))*(COUNTIF(I$8:I10,'DONNÉES BRUTES'!A$3:A$90)=0)*('DONNÉES BRUTES'!A$3:A$90<>""),0)),"—")} -> ADBE | J11: =IFERROR(_xlfn.XLOOKUP(I11,'DONNÉES BRUTES'!A$3:A$90,'DONNÉES BRUTES'!B$3:B$90),"—") -> Adobe Inc. | K11: =IFERROR(_xlfn.XLOOKUP(I11,'DONNÉES BRUTES'!A$3:A$90,'DONNÉES BRUTES'!Z$3:Z$90)&"/100","—") -> 91/100 | L11: =IFERROR(_xlfn.XLOOKUP(I11,'DONNÉES BRUTES'!A$3:A$90,'DONNÉES BRUTES'!U$3:U$90),"—") -> 7.74 | N11: 4 | O11: =IFERROR(_xlfn.XLOOKUP(LARGE('DONNÉES BRUTES'!AA$3:AA$90,4),'DONNÉES BRUTES'!AA$3:AA$90,'DONNÉES BRUTES'!A$3:A$90),"—") -> HAL | P11: =IFERROR(_xlfn.XLOOKUP(O11,'DONNÉES BRUTES'!A$3:A$90,'DONNÉES BRUTES'!B$3:B$90),"—") -> Halliburton Company | Q11: =IFERROR(_xlfn.XLOOKUP(O11,'DONNÉES BRUTES'!A$3:A$90,'DONNÉES BRUTES'!AA$3:AA$90)&"/100","—") -> 96/100 | R11: =IFERROR(_xlfn.XLOOKUP(O11,'DONNÉES BRUTES'!A$3:A$90,'DONNÉES BRUTES'!W$3:W$90),"—") -> +99.5%
B12: 5 | C12: {=IFERROR(INDEX('DONNÉES BRUTES'!A$3:A$90,MATCH(1,('DONNÉES BRUTES'!Y$3:Y$90>=LARGE('DONNÉES BRUTES'!Y$3:Y$90,5))*(COUNTIF(C$8:C11,'DONNÉES BRUTES'!A$3:A$90)=0)*('DONNÉES BRUTES'!A$3:A$90<>""),0)),"—")} -> OKE | D12: =IFERROR(_xlfn.XLOOKUP(C12,'DONNÉES BRUTES'!A$3:A$90,'DONNÉES BRUTES'!B$3:B$90),"—") -> ONEOK, Inc. | E12: =IFERROR(_xlfn.XLOOKUP(C12,'DONNÉES BRUTES'!A$3:A$90,'DONNÉES BRUTES'!Y$3:Y$90)&"/100","—") -> 88/100 | F12: =IFERROR(_xlfn.XLOOKUP(C12,'DONNÉES BRUTES'!A$3:A$90,'DONNÉES BRUTES'!P$3:P$90),"—") -> 0.55 | H12: 5 | I12: {=IFERROR(INDEX('DONNÉES BRUTES'!A$3:A$90,MATCH(1,('DONNÉES BRUTES'!Z$3:Z$90>=LARGE('DONNÉES BRUTES'!Z$3:Z$90,5))*(COUNTIF(I$8:I11,'DONNÉES BRUTES'!A$3:A$90)=0)*('DONNÉES BRUTES'!A$3:A$90<>""),0)),"—")} -> CRM | J12: =IFERROR(_xlfn.XLOOKUP(I12,'DONNÉES BRUTES'!A$3:A$90,'DONNÉES BRUTES'!B$3:B$90),"—") -> Salesforce, Inc. | K12: =IFERROR(_xlfn.XLOOKUP(I12,'DONNÉES BRUTES'!A$3:A$90,'DONNÉES BRUTES'!Z$3:Z$90)&"/100","—") -> 88/100 | L12: =IFERROR(_xlfn.XLOOKUP(I12,'DONNÉES BRUTES'!A$3:A$90,'DONNÉES BRUTES'!U$3:U$90),"—") -> — | N12: 5 | O12: =IFERROR(_xlfn.XLOOKUP(LARGE('DONNÉES BRUTES'!AA$3:AA$90,5),'DONNÉES BRUTES'!AA$3:AA$90,'DONNÉES BRUTES'!A$3:A$90),"—") -> VLO | P12: =IFERROR(_xlfn.XLOOKUP(O12,'DONNÉES BRUTES'!A$3:A$90,'DONNÉES BRUTES'!B$3:B$90),"—") -> Valero Energy Corporation | Q12: =IFERROR(_xlfn.XLOOKUP(O12,'DONNÉES BRUTES'!A$3:A$90,'DONNÉES BRUTES'!AA$3:AA$90)&"/100","—") -> 92/100 | R12: =IFERROR(_xlfn.XLOOKUP(O12,'DONNÉES BRUTES'!A$3:A$90,'DONNÉES BRUTES'!W$3:W$90),"—") -> +92.9%
B14: TOP 10 GLOBAL · Score Composite · Growth / Quality / Momentum
B15: # | C15: Ticker | D15: Société | E15: Score | G15: Revenue | H15: Rev Gr YoY | I15: EBITDA | K15: Mg EBITDA | L15: Mg Nette | N15: ROE | O15: EV/EBITDA
B16: 1 | C16: =IFERROR(_xlfn.XLOOKUP(LARGE('DONNÉES BRUTES'!AB$3:AB$90,1),'DONNÉES BRUTES'!AB$3:AB$90,'DONNÉES BRUTES'!A$3:A$90),"—") -> ENI.MI | D16: =IFERROR(_xlfn.XLOOKUP(C16,'DONNÉES BRUTES'!A$3:A$90,'DONNÉES BRUTES'!B$3:B$90),"—") -> Eni S.p.A. | E16: =IFERROR(_xlfn.XLOOKUP(C16,'DONNÉES BRUTES'!A$3:A$90,'DONNÉES BRUTES'!AB$3:AB$90)&"/100","—") -> 79/100 | G16: =IFERROR(_xlfn.XLOOKUP(C16,'DONNÉES BRUTES'!A$3:A$90,'DONNÉES BRUTES'!G$3:G$90),"—") -> — | H16: =IFERROR(_xlfn.XLOOKUP(C16,'DONNÉES BRUTES'!A$3:A$90,'DONNÉES BRUTES'!P$3:P$90),"—") -> — | I16: =IFERROR(_xlfn.XLOOKUP(C16,'DONNÉES BRUTES'!A$3:A$90,'DONNÉES BRUTES'!H$3:H$90),"—") -> — | K16: =IFERROR(_xlfn.XLOOKUP(C16,'DONNÉES BRUTES'!A$3:A$90,'DONNÉES BRUTES'!N$3:N$90),"—") -> — | L16: =IFERROR(_xlfn.XLOOKUP(C16,'DONNÉES BRUTES'!A$3:A$90,'DONNÉES BRUTES'!O$3:O$90),"—") -> — | N16: =IFERROR(_xlfn.XLOOKUP(C16,'DONNÉES BRUTES'!A$3:A$90,'DONNÉES BRUTES'!Q$3:Q$90),"—") -> — | O16: =IFERROR(_xlfn.XLOOKUP(C16,'DONNÉES BRUTES'!A$3:A$90,'DONNÉES BRUTES'!I$3:I$90),"—") -> —
B17: 2 | C17: {=IFERROR(INDEX('DONNÉES BRUTES'!A$3:A$90,MATCH(1,('DONNÉES BRUTES'!AB$3:AB$90=LARGE('DONNÉES BRUTES'!AB$3:AB$90,2))*(COUNTIF(C$16:C16,'DONNÉES BRUTES'!A$3:A$90)=0)*('DONNÉES BRUTES'!A$3:A$90<>""),0)),"—")} -> APA | D17: =IFERROR(_xlfn.XLOOKUP(C17,'DONNÉES BRUTES'!A$3:A$90,'DONNÉES BRUTES'!B$3:B$90),"—") -> APA Corporation | E17: =IFERROR(_xlfn.XLOOKUP(C17,'DONNÉES BRUTES'!A$3:A$90,'DONNÉES BRUTES'!AB$3:AB$90)&"/100","—") -> 77/100 | G17: =IFERROR(_xlfn.XLOOKUP(C17,'DONNÉES BRUTES'!A$3:A$90,'DONNÉES BRUTES'!G$3:G$90),"—") -> $8.9 | H17: =IFERROR(_xlfn.XLOOKUP(C17,'DONNÉES BRUTES'!A$3:A$90,'DONNÉES BRUTES'!P$3:P$90),"—") -> -0.084 | I17: =IFERROR(_xlfn.XLOOKUP(C17,'DONNÉES BRUTES'!A$3:A$90,'DONNÉES BRUTES'!H$3:H$90),"—") -> $5.4 | K17: =IFERROR(_xlfn.XLOOKUP(C17,'DONNÉES BRUTES'!A$3:A$90,'DONNÉES BRUTES'!N$3:N$90),"—") -> 0.602 | L17: =IFERROR(_xlfn.XLOOKUP(C17,'DONNÉES BRUTES'!A$3:A$90,'DONNÉES BRUTES'!O$3:O$90),"—") -> 0.161 | N17: =IFERROR(_xlfn.XLOOKUP(C17,'DONNÉES BRUTES'!A$3:A$90,'DONNÉES BRUTES'!Q$3:Q$90),"—") -> 0.235 | O17: =IFERROR(_xlfn.XLOOKUP(C17,'DONNÉES BRUTES'!A$3:A$90,'DONNÉES BRUTES'!I$3:I$90),"—") -> 3.2x
B18: 3 | C18: {=IFERROR(INDEX('DONNÉES BRUTES'!A$3:A$90,MATCH(1,('DONNÉES BRUTES'!AB$3:AB$90>=LARGE('DONNÉES BRUTES'!AB$3:AB$90,3))*(COUNTIF(C$16:C17,'DONNÉES BRUTES'!A$3:A$90)=0)*('DONNÉES BRUTES'!A$3:A$90<>""),0)),"—")} -> TTE.PA | D18: =IFERROR(_xlfn.XLOOKUP(C18,'DONNÉES BRUTES'!A$3:A$90,'DONNÉES BRUTES'!B$3:B$90),"—") -> TotalEnergies SE | E18: =IFERROR(_xlfn.XLOOKUP(C18,'DONNÉES BRUTES'!A$3:A$90,'DONNÉES BRUTES'!AB$3:AB$90)&"/100","—") -> 77/100 | G18: =IFERROR(_xlfn.XLOOKUP(C18,'DONNÉES BRUTES'!A$3:A$90,'DONNÉES BRUTES'!G$3:G$90),"—") -> — | H18: =IFERROR(_xlfn.XLOOKUP(C18,'DONNÉES BRUTES'!A$3:A$90,'DONNÉES BRUTES'!P$3:P$90),"—") -> — | I18: =IFERROR(_xlfn.XLOOKUP(C18,'DONNÉES BRUTES'!A$3:A$90,'DONNÉES BRUTES'!H$3:H$90),"—") -> — | K18: =IFERROR(_xlfn.XLOOKUP(C18,'DONNÉES BRUTES'!A$3:A$90,'DONNÉES BRUTES'!N$3:N$90),"—") -> — | L18: =IFERROR(_xlfn.XLOOKUP(C18,'DONNÉES BRUTES'!A$3:A$90,'DONNÉES BRUTES'!O$3:O$90),"—") -> — | N18: =IFERROR(_xlfn.XLOOKUP(C18,'DONNÉES BRUTES'!A$3:A$90,'DONNÉES BRUTES'!Q$3:Q$90),"—") -> — | O18: =IFERROR(_xlfn.XLOOKUP(C18,'DONNÉES BRUTES'!A$3:A$90,'DONNÉES BRUTES'!I$3:I$90),"—") -> —
B19: 4 | C19: {=IFERROR(INDEX('DONNÉES BRUTES'!A$3:A$90,MATCH(1,('DONNÉES BRUTES'!AB$3:AB$90>=LARGE('DONNÉES BRUTES'!AB$3:AB$90,4))*(COUNTIF(C$16:C18,'DONNÉES BRUTES'!A$3:A$90)=0)*('DONNÉES BRUTES'!A$3:A$90<>""),0)),"—")} -> AMAT | D19: =IFERROR(_xlfn.XLOOKUP(C19,'DONNÉES BRUTES'!A$3:A$90,'DONNÉES BRUTES'!B$3:B$90),"—") -> Applied Materials, Inc. | E19: =IFERROR(_xlfn.XLOOKUP(C19,'DONNÉES BRUTES'!A$3:A$90,'DONNÉES BRUTES'!AB$3:AB$90)&"/100","—") -> 77/100 | G19: =IFERROR(_xlfn.XLOOKUP(C19,'DONNÉES BRUTES'!A$3:A$90,'DONNÉES BRUTES'!G$3:G$90),"—") -> $28.4 | H19: =IFERROR(_xlfn.XLOOKUP(C19,'DONNÉES BRUTES'!A$3:A$90,'DONNÉES BRUTES'!P$3:P$90),"—") -> 0.044 | I19: =IFERROR(_xlfn.XLOOKUP(C19,'DONNÉES BRUTES'!A$3:A$90,'DONNÉES BRUTES'!H$3:H$90),"—") -> $10.0 | K19: =IFERROR(_xlfn.XLOOKUP(C19,'DONNÉES BRUTES'!A$3:A$90,'DONNÉES BRUTES'!N$3:N$90),"—") -> 0.352 | L19: =IFERROR(_xlfn.XLOOKUP(C19,'DONNÉES BRUTES'!A$3:A$90,'DONNÉES BRUTES'!O$3:O$90),"—") -> 0.247 | N19: =IFERROR(_xlfn.XLOOKUP(C19,'DONNÉES BRUTES'!A$3:A$90,'DONNÉES BRUTES'!Q$3:Q$90),"—") -> 0.343 | O19: =IFERROR(_xlfn.XLOOKUP(C19,'DONNÉES BRUTES'!A$3:A$90,'DONNÉES BRUTES'!I$3:I$90),"—") -> —
B20: 5 | C20: {=IFERROR(INDEX('DONNÉES BRUTES'!A$3:A$90,MATCH(1,('DONNÉES BRUTES'!AB$3:AB$90>=LARGE('DONNÉES BRUTES'!AB$3:AB$90,5))*(COUNTIF(C$16:C19,'DONNÉES BRUTES'!A$3:A$90)=0)*('DONNÉES BRUTES'!A$3:A$90<>""),0)),"—")} -> MSI | D20: =IFERROR(_xlfn.XLOOKUP(C20,'DONNÉES BRUTES'!A$3:A$90,'DONNÉES BRUTES'!B$3:B$90),"—") -> Motorola Solutions, Inc. | E20: =IFERROR(_xlfn.XLOOKUP(C20,'DONNÉES BRUTES'!A$3:A$90,'DONNÉES BRUTES'!AB$3:AB$90)&"/100","—") -> 77/100 | G20: =IFERROR(_xlfn.XLOOKUP(C20,'DONNÉES BRUTES'!A$3:A$90,'DONNÉES BRUTES'!G$3:G$90),"—") -> $11.7 | H20: =IFERROR(_xlfn.XLOOKUP(C20,'DONNÉES BRUTES'!A$3:A$90,'DONNÉES BRUTES'!P$3:P$90),"—") -> 0.08 | I20: =IFERROR(_xlfn.XLOOKUP(C20,'DONNÉES BRUTES'!A$3:A$90,'DONNÉES BRUTES'!H$3:H$90),"—") -> $3.6 | K20: =IFERROR(_xlfn.XLOOKUP(C20,'DONNÉES BRUTES'!A$3:A$90,'DONNÉES BRUTES'!N$3:N$90),"—") -> 0.308 | L20: =IFERROR(_xlfn.XLOOKUP(C20,'DONNÉES BRUTES'!A$3:A$90,'DONNÉES BRUTES'!O$3:O$90),"—") -> 0.184 | N20: =IFERROR(_xlfn.XLOOKUP(C20,'DONNÉES BRUTES'!A$3:A$90,'DONNÉES BRUTES'!Q$3:Q$90),"—") -> 0.894 | O20: =IFERROR(_xlfn.XLOOKUP(C20,'DONNÉES BRUTES'!A$3:A$90,'DONNÉES BRUTES'!I$3:I$90),"—") -> —
B21: 6 | C21: {=IFERROR(INDEX('DONNÉES BRUTES'!A$3:A$90,MATCH(1,('DONNÉES BRUTES'!AB$3:AB$90>=LARGE('DONNÉES BRUTES'!AB$3:AB$90,6))*(COUNTIF(C$16:C20,'DONNÉES BRUTES'!A$3:A$90)=0)*('DONNÉES BRUTES'!A$3:A$90<>""),0)),"—")} -> SAP.DE | D21: =IFERROR(_xlfn.XLOOKUP(C21,'DONNÉES BRUTES'!A$3:A$90,'DONNÉES BRUTES'!B$3:B$90),"—") -> SAP SE | E21: =IFERROR(_xlfn.XLOOKUP(C21,'DONNÉES BRUTES'!A$3:A$90,'DONNÉES BRUTES'!AB$3:AB$90)&"/100","—") -> 74/100 | G21: =IFERROR(_xlfn.XLOOKUP(C21,'DONNÉES BRUTES'!A$3:A$90,'DONNÉES BRUTES'!G$3:G$90),"—") -> €36.8 | H21: =IFERROR(_xlfn.XLOOKUP(C21,'DONNÉES BRUTES'!A$3:A$90,'DONNÉES BRUTES'!P$3:P$90),"—") -> 0.077 | I21: =IFERROR(_xlfn.XLOOKUP(C21,'DONNÉES BRUTES'!A$3:A$90,'DONNÉES BRUTES'!H$3:H$90),"—") -> €12.1 | K21: =IFERROR(_xlfn.XLOOKUP(C21,'DONNÉES BRUTES'!A$3:A$90,'DONNÉES BRUTES'!N$3:N$90),"—") -> 0.328 | L21: =IFERROR(_xlfn.XLOOKUP(C21,'DONNÉES BRUTES'!A$3:A$90,'DONNÉES BRUTES'!O$3:O$90),"—") -> 0.195 | N21: =IFERROR(_xlfn.XLOOKUP(C21,'DONNÉES BRUTES'!A$3:A$90,'DONNÉES BRUTES'!Q$3:Q$90),"—") -> 0.161 | O21: =IFERROR(_xlfn.XLOOKUP(C21,'DONNÉES BRUTES'!A$3:A$90,'DONNÉES BRUTES'!I$3:I$90),"—") -> —
B22: 7 | C22: {=IFERROR(INDEX('DONNÉES BRUTES'!A$3:A$90,MATCH(1,('DONNÉES BRUTES'!AB$3:AB$90>=LARGE('DONNÉES BRUTES'!AB$3:AB$90,7))*(COUNTIF(C$16:C21,'DONNÉES BRUTES'!A$3:A$90)=0)*('DONNÉES BRUTES'!A$3:A$90<>""),0)),"—")} -> CIEN | D22: =IFERROR(_xlfn.XLOOKUP(C22,'DONNÉES BRUTES'!A$3:A$90,'DONNÉES BRUTES'!B$3:B$90),"—") -> Ciena Corporation | E22: =IFERROR(_xlfn.XLOOKUP(C22,'DONNÉES BRUTES'!A$3:A$90,'DONNÉES BRUTES'!AB$3:AB$90)&"/100","—") -> 73/100 | G22: =IFERROR(_xlfn.XLOOKUP(C22,'DONNÉES BRUTES'!A$3:A$90,'DONNÉES BRUTES'!G$3:G$90),"—") -> $4.8 | H22: =IFERROR(_xlfn.XLOOKUP(C22,'DONNÉES BRUTES'!A$3:A$90,'DONNÉES BRUTES'!P$3:P$90),"—") -> 0.188 | I22: =IFERROR(_xlfn.XLOOKUP(C22,'DONNÉES BRUTES'!A$3:A$90,'DONNÉES BRUTES'!H$3:H$90),"—") -> $0.4 | K22: =IFERROR(_xlfn.XLOOKUP(C22,'DONNÉES BRUTES'!A$3:A$90,'DONNÉES BRUTES'!N$3:N$90),"—") -> 0.081 | L22: =IFERROR(_xlfn.XLOOKUP(C22,'DONNÉES BRUTES'!A$3:A$90,'DONNÉES BRUTES'!O$3:O$90),"—") -> 0.026 | N22: =IFERROR(_xlfn.XLOOKUP(C22,'DONNÉES BRUTES'!A$3:A$90,'DONNÉES BRUTES'!Q$3:Q$90),"—") -> 0.045 | O22: =IFERROR(_xlfn.XLOOKUP(C22,'DONNÉES BRUTES'!A$3:A$90,'DONNÉES BRUTES'!I$3:I$90),"—") -> —
B23: 8 | C23: {=IFERROR(INDEX('DONNÉES BRUTES'!A$3:A$90,MATCH(1,('DONNÉES BRUTES'!AB$3:AB$90>=LARGE('DONNÉES BRUTES'!AB$3:AB$90,8))*(COUNTIF(C$16:C22,'DONNÉES BRUTES'!A$3:A$90)=0)*('DONNÉES BRUTES'!A$3:A$90<>""),0)),"—")} -> PSX | D23: =IFERROR(_xlfn.XLOOKUP(C23,'DONNÉES BRUTES'!A$3:A$90,'DONNÉES BRUTES'!B$3:B$90),"—") -> Phillips 66 | E23: =IFERROR(_xlfn.XLOOKUP(C23,'DONNÉES BRUTES'!A$3:A$90,'DONNÉES BRUTES'!AB$3:AB$90)&"/100","—") -> 71/100 | G23: =IFERROR(_xlfn.XLOOKUP(C23,'DONNÉES BRUTES'!A$3:A$90,'DONNÉES BRUTES'!G$3:G$90),"—") -> $132.4 | H23: =IFERROR(_xlfn.XLOOKUP(C23,'DONNÉES BRUTES'!A$3:A$90,'DONNÉES BRUTES'!P$3:P$90),"—") -> -0.075 | I23: =IFERROR(_xlfn.XLOOKUP(C23,'DONNÉES BRUTES'!A$3:A$90,'DONNÉES BRUTES'!H$3:H$90),"—") -> $9.8 | K23: =IFERROR(_xlfn.XLOOKUP(C23,'DONNÉES BRUTES'!A$3:A$90,'DONNÉES BRUTES'!N$3:N$90),"—") -> 0.074 | L23: =IFERROR(_xlfn.XLOOKUP(C23,'DONNÉES BRUTES'!A$3:A$90,'DONNÉES BRUTES'!O$3:O$90),"—") -> 0.033 | N23: =IFERROR(_xlfn.XLOOKUP(C23,'DONNÉES BRUTES'!A$3:A$90,'DONNÉES BRUTES'!Q$3:Q$90),"—") -> 0.151 | O23: =IFERROR(_xlfn.XLOOKUP(C23,'DONNÉES BRUTES'!A$3:A$90,'DONNÉES BRUTES'!I$3:I$90),"—") -> 8.6x
B24: 9 | C24: {=IFERROR(INDEX('DONNÉES BRUTES'!A$3:A$90,MATCH(1,('DONNÉES BRUTES'!AB$3:AB$90>=LARGE('DONNÉES BRUTES'!AB$3:AB$90,9))*(COUNTIF(C$16:C23,'DONNÉES BRUTES'!A$3:A$90)=0)*('DONNÉES BRUTES'!A$3:A$90<>""),0)),"—")} -> FTNT | D24: =IFERROR(_xlfn.XLOOKUP(C24,'DONNÉES BRUTES'!A$3:A$90,'DONNÉES BRUTES'!B$3:B$90),"—") -> Fortinet, Inc. | E24: =IFERROR(_xlfn.XLOOKUP(C24,'DONNÉES BRUTES'!A$3:A$90,'DONNÉES BRUTES'!AB$3:AB$90)&"/100","—") -> 70/100 | G24: =IFERROR(_xlfn.XLOOKUP(C24,'DONNÉES BRUTES'!A$3:A$90,'DONNÉES BRUTES'!G$3:G$90),"—") -> $6.8 | H24: =IFERROR(_xlfn.XLOOKUP(C24,'DONNÉES BRUTES'!A$3:A$90,'DONNÉES BRUTES'!P$3:P$90),"—") -> 0.142 | I24: =IFERROR(_xlfn.XLOOKUP(C24,'DONNÉES BRUTES'!A$3:A$90,'DONNÉES BRUTES'!H$3:H$90),"—") -> $2.5 | K24: =IFERROR(_xlfn.XLOOKUP(C24,'DONNÉES BRUTES'!A$3:A$90,'DONNÉES BRUTES'!N$3:N$90),"—") -> 0.361 | L24: =IFERROR(_xlfn.XLOOKUP(C24,'DONNÉES BRUTES'!A$3:A$90,'DONNÉES BRUTES'!O$3:O$90),"—") -> 0.273 | N24: =IFERROR(_xlfn.XLOOKUP(C24,'DONNÉES BRUTES'!A$3:A$90,'DONNÉES BRUTES'!Q$3:Q$90),"—") -> 1.498 | O24: =IFERROR(_xlfn.XLOOKUP(C24,'DONNÉES BRUTES'!A$3:A$90,'DONNÉES BRUTES'!I$3:I$90),"—") -> —
B25: 10 | C25: {=IFERROR(INDEX('DONNÉES BRUTES'!A$3:A$90,MATCH(1,('DONNÉES BRUTES'!AB$3:AB$90>=LARGE('DONNÉES BRUTES'!AB$3:AB$90,10))*(COUNTIF(C$16:C24,'DONNÉES BRUTES'!A$3:A$90)=0)*('DONNÉES BRUTES'!A$3:A$90<>""),0)),"—")} -> XYZ | D25: =IFERROR(_xlfn.XLOOKUP(C25,'DONNÉES BRUTES'!A$3:A$90,'DONNÉES BRUTES'!B$3:B$90),"—") -> Block, Inc. | E25: =IFERROR(_xlfn.XLOOKUP(C25,'DONNÉES BRUTES'!A$3:A$90,'DONNÉES BRUTES'!AB$3:AB$90)&"/100","—") -> 70/100 | G25: =IFERROR(_xlfn.XLOOKUP(C25,'DONNÉES BRUTES'!A$3:A$90,'DONNÉES BRUTES'!G$3:G$90),"—") -> $24.2 | H25: =IFERROR(_xlfn.XLOOKUP(C25,'DONNÉES BRUTES'!A$3:A$90,'DONNÉES BRUTES'!P$3:P$90),"—") -> 0.003 | I25: =IFERROR(_xlfn.XLOOKUP(C25,'DONNÉES BRUTES'!A$3:A$90,'DONNÉES BRUTES'!H$3:H$90),"—") -> $3.4 | K25: =IFERROR(_xlfn.XLOOKUP(C25,'DONNÉES BRUTES'!A$3:A$90,'DONNÉES BRUTES'!N$3:N$90),"—") -> 0.141 | L25: =IFERROR(_xlfn.XLOOKUP(C25,'DONNÉES BRUTES'!A$3:A$90,'DONNÉES BRUTES'!O$3:O$90),"—") -> 0.054 | N25: =IFERROR(_xlfn.XLOOKUP(C25,'DONNÉES BRUTES'!A$3:A$90,'DONNÉES BRUTES'!Q$3:Q$90),"—") -> 0.059 | O25: =IFERROR(_xlfn.XLOOKUP(C25,'DONNÉES BRUTES'!A$3:A$90,'DONNÉES BRUTES'!I$3:I$90),"—") -> —
B27: FinSight IA · Screening Énergie · Scores calculés sur métriques Growth, Quality, Momentum · Ne constitue pas un conseil en investissement

Sheet VALUE
B1: FinSight IA · Analyse VALUE · Énergie Screening (ScoreVal N/A → classé par Score Global) | P1: Ticker | Q1: Score | S1: Ticker | T1: Mg% | V1: Ticker | W1: Altman Z | Y1: Signal | Z1: Nb
B2: Usage confidentiel · Calculs FinSight IA · Screening Énergie | P2: NVDA | Q2: 88 | S2: NVDA | T2: 66.9 | V2: NVDA | W2: 13.22 | Y2: Surpondérer | Z2: 8
C3: =COUNTA('DONNÉES BRUTES'!A$3:A$90) -> 88 | H3: =IFERROR(_xlfn.XLOOKUP(LARGE('DONNÉES BRUTES'!AB$3:AB$90,1),'DONNÉES BRUTES'!AB$3:AB$90,'DONNÉES BRUTES'!A$3:A$90),"—") -> ENI.MI | M3: =IFERROR(ROUND(AVERAGE('DONNÉES BRUTES'!AB$3:AB$90),0)&"/100","—") -> 53/100 | P3: KLAC | Q3: 84 | S3: KLAC | T3: 43.9 | V3: KLAC | W3: 5.64 | Y3: Neutre | Z3: 29
C4: Sociétés | H4: #1 Score Global | M4: Moy. Score Score Global | P4: ANET | Q4: 83 | S4: ANET | T4: 43.6 | V4: ANET | W4: 8.46 | Y4: Sous-pondérer | Z4: 51
B5: ANALYSE DÉTAILLÉE · ÉNERGIE · TOP 20 par Score Global · Triée par Score Score Global | P5: AVGO | Q5: 81 | S5: AVGO | T5: 54.3 | V5: AVGO | W5: 2.66
B6: # | C6: Ticker | D6: Société | F6: Score | G6: EV/EBITDA | H6: EV/Rev | I6: P/E | J6: Mg Brute | K6: Mg EBITDA | L6: Altman Z | M6: FCF Yield | N6: Signal | P6: MU | Q6: 78 | S6: MU | T6: 49.4 | V6: MU | W6: 6.1
B7: 1 | C7: APA | D7: APA Corporation | F7: 100/100 | G7: 3.2x | H7: 1.9x | I7: 9.3x | J7: 40.6% | K7: 60.2% | L7: 1.46 | M7: 13.3% | N7: Surpondérer | P7: MPWR | Q7: 78 | S7: MPWR | T7: 28 | V7: MPWR | W7: 11.63
B8: 2 | C8: DVN | D8: Devon Energy Corporation | F8: 96/100 | G8: 4.7x | H8: 2.1x | I8: 10.8x | J8: 25.5% | K8: 44.0% | L8: 2.89 | M8: 9.8% | N8: Surpondérer | P8: LRCX | Q8: 77 | S8: LRCX | T8: 35.4 | V8: LRCX | W8: 9.7
B9: 3 | C9: EXE | D9: Expand Energy Corporation | F9: 92/100 | G9: 5.1x | H9: 2.3x | I9: 12.8x | J9: 50.8% | K9: 45.1% | L9: 3.17 | M9: 7.0% | N9: Surpondérer | P9: WDC | Q9: 77 | S9: WDC | T9: 20.4 | V9: WDC | W9: 1.76
B10: 4 | C10: CTRA | D10: Coterra Energy Inc. | F10: 88/100 | G10: 5.8x | H10: 3.7x | I10: 14.2x | J10: 41.5% | K10: 63.5% | L10: 3.35 | M10: 6.7% | N10: Surpondérer | P10: PTC | Q10: 74 | S10: PTC | T10: 41.3 | V10: PTC | W10: 3.62
B11: 5 | C11: PSX | D11: Phillips 66 | F11: 83/100 | G11: 8.6x | H11: 0.6x | I11: 14.9x | J11: 9.8% | K11: 7.4% | L11: 3.12 | M11: 4.2% | N11: Neutre | P11: AMD | Q11: 73 | S11: AMD | T11: 21 | V11: AMD | W11: 6.9
B12: 6 | C12: EOG | D12: EOG Resources, Inc. | F12: 79/100 | G12: 6.9x | H12: 3.4x | I12: 14.4x | J12: 63.4% | K12: 49.0% | L12: 4.53 | M12: 4.8% | N12: Neutre | P12: ASML | Q12: 72 | S12: ASML | T12: 38.4 | V12: ASML.AS | W12: 4.15
B13: 7 | C13: MPC | D13: Marathon Petroleum Corporation | F13: 75/100 | G13: 8.2x | H13: 0.7x | I13: 16.5x | J13: 7.5% | K13: 8.8% | L13: 2.92 | M13: 7.1% | N13: Neutre | P13: ADI | Q13: 71 | S13: ADI | T13: 45.6 | V13: ADI | W13: 4.17
B14: 8 | C14: COP | D14: ConocoPhillips | F14: 71/100 | G14: 6.4x | H14: 2.8x | I14: 18.6x | J14: 25.1% | K14: 43.4% | L14: 3.98 | M14: 4.9% | N14: Neutre | P14: GLW | Q14: 68 | S14: GLW | T14: 23.9 | V14: GLW | W14: 3.62
B15: 9 | C15: OKE | D15: ONEOK, Inc. | F15: 67/100 | G15: 11.1x | H15: 2.6x | I15: 15.8x | J15: 26.0% | K15: 23.2% | L15: 1.10 | M15: 4.6% | N15: Neutre | P15: INTC | Q15: 67 | S15: INTC | T15: 27.2 | V15: INTC | W15: 3.25
B16: 10 | C16: EQT | D16: EQT Corporation | F16: 62/100 | G16: 7.3x | H16: 5.3x | I16: 17.8x | J16: 43.2% | K16: 72.0% | L16: 2.52 | M16: 7.8% | N16: Neutre | P16: KEYS | Q16: 67 | S16: KEYS | T16: 27.1 | V16: KEYS | W16: 5.33
B17: 11 | C17: XOM | D17: Exxon Mobil Corporation | F17: 58/100 | G17: 9.7x | H17: 2.0x | I17: 21.9x | J17: 22.0% | K17: 21.0% | L17: 5.79 | M17: 3.7% | N17: Sous-pondérer | P17: APH | Q17: 66 | S17: APH | T17: 29.8 | V17: APH | W17: 5.05
B18: 12 | C18: OXY | D18: Occidental Petroleum Corporation | F18: 54/100 | G18: 6.5x | H18: 3.5x | I18: 24.2x | J18: 34.9% | K18: 54.0% | L18: 1.74 | M18: 7.3% | N18: Neutre | P18: CDNS | Q18: 66 | S18: CDNS | T18: 35.4 | V18: CDNS | W18: 6.55
... B21: 15 | C21: BKR | D21: Baker Hughes Company | F21: 42/100 | G21: 14.6x | H21: 2.3x | I21: 23.2x | J21: 23.6% | K21: 15.5% | L21: 1.95 | M21: 4.2% | N21: Neutre | P21: ADSK | Q21: 65 | S21: ADSK | T21: 27.6 | V21: ADSK | W21: 0.48
B22: 16 | C22: CVX | D22: Chevron Corporation | F22: 38/100 | G22: 9.8x | H22: 2.2x | I22: 30.4x | J22: 30.4% | K22: 22.5% | L22: 4.09 | M22: 4.4% | N22: Sous-pondérer
B23: 17 | C23: VLO | D23: Valero Energy Corporation | F23: 33/100 | G23: 11.6x | H23: 0.6x | I23: 30.8x | J23: 4.4% | K23: 5.5% | L23: 4.93 | M23: 7.0% | N23: Sous-pondérer
B24: 18 | C24: KMI | D24: Kinder Morgan, Inc. | F24: 29/100 | G24: 14.3x | H24: 6.0x | I24: 23.2x | J24: 52.9% | K24: 42.4% | L24: 0.65 | M24: 4.1% | N24: Neutre
B25: 19 | C25: TRGP | D25: Targa Resources Corp. | F25: 25/100 | G25: 14.1x | H25: 4.0x | I25: 26.8x | J25: 29.4% | K25: 28.5% | L25: 1.02 | M25: 1.1% | N25: Neutre
B26: 20 | C26: FANG | D26: Diamondback Energy, Inc. | F26: 21/100 | G26: 9.3x | H26: 4.5x | I26: 31.6x | J26: 35.0% | K26: 48.1% | L26: 1.55 | M26: -1.3% | N26: Neutre
B28: FinSight IA · Screening Énergie · Ne constitue pas un conseil en investissement

Sheet GROWTH
B1: FinSight IA · Analyse GROWTH · Énergie Screening | N1: Ticker | O1: Score | Q1: Ticker | R1: Rev% | T1: Ticker | U1: Mg EBITDA (%) | W1: Score Growth | X1: Score Global | Z1: Signal | AA1: Nb
B2: Usage confidentiel · Calculs FinSight IA · Screening Énergie | N2: INTC | O2: 100 | Q2: INTC | R2: -0.5 | T2: INTC | U2: 27.2 | W2: 100 | X2: 67 | Z2: Surpondérer | AA2: 8
C3: =COUNTA('DONNÉES BRUTES'!A$3:A$90) -> 88 | G3: =IFERROR(_xlfn.XLOOKUP(LARGE('DONNÉES BRUTES'!Y$3:Y$90,1),'DONNÉES BRUTES'!Y$3:Y$90,'DONNÉES BRUTES'!A$3:A$90),"—") -> EXE | L3: =IFERROR(ROUND(AVERAGE('DONNÉES BRUTES'!Y$3:Y$90),0)&"/100","—") -> 41/100 | N3: WDC | O3: 99 | Q3: WDC | R3: 50.7 | T3: WDC | U3: 20.4 | W3: 99 | X3: 77 | Z3: Neutre | AA3: 29
C4: Sociétés | G4: #1 Growth | L4: Moy. Score Growth | N4: MU | O4: 98 | Q4: MU | R4: 48.9 | T4: MU | U4: 49.4 | W4: 98 | X4: 78 | Z4: Sous-pondérer | AA4: 51
B5: ANALYSE DÉTAILLÉE · ÉNERGIE · TOP 20 par Growth · Triée par Score Growth | N5: STX | O5: 97 | Q5: STX | R5: 38.9 | T5: STX | U5: 22.9 | W5: 97 | X5: 73
B6: # | C6: Ticker | D6: Société | F6: Score | G6: Croiss. Rev | H6: Mg EBITDA | I6: Mg Nette | J6: ROE | K6: Score Global | L6: Next Earn. | M6: Signal | N6: NVDA | O6: 95 | Q6: NVDA | R6: 65.5 | T6: NVDA | U6: 66.9 | W6: 95 | X6: 88
B7: 1 | C7: =IFERROR(_xlfn.XLOOKUP(LARGE('DONNÉES BRUTES'!Y$3:Y$90,1),'DONNÉES BRUTES'!Y$3:Y$90,'DONNÉES BRUTES'!A$3:A$90),"—") -> EXE | D7: =IFERROR(_xlfn.XLOOKUP(C7,'DONNÉES BRUTES'!A$3:A$90,'DONNÉES BRUTES'!B$3:B$90),"—") -> Expand Energy Corporation | F7: =IFERROR(_xlfn.XLOOKUP(C7,'DONNÉES BRUTES'!A$3:A$90,'DONNÉES BRUTES'!Y$3:Y$90)&"/100","—") -> 100/100 | G7: =IFERROR(_xlfn.XLOOKUP(C7,'DONNÉES BRUTES'!A$3:A$90,'DONNÉES BRUTES'!P$3:P$90),"—") -> 1.888 | H7: =IFERROR(_xlfn.XLOOKUP(C7,'DONNÉES BRUTES'!A$3:A$90,'DONNÉES BRUTES'!N$3:N$90),"—") -> 0.451 | I7: =IFERROR(_xlfn.XLOOKUP(C7,'DONNÉES BRUTES'!A$3:A$90,'DONNÉES BRUTES'!O$3:O$90),"—") -> 0.149 | J7: =IFERROR(_xlfn.XLOOKUP(C7,'DONNÉES BRUTES'!A$3:A$90,'DONNÉES BRUTES'!Q$3:Q$90),"—") -> 0.098 | K7: =IFERROR(_xlfn.XLOOKUP(C7,'DONNÉES BRUTES'!A$3:A$90,'DONNÉES BRUTES'!AB$3:AB$90),"—") -> 63 | L7: =IFERROR(_xlfn.XLOOKUP(C7,'DONNÉES BRUTES'!A$3:A$90,'DONNÉES BRUTES'!AC$3:AC$90),"—") -> 2026-04-28 | M7: =IFERROR(_xlfn.XLOOKUP(C7,'DONNÉES BRUTES'!A$3:A$90,'DONNÉES BRUTES'!AD$3:AD$90),"—") -> Surpondérer | N7: APH | O7: 94 | Q7: APH | R7: 51.7 | T7: APH | U7: 29.8 | W7: 94 | X7: 66
B8: 2 | C8: =IFERROR(_xlfn.XLOOKUP(LARGE('DONNÉES BRUTES'!Y$3:Y$90,2),'DONNÉES BRUTES'!Y$3:Y$90,'DONNÉES BRUTES'!A$3:A$90),"—") -> EQT | D8: =IFERROR(_xlfn.XLOOKUP(C8,'DONNÉES BRUTES'!A$3:A$90,'DONNÉES BRUTES'!B$3:B$90),"—") -> EQT Corporation | F8: =IFERROR(_xlfn.XLOOKUP(C8,'DONNÉES BRUTES'!A$3:A$90,'DONNÉES BRUTES'!Y$3:Y$90)&"/100","—") -> 96/100 | G8: =IFERROR(_xlfn.XLOOKUP(C8,'DONNÉES BRUTES'!A$3:A$90,'DONNÉES BRUTES'!P$3:P$90),"—") -> 0.6 | H8: =IFERROR(_xlfn.XLOOKUP(C8,'DONNÉES BRUTES'!A$3:A$90,'DONNÉES BRUTES'!N$3:N$90),"—") -> 0.72 | I8: =IFERROR(_xlfn.XLOOKUP(C8,'DONNÉES BRUTES'!A$3:A$90,'DONNÉES BRUTES'!O$3:O$90),"—") -> 0.244 | J8: =IFERROR(_xlfn.XLOOKUP(C8,'DONNÉES BRUTES'!A$3:A$90,'DONNÉES BRUTES'!Q$3:Q$90),"—") -> 0.086 | K8: =IFERROR(_xlfn.XLOOKUP(C8,'DONNÉES BRUTES'!A$3:A$90,'DONNÉES BRUTES'!AB$3:AB$90),"—") -> 60 | L8: =IFERROR(_xlfn.XLOOKUP(C8,'DONNÉES BRUTES'!A$3:A$90,'DONNÉES BRUTES'!AC$3:AC$90),"—") -> 2026-04-21 | M8: =IFERROR(_xlfn.XLOOKUP(C8,'DONNÉES BRUTES'!A$3:A$90,'DONNÉES BRUTES'!AD$3:AD$90),"—") -> Neutre | N8: SAP.DE | O8: 93 | Q8: SAP.DE | R8: 7.7 | T8: SAP.DE | U8: 32.8 | W8: 93 | X8: 59
B9: 3 | C9: =IFERROR(_xlfn.XLOOKUP(LARGE('DONNÉES BRUTES'!Y$3:Y$90,3),'DONNÉES BRUTES'!Y$3:Y$90,'DONNÉES BRUTES'!A$3:A$90),"—") -> SAP.DE | D9: =IFERROR(_xlfn.XLOOKUP(C9,'DONNÉES BRUTES'!A$3:A$90,'DONNÉES BRUTES'!B$3:B$90),"—") -> SAP SE | F9: =IFERROR(_xlfn.XLOOKUP(C9,'DONNÉES BRUTES'!A$3:A$90,'DONNÉES BRUTES'!Y$3:Y$90)&"/100","—") -> 93/100 | G9: =IFERROR(_xlfn.XLOOKUP(C9,'DONNÉES BRUTES'!A$3:A$90,'DONNÉES BRUTES'!P$3:P$90),"—") -> 0.077 | H9: =IFERROR(_xlfn.XLOOKUP(C9,'DONNÉES BRUTES'!A$3:A$90,'DONNÉES BRUTES'!N$3:N$90),"—") -> 0.328 | I9: =IFERROR(_xlfn.XLOOKUP(C9,'DONNÉES BRUTES'!A$3:A$90,'DONNÉES BRUTES'!O$3:O$90),"—") -> 0.195 | J9: =IFERROR(_xlfn.XLOOKUP(C9,'DONNÉES BRUTES'!A$3:A$90,'DONNÉES BRUTES'!Q$3:Q$90),"—") -> 0.161 | K9: =IFERROR(_xlfn.XLOOKUP(C9,'DONNÉES BRUTES'!A$3:A$90,'DONNÉES BRUTES'!AB$3:AB$90),"—") -> 74 | L9: =IFERROR(_xlfn.XLOOKUP(C9,'DONNÉES BRUTES'!A$3:A$90,'DONNÉES BRUTES'!AC$3:AC$90),"—") -> 2026-04-23 | M9: =IFERROR(_xlfn.XLOOKUP(C9,'DONNÉES BRUTES'!A$3:A$90,'DONNÉES BRUTES'!AD$3:AD$90),"—") -> Neutre | N9: AMD | O9: 92 | Q9: AMD | R9: 34.3 | T9: AMD | U9: 21 | W9: 92 | X9: 73
B10: 4 | C10: =IFERROR(_xlfn.XLOOKUP(LARGE('DONNÉES BRUTES'!Y$3:Y$90,4),'DONNÉES BRUTES'!Y$3:Y$90,'DONNÉES BRUTES'!A$3:A$90),"—") -> CTRA | D10: =IFERROR(_xlfn.XLOOKUP(C10,'DONNÉES BRUTES'!A$3:A$90,'DONNÉES BRUTES'!B$3:B$90),"—") -> Coterra Energy Inc. | F10: =IFERROR(_xlfn.XLOOKUP(C10,'DONNÉES BRUTES'!A$3:A$90,'DONNÉES BRUTES'!Y$3:Y$90)&"/100","—") -> 92/100 | G10: =IFERROR(_xlfn.XLOOKUP(C10,'DONNÉES BRUTES'!A$3:A$90,'DONNÉES BRUTES'!P$3:P$90),"—") -> 0.401 | H10: =IFERROR(_xlfn.XLOOKUP(C10,'DONNÉES BRUTES'!A$3:A$90,'DONNÉES BRUTES'!N$3:N$90),"—") -> 0.635 | I10: =IFERROR(_xlfn.XLOOKUP(C10,'DONNÉES BRUTES'!A$3:A$90,'DONNÉES BRUTES'!O$3:O$90),"—") -> 0.225 | J10: =IFERROR(_xlfn.XLOOKUP(C10,'DONNÉES BRUTES'!A$3:A$90,'DONNÉES BRUTES'!Q$3:Q$90),"—") -> 0.116 | K10: =IFERROR(_xlfn.XLOOKUP(C10,'DONNÉES BRUTES'!A$3:A$90,'DONNÉES BRUTES'!AB$3:AB$90),"—") -> 69 | L10: =IFERROR(_xlfn.XLOOKUP(C10,'DONNÉES BRUTES'!A$3:A$90,'DONNÉES BRUTES'!AC$3:AC$90),"—") -> 2026-05-04 | M10: =IFERROR(_xlfn.XLOOKUP(C10,'DONNÉES BRUTES'!A$3:A$90,'DONNÉES BRUTES'!AD$3:AD$90),"—") -> Surpondérer | N10: PTC | O10: 91 | Q10: PTC | R10: 19.2 | T10: PTC | U10: 41.3 | W10: 91 | X10: 74
B11: 5 | C11: =IFERROR(_xlfn.XLOOKUP(LARGE('DONNÉES BRUTES'!Y$3:Y$90,5),'DONNÉES BRUTES'!Y$3:Y$90,'DONNÉES BRUTES'!A$3:A$90),"—") -> OKE | D11: =IFERROR(_xlfn.XLOOKUP(C11,'DONNÉES BRUTES'!A$3:A$90,'DONNÉES BRUTES'!B$3:B$90),"—") -> ONEOK, Inc. | F11: =IFERROR(_xlfn.XLOOKUP(C11,'DONNÉES BRUTES'!A$3:A$90,'DONNÉES BRUTES'!Y$3:Y$90)&"/100","—") -> 88/100 | G11: =IFERROR(_xlfn.XLOOKUP(C11,'DONNÉES BRUTES'!A$3:A$90,'DONNÉES BRUTES'!P$3:P$90),"—") -> 0.55 | H11: =IFERROR(_xlfn.XLOOKUP(C11,'DONNÉES BRUTES'!A$3:A$90,'DONNÉES BRUTES'!N$3:N$90),"—") -> 0.232 | I11: =IFERROR(_xlfn.XLOOKUP(C11,'DONNÉES BRUTES'!A$3:A$90,'DONNÉES BRUTES'!O$3:O$90),"—") -> 0.101 | J11: =IFERROR(_xlfn.XLOOKUP(C11,'DONNÉES BRUTES'!A$3:A$90,'DONNÉES BRUTES'!Q$3:Q$90),"—") -> 0.151 | K11: =IFERROR(_xlfn.XLOOKUP(C11,'DONNÉES BRUTES'!A$3:A$90,'DONNÉES BRUTES'!AB$3:AB$90),"—") -> 60 | L11: =IFERROR(_xlfn.XLOOKUP(C11,'DONNÉES BRUTES'!A$3:A$90,'DONNÉES BRUTES'!AC$3:AC$90),"—") -> 2026-04-28 | M11: =IFERROR(_xlfn.XLOOKUP(C11,'DONNÉES BRUTES'!A$3:A$90,'DONNÉES BRUTES'!AD$3:AD$90),"—") -> Neutre | N11: AVGO | O11: 90 | Q11: AVGO | R11: 23.9 | T11: AVGO | U11: 54.3 | W11: 90 | X11: 81
B12: 6 | C12: =IFERROR(_xlfn.XLOOKUP(LARGE('DONNÉES BRUTES'!Y$3:Y$90,6),'DONNÉES BRUTES'!Y$3:Y$90,'DONNÉES BRUTES'!A$3:A$90),"—") -> XYZ | D12: =IFERROR(_xlfn.XLOOKUP(C12,'DONNÉES BRUTES'!A$3:A$90,'DONNÉES BRUTES'!B$3:B$90),"—") -> Block, Inc. | F12: =IFERROR(_xlfn.XLOOKUP(C12,'DONNÉES BRUTES'!A$3:A$90,'DONNÉES BRUTES'!Y$3:Y$90)&"/100","—") -> 87/100 | G12: =IFERROR(_xlfn.XLOOKUP(C12,'DONNÉES BRUTES'!A$3:A$90,'DONNÉES BRUTES'!P$3:P$90),"—") -> 0.003 | H12: =IFERROR(_xlfn.XLOOKUP(C12,'DONNÉES BRUTES'!A$3:A$90,'DONNÉES BRUTES'!N$3:N$90),"—") -> 0.141 | I12: =IFERROR(_xlfn.XLOOKUP(C12,'DONNÉES BRUTES'!A$3:A$90,'DONNÉES BRUTES'!O$3:O$90),"—") -> 0.054 | J12: =IFERROR(_xlfn.XLOOKUP(C12,'DONNÉES BRUTES'!A$3:A$90,'DONNÉES BRUTES'!Q$3:Q$90),"—") -> 0.059 | K12: =IFERROR(_xlfn.XLOOKUP(C12,'DONNÉES BRUTES'!A$3:A$90,'DONNÉES BRUTES'!AB$3:AB$90),"—") -> 70 | L12: =IFERROR(_xlfn.XLOOKUP(C12,'DONNÉES BRUTES'!A$3:A$90,'DONNÉES BRUTES'!AC$3:AC$90),"—") -> 2026-04-30 | M12: =IFERROR(_xlfn.XLOOKUP(C12,'DONNÉES BRUTES'!A$3:A$90,'DONNÉES BRUTES'!AD$3:AD$90),"—") -> Sous-pondérer | N12: GLW | O12: 88 | Q12: GLW | R12: 19.1 | T12: GLW | U12: 23.9 | W12: 88 | X12: 68
B13: 7 | C13: =IFERROR(_xlfn.XLOOKUP(LARGE('DONNÉES BRUTES'!Y$3:Y$90,7),'DONNÉES BRUTES'!Y$3:Y$90,'DONNÉES BRUTES'!A$3:A$90),"—") -> PSX | D13: =IFERROR(_xlfn.XLOOKUP(C13,'DONNÉES BRUTES'!A$3:A$90,'DONNÉES BRUTES'!B$3:B$90),"—") -> Phillips 66 | F13: =IFERROR(_xlfn.XLOOKUP(C13,'DONNÉES BRUTES'!A$3:A$90,'DONNÉES BRUTES'!Y$3:Y$90)&"/100","—") -> 83/100 | G13: =IFERROR(_xlfn.XLOOKUP(C13,'DONNÉES BRUTES'!A$3:A$90,'DONNÉES BRUTES'!P$3:P$90),"—") -> -0.075 | H13: =IFERROR(_xlfn.XLOOKUP(C13,'DONNÉES BRUTES'!A$3:A$90,'DONNÉES BRUTES'!N$3:N$90),"—") -> 0.074 | I13: =IFERROR(_xlfn.XLOOKUP(C13,'DONNÉES BRUTES'!A$3:A$90,'DONNÉES BRUTES'!O$3:O$90),"—") -> 0.033 | J13: =IFERROR(_xlfn.XLOOKUP(C13,'DONNÉES BRUTES'!A$3:A$90,'DONNÉES BRUTES'!Q$3:Q$90),"—") -> 0.151 | K13: =IFERROR(_xlfn.XLOOKUP(C13,'DONNÉES BRUTES'!A$3:A$90,'DONNÉES BRUTES'!AB$3:AB$90),"—") -> 71 | L13: =IFERROR(_xlfn.XLOOKUP(C13,'DONNÉES BRUTES'!A$3:A$90,'DONNÉES BRUTES'!AC$3:AC$90),"—") -> 2026-04-24 | M13: =IFERROR(_xlfn.XLOOKUP(C13,'DONNÉES BRUTES'!A$3:A$90,'DONNÉES BRUTES'!AD$3:AD$90),"—") -> Neutre | N13: XYZ | O13: 87 | Q13: XYZ | R13: 0.3 | T13: XYZ | U13: 14.1 | W13: 87 | X13: 53
B14: 8 | C14: =IFERROR(_xlfn.XLOOKUP(LARGE('DONNÉES BRUTES'!Y$3:Y$90,8),'DONNÉES BRUTES'!Y$3:Y$90,'DONNÉES BRUTES'!A$3:A$90),"—") -> SMCI | D14: =IFERROR(_xlfn.XLOOKUP(C14,'DONNÉES BRUTES'!A$3:A$90,'DONNÉES BRUTES'!B$3:B$90),"—") -> Super Micro Computer, Inc. | F14: =IFERROR(_xlfn.XLOOKUP(C14,'DONNÉES BRUTES'!A$3:A$90,'DONNÉES BRUTES'!Y$3:Y$90)&"/100","—") -> 81/100 | G14: =IFERROR(_xlfn.XLOOKUP(C14,'DONNÉES BRUTES'!A$3:A$90,'DONNÉES BRUTES'!P$3:P$90),"—") -> 0.466 | H14: =IFERROR(_xlfn.XLOOKUP(C14,'DONNÉES BRUTES'!A$3:A$90,'DONNÉES BRUTES'!N$3:N$90),"—") -> 0.061 | I14: =IFERROR(_xlfn.XLOOKUP(C14,'DONNÉES BRUTES'!A$3:A$90,'DONNÉES BRUTES'!O$3:O$90),"—") -> — | J14: =IFERROR(_xlfn.XLOOKUP(C14,'DONNÉES BRUTES'!A$3:A$90,'DONNÉES BRUTES'!Q$3:Q$90),"—") -> — | K14: =IFERROR(_xlfn.XLOOKUP(C14,'DONNÉES BRUTES'!A$3:A$90,'DONNÉES BRUTES'!AB$3:AB$90),"—") -> 58 | L14: =IFERROR(_xlfn.XLOOKUP(C14,'DONNÉES BRUTES'!A$3:A$90,'DONNÉES BRUTES'!AC$3:AC$90),"—") -> — | M14: =IFERROR(_xlfn.XLOOKUP(C14,'DONNÉES BRUTES'!A$3:A$90,'DONNÉES BRUTES'!AD$3:AD$90),"—") -> Sous-pondérer | N14: MPWR | O14: 86 | Q14: MPWR | R14: 26.4 | T14: MPWR | U14: 28 | W14: 86 | X14: 78
B15: 9 | C15: =IFERROR(_xlfn.XLOOKUP(LARGE('DONNÉES BRUTES'!Y$3:Y$90,9),'DONNÉES BRUTES'!Y$3:Y$90,'DONNÉES BRUTES'!A$3:A$90),"—") -> NOW | D15: =IFERROR(_xlfn.XLOOKUP(C15,'DONNÉES BRUTES'!A$3:A$90,'DONNÉES BRUTES'!B$3:B$90),"—") -> ServiceNow, Inc. | F15: =IFERROR(_xlfn.XLOOKUP(C15,'DONNÉES BRUTES'!A$3:A$90,'DONNÉES BRUTES'!Y$3:Y$90)&"/100","—") -> 80/100 | G15: =IFERROR(_xlfn.XLOOKUP(C15,'DONNÉES BRUTES'!A$3:A$90,'DONNÉES BRUTES'!P$3:P$90),"—") -> 0.209 | H15: =IFERROR(_xlfn.XLOOKUP(C15,'DONNÉES BRUTES'!A$3:A$90,'DONNÉES BRUTES'!N$3:N$90),"—") -> 0.228 | I15: =IFERROR(_xlfn.XLOOKUP(C15,'DONNÉES BRUTES'!A$3:A$90,'DONNÉES BRUTES'!O$3:O$90),"—") -> 0.132 | J15: =IFERROR(_xlfn.XLOOKUP(C15,'DONNÉES BRUTES'!A$3:A$90,'DONNÉES BRUTES'!Q$3:Q$90),"—") -> 0.135 | K15: =IFERROR(_xlfn.XLOOKUP(C15,'DONNÉES BRUTES'!A$3:A$90,'DONNÉES BRUTES'!AB$3:AB$90),"—") -> 66 | L15: =IFERROR(_xlfn.XLOOKUP(C15,'DONNÉES BRUTES'!A$3:A$90,'DONNÉES BRUTES'!AC$3:AC$90),"—") -> 2026-04-22 | M15: =IFERROR(_xlfn.XLOOKUP(C15,'DONNÉES BRUTES'!A$3:A$90,'DONNÉES BRUTES'!AD$3:AD$90),"—") -> Sous-pondérer | N15: KLAC | O15: 85 | Q15: KLAC | R15: 23.9 | T15: KLAC | U15: 43.9 | W15: 85 | X15: 84
B16: 10 | C16: =IFERROR(_xlfn.XLOOKUP(LARGE('DONNÉES BRUTES'!Y$3:Y$90,10),'DONNÉES BRUTES'!Y$3:Y$90,'DONNÉES BRUTES'!A$3:A$90),"—") -> TPL | D16: =IFERROR(_xlfn.XLOOKUP(C16,'DONNÉES BRUTES'!A$3:A$90,'DONNÉES BRUTES'!B$3:B$90),"—") -> Texas Pacific Land Corporation | F16: =IFERROR(_xlfn.XLOOKUP(C16,'DONNÉES BRUTES'!A$3:A$90,'DONNÉES BRUTES'!Y$3:Y$90)&"/100","—") -> 79/100 | G16: =IFERROR(_xlfn.XLOOKUP(C16,'DONNÉES BRUTES'!A$3:A$90,'DONNÉES BRUTES'!P$3:P$90),"—") -> 0.131 | H16: =IFERROR(_xlfn.XLOOKUP(C16,'DONNÉES BRUTES'!A$3:A$90,'DONNÉES BRUTES'!N$3:N$90),"—") -> 0.844 | I16: =IFERROR(_xlfn.XLOOKUP(C16,'DONNÉES BRUTES'!A$3:A$90,'DONNÉES BRUTES'!O$3:O$90),"—") -> 0.603 | J16: =IFERROR(_xlfn.XLOOKUP(C16,'DONNÉES BRUTES'!A$3:A$90,'DONNÉES BRUTES'!Q$3:Q$90),"—") -> 0.33 | K16: =IFERROR(_xlfn.XLOOKUP(C16,'DONNÉES BRUTES'!A$3:A$90,'DONNÉES BRUTES'!AB$3:AB$90),"—") -> 59 | L16: =IFERROR(_xlfn.XLOOKUP(C16,'DONNÉES BRUTES'!A$3:A$90,'DONNÉES BRUTES'!AC$3:AC$90),"—") -> 2026-05-06 | M16: =IFERROR(_xlfn.XLOOKUP(C16,'DONNÉES BRUTES'!A$3:A$90,'DONNÉES BRUTES'!AD$3:AD$90),"—") -> Neutre | N16: ANET | O16: 84 | Q16: ANET | R16: 28.6 | T16: ANET | U16: 43.6 | W16: 84 | X16: 83
B17: 11 | C17: =IFERROR(_xlfn.XLOOKUP(LARGE('DONNÉES BRUTES'!Y$3:Y$90,11),'DONNÉES BRUTES'!Y$3:Y$90,'DONNÉES BRUTES'!A$3:A$90),"—") -> WDAY | D17: =IFERROR(_xlfn.XLOOKUP(C17,'DONNÉES BRUTES'!A$3:A$90,'DONNÉES BRUTES'!B$3:B$90),"—") -> Workday, Inc. | F17: =IFERROR(_xlfn.XLOOKUP(C17,'DONNÉES BRUTES'!A$3:A$90,'DONNÉES BRUTES'!Y$3:Y$90)&"/100","—") -> 77/100 | G17: =IFERROR(_xlfn.XLOOKUP(C17,'DONNÉES BRUTES'!A$3:A$90,'DONNÉES BRUTES'!P$3:P$90),"—") -> 0.131 | H17: =IFERROR(_xlfn.XLOOKUP(C17,'DONNÉES BRUTES'!A$3:A$90,'DONNÉES BRUTES'!N$3:N$90),"—") -> 0.154 | I17: =IFERROR(_xlfn.XLOOKUP(C17,'DONNÉES BRUTES'!A$3:A$90,'DONNÉES BRUTES'!O$3:O$90),"—") -> — | J17: =IFERROR(_xlfn.XLOOKUP(C17,'DONNÉES BRUTES'!A$3:A$90,'DONNÉES BRUTES'!Q$3:Q$90),"—") -> — | K17: =IFERROR(_xlfn.XLOOKUP(C17,'DONNÉES BRUTES'!A$3:A$90,'DONNÉES BRUTES'!AB$3:AB$90),"—") -> 63 | L17: =IFERROR(_xlfn.XLOOKUP(C17,'DONNÉES BRUTES'!A$3:A$90,'DONNÉES BRUTES'!AC$3:AC$90),"—") -> — | M17: =IFERROR(_xlfn.XLOOKUP(C17,'DONNÉES BRUTES'!A$3:A$90,'DONNÉES BRUTES'!AD$3:AD$90),"—") -> Sous-pondérer | N17: LRCX | O17: 83 | Q17: LRCX | R17: 23.7 | T17: LRCX | U17: 35.4 | W17: 83 | X17: 77
B18: 12 | C18: =IFERROR(_xlfn.XLOOKUP(LARGE('DONNÉES BRUTES'!Y$3:Y$90,12),'DONNÉES BRUTES'!Y$3:Y$90,'DONNÉES BRUTES'!A$3:A$90),"—") -> UBER | D18: =IFERROR(_xlfn.XLOOKUP(C18,'DONNÉES BRUTES'!A$3:A$90,'DONNÉES BRUTES'!B$3:B$90),"—") -> Uber Technologies, Inc. | F18: =IFERROR(_xlfn.XLOOKUP(C18,'DONNÉES BRUTES'!A$3:A$90,'DONNÉES BRUTES'!Y$3:Y$90)&"/100","—") -> 76/100 | G18: =IFERROR(_xlfn.XLOOKUP(C18,'DONNÉES BRUTES'!A$3:A$90,'DONNÉES BRUTES'!P$3:P$90),"—") -> 0.183 | H18: =IFERROR(_xlfn.XLOOKUP(C18,'DONNÉES BRUTES'!A$3:A$90,'DONNÉES BRUTES'!N$3:N$90),"—") -> 0.134 | I18: =IFERROR(_xlfn.XLOOKUP(C18,'DONNÉES BRUTES'!A$3:A$90,'DONNÉES BRUTES'!O$3:O$90),"—") -> — | J18: =IFERROR(_xlfn.XLOOKUP(C18,'DONNÉES BRUTES'!A$3:A$90,'DONNÉES BRUTES'!Q$3:Q$90),"—") -> — | K18: =IFERROR(_xlfn.XLOOKUP(C18,'DONNÉES BRUTES'!A$3:A$90,'DONNÉES BRUTES'!AB$3:AB$90),"—") -> 63 | L18: =IFERROR(_xlfn.XLOOKUP(C18,'DONNÉES BRUTES'!A$3:A$90,'DONNÉES BRUTES'!AC$3:AC$90),"—") -> — | M18: =IFERROR(_xlfn.XLOOKUP(C18,'DONNÉES BRUTES'!A$3:A$90,'DONNÉES BRUTES'!AD$3:AD$90),"—") -> Sous-pondérer | N18: SMCI | O18: 81 | Q18: SMCI | R18: 46.6 | T18: SMCI | U18: 6.1 | W18: 81 | X18: 32
B19: 13 | C19: =IFERROR(_xlfn.XLOOKUP(LARGE('DONNÉES BRUTES'!Y$3:Y$90,13),'DONNÉES BRUTES'!Y$3:Y$90,'DONNÉES BRUTES'!A$3:A$90),"—") -> FANG | D19: =IFERROR(_xlfn.XLOOKUP(C19,'DONNÉES BRUTES'!A$3:A$90,'DONNÉES BRUTES'!B$3:B$90),"—") -> Diamondback Energy, Inc. | F19: =IFERROR(_xlfn.XLOOKUP(C19,'DONNÉES BRUTES'!A$3:A$90,'DONNÉES BRUTES'!Y$3:Y$90)&"/100","—") -> 75/100 | G19: =IFERROR(_xlfn.XLOOKUP(C19,'DONNÉES BRUTES'!A$3:A$90,'DONNÉES BRUTES'!P$3:P$90),"—") -> 0.354 | H19: =IFERROR(_xlfn.XLOOKUP(C19,'DONNÉES BRUTES'!A$3:A$90,'DONNÉES BRUTES'!N$3:N$90),"—") -> 0.481 | I19: =IFERROR(_xlfn.XLOOKUP(C19,'DONNÉES BRUTES'!A$3:A$90,'DONNÉES BRUTES'!O$3:O$90),"—") -> 0.111 | J19: =IFERROR(_xlfn.XLOOKUP(C19,'DONNÉES BRUTES'!A$3:A$90,'DONNÉES BRUTES'!Q$3:Q$90),"—") -> 0.045 | K19: =IFERROR(_xlfn.XLOOKUP(C19,'DONNÉES BRUTES'!A$3:A$90,'DONNÉES BRUTES'!AB$3:AB$90),"—") -> 57 | L19: =IFERROR(_xlfn.XLOOKUP(C19,'DONNÉES BRUTES'!A$3:A$90,'DONNÉES BRUTES'!AC$3:AC$90),"—") -> 2026-05-04 | M19: =IFERROR(_xlfn.XLOOKUP(C19,'DONNÉES BRUTES'!A$3:A$90,'DONNÉES BRUTES'!AD$3:AD$90),"—") -> Neutre | N19: NOW | O19: 80 | Q19: NOW | R19: 20.9 | T19: NOW | U19: 22.8 | W19: 80 | X19: 53
B20: 14 | C20: =IFERROR(_xlfn.XLOOKUP(LARGE('DONNÉES BRUTES'!Y$3:Y$90,14),'DONNÉES BRUTES'!Y$3:Y$90,'DONNÉES BRUTES'!A$3:A$90),"—") -> MSI | D20: =IFERROR(_xlfn.XLOOKUP(C20,'DONNÉES BRUTES'!A$3:A$90,'DONNÉES BRUTES'!B$3:B$90),"—") -> Motorola Solutions, Inc. | F20: =IFERROR(_xlfn.XLOOKUP(C20,'DONNÉES BRUTES'!A$3:A$90,'DONNÉES BRUTES'!Y$3:Y$90)&"/100","—") -> 74/100 | G20: =IFERROR(_xlfn.XLOOKUP(C20,'DONNÉES BRUTES'!A$3:A$90,'DONNÉES BRUTES'!P$3:P$90),"—") -> 0.08 | H20: =IFERROR(_xlfn.XLOOKUP(C20,'DONNÉES BRUTES'!A$3:A$90,'DONNÉES BRUTES'!N$3:N$90),"—") -> 0.308 | I20: =IFERROR(_xlfn.XLOOKUP(C20,'DONNÉES BRUTES'!A$3:A$90,'DONNÉES BRUTES'!O$3:O$90),"—") -> 0.184 | J20: =IFERROR(_xlfn.XLOOKUP(C20,'DONNÉES BRUTES'!A$3:A$90,'DONNÉES BRUTES'!Q$3:Q$90),"—") -> 0.894 | K20: =IFERROR(_xlfn.XLOOKUP(C20,'DONNÉES BRUTES'!A$3:A$90,'DONNÉES BRUTES'!AB$3:AB$90),"—") -> 77 | L20: =IFERROR(_xlfn.XLOOKUP(C20,'DONNÉES BRUTES'!A$3:A$90,'DONNÉES BRUTES'!AC$3:AC$90),"—") -> 2026-04-30 | M20: =IFERROR(_xlfn.XLOOKUP(C20,'DONNÉES BRUTES'!A$3:A$90,'DONNÉES BRUTES'!AD$3:AD$90),"—") -> Neutre | N20: SNPS | O20: 79 | Q20: SNPS | R20: 15.1 | T20: SNPS | U20: 35.4 | W20: 79 | X20: 66
B21: 15 | C21: =IFERROR(_xlfn.XLOOKUP(LARGE('DONNÉES BRUTES'!Y$3:Y$90,15),'DONNÉES BRUTES'!Y$3:Y$90,'DONNÉES BRUTES'!A$3:A$90),"—") -> INTU | D21: =IFERROR(_xlfn.XLOOKUP(C21,'DONNÉES BRUTES'!A$3:A$90,'DONNÉES BRUTES'!B$3:B$90),"—") -> Intuit Inc. | F21: =IFERROR(_xlfn.XLOOKUP(C21,'DONNÉES BRUTES'!A$3:A$90,'DONNÉES BRUTES'!Y$3:Y$90)&"/100","—") -> 72/100 | G21: =IFERROR(_xlfn.XLOOKUP(C21,'DONNÉES BRUTES'!A$3:A$90,'DONNÉES BRUTES'!P$3:P$90),"—") -> 0.156 | H21: =IFERROR(_xlfn.XLOOKUP(C21,'DONNÉES BRUTES'!A$3:A$90,'DONNÉES BRUTES'!N$3:N$90),"—") -> 0.313 | I21: =IFERROR(_xlfn.XLOOKUP(C21,'DONNÉES BRUTES'!A$3:A$90,'DONNÉES BRUTES'!O$3:O$90),"—") -> 0.205 | J21: =IFERROR(_xlfn.XLOOKUP(C21,'DONNÉES BRUTES'!A$3:A$90,'DONNÉES BRUTES'!Q$3:Q$90),"—") -> 0.196 | K21: =IFERROR(_xlfn.XLOOKUP(C21,'DONNÉES BRUTES'!A$3:A$90,'DONNÉES BRUTES'!AB$3:AB$90),"—") -> 67 | L21: =IFERROR(_xlfn.XLOOKUP(C21,'DONNÉES BRUTES'!A$3:A$90,'DONNÉES BRUTES'!AC$3:AC$90),"—") -> 2026-05-21 | M21: =IFERROR(_xlfn.XLOOKUP(C21,'DONNÉES BRUTES'!A$3:A$90,'DONNÉES BRUTES'!AD$3:AD$90),"—") -> Neutre | N21: IBM | O21: 78 | Q21: IBM | R21: 7.6 | T21: IBM | U21: 25.6 | W21: 78 | X21: 60
B22: 16 | C22: =IFERROR(_xlfn.XLOOKUP(LARGE('DONNÉES BRUTES'!Y$3:Y$90,16),'DONNÉES BRUTES'!Y$3:Y$90,'DONNÉES BRUTES'!A$3:A$90),"—") -> WMB | D22: =IFERROR(_xlfn.XLOOKUP(C22,'DONNÉES BRUTES'!A$3:A$90,'DONNÉES BRUTES'!B$3:B$90),"—") -> The Williams Companies, Inc. | F22: =IFERROR(_xlfn.XLOOKUP(C22,'DONNÉES BRUTES'!A$3:A$90,'DONNÉES BRUTES'!Y$3:Y$90)&"/100","—") -> 71/100 | G22: =IFERROR(_xlfn.XLOOKUP(C22,'DONNÉES BRUTES'!A$3:A$90,'DONNÉES BRUTES'!P$3:P$90),"—") -> 0.138 | H22: =IFERROR(_xlfn.XLOOKUP(C22,'DONNÉES BRUTES'!A$3:A$90,'DONNÉES BRUTES'!N$3:N$90),"—") -> 0.62 | I22: =IFERROR(_xlfn.XLOOKUP(C22,'DONNÉES BRUTES'!A$3:A$90,'DONNÉES BRUTES'!O$3:O$90),"—") -> 0.219 | J22: =IFERROR(_xlfn.XLOOKUP(C22,'DONNÉES BRUTES'!A$3:A$90,'DONNÉES BRUTES'!Q$3:Q$90),"—") -> 0.205 | K22: =IFERROR(_xlfn.XLOOKUP(C22,'DONNÉES BRUTES'!A$3:A$90,'DONNÉES BRUTES'!AB$3:AB$90),"—") -> 53 | L22: =IFERROR(_xlfn.XLOOKUP(C22,'DONNÉES BRUTES'!A$3:A$90,'DONNÉES BRUTES'!AC$3:AC$90),"—") -> 2026-05-04 | M22: =IFERROR(_xlfn.XLOOKUP(C22,'DONNÉES BRUTES'!A$3:A$90,'DONNÉES BRUTES'!AD$3:AD$90),"—") -> Neutre
B23: 17 | C23: =IFERROR(_xlfn.XLOOKUP(LARGE('DONNÉES BRUTES'!Y$3:Y$90,17),'DONNÉES BRUTES'!Y$3:Y$90,'DONNÉES BRUTES'!A$3:A$90),"—") -> FSLR | D23: =IFERROR(_xlfn.XLOOKUP(C23,'DONNÉES BRUTES'!A$3:A$90,'DONNÉES BRUTES'!B$3:B$90),"—") -> First Solar, Inc. | F23: =IFERROR(_xlfn.XLOOKUP(C23,'DONNÉES BRUTES'!A$3:A$90,'DONNÉES BRUTES'!Y$3:Y$90)&"/100","—") -> 69/100 | G23: =IFERROR(_xlfn.XLOOKUP(C23,'DONNÉES BRUTES'!A$3:A$90,'DONNÉES BRUTES'!P$3:P$90),"—") -> 0.241 | H23: =IFERROR(_xlfn.XLOOKUP(C23,'DONNÉES BRUTES'!A$3:A$90,'DONNÉES BRUTES'!N$3:N$90),"—") -> 0.413 | I23: =IFERROR(_xlfn.XLOOKUP(D23,'DONNÉES BRUTES'!B$3:B$90,'DONNÉES BRUTES'!O$3:O$90),"—") -> 0.293 | J23: =IFERROR(_xlfn.XLOOKUP(E23,'DONNÉES BRUTES'!C$3:C$90,'DONNÉES BRUTES'!P$3:P$90),"—") -> — | K23: =IFERROR(_xlfn.XLOOKUP(C23,'DONNÉES BRUTES'!A$3:A$90,'DONNÉES BRUTES'!AB$3:AB$90),"—") -> 63 | L23: =IFERROR(_xlfn.XLOOKUP(C23,'DONNÉES BRUTES'!A$3:A$90,'DONNÉES BRUTES'!AC$3:AC$90),"—") -> 2026-04-28 | M23: =IFERROR(_xlfn.XLOOKUP(C23,'DONNÉES BRUTES'!A$3:A$90,'DONNÉES BRUTES'!AD$3:AD$90),"—") -> Neutre
B24: 18 | C24: =IFERROR(_xlfn.XLOOKUP(LARGE('DONNÉES BRUTES'!Y$3:Y$90,18),'DONNÉES BRUTES'!Y$3:Y$90,'DONNÉES BRUTES'!A$3:A$90),"—") -> TRGP | D24: =IFERROR(_xlfn.XLOOKUP(C24,'DONNÉES BRUTES'!A$3:A$90,'DONNÉES BRUTES'!B$3:B$90),"—") -> Targa Resources Corp. | F24: =IFERROR(_xlfn.XLOOKUP(C24,'DONNÉES BRUTES'!A$3:A$90,'DONNÉES BRUTES'!Y$3:Y$90)&"/100","—") -> 67/100 | G24: =IFERROR(_xlfn.XLOOKUP(C24,'DONNÉES BRUTES'!A$3:A$90,'DONNÉES BRUTES'!P$3:P$90),"—") -> 0.039 | H24: =IFERROR(_xlfn.XLOOKUP(C24,'DONNÉES BRUTES'!A$3:A$90,'DONNÉES BRUTES'!N$3:N$90),"—") -> 0.285 | I24: =IFERROR(_xlfn.XLOOKUP(C24,'DONNÉES BRUTES'!A$3:A$90,'DONNÉES BRUTES'!O$3:O$90),"—") -> 0.113 | J24: =IFERROR(_xlfn.XLOOKUP(C24,'DONNÉES BRUTES'!A$3:A$90,'DONNÉES BRUTES'!Q$3:Q$90),"—") -> 0.627 | K24: =IFERROR(_xlfn.XLOOKUP(C24,'DONNÉES BRUTES'!A$3:A$90,'DONNÉES BRUTES'!AB$3:AB$90),"—") -> 61 | L24: =IFERROR(_xlfn.XLOOKUP(C24,'DONNÉES BRUTES'!A$3:A$90,'DONNÉES BRUTES'!AC$3:AC$90),"—") -> 2026-04-30 | M24: =IFERROR(_xlfn.XLOOKUP(C24,'DONNÉES BRUTES'!A$3:A$90,'DONNÉES BRUTES'!AD$3:AD$90),"—") -> Neutre
B25: 19 | C25: =IFERROR(_xlfn.XLOOKUP(LARGE('DONNÉES BRUTES'!Y$3:Y$90,19),'DONNÉES BRUTES'!Y$3:Y$90,'DONNÉES BRUTES'!A$3:A$90),"—") -> ADBE | D25: =IFERROR(_xlfn.XLOOKUP(C25,'DONNÉES BRUTES'!A$3:A$90,'DONNÉES BRUTES'!B$3:B$90),"—") -> Adobe Inc. | F25: =IFERROR(_xlfn.XLOOKUP(C25,'DONNÉES BRUTES'!A$3:A$90,'DONNÉES BRUTES'!Y$3:Y$90)&"/100","—") -> 65/100 | G25: =IFERROR(_xlfn.XLOOKUP(C25,'DONNÉES BRUTES'!A$3:A$90,'DONNÉES BRUTES'!P$3:P$90),"—") -> 0.105 | H25: =IFERROR(_xlfn.XLOOKUP(C25,'DONNÉES BRUTES'!A$3:A$90,'DONNÉES BRUTES'!N$3:N$90),"—") -> 0.413 | I25: =IFERROR(_xlfn.XLOOKUP(C25,'DONNÉES BRUTES'!A$3:A$90,'DONNÉES BRUTES'!O$3:O$90),"—") -> 0.3 | J25: =IFERROR(_xlfn.XLOOKUP(C25,'DONNÉES BRUTES'!A$3:A$90,'DONNÉES BRUTES'!Q$3:Q$90),"—") -> 0.613 | K25: =IFERROR(_xlfn.XLOOKUP(C25,'DONNÉES BRUTES'!A$3:A$90,'DONNÉES BRUTES'!AB$3:AB$90),"—") -> 69 | L25: =IFERROR(_xlfn.XLOOKUP(C25,'DONNÉES BRUTES'!A$3:A$90,'DONNÉES BRUTES'!AC$3:AC$90),"—") -> 2026-06-11 | M25: =IFERROR(_xlfn.XLOOKUP(C25,'DONNÉES BRUTES'!A$3:A$90,'DONNÉES BRUTES'!AD$3:AD$90),"—") -> Neutre
B26: 20 | C26: =IFERROR(_xlfn.XLOOKUP(LARGE('DONNÉES BRUTES'!Y$3:Y$90,20),'DONNÉES BRUTES'!Y$3:Y$90,'DONNÉES BRUTES'!A$3:A$90),"—") -> QCOM | D26: =IFERROR(_xlfn.XLOOKUP(C26,'DONNÉES BRUTES'!A$3:A$90,'DONNÉES BRUTES'!B$3:B$90),"—") -> QUALCOMM Incorporated | F26: =IFERROR(_xlfn.XLOOKUP(C26,'DONNÉES BRUTES'!A$3:A$90,'DONNÉES BRUTES'!Y$3:Y$90)&"/100","—") -> 63/100 | G26: =IFERROR(_xlfn.XLOOKUP(C26,'DONNÉES BRUTES'!A$3:A$90,'DONNÉES BRUTES'!P$3:P$90),"—") -> 0.137 | H26: =IFERROR(_xlfn.XLOOKUP(C26,'DONNÉES BRUTES'!A$3:A$90,'DONNÉES BRUTES'!N$3:N$90),"—") -> 0.337 | I26: =IFERROR(_xlfn.XLOOKUP(C26,'DONNÉES BRUTES'!A$3:A$90,'DONNÉES BRUTES'!O$3:O$90),"—") -> — | J26: =IFERROR(_xlfn.XLOOKUP(C26,'DONNÉES BRUTES'!A$3:A$90,'DONNÉES BRUTES'!Q$3:Q$90),"—") -> — | K26: =IFERROR(_xlfn.XLOOKUP(C26,'DONNÉES BRUTES'!A$3:A$90,'DONNÉES BRUTES'!AB$3:AB$90),"—") -> 63 | L26: =IFERROR(_xlfn.XLOOKUP(C26,'DONNÉES BRUTES'!A$3:A$90,'DONNÉES BRUTES'!AC$3:AC$90),"—") -> — | M26: =IFERROR(_xlfn.XLOOKUP(C26,'DONNÉES BRUTES'!A$3:A$90,'DONNÉES BRUTES'!AD$3:AD$90),"—") -> Sous-pondérer
B28: FinSight IA · Screening Énergie · Ne constitue pas un conseil en investissement

Sheet QUALITY
B1: FinSight IA · Analyse QUALITY · Énergie Screening | N1: Ticker | O1: Score | Q1: Ticker | R1: AltZ | T1: Ticker | U1: Beneish M | W1: Ticker | X1: Mg EBITDA (%)
B2: Usage confidentiel · Calculs FinSight IA · Screening Énergie | N2: DSY.PA | O2: 100 | Q2: DSY.PA | R2: 0 | T2: DSY.PA | W2: DSY.PA | X2: 30.4
C3: =COUNTA('DONNÉES BRUTES'!A$3:A$90) -> 88 | F3: =IFERROR(_xlfn.XLOOKUP(LARGE('DONNÉES BRUTES'!Z$3:Z$90,1),'DONNÉES BRUTES'!Z$3:Z$90,'DONNÉES BRUTES'!A$3:A$90),"—") -> TPL | J3: =IFERROR(ROUND(AVERAGE('DONNÉES BRUTES'!Z$3:Z$90),0)&"/100","—") -> 68/100 | M3: VRSN | O3: 99 | Q3: VRSN | R3: 0 | T3: VRSN | U3: -2.84 | W3: VRSN | X3: 71
C4: Sociétés | F4: #1 Quality | J4: Moy. Score Quality | M4: NVDA | O4: 98 | Q4: NVDA | R4: 13.22 | T4: NVDA | U4: -2.19 | W4: NVDA | X4: 66.9
B5: ANALYSE DÉTAILLÉE · ÉNERGIE · TOP 20 par Quality · Triée par Score Quality | N5: ADBE | O5: 97 | Q5: ADBE | R5: 7.74 | T5: ADBE | U5: -2.97 | W5: ADBE | X5: 41.3
B6: # | C6: Ticker | D6: Société | F6: Score | G6: Altman Z | H6: Beneish M | I6: Mg EBITDA | J6: ROE | K6: Current R. | L6: ND/EBITDA | M6: Score Global | N6: FICO | O6: 95 | Q6: FICO | R6: 10.3 | T6: FICO | U6: -2.94 | W6: FICO | X6: 47.8
B7: 1 | C7: {=IFERROR(INDEX('DONNÉES BRUTES'!A$3:A$90,MATCH(1,('DONNÉES BRUTES'!Z$3:Z$90=LARGE('DONNÉES BRUTES'!Z$3:Z$90,1))*(COUNTIF(C$6:C6,'DONNÉES BRUTES'!A$3:A$90)=0)*('DONNÉES BRUTES'!A$3:A$90<>""),0)),"—")} -> TPL | D7: =IFERROR(_xlfn.XLOOKUP(C7,'DONNÉES BRUTES'!A$3:A$90,'DONNÉES BRUTES'!B$3:B$90),"—") -> Texas Pacific Land Corporation | F7: =IFERROR(_xlfn.XLOOKUP(C7,'DONNÉES BRUTES'!A$3:A$90,'DONNÉES BRUTES'!Z$3:Z$90)&"/100","—") -> 91/100 | G7: =IFERROR(_xlfn.XLOOKUP(C7,'DONNÉES BRUTES'!A$3:A$90,'DONNÉES BRUTES'!U$3:U$90),"—") -> 16.05 | H7: =IFERROR(_xlfn.XLOOKUP(C7,'DONNÉES BRUTES'!A$3:A$90,'DONNÉES BRUTES'!V$3:V$90),"—") -> -2.72 | I7: =IFERROR(_xlfn.XLOOKUP(C7,'DONNÉES BRUTES'!A$3:A$90,'DONNÉES BRUTES'!N$3:N$90),"—") -> 0.844 | J7: =IFERROR(_xlfn.XLOOKUP(C7,'DONNÉES BRUTES'!A$3:A$90,'DONNÉES BRUTES'!Q$3:Q$90),"—") -> 0.33 | K7: =IFERROR(_xlfn.XLOOKUP(C7,'DONNÉES BRUTES'!A$3:A$90,'DONNÉES BRUTES'!S$3:S$90),"—") -> 4.34 | L7: =IFERROR(_xlfn.XLOOKUP(C7,'DONNÉES BRUTES'!A$3:A$90,'DONNÉES BRUTES'!T$3:T$90),"—") -> -0.2x | M7: =IFERROR(_xlfn.XLOOKUP(C7,'DONNÉES BRUTES'!A$3:A$90,'DONNÉES BRUTES'!AB$3:AB$90),"—") -> 59 | N7: PTC | O7: 94 | Q7: PTC | R7: 3.62 | T7: PTC | U7: -2.99 | W7: PTC | X7: 41.3
B8: 2 | C8: {=IFERROR(INDEX('DONNÉES BRUTES'!A$3:A$90,MATCH(1,('DONNÉES BRUTES'!Z$3:Z$90>=LARGE('DONNÉES BRUTES'!Z$3:Z$90,2))*(COUNTIF(C$6:C7,'DONNÉES BRUTES'!A$3:A$90)=0)*('DONNÉES BRUTES'!A$3:A$90<>""),0)),"—")} -> AMAT | D8: =IFERROR(_xlfn.XLOOKUP(C8,'DONNÉES BRUTES'!A$3:A$90,'DONNÉES BRUTES'!B$3:B$90),"—") -> Applied Materials, Inc. | F8: =IFERROR(_xlfn.XLOOKUP(C8,'DONNÉES BRUTES'!A$3:A$90,'DONNÉES BRUTES'!Z$3:Z$90)&"/100","—") -> 91/100 | G8: =IFERROR(_xlfn.XLOOKUP(C8,'DONNÉES BRUTES'!A$3:A$90,'DONNÉES BRUTES'!U$3:U$90),"—") -> 10.40 | H8: =IFERROR(_xlfn.XLOOKUP(C8,'DONNÉES BRUTES'!A$3:A$90,'DONNÉES BRUTES'!V$3:V$90),"—") -> -3.07 | I8: =IFERROR(_xlfn.XLOOKUP(C8,'DONNÉES BRUTES'!A$3:A$90,'DONNÉES BRUTES'!N$3:N$90),"—") -> 0.352 | J8: =IFERROR(_xlfn.XLOOKUP(C8,'DONNÉES BRUTES'!A$3:A$90,'DONNÉES BRUTES'!Q$3:Q$90),"—") -> 0.343 | K8: =IFERROR(_xlfn.XLOOKUP(C8,'DONNÉES BRUTES'!A$3:A$90,'DONNÉES BRUTES'!S$3:S$90),"—") -> 2.61 | L8: =IFERROR(_xlfn.XLOOKUP(C8,'DONNÉES BRUTES'!A$3:A$90,'DONNÉES BRUTES'!T$3:T$90),"—") -> -0.1x | M8: =IFERROR(_xlfn.XLOOKUP(C8,'DONNÉES BRUTES'!A$3:A$90,'DONNÉES BRUTES'!AB$3:AB$90),"—") -> 77 | N8: CDNS | O8: 93 | Q8: CDNS | R8: 6.55 | T8: CDNS | U8: -2.92 | W8: CDNS | X8: 35.4
B9: 3 | C9: {=IFERROR(INDEX('DONNÉES BRUTES'!A$3:A$90,MATCH(1,('DONNÉES BRUTES'!Z$3:Z$90>=LARGE('DONNÉES BRUTES'!Z$3:Z$90,3))*(COUNTIF(C$6:C8,'DONNÉES BRUTES'!A$3:A$90)=0)*('DONNÉES BRUTES'!A$3:A$90<>""),0)),"—")} -> FTNT | D9: =IFERROR(_xlfn.XLOOKUP(C9,'DONNÉES BRUTES'!A$3:A$90,'DONNÉES BRUTES'!B$3:B$90),"—") -> Fortinet, Inc. | F9: =IFERROR(_xlfn.XLOOKUP(C9,'DONNÉES BRUTES'!A$3:A$90,'DONNÉES BRUTES'!Z$3:Z$90)&"/100","—") -> 91/100 | G9: =IFERROR(_xlfn.XLOOKUP(C9,'DONNÉES BRUTES'!A$3:A$90,'DONNÉES BRUTES'!U$3:U$90),"—") -> 2.02 | H9: =IFERROR(_xlfn.XLOOKUP(C9,'DONNÉES BRUTES'!A$3:A$90,'DONNÉES BRUTES'!V$3:V$90),"—") -> -2.92 | I9: =IFERROR(_xlfn.XLOOKUP(C9,'DONNÉES BRUTES'!A$3:A$90,'DONNÉES BRUTES'!N$3:N$90),"—") -> 0.361 | J9: =IFERROR(_xlfn.XLOOKUP(C9,'DONNÉES BRUTES'!A$3:A$90,'DONNÉES BRUTES'!Q$3:Q$90),"—") -> 1.498 | K9: =IFERROR(_xlfn.XLOOKUP(C9,'DONNÉES BRUTES'!A$3:A$90,'DONNÉES BRUTES'!S$3:S$90),"—") -> 1.17 | L9: =IFERROR(_xlfn.XLOOKUP(C9,'DONNÉES BRUTES'!A$3:A$90,'DONNÉES BRUTES'!T$3:T$90),"—") -> -0.6x | M9: =IFERROR(_xlfn.XLOOKUP(C9,'DONNÉES BRUTES'!A$3:A$90,'DONNÉES BRUTES'!AB$3:AB$90),"—") -> 70 | N9: FTNT | O9: 92 | Q9: FTNT | R9: 2.02 | T9: FTNT | U9: -2.92 | W9: FTNT | X9: 36.1
B10: 4 | C10: {=IFERROR(INDEX('DONNÉES BRUTES'!A$3:A$90,MATCH(1,('DONNÉES BRUTES'!Z$3:Z$90>=LARGE('DONNÉES BRUTES'!Z$3:Z$90,4))*(COUNTIF(C$6:C9,'DONNÉES BRUTES'!A$3:A$90)=0)*('DONNÉES BRUTES'!A$3:A$90<>""),0)),"—")} -> ADBE | D10: =IFERROR(_xlfn.XLOOKUP(C10,'DONNÉES BRUTES'!A$3:A$90,'DONNÉES BRUTES'!B$3:B$90),"—") -> Adobe Inc. | F10: =IFERROR(_xlfn.XLOOKUP(C10,'DONNÉES BRUTES'!A$3:A$90,'DONNÉES BRUTES'!Z$3:Z$90)&"/100","—") -> 91/100 | G10: =IFERROR(_xlfn.XLOOKUP(C10,'DONNÉES BRUTES'!A$3:A$90,'DONNÉES BRUTES'!U$3:U$90),"—") -> 7.74 | H10: =IFERROR(_xlfn.XLOOKUP(C10,'DONNÉES BRUTES'!A$3:A$90,'DONNÉES BRUTES'!V$3:V$90),"—") -> -2.97 | I10: =IFERROR(_xlfn.XLOOKUP(C10,'DONNÉES BRUTES'!A$3:A$90,'DONNÉES BRUTES'!N$3:N$90),"—") -> 0.413 | J10: =IFERROR(_xlfn.XLOOKUP(C10,'DONNÉES BRUTES'!A$3:A$90,'DONNÉES BRUTES'!Q$3:Q$90),"—") -> 0.613 | K10: =IFERROR(_xlfn.XLOOKUP(C10,'DONNÉES BRUTES'!A$3:A$90,'DONNÉES BRUTES'!S$3:S$90),"—") -> 1.00 | L10: =IFERROR(_xlfn.XLOOKUP(C10,'DONNÉES BRUTES'!A$3:A$90,'DONNÉES BRUTES'!T$3:T$90),"—") -> 0.1x | M10: =IFERROR(_xlfn.XLOOKUP(C10,'DONNÉES BRUTES'!A$3:A$90,'DONNÉES BRUTES'!AB$3:AB$90),"—") -> 69 | N10: SGE.L | O10: 91 | Q10: SGE.L | R10: 0 | T10: SGE.L | W10: SGE.L | X10: 25
B11: 5 | C11: {=IFERROR(INDEX('DONNÉES BRUTES'!A$3:A$90,MATCH(1,('DONNÉES BRUTES'!Z$3:Z$90>=LARGE('DONNÉES BRUTES'!Z$3:Z$90,5))*(COUNTIF(C$6:C10,'DONNÉES BRUTES'!A$3:A$90)=0)*('DONNÉES BRUTES'!A$3:A$90<>""),0)),"—")} -> CRM | D11: =IFERROR(_xlfn.XLOOKUP(C11,'DONNÉES BRUTES'!A$3:A$90,'DONNÉES BRUTES'!B$3:B$90),"—") -> Salesforce, Inc. | F11: =IFERROR(_xlfn.XLOOKUP(C11,'DONNÉES BRUTES'!A$3:A$90,'DONNÉES BRUTES'!Z$3:Z$90)&"/100","—") -> 88/100 | G11: =IFERROR(_xlfn.XLOOKUP(C11,'DONNÉES BRUTES'!A$3:A$90,'DONNÉES BRUTES'!U$3:U$90),"—") -> — | H11: =IFERROR(_xlfn.XLOOKUP(C11,'DONNÉES BRUTES'!A$3:A$90,'DONNÉES BRUTES'!V$3:V$90),"—") -> — | I11: =IFERROR(_xlfn.XLOOKUP(C11,'DONNÉES BRUTES'!A$3:A$90,'DONNÉES BRUTES'!N$3:N$90),"—") -> 0.302 | J11: =IFERROR(_xlfn.XLOOKUP(C11,'DONNÉES BRUTES'!A$3:A$90,'DONNÉES BRUTES'!Q$3:Q$90),"—") -> — | K11: =IFERROR(_xlfn.XLOOKUP(C11,'DONNÉES BRUTES'!A$3:A$90,'DONNÉES BRUTES'!S$3:S$90),"—") -> — | L11: =IFERROR(_xlfn.XLOOKUP(C11,'DONNÉES BRUTES'!A$3:A$90,'DONNÉES BRUTES'!T$3:T$90),"—") -> — | M11: =IFERROR(_xlfn.XLOOKUP(C11,'DONNÉES BRUTES'!A$3:A$90,'DONNÉES BRUTES'!AB$3:AB$90),"—") -> 58 | N11: ADSK | O11: 90 | Q11: ADSK | R11: 0.48 | T11: ADSK | U11: -2.86 | W11: ADSK | X11: 27.6
B12: 6 | C12: {=IFERROR(INDEX('DONNÉES BRUTES'!A$3:A$90,MATCH(1,('DONNÉES BRUTES'!Z$3:Z$90>=LARGE('DONNÉES BRUTES'!Z$3:Z$90,6))*(COUNTIF(C$6:C11,'DONNÉES BRUTES'!A$3:A$90)=0)*('DONNÉES BRUTES'!A$3:A$90<>""),0)),"—")} -> WDAY | D12: =IFERROR(_xlfn.XLOOKUP(C12,'DONNÉES BRUTES'!A$3:A$90,'DONNÉES BRUTES'!B$3:B$90),"—") -> Workday, Inc. | F12: =IFERROR(_xlfn.XLOOKUP(C12,'DONNÉES BRUTES'!A$3:A$90,'DONNÉES BRUTES'!Z$3:Z$90)&"/100","—") -> 88/100 | G12: =IFERROR(_xlfn.XLOOKUP(C12,'DONNÉES BRUTES'!A$3:A$90,'DONNÉES BRUTES'!U$3:U$90),"—") -> — | H12: =IFERROR(_xlfn.XLOOKUP(C12,'DONNÉES BRUTES'!A$3:A$90,'DONNÉES BRUTES'!V$3:V$90),"—") -> — | I12: =IFERROR(_xlfn.XLOOKUP(C12,'DONNÉES BRUTES'!A$3:A$90,'DONNÉES BRUTES'!N$3:N$90),"—") -> 0.154 | J12: =IFERROR(_xlfn.XLOOKUP(C12,'DONNÉES BRUTES'!A$3:A$90,'DONNÉES BRUTES'!Q$3:Q$90),"—") -> — | K12: =IFERROR(_xlfn.XLOOKUP(C12,'DONNÉES BRUTES'!A$3:A$90,'DONNÉES BRUTES'!S$3:S$90),"—") -> — | L12: =IFERROR(_xlfn.XLOOKUP(C12,'DONNÉES BRUTES'!A$3:A$90,'DONNÉES BRUTES'!T$3:T$90),"—") -> — | M12: =IFERROR(_xlfn.XLOOKUP(C12,'DONNÉES BRUTES'!A$3:A$90,'DONNÉES BRUTES'!AB$3:AB$90),"—") -> 63 | N12: ANET | O12: 89 | Q12: ANET | R12: 8.46 | T12: ANET | U12: -2.58 | W12: ANET | X12: 43.6
B13: 7 | C13: {=IFERROR(INDEX('DONNÉES BRUTES'!A$3:A$90,MATCH(1,('DONNÉES BRUTES'!Z$3:Z$90>=LARGE('DONNÉES BRUTES'!Z$3:Z$90,7))*(COUNTIF(C$6:C12,'DONNÉES BRUTES'!A$3:A$90)=0)*('DONNÉES BRUTES'!A$3:A$90<>""),0)),"—")} -> FSLR | D13: =IFERROR(_xlfn.XLOOKUP(C13,'DONNÉES BRUTES'!A$3:A$90,'DONNÉES BRUTES'!B$3:B$90),"—") -> First Solar, Inc. | F13: =IFERROR(_xlfn.XLOOKUP(C13,'DONNÉES BRUTES'!A$3:A$90,'DONNÉES BRUTES'!Z$3:Z$90)&"/100","—") -> 84/100 | G13: =IFERROR(_xlfn.XLOOKUP(C13,'DONNÉES BRUTES'!A$3:A$90,'DONNÉES BRUTES'!U$3:U$90),"—") -> 6.99 | H13: =IFERROR(_xlfn.XLOOKUP(C13,'DONNÉES BRUTES'!A$3:A$90,'DONNÉES BRUTES'!V$3:V$90),"—") -> -3.05 | I13: =IFERROR(_xlfn.XLOOKUP(C13,'DONNÉES BRUTES'!A$3:A$90,'DONNÉES BRUTES'!N$3:N$90),"—") -> 0.413 | J13: =IFERROR(_xlfn.XLOOKUP(C13,'DONNÉES BRUTES'!A$3:A$90,'DONNÉES BRUTES'!Q$3:Q$90),"—") -> 0.16 | K13: =IFERROR(_xlfn.XLOOKUP(C13,'DONNÉES BRUTES'!A$3:A$90,'DONNÉES BRUTES'!S$3:S$90),"—") -> 2.67 | L13: =IFERROR(_xlfn.XLOOKUP(C13,'DONNÉES BRUTES'!A$3:A$90,'DONNÉES BRUTES'!T$3:T$90),"—") -> -1.1x | M13: =IFERROR(_xlfn.XLOOKUP(C13,'DONNÉES BRUTES'!A$3:A$90,'DONNÉES BRUTES'!AB$3:AB$90),"—") -> 63 | N13: MSFT | O13: 87 | Q13: MSFT | R13: 4.46 | T13: MSFT | U13: -3 | W13: MSFT | X13: 56.9
B14: 8 | C14: {=IFERROR(INDEX('DONNÉES BRUTES'!A$3:A$90,MATCH(1,('DONNÉES BRUTES'!Z$3:Z$90>=LARGE('DONNÉES BRUTES'!Z$3:Z$90,8))*(COUNTIF(C$6:C13,'DONNÉES BRUTES'!A$3:A$90)=0)*('DONNÉES BRUTES'!A$3:A$90<>""),0)),"—")} -> SGE.L | D14: =IFERROR(_xlfn.XLOOKUP(C14,'DONNÉES BRUTES'!A$3:A$90,'DONNÉES BRUTES'!B$3:B$90),"—") -> The Sage Group plc | F14: =IFERROR(_xlfn.XLOOKUP(C14,'DONNÉES BRUTES'!A$3:A$90,'DONNÉES BRUTES'!Z$3:Z$90)&"/100","—") -> 82/100 | G14: =IFERROR(_xlfn.XLOOKUP(C14,'DONNÉES BRUTES'!A$3:A$90,'DONNÉES BRUTES'!U$3:U$90),"—") -> — | H14: =IFERROR(_xlfn.XLOOKUP(C14,'DONNÉES BRUTES'!A$3:A$90,'DONNÉES BRUTES'!V$3:V$90),"—") -> — | I14: =IFERROR(_xlfn.XLOOKUP(C14,'DONNÉES BRUTES'!A$3:A$90,'DONNÉES BRUTES'!N$3:N$90),"—") -> 0.25 | J14: =IFERROR(_xlfn.XLOOKUP(C14,'DONNÉES BRUTES'!A$3:A$90,'DONNÉES BRUTES'!Q$3:Q$90),"—") -> — | K14: =IFERROR(_xlfn.XLOOKUP(C14,'DONNÉES BRUTES'!A$3:A$90,'DONNÉES BRUTES'!S$3:S$90),"—") -> — | L14: =IFERROR(_xlfn.XLOOKUP(C14,'DONNÉES BRUTES'!A$3:A$90,'DONNÉES BRUTES'!T$3:T$90),"—") -> — | M14: =IFERROR(_xlfn.XLOOKUP(C14,'DONNÉES BRUTES'!A$3:A$90,'DONNÉES BRUTES'!AB$3:AB$90),"—") -> 52 | N14: PAYC | O14: 86 | Q14: PAYC | R14: 0 | T14: PAYC | W14: PAYC | X14: 38.9
B15: 9 | C15: {=IFERROR(INDEX('DONNÉES BRUTES'!A$3:A$90,MATCH(1,('DONNÉES BRUTES'!Z$3:Z$90>=LARGE('DONNÉES BRUTES'!Z$3:Z$90,9))*(COUNTIF(C$6:C14,'DONNÉES BRUTES'!A$3:A$90)=0)*('DONNÉES BRUTES'!A$3:A$90<>""),0)),"—")} -> DSY.PA | D15: =IFERROR(_xlfn.XLOOKUP(C15,'DONNÉES BRUTES'!A$3:A$90,'DONNÉES BRUTES'!B$3:B$90),"—") -> Dassault Systèmes SE | F15: =IFERROR(_xlfn.XLOOKUP(C15,'DONNÉES BRUTES'!A$3:A$90,'DONNÉES BRUTES'!Z$3:Z$90)&"/100","—") -> 82/100 | G15: =IFERROR(_xlfn.XLOOKUP(C15,'DONNÉES BRUTES'!A$3:A$90,'DONNÉES BRUTES'!U$3:U$90),"—") -> — | H15: =IFERROR(_xlfn.XLOOKUP(C15,'DONNÉES BRUTES'!A$3:A$90,'DONNÉES BRUTES'!V$3:V$90),"—") -> — | I15: =IFERROR(_xlfn.XLOOKUP(C15,'DONNÉES BRUTES'!A$3:A$90,'DONNÉES BRUTES'!N$3:N$90),"—") -> 0.304 | J15: =IFERROR(_xlfn.XLOOKUP(C15,'DONNÉES BRUTES'!A$3:A$90,'DONNÉES BRUTES'!Q$3:Q$90),"—") -> — | K15: =IFERROR(_xlfn.XLOOKUP(C15,'DONNÉES BRUTES'!A$3:A$90,'DONNÉES BRUTES'!S$3:S$90),"—") -> — | L15: =IFERROR(_xlfn.XLOOKUP(C15,'DONNÉES BRUTES'!A$3:A$90,'DONNÉES BRUTES'!T$3:T$90),"—") -> — | M15: =IFERROR(_xlfn.XLOOKUP(C15,'DONNÉES BRUTES'!A$3:A$90,'DONNÉES BRUTES'!AB$3:AB$90),"—") -> 40 | N15: AVGO | O15: 85 | Q15: AVGO | R15: 2.66 | T15: AVGO | U15: -2.72 | W15: AVGO | X15: 54.3
B16: 10 | C16: {=IFERROR(INDEX('DONNÉES BRUTES'!A$3:A$90,MATCH(1,('DONNÉES BRUTES'!Z$3:Z$90>=LARGE('DONNÉES BRUTES'!Z$3:Z$90,10))*(COUNTIF(C$6:C15,'DONNÉES BRUTES'!A$3:A$90)=0)*('DONNÉES BRUTES'!A$3:A$90<>""),0)),"—")} -> JKHY | D16: =IFERROR(_xlfn.XLOOKUP(C16,'DONNÉES BRUTES'!A$3:A$90,'DONNÉES BRUTES'!B$3:B$90),"—") -> Jack Henry & Associates, Inc. | F16: =IFERROR(_xlfn.XLOOKUP(C16,'DONNÉES BRUTES'!A$3:A$90,'DONNÉES BRUTES'!Z$3:Z$90)&"/100","—") -> 82/100 | G16: =IFERROR(_xlfn.XLOOKUP(C16,'DONNÉES BRUTES'!A$3:A$90,'DONNÉES BRUTES'!U$3:U$90),"—") -> — | H16: =IFERROR(_xlfn.XLOOKUP(C16,'DONNÉES BRUTES'!A$3:A$90,'DONNÉES BRUTES'!V$3:V$90),"—") -> — | I16: =IFERROR(_xlfn.XLOOKUP(C16,'DONNÉES BRUTES'!A$3:A$90,'DONNÉES BRUTES'!N$3:N$90),"—") -> 0.337 | J16: =IFERROR(_xlfn.XLOOKUP(C16,'DONNÉES BRUTES'!A$3:A$90,'DONNÉES BRUTES'!Q$3:Q$90),"—") -> — | K16: =IFERROR(_xlfn.XLOOKUP(C16,'DONNÉES BRUTES'!A$3:A$90,'DONNÉES BRUTES'!S$3:S$90),"—") -> — | L16: =IFERROR(_xlfn.XLOOKUP(C16,'DONNÉES BRUTES'!A$3:A$90,'DONNÉES BRUTES'!T$3:T$90),"—") -> — | M16: =IFERROR(_xlfn.XLOOKUP(C16,'DONNÉES BRUTES'!A$3:A$90,'DONNÉES BRUTES'!AB$3:AB$90),"—") -> 57 | N16: FFIV | O16: 84 | Q16: FFIV | R16: 5.01 | T16: FFIV | U16: -3.06 | W16: FFIV | X16: 28.6
B17: 11 | C17: {=IFERROR(INDEX('DONNÉES BRUTES'!A$3:A$90,MATCH(1,('DONNÉES BRUTES'!Z$3:Z$90>=LARGE('DONNÉES BRUTES'!Z$3:Z$90,11))*(COUNTIF(C$6:C16,'DONNÉES BRUTES'!A$3:A$90)=0)*('DONNÉES BRUTES'!A$3:A$90<>""),0)),"—")} -> ROP | D17: =IFERROR(_xlfn.XLOOKUP(C17,'DONNÉES BRUTES'!A$3:A$90,'DONNÉES BRUTES'!B$3:B$90),"—") -> Roper Technologies, Inc. | F17: =IFERROR(_xlfn.XLOOKUP(C17,'DONNÉES BRUTES'!A$3:A$90,'DONNÉES BRUTES'!Z$3:Z$90)&"/100","—") -> 82/100 | G17: =IFERROR(_xlfn.XLOOKUP(C17,'DONNÉES BRUTES'!A$3:A$90,'DONNÉES BRUTES'!U$3:U$90),"—") -> — | H17: =IFERROR(_xlfn.XLOOKUP(C17,'DONNÉES BRUTES'!A$3:A$90,'DONNÉES BRUTES'!V$3:V$90),"—") -> — | I17: =IFERROR(_xlfn.XLOOKUP(C17,'DONNÉES BRUTES'!A$3:A$90,'DONNÉES BRUTES'!N$3:N$90),"—") -> 0.4 | J17: =IFERROR(_xlfn.XLOOKUP(C17,'DONNÉES BRUTES'!A$3:A$90,'DONNÉES BRUTES'!Q$3:Q$90),"—") -> — | K17: =IFERROR(_xlfn.XLOOKUP(C17,'DONNÉES BRUTES'!A$3:A$90,'DONNÉES BRUTES'!S$3:S$90),"—") -> — | L17: =IFERROR(_xlfn.XLOOKUP(C17,'DONNÉES BRUTES'!A$3:A$90,'DONNÉES BRUTES'!T$3:T$90),"—") -> — | M17: =IFERROR(_xlfn.XLOOKUP(C17,'DONNÉES BRUTES'!A$3:A$90,'DONNÉES BRUTES'!AB$3:AB$90),"—") -> 47 | N17: CPAY | O17: 83 | Q17: CPAY | R17: 1.86 | T17: CPAY | U17: -3.13 | W17: CPAY | X17: 51.6
B18: 12 | C18: {=IFERROR(INDEX('DONNÉES BRUTES'!A$3:A$90,MATCH(1,('DONNÉES BRUTES'!Z$3:Z$90>=LARGE('DONNÉES BRUTES'!Z$3:Z$90,12))*(COUNTIF(C$6:C17,'DONNÉES BRUTES'!A$3:A$90)=0)*('DONNÉES BRUTES'!A$3:A$90<>""),0)),"—")} -> IFX.DE | D18: =IFERROR(_xlfn.XLOOKUP(C18,'DONNÉES BRUTES'!A$3:A$90,'DONNÉES BRUTES'!B$3:B$90),"—") -> Infineon Technologies AG | F18: =IFERROR(_xlfn.XLOOKUP(C18,'DONNÉES BRUTES'!A$3:A$90,'DONNÉES BRUTES'!Z$3:Z$90)&"/100","—") -> 82/100 | G18: =IFERROR(_xlfn.XLOOKUP(C18,'DONNÉES BRUTES'!A$3:A$90,'DONNÉES BRUTES'!U$3:U$90),"—") -> — | H18: =IFERROR(_xlfn.XLOOKUP(C18,'DONNÉES BRUTES'!A$3:A$90,'DONNÉES BRUTES'!V$3:V$90),"—") -> — | I18: =IFERROR(_xlfn.XLOOKUP(C18,'DONNÉES BRUTES'!A$3:A$90,'DONNÉES BRUTES'!N$3:N$90),"—") -> 0.24 | J18: =IFERROR(_xlfn.XLOOKUP(C18,'DONNÉES BRUTES'!A$3:A$90,'DONNÉES BRUTES'!Q$3:Q$90),"—") -> — | K18: =IFERROR(_xlfn.XLOOKUP(C18,'DONNÉES BRUTES'!A$3:A$90,'DONNÉES BRUTES'!S$3:S$90),"—") -> — | L18: =IFERROR(_xlfn.XLOOKUP(C18,'DONNÉES BRUTES'!A$3:A$90,'DONNÉES BRUTES'!T$3:T$90),"—") -> — | M18: =IFERROR(_xlfn.XLOOKUP(C18,'DONNÉES BRUTES'!A$3:A$90,'DONNÉES BRUTES'!AB$3:AB$90),"—") -> 50 | N18: INTU | O18: 82 | Q18: INTU | R18: 4.52 | T18: INTU | U18: -3.05 | W18: INTU | X18: 31.3
B19: 13 | C19: {=IFERROR(INDEX('DONNÉES BRUTES'!A$3:A$90,MATCH(1,('DONNÉES BRUTES'!Z$3:Z$90>=LARGE('DONNÉES BRUTES'!Z$3:Z$90,13))*(COUNTIF(C$6:C18,'DONNÉES BRUTES'!A$3:A$90)=0)*('DONNÉES BRUTES'!A$3:A$90<>""),0)),"—")} -> CTSH | D19: =IFERROR(_xlfn.XLOOKUP(C19,'DONNÉES BRUTES'!A$3:A$90,'DONNÉES BRUTES'!B$3:B$90),"—") -> Cognizant Technology Solutions Corporation | F19: =IFERROR(_xlfn.XLOOKUP(C19,'DONNÉES BRUTES'!A$3:A$90,'DONNÉES BRUTES'!Z$3:Z$90)&"/100","—") -> 82/100 | G19: =IFERROR(_xlfn.XLOOKUP(C19,'DONNÉES BRUTES'!A$3:A$90,'DONNÉES BRUTES'!U$3:U$90),"—") -> — | H19: =IFERROR(_xlfn.XLOOKUP(C19,'DONNÉES BRUTES'!A$3:A$90,'DONNÉES BRUTES'!V$3:V$90),"—") -> — | I19: =IFERROR(_xlfn.XLOOKUP(C19,'DONNÉES BRUTES'!A$3:A$90,'DONNÉES BRUTES'!N$3:N$90),"—") -> 0.193 | J19: =IFERROR(_xlfn.XLOOKUP(C19,'DONNÉES BRUTES'!A$3:A$90,'DONNÉES BRUTES'!Q$3:Q$90),"—") -> — | K19: =IFERROR(_xlfn.XLOOKUP(C19,'DONNÉES BRUTES'!A$3:A$90,'DONNÉES BRUTES'!S$3:S$90),"—") -> — | L19: =IFERROR(_xlfn.XLOOKUP(C19,'DONNÉES BRUTES'!A$3:A$90,'DONNÉES BRUTES'!T$3:T$90),"—") -> — | M19: =IFERROR(_xlfn.XLOOKUP(C19,'DONNÉES BRUTES'!A$3:A$90,'DONNÉES BRUTES'!AB$3:AB$90),"—") -> 56 | N19: SNPS | O19: 80 | Q19: SNPS | R19: 2.76 | T19: SNPS | U19: -2.05 | W19: SNPS | X19: 35.4
B20: 14 | C20: {=IFERROR(INDEX('DONNÉES BRUTES'!A$3:A$90,MATCH(1,('DONNÉES BRUTES'!Z$3:Z$90>=LARGE('DONNÉES BRUTES'!Z$3:Z$90,14))*(COUNTIF(C$6:C19,'DONNÉES BRUTES'!A$3:A$90)=0)*('DONNÉES BRUTES'!A$3:A$90<>""),0)),"—")} -> ACN | D20: =IFERROR(_xlfn.XLOOKUP(C20,'DONNÉES BRUTES'!A$3:A$90,'DONNÉES BRUTES'!B$3:B$90),"—") -> Accenture plc | F20: =IFERROR(_xlfn.XLOOKUP(C20,'DONNÉES BRUTES'!A$3:A$90,'DONNÉES BRUTES'!Z$3:Z$90)&"/100","—") -> 82/100 | G20: =IFERROR(_xlfn.XLOOKUP(C20,'DONNÉES BRUTES'!A$3:A$90,'DONNÉES BRUTES'!U$3:U$90),"—") -> — | H20: =IFERROR(_xlfn.XLOOKUP(C20,'DONNÉES BRUTES'!A$3:A$90,'DONNÉES BRUTES'!V$3:V$90),"—") -> — | I20: =IFERROR(_xlfn.XLOOKUP(C20,'DONNÉES BRUTES'!A$3:A$90,'DONNÉES BRUTES'!N$3:N$90),"—") -> 0.17 | J20: =IFERROR(_xlfn.XLOOKUP(C20,'DONNÉES BRUTES'!A$3:A$90,'DONNÉES BRUTES'!Q$3:Q$90),"—") -> — | K20: =IFERROR(_xlfn.XLOOKUP(C20,'DONNÉES BRUTES'!A$3:A$90,'DONNÉES BRUTES'!S$3:S$90),"—") -> — | L20: =IFERROR(_xlfn.XLOOKUP(C20,'DONNÉES BRUTES'!A$3:A$90,'DONNÉES BRUTES'!T$3:T$90),"—") -> — | M20: =IFERROR(_xlfn.XLOOKUP(C20,'DONNÉES BRUTES'!A$3:A$90,'DONNÉES BRUTES'!AB$3:AB$90),"—") -> 48 | N20: KLAC | O20: 79 | Q20: KLAC | R20: 5.64 | T20: KLAC | U20: -2.95 | W20: KLAC | X20: 43.9
B21: 15 | C21: {=IFERROR(INDEX('DONNÉES BRUTES'!A$3:A$90,MATCH(1,('DONNÉES BRUTES'!Z$3:Z$90>=LARGE('DONNÉES BRUTES'!Z$3:Z$90,15))*(COUNTIF(C$6:C20,'DONNÉES BRUTES'!A$3:A$90)=0)*('DONNÉES BRUTES'!A$3:A$90<>""),0)),"—")} -> FIS | D21: =IFERROR(_xlfn.XLOOKUP(C21,'DONNÉES BRUTES'!A$3:A$90,'DONNÉES BRUTES'!B$3:B$90),"—") -> Fidelity National Information Services, Inc. | F21: =IFERROR(_xlfn.XLOOKUP(C21,'DONNÉES BRUTES'!A$3:A$90,'DONNÉES BRUTES'!Z$3:Z$90)&"/100","—") -> 82/100 | G21: =IFERROR(_xlfn.XLOOKUP(C21,'DONNÉES BRUTES'!A$3:A$90,'DONNÉES BRUTES'!U$3:U$90),"—") -> — | H21: =IFERROR(_xlfn.XLOOKUP(C21,'DONNÉES BRUTES'!A$3:A$90,'DONNÉES BRUTES'!V$3:V$90),"—") -> — | I21: =IFERROR(_xlfn.XLOOKUP(C21,'DONNÉES BRUTES'!A$3:A$90,'DONNÉES BRUTES'!N$3:N$90),"—") -> 0.323 | J21: =IFERROR(_xlfn.XLOOKUP(C21,'DONNÉES BRUTES'!A$3:A$90,'DONNÉES BRUTES'!Q$3:Q$90),"—") -> — | K21: =IFERROR(_xlfn.XLOOKUP(C21,'DONNÉES BRUTES'!A$3:A$90,'DONNÉES BRUTES'!S$3:S$90),"—") -> — | L21: =IFERROR(_xlfn.XLOOKUP(C21,'DONNÉES BRUTES'!A$3:A$90,'DONNÉES BRUTES'!T$3:T$90),"—") -> — | M21: =IFERROR(_xlfn.XLOOKUP(C21,'DONNÉES BRUTES'!A$3:A$90,'DONNÉES BRUTES'!AB$3:AB$90),"—") -> 43 | N21: APH | O21: 78 | Q21: APH | R21: 5.05 | T21: APH | U21: -2.88 | W21: APH | X21: 29.8
B22: 16 | C22: {=IFERROR(INDEX('DONNÉES BRUTES'!A$3:A$90,MATCH(1,('DONNÉES BRUTES'!Z$3:Z$90>=LARGE('DONNÉES BRUTES'!Z$3:Z$90,16))*(COUNTIF(C$6:C21,'DONNÉES BRUTES'!A$3:A$90)=0)*('DONNÉES BRUTES'!A$3:A$90<>""),0)),"—")} -> SAP.DE | D22: =IFERROR(_xlfn.XLOOKUP(C22,'DONNÉES BRUTES'!A$3:A$90,'DONNÉES BRUTES'!B$3:B$90),"—") -> SAP SE | F22: =IFERROR(_xlfn.XLOOKUP(C22,'DONNÉES BRUTES'!A$3:A$90,'DONNÉES BRUTES'!Z$3:Z$90)&"/100","—") -> 81/100 | G22: =IFERROR(_xlfn.XLOOKUP(C22,'DONNÉES BRUTES'!A$3:A$90,'DONNÉES BRUTES'!U$3:U$90),"—") -> 5.34 | H22: =IFERROR(_xlfn.XLOOKUP(C22,'DONNÉES BRUTES'!A$3:A$90,'DONNÉES BRUTES'!V$3:V$90),"—") -> -3.14 | I22: =IFERROR(_xlfn.XLOOKUP(C22,'DONNÉES BRUTES'!A$3:A$90,'DONNÉES BRUTES'!N$3:N$90),"—") -> 0.328 | J22: =IFERROR(_xlfn.XLOOKUP(C22,'DONNÉES BRUTES'!A$3:A$90,'DONNÉES BRUTES'!Q$3:Q$90),"—") -> 0.161 | K22: =IFERROR(_xlfn.XLOOKUP(C22,'DONNÉES BRUTES'!A$3:A$90,'DONNÉES BRUTES'!S$3:S$90),"—") -> 1.16 | L22: =IFERROR(_xlfn.XLOOKUP(C22,'DONNÉES BRUTES'!A$3:A$90,'DONNÉES BRUTES'!T$3:T$90),"—") -> -0.2x | M22: =IFERROR(_xlfn.XLOOKUP(C22,'DONNÉES BRUTES'!A$3:A$90,'DONNÉES BRUTES'!AB$3:AB$90),"—") -> 74 | N22: =IFERROR(_xlfn.XLOOKUP(C22,'DONNÉES BRUTES'!A$3:A$90,'DONNÉES BRUTES'!AD$3:AD$90),"—") -> Neutre
B23: 17 | C23: {=IFERROR(INDEX('DONNÉES BRUTES'!A$3:A$90,MATCH(1,('DONNÉES BRUTES'!Z$3:Z$90>=LARGE('DONNÉES BRUTES'!Z$3:Z$90,17))*(COUNTIF(C$6:C22,'DONNÉES BRUTES'!A$3:A$90)=0)*('DONNÉES BRUTES'!A$3:A$90<>""),0)),"—")} -> TTE.PA | D23: =IFERROR(_xlfn.XLOOKUP(C23,'DONNÉES BRUTES'!A$3:A$90,'DONNÉES BRUTES'!B$3:B$90),"—") -> TotalEnergies SE | F23: =IFERROR(_xlfn.XLOOKUP(C23,'DONNÉES BRUTES'!A$3:A$90,'DONNÉES BRUTES'!Z$3:Z$90)&"/100","—") -> 80/100 | G23: =IFERROR(_xlfn.XLOOKUP(C23,'DONNÉES BRUTES'!A$3:A$90,'DONNÉES BRUTES'!U$3:U$90),"—") -> — | H23: =IFERROR(_xlfn.XLOOKUP(C23,'DONNÉES BRUTES'!A$3:A$90,'DONNÉES BRUTES'!V$3:V$90),"—") -> — | I23: =IFERROR(_xlfn.XLOOKUP(C23,'DONNÉES BRUTES'!A$3:A$90,'DONNÉES BRUTES'!N$3:N$90),"—") -> — | J23: =IFERROR(_xlfn.XLOOKUP(C23,'DONNÉES BRUTES'!A$3:A$90,'DONNÉES BRUTES'!Q$3:Q$90),"—") -> — | K23: =IFERROR(_xlfn.XLOOKUP(C23,'DONNÉES BRUTES'!A$3:A$90,'DONNÉES BRUTES'!S$3:S$90),"—") -> 1.10 | L23: =IFERROR(_xlfn.XLOOKUP(C23,'DONNÉES BRUTES'!A$3:A$90,'DONNÉES BRUTES'!T$3:T$90),"—") -> — | M23: =IFERROR(_xlfn.XLOOKUP(C23,'DONNÉES BRUTES'!A$3:A$90,'DONNÉES BRUTES'!AB$3:AB$90),"—") -> 77 | N23: =IFERROR(_xlfn.XLOOKUP(C23,'DONNÉES BRUTES'!A$3:A$90,'DONNÉES BRUTES'!AD$3:AD$90),"—") -> Sous-pondérer
B24: 18 | C24: {=IFERROR(INDEX('DONNÉES BRUTES'!A$3:A$90,MATCH(1,('DONNÉES BRUTES'!Z$3:Z$90>=LARGE('DONNÉES BRUTES'!Z$3:Z$90,18))*(COUNTIF(C$6:C23,'DONNÉES BRUTES'!A$3:A$90)=0)*('DONNÉES BRUTES'!A$3:A$90<>""),0)),"—")} -> EOG | D24: =IFERROR(_xlfn.XLOOKUP(C24,'DONNÉES BRUTES'!A$3:A$90,'DONNÉES BRUTES'!B$3:B$90),"—") -> EOG Resources, Inc. | F24: =IFERROR(_xlfn.XLOOKUP(C24,'DONNÉES BRUTES'!A$3:A$90,'DONNÉES BRUTES'!Z$3:Z$90)&"/100","—") -> 78/100 | G24: =IFERROR(_xlfn.XLOOKUP(C24,'DONNÉES BRUTES'!A$3:A$90,'DONNÉES BRUTES'!U$3:U$90),"—") -> 4.53 | H24: =IFERROR(_xlfn.XLOOKUP(C24,'DONNÉES BRUTES'!A$3:A$90,'DONNÉES BRUTES'!V$3:V$90),"—") -> -3.01 | I24: =IFERROR(_xlfn.XLOOKUP(C24,'DONNÉES BRUTES'!A$3:A$90,'DONNÉES BRUTES'!N$3:N$90),"—") -> 0.49 | J24: =IFERROR(_xlfn.XLOOKUP(C24,'DONNÉES BRUTES'!A$3:A$90,'DONNÉES BRUTES'!Q$3:Q$90),"—") -> 0.167 | K24: =IFERROR(_xlfn.XLOOKUP(C24,'DONNÉES BRUTES'!A$3:A$90,'DONNÉES BRUTES'!S$3:S$90),"—") -> 1.63 | L24: =IFERROR(_xlfn.XLOOKUP(C24,'DONNÉES BRUTES'!A$3:A$90,'DONNÉES BRUTES'!T$3:T$90),"—") -> 0.4x | M24: =IFERROR(_xlfn.XLOOKUP(C24,'DONNÉES BRUTES'!A$3:A$90,'DONNÉES BRUTES'!AB$3:AB$90),"—") -> 44 | N24: =IFERROR(_xlfn.XLOOKUP(C24,'DONNÉES BRUTES'!A$3:A$90,'DONNÉES BRUTES'!AD$3:AD$90),"—") -> Neutre
B25: 19 | C25: {=IFERROR(INDEX('DONNÉES BRUTES'!A$3:A$90,MATCH(1,('DONNÉES BRUTES'!Z$3:Z$90>=LARGE('DONNÉES BRUTES'!Z$3:Z$90,19))*(COUNTIF(C$6:C24,'DONNÉES BRUTES'!A$3:A$90)=0)*('DONNÉES BRUTES'!A$3:A$90<>""),0)),"—")} -> MSI | D25: =IFERROR(_xlfn.XLOOKUP(C25,'DONNÉES BRUTES'!A$3:A$90,'DONNÉES BRUTES'!B$3:B$90),"—") -> Motorola Solutions, Inc. | F25: =IFERROR(_xlfn.XLOOKUP(C25,'DONNÉES BRUTES'!A$3:A$90,'DONNÉES BRUTES'!Z$3:Z$90)&"/100","—") -> 78/100 | G25: =IFERROR(_xlfn.XLOOKUP(C25,'DONNÉES BRUTES'!A$3:A$90,'DONNÉES BRUTES'!U$3:U$90),"—") -> 1.75 | H25: =IFERROR(_xlfn.XLOOKUP(C25,'DONNÉES BRUTES'!A$3:A$90,'DONNÉES BRUTES'!V$3:V$90),"—") -> -2.84 | I25: =IFERROR(_xlfn.XLOOKUP(C25,'DONNÉES BRUTES'!A$3:A$90,'DONNÉES BRUTES'!N$3:N$90),"—") -> 0.308 | J25: =IFERROR(_xlfn.XLOOKUP(C25,'DONNÉES BRUTES'!A$3:A$90,'DONNÉES BRUTES'!Q$3:Q$90),"—") -> 0.894 | K25: =IFERROR(_xlfn.XLOOKUP(C25,'DONNÉES BRUTES'!A$3:A$90,'DONNÉES BRUTES'!S$3:S$90),"—") -> 1.04 | L25: =IFERROR(_xlfn.XLOOKUP(C25,'DONNÉES BRUTES'!A$3:A$90,'DONNÉES BRUTES'!T$3:T$90),"—") -> 2.2x | M25: =IFERROR(_xlfn.XLOOKUP(C25,'DONNÉES BRUTES'!A$3:A$90,'DONNÉES BRUTES'!AB$3:AB$90),"—") -> 77 | N25: =IFERROR(_xlfn.XLOOKUP(C25,'DONNÉES BRUTES'!A$3:A$90,'DONNÉES BRUTES'!AD$3:AD$90),"—") -> Neutre
B26: 20 | C26: {=IFERROR(INDEX('DONNÉES BRUTES'!A$3:A$90,MATCH(1,('DONNÉES BRUTES'!Z$3:Z$90>=LARGE('DONNÉES BRUTES'!Z$3:Z$90,20))*(COUNTIF(C$6:C25,'DONNÉES BRUTES'!A$3:A$90)=0)*('DONNÉES BRUTES'!A$3:A$90<>""),0)),"—")} -> INTU | D26: =IFERROR(_xlfn.XLOOKUP(C26,'DONNÉES BRUTES'!A$3:A$90,'DONNÉES BRUTES'!B$3:B$90),"—") -> Intuit Inc. | F26: =IFERROR(_xlfn.XLOOKUP(C26,'DONNÉES BRUTES'!A$3:A$90,'DONNÉES BRUTES'!Z$3:Z$90)&"/100","—") -> 78/100 | G26: =IFERROR(_xlfn.XLOOKUP(C26,'DONNÉES BRUTES'!A$3:A$90,'DONNÉES BRUTES'!U$3:U$90),"—") -> 4.52 | H26: =IFERROR(_xlfn.XLOOKUP(C26,'DONNÉES BRUTES'!A$3:A$90,'DONNÉES BRUTES'!V$3:V$90),"—") -> -3.05 | I26: =IFERROR(_xlfn.XLOOKUP(C26,'DONNÉES BRUTES'!A$3:A$90,'DONNÉES BRUTES'!N$3:N$90),"—") -> 0.313 | J26: =IFERROR(_xlfn.XLOOKUP(C26,'DONNÉES BRUTES'!A$3:A$90,'DONNÉES BRUTES'!Q$3:Q$90),"—") -> 0.196 | K26: =IFERROR(_xlfn.XLOOKUP(C26,'DONNÉES BRUTES'!A$3:A$90,'DONNÉES BRUTES'!S$3:S$90),"—") -> 1.36 | L26: =IFERROR(_xlfn.XLOOKUP(C26,'DONNÉES BRUTES'!A$3:A$90,'DONNÉES BRUTES'!T$3:T$90),"—") -> 0.5x | M26: =IFERROR(_xlfn.XLOOKUP(C26,'DONNÉES BRUTES'!A$3:A$90,'DONNÉES BRUTES'!AB$3:AB$90),"—") -> 67 | N26: =IFERROR(_xlfn.XLOOKUP(C26,'DONNÉES BRUTES'!A$3:A$90,'DONNÉES BRUTES'!AD$3:AD$90),"—") -> Neutre
B28: FinSight IA · Screening Énergie · Ne constitue pas un conseil en investissement

Sheet MOMENTUM
B1: FinSight IA · Analyse MOMENTUM · Énergie Screening | N1: Ticker | O1: Score | Q1: Ticker | R1: Mom% | T1: Ticker | U1: Mg EBITDA (%) | W1: Score Momentum | X1: Score Global
B2: Usage confidentiel · Calculs FinSight IA · Screening Énergie | N2: SNDK | O2: 100 | Q2: SNDK | R2: 0 | T2: SNDK | U2: -17 | W2: 100 | X2: 34
C3: =COUNTA('DONNÉES BRUTES'!A$3:A$90) -> 88 | G3: =IFERROR(_xlfn.XLOOKUP(LARGE('DONNÉES BRUTES'!AA$3:AA$90,1),'DONNÉES BRUTES'!AA$3:AA$90,'DONNÉES BRUTES'!A$3:A$90),"—") -> APA | K3: =IFERROR(ROUND(AVERAGE('DONNÉES BRUTES'!AA$3:AA$90),0)&"/100","—") -> 43/100 | N3: WDC | O3: 99 | Q3: WDC | R3: 477 | T3: WDC | U3: 20.4 | W3: 99 | X3: 77
C4: Sociétés | G4: #1 Momentum | K4: Moy. Score Momentum | N4: CIEN | O4: 98 | Q4: CIEN | R4: 455 | T4: CIEN | U4: 8.1 | W4: 98 | X4: 59
B5: ANALYSE DÉTAILLÉE · ÉNERGIE · TOP 20 par Momentum · Triée par Score Momentum | N5: TER | O5: 97 | Q5: TER | R5: 292 | T5: TER | U5: 24.7 | W5: 97 | X5: 66
B6: # | C6: Ticker | D6: Société | F6: Score | G6: Mom 52W | H6: Mg EBITDA | I6: Score Global | J6: Score Growth | K6: Next Earn. | L6: Signal | N6: MU | O6: 95 | Q6: MU | R6: 283 | T6: MU | U6: 49.4 | W6: 95 | X6: 78
B7: 1 | C7: {=IFERROR(INDEX('DONNÉES BRUTES'!A$3:A$90,MATCH(1,('DONNÉES BRUTES'!AA$3:AA$90=LARGE('DONNÉES BRUTES'!AA$3:AA$90,1))*(COUNTIF(C$6:C6,'DONNÉES BRUTES'!A$3:A$90)=0)*('DONNÉES BRUTES'!A$3:A$90<>""),0)),"—")} -> APA | D7: =IFERROR(_xlfn.XLOOKUP(C7,'DONNÉES BRUTES'!A$3:A$90,'DONNÉES BRUTES'!B$3:B$90),"—") -> APA Corporation | F7: =IFERROR(_xlfn.XLOOKUP(C7,'DONNÉES BRUTES'!A$3:A$90,'DONNÉES BRUTES'!AA$3:AA$90)&"/100","—") -> 100/100 | G7: =IFERROR(_xlfn.XLOOKUP(C7,'DONNÉES BRUTES'!A$3:A$90,'DONNÉES BRUTES'!W$3:W$90),"—") -> +129.6% | H7: =IFERROR(_xlfn.XLOOKUP(C7,'DONNÉES BRUTES'!A$3:A$90,'DONNÉES BRUTES'!N$3:N$90),"—") -> 0.602 | I7: =IFERROR(_xlfn.XLOOKUP(C7,'DONNÉES BRUTES'!A$3:A$90,'DONNÉES BRUTES'!AB$3:AB$90),"—") -> 77 | J7: =IFERROR(_xlfn.XLOOKUP(C7,'DONNÉES BRUTES'!A$3:A$90,'DONNÉES BRUTES'!Y$3:Y$90),"—") -> 62 | K7: =IFERROR(_xlfn.XLOOKUP(C7,'DONNÉES BRUTES'!A$3:A$90,'DONNÉES BRUTES'!AC$3:AC$90),"—") -> 2026-05-06 | L7: =IFERROR(_xlfn.XLOOKUP(C7,'DONNÉES BRUTES'!A$3:A$90,'DONNÉES BRUTES'!AD$3:AD$90),"—") -> Surpondérer | N7: STX | O7: 94 | Q7: STX | R7: 264 | T7: STX | U7: 22.9 | W7: 94 | X7: 73
B8: 2 | C8: {=IFERROR(INDEX('DONNÉES BRUTES'!A$3:A$90,MATCH(1,('DONNÉES BRUTES'!AA$3:AA$90>=LARGE('DONNÉES BRUTES'!AA$3:AA$90,2))*(COUNTIF(C$6:C7,'DONNÉES BRUTES'!A$3:A$90)=0)*('DONNÉES BRUTES'!A$3:A$90<>""),0)),"—")} -> SNDK | D8: =IFERROR(_xlfn.XLOOKUP(C8,'DONNÉES BRUTES'!A$3:A$90,'DONNÉES BRUTES'!B$3:B$90),"—") -> Sandisk Corporation | F8: =IFERROR(_xlfn.XLOOKUP(C8,'DONNÉES BRUTES'!A$3:A$90,'DONNÉES BRUTES'!AA$3:AA$90)&"/100","—") -> 100/100 | G8: =IFERROR(_xlfn.XLOOKUP(C8,'DONNÉES BRUTES'!A$3:A$90,'DONNÉES BRUTES'!W$3:W$90),"—") -> — | H8: =IFERROR(_xlfn.XLOOKUP(C8,'DONNÉES BRUTES'!A$3:A$90,'DONNÉES BRUTES'!N$3:N$90),"—") -> -0.17 | I8: =IFERROR(_xlfn.XLOOKUP(C8,'DONNÉES BRUTES'!A$3:A$90,'DONNÉES BRUTES'!AB$3:AB$90),"—") -> 40 | J8: =IFERROR(_xlfn.XLOOKUP(C8,'DONNÉES BRUTES'!A$3:A$90,'DONNÉES BRUTES'!Y$3:Y$90),"—") -> 1 | K8: =IFERROR(_xlfn.XLOOKUP(C8,'DONNÉES BRUTES'!A$3:A$90,'DONNÉES BRUTES'!AC$3:AC$90),"—") -> — | L8: =IFERROR(_xlfn.XLOOKUP(C8,'DONNÉES BRUTES'!A$3:A$90,'DONNÉES BRUTES'!AD$3:AD$90),"—") -> Sous-pondérer | N8: GLW | O8: 93 | Q8: GLW | R8: 199 | T8: GLW | U8: 23.9 | W8: 93 | X8: 68
B9: 3 | C9: {=IFERROR(INDEX('DONNÉES BRUTES'!A$3:A$90,MATCH(1,('DONNÉES BRUTES'!AA$3:AA$90>=LARGE('DONNÉES BRUTES'!AA$3:AA$90,3))*(COUNTIF(C$6:C8,'DONNÉES BRUTES'!A$3:A$90)=0)*('DONNÉES BRUTES'!A$3:A$90<>""),0)),"—")} -> CIEN | D9: =IFERROR(_xlfn.XLOOKUP(C9,'DONNÉES BRUTES'!A$3:A$90,'DONNÉES BRUTES'!B$3:B$90),"—") -> Ciena Corporation | F9: =IFERROR(_xlfn.XLOOKUP(C9,'DONNÉES BRUTES'!A$3:A$90,'DONNÉES BRUTES'!AA$3:AA$90)&"/100","—") -> 98/100 | G9: =IFERROR(_xlfn.XLOOKUP(C9,'DONNÉES BRUTES'!A$3:A$90,'DONNÉES BRUTES'!W$3:W$90),"—") -> +454.6% | H9: =IFERROR(_xlfn.XLOOKUP(C9,'DONNÉES BRUTES'!A$3:A$90,'DONNÉES BRUTES'!N$3:N$90),"—") -> 0.081 | I9: =IFERROR(_xlfn.XLOOKUP(C9,'DONNÉES BRUTES'!A$3:A$90,'DONNÉES BRUTES'!AB$3:AB$90),"—") -> 73 | J9: =IFERROR(_xlfn.XLOOKUP(C9,'DONNÉES BRUTES'!A$3:A$90,'DONNÉES BRUTES'!Y$3:Y$90),"—") -> 59 | K9: =IFERROR(_xlfn.XLOOKUP(C9,'DONNÉES BRUTES'!A$3:A$90,'DONNÉES BRUTES'!AC$3:AC$90),"—") -> 2026-06-04 | L9: =IFERROR(_xlfn.XLOOKUP(C9,'DONNÉES BRUTES'!A$3:A$90,'DONNÉES BRUTES'!AD$3:AD$90),"—") -> Neutre | N9: LRCX | O9: 92 | Q9: LRCX | R9: 172 | T9: LRCX | U9: 35.4 | W9: 92 | X9: 77
B10: 4 | C10: {=IFERROR(INDEX('DONNÉES BRUTES'!A$3:A$90,MATCH(1,('DONNÉES BRUTES'!AA$3:AA$90>=LARGE('DONNÉES BRUTES'!AA$3:AA$90,4))*(COUNTIF(C$6:C9,'DONNÉES BRUTES'!A$3:A$90)=0)*('DONNÉES BRUTES'!A$3:A$90<>""),0)),"—")} -> HAL | D10: =IFERROR(_xlfn.XLOOKUP(C10,'DONNÉES BRUTES'!A$3:A$90,'DONNÉES BRUTES'!B$3:B$90),"—") -> Halliburton Company | F10: =IFERROR(_xlfn.XLOOKUP(C10,'DONNÉES BRUTES'!A$3:A$90,'DONNÉES BRUTES'!AA$3:AA$90)&"/100","—") -> 96/100 | G10: =IFERROR(_xlfn.XLOOKUP(C10,'DONNÉES BRUTES'!A$3:A$90,'DONNÉES BRUTES'!W$3:W$90),"—") -> +99.5% | H10: =IFERROR(_xlfn.XLOOKUP(C10,'DONNÉES BRUTES'!A$3:A$90,'DONNÉES BRUTES'!N$3:N$90),"—") -> 0.147 | I10: =IFERROR(_xlfn.XLOOKUP(C10,'DONNÉES BRUTES'!A$3:A$90,'DONNÉES BRUTES'!AB$3:AB$90),"—") -> 50 | J10: =IFERROR(_xlfn.XLOOKUP(C10,'DONNÉES BRUTES'!A$3:A$90,'DONNÉES BRUTES'!Y$3:Y$90),"—") -> 0 | K10: =IFERROR(_xlfn.XLOOKUP(C10,'DONNÉES BRUTES'!A$3:A$90,'DONNÉES BRUTES'!AC$3:AC$90),"—") -> 2026-04-21 | L10: =IFERROR(_xlfn.XLOOKUP(C10,'DONNÉES BRUTES'!A$3:A$90,'DONNÉES BRUTES'!AD$3:AD$90),"—") -> Sous-pondérer | N10: INTC | O10: 91 | Q10: INTC | R10: 152 | T10: INTC | U10: 27.2 | W10: 91 | X10: 67
B11: 5 | C11: {=IFERROR(INDEX('DONNÉES BRUTES'!A$3:A$90,MATCH(1,('DONNÉES BRUTES'!AA$3:AA$90>=LARGE('DONNÉES BRUTES'!AA$3:AA$90,5))*(COUNTIF(C$6:C10,'DONNÉES BRUTES'!A$3:A$90)=0)*('DONNÉES BRUTES'!A$3:A$90<>""),0)),"—")} -> VLO | D11: =IFERROR(_xlfn.XLOOKUP(C11,'DONNÉES BRUTES'!A$3:A$90,'DONNÉES BRUTES'!B$3:B$90),"—") -> Valero Energy Corporation | F11: =IFERROR(_xlfn.XLOOKUP(C11,'DONNÉES BRUTES'!A$3:A$90,'DONNÉES BRUTES'!AA$3:AA$90)&"/100","—") -> 92/100 | G11: =IFERROR(_xlfn.XLOOKUP(C11,'DONNÉES BRUTES'!A$3:A$90,'DONNÉES BRUTES'!W$3:W$90),"—") -> +92.9% | H11: =IFERROR(_xlfn.XLOOKUP(C11,'DONNÉES BRUTES'!A$3:A$90,'DONNÉES BRUTES'!N$3:N$90),"—") -> 0.055 | I11: =IFERROR(_xlfn.XLOOKUP(C11,'DONNÉES BRUTES'!A$3:A$90,'DONNÉES BRUTES'!AB$3:AB$90),"—") -> 55 | J11: =IFERROR(_xlfn.XLOOKUP(C11,'DONNÉES BRUTES'!A$3:A$90,'DONNÉES BRUTES'!Y$3:Y$90),"—") -> 25 | K11: =IFERROR(_xlfn.XLOOKUP(C11,'DONNÉES BRUTES'!A$3:A$90,'DONNÉES BRUTES'!AC$3:AC$90),"—") -> 2026-04-30 | L11: =IFERROR(_xlfn.XLOOKUP(C11,'DONNÉES BRUTES'!A$3:A$90,'DONNÉES BRUTES'!AD$3:AD$90),"—") -> Sous-pondérer | N11: AMAT | O11: 90 | Q11: AMAT | R11: 125 | T11: AMAT | U11: 35.2 | W11: 90 | X11: 60
B12: 6 | C12: {=IFERROR(INDEX('DONNÉES BRUTES'!A$3:A$90,MATCH(1,('DONNÉES BRUTES'!AA$3:AA$90>=LARGE('DONNÉES BRUTES'!AA$3:AA$90,6))*(COUNTIF(C$6:C11,'DONNÉES BRUTES'!A$3:A$90)=0)*('DONNÉES BRUTES'!A$3:A$90<>""),0)),"—")} -> AMAT | D12: =IFERROR(_xlfn.XLOOKUP(C12,'DONNÉES BRUTES'!A$3:A$90,'DONNÉES BRUTES'!B$3:B$90),"—") -> Applied Materials, Inc. | F12: =IFERROR(_xlfn.XLOOKUP(C12,'DONNÉES BRUTES'!A$3:A$90,'DONNÉES BRUTES'!AA$3:AA$90)&"/100","—") -> 90/100 | G12: =IFERROR(_xlfn.XLOOKUP(C12,'DONNÉES BRUTES'!A$3:A$90,'DONNÉES BRUTES'!W$3:W$90),"—") -> +124.8% | H12: =IFERROR(_xlfn.XLOOKUP(C12,'DONNÉES BRUTES'!A$3:A$90,'DONNÉES BRUTES'!N$3:N$90),"—") -> 0.352 | I12: =IFERROR(_xlfn.XLOOKUP(C12,'DONNÉES BRUTES'!A$3:A$90,'DONNÉES BRUTES'!AB$3:AB$90),"—") -> 77 | J12: =IFERROR(_xlfn.XLOOKUP(C12,'DONNÉES BRUTES'!A$3:A$90,'DONNÉES BRUTES'!Y$3:Y$90),"—") -> 38 | K12: =IFERROR(_xlfn.XLOOKUP(C12,'DONNÉES BRUTES'!A$3:A$90,'DONNÉES BRUTES'!AC$3:AC$90),"—") -> 2026-05-14 | L12: =IFERROR(_xlfn.XLOOKUP(C12,'DONNÉES BRUTES'!A$3:A$90,'DONNÉES BRUTES'!AD$3:AD$90),"—") -> Neutre | N12: KLAC | O12: 88 | Q12: KLAC | R12: 102 | T12: KLAC | U12: 43.9 | W12: 88 | X12: 84
B13: 7 | C13: {=IFERROR(INDEX('DONNÉES BRUTES'!A$3:A$90,MATCH(1,('DONNÉES BRUTES'!AA$3:AA$90>=LARGE('DONNÉES BRUTES'!AA$3:AA$90,7))*(COUNTIF(C$6:C12,'DONNÉES BRUTES'!A$3:A$90)=0)*('DONNÉES BRUTES'!A$3:A$90<>""),0)),"—")} -> ENI.MI | D13: =IFERROR(_xlfn.XLOOKUP(C13,'DONNÉES BRUTES'!A$3:A$90,'DONNÉES BRUTES'!B$3:B$90),"—") -> Eni S.p.A. | F13: =IFERROR(_xlfn.XLOOKUP(C13,'DONNÉES BRUTES'!A$3:A$90,'DONNÉES BRUTES'!AA$3:AA$90)&"/100","—") -> 88/100 | G13: =IFERROR(_xlfn.XLOOKUP(C13,'DONNÉES BRUTES'!A$3:A$90,'DONNÉES BRUTES'!W$3:W$90),"—") -> +92.3% | H13: =IFERROR(_xlfn.XLOOKUP(C13,'DONNÉES BRUTES'!A$3:A$90,'DONNÉES BRUTES'!N$3:N$90),"—") -> — | I13: =IFERROR(_xlfn.XLOOKUP(C13,'DONNÉES BRUTES'!A$3:A$90,'DONNÉES BRUTES'!AB$3:AB$90),"—") -> 79 | J13: =IFERROR(_xlfn.XLOOKUP(C13,'DONNÉES BRUTES'!A$3:A$90,'DONNÉES BRUTES'!Y$3:Y$90),"—") -> — | K13: =IFERROR(_xlfn.XLOOKUP(C13,'DONNÉES BRUTES'!A$3:A$90,'DONNÉES BRUTES'!AC$3:AC$90),"—") -> 2026-04-24 | L13: =IFERROR(_xlfn.XLOOKUP(C13,'DONNÉES BRUTES'!A$3:A$90,'DONNÉES BRUTES'!AD$3:AD$90),"—") -> Neutre | N13: AMD | O13: 87 | Q13: AMD | R13: 93 | T13: AMD | U13: 21 | W13: 87 | X13: 73
B14: 8 | C14: {=IFERROR(INDEX('DONNÉES BRUTES'!A$3:A$90,MATCH(1,('DONNÉES BRUTES'!AA$3:AA$90>=LARGE('DONNÉES BRUTES'!AA$3:AA$90,8))*(COUNTIF(C$6:C13,'DONNÉES BRUTES'!A$3:A$90)=0)*('DONNÉES BRUTES'!A$3:A$90<>""),0)),"—")} -> BKR | D14: =IFERROR(_xlfn.XLOOKUP(C14,'DONNÉES BRUTES'!A$3:A$90,'DONNÉES BRUTES'!B$3:B$90),"—") -> Baker Hughes Company | F14: =IFERROR(_xlfn.XLOOKUP(C14,'DONNÉES BRUTES'!A$3:A$90,'DONNÉES BRUTES'!AA$3:AA$90)&"/100","—") -> 85/100 | G14: =IFERROR(_xlfn.XLOOKUP(C14,'DONNÉES BRUTES'!A$3:A$90,'DONNÉES BRUTES'!W$3:W$90),"—") -> +66.8% | H14: =IFERROR(_xlfn.XLOOKUP(C14,'DONNÉES BRUTES'!A$3:A$90,'DONNÉES BRUTES'!N$3:N$90),"—") -> 0.155 | I14: =IFERROR(_xlfn.XLOOKUP(C14,'DONNÉES BRUTES'!A$3:A$90,'DONNÉES BRUTES'!AB$3:AB$90),"—") -> 57 | J14: =IFERROR(_xlfn.XLOOKUP(C14,'DONNÉES BRUTES'!A$3:A$90,'DONNÉES BRUTES'!Y$3:Y$90),"—") -> 33 | K14: =IFERROR(_xlfn.XLOOKUP(C14,'DONNÉES BRUTES'!A$3:A$90,'DONNÉES BRUTES'!AC$3:AC$90),"—") -> 2026-04-23 | L14: =IFERROR(_xlfn.XLOOKUP(C14,'DONNÉES BRUTES'!A$3:A$90,'DONNÉES BRUTES'!AD$3:AD$90),"—") -> Neutre | N14: KEYS | O14: 86 | Q14: KEYS | R14: 85 | T14: KEYS | U14: 27.1 | W14: 86 | X14: 67
B15: 9 | C15: {=IFERROR(INDEX('DONNÉES BRUTES'!A$3:A$90,MATCH(1,('DONNÉES BRUTES'!AA$3:AA$90>=LARGE('DONNÉES BRUTES'!AA$3:AA$90,9))*(COUNTIF(C$6:C14,'DONNÉES BRUTES'!A$3:A$90)=0)*('DONNÉES BRUTES'!A$3:A$90<>""),0)),"—")} -> NOKIA.HE | D15: =IFERROR(_xlfn.XLOOKUP(C15,'DONNÉES BRUTES'!A$3:A$90,'DONNÉES BRUTES'!B$3:B$90),"—") -> Nokia Oyj | F15: =IFERROR(_xlfn.XLOOKUP(C15,'DONNÉES BRUTES'!A$3:A$90,'DONNÉES BRUTES'!AA$3:AA$90)&"/100","—") -> 83/100 | G15: =IFERROR(_xlfn.XLOOKUP(C15,'DONNÉES BRUTES'!A$3:A$90,'DONNÉES BRUTES'!W$3:W$90),"—") -> — | H15: =IFERROR(_xlfn.XLOOKUP(C15,'DONNÉES BRUTES'!A$3:A$90,'DONNÉES BRUTES'!N$3:N$90),"—") -> 0.113 | I15: =IFERROR(_xlfn.XLOOKUP(C15,'DONNÉES BRUTES'!A$3:A$90,'DONNÉES BRUTES'!AB$3:AB$90),"—") -> 49 | J15: =IFERROR(_xlfn.XLOOKUP(C15,'DONNÉES BRUTES'!A$3:A$90,'DONNÉES BRUTES'!Y$3:Y$90),"—") -> 9 | K15: =IFERROR(_xlfn.XLOOKUP(C15,'DONNÉES BRUTES'!A$3:A$90,'DONNÉES BRUTES'!AC$3:AC$90),"—") -> — | L15: =IFERROR(_xlfn.XLOOKUP(C15,'DONNÉES BRUTES'!A$3:A$90,'DONNÉES BRUTES'!AD$3:AD$90),"—") -> Sous-pondérer | N15: ASML | O15: 85 | Q15: ASML | R15: 79 | T15: ASML | U15: 38.4 | W15: 85 | X15: 72
B16: 10 | C16: {=IFERROR(INDEX('DONNÉES BRUTES'!A$3:A$90,MATCH(1,('DONNÉES BRUTES'!AA$3:AA$90>=LARGE('DONNÉES BRUTES'!AA$3:AA$90,10))*(COUNTIF(C$6:C15,'DONNÉES BRUTES'!A$3:A$90)=0)*('DONNÉES BRUTES'!A$3:A$90<>""),0)),"—")} -> BP.L | D16: =IFERROR(_xlfn.XLOOKUP(C16,'DONNÉES BRUTES'!A$3:A$90,'DONNÉES BRUTES'!B$3:B$90),"—") -> BP p.l.c. | F16: =IFERROR(_xlfn.XLOOKUP(C16,'DONNÉES BRUTES'!A$3:A$90,'DONNÉES BRUTES'!AA$3:AA$90)&"/100","—") -> 81/100 | G16: =IFERROR(_xlfn.XLOOKUP(C16,'DONNÉES BRUTES'!A$3:A$90,'DONNÉES BRUTES'!W$3:W$90),"—") -> +62.4% | H16: =IFERROR(_xlfn.XLOOKUP(C16,'DONNÉES BRUTES'!A$3:A$90,'DONNÉES BRUTES'!N$3:N$90),"—") -> 0.162 | I16: =IFERROR(_xlfn.XLOOKUP(C16,'DONNÉES BRUTES'!A$3:A$90,'DONNÉES BRUTES'!AB$3:AB$90),"—") -> 47 | J16: =IFERROR(_xlfn.XLOOKUP(C16,'DONNÉES BRUTES'!A$3:A$90,'DONNÉES BRUTES'!Y$3:Y$90),"—") -> 46 | K16: =IFERROR(_xlfn.XLOOKUP(C16,'DONNÉES BRUTES'!A$3:A$90,'DONNÉES BRUTES'!AC$3:AC$90),"—") -> 2026-04-28 | L16: =IFERROR(_xlfn.XLOOKUP(C16,'DONNÉES BRUTES'!A$3:A$90,'DONNÉES BRUTES'!AD$3:AD$90),"—") -> Sous-pondérer | N16: MPWR | O16: 84 | Q16: MPWR | R16: 69 | T16: MPWR | U16: 28 | W16: 84 | X16: 78
B17: 11 | C17: {=IFERROR(INDEX('DONNÉES BRUTES'!A$3:A$90,MATCH(1,('DONNÉES BRUTES'!AA$3:AA$90>=LARGE('DONNÉES BRUTES'!AA$3:AA$90,11))*(COUNTIF(C$6:C16,'DONNÉES BRUTES'!A$3:A$90)=0)*('DONNÉES BRUTES'!A$3:A$90<>""),0)),"—")} -> JBL | D17: =IFERROR(_xlfn.XLOOKUP(C17,'DONNÉES BRUTES'!A$3:A$90,'DONNÉES BRUTES'!B$3:B$90),"—") -> Jabil Inc. | F17: =IFERROR(_xlfn.XLOOKUP(C17,'DONNÉES BRUTES'!A$3:A$90,'DONNÉES BRUTES'!AA$3:AA$90)&"/100","—") -> 81/100 | G17: =IFERROR(_xlfn.XLOOKUP(C17,'DONNÉES BRUTES'!A$3:A$90,'DONNÉES BRUTES'!W$3:W$90),"—") -> — | H17: =IFERROR(_xlfn.XLOOKUP(C17,'DONNÉES BRUTES'!A$3:A$90,'DONNÉES BRUTES'!N$3:N$90),"—") -> 0.057 | I17: =IFERROR(_xlfn.XLOOKUP(C17,'DONNÉES BRUTES'!A$3:A$90,'DONNÉES BRUTES'!AB$3:AB$90),"—") -> 43 | J17: =IFERROR(_xlfn.XLOOKUP(C17,'DONNÉES BRUTES'!A$3:A$90,'DONNÉES BRUTES'!Y$3:Y$90),"—") -> 8 | K17: =IFERROR(_xlfn.XLOOKUP(C17,'DONNÉES BRUTES'!A$3:A$90,'DONNÉES BRUTES'!AC$3:AC$90),"—") -> — | L17: =IFERROR(_xlfn.XLOOKUP(C17,'DONNÉES BRUTES'!A$3:A$90,'DONNÉES BRUTES'!AD$3:AD$90),"—") -> Sous-pondérer | N17: NOKIA | O17: 83 | Q17: NOKIA | R17: 0 | T17: NOKIA.HE | U17: 11.3 | W17: 83 | X17: 39
B18: 12 | C18: {=IFERROR(INDEX('DONNÉES BRUTES'!A$3:A$90,MATCH(1,('DONNÉES BRUTES'!AA$3:AA$90>=LARGE('DONNÉES BRUTES'!AA$3:AA$90,12))*(COUNTIF(C$6:C17,'DONNÉES BRUTES'!A$3:A$90)=0)*('DONNÉES BRUTES'!A$3:A$90<>""),0)),"—")} -> AKAM | D18: =IFERROR(_xlfn.XLOOKUP(C18,'DONNÉES BRUTES'!A$3:A$90,'DONNÉES BRUTES'!B$3:B$90),"—") -> Akamai Technologies, Inc. | F18: =IFERROR(_xlfn.XLOOKUP(C18,'DONNÉES BRUTES'!A$3:A$90,'DONNÉES BRUTES'!AA$3:AA$90)&"/100","—") -> 79/100 | G18: =IFERROR(_xlfn.XLOOKUP(C18,'DONNÉES BRUTES'!A$3:A$90,'DONNÉES BRUTES'!W$3:W$90),"—") -> — | H18: =IFERROR(_xlfn.XLOOKUP(C18,'DONNÉES BRUTES'!A$3:A$90,'DONNÉES BRUTES'!N$3:N$90),"—") -> 0.319 | I18: =IFERROR(_xlfn.XLOOKUP(C18,'DONNÉES BRUTES'!A$3:A$90,'DONNÉES BRUTES'!AB$3:AB$90),"—") -> 57 | J18: =IFERROR(_xlfn.XLOOKUP(C18,'DONNÉES BRUTES'!A$3:A$90,'DONNÉES BRUTES'!Y$3:Y$90),"—") -> 30 | K18: =IFERROR(_xlfn.XLOOKUP(C18,'DONNÉES BRUTES'!A$3:A$90,'DONNÉES BRUTES'!AC$3:AC$90),"—") -> — | L18: =IFERROR(_xlfn.XLOOKUP(C18,'DONNÉES BRUTES'!A$3:A$90,'DONNÉES BRUTES'!AD$3:AD$90),"—") -> Sous-pondérer | N18: JBL | O18: 81 | Q18: JBL | R18: 0 | T18: JBL | U18: 5.7 | W18: 81 | X18: 31
B19: 13 | C19: {=IFERROR(INDEX('DONNÉES BRUTES'!A$3:A$90,MATCH(1,('DONNÉES BRUTES'!AA$3:AA$90>=LARGE('DONNÉES BRUTES'!AA$3:AA$90,13))*(COUNTIF(C$6:C18,'DONNÉES BRUTES'!A$3:A$90)=0)*('DONNÉES BRUTES'!A$3:A$90<>""),0)),"—")} -> SLB | D19: =IFERROR(_xlfn.XLOOKUP(C19,'DONNÉES BRUTES'!A$3:A$90,'DONNÉES BRUTES'!B$3:B$90),"—") -> SLB N.V. | F19: =IFERROR(_xlfn.XLOOKUP(C19,'DONNÉES BRUTES'!A$3:A$90,'DONNÉES BRUTES'!AA$3:AA$90)&"/100","—") -> 77/100 | G19: =IFERROR(_xlfn.XLOOKUP(C19,'DONNÉES BRUTES'!A$3:A$90,'DONNÉES BRUTES'!W$3:W$90),"—") -> +61.7% | H19: =IFERROR(_xlfn.XLOOKUP(C19,'DONNÉES BRUTES'!A$3:A$90,'DONNÉES BRUTES'!N$3:N$90),"—") -> 0.195 | I19: =IFERROR(_xlfn.XLOOKUP(C19,'DONNÉES BRUTES'!A$3:A$90,'DONNÉES BRUTES'!AB$3:AB$90),"—") -> 47 | J19: =IFERROR(_xlfn.XLOOKUP(C19,'DONNÉES BRUTES'!A$3:A$90,'DONNÉES BRUTES'!Y$3:Y$90),"—") -> 4 | K19: =IFERROR(_xlfn.XLOOKUP(C19,'DONNÉES BRUTES'!A$3:A$90,'DONNÉES BRUTES'!AC$3:AC$90),"—") -> 2026-05-01 | L19: =IFERROR(_xlfn.XLOOKUP(C19,'DONNÉES BRUTES'!A$3:A$90,'DONNÉES BRUTES'!AD$3:AD$90),"—") -> Sous-pondérer | N19: AKAM | O19: 79 | Q19: AKAM | R19: 0 | T19: AKAM | U19: 31.9 | W19: 79 | X19: 52
B20: 14 | C20: {=IFERROR(INDEX('DONNÉES BRUTES'!A$3:A$90,MATCH(1,('DONNÉES BRUTES'!AA$3:AA$90>=LARGE('DONNÉES BRUTES'!AA$3:AA$90,14))*(COUNTIF(C$6:C19,'DONNÉES BRUTES'!A$3:A$90)=0)*('DONNÉES BRUTES'!A$3:A$90<>""),0)),"—")} -> ON | D20: =IFERROR(_xlfn.XLOOKUP(C20,'DONNÉES BRUTES'!A$3:A$90,'DONNÉES BRUTES'!B$3:B$90),"—") -> ON Semiconductor Corporation | F20: =IFERROR(_xlfn.XLOOKUP(C20,'DONNÉES BRUTES'!A$3:A$90,'DONNÉES BRUTES'!AA$3:AA$90)&"/100","—") -> 77/100 | G20: =IFERROR(_xlfn.XLOOKUP(C20,'DONNÉES BRUTES'!A$3:A$90,'DONNÉES BRUTES'!W$3:W$90),"—") -> — | H20: =IFERROR(_xlfn.XLOOKUP(C20,'DONNÉES BRUTES'!A$3:A$90,'DONNÉES BRUTES'!N$3:N$90),"—") -> 0.148 | I20: =IFERROR(_xlfn.XLOOKUP(C20,'DONNÉES BRUTES'!A$3:A$90,'DONNÉES BRUTES'!AB$3:AB$90),"—") -> 45 | J20: =IFERROR(_xlfn.XLOOKUP(C20,'DONNÉES BRUTES'!A$3:A$90,'DONNÉES BRUTES'!Y$3:Y$90),"—") -> 3 | K20: =IFERROR(_xlfn.XLOOKUP(C20,'DONNÉES BRUTES'!A$3:A$90,'DONNÉES BRUTES'!AC$3:AC$90),"—") -> — | L20: =IFERROR(_xlfn.XLOOKUP(C20,'DONNÉES BRUTES'!A$3:A$90,'DONNÉES BRUTES'!AD$3:AD$90),"—") -> Sous-pondérer | N20: ADI | O20: 78 | Q20: ADI | R20: 50 | T20: ADI | U20: 45.6 | W20: 78 | X20: 71
B21: 15 | C21: {=IFERROR(INDEX('DONNÉES BRUTES'!A$3:A$90,MATCH(1,('DONNÉES BRUTES'!AA$3:AA$90>=LARGE('DONNÉES BRUTES'!AA$3:AA$90,15))*(COUNTIF(C$6:C20,'DONNÉES BRUTES'!A$3:A$90)=0)*('DONNÉES BRUTES'!A$3:A$90<>""),0)),"—")} -> HPE | D21: =IFERROR(_xlfn.XLOOKUP(C21,'DONNÉES BRUTES'!A$3:A$90,'DONNÉES BRUTES'!B$3:B$90),"—") -> Hewlett Packard Enterprise Company | F21: =IFERROR(_xlfn.XLOOKUP(C21,'DONNÉES BRUTES'!A$3:A$90,'DONNÉES BRUTES'!AA$3:AA$90)&"/100","—") -> 74/100 | G21: =IFERROR(_xlfn.XLOOKUP(C21,'DONNÉES BRUTES'!A$3:A$90,'DONNÉES BRUTES'!W$3:W$90),"—") -> — | H21: =IFERROR(_xlfn.XLOOKUP(C21,'DONNÉES BRUTES'!A$3:A$90,'DONNÉES BRUTES'!N$3:N$90),"—") -> 0.128 | I21: =IFERROR(_xlfn.XLOOKUP(C21,'DONNÉES BRUTES'!A$3:A$90,'DONNÉES BRUTES'!AB$3:AB$90),"—") -> 48 | J21: =IFERROR(_xlfn.XLOOKUP(C21,'DONNÉES BRUTES'!A$3:A$90,'DONNÉES BRUTES'!Y$3:Y$90),"—") -> 20 | K21: =IFERROR(_xlfn.XLOOKUP(C21,'DONNÉES BRUTES'!A$3:A$90,'DONNÉES BRUTES'!AC$3:AC$90),"—") -> — | L21: =IFERROR(_xlfn.XLOOKUP(C21,'DONNÉES BRUTES'!A$3:A$90,'DONNÉES BRUTES'!AD$3:AD$90),"—") -> Sous-pondérer | N21: ON | O21: 77 | Q21: ON | R21: 0 | T21: ON | U21: 14.8 | W21: 77 | X21: 32
B22: 16 | C22: {=IFERROR(INDEX('DONNÉES BRUTES'!A$3:A$90,MATCH(1,('DONNÉES BRUTES'!AA$3:AA$90>=LARGE('DONNÉES BRUTES'!AA$3:AA$90,16))*(COUNTIF(C$6:C21,'DONNÉES BRUTES'!A$3:A$90)=0)*('DONNÉES BRUTES'!A$3:A$90<>""),0)),"—")} -> TTE.PA | D22: =IFERROR(_xlfn.XLOOKUP(C22,'DONNÉES BRUTES'!A$3:A$90,'DONNÉES BRUTES'!B$3:B$90),"—") -> TotalEnergies SE | F22: =IFERROR(_xlfn.XLOOKUP(C22,'DONNÉES BRUTES'!A$3:A$90,'DONNÉES BRUTES'!AA$3:AA$90)&"/100","—") -> 73/100 | G22: =IFERROR(_xlfn.XLOOKUP(C22,'DONNÉES BRUTES'!A$3:A$90,'DONNÉES BRUTES'!W$3:W$90),"—") -> +58.2% | H22: =IFERROR(_xlfn.XLOOKUP(C22,'DONNÉES BRUTES'!A$3:A$90,'DONNÉES BRUTES'!N$3:N$90),"—") -> — | I22: =IFERROR(_xlfn.XLOOKUP(C22,'DONNÉES BRUTES'!A$3:A$90,'DONNÉES BRUTES'!AB$3:AB$90),"—") -> 77 | J22: =IFERROR(_xlfn.XLOOKUP(C22,'DONNÉES BRUTES'!A$3:A$90,'DONNÉES BRUTES'!Y$3:Y$90),"—") -> — | K22: =IFERROR(_xlfn.XLOOKUP(C22,'DONNÉES BRUTES'!A$3:A$90,'DONNÉES BRUTES'!AC$3:AC$90),"—") -> 2026-04-29 | L22: =IFERROR(_xlfn.XLOOKUP(C22,'DONNÉES BRUTES'!A$3:A$90,'DONNÉES BRUTES'!AD$3:AD$90),"—") -> Sous-pondérer
B23: 17 | C23: {=IFERROR(INDEX('DONNÉES BRUTES'!A$3:A$90,MATCH(1,('DONNÉES BRUTES'!AA$3:AA$90>=LARGE('DONNÉES BRUTES'!AA$3:AA$90,17))*(COUNTIF(C$6:C22,'DONNÉES BRUTES'!A$3:A$90)=0)*('DONNÉES BRUTES'!A$3:A$90<>""),0)),"—")} -> STMPA.PA | D23: =IFERROR(_xlfn.XLOOKUP(C23,'DONNÉES BRUTES'!A$3:A$90,'DONNÉES BRUTES'!B$3:B$90),"—") -> STMicroelectronics N.V. | F23: =IFERROR(_xlfn.XLOOKUP(C23,'DONNÉES BRUTES'!A$3:A$90,'DONNÉES BRUTES'!AA$3:AA$90)&"/100","—") -> 72/100 | G23: =IFERROR(_xlfn.XLOOKUP(C23,'DONNÉES BRUTES'!A$3:A$90,'DONNÉES BRUTES'!W$3:W$90),"—") -> — | H23: =IFERROR(_xlfn.XLOOKUP(C23,'DONNÉES BRUTES'!A$3:A$90,'DONNÉES BRUTES'!N$3:N$90),"—") -> 0.196 | I23: =IFERROR(_xlfn.XLOOKUP(C23,'DONNÉES BRUTES'!A$3:A$90,'DONNÉES BRUTES'!AB$3:AB$90),"—") -> 49 | J23: =IFERROR(_xlfn.XLOOKUP(C23,'DONNÉES BRUTES'!A$3:A$90,'DONNÉES BRUTES'!Y$3:Y$90),"—") -> 7 | K23: =IFERROR(_xlfn.XLOOKUP(C23,'DONNÉES BRUTES'!A$3:A$90,'DONNÉES BRUTES'!AC$3:AC$90),"—") -> — | L23: =IFERROR(_xlfn.XLOOKUP(C23,'DONNÉES BRUTES'!A$3:A$90,'DONNÉES BRUTES'!AD$3:AD$90),"—") -> Sous-pondérer
B24: 18 | C24: {=IFERROR(INDEX('DONNÉES BRUTES'!A$3:A$90,MATCH(1,('DONNÉES BRUTES'!AA$3:AA$90>=LARGE('DONNÉES BRUTES'!AA$3:AA$90,18))*(COUNTIF(C$6:C23,'DONNÉES BRUTES'!A$3:A$90)=0)*('DONNÉES BRUTES'!A$3:A$90<>""),0)),"—")} -> TEL | D24: =IFERROR(_xlfn.XLOOKUP(C24,'DONNÉES BRUTES'!A$3:A$90,'DONNÉES BRUTES'!B$3:B$90),"—") -> TE Connectivity plc | F24: =IFERROR(_xlfn.XLOOKUP(C24,'DONNÉES BRUTES'!A$3:A$90,'DONNÉES BRUTES'!AA$3:AA$90)&"/100","—") -> 71/100 | G24: =IFERROR(_xlfn.XLOOKUP(C24,'DONNÉES BRUTES'!A$3:A$90,'DONNÉES BRUTES'!W$3:W$90),"—") -> — | H24: =IFERROR(_xlfn.XLOOKUP(C24,'DONNÉES BRUTES'!A$3:A$90,'DONNÉES BRUTES'!N$3:N$90),"—") -> 0.239 | I24: =IFERROR(_xlfn.XLOOKUP(C24,'DONNÉES BRUTES'!A$3:A$90,'DONNÉES BRUTES'!AB$3:AB$90),"—") -> 60 | J24: =IFERROR(_xlfn.XLOOKUP(C24,'DONNÉES BRUTES'!A$3:A$90,'DONNÉES BRUTES'!Y$3:Y$90),"—") -> 45 | K24: =IFERROR(_xlfn.XLOOKUP(C24,'DONNÉES BRUTES'!A$3:A$90,'DONNÉES BRUTES'!AC$3:AC$90),"—") -> — | L24: =IFERROR(_xlfn.XLOOKUP(C24,'DONNÉES BRUTES'!A$3:A$90,'DONNÉES BRUTES'!AD$3:AD$90),"—") -> Sous-pondérer
B25: 19 | C25: {=IFERROR(INDEX('DONNÉES BRUTES'!A$3:A$90,MATCH(1,('DONNÉES BRUTES'!AA$3:AA$90>=LARGE('DONNÉES BRUTES'!AA$3:AA$90,19))*(COUNTIF(C$6:C24,'DONNÉES BRUTES'!A$3:A$90)=0)*('DONNÉES BRUTES'!A$3:A$90<>""),0)),"—")} -> DVN | D25: =IFERROR(_xlfn.XLOOKUP(C25,'DONNÉES BRUTES'!A$3:A$90,'DONNÉES BRUTES'!B$3:B$90),"—") -> Devon Energy Corporation | F25: =IFERROR(_xlfn.XLOOKUP(C25,'DONNÉES BRUTES'!A$3:A$90,'DONNÉES BRUTES'!AA$3:AA$90)&"/100","—") -> 69/100 | G25: =IFERROR(_xlfn.XLOOKUP(C25,'DONNÉES BRUTES'!A$3:A$90,'DONNÉES BRUTES'!W$3:W$90),"—") -> +55.1% | H25: =IFERROR(_xlfn.XLOOKUP(C25,'DONNÉES BRUTES'!A$3:A$90,'DONNÉES BRUTES'!N$3:N$90),"—") -> 0.44 | I25: =IFERROR(_xlfn.XLOOKUP(C25,'DONNÉES BRUTES'!A$3:A$90,'DONNÉES BRUTES'!AB$3:AB$90),"—") -> 66 | J25: =IFERROR(_xlfn.XLOOKUP(C25,'DONNÉES BRUTES'!A$3:A$90,'DONNÉES BRUTES'!Y$3:Y$90),"—") -> 50 | K25: =IFERROR(_xlfn.XLOOKUP(C25,'DONNÉES BRUTES'!A$3:A$90,'DONNÉES BRUTES'!AC$3:AC$90),"—") -> 2026-05-05 | L25: =IFERROR(_xlfn.XLOOKUP(C25,'DONNÉES BRUTES'!A$3:A$90,'DONNÉES BRUTES'!AD$3:AD$90),"—") -> Surpondérer
B26: 20 | C26: {=IFERROR(INDEX('DONNÉES BRUTES'!A$3:A$90,MATCH(1,('DONNÉES BRUTES'!AA$3:AA$90>=LARGE('DONNÉES BRUTES'!AA$3:AA$90,20))*(COUNTIF(C$6:C25,'DONNÉES BRUTES'!A$3:A$90)=0)*('DONNÉES BRUTES'!A$3:A$90<>""),0)),"—")} -> AAPL | D26: =IFERROR(_xlfn.XLOOKUP(C26,'DONNÉES BRUTES'!A$3:A$90,'DONNÉES BRUTES'!B$3:B$90),"—") -> Apple Inc. | F26: =IFERROR(_xlfn.XLOOKUP(C26,'DONNÉES BRUTES'!A$3:A$90,'DONNÉES BRUTES'!AA$3:AA$90)&"/100","—") -> 67/100 | G26: =IFERROR(_xlfn.XLOOKUP(C26,'DONNÉES BRUTES'!A$3:A$90,'DONNÉES BRUTES'!W$3:W$90),"—") -> — | H26: =IFERROR(_xlfn.XLOOKUP(C26,'DONNÉES BRUTES'!A$3:A$90,'DONNÉES BRUTES'!N$3:N$90),"—") -> 0.348 | I26: =IFERROR(_xlfn.XLOOKUP(C26,'DONNÉES BRUTES'!A$3:A$90,'DONNÉES BRUTES'!AB$3:AB$90),"—") -> 56 | J26: =IFERROR(_xlfn.XLOOKUP(C26,'DONNÉES BRUTES'!A$3:A$90,'DONNÉES BRUTES'!Y$3:Y$90),"—") -> 31 | K26: =IFERROR(_xlfn.XLOOKUP(C26,'DONNÉES BRUTES'!A$3:A$90,'DONNÉES BRUTES'!AC$3:AC$90),"—") -> — | L26: =IFERROR(_xlfn.XLOOKUP(C26,'DONNÉES BRUTES'!A$3:A$90,'DONNÉES BRUTES'!AD$3:AD$90),"—") -> Sous-pondérer
B28: FinSight IA · Screening Énergie · Ne constitue pas un conseil en investissement

Sheet ÉNERGIE
B1: FinSight IA · Analyse Sectorielle · Énergie Screening | R1: Ticker | S1: Score Global | U1: Signal | V1: Nb | X1: Ticker | Y1: Growth | Z1: Quality | AA1: Momentum | AC1: Ticker | AD1: Mg EBITDA (%)
B2: Zoom sectoriel · Ratios clés · Score FinSight · Usage confidentiel | R2: APA | S2: 84 | U2: Surpondérer | V2: 4 | X2: APA | Y2: 62 | Z2: 73 | AA2: 100 | AC2: APA | AD2: 60.2
R3: CTRA | S3: 72 | U3: Surpondérer | V3: 4 | X3: CTRA | Y3: 92 | Z3: 77 | AA3: 31 | AC3: CTRA | AD3: 63.5
C4: =COUNTIF('DONNÉES BRUTES'!C$3:C$90,"Énergie") -> 27 | E4: 30761.2 | H4: =IFERROR(ROUND(AVERAGEIF('DONNÉES BRUTES'!C$3:C$90,"Énergie",'DONNÉES BRUTES'!AB$3:AB$90),0),"—") -> 56 | K4: APA Corporation | N4: {=TEXT(MEDIAN(IF(IFERROR(_xlfn.NUMBERVALUE(SUBSTITUTE('DONNÉES BRUTES'!I$3:I$29,"x",""),".",","),0)>0,IFERROR(_xlfn.NUMBERVALUE(SUBSTITUTE('DONNÉES BRUTES'!I$3:I$29,"x",""),".",","),0),FALSE)),"0,0")&"x"} -> 9,8x | R4: DVN | S4: 69 | U4: Surpondérer | V4: 4 | X4: DVN | Y4: 50 | Z4: 62 | AA4: 69 | AC4: DVN | AD4: 44
R5: EXE | S5: 68 | U5: Surpondérer | V5: 4 | X5: EXE | Y5: 100 | Z5: 81 | AA5: 0 | AC5: EXE | AD5: 45.1
C6: Sociétés dans le secteur | E6: Market Cap totale | H6: Score moyen FinSight | K6: Meilleure société | N6: EV/EBITDA médiane | R6: EQT | S6: 62 | U6: Neutre | V6: 14 | X6: EQT | Y6: 96 | Z6: 85 | AA6: 4 | AC6: EQT | AD6: 72
R7: PSX | S7: 60 | U7: Neutre | V7: 14 | X7: PSX | Y7: 83 | Z7: 15 | AA7: 58 | AC7: PSX | AD7: 7.4
B8: =" ANALYSE DÉTAILLÉE · ÉNERGIE · "&COUNTA('DONNÉES BRUTES'!A$3:A$90)&" sociétés" -> ANALYSE DÉTAILLÉE · ÉNERGIE · 88 sociétés | R8: COP | S8: 58 | U8: Neutre | V8: 14 | X8: COP | Y8: 54 | Z8: 54 | AA8: 54 | AC8: COP | AD8: 43.4
B9: # | C9: Ticker | D9: Société | E9: Score | F9: Val. | G9: Growth | H9: Quality | I9: Mom. | J9: EV/EBITDA | K9: EV/Rev. | L9: P/E | M9: Mg Brute | N9: Mg EBITDA | O9: Mom. 52S | P9: Altman Z | R9: TRGP | S9: 54 | U9: Neutre | V9: 14 | X9: TRGP | Y9: 67 | Z9: 58 | AA9: 65 | AC9: TRGP | AD9: 28.5
B10: =" ▸ SURPONDÉRER · "&COUNTIFS('DONNÉES BRUTES'!C$3:C$90,"Énergie",'DONNÉES BRUTES'!AD$3:AD$90,"Surpondérer")&" sociétés" -> ▸ SURPONDÉRER · 4 sociétés | R10: EOG | S10: 52 | U10: Neutre | V10: 14 | X10: EOG | Y10: 8 | Z10: 96 | AA10: 27 | AC10: EOG | AD10: 49
B11: 1 | C11: APA | D11: APA Corporation | E11: 84 | F11: 100 | G11: 62 | H11: 73 | I11: 100 | J11: 3.2 | K11: 1.9 | L11: 9.3 | M11: 0.406 | N11: 0.602 | O11: 1.296 | P11: 1.46 | R11: OKE | S11: 52 | U11: Neutre | V11: 14 | X11: OKE | Y11: 88 | Z11: 46 | AA11: 8 | AC11: OKE | AD11: 23.2
B12: 2 | C12: CTRA | D12: Coterra Energy Inc. | E12: 72 | F12: 88 | G12: 92 | H12: 77 | I12: 31 | J12: 5.8 | K12: 3.7 | L12: 14.2 | M12: 0.415 | N12: 0.635 | O12: 0.361 | P12: 3.35 | R12: TPL | S12: 52 | U12: Neutre | V12: 14 | X12: TPL | Y12: 79 | Z12: 100 | AA12: 15 | AC12: TPL | AD12: 84.4
B13: 3 | C13: DVN | D13: Devon Energy Corporation | E13: 69 | F13: 96 | G13: 50 | H13: 62 | I13: 69 | J13: 4.7 | K13: 2.1 | L13: 10.8 | M13: 0.255 | N13: 0.44 | O13: 0.551 | P13: 2.89 | R13: FANG | S13: 51 | U13: Neutre | V13: 14 | X13: FANG | Y13: 75 | Z13: 65 | AA13: 42 | AC13: FANG | AD13: 48.1
B14: 4 | C14: EXE | D14: Expand Energy Corporation | E14: 68 | F14: 92 | G14: 100 | H14: 81 | I14: 0 | J14: 5.1 | K14: 2.3 | L14: 12.8 | M14: 0.508 | N14: 0.451 | O14: -0.138 | P14: 3.17 | R14: WMB | S14: 51 | U14: Neutre | V14: 14 | X14: WMB | Y14: 71 | Z14: 92 | AA14: 23 | AC14: WMB | AD14: 62
R15: BKR | S15: 50 | U15: Neutre | V15: 14 | X15: BKR | Y15: 33 | Z15: 42 | AA15: 85 | AC15: BKR | AD15: 15.5
B16: =" ▸ NEUTRE · "&COUNTIFS('DONNÉES BRUTES'!C$3:C$90,"Énergie",'DONNÉES BRUTES'!AD$3:AD$90,"Neutre")&" sociétés" -> ▸ NEUTRE · 14 sociétés | R16: OXY | S16: 50 | U16: Neutre | V16: 14 | X16: OXY | Y16: 38 | Z16: 69 | AA16: 38 | AC16: OXY | AD16: 54
B17: 5 | C17: EQT | D17: EQT Corporation | E17: 62 | F17: 62 | G17: 96 | H17: 85 | I17: 4 | J17: 7.3 | K17: 5.3 | L17: 17.8 | M17: 0.432 | N17: 0.72 | O17: 0.071 | P17: 2.52 | R17: KMI | S17: 48 | U17: Neutre | V17: 14 | X17: KMI | Y17: 58 | Z17: 88 | AA17: 19 | AC17: KMI | AD17: 42.4
B18: 6 | C18: PSX | D18: Phillips 66 | E18: 60 | F18: 83 | G18: 83 | H18: 15 | I18: 58 | J18: 8.6 | K18: 0.6 | L18: 14.9 | M18: 0.098 | N18: 0.074 | O18: 0.493 | P18: 3.12 | R18: ENI.MI | S18: 46 | U18: Neutre | V18: 14 | X18: ENI.MI | Z18: 4 | AA18: 88 | AC18: ENI.MI
B19: 7 | C19: COP | D19: ConocoPhillips | E19: 58 | F19: 71 | G19: 54 | H19: 54 | I19: 54 | J19: 6.4 | K19: 2.8 | L19: 18.6 | M19: 0.251 | N19: 0.434 | O19: 0.47 | P19: 3.98 | R19: MPC | S19: 45 | U19: Neutre | V19: 14 | X19: MPC | Y19: 42 | Z19: 12 | AA19: 50 | AC19: MPC | AD19: 8.8
B20: 8 | C20: TRGP | D20: Targa Resources Corp. | E20: 54 | F20: 25 | G20: 67 | H20: 58 | I20: 65 | J20: 14.1 | K20: 4 | L20: 26.8 | M20: 0.294 | N20: 0.285 | O20: 0.544 | P20: 1.02 | R20: XOM | S20: 44 | U20: Sous-pondérer | V20: 9 | X20: XOM | Y20: 17 | Z20: 38 | AA20: 62 | AC20: XOM | AD20: 21
B21: 9 | C21: EOG | D21: EOG Resources, Inc. | E21: 52 | F21: 79 | G21: 8 | H21: 96 | I21: 27 | J21: 6.9 | K21: 3.4 | L21: 14.4 | M21: 0.634 | N21: 0.49 | O21: 0.268 | P21: 4.53 | R21: HAL | S21: 43 | U21: Sous-pondérer | V21: 9 | X21: HAL | Y21: 0 | Z21: 27 | AA21: 96 | AC21: HAL | AD21: 14.7
B22: 10 | C22: OKE | D22: ONEOK, Inc. | E22: 52 | F22: 67 | G22: 88 | H22: 46 | I22: 8 | J22: 11.1 | K22: 2.6 | L22: 15.8 | M22: 0.26 | N22: 0.232 | O22: 0.11 | P22: 1.1 | R22: BP.L | S22: 40 | U22: Sous-pondérer | V22: 9 | X22: BP.L | Y22: 46 | Z22: 23 | AA22: 81 | AC22: BP.L | AD22: 16.2
B23: 11 | C23: TPL | D23: Texas Pacific Land Corporation | E23: 52 | F23: 12 | G23: 79 | H23: 100 | I23: 15 | J23: 43.6 | K23: 36.5 | L23: 61 | M23: 0.855 | N23: 0.844 | O23: 0.153 | P23: 16.05 | R23: SLB | S23: 40 | U23: Sous-pondérer | V23: 9 | X23: SLB | Y23: 4 | Z23: 35 | AA23: 77 | AC23: SLB | AD23: 19.5
B24: 12 | C24: FANG | D24: Diamondback Energy, Inc. | E24: 51 | F24: 21 | G24: 75 | H24: 65 | I24: 42 | J24: 9.3 | K24: 4.5 | L24: 31.6 | M24: 0.35 | N24: 0.481 | O24: 0.427 | P24: 1.55 | R24: VLO | S24: 40 | U24: Sous-pondérer | V24: 9 | X24: VLO | Y24: 25 | Z24: 8 | AA24: 92 | AC24: VLO | AD24: 5.5
B25: 13 | C25: WMB | D25: The Williams Companies, Inc. | E25: 51 | F25: 17 | G25: 71 | H25: 92 | I25: 23 | J25: 15.6 | K25: 9.7 | L25: 33.1 | M25: 0.62 | N25: 0.62 | O25: 0.208 | P25: -0.11 | R25: TTE.PA | S25: 36 | U25: Sous-pondérer | V25: 9 | X25: TTE.PA | Z25: 0 | AA25: 73 | AC25: TTE.PA
B26: 14 | C26: BKR | D26: Baker Hughes Company | E26: 50 | F26: 42 | G26: 33 | H26: 42 | I26: 85 | J26: 14.6 | K26: 2.3 | L26: 23.2 | M26: 0.236 | N26: 0.155 | O26: 0.668 | P26: 1.95 | R26: CVX | S26: 36 | U26: Sous-pondérer | V26: 9 | X26: CVX | Y26: 12 | Z26: 50 | AA26: 46 | AC26: CVX | AD26: 22.5
B27: 15 | C27: OXY | D27: Occidental Petroleum Corporation | E27: 50 | F27: 54 | G27: 38 | H27: 69 | I27: 38 | J27: 6.5 | K27: 3.5 | L27: 24.2 | M27: 0.349 | N27: 0.54 | O27: 0.426 | P27: 1.74 | R27: SHEL.L | S27: 25 | U27: Sous-pondérer | V27: 9 | X27: SHEL.L | Y27: 29 | Z27: 31 | AA27: 35 | AC27: SHEL.L | AD27: 21.2
B28: 16 | C28: KMI | D28: Kinder Morgan, Inc. | E28: 48 | F28: 29 | G28: 58 | H28: 88 | I28: 19 | J28: 14.3 | K28: 6 | L28: 23.2 | M28: 0.529 | N28: 0.424 | O28: 0.169 | P28: 0.65 | R28: DCC.L | S28: 13 | U28: Sous-pondérer | V28: 9 | X28: DCC.L | Y28: 21 | Z28: 19 | AA28: 12 | AC28: DCC.L | AD28: 4.3
B29: 17 | C29: ENI.MI | D29: Eni S.p.A. | E29: 46 | F29: — | H29: 4 | I29: 88 | J29: — | K29: — | L29: — | M29: — | N29: — | O29: 0.923 | P29: —
B30: 18 | C30: MPC | D30: Marathon Petroleum Corporation | E30: 45 | F30: 75 | G30: 42 | H30: 12 | I30: 50 | J30: 8.2 | K30: 0.7 | L30: 16.5 | M30: 0.075 | N30: 0.088 | O30: 0.441 | P30: 2.92
B32: =" ▸ SOUS-PONDÉRER · "&COUNTIFS('DONNÉES BRUTES'!C$3:C$90,"Énergie",'DONNÉES BRUTES'!AD$3:AD$90,"Sous-pondérer")&" sociétés" -> ▸ SOUS-PONDÉRER · 9 sociétés
B33: 19 | C33: XOM | D33: Exxon Mobil Corporation | E33: 44 | F33: 58 | G33: 17 | H33: 38 | I33: 62 | J33: 9.7 | K33: 2 | L33: 21.9 | M33: 0.22 | N33: 0.21 | O33: 0.535 | P33: 5.79
B34: 20 | C34: HAL | D34: Halliburton Company | E34: 43 | F34: 50 | G34: 0 | H34: 27 | I34: 96 | J34: 11.3 | K34: 1.7 | L34: 24.7 | M34: 0.157 | N34: 0.147 | O34: 0.995 | P34: 4.81
B35: 21 | C35: BP.L | D35: BP p.l.c. | E35: 40 | F35: 8 | G35: 46 | H35: 23 | I35: 81 | J35: 294.7 | K35: 47.8 | L35: — | M35: 0.177 | N35: 0.162 | O35: 0.624 | P35: 1.25
B36: 22 | C36: SLB | D36: SLB N.V. | E36: 40 | F36: 46 | G36: 4 | H36: 35 | I36: 77 | J36: 12.4 | K36: 2.4 | L36: 23 | M36: 0.182 | N36: 0.195 | O36: 0.617 | P36: 3.23
B37: 23 | C37: VLO | D37: Valero Energy Corporation | E37: 40 | F37: 33 | G37: 25 | H37: 8 | I37: 92 | J37: 11.6 | K37: 0.6 | L37: 30.8 | M37: 0.044 | N37: 0.055 | O37: 0.929 | P37: 4.93
B38: 24 | C38: TTE.PA | D38: TotalEnergies SE | E38: 36 | F38: — | H38: 0 | I38: 73 | J38: — | K38: — | L38: — | M38: — | N38: — | O38: 0.582 | P38: —
B39: 25 | C39: CVX | D39: Chevron Corporation | E39: 36 | F39: 38 | G39: 12 | H39: 50 | I39: 46 | J39: 9.8 | K39: 2.2 | L39: 30.4 | M39: 0.304 | N39: 0.225 | O39: 0.434 | P39: 4.09
B40: 26 | C40: SHEL.L | D40: Shell plc | E40: 25 | F40: 4 | G40: 29 | H40: 31 | I40: 35 | J40: 334.5 | K40: 71 | L40: 1061 | M40: 0.159 | N40: 0.212 | O40: 0.382 | P40: 3.35
B41: 27 | C41: DCC.L | D41: DCC plc | E41: 13 | F41: 0 | G41: 21 | H41: 19 | I41: 12 | J41: 579.7 | K41: 24.8 | L41: 2155 | M41: 0.133 | N41: 0.043 | O41: 0.125 | P41: 2.78

Sheet DONNÉES BRUTES
A1: DONNÉES BRUTES · Source de vérité · Énergie Screening
A2: Ticker | B2: Société | C2: Secteur | D2: Cours | E2: Mkt Cap | F2: EV | G2: Rev LTM | H2: EBITDA LTM | I2: EV/EBITDA | J2: EV/Rev | K2: P/E | L2: EPS | M2: Mg Brute | N2: Mg EBITDA | O2: Mg Nette | P2: Cro Rev | Q2: ROE | R2: ROA | S2: Current R | T2: ND/EBITDA | U2: Altman Z | V2: Beneish M | W2: Mom 52W | X2: Score Val | Y2: Score Gr | Z2: Score Qual | AA2: Score Mom | AB2: Score Global | AC2: Next Earn | AD2: Signal | AE2: Net Income | AF2: Equity | AG2: Debt | AH2: Cash | AI2: FCF | AJ2: Capex | AK2: FCF Yield | AL2: D/E Ratio | AM2: Cash Conv | AN2: Capex/Rev | AO2: Net Debt
A3: APA | B3: APA Corporation | C3: Énergie | D3: $37.74 | E3: $13.3 | F3: $17.3 | G3: $8.9 | H3: $5.4 | I3: 3.2x | J3: 1.9x | K3: 9.3x | L3: $4.06 | M3: 0.406 | N3: 0.602 | O3: 0.161 | P3: -0.084 | Q3: 0.235 | R3: 0.081 | S3: 0.82 | T3: 0.7x | U3: 1.46 | V3: -3.44 | W3: +129.6% | X3: 75 | Y3: 62 | Z3: 77 | AA3: 100 | AB3: 77 | AC3: 2026-05-06 | AD3: Surpondérer | AE3: 1.43 | AF3: 5.2 | AG3: 8 | AH3: 4 | AI3: 1.2 | AJ3: 2.4 | AK3: 0.09 | AL3: 1.54 | AM3: 0.84 | AN3: 0.27 | AO3: 4
A4: CTRA | B4: Coterra Energy Inc. | C4: Énergie | D4: $31.99 | E4: $24.3 | F4: $28.0 | G4: $7.6 | H4: $4.8 | I4: 5.8x | J4: 3.7x | K4: 14.2x | L4: $2.26 | M4: 0.415 | N4: 0.635 | O4: 0.225 | P4: 0.401 | Q4: 0.116 | R4: 0.071 | S4: 1.19 | T4: 0.8x | U4: 3.35 | V4: -3.11 | W4: +36.1% | X4: 63 | Y4: 92 | Z4: 74 | AA4: 31 | AB4: 69 | AC4: 2026-05-04 | AD4: Surpondérer | AE4: 1.71 | AF4: 9.8 | AG4: 5.5 | AH4: 3.2 | AI4: 1.5 | AJ4: 1.8 | AK4: 0.062 | AL4: 0.56 | AM4: 0.88 | AN4: 0.237 | AO4: 2.3
A5: DVN | B5: Devon Energy Corporation | C5: Énergie | D5: $45.74 | E5: $28.4 | F5: $35.4 | G5: $17.2 | H5: $7.6 | I5: 4.7x | J5: 2.1x | K5: 10.8x | L5: $4.25 | M5: 0.255 | N5: 0.44 | O5: 0.154 | P5: 0.078 | Q5: 0.17 | R5: 0.084 | S5: 0.98 | T5: 0.9x | U5: 2.89 | V5: -2.99 | W5: +55.1% | X5: 71 | Y5: 50 | Z5: 75 | AA5: 69 | AB5: 66 | AC5: 2026-05-05 | AD5: Surpondérer | AE5: 2.65 | AF5: 11.4 | AG5: 9.8 | AH5: 3.8 | AI5: 2.3 | AJ5: 3.5 | AK5: 0.081 | AL5: 0.86 | AM5: 0.87 | AN5: 0.203 | AO5: 6
A6: EXE | B6: Expand Energy Corporation | C6: Énergie | D6: $97.12 | E6: $23.4 | F6: $27.8 | G6: $12.2 | H6: $5.5 | I6: 5.1x | J6: 2.3x | K6: 12.8x | L6: $7.57 | M6: 0.508 | N6: 0.451 | O6: 0.149 | P6: 1.888 | Q6: 0.098 | R6: 0.064 | S6: 1.01 | T6: 0.8x | U6: 3.17 | V6: -2.82 | W6: -13.8% | X6: 68 | Y6: 100 | Z6: 64 | AA6: 0 | AB6: 63 | AC6: 2026-04-28 | AD6: Surpondérer | AE6: 1.82 | AF6: 9.2 | AG6: 8.1 | AH6: 2.9 | AI6: 1.6 | AJ6: 2.6 | AK6: 0.068 | AL6: 0.88 | AM6: 0.88 | AN6: 0.213 | AO6: 5.2
A7: EQT | B7: EQT Corporation | C7: Énergie | D7: $58.33 | E7: $36.4 | F7: $44.1 | G7: $8.3 | H7: $6.0 | I7: 7.3x | J7: 5.3x | K7: 17.8x | L7: $3.27 | M7: 0.432 | N7: 0.72 | O7: 0.244 | P7: 0.6 | Q7: 0.086 | R7: 0.049 | S7: 0.76 | T7: 1.3x | U7: 2.52 | V7: -3.41 | W7: +7.1% | X7: 50 | Y7: 96 | Z7: 69 | AA7: 4 | AB7: 60 | AC7: 2026-04-21 | AD7: Neutre | AE7: 2.03 | AF7: 14.8 | AG7: 11.2 | AH7: 4.1 | AI7: 1.7 | AJ7: 1.9 | AK7: 0.047 | AL7: 0.76 | AM7: 0.84 | AN7: 0.229 | AO7: 7.1
A8: PSX | B8: Phillips 66 | C8: Énergie | D8: $163.47 | E8: $65.5 | F8: $84.2 | G8: $132.4 | H8: $9.8 | I8: 8.6x | J8: 0.6x | K8: 14.9x | L8: $10.98 | M8: 0.098 | N8: 0.074 | O8: 0.033 | P8: -0.075 | Q8: 0.151 | R8: 0.06 | S8: 1.30 | T8: 1.9x | U8: 3.12 | V8: -3.47 | W8: +49.3% | X8: 88 | Y8: 83 | Z8: 57 | AA8: 58 | AB8: 71 | AC8: 2026-04-24 | AD8: Neutre | AE8: 4.37 | AF8: 21.6 | AG8: 18.7 | AH8: 3.2 | AI8: 3.8 | AJ8: 2 | AK8: 0.058 | AL8: 0.87 | AM8: 0.87 | AN8: 0.015 | AO8: 15.5
A9: COP | B9: ConocoPhillips | C9: Énergie | D9: $121.32 | E9: $148.3 | F9: $164.4 | G9: $58.9 | H9: $25.6 | I9: 6.4x | J9: 2.8x | K9: 18.6x | L9: $6.54 | M9: 0.251 | N9: 0.434 | O9: 0.136 | P9: 0.077 | Q9: 0.124 | R9: 0.066 | S9: 1.30 | T9: 0.6x | U9: 3.98 | V9: -2.97 | W9: +47.0% | X9: 63 | Y9: 54 | Z9: 69 | AA9: 54 | AB9: 60 | AC9: 2026-04-30 | AD9: Neutre | AE9: 8.01 | AF9: 45.2 | AG9: 18.3 | AH9: 7.9 | AI9: 6.8 | AJ9: 9.2 | AK9: 0.046 | AL9: 0.4 | AM9: 0.85 | AN9: 0.156 | AO9: 10.4
A10: TRGP | B10: Targa Resources Corp. | C10: Énergie | D10: $239.64 | E10: $51.5 | F10: $68.4 | G10: $17.0 | H10: $4.8 | I10: 14.1x | J10: 4.0x | K10: 26.8x | L10: $8.95 | M10: 0.294 | N10: 0.285 | O10: 0.113 | P10: 0.039 | Q10: 0.627 | R10: 0.076 | S10: 0.67 | T10: 3.5x | U10: 1.02 | V10: -3.34 | W10: +54.4% | X10: 45 | Y10: 67 | Z10: 64 | AA10: 65 | AB10: 61 | AC10: 2026-04-30 | AD10: Neutre | AE10: 1.92 | AF10: 7.4 | AG10: 17.8 | AH10: 2.1 | AI10: 1.6 | AJ10: 2.3 | AK10: 0.031 | AL10: 2.41 | AM10: 0.83 | AN10: 0.135 | AO10: 15.7
A11: EOG | B11: EOG Resources, Inc. | C11: Énergie | D11: $133.94 | E11: $71.9 | F11: $76.8 | G11: $22.6 | H11: $11.1 | I11: 6.9x | J11: 3.4x | K11: 14.4x | L11: $9.28 | M11: 0.634 | N11: 0.49 | O11: 0.221 | P11: -0.034 | Q11: 0.167 | R11: 0.096 | S11: 1.63 | T11: 0.4x | U11: 4.53 | V11: -3.01 | W11: +26.8% | X11: 63 | Y11: 8 | Z11: 78 | AA11: 27 | AB11: 44 | AC11: 2026-04-30 | AD11: Neutre | AE11: 4.99 | AF11: 18.3 | AG11: 4.8 | AH11: 5.2 | AI11: 4.4 | AJ11: 3.8 | AK11: 0.061 | AL11: 0.26 | AM11: 0.88 | AN11: 0.168 | AO11: -0.4
A12: OKE | B12: ONEOK, Inc. | C12: Énergie | D12: $85.03 | E12: $53.6 | F12: $86.3 | G12: $33.6 | H12: $7.8 | I12: 11.1x | J12: 2.6x | K12: 15.8x | L12: $5.39 | M12: 0.26 | N12: 0.232 | O12: 0.101 | P12: 0.55 | Q12: 0.151 | R12: 0.051 | S12: 0.71 | T12: 4.2x | U12: 1.10 | V12: -2.60 | W12: +11.0% | X12: 68 | Y12: 88 | Z12: 61 | AA12: 8 | AB12: 60 | AC12: 2026-04-28 | AD12: Neutre | AE12: 3.39 | AF12: 13.8 | AG12: 30.8 | AH12: 3.4 | AI12: 2.9 | AJ12: 2.2 | AK12: 0.054 | AL12: 2.23 | AM12: 0.86 | AN12: 0.065 | AO12: 27.4
A13: TPL | B13: Texas Pacific Land Corporation | C13: Énergie | D13: $425.61 | E13: $29.3 | F13: $29.2 | G13: $0.8 | H13: $0.7 | I13: 43.6x | J13: 36.5x | K13: 61.0x | L13: $6.98 | M13: 0.855 | N13: 0.844 | O13: 0.603 | P13: 0.131 | Q13: 0.33 | R13: 0.297 | S13: 4.34 | T13: -0.2x | U13: 16.05 | V13: -2.72 | W13: +15.3% | X13: 25 | Y13: 79 | Z13: 91 | AA13: 15 | AB13: 59 | AC13: 2026-05-06 | AD13: Neutre | AE13: 0.48 | AF13: 2.1 | AG13: 0 | AH13: 0.8 | AI13: 0.45 | AJ13: 0.05 | AK13: 0.015 | AL13: 0 | AM13: 0.94 | AN13: 0.063 | AO13: -0.8
A14: FANG | B14: Diamondback Energy, Inc. | C14: Énergie | D14: $186.87 | E14: $52.6 | F14: $67.0 | G14: $14.9 | H14: $7.2 | I14: 9.3x | J14: 4.5x | K14: 31.6x | L14: $5.92 | M14: 0.35 | N14: 0.481 | O14: 0.111 | P14: 0.354 | Q14: 0.045 | R14: 0.023 | S14: 0.42 | T14: 2.0x | U14: 1.55 | V14: -3.08 | W14: +42.7% | X14: 41 | Y14: 75 | Z14: 58 | AA14: 42 | AB14: 57 | AC14: 2026-05-04 | AD14: Neutre | AE14: 1.65 | AF14: 16.8 | AG14: 16.2 | AH14: 2.1 | AI14: 1.4 | AJ14: 3.2 | AK14: 0.027 | AL14: 0.96 | AM14: 0.85 | AN14: 0.215 | AO14: 14.1
... A18: KMI | B18: Kinder Morgan, Inc. | C18: Énergie | D18: $31.77 | E18: $70.7 | F18: $102.4 | G18: $16.9 | H18: $7.2 | I18: 14.3x | J18: 6.0x | K18: 23.2x | L18: $1.37 | M18: 0.529 | N18: 0.424 | O18: 0.18 | P18: 0.122 | Q18: 0.098 | R18: 0.042 | S18: 0.64 | T18: 4.4x | U18: 0.65 | V18: -2.95 | W18: +16.9% | X18: 43 | Y18: 58 | Z18: 64 | AA18: 19 | AB18: 49 | AC18: 2026-04-15 | AD18: Neutre | AE18: 3.04 | AF18: 21.4 | AG18: 29.8 | AH18: 2.8 | AI18: 2.6 | AJ18: 1.6 | AK18: 0.037 | AL18: 1.39 | AM18: 0.86 | AN18: 0.095 | AO18: 27
A19: ENI.MI | B19: Eni S.p.A. | C19: Énergie | D19: €23.41 | E19: €68.8 | F19: €89.2 | G19: — | H19: — | I19: — | J19: — | K19: — | L19: — | M19: — | N19: — | O19: — | P19: — | Q19: — | R19: — | S19: 1.14 | T19: — | U19: — | V19: — | W19: +92.3% | X19: — | Y19: — | Z19: 73 | AA19: 88 | AB19: 79 | AC19: 2026-04-24 | AD19: Neutre | AE19: 5.8 | AF19: 48.2 | AG19: 19.4 | AH19: 12.6 | AI19: 5.1 | AJ19: 8.9 | AK19: 0.074 | AL19: 0.4 | AM19: 0.88 | AN19: — | AO19: 6.8
A20: MPC | B20: Marathon Petroleum Corporation | C20: Énergie | D20: $226.76 | E20: $66.8 | F20: $96.0 | G20: $132.7 | H20: $11.7 | I20: 8.2x | J20: 0.7x | K20: 16.5x | L20: $13.74 | M20: 0.075 | N20: 0.088 | O20: 0.03 | P20: -0.044 | Q20: 0.234 | R20: 0.048 | S20: 1.26 | T20: 2.5x | U20: 2.92 | V20: -3.22 | W20: +44.1% | X20: 83 | Y20: 42 | Z20: 60 | AA20: 50 | AB20: 57 | AC20: 2026-05-05 | AD20: Neutre | AE20: 3.98 | AF20: 18.2 | AG20: 25.4 | AH20: 4.6 | AI20: 3.4 | AJ20: 2.1 | AK20: 0.051 | AL20: 1.4 | AM20: 0.85 | AN20: 0.016 | AO20: 20.8
A21: XOM | B21: Exxon Mobil Corporation | C21: Énergie | D21: $151.85 | E21: $631.2 | F21: $657.7 | G21: $323.9 | H21: $67.9 | I21: 9.7x | J21: 2.0x | K21: 21.9x | L21: $6.94 | M21: 0.22 | N21: 0.21 | O21: 0.089 | P21: -0.045 | Q21: 0.111 | R21: 0.064 | S21: 1.15 | T21: 0.4x | U21: 5.79 | V21: -3.09 | W21: +53.5% | X21: 61 | Y21: 17 | Z21: 66 | AA21: 62 | AB21: 50 | AC21: 2026-05-01 | AD21: Sous-pondérer | AE21: 28.83 | AF21: 167.4 | AG21: 37.1 | AH21: 22.3 | AI21: 24.6 | AJ21: 16.8 | AK21: 0.039 | AL21: 0.22 | AM21: 0.85 | AN21: 0.052 | AO21: 14.8
A22: HAL | B22: Halliburton Company | C22: Énergie | D22: $38.03 | E22: $31.8 | F22: $37.0 | G22: $22.2 | H22: $3.3 | I22: 11.3x | J22: 1.7x | K22: 24.7x | L22: $1.54 | M22: 0.157 | N22: 0.147 | O22: 0.058 | P22: -0.033 | Q22: 0.123 | R22: 0.051 | S22: 2.04 | T22: 1.6x | U22: 4.81 | V22: -2.91 | W22: +99.5% | X22: 71 | Y22: 0 | Z22: 54 | AA22: 96 | AB22: 50 | AC22: 2026-04-21 | AD22: Sous-pondérer | AE22: 1.29 | AF22: 10.2 | AG22: 7.4 | AH22: 2.6 | AI22: 1.1 | AJ22: 1 | AK22: 0.035 | AL22: 0.73 | AM22: 0.85 | AN22: 0.045 | AO22: 4.8
A23: BP.L | B23: BP p.l.c. | C23: Énergie | D23: $584.00 | E23: $9,022.1 | F23: $9,048.2 | G23: $189.3 | H23: $30.7 | I23: 294.7x | J23: 47.8x | K23: — | L23: $0.00 | M23: 0.177 | N23: 0.162 | O23: 0 | P23: 0.001 | Q23: 0.001 | R23: 0 | S23: 1.26 | T23: 0.9x | U23: 1.25 | V23: -3.22 | W23: +62.4% | X23: 32 | Y23: 46 | Z23: 36 | AA23: 81 | AB23: 47 | AC23: 2026-04-28 | AD23: Sous-pondérer | AE23: 0 | AF23: 82.4 | AG23: 51.8 | AH23: 14.2 | AI23: 2.8 | AJ23: 12.6 | AK23: 0 | AL23: 0.63 | AM23: — | AN23: 0.067 | AO23: 37.6
A24: SLB | B24: SLB N.V. | C24: Énergie | D24: $51.85 | E24: $77.8 | F24: $86.4 | G24: $35.7 | H24: $7.0 | I24: 12.4x | J24: 2.4x | K24: 23.0x | L24: $2.25 | M24: 0.182 | N24: 0.195 | O24: 0.094 | P24: -0.016 | Q24: 0.129 | R24: 0.061 | S24: 1.33 | T24: 1.2x | U24: 3.23 | V24: -2.85 | W24: +61.7% | X24: 55 | Y24: 4 | Z24: 64 | AA24: 77 | AB24: 47 | AC24: 2026-05-01 | AD24: Sous-pondérer | AE24: 3.36 | AF24: 22.8 | AG24: 12.4 | AH24: 4.8 | AI24: 2.9 | AJ24: 2.1 | AK24: 0.037 | AL24: 0.54 | AM24: 0.86 | AN24: 0.059 | AO24: 7.6
A25: VLO | B25: Valero Energy Corporation | C25: Énergie | D25: $241.69 | E25: $72.2 | F25: $78.2 | G25: $122.7 | H25: $6.7 | I25: 11.6x | J25: 0.6x | K25: 30.8x | L25: $7.85 | M25: 0.044 | N25: 0.055 | O25: 0.019 | P25: -0.055 | Q25: 0.099 | R25: 0.04 | S25: 1.65 | T25: 0.9x | U25: 4.93 | V25: -3.29 | W25: +92.9% | X25: 71 | Y25: 25 | Z25: 51 | AA25: 92 | AB25: 55 | AC25: 2026-04-30 | AD25: Sous-pondérer | AE25: 2.33 | AF25: 20.4 | AG25: 13.6 | AH25: 4.2 | AI25: 2 | AJ25: 1.8 | AK25: 0.028 | AL25: 0.67 | AM25: 0.86 | AN25: 0.015 | AO25: 9.4
A26: TTE.PA | B26: TotalEnergies SE | C26: Énergie | D26: €77.12 | E26: €164.5 | F26: €189.6 | G26: — | H26: — | I26: — | J26: — | K26: — | L26: — | M26: — | N26: — | O26: — | P26: — | Q26: — | R26: — | S26: 1.10 | T26: — | U26: — | V26: — | W26: +58.2% | X26: — | Y26: — | Z26: 80 | AA26: 73 | AB26: 77 | AC26: 2026-04-29 | AD26: Sous-pondérer | AE26: 15.6 | AF26: 119.4 | AG26: 51.2 | AH26: 34.8 | AI26: 13.8 | AJ26: 16.4 | AK26: 0.084 | AL26: 0.43 | AM26: 0.88 | AN26: — | AO26: 16.4
A27: CVX | B27: Chevron Corporation | C27: Énergie | D27: $187.65 | E27: $373.8 | F27: $406.8 | G27: $184.4 | H27: $41.4 | I27: 9.8x | J27: 2.2x | K27: 30.4x | L27: $6.17 | M27: 0.304 | N27: 0.225 | O27: 0.067 | P27: -0.046 | Q27: 0.066 | R27: 0.038 | S27: 1.15 | T27: 0.8x | U27: 4.09 | V27: -3.35 | W27: +43.4% | X27: 56 | Y27: 12 | Z27: 58 | AA27: 46 | AB27: 41 | AC27: 2026-05-01 | AD27: Sous-pondérer | AE27: 12.35 | AF27: 142.6 | AG27: 29.8 | AH27: 16.4 | AI27: 10.8 | AJ27: 13.2 | AK27: 0.029 | AL27: 0.21 | AM27: 0.87 | AN27: 0.072 | AO27: 13.4
A28: SHEL.L | B28: Shell plc | C28: Énergie | D28: $3,384.50 | E28: $18,934.5 | F28: $18,951.6 | G28: $266.9 | H28: $56.7 | I28: 334.5x | J28: 71.0x | K28: 1061.0x | L28: $3.19 | M28: 0.159 | N28: 0.212 | O28: 0.067 | P28: -0.061 | Q28: 0.102 | R28: 0.048 | S28: 1.30 | T28: 0.3x | U28: 3.35 | V28: -3.05 | W28: +38.2% | X28: 25 | Y28: 29 | Z28: 58 | AA28: 35 | AB28: 38 | AC28: 2026-05-07 | AD28: Sous-pondérer | AE28: 17.88 | AF28: 162.8 | AG28: 82.4 | AH28: 28.6 | AI28: 15.2 | AJ28: 18.8 | AK28: 0.001 | AL28: 0.51 | AM28: 0.85 | AN28: 0.07 | AO28: 53.8
A29: DCC.L | B29: DCC plc | C29: Énergie | D29: $5,215.00 | E29: $445.5 | F29: $446.4 | G29: $18.0 | H29: $0.8 | I29: 579.7x | J29: 24.8x | K29: 2155.0x | L29: $2.42 | M29: 0.133 | N29: 0.043 | O29: 0.011 | P29: -0.045 | Q29: 0.067 | R29: 0.022 | S29: 1.51 | T29: 1.1x | U29: 2.78 | V29: -3.40 | W29: +12.5% | X29: 30 | Y29: 21 | Z29: 38 | AA29: 12 | AB29: 26 | AC29: — | AD29: Sous-pondérer | AE29: 0.2 | AF29: 2.8 | AG29: 2.6 | AH29: 1.1 | AI29: 0.18 | AJ29: 0.4 | AK29: 0 | AL29: 0.93 | AM29: 0.9 | AN29: 0.022 | AO29: 1.5
A30: AMAT | B30: Applied Materials, Inc. | C30: Technology | D30: — | E30: — | F30: — | G30: $28.4 | H30: $10.0 | I30: — | J30: — | K30: — | L30: — | M30: 0.487 | N30: 0.352 | O30: 0.247 | P30: 0.044 | Q30: 0.343 | R30: 0.193 | S30: 2.61 | T30: -0.1x | U30: 10.40 | V30: -3.07 | W30: +124.8% | X30: 100 | Y30: 38 | Z30: 91 | AA30: 90 | AB30: 77 | AC30: 2026-05-14 | AD30: Neutre | AE30: 7.01 | AF30: 26.4 | AG30: 6.2 | AH30: 8.4 | AI30: 7.8 | AJ30: 0.9 | AK30: — | AL30: 0.23 | AM30: 1.11 | AN30: 0.032 | AO30: -2.2
A31: CPAY | B31: Corpay, Inc. | C31: Technology | D31: — | E31: — | F31: — | G31: $4.5 | H31: $2.3 | I31: — | J31: — | K31: — | L31: — | M31: 0.786 | N31: 0.516 | O31: 0.236 | P31: 0.139 | Q31: 0.275 | R31: 0.041 | S31: 0.98 | T31: 3.2x | U31: 1.86 | V31: -3.13 | W31: -9.7% | X31: 100 | Y31: 53 | Z31: 77 | AA31: 44 | AB31: 68 | AC31: 2026-05-06 | AD31: Neutre | AE31: 1.06 | AF31: 6.8 | AG31: 9.2 | AH31: 1.4 | AI31: 1.2 | AJ31: 0.2 | AK31: — | AL31: 1.35 | AM31: 1.13 | AN31: 0.044 | AO31: 7.8
A32: FSLR | B32: First Solar, Inc. | C32: Technology | D32: — | E32: — | F32: — | G32: $5.2 | H32: $2.1 | I32: — | J32: — | K32: — | L32: — | M32: 0.406 | N32: 0.413 | O32: 0.293 | P32: 0.241 | Q32: 0.16 | R32: 0.115 | S32: 2.67 | T32: -1.1x | U32: 6.99 | V32: -3.05 | W32: +24.1% | X32: 20 | Y32: 69 | Z32: 84 | AA32: 64 | AB32: 63 | AC32: 2026-04-28 | AD32: Neutre | AE32: 1.52 | AF32: 9.8 | AG32: 2.1 | AH32: 3.2 | AI32: 1.4 | AJ32: 1.8 | AK32: — | AL32: 0.21 | AM32: 0.92 | AN32: 0.346 | AO32: -1.1
A33: SAP.DE | B33: SAP SE | C33: Technology | D33: — | E33: — | F33: — | G33: €36.8 | H33: €12.1 | I33: — | J33: — | K33: — | L33: — | M33: 0.729 | N33: 0.328 | O33: 0.195 | P33: 0.077 | Q33: 0.161 | R33: 0.102 | S33: 1.16 | T33: -0.2x | U33: 5.34 | V33: -3.14 | W33: -43.5% | X33: 100 | Y33: 93 | Z33: 81 | AA33: 8 | AB33: 74 | AC33: 2026-04-23 | AD33: Neutre | AE33: 7.18 | AF33: 62.4 | AG33: 12.8 | AH33: 9.6 | AI33: 7.8 | AJ33: 1.2 | AK33: — | AL33: 0.21 | AM33: 1.09 | AN33: 0.033 | AO33: 3.2
A34: CIEN | B34: Ciena Corporation | C34: Technology | D34: — | E34: — | F34: — | G34: $4.8 | H34: $0.4 | I34: — | J34: — | K34: — | L34: — | M34: 0.42 | N34: 0.081 | O34: 0.026 | P34: 0.188 | Q34: 0.045 | R34: 0.021 | S34: 2.73 | T34: 1.1x | U34: 1.96 | V34: -2.98 | W34: +454.6% | X34: 100 | Y34: 59 | Z34: 53 | AA34: 98 | AB34: 73 | AC34: 2026-06-04 | AD34: Neutre | AE34: 0.12 | AF34: 3.8 | AG34: 1.4 | AH34: 1.2 | AI34: 0.11 | AJ34: 0.15 | AK34: — | AL34: 0.37 | AM34: 0.92 | AN34: 0.031 | AO34: 0.2
A35: FTNT | B35: Fortinet, Inc. | C35: Technology | D35: — | E35: — | F35: — | G35: $6.8 | H35: $2.5 | I35: — | J35: — | K35: — | L35: — | M35: 0.805 | N35: 0.361 | O35: 0.273 | P35: 0.142 | Q35: 1.498 | R35: 0.178 | S35: 1.17 | T35: -0.6x | U35: 2.02 | V35: -2.92 | W35: -20.0% | X35: 100 | Y35: 56 | Z35: 91 | AA35: 30 | AB35: 70 | AC35: 2026-05-07 | AD35: Neutre | AE35: 1.86 | AF35: 4.2 | AG35: 2.8 | AH35: 2.1 | AI35: 2.1 | AJ35: 0.18 | AK35: — | AL35: 0.67 | AM35: 1.13 | AN35: 0.026 | AO35: 0.7
A36: MSI | B36: Motorola Solutions, Inc. | C36: Technology | D36: — | E36: — | F36: — | G36: $11.7 | H36: $3.6 | I36: — | J36: — | K36: — | L36: — | M36: 0.517 | N36: 0.308 | O36: 0.184 | P36: 0.08 | Q36: 0.894 | R36: 0.111 | S36: 1.04 | T36: 2.2x | U36: 1.75 | V36: -2.84 | W36: +6.7% | X36: 100 | Y36: 74 | Z36: 78 | AA36: 57 | AB36: 77 | AC36: 2026-04-30 | AD36: Neutre | AE36: 2.15 | AF36: 3.6 | AG36: 6.8 | AH36: 1.8 | AI36: 2.3 | AJ36: 0.32 | AK36: — | AL36: 1.89 | AM36: 1.07 | AN36: 0.027 | AO36: 5
A37: ADBE | B37: Adobe Inc. | C37: Technology | D37: — | E37: — | F37: — | G37: $23.8 | H37: $9.8 | I37: — | J37: — | K37: — | L37: — | M37: 0.893 | N37: 0.413 | O37: 0.3 | P37: 0.105 | Q37: 0.613 | R37: 0.242 | S37: 1.00 | T37: 0.1x | U37: 7.74 | V37: -2.97 | W37: -41.9% | X37: 100 | Y37: 65 | Z37: 91 | AA37: 12 | AB37: 69 | AC37: 2026-06-11 | AD37: Neutre | AE37: 7.14 | AF37: 14.8 | AG37: 5.4 | AH37: 7.2 | AI37: 7.8 | AJ37: 0.48 | AK37: — | AL37: 0.36 | AM37: 1.09 | AN37: 0.02 | AO37: -1.8
A38: VRSN | B38: VeriSign, Inc. | C38: Technology | D38: — | E38: — | F38: — | G38: $1.7 | H38: $1.2 | I38: — | J38: — | K38: — | L38: — | M38: 0.882 | N38: 0.71 | O38: 0.498 | P38: 0.064 | Q38: -0.383 | R38: 0.623 | S38: 0.49 | T38: 1.3x | U38: -27.16 | V38: -2.84 | W38: -3.6% | X38: 100 | Y38: 28 | Z38: 72 | AA38: 48 | AB38: 60 | AC38: 2026-04-23 | AD38: Neutre | AE38: 0.85 | AF38: -1.2 | AG38: 1.9 | AH38: 0.9 | AI38: 0.92 | AJ38: 0.04 | AK38: — | AL38: 1.58 | AM38: 1.08 | AN38: 0.024 | AO38: 1
A39: INTU | B39: Intuit Inc. | C39: Technology | D39: — | E39: — | F39: — | G39: $18.8 | H39: $5.9 | I39: — | J39: — | K39: — | L39: — | M39: 0.796 | N39: 0.313 | O39: 0.205 | P39: 0.156 | Q39: 0.196 | R39: 0.105 | S39: 1.36 | T39: 0.5x | U39: 4.52 | V39: -3.05 | W39: -42.6% | X39: 100 | Y39: 72 | Z39: 78 | AA39: 10 | AB39: 67 | AC39: 2026-05-21 | AD39: Neutre | AE39: 3.85 | AF39: 22.4 | AG39: 6.8 | AH39: 4.2 | AI39: 4.1 | AJ39: 0.48 | AK39: — | AL39: 0.3 | AM39: 1.06 | AN39: 0.026 | AO39: 2.6
A40: ORCL | B40: Oracle Corporation | C40: Technology | D40: — | E40: — | F40: — | G40: $57.4 | H40: $23.9 | I40: — | J40: — | K40: — | L40: — | M40: 0.705 | N40: 0.417 | O40: 0.217 | P40: 0.084 | Q40: 0.608 | R40: 0.074 | S40: 0.75 | T40: 3.4x | U40: 0.24 | V40: -3.01 | W40: -11.6% | X40: 100 | Y40: 44 | Z40: 69 | AA40: 42 | AB40: 62 | AC40: 2026-06-10 | AD40: Sous-pondérer | AE40: 12.45 | AF40: 18.6 | AG40: 88.2 | AH40: 9.8 | AI40: 14.2 | AJ40: 1.2 | AK40: — | AL40: 4.74 | AM40: 1.14 | AN40: 0.021 | AO40: 78.4
A41: NOW | B41: ServiceNow, Inc. | C41: Technology | D41: — | E41: — | F41: — | G41: $13.3 | H41: $3.0 | I41: — | J41: — | K41: — | L41: — | M41: 0.775 | N41: 0.228 | O41: 0.132 | P41: 0.209 | Q41: 0.135 | R41: 0.067 | S41: 1.00 | T41: -0.7x | U41: 2.29 | V41: -2.87 | W41: -49.5% | X41: 100 | Y41: 80 | Z41: 71 | AA41: 5 | AB41: 66 | AC41: 2026-04-22 | AD41: Sous-pondérer | AE41: 1.76 | AF41: 18.4 | AG41: 1.8 | AH41: 3.8 | AI41: 2.1 | AJ41: 0.42 | AK41: — | AL41: 0.1 | AM41: 1.19 | AN41: 0.032 | AO41: -2
A42: XYZ | B42: Block, Inc. | C42: Technology | D42: — | E42: — | F42: — | G42: $24.2 | H42: $3.4 | I42: — | J42: — | K42: — | L42: — | M42: 0.428 | N42: 0.141 | O42: 0.054 | P42: 0.003 | Q42: 0.059 | R42: 0.033 | S42: 2.20 | T42: -0.8x | U42: 4.23 | V42: -3.15 | W42: -4.4% | X42: 100 | Y42: 87 | Z42: 47 | AA42: 47 | AB42: 70 | AC42: 2026-04-30 | AD42: Sous-pondérer | AE42: 1.31 | AF42: 8.6 | AG42: 6.2 | AH42: 5.8 | AI42: 1.1 | AJ42: 0.48 | AK42: — | AL42: 0.72 | AM42: 0.84 | AN42: 0.02 | AO42: 0.4
A43: GEN | B43: Gen Digital Inc. | C43: Technology | D43: — | E43: — | F43: — | G43: — | H43: — | I43: — | J43: — | K43: — | L43: — | M43: 0.803 | N43: 0.515 | O43: — | P43: 0.036 | Q43: — | R43: — | S43: — | T43: — | U43: — | V43: — | W43: — | X43: — | Y43: 62 | Z43: 63 | AA43: 20 | AB43: 52 | AC43: — | AD43: Sous-pondérer | AE43: 0.48 | AF43: 1.8 | AG43: 6.4 | AH43: 1.2 | AI43: 0.52 | AJ43: 0.08 | AK43: — | AL43: 3.56 | AM43: 1.08 | AN43: — | AO43: 5.2
A44: SGE.L | B44: The Sage Group plc | C44: Technology | D44: — | E44: — | F44: — | G44: — | H44: — | I44: — | J44: — | K44: — | L44: — | M44: 0.927 | N44: 0.25 | O44: — | P44: 0.078 | Q44: — | R44: — | S44: — | T44: — | U44: — | V44: — | W44: — | X44: — | Y44: 42 | Z44: 82 | AA44: 23 | AB44: 52 | AC44: — | AD44: Sous-pondérer | AE44: 0.54 | AF44: 8.2 | AG44: 1.4 | AH44: 1.8 | AI44: 0.58 | AJ44: 0.12 | AK44: — | AL44: 0.17 | AM44: 1.07 | AN44: — | AO44: -0.4
A45: AKAM | B45: Akamai Technologies, Inc. | C45: Technology | D45: — | E45: — | F45: — | G45: — | H45: — | I45: — | J45: — | K45: — | L45: — | M45: 0.589 | N45: 0.319 | O45: — | P45: 0.054 | Q45: — | R45: — | S45: — | T45: — | U45: — | V45: — | W45: — | X45: — | Y45: 30 | Z45: 68 | AA45: 79 | AB45: 57 | AC45: — | AD45: Sous-pondérer | AE45: 0.52 | AF45: 2.4 | AG45: 3.8 | AH45: 0.8 | AI45: 0.56 | AJ45: 0.22 | AK45: — | AL45: 1.58 | AM45: 1.08 | AN45: — | AO45: 3
A46: CSCO | B46: Cisco Systems, Inc. | C46: Technology | D46: — | E46: — | F46: — | G46: — | H46: — | I46: — | J46: — | K46: — | L46: — | M46: 0.649 | N46: 0.274 | O46: — | P46: 0.053 | Q46: — | R46: — | S46: — | T46: — | U46: — | V46: — | W46: — | X46: — | Y46: 23 | Z46: 75 | AA46: 66 | AB46: 53 | AC46: — | AD46: Sous-pondérer | AE46: 9.2 | AF46: 36.8 | AG46: 14.2 | AH46: 9.6 | AI46: 9.8 | AJ46: 1.2 | AK46: — | AL46: 0.39 | AM46: 1.07 | AN46: — | AO46: 4.6
A47: CRM | B47: Salesforce, Inc. | C47: Technology | D47: — | E47: — | F47: — | G47: — | H47: — | I47: — | J47: — | K47: — | L47: — | M47: 0.777 | N47: 0.302 | O47: — | P47: 0.096 | Q47: — | R47: — | S47: — | T47: — | U47: — | V47: — | W47: — | X47: — | Y47: 50 | Z47: 88 | AA47: 26 | AB47: 58 | AC47: — | AD47: Sous-pondérer | AE47: 1.8 | AF47: 48.2 | AG47: 11.4 | AH47: 7.8 | AI47: 2.1 | AJ47: 0.62 | AK47: — | AL47: 0.24 | AM47: 1.17 | AN47: — | AO47: 3.6
A48: NTAP | B48: NetApp, Inc. | C48: Technology | D48: — | E48: — | F48: — | G48: — | H48: — | I48: — | J48: — | K48: — | L48: — | M48: 0.702 | N48: 0.257 | O48: — | P48: 0.049 | Q48: — | R48: — | S48: — | T48: — | U48: — | V48: — | W48: — | X48: — | Y48: 29 | Z48: 52 | AA48: 53 | AB48: 44 | AC48: — | AD48: Sous-pondérer | AE48: 1.42 | AF48: 1.8 | AG48: 6.2 | AH48: 2.4 | AI48: 1.6 | AJ48: 0.18 | AK48: — | AL48: 3.44 | AM48: 1.13 | AN48: — | AO48: 3.8
A49: AAPL | B49: Apple Inc. | C49: Technology | D49: — | E49: — | F49: — | G49: — | H49: — | I49: — | J49: — | K49: — | L49: — | M49: 0.469 | N49: 0.348 | O49: — | P49: 0.064 | Q49: — | R49: — | S49: — | T49: — | U49: — | V49: — | W49: — | X49: — | Y49: 31 | Z49: 75 | AA49: 67 | AB49: 56 | AC49: — | AD49: Sous-pondérer | AE49: 96 | AF49: 74.2 | AG49: 108 | AH49: 52 | AI49: 104 | AJ49: 9.4 | AK49: — | AL49: 1.46 | AM49: 1.08 | AN49: — | AO49: 56
A50: QCOM | B50: QUALCOMM Incorporated | C50: Technology | D50: — | E50: — | F50: — | G50: — | H50: — | I50: — | J50: — | K50: — | L50: — | M50: 0.554 | N50: 0.337 | O50: — | P50: 0.137 | Q50: — | R50: — | S50: — | T50: — | U50: — | V50: — | W50: — | X50: — | Y50: 63 | Z50: 75 | AA50: 43 | AB50: 63 | AC50: — | AD50: Sous-pondérer | AE50: 7.44 | AF50: 12.4 | AG50: 15.8 | AH50: 8.2 | AI50: 8.6 | AJ50: 0.88 | AK50: — | AL50: 1.27 | AM50: 1.16 | AN50: — | AO50: 7.6
A51: UBER | B51: Uber Technologies, Inc. | C51: Technology | D51: — | E51: — | F51: — | G51: — | H51: — | I51: — | J51: — | K51: — | L51: — | M51: 0.398 | N51: 0.134 | O51: — | P51: 0.183 | Q51: — | R51: — | S51: — | T51: — | U51: — | V51: — | W51: — | X51: — | Y51: 76 | Z51: 67 | AA51: 38 | AB51: 63 | AC51: — | AD51: Sous-pondérer | AE51: 1.88 | AF51: 22.8 | AG51: 9.8 | AH51: 5.8 | AI51: 2.1 | AJ51: 0.58 | AK51: — | AL51: 0.43 | AM51: 1.12 | AN51: — | AO51: 4
A52: WDAY | B52: Workday, Inc. | C52: Technology | D52: — | E52: — | F52: — | G52: — | H52: — | I52: — | J52: — | K52: — | L52: — | M52: 0.757 | N52: 0.154 | O52: — | P52: 0.131 | Q52: — | R52: — | S52: — | T52: — | U52: — | V52: — | W52: — | X52: — | Y52: 77 | Z52: 88 | AA52: 6 | AB52: 63 | AC52: — | AD52: Sous-pondérer | AE52: 0.52 | AF52: 12.8 | AG52: 3.4 | AH52: 4.2 | AI52: 0.68 | AJ52: 0.32 | AK52: — | AL52: 0.27 | AM52: 1.31 | AN52: — | AO52: -0.8
A53: TDY | B53: Teledyne Technologies Incorporated | C53: Technology | D53: — | E53: — | F53: — | G53: — | H53: — | I53: — | J53: — | K53: — | L53: — | M53: 0.428 | N53: 0.244 | O53: — | P53: 0.079 | Q53: — | R53: — | S53: — | T53: — | U53: — | V53: — | W53: — | X53: — | Y53: 48 | Z53: 75 | AA53: 65 | AB53: 62 | AC53: — | AD53: Sous-pondérer | AE53: 0.88 | AF53: 10.4 | AG53: 3.8 | AH53: 0.8 | AI53: 0.94 | AJ53: 0.22 | AK53: — | AL53: 0.37 | AM53: 1.07 | AN53: — | AO53: 3
A54: DDOG | B54: Datadog, Inc. | C54: Technology | D54: — | E54: — | F54: — | G54: — | H54: — | I54: — | J54: — | K54: — | L54: — | M54: 0.8 | N54: 0.057 | O54: — | P54: 0.277 | Q54: — | R54: — | S54: — | T54: — | U54: — | V54: — | W54: — | X54: — | Y54: 21 | Z54: 50 | AA54: 51 | AB54: 39 | AC54: — | AD54: Sous-pondérer | AE54: -0.08 | AF54: 12.6 | AG54: 0.8 | AH54: 4.2 | AI54: 0.18 | AJ54: 0.38 | AK54: — | AL54: 0.06 | AM54: -2.25 | AN54: — | AO54: -3.4
A55: TEL | B55: TE Connectivity plc | C55: Technology | D55: — | E55: — | F55: — | G55: — | H55: — | I55: — | J55: — | K55: — | L55: — | M55: 0.352 | N55: 0.239 | O55: — | P55: 0.089 | Q55: — | R55: — | S55: — | T55: — | U55: — | V55: — | W55: — | X55: — | Y55: 45 | Z55: 68 | AA55: 71 | AB55: 60 | AC55: — | AD55: Sous-pondérer | AE55: 2.48 | AF55: 18.4 | AG55: 14.2 | AH55: 1.8 | AI55: 2.6 | AJ55: 0.92 | AK55: — | AL55: 0.77 | AM55: 1.05 | AN55: — | AO55: 12.4
A56: DSY.PA | B56: Dassault Systèmes SE | C56: Technology | D56: — | E56: — | F56: — | G56: — | H56: — | I56: — | J56: — | K56: — | L56: — | M56: 0.837 | N56: 0.304 | O56: — | P56: 0.004 | Q56: — | R56: — | S56: — | T56: — | U56: — | V56: — | W56: — | X56: — | Y56: 19 | Z56: 82 | AA56: 7 | AB56: 40 | AC56: 46135 | AD56: Sous-pondérer | AE56: 1.18 | AF56: 14.8 | AG56: 6.2 | AH56: 3.8 | AI56: 1.2 | AJ56: 0.28 | AK56: — | AL56: 0.42 | AM56: 1.02 | AN56: — | AO56: 2.4
A57: GDDY | B57: GoDaddy Inc. | C57: Technology | D57: — | E57: — | F57: — | G57: — | H57: — | I57: — | J57: — | K57: — | L57: — | M57: 0.636 | N57: 0.26 | O57: — | P57: 0.083 | Q57: — | R57: — | S57: — | T57: — | U57: — | V57: — | W57: — | X57: — | Y57: 60 | Z57: 68 | AA57: 2 | AB57: 48 | AC57: — | AD57: Sous-pondérer | AE57: 0.68 | AF57: 2.4 | AG57: 5.8 | AH57: 1.2 | AI57: 0.88 | AJ57: 0.12 | AK57: — | AL57: 2.42 | AM57: 1.29 | AN57: — | AO57: 4.6
A58: JKHY | B58: Jack Henry & Associates, Inc. | C58: Technology | D58: — | E58: — | F58: — | G58: — | H58: — | I58: — | J58: — | K58: — | L58: — | M58: 0.427 | N58: 0.337 | O58: — | P58: 0.072 | Q58: — | R58: — | S58: — | T58: — | U58: — | V58: — | W58: — | X58: — | Y58: 43 | Z58: 82 | AA58: 41 | AB58: 57 | AC58: — | AD58: Sous-pondérer | AE58: 0.62 | AF58: 3.8 | AG58: 1.4 | AH58: 0.8 | AI58: 0.68 | AJ58: 0.18 | AK58: — | AL58: 0.37 | AM58: 1.1 | AN58: — | AO58: 0.6
A59: DELL | B59: Dell Technologies Inc. | C59: Technology | D59: — | E59: — | F59: — | G59: — | H59: — | I59: — | J59: — | K59: — | L59: — | M59: — | N59: — | O59: — | P59: — | Q59: — | R59: — | S59: — | T59: — | U59: — | V59: — | W59: — | X59: — | Y59: 1 | Z59: 45 | AA59: 40 | AB59: 27 | AC59: — | AD59: Sous-pondérer | AE59: 3.88 | AF59: 3.2 | AG59: 28.4 | AH59: 6.8 | AI59: 4.2 | AJ59: 1.2 | AK59: — | AL59: 8.87 | AM59: 1.08 | AN59: — | AO59: 21.6
A60: ROP | B60: Roper Technologies, Inc. | C60: Technology | D60: — | E60: — | F60: — | G60: — | H60: — | I60: — | J60: — | K60: — | L60: — | M60: 0.692 | N60: 0.4 | O60: — | P60: 0.123 | Q60: — | R60: — | S60: — | T60: — | U60: — | V60: — | W60: — | X60: — | Y60: 33 | Z60: 82 | AA60: 16 | AB60: 47 | AC60: — | AD60: Sous-pondérer | AE60: 2.08 | AF60: 22.4 | AG60: 14.8 | AH60: 2.1 | AI60: 2.2 | AJ60: 0.18 | AK60: — | AL60: 0.66 | AM60: 1.06 | AN60: — | AO60: 12.7
A61: NOKIA.HE | B61: Nokia Oyj | C61: Technology | D61: — | E61: — | F61: — | G61: — | H61: — | I61: — | J61: — | K61: — | L61: — | M61: 0.435 | N61: 0.113 | O61: — | P61: 0.035 | Q61: — | R61: — | S61: — | T61: — | U61: — | V61: — | W61: — | X61: — | Y61: 9 | Z61: 67 | AA61: 83 | AB61: 49 | AC61: — | AD61: Sous-pondérer | AE61: 0.92 | AF61: 12.4 | AG61: 4.8 | AH61: 7.8 | AI61: 0.98 | AJ61: 0.48 | AK61: — | AL61: 0.39 | AM61: 1.07 | AN61: — | AO61: -3
A62: FTV | B62: Fortive Corporation | C62: Technology | D62: — | E62: — | F62: — | G62: — | H62: — | I62: — | J62: — | K62: — | L62: — | M62: 0.635 | N62: 0.279 | O62: — | P62: -0.333 | Q62: — | R62: — | S62: — | T62: — | U62: — | V62: — | W62: — | X62: — | Y62: 6 | Z62: 75 | AA62: 56 | AB62: 44 | AC62: — | AD62: Sous-pondérer | AE62: 1.42 | AF62: 12.8 | AG62: 6.4 | AH62: 2.4 | AI62: 1.5 | AJ62: 0.28 | AK62: — | AL62: 0.5 | AM62: 1.06 | AN62: — | AO62: 4
A63: PAYC | B63: Paycom Software, Inc. | C63: Technology | D63: — | E63: — | F63: — | G63: — | H63: — | I63: — | J63: — | K63: — | L63: — | M63: 0.832 | N63: 0.389 | O63: — | P63: 0.089 | Q63: — | R63: — | S63: — | T63: — | U63: — | V63: — | W63: — | X63: — | Y63: 27 | Z63: 75 | AA63: 3 | AB63: 39 | AC63: — | AD63: Sous-pondérer | AE63: 0.78 | AF63: 2.8 | AG63: 2.4 | AH63: 0.8 | AI63: 0.88 | AJ63: 0.08 | AK63: — | AL63: 0.86 | AM63: 1.13 | AN63: — | AO63: 1.6
A64: Q | B64: Qnity Electronics, Inc. | C64: Technology | D64: — | E64: — | F64: — | G64: — | H64: — | I64: — | J64: — | K64: — | L64: — | M64: 0.462 | N64: 0.295 | O64: — | P64: 0.097 | Q64: — | R64: — | S64: — | T64: — | U64: — | V64: — | W64: — | X64: — | Y64: 40 | Z64: 68 | AA64: 0 | AB64: 40 | AC64: — | AD64: Sous-pondérer | AE64: 0.38 | AF64: 2.4 | AG64: 1.8 | AH64: 0.6 | AI64: 0.42 | AJ64: 0.08 | AK64: — | AL64: 0.75 | AM64: 1.11 | AN64: — | AO64: 1.2
A65: NXPI | B65: NXP Semiconductors N.V. | C65: Technology | D65: — | E65: — | F65: — | G65: — | H65: — | I65: — | J65: — | K65: — | L65: — | M65: 0.547 | N65: 0.323 | O65: — | P65: -0.027 | Q65: — | R65: — | S65: — | T65: — | U65: — | V65: — | W65: — | X65: — | Y65: 14 | Z65: 75 | AA65: 52 | AB65: 46 | AC65: — | AD65: Sous-pondérer | AE65: 2.92 | AF65: 14.8 | AG65: 11.4 | AH65: 3.2 | AI65: 3.1 | AJ65: 0.88 | AK65: — | AL65: 0.77 | AM65: 1.06 | AN65: — | AO65: 8.2
A66: TRMB | B66: Trimble Inc. | C66: Technology | D66: — | E66: — | F66: — | G66: — | H66: — | I66: — | J66: — | K66: — | L66: — | M66: 0.691 | N66: 0.218 | O66: — | P66: -0.026 | Q66: — | R66: — | S66: — | T66: — | U66: — | V66: — | W66: — | X66: — | Y66: 5 | Z66: 75 | AA66: 45 | AB66: 41 | AC66: — | AD66: Sous-pondérer | AE66: 0.62 | AF66: 6.8 | AG66: 4.2 | AH66: 0.8 | AI66: 0.68 | AJ66: 0.22 | AK66: — | AL66: 0.62 | AM66: 1.1 | AN66: — | AO66: 3.4
A67: TYL | B67: Tyler Technologies, Inc. | C67: Technology | D67: — | E67: — | F67: — | G67: — | H67: — | I67: — | J67: — | K67: — | L67: — | M67: 0.465 | N67: 0.233 | O67: — | P67: 0.091 | Q67: — | R67: — | S67: — | T67: — | U67: — | V67: — | W67: — | X67: — | Y67: 55 | Z67: 75 | AA67: 13 | AB67: 52 | AC67: — | AD67: Sous-pondérer | AE67: 0.48 | AF67: 4.8 | AG67: 2.8 | AH67: 0.6 | AI67: 0.52 | AJ67: 0.12 | AK67: — | AL67: 0.58 | AM67: 1.08 | AN67: — | AO67: 2.2
A68: HPE | B68: Hewlett Packard Enterprise Company | C68: Technology | D68: — | E68: — | F68: — | G68: — | H68: — | I68: — | J68: — | K68: — | L68: — | M68: 0.303 | N68: 0.128 | O68: — | P68: 0.138 | Q68: — | R68: — | S68: — | T68: — | U68: — | V68: — | W68: — | X68: — | Y68: 20 | Z68: 60 | AA68: 74 | AB68: 48 | AC68: — | AD68: Sous-pondérer | AE68: 2.48 | AF68: 21.8 | AG68: 18.4 | AH68: 4.2 | AI68: 2.6 | AJ68: 1.8 | AK68: — | AL68: 0.84 | AM68: 1.05 | AN68: — | AO68: 14.2
A69: SNDK | B69: Sandisk Corporation | C69: Technology | D69: — | E69: — | F69: — | G69: — | H69: — | I69: — | J69: — | K69: — | L69: — | M69: 0.301 | N69: -0.17 | O69: — | P69: 0.104 | Q69: — | R69: — | S69: — | T69: — | U69: — | V69: — | W69: — | X69: — | Y69: 1 | Z69: 38 | AA69: 100 | AB69: 40 | AC69: — | AD69: Sous-pondérer | AE69: -0.88 | AF69: 4.2 | AG69: 6.8 | AH69: 1.8 | AI69: -0.72 | AJ69: 0.38 | AK69: — | AL69: 1.62 | AM69: 0.82 | AN69: — | AO69: 5
A70: LDOS | B70: Leidos Holdings, Inc. | C70: Technology | D70: — | E70: — | F70: — | G70: — | H70: — | I70: — | J70: — | K70: — | L70: — | M70: 0.18 | N70: 0.14 | O70: — | P70: 0.031 | Q70: — | R70: — | S70: — | T70: — | U70: — | V70: — | W70: — | X70: — | Y70: 34 | Z70: 60 | AA70: 58 | AB70: 50 | AC70: — | AD70: Sous-pondérer | AE70: 0.58 | AF70: 4.8 | AG70: 4.2 | AH70: 0.8 | AI70: 0.62 | AJ70: 0.18 | AK70: — | AL70: 0.88 | AM70: 1.07 | AN70: — | AO70: 3.4
A71: IFX.DE | B71: Infineon Technologies AG | C71: Technology | D71: — | E71: — | F71: — | G71: — | H71: — | I71: — | J71: — | K71: — | L71: — | M71: 0.392 | N71: 0.24 | O71: — | P71: -0.02 | Q71: — | R71: — | S71: — | T71: — | U71: — | V71: — | W71: — | X71: — | Y71: 12 | Z71: 82 | AA71: 60 | AB71: 50 | AC71: — | AD71: Sous-pondérer | AE71: 1.28 | AF71: 16.4 | AG71: 3.8 | AH71: 4.2 | AI71: 1.4 | AJ71: 1.6 | AK71: — | AL71: 0.23 | AM71: 1.09 | AN71: — | AO71: -0.4
... A90: WLN.PA | B90: Worldline SA | C90: Technology | D90: — | E90: — | F90: — | G90: — | H90: — | I90: — | J90: — | K90: — | L90: — | M90: 0.565 | N90: -1.122 | O90: — | P90: -0.032 | Q90: — | R90: — | S90: — | T90: — | U90: — | V90: — | W90: — | X90: — | Y90: 0 | Z90: 28 | AA90: 0 | AB90: 11 | AC90: — | AD90: Sous-pondérer | AE90: -1.12 | AF90: 3.4 | AG90: 12.8 | AH90: 0.8 | AI90: -1 | AJ90: 0.38 | AK90: — | AL90: 3.76 | AM90: 0.89 | AN90: — | AO90: 12
